Workbook

Sheet CEO Report
A1: ⚡ MiT Strom Schweiz — CEO Sales Report · Mai 2026
A2: Mobil in Time AG · An Aggreko Company · Burak Ücöz · Neue Einträge in «MiT Strom Pipeline» erscheinen automatisch.
A5: ✅ AUFTRAGSEINGANG (WON) | E5: 📄 OFFERTE — Laufend | I5: 🎯 OPPORTUNITÄT
A6: =SUMIFS('MiT Strom Pipeline'!I$6:I$904,'MiT Strom Pipeline'!R$6:R$904,"WON") -> 333100 | E6: =SUMIFS('MiT Strom Pipeline'!I$6:I$904,'MiT Strom Pipeline'!R$6:R$904,"offered")+SUMIFS('MiT Strom Pipeline'!I$6:I$904,'MiT Strom Pipeline'!R$6:R$904,"to be offered")+SUMIFS('MiT Strom Pipeline'!I$6:I$904,'MiT Strom Pipeline'!R$6:R$904,"on hold") -> 3866028.6 | I6: =SUMIFS('MiT Strom Pipeline'!I$6:I$904,'MiT Strom Pipeline'!R$6:R$904,"follow-up")+SUMIFS('MiT Strom Pipeline'!I$6:I$904,'MiT Strom Pipeline'!R$6:R$904,"Evaluation")+SUMIFS('MiT Strom Pipeline'!I$6:I$904,'MiT Strom Pipeline'!R$6:R$904,"tbd")+SUMIFS('MiT Strom Pipeline'!I$6:I$904,'MiT Strom Pipeline'!R$6:R$904,"In evaluation") -> 672987.69
A7: =COUNTIF('MiT Strom Pipeline'!R$6:R$904,"WON") -> 4 | E7: =COUNTIF('MiT Strom Pipeline'!R$6:R$904,"offered")+COUNTIF('MiT Strom Pipeline'!R$6:R$904,"to be offered")+COUNTIF('MiT Strom Pipeline'!R$6:R$904,"on hold") -> 12 | I7: =COUNTIF('MiT Strom Pipeline'!R$6:R$904,"follow-up")+COUNTIF('MiT Strom Pipeline'!R$6:R$904,"Evaluation")+COUNTIF('MiT Strom Pipeline'!R$6:R$904,"tbd")+COUNTIF('MiT Strom Pipeline'!R$6:R$904,"In evaluation") -> 16
A9: ✅ 1. AUFTRAGSEINGANG (WON) — Bestätigte Aufträge
A10: # | B10: Kunde / Unternehmen | C10: Kt. | D10: Segment | E10: Leistung / Fleet | F10: Volumen CHF | G10: Gew.Wert CHF | H10: Marge CHF | I10: Status | J10: Wahr.% | K10: Nächster Schritt
A11: =IF('MiT Strom Pipeline'!R6="WON",IF(ISNUMBER('MiT Strom Pipeline'!A6),'MiT Strom Pipeline'!A6,""),"") -> 1 | B11: =IF('MiT Strom Pipeline'!R6="WON",'MiT Strom Pipeline'!B6,"") -> Ice Hockey Championship | C11: =IF('MiT Strom Pipeline'!R6="WON",'MiT Strom Pipeline'!C6,"") -> ZH | D11: =IF('MiT Strom Pipeline'!R6="WON",'MiT Strom Pipeline'!D6,"") -> Events & Sport | E11: =IF('MiT Strom Pipeline'!R6="WON",'MiT Strom Pipeline'!E6,"") -> 2×600+2×200 kVA | F11: =IF('MiT Strom Pipeline'!R6="WON",IF(ISNUMBER('MiT Strom Pipeline'!I6),'MiT Strom Pipeline'!I6,0),"") -> 310000 | G11: =IF('MiT Strom Pipeline'!R6="WON",IF(ISNUMBER('MiT Strom Pipeline'!Q6),'MiT Strom Pipeline'!Q6,0),"") -> 3100 | H11: =IF('MiT Strom Pipeline'!R6="WON",IF(ISNUMBER('MiT Strom Pipeline'!O6),'MiT Strom Pipeline'!O6,0),"") -> 75000 | I11: =IF('MiT Strom Pipeline'!R6="WON",'MiT Strom Pipeline'!R6,"") -> WON | J11: =IF('MiT Strom Pipeline'!R6="WON",'MiT Strom Pipeline'!S6,"") -> 100% | K11: =IF('MiT Strom Pipeline'!R6="WON",IF(LEN('MiT Strom Pipeline'!V6)>0,LEFT('MiT Strom Pipeline'!V6,55),""),"") -> ✅ Einsatzplanung läuft – Logistik finalisieren
A12: =IF('MiT Strom Pipeline'!R7="WON",IF(ISNUMBER('MiT Strom Pipeline'!A7),'MiT Strom Pipeline'!A7,""),"") -> 2 | B12: =IF('MiT Strom Pipeline'!R7="WON",'MiT Strom Pipeline'!B7,"") -> Oerlikon Metco Wohlen | C12: =IF('MiT Strom Pipeline'!R7="WON",'MiT Strom Pipeline'!C7,"") -> AG | D12: =IF('MiT Strom Pipeline'!R7="WON",'MiT Strom Pipeline'!D7,"") -> Industrie / Oberfläche | E12: =IF('MiT Strom Pipeline'!R7="WON",'MiT Strom Pipeline'!E7,"") -> 240 kVA Generator | F12: =IF('MiT Strom Pipeline'!R7="WON",IF(ISNUMBER('MiT Strom Pipeline'!I7),'MiT Strom Pipeline'!I7,0),"") -> 13100 | G12: =IF('MiT Strom Pipeline'!R7="WON",IF(ISNUMBER('MiT Strom Pipeline'!Q7),'MiT Strom Pipeline'!Q7,0),"") -> 131 | H12: =IF('MiT Strom Pipeline'!R7="WON",IF(ISNUMBER('MiT Strom Pipeline'!O7),'MiT Strom Pipeline'!O7,0),"") -> 3000 | I12: =IF('MiT Strom Pipeline'!R7="WON",'MiT Strom Pipeline'!R7,"") -> WON | J12: =IF('MiT Strom Pipeline'!R7="WON",'MiT Strom Pipeline'!S7,"") -> 100% | K12: =IF('MiT Strom Pipeline'!R7="WON",IF(LEN('MiT Strom Pipeline'!V7)>0,LEFT('MiT Strom Pipeline'!V7,55),""),"") -> ✅ Abgeschlossen – Invoice prüfen, Referenz sichern
A13: =IF('MiT Strom Pipeline'!R8="WON",IF(ISNUMBER('MiT Strom Pipeline'!A8),'MiT Strom Pipeline'!A8,""),"") -> 3 | B13: =IF('MiT Strom Pipeline'!R8="WON",'MiT Strom Pipeline'!B8,"") -> Siemens | C13: =IF('MiT Strom Pipeline'!R8="WON",'MiT Strom Pipeline'!C8,"") -> ZH | D13: =IF('MiT Strom Pipeline'!R8="WON",'MiT Strom Pipeline'!D8,"") -> Industrie / Elektro | E13: =IF('MiT Strom Pipeline'!R8="WON",'MiT Strom Pipeline'!E8,"") -> 600 kVA Generator | F13: =IF('MiT Strom Pipeline'!R8="WON",IF(ISNUMBER('MiT Strom Pipeline'!I8),'MiT Strom Pipeline'!I8,0),"") -> 10000 | G13: =IF('MiT Strom Pipeline'!R8="WON",IF(ISNUMBER('MiT Strom Pipeline'!Q8),'MiT Strom Pipeline'!Q8,0),"") -> 100 | H13: =IF('MiT Strom Pipeline'!R8="WON",IF(ISNUMBER('MiT Strom Pipeline'!O8),'MiT Strom Pipeline'!O8,0),"") -> 10000 | I13: =IF('MiT Strom Pipeline'!R8="WON",'MiT Strom Pipeline'!R8,"") -> WON | J13: =IF('MiT Strom Pipeline'!R8="WON",'MiT Strom Pipeline'!S8,"") -> 100% | K13: =IF('MiT Strom Pipeline'!R8="WON",IF(LEN('MiT Strom Pipeline'!V8)>0,LEFT('MiT Strom Pipeline'!V8,55),""),"") -> ✅ Referenzschreiben anfordern
A14: =IF('MiT Strom Pipeline'!R9="WON",IF(ISNUMBER('MiT Strom Pipeline'!A9),'MiT Strom Pipeline'!A9,""),"") | B14: =IF('MiT Strom Pipeline'!R9="WON",'MiT Strom Pipeline'!B9,"") | C14: =IF('MiT Strom Pipeline'!R9="WON",'MiT Strom Pipeline'!C9,"") | D14: =IF('MiT Strom Pipeline'!R9="WON",'MiT Strom Pipeline'!D9,"") | E14: =IF('MiT Strom Pipeline'!R9="WON",'MiT Strom Pipeline'!E9,"") | F14: =IF('MiT Strom Pipeline'!R9="WON",IF(ISNUMBER('MiT Strom Pipeline'!I9),'MiT Strom Pipeline'!I9,0),"") | G14: =IF('MiT Strom Pipeline'!R9="WON",IF(ISNUMBER('MiT Strom Pipeline'!Q9),'MiT Strom Pipeline'!Q9,0),"") | H14: =IF('MiT Strom Pipeline'!R9="WON",IF(ISNUMBER('MiT Strom Pipeline'!O9),'MiT Strom Pipeline'!O9,0),"") | I14: =IF('MiT Strom Pipeline'!R9="WON",'MiT Strom Pipeline'!R9,"") | J14: =IF('MiT Strom Pipeline'!R9="WON",'MiT Strom Pipeline'!S9,"") | K14: =IF('MiT Strom Pipeline'!R9="WON",IF(LEN('MiT Strom Pipeline'!V9)>0,LEFT('MiT Strom Pipeline'!V9,55),""),"")
A15: =IF('MiT Strom Pipeline'!R10="WON",IF(ISNUMBER('MiT Strom Pipeline'!A10),'MiT Strom Pipeline'!A10,""),"") | B15: =IF('MiT Strom Pipeline'!R10="WON",'MiT Strom Pipeline'!B10,"") | C15: =IF('MiT Strom Pipeline'!R10="WON",'MiT Strom Pipeline'!C10,"") | D15: =IF('MiT Strom Pipeline'!R10="WON",'MiT Strom Pipeline'!D10,"") | E15: =IF('MiT Strom Pipeline'!R10="WON",'MiT Strom Pipeline'!E10,"") | F15: =IF('MiT Strom Pipeline'!R10="WON",IF(ISNUMBER('MiT Strom Pipeline'!I10),'MiT Strom Pipeline'!I10,0),"") | G15: =IF('MiT Strom Pipeline'!R10="WON",IF(ISNUMBER('MiT Strom Pipeline'!Q10),'MiT Strom Pipeline'!Q10,0),"") | H15: =IF('MiT Strom Pipeline'!R10="WON",IF(ISNUMBER('MiT Strom Pipeline'!O10),'MiT Strom Pipeline'!O10,0),"") | I15: =IF('MiT Strom Pipeline'!R10="WON",'MiT Strom Pipeline'!R10,"") | J15: =IF('MiT Strom Pipeline'!R10="WON",'MiT Strom Pipeline'!S10,"") | K15: =IF('MiT Strom Pipeline'!R10="WON",IF(LEN('MiT Strom Pipeline'!V10)>0,LEFT('MiT Strom Pipeline'!V10,55),""),"")
A16: =IF('MiT Strom Pipeline'!R11="WON",IF(ISNUMBER('MiT Strom Pipeline'!A11),'MiT Strom Pipeline'!A11,""),"") | B16: =IF('MiT Strom Pipeline'!R11="WON",'MiT Strom Pipeline'!B11,"") | C16: =IF('MiT Strom Pipeline'!R11="WON",'MiT Strom Pipeline'!C11,"") | D16: =IF('MiT Strom Pipeline'!R11="WON",'MiT Strom Pipeline'!D11,"") | E16: =IF('MiT Strom Pipeline'!R11="WON",'MiT Strom Pipeline'!E11,"") | F16: =IF('MiT Strom Pipeline'!R11="WON",IF(ISNUMBER('MiT Strom Pipeline'!I11),'MiT Strom Pipeline'!I11,0),"") | G16: =IF('MiT Strom Pipeline'!R11="WON",IF(ISNUMBER('MiT Strom Pipeline'!Q11),'MiT Strom Pipeline'!Q11,0),"") | H16: =IF('MiT Strom Pipeline'!R11="WON",IF(ISNUMBER('MiT Strom Pipeline'!O11),'MiT Strom Pipeline'!O11,0),"") | I16: =IF('MiT Strom Pipeline'!R11="WON",'MiT Strom Pipeline'!R11,"") | J16: =IF('MiT Strom Pipeline'!R11="WON",'MiT Strom Pipeline'!S11,"") | K16: =IF('MiT Strom Pipeline'!R11="WON",IF(LEN('MiT Strom Pipeline'!V11)>0,LEFT('MiT Strom Pipeline'!V11,55),""),"")
A17: =IF('MiT Strom Pipeline'!R12="WON",IF(ISNUMBER('MiT Strom Pipeline'!A12),'MiT Strom Pipeline'!A12,""),"") | B17: =IF('MiT Strom Pipeline'!R12="WON",'MiT Strom Pipeline'!B12,"") | C17: =IF('MiT Strom Pipeline'!R12="WON",'MiT Strom Pipeline'!C12,"") | D17: =IF('MiT Strom Pipeline'!R12="WON",'MiT Strom Pipeline'!D12,"") | E17: =IF('MiT Strom Pipeline'!R12="WON",'MiT Strom Pipeline'!E12,"") | F17: =IF('MiT Strom Pipeline'!R12="WON",IF(ISNUMBER('MiT Strom Pipeline'!I12),'MiT Strom Pipeline'!I12,0),"") | G17: =IF('MiT Strom Pipeline'!R12="WON",IF(ISNUMBER('MiT Strom Pipeline'!Q12),'MiT Strom Pipeline'!Q12,0),"") | H17: =IF('MiT Strom Pipeline'!R12="WON",IF(ISNUMBER('MiT Strom Pipeline'!O12),'MiT Strom Pipeline'!O12,0),"") | I17: =IF('MiT Strom Pipeline'!R12="WON",'MiT Strom Pipeline'!R12,"") | J17: =IF('MiT Strom Pipeline'!R12="WON",'MiT Strom Pipeline'!S12,"") | K17: =IF('MiT Strom Pipeline'!R12="WON",IF(LEN('MiT Strom Pipeline'!V12)>0,LEFT('MiT Strom Pipeline'!V12,55),""),"")
A18: =IF('MiT Strom Pipeline'!R13="WON",IF(ISNUMBER('MiT Strom Pipeline'!A13),'MiT Strom Pipeline'!A13,""),"") | B18: =IF('MiT Strom Pipeline'!R13="WON",'MiT Strom Pipeline'!B13,"") | C18: =IF('MiT Strom Pipeline'!R13="WON",'MiT Strom Pipeline'!C13,"") | D18: =IF('MiT Strom Pipeline'!R13="WON",'MiT Strom Pipeline'!D13,"") | E18: =IF('MiT Strom Pipeline'!R13="WON",'MiT Strom Pipeline'!E13,"") | F18: =IF('MiT Strom Pipeline'!R13="WON",IF(ISNUMBER('MiT Strom Pipeline'!I13),'MiT Strom Pipeline'!I13,0),"") | G18: =IF('MiT Strom Pipeline'!R13="WON",IF(ISNUMBER('MiT Strom Pipeline'!Q13),'MiT Strom Pipeline'!Q13,0),"") | H18: =IF('MiT Strom Pipeline'!R13="WON",IF(ISNUMBER('MiT Strom Pipeline'!O13),'MiT Strom Pipeline'!O13,0),"") | I18: =IF('MiT Strom Pipeline'!R13="WON",'MiT Strom Pipeline'!R13,"") | J18: =IF('MiT Strom Pipeline'!R13="WON",'MiT Strom Pipeline'!S13,"") | K18: =IF('MiT Strom Pipeline'!R13="WON",IF(LEN('MiT Strom Pipeline'!V13)>0,LEFT('MiT Strom Pipeline'!V13,55),""),"")
A19: =IF('MiT Strom Pipeline'!R14="WON",IF(ISNUMBER('MiT Strom Pipeline'!A14),'MiT Strom Pipeline'!A14,""),"") | B19: =IF('MiT Strom Pipeline'!R14="WON",'MiT Strom Pipeline'!B14,"") | C19: =IF('MiT Strom Pipeline'!R14="WON",'MiT Strom Pipeline'!C14,"") | D19: =IF('MiT Strom Pipeline'!R14="WON",'MiT Strom Pipeline'!D14,"") | E19: =IF('MiT Strom Pipeline'!R14="WON",'MiT Strom Pipeline'!E14,"") | F19: =IF('MiT Strom Pipeline'!R14="WON",IF(ISNUMBER('MiT Strom Pipeline'!I14),'MiT Strom Pipeline'!I14,0),"") | G19: =IF('MiT Strom Pipeline'!R14="WON",IF(ISNUMBER('MiT Strom Pipeline'!Q14),'MiT Strom Pipeline'!Q14,0),"") | H19: =IF('MiT Strom Pipeline'!R14="WON",IF(ISNUMBER('MiT Strom Pipeline'!O14),'MiT Strom Pipeline'!O14,0),"") | I19: =IF('MiT Strom Pipeline'!R14="WON",'MiT Strom Pipeline'!R14,"") | J19: =IF('MiT Strom Pipeline'!R14="WON",'MiT Strom Pipeline'!S14,"") | K19: =IF('MiT Strom Pipeline'!R14="WON",IF(LEN('MiT Strom Pipeline'!V14)>0,LEFT('MiT Strom Pipeline'!V14,55),""),"")
A20: =IF('MiT Strom Pipeline'!R15="WON",IF(ISNUMBER('MiT Strom Pipeline'!A15),'MiT Strom Pipeline'!A15,""),"") | B20: =IF('MiT Strom Pipeline'!R15="WON",'MiT Strom Pipeline'!B15,"") | C20: =IF('MiT Strom Pipeline'!R15="WON",'MiT Strom Pipeline'!C15,"") | D20: =IF('MiT Strom Pipeline'!R15="WON",'MiT Strom Pipeline'!D15,"") | E20: =IF('MiT Strom Pipeline'!R15="WON",'MiT Strom Pipeline'!E15,"") | F20: =IF('MiT Strom Pipeline'!R15="WON",IF(ISNUMBER('MiT Strom Pipeline'!I15),'MiT Strom Pipeline'!I15,0),"") | G20: =IF('MiT Strom Pipeline'!R15="WON",IF(ISNUMBER('MiT Strom Pipeline'!Q15),'MiT Strom Pipeline'!Q15,0),"") | H20: =IF('MiT Strom Pipeline'!R15="WON",IF(ISNUMBER('MiT Strom Pipeline'!O15),'MiT Strom Pipeline'!O15,0),"") | I20: =IF('MiT Strom Pipeline'!R15="WON",'MiT Strom Pipeline'!R15,"") | J20: =IF('MiT Strom Pipeline'!R15="WON",'MiT Strom Pipeline'!S15,"") | K20: =IF('MiT Strom Pipeline'!R15="WON",IF(LEN('MiT Strom Pipeline'!V15)>0,LEFT('MiT Strom Pipeline'!V15,55),""),"")
A21: =IF('MiT Strom Pipeline'!R16="WON",IF(ISNUMBER('MiT Strom Pipeline'!A16),'MiT Strom Pipeline'!A16,""),"") | B21: =IF('MiT Strom Pipeline'!R16="WON",'MiT Strom Pipeline'!B16,"") | C21: =IF('MiT Strom Pipeline'!R16="WON",'MiT Strom Pipeline'!C16,"") | D21: =IF('MiT Strom Pipeline'!R16="WON",'MiT Strom Pipeline'!D16,"") | E21: =IF('MiT Strom Pipeline'!R16="WON",'MiT Strom Pipeline'!E16,"") | F21: =IF('MiT Strom Pipeline'!R16="WON",IF(ISNUMBER('MiT Strom Pipeline'!I16),'MiT Strom Pipeline'!I16,0),"") | G21: =IF('MiT Strom Pipeline'!R16="WON",IF(ISNUMBER('MiT Strom Pipeline'!Q16),'MiT Strom Pipeline'!Q16,0),"") | H21: =IF('MiT Strom Pipeline'!R16="WON",IF(ISNUMBER('MiT Strom Pipeline'!O16),'MiT Strom Pipeline'!O16,0),"") | I21: =IF('MiT Strom Pipeline'!R16="WON",'MiT Strom Pipeline'!R16,"") | J21: =IF('MiT Strom Pipeline'!R16="WON",'MiT Strom Pipeline'!S16,"") | K21: =IF('MiT Strom Pipeline'!R16="WON",IF(LEN('MiT Strom Pipeline'!V16)>0,LEFT('MiT Strom Pipeline'!V16,55),""),"")
A22: =IF('MiT Strom Pipeline'!R17="WON",IF(ISNUMBER('MiT Strom Pipeline'!A17),'MiT Strom Pipeline'!A17,""),"") | B22: =IF('MiT Strom Pipeline'!R17="WON",'MiT Strom Pipeline'!B17,"") | C22: =IF('MiT Strom Pipeline'!R17="WON",'MiT Strom Pipeline'!C17,"") | D22: =IF('MiT Strom Pipeline'!R17="WON",'MiT Strom Pipeline'!D17,"") | E22: =IF('MiT Strom Pipeline'!R17="WON",'MiT Strom Pipeline'!E17,"") | F22: =IF('MiT Strom Pipeline'!R17="WON",IF(ISNUMBER('MiT Strom Pipeline'!I17),'MiT Strom Pipeline'!I17,0),"") | G22: =IF('MiT Strom Pipeline'!R17="WON",IF(ISNUMBER('MiT Strom Pipeline'!Q17),'MiT Strom Pipeline'!Q17,0),"") | H22: =IF('MiT Strom Pipeline'!R17="WON",IF(ISNUMBER('MiT Strom Pipeline'!O17),'MiT Strom Pipeline'!O17,0),"") | I22: =IF('MiT Strom Pipeline'!R17="WON",'MiT Strom Pipeline'!R17,"") | J22: =IF('MiT Strom Pipeline'!R17="WON",'MiT Strom Pipeline'!S17,"") | K22: =IF('MiT Strom Pipeline'!R17="WON",IF(LEN('MiT Strom Pipeline'!V17)>0,LEFT('MiT Strom Pipeline'!V17,55),""),"")
... A70: =IF('MiT Strom Pipeline'!R65="WON",IF(ISNUMBER('MiT Strom Pipeline'!A65),'MiT Strom Pipeline'!A65,""),"") | B70: =IF('MiT Strom Pipeline'!R65="WON",'MiT Strom Pipeline'!B65,"") | C70: =IF('MiT Strom Pipeline'!R65="WON",'MiT Strom Pipeline'!C65,"") | D70: =IF('MiT Strom Pipeline'!R65="WON",'MiT Strom Pipeline'!D65,"") | E70: =IF('MiT Strom Pipeline'!R65="WON",'MiT Strom Pipeline'!E65,"") | F70: =IF('MiT Strom Pipeline'!R65="WON",IF(ISNUMBER('MiT Strom Pipeline'!I65),'MiT Strom Pipeline'!I65,0),"") | G70: =IF('MiT Strom Pipeline'!R65="WON",IF(ISNUMBER('MiT Strom Pipeline'!Q65),'MiT Strom Pipeline'!Q65,0),"") | H70: =IF('MiT Strom Pipeline'!R65="WON",IF(ISNUMBER('MiT Strom Pipeline'!O65),'MiT Strom Pipeline'!O65,0),"") | I70: =IF('MiT Strom Pipeline'!R65="WON",'MiT Strom Pipeline'!R65,"") | J70: =IF('MiT Strom Pipeline'!R65="WON",'MiT Strom Pipeline'!S65,"") | K70: =IF('MiT Strom Pipeline'!R65="WON",IF(LEN('MiT Strom Pipeline'!V65)>0,LEFT('MiT Strom Pipeline'!V65,55),""),"")
A71: =IF('MiT Strom Pipeline'!R66="WON",IF(ISNUMBER('MiT Strom Pipeline'!A66),'MiT Strom Pipeline'!A66,""),"") | B71: =IF('MiT Strom Pipeline'!R66="WON",'MiT Strom Pipeline'!B66,"") | F71: =IF('MiT Strom Pipeline'!R66="WON",IF(ISNUMBER('MiT Strom Pipeline'!I66),'MiT Strom Pipeline'!I66,0),"") | G71: =IF('MiT Strom Pipeline'!R66="WON",IF(ISNUMBER('MiT Strom Pipeline'!Q66),'MiT Strom Pipeline'!Q66,0),"") | H71: =IF('MiT Strom Pipeline'!R66="WON",IF(ISNUMBER('MiT Strom Pipeline'!O66),'MiT Strom Pipeline'!O66,0),"") | I71: =IF('MiT Strom Pipeline'!R66="WON",'MiT Strom Pipeline'!R66,"") | J71: =IF('MiT Strom Pipeline'!R66="WON",'MiT Strom Pipeline'!S66,"") | K71: =IF('MiT Strom Pipeline'!R66="WON",IF(LEN('MiT Strom Pipeline'!V66)>0,LEFT('MiT Strom Pipeline'!V66,55),""),"")
A72: =IF('MiT Strom Pipeline'!R67="WON",IF(ISNUMBER('MiT Strom Pipeline'!A67),'MiT Strom Pipeline'!A67,""),"") | B72: =IF('MiT Strom Pipeline'!R67="WON",'MiT Strom Pipeline'!B67,"") | C72: =IF('MiT Strom Pipeline'!R67="WON",'MiT Strom Pipeline'!C67,"") | D72: =IF('MiT Strom Pipeline'!R67="WON",'MiT Strom Pipeline'!D67,"") | E72: =IF('MiT Strom Pipeline'!R67="WON",'MiT Strom Pipeline'!E67,"") | F72: =IF('MiT Strom Pipeline'!R67="WON",IF(ISNUMBER('MiT Strom Pipeline'!I67),'MiT Strom Pipeline'!I67,0),"") | G72: =IF('MiT Strom Pipeline'!R67="WON",IF(ISNUMBER('MiT Strom Pipeline'!Q67),'MiT Strom Pipeline'!Q67,0),"") | H72: =IF('MiT Strom Pipeline'!R67="WON",IF(ISNUMBER('MiT Strom Pipeline'!O67),'MiT Strom Pipeline'!O67,0),"") | I72: =IF('MiT Strom Pipeline'!R67="WON",'MiT Strom Pipeline'!R67,"") | J72: =IF('MiT Strom Pipeline'!R67="WON",'MiT Strom Pipeline'!S67,"") | K72: =IF('MiT Strom Pipeline'!R67="WON",IF(LEN('MiT Strom Pipeline'!V67)>0,LEFT('MiT Strom Pipeline'!V67,55),""),"")
A73: 📄 2. OFFERTE — Versendete & laufende Angebote
A74: # | B74: Kunde / Unternehmen | C74: Kt. | D74: Segment | E74: Leistung / Fleet | F74: Volumen CHF | G74: Gew.Wert CHF | H74: Marge CHF | I74: Status | J74: Wahr.% | K74: Nächster Schritt
A75: =IF(('MiT Strom Pipeline'!R6="offered")+('MiT Strom Pipeline'!R6="to be offered")+('MiT Strom Pipeline'!R6="on hold")>0,IF(ISNUMBER('MiT Strom Pipeline'!A6),'MiT Strom Pipeline'!A6,""),"") | B75: =IF(('MiT Strom Pipeline'!R6="offered")+('MiT Strom Pipeline'!R6="to be offered")+('MiT Strom Pipeline'!R6="on hold")>0,'MiT Strom Pipeline'!B6,"") | C75: =IF(('MiT Strom Pipeline'!R6="offered")+('MiT Strom Pipeline'!R6="to be offered")+('MiT Strom Pipeline'!R6="on hold")>0,'MiT Strom Pipeline'!C6,"") | D75: =IF(('MiT Strom Pipeline'!R6="offered")+('MiT Strom Pipeline'!R6="to be offered")+('MiT Strom Pipeline'!R6="on hold")>0,'MiT Strom Pipeline'!D6,"") | E75: =IF(('MiT Strom Pipeline'!R6="offered")+('MiT Strom Pipeline'!R6="to be offered")+('MiT Strom Pipeline'!R6="on hold")>0,'MiT Strom Pipeline'!E6,"") | F75: =IF(('MiT Strom Pipeline'!R6="offered")+('MiT Strom Pipeline'!R6="to be offered")+('MiT Strom Pipeline'!R6="on hold")>0,IF(ISNUMBER('MiT Strom Pipeline'!I6),'MiT Strom Pipeline'!I6,0),"") | G75: =IF(('MiT Strom Pipeline'!R6="offered")+('MiT Strom Pipeline'!R6="to be offered")+('MiT Strom Pipeline'!R6="on hold")>0,IF(ISNUMBER('MiT Strom Pipeline'!Q6),'MiT Strom Pipeline'!Q6,0),"") | H75: =IF(('MiT Strom Pipeline'!R6="offered")+('MiT Strom Pipeline'!R6="to be offered")+('MiT Strom Pipeline'!R6="on hold")>0,IF(ISNUMBER('MiT Strom Pipeline'!O6),'MiT Strom Pipeline'!O6,0),"") | I75: =IF(('MiT Strom Pipeline'!R6="offered")+('MiT Strom Pipeline'!R6="to be offered")+('MiT Strom Pipeline'!R6="on hold")>0,'MiT Strom Pipeline'!R6,"") | J75: =IF(('MiT Strom Pipeline'!R6="offered")+('MiT Strom Pipeline'!R6="to be offered")+('MiT Strom Pipeline'!R6="on hold")>0,'MiT Strom Pipeline'!S6,"") | K75: =IF(('MiT Strom Pipeline'!R6="offered")+('MiT Strom Pipeline'!R6="to be offered")+('MiT Strom Pipeline'!R6="on hold")>0,IF(LEN('MiT Strom Pipeline'!V6)>0,LEFT('MiT Strom Pipeline'!V6,55),""),"")
A76: =IF(('MiT Strom Pipeline'!R7="offered")+('MiT Strom Pipeline'!R7="to be offered")+('MiT Strom Pipeline'!R7="on hold")>0,IF(ISNUMBER('MiT Strom Pipeline'!A7),'MiT Strom Pipeline'!A7,""),"") | B76: =IF(('MiT Strom Pipeline'!R7="offered")+('MiT Strom Pipeline'!R7="to be offered")+('MiT Strom Pipeline'!R7="on hold")>0,'MiT Strom Pipeline'!B7,"") | C76: =IF(('MiT Strom Pipeline'!R7="offered")+('MiT Strom Pipeline'!R7="to be offered")+('MiT Strom Pipeline'!R7="on hold")>0,'MiT Strom Pipeline'!C7,"") | D76: =IF(('MiT Strom Pipeline'!R7="offered")+('MiT Strom Pipeline'!R7="to be offered")+('MiT Strom Pipeline'!R7="on hold")>0,'MiT Strom Pipeline'!D7,"") | E76: =IF(('MiT Strom Pipeline'!R7="offered")+('MiT Strom Pipeline'!R7="to be offered")+('MiT Strom Pipeline'!R7="on hold")>0,'MiT Strom Pipeline'!E7,"") | F76: =IF(('MiT Strom Pipeline'!R7="offered")+('MiT Strom Pipeline'!R7="to be offered")+('MiT Strom Pipeline'!R7="on hold")>0,IF(ISNUMBER('MiT Strom Pipeline'!I7),'MiT Strom Pipeline'!I7,0),"") | G76: =IF(('MiT Strom Pipeline'!R7="offered")+('MiT Strom Pipeline'!R7="to be offered")+('MiT Strom Pipeline'!R7="on hold")>0,IF(ISNUMBER('MiT Strom Pipeline'!Q7),'MiT Strom Pipeline'!Q7,0),"") | H76: =IF(('MiT Strom Pipeline'!R7="offered")+('MiT Strom Pipeline'!R7="to be offered")+('MiT Strom Pipeline'!R7="on hold")>0,IF(ISNUMBER('MiT Strom Pipeline'!O7),'MiT Strom Pipeline'!O7,0),"") | I76: =IF(('MiT Strom Pipeline'!R7="offered")+('MiT Strom Pipeline'!R7="to be offered")+('MiT Strom Pipeline'!R7="on hold")>0,'MiT Strom Pipeline'!R7,"") | J76: =IF(('MiT Strom Pipeline'!R7="offered")+('MiT Strom Pipeline'!R7="to be offered")+('MiT Strom Pipeline'!R7="on hold")>0,'MiT Strom Pipeline'!S7,"") | K76: =IF(('MiT Strom Pipeline'!R7="offered")+('MiT Strom Pipeline'!R7="to be offered")+('MiT Strom Pipeline'!R7="on hold")>0,IF(LEN('MiT Strom Pipeline'!V7)>0,LEFT('MiT Strom Pipeline'!V7,55),""),"")
A77: =IF(('MiT Strom Pipeline'!R8="offered")+('MiT Strom Pipeline'!R8="to be offered")+('MiT Strom Pipeline'!R8="on hold")>0,IF(ISNUMBER('MiT Strom Pipeline'!A8),'MiT Strom Pipeline'!A8,""),"") | B77: =IF(('MiT Strom Pipeline'!R8="offered")+('MiT Strom Pipeline'!R8="to be offered")+('MiT Strom Pipeline'!R8="on hold")>0,'MiT Strom Pipeline'!B8,"") | C77: =IF(('MiT Strom Pipeline'!R8="offered")+('MiT Strom Pipeline'!R8="to be offered")+('MiT Strom Pipeline'!R8="on hold")>0,'MiT Strom Pipeline'!C8,"") | D77: =IF(('MiT Strom Pipeline'!R8="offered")+('MiT Strom Pipeline'!R8="to be offered")+('MiT Strom Pipeline'!R8="on hold")>0,'MiT Strom Pipeline'!D8,"") | E77: =IF(('MiT Strom Pipeline'!R8="offered")+('MiT Strom Pipeline'!R8="to be offered")+('MiT Strom Pipeline'!R8="on hold")>0,'MiT Strom Pipeline'!E8,"") | F77: =IF(('MiT Strom Pipeline'!R8="offered")+('MiT Strom Pipeline'!R8="to be offered")+('MiT Strom Pipeline'!R8="on hold")>0,IF(ISNUMBER('MiT Strom Pipeline'!I8),'MiT Strom Pipeline'!I8,0),"") | G77: =IF(('MiT Strom Pipeline'!R8="offered")+('MiT Strom Pipeline'!R8="to be offered")+('MiT Strom Pipeline'!R8="on hold")>0,IF(ISNUMBER('MiT Strom Pipeline'!Q8),'MiT Strom Pipeline'!Q8,0),"") | H77: =IF(('MiT Strom Pipeline'!R8="offered")+('MiT Strom Pipeline'!R8="to be offered")+('MiT Strom Pipeline'!R8="on hold")>0,IF(ISNUMBER('MiT Strom Pipeline'!O8),'MiT Strom Pipeline'!O8,0),"") | I77: =IF(('MiT Strom Pipeline'!R8="offered")+('MiT Strom Pipeline'!R8="to be offered")+('MiT Strom Pipeline'!R8="on hold")>0,'MiT Strom Pipeline'!R8,"") | J77: =IF(('MiT Strom Pipeline'!R8="offered")+('MiT Strom Pipeline'!R8="to be offered")+('MiT Strom Pipeline'!R8="on hold")>0,'MiT Strom Pipeline'!S8,"") | K77: =IF(('MiT Strom Pipeline'!R8="offered")+('MiT Strom Pipeline'!R8="to be offered")+('MiT Strom Pipeline'!R8="on hold")>0,IF(LEN('MiT Strom Pipeline'!V8)>0,LEFT('MiT Strom Pipeline'!V8,55),""),"")
A78: =IF(('MiT Strom Pipeline'!R9="offered")+('MiT Strom Pipeline'!R9="to be offered")+('MiT Strom Pipeline'!R9="on hold")>0,IF(ISNUMBER('MiT Strom Pipeline'!A9),'MiT Strom Pipeline'!A9,""),"") -> 4 | B78: =IF(('MiT Strom Pipeline'!R9="offered")+('MiT Strom Pipeline'!R9="to be offered")+('MiT Strom Pipeline'!R9="on hold")>0,'MiT Strom Pipeline'!B9,"") -> Stagelight – OpenAir Frauenfeld | C78: =IF(('MiT Strom Pipeline'!R9="offered")+('MiT Strom Pipeline'!R9="to be offered")+('MiT Strom Pipeline'!R9="on hold")>0,'MiT Strom Pipeline'!C9,"") -> TG | D78: =IF(('MiT Strom Pipeline'!R9="offered")+('MiT Strom Pipeline'!R9="to be offered")+('MiT Strom Pipeline'!R9="on hold")>0,'MiT Strom Pipeline'!D9,"") -> Events & Kultur | E78: =IF(('MiT Strom Pipeline'!R9="offered")+('MiT Strom Pipeline'!R9="to be offered")+('MiT Strom Pipeline'!R9="on hold")>0,'MiT Strom Pipeline'!E9,"") -> ~500 kVA Generator | F78: =IF(('MiT Strom Pipeline'!R9="offered")+('MiT Strom Pipeline'!R9="to be offered")+('MiT Strom Pipeline'!R9="on hold")>0,IF(ISNUMBER('MiT Strom Pipeline'!I9),'MiT Strom Pipeline'!I9,0),"") -> 150000 | G78: =IF(('MiT Strom Pipeline'!R9="offered")+('MiT Strom Pipeline'!R9="to be offered")+('MiT Strom Pipeline'!R9="on hold")>0,IF(ISNUMBER('MiT Strom Pipeline'!Q9),'MiT Strom Pipeline'!Q9,0),"") -> 1350 | H78: =IF(('MiT Strom Pipeline'!R9="offered")+('MiT Strom Pipeline'!R9="to be offered")+('MiT Strom Pipeline'!R9="on hold")>0,IF(ISNUMBER('MiT Strom Pipeline'!O9),'MiT Strom Pipeline'!O9,0),"") -> 39500 | I78: =IF(('MiT Strom Pipeline'!R9="offered")+('MiT Strom Pipeline'!R9="to be offered")+('MiT Strom Pipeline'!R9="on hold")>0,'MiT Strom Pipeline'!R9,"") -> offered | J78: =IF(('MiT Strom Pipeline'!R9="offered")+('MiT Strom Pipeline'!R9="to be offered")+('MiT Strom Pipeline'!R9="on hold")>0,'MiT Strom Pipeline'!S9,"") -> 90% | K78: =IF(('MiT Strom Pipeline'!R9="offered")+('MiT Strom Pipeline'!R9="to be offered")+('MiT Strom Pipeline'!R9="on hold")>0,IF(LEN('MiT Strom Pipeline'!V9)>0,LEFT('MiT Strom Pipeline'!V9,55),""),"") -> Follow-up + Vertragsverhandlung initiieren
A79: =IF(('MiT Strom Pipeline'!R10="offered")+('MiT Strom Pipeline'!R10="to be offered")+('MiT Strom Pipeline'!R10="on hold")>0,IF(ISNUMBER('MiT Strom Pipeline'!A10),'MiT Strom Pipeline'!A10,""),"") -> 6 | B79: =IF(('MiT Strom Pipeline'!R10="offered")+('MiT Strom Pipeline'!R10="to be offered")+('MiT Strom Pipeline'!R10="on hold")>0,'MiT Strom Pipeline'!B10,"") -> Wincasa Solothurn | C79: =IF(('MiT Strom Pipeline'!R10="offered")+('MiT Strom Pipeline'!R10="to be offered")+('MiT Strom Pipeline'!R10="on hold")>0,'MiT Strom Pipeline'!C10,"") -> SO | D79: =IF(('MiT Strom Pipeline'!R10="offered")+('MiT Strom Pipeline'!R10="to be offered")+('MiT Strom Pipeline'!R10="on hold")>0,'MiT Strom Pipeline'!D10,"") -> Immobilien / FM | E79: =IF(('MiT Strom Pipeline'!R10="offered")+('MiT Strom Pipeline'!R10="to be offered")+('MiT Strom Pipeline'!R10="on hold")>0,'MiT Strom Pipeline'!E10,"") -> BESS 1 MWh | F79: =IF(('MiT Strom Pipeline'!R10="offered")+('MiT Strom Pipeline'!R10="to be offered")+('MiT Strom Pipeline'!R10="on hold")>0,IF(ISNUMBER('MiT Strom Pipeline'!I10),'MiT Strom Pipeline'!I10,0),"") -> 390000 | G79: =IF(('MiT Strom Pipeline'!R10="offered")+('MiT Strom Pipeline'!R10="to be offered")+('MiT Strom Pipeline'!R10="on hold")>0,IF(ISNUMBER('MiT Strom Pipeline'!Q10),'MiT Strom Pipeline'!Q10,0),"") -> 1950 | H79: =IF(('MiT Strom Pipeline'!R10="offered")+('MiT Strom Pipeline'!R10="to be offered")+('MiT Strom Pipeline'!R10="on hold")>0,IF(ISNUMBER('MiT Strom Pipeline'!O10),'MiT Strom Pipeline'!O10,0),"") -> 118000 | I79: =IF(('MiT Strom Pipeline'!R10="offered")+('MiT Strom Pipeline'!R10="to be offered")+('MiT Strom Pipeline'!R10="on hold")>0,'MiT Strom Pipeline'!R10,"") -> on hold | J79: =IF(('MiT Strom Pipeline'!R10="offered")+('MiT Strom Pipeline'!R10="to be offered")+('MiT Strom Pipeline'!R10="on hold")>0,'MiT Strom Pipeline'!S10,"") -> 50% | K79: =IF(('MiT Strom Pipeline'!R10="offered")+('MiT Strom Pipeline'!R10="to be offered")+('MiT Strom Pipeline'!R10="on hold")>0,IF(LEN('MiT Strom Pipeline'!V10)>0,LEFT('MiT Strom Pipeline'!V10,55),""),"") -> Entscheider-Meeting anfordern, Businesscase Energie-ROI
A80: =IF(('MiT Strom Pipeline'!R11="offered")+('MiT Strom Pipeline'!R11="to be offered")+('MiT Strom Pipeline'!R11="on hold")>0,IF(ISNUMBER('MiT Strom Pipeline'!A11),'MiT Strom Pipeline'!A11,""),"") | B80: =IF(('MiT Strom Pipeline'!R11="offered")+('MiT Strom Pipeline'!R11="to be offered")+('MiT Strom Pipeline'!R11="on hold")>0,'MiT Strom Pipeline'!B11,"") | C80: =IF(('MiT Strom Pipeline'!R11="offered")+('MiT Strom Pipeline'!R11="to be offered")+('MiT Strom Pipeline'!R11="on hold")>0,'MiT Strom Pipeline'!C11,"") | D80: =IF(('MiT Strom Pipeline'!R11="offered")+('MiT Strom Pipeline'!R11="to be offered")+('MiT Strom Pipeline'!R11="on hold")>0,'MiT Strom Pipeline'!D11,"") | E80: =IF(('MiT Strom Pipeline'!R11="offered")+('MiT Strom Pipeline'!R11="to be offered")+('MiT Strom Pipeline'!R11="on hold")>0,'MiT Strom Pipeline'!E11,"") | F80: =IF(('MiT Strom Pipeline'!R11="offered")+('MiT Strom Pipeline'!R11="to be offered")+('MiT Strom Pipeline'!R11="on hold")>0,IF(ISNUMBER('MiT Strom Pipeline'!I11),'MiT Strom Pipeline'!I11,0),"") | G80: =IF(('MiT Strom Pipeline'!R11="offered")+('MiT Strom Pipeline'!R11="to be offered")+('MiT Strom Pipeline'!R11="on hold")>0,IF(ISNUMBER('MiT Strom Pipeline'!Q11),'MiT Strom Pipeline'!Q11,0),"") | H80: =IF(('MiT Strom Pipeline'!R11="offered")+('MiT Strom Pipeline'!R11="to be offered")+('MiT Strom Pipeline'!R11="on hold")>0,IF(ISNUMBER('MiT Strom Pipeline'!O11),'MiT Strom Pipeline'!O11,0),"") | I80: =IF(('MiT Strom Pipeline'!R11="offered")+('MiT Strom Pipeline'!R11="to be offered")+('MiT Strom Pipeline'!R11="on hold")>0,'MiT Strom Pipeline'!R11,"") | J80: =IF(('MiT Strom Pipeline'!R11="offered")+('MiT Strom Pipeline'!R11="to be offered")+('MiT Strom Pipeline'!R11="on hold")>0,'MiT Strom Pipeline'!S11,"") | K80: =IF(('MiT Strom Pipeline'!R11="offered")+('MiT Strom Pipeline'!R11="to be offered")+('MiT Strom Pipeline'!R11="on hold")>0,IF(LEN('MiT Strom Pipeline'!V11)>0,LEFT('MiT Strom Pipeline'!V11,55),""),"")
A81: =IF(('MiT Strom Pipeline'!R12="offered")+('MiT Strom Pipeline'!R12="to be offered")+('MiT Strom Pipeline'!R12="on hold")>0,IF(ISNUMBER('MiT Strom Pipeline'!A12),'MiT Strom Pipeline'!A12,""),"") | B81: =IF(('MiT Strom Pipeline'!R12="offered")+('MiT Strom Pipeline'!R12="to be offered")+('MiT Strom Pipeline'!R12="on hold")>0,'MiT Strom Pipeline'!B12,"") | C81: =IF(('MiT Strom Pipeline'!R12="offered")+('MiT Strom Pipeline'!R12="to be offered")+('MiT Strom Pipeline'!R12="on hold")>0,'MiT Strom Pipeline'!C12,"") | D81: =IF(('MiT Strom Pipeline'!R12="offered")+('MiT Strom Pipeline'!R12="to be offered")+('MiT Strom Pipeline'!R12="on hold")>0,'MiT Strom Pipeline'!D12,"") | E81: =IF(('MiT Strom Pipeline'!R12="offered")+('MiT Strom Pipeline'!R12="to be offered")+('MiT Strom Pipeline'!R12="on hold")>0,'MiT Strom Pipeline'!E12,"") | F81: =IF(('MiT Strom Pipeline'!R12="offered")+('MiT Strom Pipeline'!R12="to be offered")+('MiT Strom Pipeline'!R12="on hold")>0,IF(ISNUMBER('MiT Strom Pipeline'!I12),'MiT Strom Pipeline'!I12,0),"") | G81: =IF(('MiT Strom Pipeline'!R12="offered")+('MiT Strom Pipeline'!R12="to be offered")+('MiT Strom Pipeline'!R12="on hold")>0,IF(ISNUMBER('MiT Strom Pipeline'!Q12),'MiT Strom Pipeline'!Q12,0),"") | H81: =IF(('MiT Strom Pipeline'!R12="offered")+('MiT Strom Pipeline'!R12="to be offered")+('MiT Strom Pipeline'!R12="on hold")>0,IF(ISNUMBER('MiT Strom Pipeline'!O12),'MiT Strom Pipeline'!O12,0),"") | I81: =IF(('MiT Strom Pipeline'!R12="offered")+('MiT Strom Pipeline'!R12="to be offered")+('MiT Strom Pipeline'!R12="on hold")>0,'MiT Strom Pipeline'!R12,"") | J81: =IF(('MiT Strom Pipeline'!R12="offered")+('MiT Strom Pipeline'!R12="to be offered")+('MiT Strom Pipeline'!R12="on hold")>0,'MiT Strom Pipeline'!S12,"") | K81: =IF(('MiT Strom Pipeline'!R12="offered")+('MiT Strom Pipeline'!R12="to be offered")+('MiT Strom Pipeline'!R12="on hold")>0,IF(LEN('MiT Strom Pipeline'!V12)>0,LEFT('MiT Strom Pipeline'!V12,55),""),"")
A82: =IF(('MiT Strom Pipeline'!R13="offered")+('MiT Strom Pipeline'!R13="to be offered")+('MiT Strom Pipeline'!R13="on hold")>0,IF(ISNUMBER('MiT Strom Pipeline'!A13),'MiT Strom Pipeline'!A13,""),"") | B82: =IF(('MiT Strom Pipeline'!R13="offered")+('MiT Strom Pipeline'!R13="to be offered")+('MiT Strom Pipeline'!R13="on hold")>0,'MiT Strom Pipeline'!B13,"") | C82: =IF(('MiT Strom Pipeline'!R13="offered")+('MiT Strom Pipeline'!R13="to be offered")+('MiT Strom Pipeline'!R13="on hold")>0,'MiT Strom Pipeline'!C13,"") | D82: =IF(('MiT Strom Pipeline'!R13="offered")+('MiT Strom Pipeline'!R13="to be offered")+('MiT Strom Pipeline'!R13="on hold")>0,'MiT Strom Pipeline'!D13,"") | E82: =IF(('MiT Strom Pipeline'!R13="offered")+('MiT Strom Pipeline'!R13="to be offered")+('MiT Strom Pipeline'!R13="on hold")>0,'MiT Strom Pipeline'!E13,"") | F82: =IF(('MiT Strom Pipeline'!R13="offered")+('MiT Strom Pipeline'!R13="to be offered")+('MiT Strom Pipeline'!R13="on hold")>0,IF(ISNUMBER('MiT Strom Pipeline'!I13),'MiT Strom Pipeline'!I13,0),"") | G82: =IF(('MiT Strom Pipeline'!R13="offered")+('MiT Strom Pipeline'!R13="to be offered")+('MiT Strom Pipeline'!R13="on hold")>0,IF(ISNUMBER('MiT Strom Pipeline'!Q13),'MiT Strom Pipeline'!Q13,0),"") | H82: =IF(('MiT Strom Pipeline'!R13="offered")+('MiT Strom Pipeline'!R13="to be offered")+('MiT Strom Pipeline'!R13="on hold")>0,IF(ISNUMBER('MiT Strom Pipeline'!O13),'MiT Strom Pipeline'!O13,0),"") | I82: =IF(('MiT Strom Pipeline'!R13="offered")+('MiT Strom Pipeline'!R13="to be offered")+('MiT Strom Pipeline'!R13="on hold")>0,'MiT Strom Pipeline'!R13,"") | J82: =IF(('MiT Strom Pipeline'!R13="offered")+('MiT Strom Pipeline'!R13="to be offered")+('MiT Strom Pipeline'!R13="on hold")>0,'MiT Strom Pipeline'!S13,"") | K82: =IF(('MiT Strom Pipeline'!R13="offered")+('MiT Strom Pipeline'!R13="to be offered")+('MiT Strom Pipeline'!R13="on hold")>0,IF(LEN('MiT Strom Pipeline'!V13)>0,LEFT('MiT Strom Pipeline'!V13,55),""),"")
A83: =IF(('MiT Strom Pipeline'!R14="offered")+('MiT Strom Pipeline'!R14="to be offered")+('MiT Strom Pipeline'!R14="on hold")>0,IF(ISNUMBER('MiT Strom Pipeline'!A14),'MiT Strom Pipeline'!A14,""),"") | B83: =IF(('MiT Strom Pipeline'!R14="offered")+('MiT Strom Pipeline'!R14="to be offered")+('MiT Strom Pipeline'!R14="on hold")>0,'MiT Strom Pipeline'!B14,"") | C83: =IF(('MiT Strom Pipeline'!R14="offered")+('MiT Strom Pipeline'!R14="to be offered")+('MiT Strom Pipeline'!R14="on hold")>0,'MiT Strom Pipeline'!C14,"") | D83: =IF(('MiT Strom Pipeline'!R14="offered")+('MiT Strom Pipeline'!R14="to be offered")+('MiT Strom Pipeline'!R14="on hold")>0,'MiT Strom Pipeline'!D14,"") | E83: =IF(('MiT Strom Pipeline'!R14="offered")+('MiT Strom Pipeline'!R14="to be offered")+('MiT Strom Pipeline'!R14="on hold")>0,'MiT Strom Pipeline'!E14,"") | F83: =IF(('MiT Strom Pipeline'!R14="offered")+('MiT Strom Pipeline'!R14="to be offered")+('MiT Strom Pipeline'!R14="on hold")>0,IF(ISNUMBER('MiT Strom Pipeline'!I14),'MiT Strom Pipeline'!I14,0),"") | G83: =IF(('MiT Strom Pipeline'!R14="offered")+('MiT Strom Pipeline'!R14="to be offered")+('MiT Strom Pipeline'!R14="on hold")>0,IF(ISNUMBER('MiT Strom Pipeline'!Q14),'MiT Strom Pipeline'!Q14,0),"") | H83: =IF(('MiT Strom Pipeline'!R14="offered")+('MiT Strom Pipeline'!R14="to be offered")+('MiT Strom Pipeline'!R14="on hold")>0,IF(ISNUMBER('MiT Strom Pipeline'!O14),'MiT Strom Pipeline'!O14,0),"") | I83: =IF(('MiT Strom Pipeline'!R14="offered")+('MiT Strom Pipeline'!R14="to be offered")+('MiT Strom Pipeline'!R14="on hold")>0,'MiT Strom Pipeline'!R14,"") | J83: =IF(('MiT Strom Pipeline'!R14="offered")+('MiT Strom Pipeline'!R14="to be offered")+('MiT Strom Pipeline'!R14="on hold")>0,'MiT Strom Pipeline'!S14,"") | K83: =IF(('MiT Strom Pipeline'!R14="offered")+('MiT Strom Pipeline'!R14="to be offered")+('MiT Strom Pipeline'!R14="on hold")>0,IF(LEN('MiT Strom Pipeline'!V14)>0,LEFT('MiT Strom Pipeline'!V14,55),""),"")
A84: =IF(('MiT Strom Pipeline'!R15="offered")+('MiT Strom Pipeline'!R15="to be offered")+('MiT Strom Pipeline'!R15="on hold")>0,IF(ISNUMBER('MiT Strom Pipeline'!A15),'MiT Strom Pipeline'!A15,""),"") | B84: =IF(('MiT Strom Pipeline'!R15="offered")+('MiT Strom Pipeline'!R15="to be offered")+('MiT Strom Pipeline'!R15="on hold")>0,'MiT Strom Pipeline'!B15,"") | C84: =IF(('MiT Strom Pipeline'!R15="offered")+('MiT Strom Pipeline'!R15="to be offered")+('MiT Strom Pipeline'!R15="on hold")>0,'MiT Strom Pipeline'!C15,"") | D84: =IF(('MiT Strom Pipeline'!R15="offered")+('MiT Strom Pipeline'!R15="to be offered")+('MiT Strom Pipeline'!R15="on hold")>0,'MiT Strom Pipeline'!D15,"") | E84: =IF(('MiT Strom Pipeline'!R15="offered")+('MiT Strom Pipeline'!R15="to be offered")+('MiT Strom Pipeline'!R15="on hold")>0,'MiT Strom Pipeline'!E15,"") | F84: =IF(('MiT Strom Pipeline'!R15="offered")+('MiT Strom Pipeline'!R15="to be offered")+('MiT Strom Pipeline'!R15="on hold")>0,IF(ISNUMBER('MiT Strom Pipeline'!I15),'MiT Strom Pipeline'!I15,0),"") | G84: =IF(('MiT Strom Pipeline'!R15="offered")+('MiT Strom Pipeline'!R15="to be offered")+('MiT Strom Pipeline'!R15="on hold")>0,IF(ISNUMBER('MiT Strom Pipeline'!Q15),'MiT Strom Pipeline'!Q15,0),"") | H84: =IF(('MiT Strom Pipeline'!R15="offered")+('MiT Strom Pipeline'!R15="to be offered")+('MiT Strom Pipeline'!R15="on hold")>0,IF(ISNUMBER('MiT Strom Pipeline'!O15),'MiT Strom Pipeline'!O15,0),"") | I84: =IF(('MiT Strom Pipeline'!R15="offered")+('MiT Strom Pipeline'!R15="to be offered")+('MiT Strom Pipeline'!R15="on hold")>0,'MiT Strom Pipeline'!R15,"") | J84: =IF(('MiT Strom Pipeline'!R15="offered")+('MiT Strom Pipeline'!R15="to be offered")+('MiT Strom Pipeline'!R15="on hold")>0,'MiT Strom Pipeline'!S15,"") | K84: =IF(('MiT Strom Pipeline'!R15="offered")+('MiT Strom Pipeline'!R15="to be offered")+('MiT Strom Pipeline'!R15="on hold")>0,IF(LEN('MiT Strom Pipeline'!V15)>0,LEFT('MiT Strom Pipeline'!V15,55),""),"")
A85: =IF(('MiT Strom Pipeline'!R16="offered")+('MiT Strom Pipeline'!R16="to be offered")+('MiT Strom Pipeline'!R16="on hold")>0,IF(ISNUMBER('MiT Strom Pipeline'!A16),'MiT Strom Pipeline'!A16,""),"") | B85: =IF(('MiT Strom Pipeline'!R16="offered")+('MiT Strom Pipeline'!R16="to be offered")+('MiT Strom Pipeline'!R16="on hold")>0,'MiT Strom Pipeline'!B16,"") | C85: =IF(('MiT Strom Pipeline'!R16="offered")+('MiT Strom Pipeline'!R16="to be offered")+('MiT Strom Pipeline'!R16="on hold")>0,'MiT Strom Pipeline'!C16,"") | D85: =IF(('MiT Strom Pipeline'!R16="offered")+('MiT Strom Pipeline'!R16="to be offered")+('MiT Strom Pipeline'!R16="on hold")>0,'MiT Strom Pipeline'!D16,"") | E85: =IF(('MiT Strom Pipeline'!R16="offered")+('MiT Strom Pipeline'!R16="to be offered")+('MiT Strom Pipeline'!R16="on hold")>0,'MiT Strom Pipeline'!E16,"") | F85: =IF(('MiT Strom Pipeline'!R16="offered")+('MiT Strom Pipeline'!R16="to be offered")+('MiT Strom Pipeline'!R16="on hold")>0,IF(ISNUMBER('MiT Strom Pipeline'!I16),'MiT Strom Pipeline'!I16,0),"") | G85: =IF(('MiT Strom Pipeline'!R16="offered")+('MiT Strom Pipeline'!R16="to be offered")+('MiT Strom Pipeline'!R16="on hold")>0,IF(ISNUMBER('MiT Strom Pipeline'!Q16),'MiT Strom Pipeline'!Q16,0),"") | H85: =IF(('MiT Strom Pipeline'!R16="offered")+('MiT Strom Pipeline'!R16="to be offered")+('MiT Strom Pipeline'!R16="on hold")>0,IF(ISNUMBER('MiT Strom Pipeline'!O16),'MiT Strom Pipeline'!O16,0),"") | I85: =IF(('MiT Strom Pipeline'!R16="offered")+('MiT Strom Pipeline'!R16="to be offered")+('MiT Strom Pipeline'!R16="on hold")>0,'MiT Strom Pipeline'!R16,"") | J85: =IF(('MiT Strom Pipeline'!R16="offered")+('MiT Strom Pipeline'!R16="to be offered")+('MiT Strom Pipeline'!R16="on hold")>0,'MiT Strom Pipeline'!S16,"") | K85: =IF(('MiT Strom Pipeline'!R16="offered")+('MiT Strom Pipeline'!R16="to be offered")+('MiT Strom Pipeline'!R16="on hold")>0,IF(LEN('MiT Strom Pipeline'!V16)>0,LEFT('MiT Strom Pipeline'!V16,55),""),"")
A86: =IF(('MiT Strom Pipeline'!R17="offered")+('MiT Strom Pipeline'!R17="to be offered")+('MiT Strom Pipeline'!R17="on hold")>0,IF(ISNUMBER('MiT Strom Pipeline'!A17),'MiT Strom Pipeline'!A17,""),"") -> 13 | B86: =IF(('MiT Strom Pipeline'!R17="offered")+('MiT Strom Pipeline'!R17="to be offered")+('MiT Strom Pipeline'!R17="on hold")>0,'MiT Strom Pipeline'!B17,"") -> Proxima Fusion AG | C86: =IF(('MiT Strom Pipeline'!R17="offered")+('MiT Strom Pipeline'!R17="to be offered")+('MiT Strom Pipeline'!R17="on hold")>0,'MiT Strom Pipeline'!C17,"") -> ZH | D86: =IF(('MiT Strom Pipeline'!R17="offered")+('MiT Strom Pipeline'!R17="to be offered")+('MiT Strom Pipeline'!R17="on hold")>0,'MiT Strom Pipeline'!D17,"") -> Forschung / Hightech | E86: =IF(('MiT Strom Pipeline'!R17="offered")+('MiT Strom Pipeline'!R17="to be offered")+('MiT Strom Pipeline'!R17="on hold")>0,'MiT Strom Pipeline'!E17,"") -> BESS 1 MWh | F86: =IF(('MiT Strom Pipeline'!R17="offered")+('MiT Strom Pipeline'!R17="to be offered")+('MiT Strom Pipeline'!R17="on hold")>0,IF(ISNUMBER('MiT Strom Pipeline'!I17),'MiT Strom Pipeline'!I17,0),"") -> 365003 | G86: =IF(('MiT Strom Pipeline'!R17="offered")+('MiT Strom Pipeline'!R17="to be offered")+('MiT Strom Pipeline'!R17="on hold")>0,IF(ISNUMBER('MiT Strom Pipeline'!Q17),'MiT Strom Pipeline'!Q17,0),"") -> 182501.5 | H86: =IF(('MiT Strom Pipeline'!R17="offered")+('MiT Strom Pipeline'!R17="to be offered")+('MiT Strom Pipeline'!R17="on hold")>0,IF(ISNUMBER('MiT Strom Pipeline'!O17),'MiT Strom Pipeline'!O17,0),"") -> 0 | I86: =IF(('MiT Strom Pipeline'!R17="offered")+('MiT Strom Pipeline'!R17="to be offered")+('MiT Strom Pipeline'!R17="on hold")>0,'MiT Strom Pipeline'!R17,"") -> offered | J86: =IF(('MiT Strom Pipeline'!R17="offered")+('MiT Strom Pipeline'!R17="to be offered")+('MiT Strom Pipeline'!R17="on hold")>0,'MiT Strom Pipeline'!S17,"") -> 50 | K86: =IF(('MiT Strom Pipeline'!R17="offered")+('MiT Strom Pipeline'!R17="to be offered")+('MiT Strom Pipeline'!R17="on hold")>0,IF(LEN('MiT Strom Pipeline'!V17)>0,LEFT('MiT Strom Pipeline'!V17,55),""),"") -> Technisches Gespräch – USV + PQ-Anforderungen klären, K
... A134: =IF(('MiT Strom Pipeline'!R65="offered")+('MiT Strom Pipeline'!R65="to be offered")+('MiT Strom Pipeline'!R65="on hold")>0,IF(ISNUMBER('MiT Strom Pipeline'!A65),'MiT Strom Pipeline'!A65,""),"") | B134: =IF(('MiT Strom Pipeline'!R65="offered")+('MiT Strom Pipeline'!R65="to be offered")+('MiT Strom Pipeline'!R65="on hold")>0,'MiT Strom Pipeline'!B65,"") | C134: =IF(('MiT Strom Pipeline'!R65="offered")+('MiT Strom Pipeline'!R65="to be offered")+('MiT Strom Pipeline'!R65="on hold")>0,'MiT Strom Pipeline'!C65,"") | D134: =IF(('MiT Strom Pipeline'!R65="offered")+('MiT Strom Pipeline'!R65="to be offered")+('MiT Strom Pipeline'!R65="on hold")>0,'MiT Strom Pipeline'!D65,"") | E134: =IF(('MiT Strom Pipeline'!R65="offered")+('MiT Strom Pipeline'!R65="to be offered")+('MiT Strom Pipeline'!R65="on hold")>0,'MiT Strom Pipeline'!E65,"") | F134: =IF(('MiT Strom Pipeline'!R65="offered")+('MiT Strom Pipeline'!R65="to be offered")+('MiT Strom Pipeline'!R65="on hold")>0,IF(ISNUMBER('MiT Strom Pipeline'!I65),'MiT Strom Pipeline'!I65,0),"") | G134: =IF(('MiT Strom Pipeline'!R65="offered")+('MiT Strom Pipeline'!R65="to be offered")+('MiT Strom Pipeline'!R65="on hold")>0,IF(ISNUMBER('MiT Strom Pipeline'!Q65),'MiT Strom Pipeline'!Q65,0),"") | H134: =IF(('MiT Strom Pipeline'!R65="offered")+('MiT Strom Pipeline'!R65="to be offered")+('MiT Strom Pipeline'!R65="on hold")>0,IF(ISNUMBER('MiT Strom Pipeline'!O65),'MiT Strom Pipeline'!O65,0),"") | I134: =IF(('MiT Strom Pipeline'!R65="offered")+('MiT Strom Pipeline'!R65="to be offered")+('MiT Strom Pipeline'!R65="on hold")>0,'MiT Strom Pipeline'!R65,"") | J134: =IF(('MiT Strom Pipeline'!R65="offered")+('MiT Strom Pipeline'!R65="to be offered")+('MiT Strom Pipeline'!R65="on hold")>0,'MiT Strom Pipeline'!S65,"") | K134: =IF(('MiT Strom Pipeline'!R65="offered")+('MiT Strom Pipeline'!R65="to be offered")+('MiT Strom Pipeline'!R65="on hold")>0,IF(LEN('MiT Strom Pipeline'!V65)>0,LEFT('MiT Strom Pipeline'!V65,55),""),"")
A135: =IF(('MiT Strom Pipeline'!R66="offered")+('MiT Strom Pipeline'!R66="to be offered")+('MiT Strom Pipeline'!R66="on hold")>0,IF(ISNUMBER('MiT Strom Pipeline'!A66),'MiT Strom Pipeline'!A66,""),"") | B135: =IF(('MiT Strom Pipeline'!R66="offered")+('MiT Strom Pipeline'!R66="to be offered")+('MiT Strom Pipeline'!R66="on hold")>0,'MiT Strom Pipeline'!B66,"") | F135: =IF(('MiT Strom Pipeline'!R66="offered")+('MiT Strom Pipeline'!R66="to be offered")+('MiT Strom Pipeline'!R66="on hold")>0,IF(ISNUMBER('MiT Strom Pipeline'!I66),'MiT Strom Pipeline'!I66,0),"") | G135: =IF(('MiT Strom Pipeline'!R66="offered")+('MiT Strom Pipeline'!R66="to be offered")+('MiT Strom Pipeline'!R66="on hold")>0,IF(ISNUMBER('MiT Strom Pipeline'!Q66),'MiT Strom Pipeline'!Q66,0),"") | H135: =IF(('MiT Strom Pipeline'!R66="offered")+('MiT Strom Pipeline'!R66="to be offered")+('MiT Strom Pipeline'!R66="on hold")>0,IF(ISNUMBER('MiT Strom Pipeline'!O66),'MiT Strom Pipeline'!O66,0),"") | I135: =IF(('MiT Strom Pipeline'!R66="offered")+('MiT Strom Pipeline'!R66="to be offered")+('MiT Strom Pipeline'!R66="on hold")>0,'MiT Strom Pipeline'!R66,"") | J135: =IF(('MiT Strom Pipeline'!R66="offered")+('MiT Strom Pipeline'!R66="to be offered")+('MiT Strom Pipeline'!R66="on hold")>0,'MiT Strom Pipeline'!S66,"") | K135: =IF(('MiT Strom Pipeline'!R66="offered")+('MiT Strom Pipeline'!R66="to be offered")+('MiT Strom Pipeline'!R66="on hold")>0,IF(LEN('MiT Strom Pipeline'!V66)>0,LEFT('MiT Strom Pipeline'!V66,55),""),"")
A136: =IF(('MiT Strom Pipeline'!R67="offered")+('MiT Strom Pipeline'!R67="to be offered")+('MiT Strom Pipeline'!R67="on hold")>0,IF(ISNUMBER('MiT Strom Pipeline'!A67),'MiT Strom Pipeline'!A67,""),"") | B136: =IF(('MiT Strom Pipeline'!R67="offered")+('MiT Strom Pipeline'!R67="to be offered")+('MiT Strom Pipeline'!R67="on hold")>0,'MiT Strom Pipeline'!B67,"") | C136: =IF(('MiT Strom Pipeline'!R67="offered")+('MiT Strom Pipeline'!R67="to be offered")+('MiT Strom Pipeline'!R67="on hold")>0,'MiT Strom Pipeline'!C67,"") | D136: =IF(('MiT Strom Pipeline'!R67="offered")+('MiT Strom Pipeline'!R67="to be offered")+('MiT Strom Pipeline'!R67="on hold")>0,'MiT Strom Pipeline'!D67,"") | E136: =IF(('MiT Strom Pipeline'!R67="offered")+('MiT Strom Pipeline'!R67="to be offered")+('MiT Strom Pipeline'!R67="on hold")>0,'MiT Strom Pipeline'!E67,"") | F136: =IF(('MiT Strom Pipeline'!R67="offered")+('MiT Strom Pipeline'!R67="to be offered")+('MiT Strom Pipeline'!R67="on hold")>0,IF(ISNUMBER('MiT Strom Pipeline'!I67),'MiT Strom Pipeline'!I67,0),"") | G136: =IF(('MiT Strom Pipeline'!R67="offered")+('MiT Strom Pipeline'!R67="to be offered")+('MiT Strom Pipeline'!R67="on hold")>0,IF(ISNUMBER('MiT Strom Pipeline'!Q67),'MiT Strom Pipeline'!Q67,0),"") | H136: =IF(('MiT Strom Pipeline'!R67="offered")+('MiT Strom Pipeline'!R67="to be offered")+('MiT Strom Pipeline'!R67="on hold")>0,IF(ISNUMBER('MiT Strom Pipeline'!O67),'MiT Strom Pipeline'!O67,0),"") | I136: =IF(('MiT Strom Pipeline'!R67="offered")+('MiT Strom Pipeline'!R67="to be offered")+('MiT Strom Pipeline'!R67="on hold")>0,'MiT Strom Pipeline'!R67,"") | J136: =IF(('MiT Strom Pipeline'!R67="offered")+('MiT Strom Pipeline'!R67="to be offered")+('MiT Strom Pipeline'!R67="on hold")>0,'MiT Strom Pipeline'!S67,"") | K136: =IF(('MiT Strom Pipeline'!R67="offered")+('MiT Strom Pipeline'!R67="to be offered")+('MiT Strom Pipeline'!R67="on hold")>0,IF(LEN('MiT Strom Pipeline'!V67)>0,LEFT('MiT Strom Pipeline'!V67,55),""),"")
A137: 🎯 3. OPPORTUNITÄT — Qualifizierte Leads
A138: # | B138: Kunde / Unternehmen | C138: Kt. | D138: Segment | E138: Leistung / Fleet | F138: Volumen CHF | G138: Gew.Wert CHF | H138: Marge CHF | I138: Status | J138: Wahr.% | K138: Nächster Schritt
A139: =IF(('MiT Strom Pipeline'!R6="follow-up")+('MiT Strom Pipeline'!R6="Evaluation")+('MiT Strom Pipeline'!R6="tbd")+('MiT Strom Pipeline'!R6="In evaluation")>0,IF(ISNUMBER('MiT Strom Pipeline'!A6),'MiT Strom Pipeline'!A6,""),"") | B139: =IF(('MiT Strom Pipeline'!R6="follow-up")+('MiT Strom Pipeline'!R6="Evaluation")+('MiT Strom Pipeline'!R6="tbd")+('MiT Strom Pipeline'!R6="In evaluation")>0,'MiT Strom Pipeline'!B6,"") | C139: =IF(('MiT Strom Pipeline'!R6="follow-up")+('MiT Strom Pipeline'!R6="Evaluation")+('MiT Strom Pipeline'!R6="tbd")+('MiT Strom Pipeline'!R6="In evaluation")>0,'MiT Strom Pipeline'!C6,"") | D139: =IF(('MiT Strom Pipeline'!R6="follow-up")+('MiT Strom Pipeline'!R6="Evaluation")+('MiT Strom Pipeline'!R6="tbd")+('MiT Strom Pipeline'!R6="In evaluation")>0,'MiT Strom Pipeline'!D6,"") | E139: =IF(('MiT Strom Pipeline'!R6="follow-up")+('MiT Strom Pipeline'!R6="Evaluation")+('MiT Strom Pipeline'!R6="tbd")+('MiT Strom Pipeline'!R6="In evaluation")>0,'MiT Strom Pipeline'!E6,"") | F139: =IF(('MiT Strom Pipeline'!R6="follow-up")+('MiT Strom Pipeline'!R6="Evaluation")+('MiT Strom Pipeline'!R6="tbd")+('MiT Strom Pipeline'!R6="In evaluation")>0,IF(ISNUMBER('MiT Strom Pipeline'!I6),'MiT Strom Pipeline'!I6,0),"") | G139: =IF(('MiT Strom Pipeline'!R6="follow-up")+('MiT Strom Pipeline'!R6="Evaluation")+('MiT Strom Pipeline'!R6="tbd")+('MiT Strom Pipeline'!R6="In evaluation")>0,IF(ISNUMBER('MiT Strom Pipeline'!Q6),'MiT Strom Pipeline'!Q6,0),"") | H139: =IF(('MiT Strom Pipeline'!R6="follow-up")+('MiT Strom Pipeline'!R6="Evaluation")+('MiT Strom Pipeline'!R6="tbd")+('MiT Strom Pipeline'!R6="In evaluation")>0,IF(ISNUMBER('MiT Strom Pipeline'!O6),'MiT Strom Pipeline'!O6,0),"") | I139: =IF(('MiT Strom Pipeline'!R6="follow-up")+('MiT Strom Pipeline'!R6="Evaluation")+('MiT Strom Pipeline'!R6="tbd")+('MiT Strom Pipeline'!R6="In evaluation")>0,'MiT Strom Pipeline'!R6,"") | J139: =IF(('MiT Strom Pipeline'!R6="follow-up")+('MiT Strom Pipeline'!R6="Evaluation")+('MiT Strom Pipeline'!R6="tbd")+('MiT Strom Pipeline'!R6="In evaluation")>0,'MiT Strom Pipeline'!S6,"") | K139: =IF(('MiT Strom Pipeline'!R6="follow-up")+('MiT Strom Pipeline'!R6="Evaluation")+('MiT Strom Pipeline'!R6="tbd")+('MiT Strom Pipeline'!R6="In evaluation")>0,IF(LEN('MiT Strom Pipeline'!V6)>0,LEFT('MiT Strom Pipeline'!V6,55),""),"")
A140: =IF(('MiT Strom Pipeline'!R7="follow-up")+('MiT Strom Pipeline'!R7="Evaluation")+('MiT Strom Pipeline'!R7="tbd")+('MiT Strom Pipeline'!R7="In evaluation")>0,IF(ISNUMBER('MiT Strom Pipeline'!A7),'MiT Strom Pipeline'!A7,""),"") | B140: =IF(('MiT Strom Pipeline'!R7="follow-up")+('MiT Strom Pipeline'!R7="Evaluation")+('MiT Strom Pipeline'!R7="tbd")+('MiT Strom Pipeline'!R7="In evaluation")>0,'MiT Strom Pipeline'!B7,"") | C140: =IF(('MiT Strom Pipeline'!R7="follow-up")+('MiT Strom Pipeline'!R7="Evaluation")+('MiT Strom Pipeline'!R7="tbd")+('MiT Strom Pipeline'!R7="In evaluation")>0,'MiT Strom Pipeline'!C7,"") | D140: =IF(('MiT Strom Pipeline'!R7="follow-up")+('MiT Strom Pipeline'!R7="Evaluation")+('MiT Strom Pipeline'!R7="tbd")+('MiT Strom Pipeline'!R7="In evaluation")>0,'MiT Strom Pipeline'!D7,"") | E140: =IF(('MiT Strom Pipeline'!R7="follow-up")+('MiT Strom Pipeline'!R7="Evaluation")+('MiT Strom Pipeline'!R7="tbd")+('MiT Strom Pipeline'!R7="In evaluation")>0,'MiT Strom Pipeline'!E7,"") | F140: =IF(('MiT Strom Pipeline'!R7="follow-up")+('MiT Strom Pipeline'!R7="Evaluation")+('MiT Strom Pipeline'!R7="tbd")+('MiT Strom Pipeline'!R7="In evaluation")>0,IF(ISNUMBER('MiT Strom Pipeline'!I7),'MiT Strom Pipeline'!I7,0),"") | G140: =IF(('MiT Strom Pipeline'!R7="follow-up")+('MiT Strom Pipeline'!R7="Evaluation")+('MiT Strom Pipeline'!R7="tbd")+('MiT Strom Pipeline'!R7="In evaluation")>0,IF(ISNUMBER('MiT Strom Pipeline'!Q7),'MiT Strom Pipeline'!Q7,0),"") | H140: =IF(('MiT Strom Pipeline'!R7="follow-up")+('MiT Strom Pipeline'!R7="Evaluation")+('MiT Strom Pipeline'!R7="tbd")+('MiT Strom Pipeline'!R7="In evaluation")>0,IF(ISNUMBER('MiT Strom Pipeline'!O7),'MiT Strom Pipeline'!O7,0),"") | I140: =IF(('MiT Strom Pipeline'!R7="follow-up")+('MiT Strom Pipeline'!R7="Evaluation")+('MiT Strom Pipeline'!R7="tbd")+('MiT Strom Pipeline'!R7="In evaluation")>0,'MiT Strom Pipeline'!R7,"") | J140: =IF(('MiT Strom Pipeline'!R7="follow-up")+('MiT Strom Pipeline'!R7="Evaluation")+('MiT Strom Pipeline'!R7="tbd")+('MiT Strom Pipeline'!R7="In evaluation")>0,'MiT Strom Pipeline'!S7,"") | K140: =IF(('MiT Strom Pipeline'!R7="follow-up")+('MiT Strom Pipeline'!R7="Evaluation")+('MiT Strom Pipeline'!R7="tbd")+('MiT Strom Pipeline'!R7="In evaluation")>0,IF(LEN('MiT Strom Pipeline'!V7)>0,LEFT('MiT Strom Pipeline'!V7,55),""),"")
A141: =IF(('MiT Strom Pipeline'!R8="follow-up")+('MiT Strom Pipeline'!R8="Evaluation")+('MiT Strom Pipeline'!R8="tbd")+('MiT Strom Pipeline'!R8="In evaluation")>0,IF(ISNUMBER('MiT Strom Pipeline'!A8),'MiT Strom Pipeline'!A8,""),"") | B141: =IF(('MiT Strom Pipeline'!R8="follow-up")+('MiT Strom Pipeline'!R8="Evaluation")+('MiT Strom Pipeline'!R8="tbd")+('MiT Strom Pipeline'!R8="In evaluation")>0,'MiT Strom Pipeline'!B8,"") | C141: =IF(('MiT Strom Pipeline'!R8="follow-up")+('MiT Strom Pipeline'!R8="Evaluation")+('MiT Strom Pipeline'!R8="tbd")+('MiT Strom Pipeline'!R8="In evaluation")>0,'MiT Strom Pipeline'!C8,"") | D141: =IF(('MiT Strom Pipeline'!R8="follow-up")+('MiT Strom Pipeline'!R8="Evaluation")+('MiT Strom Pipeline'!R8="tbd")+('MiT Strom Pipeline'!R8="In evaluation")>0,'MiT Strom Pipeline'!D8,"") | E141: =IF(('MiT Strom Pipeline'!R8="follow-up")+('MiT Strom Pipeline'!R8="Evaluation")+('MiT Strom Pipeline'!R8="tbd")+('MiT Strom Pipeline'!R8="In evaluation")>0,'MiT Strom Pipeline'!E8,"") | F141: =IF(('MiT Strom Pipeline'!R8="follow-up")+('MiT Strom Pipeline'!R8="Evaluation")+('MiT Strom Pipeline'!R8="tbd")+('MiT Strom Pipeline'!R8="In evaluation")>0,IF(ISNUMBER('MiT Strom Pipeline'!I8),'MiT Strom Pipeline'!I8,0),"") | G141: =IF(('MiT Strom Pipeline'!R8="follow-up")+('MiT Strom Pipeline'!R8="Evaluation")+('MiT Strom Pipeline'!R8="tbd")+('MiT Strom Pipeline'!R8="In evaluation")>0,IF(ISNUMBER('MiT Strom Pipeline'!Q8),'MiT Strom Pipeline'!Q8,0),"") | H141: =IF(('MiT Strom Pipeline'!R8="follow-up")+('MiT Strom Pipeline'!R8="Evaluation")+('MiT Strom Pipeline'!R8="tbd")+('MiT Strom Pipeline'!R8="In evaluation")>0,IF(ISNUMBER('MiT Strom Pipeline'!O8),'MiT Strom Pipeline'!O8,0),"") | I141: =IF(('MiT Strom Pipeline'!R8="follow-up")+('MiT Strom Pipeline'!R8="Evaluation")+('MiT Strom Pipeline'!R8="tbd")+('MiT Strom Pipeline'!R8="In evaluation")>0,'MiT Strom Pipeline'!R8,"") | J141: =IF(('MiT Strom Pipeline'!R8="follow-up")+('MiT Strom Pipeline'!R8="Evaluation")+('MiT Strom Pipeline'!R8="tbd")+('MiT Strom Pipeline'!R8="In evaluation")>0,'MiT Strom Pipeline'!S8,"") | K141: =IF(('MiT Strom Pipeline'!R8="follow-up")+('MiT Strom Pipeline'!R8="Evaluation")+('MiT Strom Pipeline'!R8="tbd")+('MiT Strom Pipeline'!R8="In evaluation")>0,IF(LEN('MiT Strom Pipeline'!V8)>0,LEFT('MiT Strom Pipeline'!V8,55),""),"")
A142: =IF(('MiT Strom Pipeline'!R9="follow-up")+('MiT Strom Pipeline'!R9="Evaluation")+('MiT Strom Pipeline'!R9="tbd")+('MiT Strom Pipeline'!R9="In evaluation")>0,IF(ISNUMBER('MiT Strom Pipeline'!A9),'MiT Strom Pipeline'!A9,""),"") | B142: =IF(('MiT Strom Pipeline'!R9="follow-up")+('MiT Strom Pipeline'!R9="Evaluation")+('MiT Strom Pipeline'!R9="tbd")+('MiT Strom Pipeline'!R9="In evaluation")>0,'MiT Strom Pipeline'!B9,"") | C142: =IF(('MiT Strom Pipeline'!R9="follow-up")+('MiT Strom Pipeline'!R9="Evaluation")+('MiT Strom Pipeline'!R9="tbd")+('MiT Strom Pipeline'!R9="In evaluation")>0,'MiT Strom Pipeline'!C9,"") | D142: =IF(('MiT Strom Pipeline'!R9="follow-up")+('MiT Strom Pipeline'!R9="Evaluation")+('MiT Strom Pipeline'!R9="tbd")+('MiT Strom Pipeline'!R9="In evaluation")>0,'MiT Strom Pipeline'!D9,"") | E142: =IF(('MiT Strom Pipeline'!R9="follow-up")+('MiT Strom Pipeline'!R9="Evaluation")+('MiT Strom Pipeline'!R9="tbd")+('MiT Strom Pipeline'!R9="In evaluation")>0,'MiT Strom Pipeline'!E9,"") | F142: =IF(('MiT Strom Pipeline'!R9="follow-up")+('MiT Strom Pipeline'!R9="Evaluation")+('MiT Strom Pipeline'!R9="tbd")+('MiT Strom Pipeline'!R9="In evaluation")>0,IF(ISNUMBER('MiT Strom Pipeline'!I9),'MiT Strom Pipeline'!I9,0),"") | G142: =IF(('MiT Strom Pipeline'!R9="follow-up")+('MiT Strom Pipeline'!R9="Evaluation")+('MiT Strom Pipeline'!R9="tbd")+('MiT Strom Pipeline'!R9="In evaluation")>0,IF(ISNUMBER('MiT Strom Pipeline'!Q9),'MiT Strom Pipeline'!Q9,0),"") | H142: =IF(('MiT Strom Pipeline'!R9="follow-up")+('MiT Strom Pipeline'!R9="Evaluation")+('MiT Strom Pipeline'!R9="tbd")+('MiT Strom Pipeline'!R9="In evaluation")>0,IF(ISNUMBER('MiT Strom Pipeline'!O9),'MiT Strom Pipeline'!O9,0),"") | I142: =IF(('MiT Strom Pipeline'!R9="follow-up")+('MiT Strom Pipeline'!R9="Evaluation")+('MiT Strom Pipeline'!R9="tbd")+('MiT Strom Pipeline'!R9="In evaluation")>0,'MiT Strom Pipeline'!R9,"") | J142: =IF(('MiT Strom Pipeline'!R9="follow-up")+('MiT Strom Pipeline'!R9="Evaluation")+('MiT Strom Pipeline'!R9="tbd")+('MiT Strom Pipeline'!R9="In evaluation")>0,'MiT Strom Pipeline'!S9,"") | K142: =IF(('MiT Strom Pipeline'!R9="follow-up")+('MiT Strom Pipeline'!R9="Evaluation")+('MiT Strom Pipeline'!R9="tbd")+('MiT Strom Pipeline'!R9="In evaluation")>0,IF(LEN('MiT Strom Pipeline'!V9)>0,LEFT('MiT Strom Pipeline'!V9,55),""),"")
A143: =IF(('MiT Strom Pipeline'!R10="follow-up")+('MiT Strom Pipeline'!R10="Evaluation")+('MiT Strom Pipeline'!R10="tbd")+('MiT Strom Pipeline'!R10="In evaluation")>0,IF(ISNUMBER('MiT Strom Pipeline'!A10),'MiT Strom Pipeline'!A10,""),"") | B143: =IF(('MiT Strom Pipeline'!R10="follow-up")+('MiT Strom Pipeline'!R10="Evaluation")+('MiT Strom Pipeline'!R10="tbd")+('MiT Strom Pipeline'!R10="In evaluation")>0,'MiT Strom Pipeline'!B10,"") | C143: =IF(('MiT Strom Pipeline'!R10="follow-up")+('MiT Strom Pipeline'!R10="Evaluation")+('MiT Strom Pipeline'!R10="tbd")+('MiT Strom Pipeline'!R10="In evaluation")>0,'MiT Strom Pipeline'!C10,"") | D143: =IF(('MiT Strom Pipeline'!R10="follow-up")+('MiT Strom Pipeline'!R10="Evaluation")+('MiT Strom Pipeline'!R10="tbd")+('MiT Strom Pipeline'!R10="In evaluation")>0,'MiT Strom Pipeline'!D10,"") | E143: =IF(('MiT Strom Pipeline'!R10="follow-up")+('MiT Strom Pipeline'!R10="Evaluation")+('MiT Strom Pipeline'!R10="tbd")+('MiT Strom Pipeline'!R10="In evaluation")>0,'MiT Strom Pipeline'!E10,"") | F143: =IF(('MiT Strom Pipeline'!R10="follow-up")+('MiT Strom Pipeline'!R10="Evaluation")+('MiT Strom Pipeline'!R10="tbd")+('MiT Strom Pipeline'!R10="In evaluation")>0,IF(ISNUMBER('MiT Strom Pipeline'!I10),'MiT Strom Pipeline'!I10,0),"") | G143: =IF(('MiT Strom Pipeline'!R10="follow-up")+('MiT Strom Pipeline'!R10="Evaluation")+('MiT Strom Pipeline'!R10="tbd")+('MiT Strom Pipeline'!R10="In evaluation")>0,IF(ISNUMBER('MiT Strom Pipeline'!Q10),'MiT Strom Pipeline'!Q10,0),"") | H143: =IF(('MiT Strom Pipeline'!R10="follow-up")+('MiT Strom Pipeline'!R10="Evaluation")+('MiT Strom Pipeline'!R10="tbd")+('MiT Strom Pipeline'!R10="In evaluation")>0,IF(ISNUMBER('MiT Strom Pipeline'!O10),'MiT Strom Pipeline'!O10,0),"") | I143: =IF(('MiT Strom Pipeline'!R10="follow-up")+('MiT Strom Pipeline'!R10="Evaluation")+('MiT Strom Pipeline'!R10="tbd")+('MiT Strom Pipeline'!R10="In evaluation")>0,'MiT Strom Pipeline'!R10,"") | J143: =IF(('MiT Strom Pipeline'!R10="follow-up")+('MiT Strom Pipeline'!R10="Evaluation")+('MiT Strom Pipeline'!R10="tbd")+('MiT Strom Pipeline'!R10="In evaluation")>0,'MiT Strom Pipeline'!S10,"") | K143: =IF(('MiT Strom Pipeline'!R10="follow-up")+('MiT Strom Pipeline'!R10="Evaluation")+('MiT Strom Pipeline'!R10="tbd")+('MiT Strom Pipeline'!R10="In evaluation")>0,IF(LEN('MiT Strom Pipeline'!V10)>0,LEFT('MiT Strom Pipeline'!V10,55),""),"")
A144: =IF(('MiT Strom Pipeline'!R11="follow-up")+('MiT Strom Pipeline'!R11="Evaluation")+('MiT Strom Pipeline'!R11="tbd")+('MiT Strom Pipeline'!R11="In evaluation")>0,IF(ISNUMBER('MiT Strom Pipeline'!A11),'MiT Strom Pipeline'!A11,""),"") | B144: =IF(('MiT Strom Pipeline'!R11="follow-up")+('MiT Strom Pipeline'!R11="Evaluation")+('MiT Strom Pipeline'!R11="tbd")+('MiT Strom Pipeline'!R11="In evaluation")>0,'MiT Strom Pipeline'!B11,"") | C144: =IF(('MiT Strom Pipeline'!R11="follow-up")+('MiT Strom Pipeline'!R11="Evaluation")+('MiT Strom Pipeline'!R11="tbd")+('MiT Strom Pipeline'!R11="In evaluation")>0,'MiT Strom Pipeline'!C11,"") | D144: =IF(('MiT Strom Pipeline'!R11="follow-up")+('MiT Strom Pipeline'!R11="Evaluation")+('MiT Strom Pipeline'!R11="tbd")+('MiT Strom Pipeline'!R11="In evaluation")>0,'MiT Strom Pipeline'!D11,"") | E144: =IF(('MiT Strom Pipeline'!R11="follow-up")+('MiT Strom Pipeline'!R11="Evaluation")+('MiT Strom Pipeline'!R11="tbd")+('MiT Strom Pipeline'!R11="In evaluation")>0,'MiT Strom Pipeline'!E11,"") | F144: =IF(('MiT Strom Pipeline'!R11="follow-up")+('MiT Strom Pipeline'!R11="Evaluation")+('MiT Strom Pipeline'!R11="tbd")+('MiT Strom Pipeline'!R11="In evaluation")>0,IF(ISNUMBER('MiT Strom Pipeline'!I11),'MiT Strom Pipeline'!I11,0),"") | G144: =IF(('MiT Strom Pipeline'!R11="follow-up")+('MiT Strom Pipeline'!R11="Evaluation")+('MiT Strom Pipeline'!R11="tbd")+('MiT Strom Pipeline'!R11="In evaluation")>0,IF(ISNUMBER('MiT Strom Pipeline'!Q11),'MiT Strom Pipeline'!Q11,0),"") | H144: =IF(('MiT Strom Pipeline'!R11="follow-up")+('MiT Strom Pipeline'!R11="Evaluation")+('MiT Strom Pipeline'!R11="tbd")+('MiT Strom Pipeline'!R11="In evaluation")>0,IF(ISNUMBER('MiT Strom Pipeline'!O11),'MiT Strom Pipeline'!O11,0),"") | I144: =IF(('MiT Strom Pipeline'!R11="follow-up")+('MiT Strom Pipeline'!R11="Evaluation")+('MiT Strom Pipeline'!R11="tbd")+('MiT Strom Pipeline'!R11="In evaluation")>0,'MiT Strom Pipeline'!R11,"") | J144: =IF(('MiT Strom Pipeline'!R11="follow-up")+('MiT Strom Pipeline'!R11="Evaluation")+('MiT Strom Pipeline'!R11="tbd")+('MiT Strom Pipeline'!R11="In evaluation")>0,'MiT Strom Pipeline'!S11,"") | K144: =IF(('MiT Strom Pipeline'!R11="follow-up")+('MiT Strom Pipeline'!R11="Evaluation")+('MiT Strom Pipeline'!R11="tbd")+('MiT Strom Pipeline'!R11="In evaluation")>0,IF(LEN('MiT Strom Pipeline'!V11)>0,LEFT('MiT Strom Pipeline'!V11,55),""),"")
A145: =IF(('MiT Strom Pipeline'!R12="follow-up")+('MiT Strom Pipeline'!R12="Evaluation")+('MiT Strom Pipeline'!R12="tbd")+('MiT Strom Pipeline'!R12="In evaluation")>0,IF(ISNUMBER('MiT Strom Pipeline'!A12),'MiT Strom Pipeline'!A12,""),"") -> 8 | B145: =IF(('MiT Strom Pipeline'!R12="follow-up")+('MiT Strom Pipeline'!R12="Evaluation")+('MiT Strom Pipeline'!R12="tbd")+('MiT Strom Pipeline'!R12="In evaluation")>0,'MiT Strom Pipeline'!B12,"") -> Sade CGTH (Schweiz) | C145: =IF(('MiT Strom Pipeline'!R12="follow-up")+('MiT Strom Pipeline'!R12="Evaluation")+('MiT Strom Pipeline'!R12="tbd")+('MiT Strom Pipeline'!R12="In evaluation")>0,'MiT Strom Pipeline'!C12,"") -> GE | D145: =IF(('MiT Strom Pipeline'!R12="follow-up")+('MiT Strom Pipeline'!R12="Evaluation")+('MiT Strom Pipeline'!R12="tbd")+('MiT Strom Pipeline'!R12="In evaluation")>0,'MiT Strom Pipeline'!D12,"") -> Infrastruktur / Bau | E145: =IF(('MiT Strom Pipeline'!R12="follow-up")+('MiT Strom Pipeline'!R12="Evaluation")+('MiT Strom Pipeline'!R12="tbd")+('MiT Strom Pipeline'!R12="In evaluation")>0,'MiT Strom Pipeline'!E12,"") -> 750 kVA Generator | F145: =IF(('MiT Strom Pipeline'!R12="follow-up")+('MiT Strom Pipeline'!R12="Evaluation")+('MiT Strom Pipeline'!R12="tbd")+('MiT Strom Pipeline'!R12="In evaluation")>0,IF(ISNUMBER('MiT Strom Pipeline'!I12),'MiT Strom Pipeline'!I12,0),"") -> 38885 | G145: =IF(('MiT Strom Pipeline'!R12="follow-up")+('MiT Strom Pipeline'!R12="Evaluation")+('MiT Strom Pipeline'!R12="tbd")+('MiT Strom Pipeline'!R12="In evaluation")>0,IF(ISNUMBER('MiT Strom Pipeline'!Q12),'MiT Strom Pipeline'!Q12,0),"") -> 19442.5 | H145: =IF(('MiT Strom Pipeline'!R12="follow-up")+('MiT Strom Pipeline'!R12="Evaluation")+('MiT Strom Pipeline'!R12="tbd")+('MiT Strom Pipeline'!R12="In evaluation")>0,IF(ISNUMBER('MiT Strom Pipeline'!O12),'MiT Strom Pipeline'!O12,0),"") -> 7085 | I145: =IF(('MiT Strom Pipeline'!R12="follow-up")+('MiT Strom Pipeline'!R12="Evaluation")+('MiT Strom Pipeline'!R12="tbd")+('MiT Strom Pipeline'!R12="In evaluation")>0,'MiT Strom Pipeline'!R12,"") -> follow-up | J145: =IF(('MiT Strom Pipeline'!R12="follow-up")+('MiT Strom Pipeline'!R12="Evaluation")+('MiT Strom Pipeline'!R12="tbd")+('MiT Strom Pipeline'!R12="In evaluation")>0,'MiT Strom Pipeline'!S12,"") -> 50 | K145: =IF(('MiT Strom Pipeline'!R12="follow-up")+('MiT Strom Pipeline'!R12="Evaluation")+('MiT Strom Pipeline'!R12="tbd")+('MiT Strom Pipeline'!R12="In evaluation")>0,IF(LEN('MiT Strom Pipeline'!V12)>0,LEFT('MiT Strom Pipeline'!V12,55),""),"") -> Auftragsbestätigung anfordern – Entscheid steht bevor
A146: =IF(('MiT Strom Pipeline'!R13="follow-up")+('MiT Strom Pipeline'!R13="Evaluation")+('MiT Strom Pipeline'!R13="tbd")+('MiT Strom Pipeline'!R13="In evaluation")>0,IF(ISNUMBER('MiT Strom Pipeline'!A13),'MiT Strom Pipeline'!A13,""),"") -> 9 | B146: =IF(('MiT Strom Pipeline'!R13="follow-up")+('MiT Strom Pipeline'!R13="Evaluation")+('MiT Strom Pipeline'!R13="tbd")+('MiT Strom Pipeline'!R13="In evaluation")>0,'MiT Strom Pipeline'!B13,"") -> Badermetaux Sàrl (Schweiz) | C146: =IF(('MiT Strom Pipeline'!R13="follow-up")+('MiT Strom Pipeline'!R13="Evaluation")+('MiT Strom Pipeline'!R13="tbd")+('MiT Strom Pipeline'!R13="In evaluation")>0,'MiT Strom Pipeline'!C13,"") -> ZH | D146: =IF(('MiT Strom Pipeline'!R13="follow-up")+('MiT Strom Pipeline'!R13="Evaluation")+('MiT Strom Pipeline'!R13="tbd")+('MiT Strom Pipeline'!R13="In evaluation")>0,'MiT Strom Pipeline'!D13,"") -> Industrie / Metall | E146: =IF(('MiT Strom Pipeline'!R13="follow-up")+('MiT Strom Pipeline'!R13="Evaluation")+('MiT Strom Pipeline'!R13="tbd")+('MiT Strom Pipeline'!R13="In evaluation")>0,'MiT Strom Pipeline'!E13,"") -> 600 kVA Langzeitmiete | F146: =IF(('MiT Strom Pipeline'!R13="follow-up")+('MiT Strom Pipeline'!R13="Evaluation")+('MiT Strom Pipeline'!R13="tbd")+('MiT Strom Pipeline'!R13="In evaluation")>0,IF(ISNUMBER('MiT Strom Pipeline'!I13),'MiT Strom Pipeline'!I13,0),"") -> 500000 | G146: =IF(('MiT Strom Pipeline'!R13="follow-up")+('MiT Strom Pipeline'!R13="Evaluation")+('MiT Strom Pipeline'!R13="tbd")+('MiT Strom Pipeline'!R13="In evaluation")>0,IF(ISNUMBER('MiT Strom Pipeline'!Q13),'MiT Strom Pipeline'!Q13,0),"") -> 50000 | H146: =IF(('MiT Strom Pipeline'!R13="follow-up")+('MiT Strom Pipeline'!R13="Evaluation")+('MiT Strom Pipeline'!R13="tbd")+('MiT Strom Pipeline'!R13="In evaluation")>0,IF(ISNUMBER('MiT Strom Pipeline'!O13),'MiT Strom Pipeline'!O13,0),"") -> 130000 | I146: =IF(('MiT Strom Pipeline'!R13="follow-up")+('MiT Strom Pipeline'!R13="Evaluation")+('MiT Strom Pipeline'!R13="tbd")+('MiT Strom Pipeline'!R13="In evaluation")>0,'MiT Strom Pipeline'!R13,"") -> follow-up | J146: =IF(('MiT Strom Pipeline'!R13="follow-up")+('MiT Strom Pipeline'!R13="Evaluation")+('MiT Strom Pipeline'!R13="tbd")+('MiT Strom Pipeline'!R13="In evaluation")>0,'MiT Strom Pipeline'!S13,"") -> 10 | K146: =IF(('MiT Strom Pipeline'!R13="follow-up")+('MiT Strom Pipeline'!R13="Evaluation")+('MiT Strom Pipeline'!R13="tbd")+('MiT Strom Pipeline'!R13="In evaluation")>0,IF(LEN('MiT Strom Pipeline'!V13)>0,LEFT('MiT Strom Pipeline'!V13,55),""),"") -> PQ-Analyse + Langzeitkonzept vorlegen
A147: =IF(('MiT Strom Pipeline'!R14="follow-up")+('MiT Strom Pipeline'!R14="Evaluation")+('MiT Strom Pipeline'!R14="tbd")+('MiT Strom Pipeline'!R14="In evaluation")>0,IF(ISNUMBER('MiT Strom Pipeline'!A14),'MiT Strom Pipeline'!A14,""),"") -> 10 | B147: =IF(('MiT Strom Pipeline'!R14="follow-up")+('MiT Strom Pipeline'!R14="Evaluation")+('MiT Strom Pipeline'!R14="tbd")+('MiT Strom Pipeline'!R14="In evaluation")>0,'MiT Strom Pipeline'!B14,"") -> Murg Flums Energie | C147: =IF(('MiT Strom Pipeline'!R14="follow-up")+('MiT Strom Pipeline'!R14="Evaluation")+('MiT Strom Pipeline'!R14="tbd")+('MiT Strom Pipeline'!R14="In evaluation")>0,'MiT Strom Pipeline'!C14,"") -> SG | D147: =IF(('MiT Strom Pipeline'!R14="follow-up")+('MiT Strom Pipeline'!R14="Evaluation")+('MiT Strom Pipeline'!R14="tbd")+('MiT Strom Pipeline'!R14="In evaluation")>0,'MiT Strom Pipeline'!D14,"") -> EVU / Energie | E147: =IF(('MiT Strom Pipeline'!R14="follow-up")+('MiT Strom Pipeline'!R14="Evaluation")+('MiT Strom Pipeline'!R14="tbd")+('MiT Strom Pipeline'!R14="In evaluation")>0,'MiT Strom Pipeline'!E14,"") -> 250 kVA Generator | F147: =IF(('MiT Strom Pipeline'!R14="follow-up")+('MiT Strom Pipeline'!R14="Evaluation")+('MiT Strom Pipeline'!R14="tbd")+('MiT Strom Pipeline'!R14="In evaluation")>0,IF(ISNUMBER('MiT Strom Pipeline'!I14),'MiT Strom Pipeline'!I14,0),"") -> 96658.69 | G147: =IF(('MiT Strom Pipeline'!R14="follow-up")+('MiT Strom Pipeline'!R14="Evaluation")+('MiT Strom Pipeline'!R14="tbd")+('MiT Strom Pipeline'!R14="In evaluation")>0,IF(ISNUMBER('MiT Strom Pipeline'!Q14),'MiT Strom Pipeline'!Q14,0),"") -> 48329.345 | H147: =IF(('MiT Strom Pipeline'!R14="follow-up")+('MiT Strom Pipeline'!R14="Evaluation")+('MiT Strom Pipeline'!R14="tbd")+('MiT Strom Pipeline'!R14="In evaluation")>0,IF(ISNUMBER('MiT Strom Pipeline'!O14),'MiT Strom Pipeline'!O14,0),"") -> 0 | I147: =IF(('MiT Strom Pipeline'!R14="follow-up")+('MiT Strom Pipeline'!R14="Evaluation")+('MiT Strom Pipeline'!R14="tbd")+('MiT Strom Pipeline'!R14="In evaluation")>0,'MiT Strom Pipeline'!R14,"") -> follow-up | J147: =IF(('MiT Strom Pipeline'!R14="follow-up")+('MiT Strom Pipeline'!R14="Evaluation")+('MiT Strom Pipeline'!R14="tbd")+('MiT Strom Pipeline'!R14="In evaluation")>0,'MiT Strom Pipeline'!S14,"") -> 0.5 | K147: =IF(('MiT Strom Pipeline'!R14="follow-up")+('MiT Strom Pipeline'!R14="Evaluation")+('MiT Strom Pipeline'!R14="tbd")+('MiT Strom Pipeline'!R14="In evaluation")>0,IF(LEN('MiT Strom Pipeline'!V14)>0,LEFT('MiT Strom Pipeline'!V14,55),""),"") -> Bedarfsanalyse, NEA-Konzept vorschlagen, Termin vor Ort
A148: =IF(('MiT Strom Pipeline'!R15="follow-up")+('MiT Strom Pipeline'!R15="Evaluation")+('MiT Strom Pipeline'!R15="tbd")+('MiT Strom Pipeline'!R15="In evaluation")>0,IF(ISNUMBER('MiT Strom Pipeline'!A15),'MiT Strom Pipeline'!A15,""),"") -> 11 | B148: =IF(('MiT Strom Pipeline'!R15="follow-up")+('MiT Strom Pipeline'!R15="Evaluation")+('MiT Strom Pipeline'!R15="tbd")+('MiT Strom Pipeline'!R15="In evaluation")>0,'MiT Strom Pipeline'!B15,"") -> Burkhalter Technics AG | C148: =IF(('MiT Strom Pipeline'!R15="follow-up")+('MiT Strom Pipeline'!R15="Evaluation")+('MiT Strom Pipeline'!R15="tbd")+('MiT Strom Pipeline'!R15="In evaluation")>0,'MiT Strom Pipeline'!C15,"") -> ZH | D148: =IF(('MiT Strom Pipeline'!R15="follow-up")+('MiT Strom Pipeline'!R15="Evaluation")+('MiT Strom Pipeline'!R15="tbd")+('MiT Strom Pipeline'!R15="In evaluation")>0,'MiT Strom Pipeline'!D15,"") -> Elektroinstallation | E148: =IF(('MiT Strom Pipeline'!R15="follow-up")+('MiT Strom Pipeline'!R15="Evaluation")+('MiT Strom Pipeline'!R15="tbd")+('MiT Strom Pipeline'!R15="In evaluation")>0,'MiT Strom Pipeline'!E15,"") -> 150 kVA Generator | F148: =IF(('MiT Strom Pipeline'!R15="follow-up")+('MiT Strom Pipeline'!R15="Evaluation")+('MiT Strom Pipeline'!R15="tbd")+('MiT Strom Pipeline'!R15="In evaluation")>0,IF(ISNUMBER('MiT Strom Pipeline'!I15),'MiT Strom Pipeline'!I15,0),"") -> 0 | G148: =IF(('MiT Strom Pipeline'!R15="follow-up")+('MiT Strom Pipeline'!R15="Evaluation")+('MiT Strom Pipeline'!R15="tbd")+('MiT Strom Pipeline'!R15="In evaluation")>0,IF(ISNUMBER('MiT Strom Pipeline'!Q15),'MiT Strom Pipeline'!Q15,0),"") -> 0 | H148: =IF(('MiT Strom Pipeline'!R15="follow-up")+('MiT Strom Pipeline'!R15="Evaluation")+('MiT Strom Pipeline'!R15="tbd")+('MiT Strom Pipeline'!R15="In evaluation")>0,IF(ISNUMBER('MiT Strom Pipeline'!O15),'MiT Strom Pipeline'!O15,0),"") -> 0 | I148: =IF(('MiT Strom Pipeline'!R15="follow-up")+('MiT Strom Pipeline'!R15="Evaluation")+('MiT Strom Pipeline'!R15="tbd")+('MiT Strom Pipeline'!R15="In evaluation")>0,'MiT Strom Pipeline'!R15,"") -> Evaluation | J148: =IF(('MiT Strom Pipeline'!R15="follow-up")+('MiT Strom Pipeline'!R15="Evaluation")+('MiT Strom Pipeline'!R15="tbd")+('MiT Strom Pipeline'!R15="In evaluation")>0,'MiT Strom Pipeline'!S15,"") -> 40% | K148: =IF(('MiT Strom Pipeline'!R15="follow-up")+('MiT Strom Pipeline'!R15="Evaluation")+('MiT Strom Pipeline'!R15="tbd")+('MiT Strom Pipeline'!R15="In evaluation")>0,IF(LEN('MiT Strom Pipeline'!V15)>0,LEFT('MiT Strom Pipeline'!V15,55),""),"") -> Angebot finalisieren – CBM-Beziehung nutzen, Abrufberei
A149: =IF(('MiT Strom Pipeline'!R16="follow-up")+('MiT Strom Pipeline'!R16="Evaluation")+('MiT Strom Pipeline'!R16="tbd")+('MiT Strom Pipeline'!R16="In evaluation")>0,IF(ISNUMBER('MiT Strom Pipeline'!A16),'MiT Strom Pipeline'!A16,""),"") -> 12 | B149: =IF(('MiT Strom Pipeline'!R16="follow-up")+('MiT Strom Pipeline'!R16="Evaluation")+('MiT Strom Pipeline'!R16="tbd")+('MiT Strom Pipeline'!R16="In evaluation")>0,'MiT Strom Pipeline'!B16,"") -> Show-Concept.ch AG | C149: =IF(('MiT Strom Pipeline'!R16="follow-up")+('MiT Strom Pipeline'!R16="Evaluation")+('MiT Strom Pipeline'!R16="tbd")+('MiT Strom Pipeline'!R16="In evaluation")>0,'MiT Strom Pipeline'!C16,"") -> ZH | D149: =IF(('MiT Strom Pipeline'!R16="follow-up")+('MiT Strom Pipeline'!R16="Evaluation")+('MiT Strom Pipeline'!R16="tbd")+('MiT Strom Pipeline'!R16="In evaluation")>0,'MiT Strom Pipeline'!D16,"") -> Events / Medien | E149: =IF(('MiT Strom Pipeline'!R16="follow-up")+('MiT Strom Pipeline'!R16="Evaluation")+('MiT Strom Pipeline'!R16="tbd")+('MiT Strom Pipeline'!R16="In evaluation")>0,'MiT Strom Pipeline'!E16,"") -> 200 kW Lastbank | F149: =IF(('MiT Strom Pipeline'!R16="follow-up")+('MiT Strom Pipeline'!R16="Evaluation")+('MiT Strom Pipeline'!R16="tbd")+('MiT Strom Pipeline'!R16="In evaluation")>0,IF(ISNUMBER('MiT Strom Pipeline'!I16),'MiT Strom Pipeline'!I16,0),"") -> 0 | G149: =IF(('MiT Strom Pipeline'!R16="follow-up")+('MiT Strom Pipeline'!R16="Evaluation")+('MiT Strom Pipeline'!R16="tbd")+('MiT Strom Pipeline'!R16="In evaluation")>0,IF(ISNUMBER('MiT Strom Pipeline'!Q16),'MiT Strom Pipeline'!Q16,0),"") -> 0 | H149: =IF(('MiT Strom Pipeline'!R16="follow-up")+('MiT Strom Pipeline'!R16="Evaluation")+('MiT Strom Pipeline'!R16="tbd")+('MiT Strom Pipeline'!R16="In evaluation")>0,IF(ISNUMBER('MiT Strom Pipeline'!O16),'MiT Strom Pipeline'!O16,0),"") -> 0 | I149: =IF(('MiT Strom Pipeline'!R16="follow-up")+('MiT Strom Pipeline'!R16="Evaluation")+('MiT Strom Pipeline'!R16="tbd")+('MiT Strom Pipeline'!R16="In evaluation")>0,'MiT Strom Pipeline'!R16,"") -> Evaluation | J149: =IF(('MiT Strom Pipeline'!R16="follow-up")+('MiT Strom Pipeline'!R16="Evaluation")+('MiT Strom Pipeline'!R16="tbd")+('MiT Strom Pipeline'!R16="In evaluation")>0,'MiT Strom Pipeline'!S16,"") -> 35% | K149: =IF(('MiT Strom Pipeline'!R16="follow-up")+('MiT Strom Pipeline'!R16="Evaluation")+('MiT Strom Pipeline'!R16="tbd")+('MiT Strom Pipeline'!R16="In evaluation")>0,IF(LEN('MiT Strom Pipeline'!V16)>0,LEFT('MiT Strom Pipeline'!V16,55),""),"") -> Use-Case klären – Lastbank oder Generator?
A150: =IF(('MiT Strom Pipeline'!R17="follow-up")+('MiT Strom Pipeline'!R17="Evaluation")+('MiT Strom Pipeline'!R17="tbd")+('MiT Strom Pipeline'!R17="In evaluation")>0,IF(ISNUMBER('MiT Strom Pipeline'!A17),'MiT Strom Pipeline'!A17,""),"") | B150: =IF(('MiT Strom Pipeline'!R17="follow-up")+('MiT Strom Pipeline'!R17="Evaluation")+('MiT Strom Pipeline'!R17="tbd")+('MiT Strom Pipeline'!R17="In evaluation")>0,'MiT Strom Pipeline'!B17,"") | C150: =IF(('MiT Strom Pipeline'!R17="follow-up")+('MiT Strom Pipeline'!R17="Evaluation")+('MiT Strom Pipeline'!R17="tbd")+('MiT Strom Pipeline'!R17="In evaluation")>0,'MiT Strom Pipeline'!C17,"") | D150: =IF(('MiT Strom Pipeline'!R17="follow-up")+('MiT Strom Pipeline'!R17="Evaluation")+('MiT Strom Pipeline'!R17="tbd")+('MiT Strom Pipeline'!R17="In evaluation")>0,'MiT Strom Pipeline'!D17,"") | E150: =IF(('MiT Strom Pipeline'!R17="follow-up")+('MiT Strom Pipeline'!R17="Evaluation")+('MiT Strom Pipeline'!R17="tbd")+('MiT Strom Pipeline'!R17="In evaluation")>0,'MiT Strom Pipeline'!E17,"") | F150: =IF(('MiT Strom Pipeline'!R17="follow-up")+('MiT Strom Pipeline'!R17="Evaluation")+('MiT Strom Pipeline'!R17="tbd")+('MiT Strom Pipeline'!R17="In evaluation")>0,IF(ISNUMBER('MiT Strom Pipeline'!I17),'MiT Strom Pipeline'!I17,0),"") | G150: =IF(('MiT Strom Pipeline'!R17="follow-up")+('MiT Strom Pipeline'!R17="Evaluation")+('MiT Strom Pipeline'!R17="tbd")+('MiT Strom Pipeline'!R17="In evaluation")>0,IF(ISNUMBER('MiT Strom Pipeline'!Q17),'MiT Strom Pipeline'!Q17,0),"") | H150: =IF(('MiT Strom Pipeline'!R17="follow-up")+('MiT Strom Pipeline'!R17="Evaluation")+('MiT Strom Pipeline'!R17="tbd")+('MiT Strom Pipeline'!R17="In evaluation")>0,IF(ISNUMBER('MiT Strom Pipeline'!O17),'MiT Strom Pipeline'!O17,0),"") | I150: =IF(('MiT Strom Pipeline'!R17="follow-up")+('MiT Strom Pipeline'!R17="Evaluation")+('MiT Strom Pipeline'!R17="tbd")+('MiT Strom Pipeline'!R17="In evaluation")>0,'MiT Strom Pipeline'!R17,"") | J150: =IF(('MiT Strom Pipeline'!R17="follow-up")+('MiT Strom Pipeline'!R17="Evaluation")+('MiT Strom Pipeline'!R17="tbd")+('MiT Strom Pipeline'!R17="In evaluation")>0,'MiT Strom Pipeline'!S17,"") | K150: =IF(('MiT Strom Pipeline'!R17="follow-up")+('MiT Strom Pipeline'!R17="Evaluation")+('MiT Strom Pipeline'!R17="tbd")+('MiT Strom Pipeline'!R17="In evaluation")>0,IF(LEN('MiT Strom Pipeline'!V17)>0,LEFT('MiT Strom Pipeline'!V17,55),""),"")
... A198: =IF(('MiT Strom Pipeline'!R65="follow-up")+('MiT Strom Pipeline'!R65="Evaluation")+('MiT Strom Pipeline'!R65="tbd")+('MiT Strom Pipeline'!R65="In evaluation")>0,IF(ISNUMBER('MiT Strom Pipeline'!A65),'MiT Strom Pipeline'!A65,""),"") | B198: =IF(('MiT Strom Pipeline'!R65="follow-up")+('MiT Strom Pipeline'!R65="Evaluation")+('MiT Strom Pipeline'!R65="tbd")+('MiT Strom Pipeline'!R65="In evaluation")>0,'MiT Strom Pipeline'!B65,"") | C198: =IF(('MiT Strom Pipeline'!R65="follow-up")+('MiT Strom Pipeline'!R65="Evaluation")+('MiT Strom Pipeline'!R65="tbd")+('MiT Strom Pipeline'!R65="In evaluation")>0,'MiT Strom Pipeline'!C65,"") | D198: =IF(('MiT Strom Pipeline'!R65="follow-up")+('MiT Strom Pipeline'!R65="Evaluation")+('MiT Strom Pipeline'!R65="tbd")+('MiT Strom Pipeline'!R65="In evaluation")>0,'MiT Strom Pipeline'!D65,"") | E198: =IF(('MiT Strom Pipeline'!R65="follow-up")+('MiT Strom Pipeline'!R65="Evaluation")+('MiT Strom Pipeline'!R65="tbd")+('MiT Strom Pipeline'!R65="In evaluation")>0,'MiT Strom Pipeline'!E65,"") | F198: =IF(('MiT Strom Pipeline'!R65="follow-up")+('MiT Strom Pipeline'!R65="Evaluation")+('MiT Strom Pipeline'!R65="tbd")+('MiT Strom Pipeline'!R65="In evaluation")>0,IF(ISNUMBER('MiT Strom Pipeline'!I65),'MiT Strom Pipeline'!I65,0),"") | G198: =IF(('MiT Strom Pipeline'!R65="follow-up")+('MiT Strom Pipeline'!R65="Evaluation")+('MiT Strom Pipeline'!R65="tbd")+('MiT Strom Pipeline'!R65="In evaluation")>0,IF(ISNUMBER('MiT Strom Pipeline'!Q65),'MiT Strom Pipeline'!Q65,0),"") | H198: =IF(('MiT Strom Pipeline'!R65="follow-up")+('MiT Strom Pipeline'!R65="Evaluation")+('MiT Strom Pipeline'!R65="tbd")+('MiT Strom Pipeline'!R65="In evaluation")>0,IF(ISNUMBER('MiT Strom Pipeline'!O65),'MiT Strom Pipeline'!O65,0),"") | I198: =IF(('MiT Strom Pipeline'!R65="follow-up")+('MiT Strom Pipeline'!R65="Evaluation")+('MiT Strom Pipeline'!R65="tbd")+('MiT Strom Pipeline'!R65="In evaluation")>0,'MiT Strom Pipeline'!R65,"") | J198: =IF(('MiT Strom Pipeline'!R65="follow-up")+('MiT Strom Pipeline'!R65="Evaluation")+('MiT Strom Pipeline'!R65="tbd")+('MiT Strom Pipeline'!R65="In evaluation")>0,'MiT Strom Pipeline'!S65,"") | K198: =IF(('MiT Strom Pipeline'!R65="follow-up")+('MiT Strom Pipeline'!R65="Evaluation")+('MiT Strom Pipeline'!R65="tbd")+('MiT Strom Pipeline'!R65="In evaluation")>0,IF(LEN('MiT Strom Pipeline'!V65)>0,LEFT('MiT Strom Pipeline'!V65,55),""),"")
A199: =IF(('MiT Strom Pipeline'!R66="follow-up")+('MiT Strom Pipeline'!R66="Evaluation")+('MiT Strom Pipeline'!R66="tbd")+('MiT Strom Pipeline'!R66="In evaluation")>0,IF(ISNUMBER('MiT Strom Pipeline'!A66),'MiT Strom Pipeline'!A66,""),"") | B199: =IF(('MiT Strom Pipeline'!R66="follow-up")+('MiT Strom Pipeline'!R66="Evaluation")+('MiT Strom Pipeline'!R66="tbd")+('MiT Strom Pipeline'!R66="In evaluation")>0,'MiT Strom Pipeline'!B66,"") | F199: =IF(('MiT Strom Pipeline'!R66="follow-up")+('MiT Strom Pipeline'!R66="Evaluation")+('MiT Strom Pipeline'!R66="tbd")+('MiT Strom Pipeline'!R66="In evaluation")>0,IF(ISNUMBER('MiT Strom Pipeline'!I66),'MiT Strom Pipeline'!I66,0),"") | G199: =IF(('MiT Strom Pipeline'!R66="follow-up")+('MiT Strom Pipeline'!R66="Evaluation")+('MiT Strom Pipeline'!R66="tbd")+('MiT Strom Pipeline'!R66="In evaluation")>0,IF(ISNUMBER('MiT Strom Pipeline'!Q66),'MiT Strom Pipeline'!Q66,0),"") | H199: =IF(('MiT Strom Pipeline'!R66="follow-up")+('MiT Strom Pipeline'!R66="Evaluation")+('MiT Strom Pipeline'!R66="tbd")+('MiT Strom Pipeline'!R66="In evaluation")>0,IF(ISNUMBER('MiT Strom Pipeline'!O66),'MiT Strom Pipeline'!O66,0),"") | I199: =IF(('MiT Strom Pipeline'!R66="follow-up")+('MiT Strom Pipeline'!R66="Evaluation")+('MiT Strom Pipeline'!R66="tbd")+('MiT Strom Pipeline'!R66="In evaluation")>0,'MiT Strom Pipeline'!R66,"") | J199: =IF(('MiT Strom Pipeline'!R66="follow-up")+('MiT Strom Pipeline'!R66="Evaluation")+('MiT Strom Pipeline'!R66="tbd")+('MiT Strom Pipeline'!R66="In evaluation")>0,'MiT Strom Pipeline'!S66,"") | K199: =IF(('MiT Strom Pipeline'!R66="follow-up")+('MiT Strom Pipeline'!R66="Evaluation")+('MiT Strom Pipeline'!R66="tbd")+('MiT Strom Pipeline'!R66="In evaluation")>0,IF(LEN('MiT Strom Pipeline'!V66)>0,LEFT('MiT Strom Pipeline'!V66,55),""),"")
A200: =IF(('MiT Strom Pipeline'!R67="follow-up")+('MiT Strom Pipeline'!R67="Evaluation")+('MiT Strom Pipeline'!R67="tbd")+('MiT Strom Pipeline'!R67="In evaluation")>0,IF(ISNUMBER('MiT Strom Pipeline'!A67),'MiT Strom Pipeline'!A67,""),"") | B200: =IF(('MiT Strom Pipeline'!R67="follow-up")+('MiT Strom Pipeline'!R67="Evaluation")+('MiT Strom Pipeline'!R67="tbd")+('MiT Strom Pipeline'!R67="In evaluation")>0,'MiT Strom Pipeline'!B67,"") | C200: =IF(('MiT Strom Pipeline'!R67="follow-up")+('MiT Strom Pipeline'!R67="Evaluation")+('MiT Strom Pipeline'!R67="tbd")+('MiT Strom Pipeline'!R67="In evaluation")>0,'MiT Strom Pipeline'!C67,"") | D200: =IF(('MiT Strom Pipeline'!R67="follow-up")+('MiT Strom Pipeline'!R67="Evaluation")+('MiT Strom Pipeline'!R67="tbd")+('MiT Strom Pipeline'!R67="In evaluation")>0,'MiT Strom Pipeline'!D67,"") | E200: =IF(('MiT Strom Pipeline'!R67="follow-up")+('MiT Strom Pipeline'!R67="Evaluation")+('MiT Strom Pipeline'!R67="tbd")+('MiT Strom Pipeline'!R67="In evaluation")>0,'MiT Strom Pipeline'!E67,"") | F200: =IF(('MiT Strom Pipeline'!R67="follow-up")+('MiT Strom Pipeline'!R67="Evaluation")+('MiT Strom Pipeline'!R67="tbd")+('MiT Strom Pipeline'!R67="In evaluation")>0,IF(ISNUMBER('MiT Strom Pipeline'!I67),'MiT Strom Pipeline'!I67,0),"") | G200: =IF(('MiT Strom Pipeline'!R67="follow-up")+('MiT Strom Pipeline'!R67="Evaluation")+('MiT Strom Pipeline'!R67="tbd")+('MiT Strom Pipeline'!R67="In evaluation")>0,IF(ISNUMBER('MiT Strom Pipeline'!Q67),'MiT Strom Pipeline'!Q67,0),"") | H200: =IF(('MiT Strom Pipeline'!R67="follow-up")+('MiT Strom Pipeline'!R67="Evaluation")+('MiT Strom Pipeline'!R67="tbd")+('MiT Strom Pipeline'!R67="In evaluation")>0,IF(ISNUMBER('MiT Strom Pipeline'!O67),'MiT Strom Pipeline'!O67,0),"") | I200: =IF(('MiT Strom Pipeline'!R67="follow-up")+('MiT Strom Pipeline'!R67="Evaluation")+('MiT Strom Pipeline'!R67="tbd")+('MiT Strom Pipeline'!R67="In evaluation")>0,'MiT Strom Pipeline'!R67,"") | J200: =IF(('MiT Strom Pipeline'!R67="follow-up")+('MiT Strom Pipeline'!R67="Evaluation")+('MiT Strom Pipeline'!R67="tbd")+('MiT Strom Pipeline'!R67="In evaluation")>0,'MiT Strom Pipeline'!S67,"") | K200: =IF(('MiT Strom Pipeline'!R67="follow-up")+('MiT Strom Pipeline'!R67="Evaluation")+('MiT Strom Pipeline'!R67="tbd")+('MiT Strom Pipeline'!R67="In evaluation")>0,IF(LEN('MiT Strom Pipeline'!V67)>0,LEFT('MiT Strom Pipeline'!V67,55),""),"")
A201: 📊 GESAMTTOTAL — Aktive Pipeline | F201: =SUMIFS('MiT Strom Pipeline'!I$6:I$904,'MiT Strom Pipeline'!R$6:R$904,"WON")+SUMIFS('MiT Strom Pipeline'!I$6:I$904,'MiT Strom Pipeline'!R$6:R$904,"offered")+SUMIFS('MiT Strom Pipeline'!I$6:I$904,'MiT Strom Pipeline'!R$6:R$904,"to be offered")+SUMIFS('MiT Strom Pipeline'!I$6:I$904,'MiT Strom Pipeline'!R$6:R$904,"on hold")+SUMIFS('MiT Strom Pipeline'!I$6:I$904,'MiT Strom Pipeline'!R$6:R$904,"follow-up")+SUMIFS('MiT Strom Pipeline'!I$6:I$904,'MiT Strom Pipeline'!R$6:R$904,"Evaluation")+SUMIFS('MiT Strom Pipeline'!I$6:I$904,'MiT Strom Pipeline'!R$6:R$904,"tbd")+SUMIFS('MiT Strom Pipeline'!I$6:I$904,'MiT Strom Pipeline'!R$6:R$904,"In evaluation") -> 4872116.3
A202: → WON | F202: =SUMIFS('MiT Strom Pipeline'!I$6:I$904,'MiT Strom Pipeline'!R$6:R$904,"WON") -> 333100
A203: → Offerte | F203: =SUMIFS('MiT Strom Pipeline'!I$6:I$904,'MiT Strom Pipeline'!R$6:R$904,"offered")+SUMIFS('MiT Strom Pipeline'!I$6:I$904,'MiT Strom Pipeline'!R$6:R$904,"to be offered")+SUMIFS('MiT Strom Pipeline'!I$6:I$904,'MiT Strom Pipeline'!R$6:R$904,"on hold") -> 3866028.6
A204: → Opportunität | F204: =SUMIFS('MiT Strom Pipeline'!I$6:I$904,'MiT Strom Pipeline'!R$6:R$904,"follow-up")+SUMIFS('MiT Strom Pipeline'!I$6:I$904,'MiT Strom Pipeline'!R$6:R$904,"Evaluation")+SUMIFS('MiT Strom Pipeline'!I$6:I$904,'MiT Strom Pipeline'!R$6:R$904,"tbd")+SUMIFS('MiT Strom Pipeline'!I$6:I$904,'MiT Strom Pipeline'!R$6:R$904,"In evaluation") -> 672987.69
A206: Stand: Mai 2026 | Burak Ücöz | Mobil in Time AG – An Aggreko Company | VERTRAULICH

Sheet Dashboard
A1: ⚡ MiT Strom Schweiz | Sales Dashboard | Mai 2026
A2: Mobil in Time AG · An Aggreko Company · Burak Ücöz · Neue Einträge in «MiT Strom Pipeline» (bis Zeile 100) erscheinen automatisch.
A5: ✅ WON | D5: 📄 OFFERTE | G5: 🎯 OPP. | I5: 📊 GESAMT
A6: =SUMIFS('MiT Strom Pipeline'!I$6:I$904,'MiT Strom Pipeline'!R$6:R$904,"WON") -> 333100 | D6: =SUMIFS('MiT Strom Pipeline'!I$6:I$904,'MiT Strom Pipeline'!R$6:R$904,"offered")+SUMIFS('MiT Strom Pipeline'!I$6:I$904,'MiT Strom Pipeline'!R$6:R$904,"to be offered")+SUMIFS('MiT Strom Pipeline'!I$6:I$904,'MiT Strom Pipeline'!R$6:R$904,"on hold") -> 3866028.6 | G6: =SUMIFS('MiT Strom Pipeline'!I$6:I$904,'MiT Strom Pipeline'!R$6:R$904,"follow-up")+SUMIFS('MiT Strom Pipeline'!I$6:I$904,'MiT Strom Pipeline'!R$6:R$904,"Evaluation")+SUMIFS('MiT Strom Pipeline'!I$6:I$904,'MiT Strom Pipeline'!R$6:R$904,"tbd")+SUMIFS('MiT Strom Pipeline'!I$6:I$904,'MiT Strom Pipeline'!R$6:R$904,"In evaluation") -> 672987.69 | I6: =SUMIFS('MiT Strom Pipeline'!I$6:I$904,'MiT Strom Pipeline'!R$6:R$904,"WON")+SUMIFS('MiT Strom Pipeline'!I$6:I$904,'MiT Strom Pipeline'!R$6:R$904,"offered")+SUMIFS('MiT Strom Pipeline'!I$6:I$904,'MiT Strom Pipeline'!R$6:R$904,"to be offered")+SUMIFS('MiT Strom Pipeline'!I$6:I$904,'MiT Strom Pipeline'!R$6:R$904,"on hold")+SUMIFS('MiT Strom Pipeline'!I$6:I$904,'MiT Strom Pipeline'!R$6:R$904,"follow-up")+SUMIFS('MiT Strom Pipeline'!I$6:I$904,'MiT Strom Pipeline'!R$6:R$904,"Evaluation")+SUMIFS('MiT Strom Pipeline'!I$6:I$904,'MiT Strom Pipeline'!R$6:R$904,"tbd")+SUMIFS('MiT Strom Pipeline'!I$6:I$904,'MiT Strom Pipeline'!R$6:R$904,"In evaluation") -> 4872116.3
A7: =COUNTIF('MiT Strom Pipeline'!R$6:R$904,"WON") -> 4 | D7: =COUNTIF('MiT Strom Pipeline'!R$6:R$904,"offered")+COUNTIF('MiT Strom Pipeline'!R$6:R$904,"to be offered")+COUNTIF('MiT Strom Pipeline'!R$6:R$904,"on hold") -> 12 | G7: =COUNTIF('MiT Strom Pipeline'!R$6:R$904,"follow-up")+COUNTIF('MiT Strom Pipeline'!R$6:R$904,"Evaluation")+COUNTIF('MiT Strom Pipeline'!R$6:R$904,"tbd")+COUNTIF('MiT Strom Pipeline'!R$6:R$904,"In evaluation") -> 16 | I7: =COUNTIF('MiT Strom Pipeline'!R$6:R$904,"WON")+COUNTIF('MiT Strom Pipeline'!R$6:R$904,"offered")+COUNTIF('MiT Strom Pipeline'!R$6:R$904,"to be offered")+COUNTIF('MiT Strom Pipeline'!R$6:R$904,"on hold")+COUNTIF('MiT Strom Pipeline'!R$6:R$904,"follow-up")+COUNTIF('MiT Strom Pipeline'!R$6:R$904,"Evaluation")+COUNTIF('MiT Strom Pipeline'!R$6:R$904,"tbd")+COUNTIF('MiT Strom Pipeline'!R$6:R$904,"In evaluation") -> 32
A9: ✅ 1. AUFTRAGSEINGANG (WON) — Gewonnene Aufträge
A10: # | B10: Kunde / Unternehmen | C10: Kt. | D10: Segment | E10: Leistung / Fleet | F10: Volumen CHF | G10: Gew.Wert CHF | H10: Status | I10: Wahr.% | J10: Nächster Schritt
A11: =IF('MiT Strom Pipeline'!R6="WON",IF(ISNUMBER('MiT Strom Pipeline'!A6),'MiT Strom Pipeline'!A6,""),"") -> 1 | B11: =IF('MiT Strom Pipeline'!R6="WON",'MiT Strom Pipeline'!B6,"") -> Ice Hockey Championship | C11: =IF('MiT Strom Pipeline'!R6="WON",'MiT Strom Pipeline'!C6,"") -> ZH | D11: =IF('MiT Strom Pipeline'!R6="WON",'MiT Strom Pipeline'!D6,"") -> Events & Sport | E11: =IF('MiT Strom Pipeline'!R6="WON",'MiT Strom Pipeline'!E6,"") -> 2×600+2×200 kVA | F11: =IF('MiT Strom Pipeline'!R6="WON",IF(ISNUMBER('MiT Strom Pipeline'!I6),'MiT Strom Pipeline'!I6,0),"") -> 310000 | G11: =IF('MiT Strom Pipeline'!R6="WON",IF(ISNUMBER('MiT Strom Pipeline'!Q6),'MiT Strom Pipeline'!Q6,0),"") -> 3100 | H11: =IF('MiT Strom Pipeline'!R6="WON",'MiT Strom Pipeline'!R6,"") -> WON | I11: =IF('MiT Strom Pipeline'!R6="WON",'MiT Strom Pipeline'!S6,"") -> 100% | J11: =IF('MiT Strom Pipeline'!R6="WON",IF(LEN('MiT Strom Pipeline'!V6)>0,LEFT('MiT Strom Pipeline'!V6,55),""),"") -> ✅ Einsatzplanung läuft – Logistik finalisieren
A12: =IF('MiT Strom Pipeline'!R7="WON",IF(ISNUMBER('MiT Strom Pipeline'!A7),'MiT Strom Pipeline'!A7,""),"") -> 2 | B12: =IF('MiT Strom Pipeline'!R7="WON",'MiT Strom Pipeline'!B7,"") -> Oerlikon Metco Wohlen | C12: =IF('MiT Strom Pipeline'!R7="WON",'MiT Strom Pipeline'!C7,"") -> AG | D12: =IF('MiT Strom Pipeline'!R7="WON",'MiT Strom Pipeline'!D7,"") -> Industrie / Oberfläche | E12: =IF('MiT Strom Pipeline'!R7="WON",'MiT Strom Pipeline'!E7,"") -> 240 kVA Generator | F12: =IF('MiT Strom Pipeline'!R7="WON",IF(ISNUMBER('MiT Strom Pipeline'!I7),'MiT Strom Pipeline'!I7,0),"") -> 13100 | G12: =IF('MiT Strom Pipeline'!R7="WON",IF(ISNUMBER('MiT Strom Pipeline'!Q7),'MiT Strom Pipeline'!Q7,0),"") -> 131 | H12: =IF('MiT Strom Pipeline'!R7="WON",'MiT Strom Pipeline'!R7,"") -> WON | I12: =IF('MiT Strom Pipeline'!R7="WON",'MiT Strom Pipeline'!S7,"") -> 100% | J12: =IF('MiT Strom Pipeline'!R7="WON",IF(LEN('MiT Strom Pipeline'!V7)>0,LEFT('MiT Strom Pipeline'!V7,55),""),"") -> ✅ Abgeschlossen – Invoice prüfen, Referenz sichern
A13: =IF('MiT Strom Pipeline'!R8="WON",IF(ISNUMBER('MiT Strom Pipeline'!A8),'MiT Strom Pipeline'!A8,""),"") -> 3 | B13: =IF('MiT Strom Pipeline'!R8="WON",'MiT Strom Pipeline'!B8,"") -> Siemens | C13: =IF('MiT Strom Pipeline'!R8="WON",'MiT Strom Pipeline'!C8,"") -> ZH | D13: =IF('MiT Strom Pipeline'!R8="WON",'MiT Strom Pipeline'!D8,"") -> Industrie / Elektro | E13: =IF('MiT Strom Pipeline'!R8="WON",'MiT Strom Pipeline'!E8,"") -> 600 kVA Generator | F13: =IF('MiT Strom Pipeline'!R8="WON",IF(ISNUMBER('MiT Strom Pipeline'!I8),'MiT Strom Pipeline'!I8,0),"") -> 10000 | G13: =IF('MiT Strom Pipeline'!R8="WON",IF(ISNUMBER('MiT Strom Pipeline'!Q8),'MiT Strom Pipeline'!Q8,0),"") -> 100 | H13: =IF('MiT Strom Pipeline'!R8="WON",'MiT Strom Pipeline'!R8,"") -> WON | I13: =IF('MiT Strom Pipeline'!R8="WON",'MiT Strom Pipeline'!S8,"") -> 100% | J13: =IF('MiT Strom Pipeline'!R8="WON",IF(LEN('MiT Strom Pipeline'!V8)>0,LEFT('MiT Strom Pipeline'!V8,55),""),"") -> ✅ Referenzschreiben anfordern
A14: =IF('MiT Strom Pipeline'!R9="WON",IF(ISNUMBER('MiT Strom Pipeline'!A9),'MiT Strom Pipeline'!A9,""),"") | B14: =IF('MiT Strom Pipeline'!R9="WON",'MiT Strom Pipeline'!B9,"") | C14: =IF('MiT Strom Pipeline'!R9="WON",'MiT Strom Pipeline'!C9,"") | D14: =IF('MiT Strom Pipeline'!R9="WON",'MiT Strom Pipeline'!D9,"") | E14: =IF('MiT Strom Pipeline'!R9="WON",'MiT Strom Pipeline'!E9,"") | F14: =IF('MiT Strom Pipeline'!R9="WON",IF(ISNUMBER('MiT Strom Pipeline'!I9),'MiT Strom Pipeline'!I9,0),"") | G14: =IF('MiT Strom Pipeline'!R9="WON",IF(ISNUMBER('MiT Strom Pipeline'!Q9),'MiT Strom Pipeline'!Q9,0),"") | H14: =IF('MiT Strom Pipeline'!R9="WON",'MiT Strom Pipeline'!R9,"") | I14: =IF('MiT Strom Pipeline'!R9="WON",'MiT Strom Pipeline'!S9,"") | J14: =IF('MiT Strom Pipeline'!R9="WON",IF(LEN('MiT Strom Pipeline'!V9)>0,LEFT('MiT Strom Pipeline'!V9,55),""),"")
A15: =IF('MiT Strom Pipeline'!R10="WON",IF(ISNUMBER('MiT Strom Pipeline'!A10),'MiT Strom Pipeline'!A10,""),"") | B15: =IF('MiT Strom Pipeline'!R10="WON",'MiT Strom Pipeline'!B10,"") | C15: =IF('MiT Strom Pipeline'!R10="WON",'MiT Strom Pipeline'!C10,"") | D15: =IF('MiT Strom Pipeline'!R10="WON",'MiT Strom Pipeline'!D10,"") | E15: =IF('MiT Strom Pipeline'!R10="WON",'MiT Strom Pipeline'!E10,"") | F15: =IF('MiT Strom Pipeline'!R10="WON",IF(ISNUMBER('MiT Strom Pipeline'!I10),'MiT Strom Pipeline'!I10,0),"") | G15: =IF('MiT Strom Pipeline'!R10="WON",IF(ISNUMBER('MiT Strom Pipeline'!Q10),'MiT Strom Pipeline'!Q10,0),"") | H15: =IF('MiT Strom Pipeline'!R10="WON",'MiT Strom Pipeline'!R10,"") | I15: =IF('MiT Strom Pipeline'!R10="WON",'MiT Strom Pipeline'!S10,"") | J15: =IF('MiT Strom Pipeline'!R10="WON",IF(LEN('MiT Strom Pipeline'!V10)>0,LEFT('MiT Strom Pipeline'!V10,55),""),"")
A16: =IF('MiT Strom Pipeline'!R11="WON",IF(ISNUMBER('MiT Strom Pipeline'!A11),'MiT Strom Pipeline'!A11,""),"") | B16: =IF('MiT Strom Pipeline'!R11="WON",'MiT Strom Pipeline'!B11,"") | C16: =IF('MiT Strom Pipeline'!R11="WON",'MiT Strom Pipeline'!C11,"") | D16: =IF('MiT Strom Pipeline'!R11="WON",'MiT Strom Pipeline'!D11,"") | E16: =IF('MiT Strom Pipeline'!R11="WON",'MiT Strom Pipeline'!E11,"") | F16: =IF('MiT Strom Pipeline'!R11="WON",IF(ISNUMBER('MiT Strom Pipeline'!I11),'MiT Strom Pipeline'!I11,0),"") | G16: =IF('MiT Strom Pipeline'!R11="WON",IF(ISNUMBER('MiT Strom Pipeline'!Q11),'MiT Strom Pipeline'!Q11,0),"") | H16: =IF('MiT Strom Pipeline'!R11="WON",'MiT Strom Pipeline'!R11,"") | I16: =IF('MiT Strom Pipeline'!R11="WON",'MiT Strom Pipeline'!S11,"") | J16: =IF('MiT Strom Pipeline'!R11="WON",IF(LEN('MiT Strom Pipeline'!V11)>0,LEFT('MiT Strom Pipeline'!V11,55),""),"")
A17: =IF('MiT Strom Pipeline'!R12="WON",IF(ISNUMBER('MiT Strom Pipeline'!A12),'MiT Strom Pipeline'!A12,""),"") | B17: =IF('MiT Strom Pipeline'!R12="WON",'MiT Strom Pipeline'!B12,"") | C17: =IF('MiT Strom Pipeline'!R12="WON",'MiT Strom Pipeline'!C12,"") | D17: =IF('MiT Strom Pipeline'!R12="WON",'MiT Strom Pipeline'!D12,"") | E17: =IF('MiT Strom Pipeline'!R12="WON",'MiT Strom Pipeline'!E12,"") | F17: =IF('MiT Strom Pipeline'!R12="WON",IF(ISNUMBER('MiT Strom Pipeline'!I12),'MiT Strom Pipeline'!I12,0),"") | G17: =IF('MiT Strom Pipeline'!R12="WON",IF(ISNUMBER('MiT Strom Pipeline'!Q12),'MiT Strom Pipeline'!Q12,0),"") | H17: =IF('MiT Strom Pipeline'!R12="WON",'MiT Strom Pipeline'!R12,"") | I17: =IF('MiT Strom Pipeline'!R12="WON",'MiT Strom Pipeline'!S12,"") | J17: =IF('MiT Strom Pipeline'!R12="WON",IF(LEN('MiT Strom Pipeline'!V12)>0,LEFT('MiT Strom Pipeline'!V12,55),""),"")
A18: =IF('MiT Strom Pipeline'!R13="WON",IF(ISNUMBER('MiT Strom Pipeline'!A13),'MiT Strom Pipeline'!A13,""),"") | B18: =IF('MiT Strom Pipeline'!R13="WON",'MiT Strom Pipeline'!B13,"") | C18: =IF('MiT Strom Pipeline'!R13="WON",'MiT Strom Pipeline'!C13,"") | D18: =IF('MiT Strom Pipeline'!R13="WON",'MiT Strom Pipeline'!D13,"") | E18: =IF('MiT Strom Pipeline'!R13="WON",'MiT Strom Pipeline'!E13,"") | F18: =IF('MiT Strom Pipeline'!R13="WON",IF(ISNUMBER('MiT Strom Pipeline'!I13),'MiT Strom Pipeline'!I13,0),"") | G18: =IF('MiT Strom Pipeline'!R13="WON",IF(ISNUMBER('MiT Strom Pipeline'!Q13),'MiT Strom Pipeline'!Q13,0),"") | H18: =IF('MiT Strom Pipeline'!R13="WON",'MiT Strom Pipeline'!R13,"") | I18: =IF('MiT Strom Pipeline'!R13="WON",'MiT Strom Pipeline'!S13,"") | J18: =IF('MiT Strom Pipeline'!R13="WON",IF(LEN('MiT Strom Pipeline'!V13)>0,LEFT('MiT Strom Pipeline'!V13,55),""),"")
A19: =IF('MiT Strom Pipeline'!R14="WON",IF(ISNUMBER('MiT Strom Pipeline'!A14),'MiT Strom Pipeline'!A14,""),"") | B19: =IF('MiT Strom Pipeline'!R14="WON",'MiT Strom Pipeline'!B14,"") | C19: =IF('MiT Strom Pipeline'!R14="WON",'MiT Strom Pipeline'!C14,"") | D19: =IF('MiT Strom Pipeline'!R14="WON",'MiT Strom Pipeline'!D14,"") | E19: =IF('MiT Strom Pipeline'!R14="WON",'MiT Strom Pipeline'!E14,"") | F19: =IF('MiT Strom Pipeline'!R14="WON",IF(ISNUMBER('MiT Strom Pipeline'!I14),'MiT Strom Pipeline'!I14,0),"") | G19: =IF('MiT Strom Pipeline'!R14="WON",IF(ISNUMBER('MiT Strom Pipeline'!Q14),'MiT Strom Pipeline'!Q14,0),"") | H19: =IF('MiT Strom Pipeline'!R14="WON",'MiT Strom Pipeline'!R14,"") | I19: =IF('MiT Strom Pipeline'!R14="WON",'MiT Strom Pipeline'!S14,"") | J19: =IF('MiT Strom Pipeline'!R14="WON",IF(LEN('MiT Strom Pipeline'!V14)>0,LEFT('MiT Strom Pipeline'!V14,55),""),"")
A20: =IF('MiT Strom Pipeline'!R15="WON",IF(ISNUMBER('MiT Strom Pipeline'!A15),'MiT Strom Pipeline'!A15,""),"") | B20: =IF('MiT Strom Pipeline'!R15="WON",'MiT Strom Pipeline'!B15,"") | C20: =IF('MiT Strom Pipeline'!R15="WON",'MiT Strom Pipeline'!C15,"") | D20: =IF('MiT Strom Pipeline'!R15="WON",'MiT Strom Pipeline'!D15,"") | E20: =IF('MiT Strom Pipeline'!R15="WON",'MiT Strom Pipeline'!E15,"") | F20: =IF('MiT Strom Pipeline'!R15="WON",IF(ISNUMBER('MiT Strom Pipeline'!I15),'MiT Strom Pipeline'!I15,0),"") | G20: =IF('MiT Strom Pipeline'!R15="WON",IF(ISNUMBER('MiT Strom Pipeline'!Q15),'MiT Strom Pipeline'!Q15,0),"") | H20: =IF('MiT Strom Pipeline'!R15="WON",'MiT Strom Pipeline'!R15,"") | I20: =IF('MiT Strom Pipeline'!R15="WON",'MiT Strom Pipeline'!S15,"") | J20: =IF('MiT Strom Pipeline'!R15="WON",IF(LEN('MiT Strom Pipeline'!V15)>0,LEFT('MiT Strom Pipeline'!V15,55),""),"")
A21: =IF('MiT Strom Pipeline'!R16="WON",IF(ISNUMBER('MiT Strom Pipeline'!A16),'MiT Strom Pipeline'!A16,""),"") | B21: =IF('MiT Strom Pipeline'!R16="WON",'MiT Strom Pipeline'!B16,"") | C21: =IF('MiT Strom Pipeline'!R16="WON",'MiT Strom Pipeline'!C16,"") | D21: =IF('MiT Strom Pipeline'!R16="WON",'MiT Strom Pipeline'!D16,"") | E21: =IF('MiT Strom Pipeline'!R16="WON",'MiT Strom Pipeline'!E16,"") | F21: =IF('MiT Strom Pipeline'!R16="WON",IF(ISNUMBER('MiT Strom Pipeline'!I16),'MiT Strom Pipeline'!I16,0),"") | G21: =IF('MiT Strom Pipeline'!R16="WON",IF(ISNUMBER('MiT Strom Pipeline'!Q16),'MiT Strom Pipeline'!Q16,0),"") | H21: =IF('MiT Strom Pipeline'!R16="WON",'MiT Strom Pipeline'!R16,"") | I21: =IF('MiT Strom Pipeline'!R16="WON",'MiT Strom Pipeline'!S16,"") | J21: =IF('MiT Strom Pipeline'!R16="WON",IF(LEN('MiT Strom Pipeline'!V16)>0,LEFT('MiT Strom Pipeline'!V16,55),""),"")
A22: =IF('MiT Strom Pipeline'!R17="WON",IF(ISNUMBER('MiT Strom Pipeline'!A17),'MiT Strom Pipeline'!A17,""),"") | B22: =IF('MiT Strom Pipeline'!R17="WON",'MiT Strom Pipeline'!B17,"") | C22: =IF('MiT Strom Pipeline'!R17="WON",'MiT Strom Pipeline'!C17,"") | D22: =IF('MiT Strom Pipeline'!R17="WON",'MiT Strom Pipeline'!D17,"") | E22: =IF('MiT Strom Pipeline'!R17="WON",'MiT Strom Pipeline'!E17,"") | F22: =IF('MiT Strom Pipeline'!R17="WON",IF(ISNUMBER('MiT Strom Pipeline'!I17),'MiT Strom Pipeline'!I17,0),"") | G22: =IF('MiT Strom Pipeline'!R17="WON",IF(ISNUMBER('MiT Strom Pipeline'!Q17),'MiT Strom Pipeline'!Q17,0),"") | H22: =IF('MiT Strom Pipeline'!R17="WON",'MiT Strom Pipeline'!R17,"") | I22: =IF('MiT Strom Pipeline'!R17="WON",'MiT Strom Pipeline'!S17,"") | J22: =IF('MiT Strom Pipeline'!R17="WON",IF(LEN('MiT Strom Pipeline'!V17)>0,LEFT('MiT Strom Pipeline'!V17,55),""),"")
... A70: =IF('MiT Strom Pipeline'!R65="WON",IF(ISNUMBER('MiT Strom Pipeline'!A65),'MiT Strom Pipeline'!A65,""),"") | B70: =IF('MiT Strom Pipeline'!R65="WON",'MiT Strom Pipeline'!B65,"") | C70: =IF('MiT Strom Pipeline'!R65="WON",'MiT Strom Pipeline'!C65,"") | D70: =IF('MiT Strom Pipeline'!R65="WON",'MiT Strom Pipeline'!D65,"") | E70: =IF('MiT Strom Pipeline'!R65="WON",'MiT Strom Pipeline'!E65,"") | F70: =IF('MiT Strom Pipeline'!R65="WON",IF(ISNUMBER('MiT Strom Pipeline'!I65),'MiT Strom Pipeline'!I65,0),"") | G70: =IF('MiT Strom Pipeline'!R65="WON",IF(ISNUMBER('MiT Strom Pipeline'!Q65),'MiT Strom Pipeline'!Q65,0),"") | H70: =IF('MiT Strom Pipeline'!R65="WON",'MiT Strom Pipeline'!R65,"") | I70: =IF('MiT Strom Pipeline'!R65="WON",'MiT Strom Pipeline'!S65,"") | J70: =IF('MiT Strom Pipeline'!R65="WON",IF(LEN('MiT Strom Pipeline'!V65)>0,LEFT('MiT Strom Pipeline'!V65,55),""),"")
A71: =IF('MiT Strom Pipeline'!R66="WON",IF(ISNUMBER('MiT Strom Pipeline'!A66),'MiT Strom Pipeline'!A66,""),"") | B71: =IF('MiT Strom Pipeline'!R66="WON",'MiT Strom Pipeline'!B66,"") | F71: =IF('MiT Strom Pipeline'!R66="WON",IF(ISNUMBER('MiT Strom Pipeline'!I66),'MiT Strom Pipeline'!I66,0),"") | G71: =IF('MiT Strom Pipeline'!R66="WON",IF(ISNUMBER('MiT Strom Pipeline'!Q66),'MiT Strom Pipeline'!Q66,0),"") | H71: =IF('MiT Strom Pipeline'!R66="WON",'MiT Strom Pipeline'!R66,"") | I71: =IF('MiT Strom Pipeline'!R66="WON",'MiT Strom Pipeline'!S66,"") | J71: =IF('MiT Strom Pipeline'!R66="WON",IF(LEN('MiT Strom Pipeline'!V66)>0,LEFT('MiT Strom Pipeline'!V66,55),""),"")
A72: =IF('MiT Strom Pipeline'!R67="WON",IF(ISNUMBER('MiT Strom Pipeline'!A67),'MiT Strom Pipeline'!A67,""),"") | B72: =IF('MiT Strom Pipeline'!R67="WON",'MiT Strom Pipeline'!B67,"") | C72: =IF('MiT Strom Pipeline'!R67="WON",'MiT Strom Pipeline'!C67,"") | D72: =IF('MiT Strom Pipeline'!R67="WON",'MiT Strom Pipeline'!D67,"") | E72: =IF('MiT Strom Pipeline'!R67="WON",'MiT Strom Pipeline'!E67,"") | F72: =IF('MiT Strom Pipeline'!R67="WON",IF(ISNUMBER('MiT Strom Pipeline'!I67),'MiT Strom Pipeline'!I67,0),"") | G72: =IF('MiT Strom Pipeline'!R67="WON",IF(ISNUMBER('MiT Strom Pipeline'!Q67),'MiT Strom Pipeline'!Q67,0),"") | H72: =IF('MiT Strom Pipeline'!R67="WON",'MiT Strom Pipeline'!R67,"") | I72: =IF('MiT Strom Pipeline'!R67="WON",'MiT Strom Pipeline'!S67,"") | J72: =IF('MiT Strom Pipeline'!R67="WON",IF(LEN('MiT Strom Pipeline'!V67)>0,LEFT('MiT Strom Pipeline'!V67,55),""),"")
A73: 📄 2. OFFERTE — Versendete & laufende Angebote
A74: # | B74: Kunde / Unternehmen | C74: Kt. | D74: Segment | E74: Leistung / Fleet | F74: Volumen CHF | G74: Gew.Wert CHF | H74: Status | I74: Wahr.% | J74: Nächster Schritt
A75: =IF(('MiT Strom Pipeline'!R6="offered")+('MiT Strom Pipeline'!R6="to be offered")+('MiT Strom Pipeline'!R6="on hold")>0,IF(ISNUMBER('MiT Strom Pipeline'!A6),'MiT Strom Pipeline'!A6,""),"") | B75: =IF(('MiT Strom Pipeline'!R6="offered")+('MiT Strom Pipeline'!R6="to be offered")+('MiT Strom Pipeline'!R6="on hold")>0,'MiT Strom Pipeline'!B6,"") | C75: =IF(('MiT Strom Pipeline'!R6="offered")+('MiT Strom Pipeline'!R6="to be offered")+('MiT Strom Pipeline'!R6="on hold")>0,'MiT Strom Pipeline'!C6,"") | D75: =IF(('MiT Strom Pipeline'!R6="offered")+('MiT Strom Pipeline'!R6="to be offered")+('MiT Strom Pipeline'!R6="on hold")>0,'MiT Strom Pipeline'!D6,"") | E75: =IF(('MiT Strom Pipeline'!R6="offered")+('MiT Strom Pipeline'!R6="to be offered")+('MiT Strom Pipeline'!R6="on hold")>0,'MiT Strom Pipeline'!E6,"") | F75: =IF(('MiT Strom Pipeline'!R6="offered")+('MiT Strom Pipeline'!R6="to be offered")+('MiT Strom Pipeline'!R6="on hold")>0,IF(ISNUMBER('MiT Strom Pipeline'!I6),'MiT Strom Pipeline'!I6,0),"") | G75: =IF(('MiT Strom Pipeline'!R6="offered")+('MiT Strom Pipeline'!R6="to be offered")+('MiT Strom Pipeline'!R6="on hold")>0,IF(ISNUMBER('MiT Strom Pipeline'!Q6),'MiT Strom Pipeline'!Q6,0),"") | H75: =IF(('MiT Strom Pipeline'!R6="offered")+('MiT Strom Pipeline'!R6="to be offered")+('MiT Strom Pipeline'!R6="on hold")>0,'MiT Strom Pipeline'!R6,"") | I75: =IF(('MiT Strom Pipeline'!R6="offered")+('MiT Strom Pipeline'!R6="to be offered")+('MiT Strom Pipeline'!R6="on hold")>0,'MiT Strom Pipeline'!S6,"") | J75: =IF(('MiT Strom Pipeline'!R6="offered")+('MiT Strom Pipeline'!R6="to be offered")+('MiT Strom Pipeline'!R6="on hold")>0,IF(LEN('MiT Strom Pipeline'!V6)>0,LEFT('MiT Strom Pipeline'!V6,55),""),"")
A76: =IF(('MiT Strom Pipeline'!R7="offered")+('MiT Strom Pipeline'!R7="to be offered")+('MiT Strom Pipeline'!R7="on hold")>0,IF(ISNUMBER('MiT Strom Pipeline'!A7),'MiT Strom Pipeline'!A7,""),"") | B76: =IF(('MiT Strom Pipeline'!R7="offered")+('MiT Strom Pipeline'!R7="to be offered")+('MiT Strom Pipeline'!R7="on hold")>0,'MiT Strom Pipeline'!B7,"") | C76: =IF(('MiT Strom Pipeline'!R7="offered")+('MiT Strom Pipeline'!R7="to be offered")+('MiT Strom Pipeline'!R7="on hold")>0,'MiT Strom Pipeline'!C7,"") | D76: =IF(('MiT Strom Pipeline'!R7="offered")+('MiT Strom Pipeline'!R7="to be offered")+('MiT Strom Pipeline'!R7="on hold")>0,'MiT Strom Pipeline'!D7,"") | E76: =IF(('MiT Strom Pipeline'!R7="offered")+('MiT Strom Pipeline'!R7="to be offered")+('MiT Strom Pipeline'!R7="on hold")>0,'MiT Strom Pipeline'!E7,"") | F76: =IF(('MiT Strom Pipeline'!R7="offered")+('MiT Strom Pipeline'!R7="to be offered")+('MiT Strom Pipeline'!R7="on hold")>0,IF(ISNUMBER('MiT Strom Pipeline'!I7),'MiT Strom Pipeline'!I7,0),"") | G76: =IF(('MiT Strom Pipeline'!R7="offered")+('MiT Strom Pipeline'!R7="to be offered")+('MiT Strom Pipeline'!R7="on hold")>0,IF(ISNUMBER('MiT Strom Pipeline'!Q7),'MiT Strom Pipeline'!Q7,0),"") | H76: =IF(('MiT Strom Pipeline'!R7="offered")+('MiT Strom Pipeline'!R7="to be offered")+('MiT Strom Pipeline'!R7="on hold")>0,'MiT Strom Pipeline'!R7,"") | I76: =IF(('MiT Strom Pipeline'!R7="offered")+('MiT Strom Pipeline'!R7="to be offered")+('MiT Strom Pipeline'!R7="on hold")>0,'MiT Strom Pipeline'!S7,"") | J76: =IF(('MiT Strom Pipeline'!R7="offered")+('MiT Strom Pipeline'!R7="to be offered")+('MiT Strom Pipeline'!R7="on hold")>0,IF(LEN('MiT Strom Pipeline'!V7)>0,LEFT('MiT Strom Pipeline'!V7,55),""),"")
A77: =IF(('MiT Strom Pipeline'!R8="offered")+('MiT Strom Pipeline'!R8="to be offered")+('MiT Strom Pipeline'!R8="on hold")>0,IF(ISNUMBER('MiT Strom Pipeline'!A8),'MiT Strom Pipeline'!A8,""),"") | B77: =IF(('MiT Strom Pipeline'!R8="offered")+('MiT Strom Pipeline'!R8="to be offered")+('MiT Strom Pipeline'!R8="on hold")>0,'MiT Strom Pipeline'!B8,"") | C77: =IF(('MiT Strom Pipeline'!R8="offered")+('MiT Strom Pipeline'!R8="to be offered")+('MiT Strom Pipeline'!R8="on hold")>0,'MiT Strom Pipeline'!C8,"") | D77: =IF(('MiT Strom Pipeline'!R8="offered")+('MiT Strom Pipeline'!R8="to be offered")+('MiT Strom Pipeline'!R8="on hold")>0,'MiT Strom Pipeline'!D8,"") | E77: =IF(('MiT Strom Pipeline'!R8="offered")+('MiT Strom Pipeline'!R8="to be offered")+('MiT Strom Pipeline'!R8="on hold")>0,'MiT Strom Pipeline'!E8,"") | F77: =IF(('MiT Strom Pipeline'!R8="offered")+('MiT Strom Pipeline'!R8="to be offered")+('MiT Strom Pipeline'!R8="on hold")>0,IF(ISNUMBER('MiT Strom Pipeline'!I8),'MiT Strom Pipeline'!I8,0),"") | G77: =IF(('MiT Strom Pipeline'!R8="offered")+('MiT Strom Pipeline'!R8="to be offered")+('MiT Strom Pipeline'!R8="on hold")>0,IF(ISNUMBER('MiT Strom Pipeline'!Q8),'MiT Strom Pipeline'!Q8,0),"") | H77: =IF(('MiT Strom Pipeline'!R8="offered")+('MiT Strom Pipeline'!R8="to be offered")+('MiT Strom Pipeline'!R8="on hold")>0,'MiT Strom Pipeline'!R8,"") | I77: =IF(('MiT Strom Pipeline'!R8="offered")+('MiT Strom Pipeline'!R8="to be offered")+('MiT Strom Pipeline'!R8="on hold")>0,'MiT Strom Pipeline'!S8,"") | J77: =IF(('MiT Strom Pipeline'!R8="offered")+('MiT Strom Pipeline'!R8="to be offered")+('MiT Strom Pipeline'!R8="on hold")>0,IF(LEN('MiT Strom Pipeline'!V8)>0,LEFT('MiT Strom Pipeline'!V8,55),""),"")
A78: =IF(('MiT Strom Pipeline'!R9="offered")+('MiT Strom Pipeline'!R9="to be offered")+('MiT Strom Pipeline'!R9="on hold")>0,IF(ISNUMBER('MiT Strom Pipeline'!A9),'MiT Strom Pipeline'!A9,""),"") -> 4 | B78: =IF(('MiT Strom Pipeline'!R9="offered")+('MiT Strom Pipeline'!R9="to be offered")+('MiT Strom Pipeline'!R9="on hold")>0,'MiT Strom Pipeline'!B9,"") -> Stagelight – OpenAir Frauenfeld | C78: =IF(('MiT Strom Pipeline'!R9="offered")+('MiT Strom Pipeline'!R9="to be offered")+('MiT Strom Pipeline'!R9="on hold")>0,'MiT Strom Pipeline'!C9,"") -> TG | D78: =IF(('MiT Strom Pipeline'!R9="offered")+('MiT Strom Pipeline'!R9="to be offered")+('MiT Strom Pipeline'!R9="on hold")>0,'MiT Strom Pipeline'!D9,"") -> Events & Kultur | E78: =IF(('MiT Strom Pipeline'!R9="offered")+('MiT Strom Pipeline'!R9="to be offered")+('MiT Strom Pipeline'!R9="on hold")>0,'MiT Strom Pipeline'!E9,"") -> ~500 kVA Generator | F78: =IF(('MiT Strom Pipeline'!R9="offered")+('MiT Strom Pipeline'!R9="to be offered")+('MiT Strom Pipeline'!R9="on hold")>0,IF(ISNUMBER('MiT Strom Pipeline'!I9),'MiT Strom Pipeline'!I9,0),"") -> 150000 | G78: =IF(('MiT Strom Pipeline'!R9="offered")+('MiT Strom Pipeline'!R9="to be offered")+('MiT Strom Pipeline'!R9="on hold")>0,IF(ISNUMBER('MiT Strom Pipeline'!Q9),'MiT Strom Pipeline'!Q9,0),"") -> 1350 | H78: =IF(('MiT Strom Pipeline'!R9="offered")+('MiT Strom Pipeline'!R9="to be offered")+('MiT Strom Pipeline'!R9="on hold")>0,'MiT Strom Pipeline'!R9,"") -> offered | I78: =IF(('MiT Strom Pipeline'!R9="offered")+('MiT Strom Pipeline'!R9="to be offered")+('MiT Strom Pipeline'!R9="on hold")>0,'MiT Strom Pipeline'!S9,"") -> 90% | J78: =IF(('MiT Strom Pipeline'!R9="offered")+('MiT Strom Pipeline'!R9="to be offered")+('MiT Strom Pipeline'!R9="on hold")>0,IF(LEN('MiT Strom Pipeline'!V9)>0,LEFT('MiT Strom Pipeline'!V9,55),""),"") -> Follow-up + Vertragsverhandlung initiieren
A79: =IF(('MiT Strom Pipeline'!R10="offered")+('MiT Strom Pipeline'!R10="to be offered")+('MiT Strom Pipeline'!R10="on hold")>0,IF(ISNUMBER('MiT Strom Pipeline'!A10),'MiT Strom Pipeline'!A10,""),"") -> 6 | B79: =IF(('MiT Strom Pipeline'!R10="offered")+('MiT Strom Pipeline'!R10="to be offered")+('MiT Strom Pipeline'!R10="on hold")>0,'MiT Strom Pipeline'!B10,"") -> Wincasa Solothurn | C79: =IF(('MiT Strom Pipeline'!R10="offered")+('MiT Strom Pipeline'!R10="to be offered")+('MiT Strom Pipeline'!R10="on hold")>0,'MiT Strom Pipeline'!C10,"") -> SO | D79: =IF(('MiT Strom Pipeline'!R10="offered")+('MiT Strom Pipeline'!R10="to be offered")+('MiT Strom Pipeline'!R10="on hold")>0,'MiT Strom Pipeline'!D10,"") -> Immobilien / FM | E79: =IF(('MiT Strom Pipeline'!R10="offered")+('MiT Strom Pipeline'!R10="to be offered")+('MiT Strom Pipeline'!R10="on hold")>0,'MiT Strom Pipeline'!E10,"") -> BESS 1 MWh | F79: =IF(('MiT Strom Pipeline'!R10="offered")+('MiT Strom Pipeline'!R10="to be offered")+('MiT Strom Pipeline'!R10="on hold")>0,IF(ISNUMBER('MiT Strom Pipeline'!I10),'MiT Strom Pipeline'!I10,0),"") -> 390000 | G79: =IF(('MiT Strom Pipeline'!R10="offered")+('MiT Strom Pipeline'!R10="to be offered")+('MiT Strom Pipeline'!R10="on hold")>0,IF(ISNUMBER('MiT Strom Pipeline'!Q10),'MiT Strom Pipeline'!Q10,0),"") -> 1950 | H79: =IF(('MiT Strom Pipeline'!R10="offered")+('MiT Strom Pipeline'!R10="to be offered")+('MiT Strom Pipeline'!R10="on hold")>0,'MiT Strom Pipeline'!R10,"") -> on hold | I79: =IF(('MiT Strom Pipeline'!R10="offered")+('MiT Strom Pipeline'!R10="to be offered")+('MiT Strom Pipeline'!R10="on hold")>0,'MiT Strom Pipeline'!S10,"") -> 50% | J79: =IF(('MiT Strom Pipeline'!R10="offered")+('MiT Strom Pipeline'!R10="to be offered")+('MiT Strom Pipeline'!R10="on hold")>0,IF(LEN('MiT Strom Pipeline'!V10)>0,LEFT('MiT Strom Pipeline'!V10,55),""),"") -> Entscheider-Meeting anfordern, Businesscase Energie-ROI
A80: =IF(('MiT Strom Pipeline'!R11="offered")+('MiT Strom Pipeline'!R11="to be offered")+('MiT Strom Pipeline'!R11="on hold")>0,IF(ISNUMBER('MiT Strom Pipeline'!A11),'MiT Strom Pipeline'!A11,""),"") | B80: =IF(('MiT Strom Pipeline'!R11="offered")+('MiT Strom Pipeline'!R11="to be offered")+('MiT Strom Pipeline'!R11="on hold")>0,'MiT Strom Pipeline'!B11,"") | C80: =IF(('MiT Strom Pipeline'!R11="offered")+('MiT Strom Pipeline'!R11="to be offered")+('MiT Strom Pipeline'!R11="on hold")>0,'MiT Strom Pipeline'!C11,"") | D80: =IF(('MiT Strom Pipeline'!R11="offered")+('MiT Strom Pipeline'!R11="to be offered")+('MiT Strom Pipeline'!R11="on hold")>0,'MiT Strom Pipeline'!D11,"") | E80: =IF(('MiT Strom Pipeline'!R11="offered")+('MiT Strom Pipeline'!R11="to be offered")+('MiT Strom Pipeline'!R11="on hold")>0,'MiT Strom Pipeline'!E11,"") | F80: =IF(('MiT Strom Pipeline'!R11="offered")+('MiT Strom Pipeline'!R11="to be offered")+('MiT Strom Pipeline'!R11="on hold")>0,IF(ISNUMBER('MiT Strom Pipeline'!I11),'MiT Strom Pipeline'!I11,0),"") | G80: =IF(('MiT Strom Pipeline'!R11="offered")+('MiT Strom Pipeline'!R11="to be offered")+('MiT Strom Pipeline'!R11="on hold")>0,IF(ISNUMBER('MiT Strom Pipeline'!Q11),'MiT Strom Pipeline'!Q11,0),"") | H80: =IF(('MiT Strom Pipeline'!R11="offered")+('MiT Strom Pipeline'!R11="to be offered")+('MiT Strom Pipeline'!R11="on hold")>0,'MiT Strom Pipeline'!R11,"") | I80: =IF(('MiT Strom Pipeline'!R11="offered")+('MiT Strom Pipeline'!R11="to be offered")+('MiT Strom Pipeline'!R11="on hold")>0,'MiT Strom Pipeline'!S11,"") | J80: =IF(('MiT Strom Pipeline'!R11="offered")+('MiT Strom Pipeline'!R11="to be offered")+('MiT Strom Pipeline'!R11="on hold")>0,IF(LEN('MiT Strom Pipeline'!V11)>0,LEFT('MiT Strom Pipeline'!V11,55),""),"")
A81: =IF(('MiT Strom Pipeline'!R12="offered")+('MiT Strom Pipeline'!R12="to be offered")+('MiT Strom Pipeline'!R12="on hold")>0,IF(ISNUMBER('MiT Strom Pipeline'!A12),'MiT Strom Pipeline'!A12,""),"") | B81: =IF(('MiT Strom Pipeline'!R12="offered")+('MiT Strom Pipeline'!R12="to be offered")+('MiT Strom Pipeline'!R12="on hold")>0,'MiT Strom Pipeline'!B12,"") | C81: =IF(('MiT Strom Pipeline'!R12="offered")+('MiT Strom Pipeline'!R12="to be offered")+('MiT Strom Pipeline'!R12="on hold")>0,'MiT Strom Pipeline'!C12,"") | D81: =IF(('MiT Strom Pipeline'!R12="offered")+('MiT Strom Pipeline'!R12="to be offered")+('MiT Strom Pipeline'!R12="on hold")>0,'MiT Strom Pipeline'!D12,"") | E81: =IF(('MiT Strom Pipeline'!R12="offered")+('MiT Strom Pipeline'!R12="to be offered")+('MiT Strom Pipeline'!R12="on hold")>0,'MiT Strom Pipeline'!E12,"") | F81: =IF(('MiT Strom Pipeline'!R12="offered")+('MiT Strom Pipeline'!R12="to be offered")+('MiT Strom Pipeline'!R12="on hold")>0,IF(ISNUMBER('MiT Strom Pipeline'!I12),'MiT Strom Pipeline'!I12,0),"") | G81: =IF(('MiT Strom Pipeline'!R12="offered")+('MiT Strom Pipeline'!R12="to be offered")+('MiT Strom Pipeline'!R12="on hold")>0,IF(ISNUMBER('MiT Strom Pipeline'!Q12),'MiT Strom Pipeline'!Q12,0),"") | H81: =IF(('MiT Strom Pipeline'!R12="offered")+('MiT Strom Pipeline'!R12="to be offered")+('MiT Strom Pipeline'!R12="on hold")>0,'MiT Strom Pipeline'!R12,"") | I81: =IF(('MiT Strom Pipeline'!R12="offered")+('MiT Strom Pipeline'!R12="to be offered")+('MiT Strom Pipeline'!R12="on hold")>0,'MiT Strom Pipeline'!S12,"") | J81: =IF(('MiT Strom Pipeline'!R12="offered")+('MiT Strom Pipeline'!R12="to be offered")+('MiT Strom Pipeline'!R12="on hold")>0,IF(LEN('MiT Strom Pipeline'!V12)>0,LEFT('MiT Strom Pipeline'!V12,55),""),"")
A82: =IF(('MiT Strom Pipeline'!R13="offered")+('MiT Strom Pipeline'!R13="to be offered")+('MiT Strom Pipeline'!R13="on hold")>0,IF(ISNUMBER('MiT Strom Pipeline'!A13),'MiT Strom Pipeline'!A13,""),"") | B82: =IF(('MiT Strom Pipeline'!R13="offered")+('MiT Strom Pipeline'!R13="to be offered")+('MiT Strom Pipeline'!R13="on hold")>0,'MiT Strom Pipeline'!B13,"") | C82: =IF(('MiT Strom Pipeline'!R13="offered")+('MiT Strom Pipeline'!R13="to be offered")+('MiT Strom Pipeline'!R13="on hold")>0,'MiT Strom Pipeline'!C13,"") | D82: =IF(('MiT Strom Pipeline'!R13="offered")+('MiT Strom Pipeline'!R13="to be offered")+('MiT Strom Pipeline'!R13="on hold")>0,'MiT Strom Pipeline'!D13,"") | E82: =IF(('MiT Strom Pipeline'!R13="offered")+('MiT Strom Pipeline'!R13="to be offered")+('MiT Strom Pipeline'!R13="on hold")>0,'MiT Strom Pipeline'!E13,"") | F82: =IF(('MiT Strom Pipeline'!R13="offered")+('MiT Strom Pipeline'!R13="to be offered")+('MiT Strom Pipeline'!R13="on hold")>0,IF(ISNUMBER('MiT Strom Pipeline'!I13),'MiT Strom Pipeline'!I13,0),"") | G82: =IF(('MiT Strom Pipeline'!R13="offered")+('MiT Strom Pipeline'!R13="to be offered")+('MiT Strom Pipeline'!R13="on hold")>0,IF(ISNUMBER('MiT Strom Pipeline'!Q13),'MiT Strom Pipeline'!Q13,0),"") | H82: =IF(('MiT Strom Pipeline'!R13="offered")+('MiT Strom Pipeline'!R13="to be offered")+('MiT Strom Pipeline'!R13="on hold")>0,'MiT Strom Pipeline'!R13,"") | I82: =IF(('MiT Strom Pipeline'!R13="offered")+('MiT Strom Pipeline'!R13="to be offered")+('MiT Strom Pipeline'!R13="on hold")>0,'MiT Strom Pipeline'!S13,"") | J82: =IF(('MiT Strom Pipeline'!R13="offered")+('MiT Strom Pipeline'!R13="to be offered")+('MiT Strom Pipeline'!R13="on hold")>0,IF(LEN('MiT Strom Pipeline'!V13)>0,LEFT('MiT Strom Pipeline'!V13,55),""),"")
A83: =IF(('MiT Strom Pipeline'!R14="offered")+('MiT Strom Pipeline'!R14="to be offered")+('MiT Strom Pipeline'!R14="on hold")>0,IF(ISNUMBER('MiT Strom Pipeline'!A14),'MiT Strom Pipeline'!A14,""),"") | B83: =IF(('MiT Strom Pipeline'!R14="offered")+('MiT Strom Pipeline'!R14="to be offered")+('MiT Strom Pipeline'!R14="on hold")>0,'MiT Strom Pipeline'!B14,"") | C83: =IF(('MiT Strom Pipeline'!R14="offered")+('MiT Strom Pipeline'!R14="to be offered")+('MiT Strom Pipeline'!R14="on hold")>0,'MiT Strom Pipeline'!C14,"") | D83: =IF(('MiT Strom Pipeline'!R14="offered")+('MiT Strom Pipeline'!R14="to be offered")+('MiT Strom Pipeline'!R14="on hold")>0,'MiT Strom Pipeline'!D14,"") | E83: =IF(('MiT Strom Pipeline'!R14="offered")+('MiT Strom Pipeline'!R14="to be offered")+('MiT Strom Pipeline'!R14="on hold")>0,'MiT Strom Pipeline'!E14,"") | F83: =IF(('MiT Strom Pipeline'!R14="offered")+('MiT Strom Pipeline'!R14="to be offered")+('MiT Strom Pipeline'!R14="on hold")>0,IF(ISNUMBER('MiT Strom Pipeline'!I14),'MiT Strom Pipeline'!I14,0),"") | G83: =IF(('MiT Strom Pipeline'!R14="offered")+('MiT Strom Pipeline'!R14="to be offered")+('MiT Strom Pipeline'!R14="on hold")>0,IF(ISNUMBER('MiT Strom Pipeline'!Q14),'MiT Strom Pipeline'!Q14,0),"") | H83: =IF(('MiT Strom Pipeline'!R14="offered")+('MiT Strom Pipeline'!R14="to be offered")+('MiT Strom Pipeline'!R14="on hold")>0,'MiT Strom Pipeline'!R14,"") | I83: =IF(('MiT Strom Pipeline'!R14="offered")+('MiT Strom Pipeline'!R14="to be offered")+('MiT Strom Pipeline'!R14="on hold")>0,'MiT Strom Pipeline'!S14,"") | J83: =IF(('MiT Strom Pipeline'!R14="offered")+('MiT Strom Pipeline'!R14="to be offered")+('MiT Strom Pipeline'!R14="on hold")>0,IF(LEN('MiT Strom Pipeline'!V14)>0,LEFT('MiT Strom Pipeline'!V14,55),""),"")
A84: =IF(('MiT Strom Pipeline'!R15="offered")+('MiT Strom Pipeline'!R15="to be offered")+('MiT Strom Pipeline'!R15="on hold")>0,IF(ISNUMBER('MiT Strom Pipeline'!A15),'MiT Strom Pipeline'!A15,""),"") | B84: =IF(('MiT Strom Pipeline'!R15="offered")+('MiT Strom Pipeline'!R15="to be offered")+('MiT Strom Pipeline'!R15="on hold")>0,'MiT Strom Pipeline'!B15,"") | C84: =IF(('MiT Strom Pipeline'!R15="offered")+('MiT Strom Pipeline'!R15="to be offered")+('MiT Strom Pipeline'!R15="on hold")>0,'MiT Strom Pipeline'!C15,"") | D84: =IF(('MiT Strom Pipeline'!R15="offered")+('MiT Strom Pipeline'!R15="to be offered")+('MiT Strom Pipeline'!R15="on hold")>0,'MiT Strom Pipeline'!D15,"") | E84: =IF(('MiT Strom Pipeline'!R15="offered")+('MiT Strom Pipeline'!R15="to be offered")+('MiT Strom Pipeline'!R15="on hold")>0,'MiT Strom Pipeline'!E15,"") | F84: =IF(('MiT Strom Pipeline'!R15="offered")+('MiT Strom Pipeline'!R15="to be offered")+('MiT Strom Pipeline'!R15="on hold")>0,IF(ISNUMBER('MiT Strom Pipeline'!I15),'MiT Strom Pipeline'!I15,0),"") | G84: =IF(('MiT Strom Pipeline'!R15="offered")+('MiT Strom Pipeline'!R15="to be offered")+('MiT Strom Pipeline'!R15="on hold")>0,IF(ISNUMBER('MiT Strom Pipeline'!Q15),'MiT Strom Pipeline'!Q15,0),"") | H84: =IF(('MiT Strom Pipeline'!R15="offered")+('MiT Strom Pipeline'!R15="to be offered")+('MiT Strom Pipeline'!R15="on hold")>0,'MiT Strom Pipeline'!R15,"") | I84: =IF(('MiT Strom Pipeline'!R15="offered")+('MiT Strom Pipeline'!R15="to be offered")+('MiT Strom Pipeline'!R15="on hold")>0,'MiT Strom Pipeline'!S15,"") | J84: =IF(('MiT Strom Pipeline'!R15="offered")+('MiT Strom Pipeline'!R15="to be offered")+('MiT Strom Pipeline'!R15="on hold")>0,IF(LEN('MiT Strom Pipeline'!V15)>0,LEFT('MiT Strom Pipeline'!V15,55),""),"")
A85: =IF(('MiT Strom Pipeline'!R16="offered")+('MiT Strom Pipeline'!R16="to be offered")+('MiT Strom Pipeline'!R16="on hold")>0,IF(ISNUMBER('MiT Strom Pipeline'!A16),'MiT Strom Pipeline'!A16,""),"") | B85: =IF(('MiT Strom Pipeline'!R16="offered")+('MiT Strom Pipeline'!R16="to be offered")+('MiT Strom Pipeline'!R16="on hold")>0,'MiT Strom Pipeline'!B16,"") | C85: =IF(('MiT Strom Pipeline'!R16="offered")+('MiT Strom Pipeline'!R16="to be offered")+('MiT Strom Pipeline'!R16="on hold")>0,'MiT Strom Pipeline'!C16,"") | D85: =IF(('MiT Strom Pipeline'!R16="offered")+('MiT Strom Pipeline'!R16="to be offered")+('MiT Strom Pipeline'!R16="on hold")>0,'MiT Strom Pipeline'!D16,"") | E85: =IF(('MiT Strom Pipeline'!R16="offered")+('MiT Strom Pipeline'!R16="to be offered")+('MiT Strom Pipeline'!R16="on hold")>0,'MiT Strom Pipeline'!E16,"") | F85: =IF(('MiT Strom Pipeline'!R16="offered")+('MiT Strom Pipeline'!R16="to be offered")+('MiT Strom Pipeline'!R16="on hold")>0,IF(ISNUMBER('MiT Strom Pipeline'!I16),'MiT Strom Pipeline'!I16,0),"") | G85: =IF(('MiT Strom Pipeline'!R16="offered")+('MiT Strom Pipeline'!R16="to be offered")+('MiT Strom Pipeline'!R16="on hold")>0,IF(ISNUMBER('MiT Strom Pipeline'!Q16),'MiT Strom Pipeline'!Q16,0),"") | H85: =IF(('MiT Strom Pipeline'!R16="offered")+('MiT Strom Pipeline'!R16="to be offered")+('MiT Strom Pipeline'!R16="on hold")>0,'MiT Strom Pipeline'!R16,"") | I85: =IF(('MiT Strom Pipeline'!R16="offered")+('MiT Strom Pipeline'!R16="to be offered")+('MiT Strom Pipeline'!R16="on hold")>0,'MiT Strom Pipeline'!S16,"") | J85: =IF(('MiT Strom Pipeline'!R16="offered")+('MiT Strom Pipeline'!R16="to be offered")+('MiT Strom Pipeline'!R16="on hold")>0,IF(LEN('MiT Strom Pipeline'!V16)>0,LEFT('MiT Strom Pipeline'!V16,55),""),"")
A86: =IF(('MiT Strom Pipeline'!R17="offered")+('MiT Strom Pipeline'!R17="to be offered")+('MiT Strom Pipeline'!R17="on hold")>0,IF(ISNUMBER('MiT Strom Pipeline'!A17),'MiT Strom Pipeline'!A17,""),"") -> 13 | B86: =IF(('MiT Strom Pipeline'!R17="offered")+('MiT Strom Pipeline'!R17="to be offered")+('MiT Strom Pipeline'!R17="on hold")>0,'MiT Strom Pipeline'!B17,"") -> Proxima Fusion AG | C86: =IF(('MiT Strom Pipeline'!R17="offered")+('MiT Strom Pipeline'!R17="to be offered")+('MiT Strom Pipeline'!R17="on hold")>0,'MiT Strom Pipeline'!C17,"") -> ZH | D86: =IF(('MiT Strom Pipeline'!R17="offered")+('MiT Strom Pipeline'!R17="to be offered")+('MiT Strom Pipeline'!R17="on hold")>0,'MiT Strom Pipeline'!D17,"") -> Forschung / Hightech | E86: =IF(('MiT Strom Pipeline'!R17="offered")+('MiT Strom Pipeline'!R17="to be offered")+('MiT Strom Pipeline'!R17="on hold")>0,'MiT Strom Pipeline'!E17,"") -> BESS 1 MWh | F86: =IF(('MiT Strom Pipeline'!R17="offered")+('MiT Strom Pipeline'!R17="to be offered")+('MiT Strom Pipeline'!R17="on hold")>0,IF(ISNUMBER('MiT Strom Pipeline'!I17),'MiT Strom Pipeline'!I17,0),"") -> 365003 | G86: =IF(('MiT Strom Pipeline'!R17="offered")+('MiT Strom Pipeline'!R17="to be offered")+('MiT Strom Pipeline'!R17="on hold")>0,IF(ISNUMBER('MiT Strom Pipeline'!Q17),'MiT Strom Pipeline'!Q17,0),"") -> 182501.5 | H86: =IF(('MiT Strom Pipeline'!R17="offered")+('MiT Strom Pipeline'!R17="to be offered")+('MiT Strom Pipeline'!R17="on hold")>0,'MiT Strom Pipeline'!R17,"") -> offered | I86: =IF(('MiT Strom Pipeline'!R17="offered")+('MiT Strom Pipeline'!R17="to be offered")+('MiT Strom Pipeline'!R17="on hold")>0,'MiT Strom Pipeline'!S17,"") -> 50 | J86: =IF(('MiT Strom Pipeline'!R17="offered")+('MiT Strom Pipeline'!R17="to be offered")+('MiT Strom Pipeline'!R17="on hold")>0,IF(LEN('MiT Strom Pipeline'!V17)>0,LEFT('MiT Strom Pipeline'!V17,55),""),"") -> Technisches Gespräch – USV + PQ-Anforderungen klären, K
... A134: =IF(('MiT Strom Pipeline'!R65="offered")+('MiT Strom Pipeline'!R65="to be offered")+('MiT Strom Pipeline'!R65="on hold")>0,IF(ISNUMBER('MiT Strom Pipeline'!A65),'MiT Strom Pipeline'!A65,""),"") | B134: =IF(('MiT Strom Pipeline'!R65="offered")+('MiT Strom Pipeline'!R65="to be offered")+('MiT Strom Pipeline'!R65="on hold")>0,'MiT Strom Pipeline'!B65,"") | C134: =IF(('MiT Strom Pipeline'!R65="offered")+('MiT Strom Pipeline'!R65="to be offered")+('MiT Strom Pipeline'!R65="on hold")>0,'MiT Strom Pipeline'!C65,"") | D134: =IF(('MiT Strom Pipeline'!R65="offered")+('MiT Strom Pipeline'!R65="to be offered")+('MiT Strom Pipeline'!R65="on hold")>0,'MiT Strom Pipeline'!D65,"") | E134: =IF(('MiT Strom Pipeline'!R65="offered")+('MiT Strom Pipeline'!R65="to be offered")+('MiT Strom Pipeline'!R65="on hold")>0,'MiT Strom Pipeline'!E65,"") | F134: =IF(('MiT Strom Pipeline'!R65="offered")+('MiT Strom Pipeline'!R65="to be offered")+('MiT Strom Pipeline'!R65="on hold")>0,IF(ISNUMBER('MiT Strom Pipeline'!I65),'MiT Strom Pipeline'!I65,0),"") | G134: =IF(('MiT Strom Pipeline'!R65="offered")+('MiT Strom Pipeline'!R65="to be offered")+('MiT Strom Pipeline'!R65="on hold")>0,IF(ISNUMBER('MiT Strom Pipeline'!Q65),'MiT Strom Pipeline'!Q65,0),"") | H134: =IF(('MiT Strom Pipeline'!R65="offered")+('MiT Strom Pipeline'!R65="to be offered")+('MiT Strom Pipeline'!R65="on hold")>0,'MiT Strom Pipeline'!R65,"") | I134: =IF(('MiT Strom Pipeline'!R65="offered")+('MiT Strom Pipeline'!R65="to be offered")+('MiT Strom Pipeline'!R65="on hold")>0,'MiT Strom Pipeline'!S65,"") | J134: =IF(('MiT Strom Pipeline'!R65="offered")+('MiT Strom Pipeline'!R65="to be offered")+('MiT Strom Pipeline'!R65="on hold")>0,IF(LEN('MiT Strom Pipeline'!V65)>0,LEFT('MiT Strom Pipeline'!V65,55),""),"")
A135: =IF(('MiT Strom Pipeline'!R66="offered")+('MiT Strom Pipeline'!R66="to be offered")+('MiT Strom Pipeline'!R66="on hold")>0,IF(ISNUMBER('MiT Strom Pipeline'!A66),'MiT Strom Pipeline'!A66,""),"") | B135: =IF(('MiT Strom Pipeline'!R66="offered")+('MiT Strom Pipeline'!R66="to be offered")+('MiT Strom Pipeline'!R66="on hold")>0,'MiT Strom Pipeline'!B66,"") | F135: =IF(('MiT Strom Pipeline'!R66="offered")+('MiT Strom Pipeline'!R66="to be offered")+('MiT Strom Pipeline'!R66="on hold")>0,IF(ISNUMBER('MiT Strom Pipeline'!I66),'MiT Strom Pipeline'!I66,0),"") | G135: =IF(('MiT Strom Pipeline'!R66="offered")+('MiT Strom Pipeline'!R66="to be offered")+('MiT Strom Pipeline'!R66="on hold")>0,IF(ISNUMBER('MiT Strom Pipeline'!Q66),'MiT Strom Pipeline'!Q66,0),"") | H135: =IF(('MiT Strom Pipeline'!R66="offered")+('MiT Strom Pipeline'!R66="to be offered")+('MiT Strom Pipeline'!R66="on hold")>0,'MiT Strom Pipeline'!R66,"") | I135: =IF(('MiT Strom Pipeline'!R66="offered")+('MiT Strom Pipeline'!R66="to be offered")+('MiT Strom Pipeline'!R66="on hold")>0,'MiT Strom Pipeline'!S66,"") | J135: =IF(('MiT Strom Pipeline'!R66="offered")+('MiT Strom Pipeline'!R66="to be offered")+('MiT Strom Pipeline'!R66="on hold")>0,IF(LEN('MiT Strom Pipeline'!V66)>0,LEFT('MiT Strom Pipeline'!V66,55),""),"")
A136: =IF(('MiT Strom Pipeline'!R67="offered")+('MiT Strom Pipeline'!R67="to be offered")+('MiT Strom Pipeline'!R67="on hold")>0,IF(ISNUMBER('MiT Strom Pipeline'!A67),'MiT Strom Pipeline'!A67,""),"") | B136: =IF(('MiT Strom Pipeline'!R67="offered")+('MiT Strom Pipeline'!R67="to be offered")+('MiT Strom Pipeline'!R67="on hold")>0,'MiT Strom Pipeline'!B67,"") | C136: =IF(('MiT Strom Pipeline'!R67="offered")+('MiT Strom Pipeline'!R67="to be offered")+('MiT Strom Pipeline'!R67="on hold")>0,'MiT Strom Pipeline'!C67,"") | D136: =IF(('MiT Strom Pipeline'!R67="offered")+('MiT Strom Pipeline'!R67="to be offered")+('MiT Strom Pipeline'!R67="on hold")>0,'MiT Strom Pipeline'!D67,"") | E136: =IF(('MiT Strom Pipeline'!R67="offered")+('MiT Strom Pipeline'!R67="to be offered")+('MiT Strom Pipeline'!R67="on hold")>0,'MiT Strom Pipeline'!E67,"") | F136: =IF(('MiT Strom Pipeline'!R67="offered")+('MiT Strom Pipeline'!R67="to be offered")+('MiT Strom Pipeline'!R67="on hold")>0,IF(ISNUMBER('MiT Strom Pipeline'!I67),'MiT Strom Pipeline'!I67,0),"") | G136: =IF(('MiT Strom Pipeline'!R67="offered")+('MiT Strom Pipeline'!R67="to be offered")+('MiT Strom Pipeline'!R67="on hold")>0,IF(ISNUMBER('MiT Strom Pipeline'!Q67),'MiT Strom Pipeline'!Q67,0),"") | H136: =IF(('MiT Strom Pipeline'!R67="offered")+('MiT Strom Pipeline'!R67="to be offered")+('MiT Strom Pipeline'!R67="on hold")>0,'MiT Strom Pipeline'!R67,"") | I136: =IF(('MiT Strom Pipeline'!R67="offered")+('MiT Strom Pipeline'!R67="to be offered")+('MiT Strom Pipeline'!R67="on hold")>0,'MiT Strom Pipeline'!S67,"") | J136: =IF(('MiT Strom Pipeline'!R67="offered")+('MiT Strom Pipeline'!R67="to be offered")+('MiT Strom Pipeline'!R67="on hold")>0,IF(LEN('MiT Strom Pipeline'!V67)>0,LEFT('MiT Strom Pipeline'!V67,55),""),"")
A137: 🎯 3. OPPORTUNITÄT — Qualifizierte Leads
A138: # | B138: Kunde / Unternehmen | C138: Kt. | D138: Segment | E138: Leistung / Fleet | F138: Volumen CHF | G138: Gew.Wert CHF | H138: Status | I138: Wahr.% | J138: Nächster Schritt
A139: =IF(('MiT Strom Pipeline'!R6="follow-up")+('MiT Strom Pipeline'!R6="Evaluation")+('MiT Strom Pipeline'!R6="tbd")+('MiT Strom Pipeline'!R6="In evaluation")>0,IF(ISNUMBER('MiT Strom Pipeline'!A6),'MiT Strom Pipeline'!A6,""),"") | B139: =IF(('MiT Strom Pipeline'!R6="follow-up")+('MiT Strom Pipeline'!R6="Evaluation")+('MiT Strom Pipeline'!R6="tbd")+('MiT Strom Pipeline'!R6="In evaluation")>0,'MiT Strom Pipeline'!B6,"") | C139: =IF(('MiT Strom Pipeline'!R6="follow-up")+('MiT Strom Pipeline'!R6="Evaluation")+('MiT Strom Pipeline'!R6="tbd")+('MiT Strom Pipeline'!R6="In evaluation")>0,'MiT Strom Pipeline'!C6,"") | D139: =IF(('MiT Strom Pipeline'!R6="follow-up")+('MiT Strom Pipeline'!R6="Evaluation")+('MiT Strom Pipeline'!R6="tbd")+('MiT Strom Pipeline'!R6="In evaluation")>0,'MiT Strom Pipeline'!D6,"") | E139: =IF(('MiT Strom Pipeline'!R6="follow-up")+('MiT Strom Pipeline'!R6="Evaluation")+('MiT Strom Pipeline'!R6="tbd")+('MiT Strom Pipeline'!R6="In evaluation")>0,'MiT Strom Pipeline'!E6,"") | F139: =IF(('MiT Strom Pipeline'!R6="follow-up")+('MiT Strom Pipeline'!R6="Evaluation")+('MiT Strom Pipeline'!R6="tbd")+('MiT Strom Pipeline'!R6="In evaluation")>0,IF(ISNUMBER('MiT Strom Pipeline'!I6),'MiT Strom Pipeline'!I6,0),"") | G139: =IF(('MiT Strom Pipeline'!R6="follow-up")+('MiT Strom Pipeline'!R6="Evaluation")+('MiT Strom Pipeline'!R6="tbd")+('MiT Strom Pipeline'!R6="In evaluation")>0,IF(ISNUMBER('MiT Strom Pipeline'!Q6),'MiT Strom Pipeline'!Q6,0),"") | H139: =IF(('MiT Strom Pipeline'!R6="follow-up")+('MiT Strom Pipeline'!R6="Evaluation")+('MiT Strom Pipeline'!R6="tbd")+('MiT Strom Pipeline'!R6="In evaluation")>0,'MiT Strom Pipeline'!R6,"") | I139: =IF(('MiT Strom Pipeline'!R6="follow-up")+('MiT Strom Pipeline'!R6="Evaluation")+('MiT Strom Pipeline'!R6="tbd")+('MiT Strom Pipeline'!R6="In evaluation")>0,'MiT Strom Pipeline'!S6,"") | J139: =IF(('MiT Strom Pipeline'!R6="follow-up")+('MiT Strom Pipeline'!R6="Evaluation")+('MiT Strom Pipeline'!R6="tbd")+('MiT Strom Pipeline'!R6="In evaluation")>0,IF(LEN('MiT Strom Pipeline'!V6)>0,LEFT('MiT Strom Pipeline'!V6,55),""),"")
A140: =IF(('MiT Strom Pipeline'!R7="follow-up")+('MiT Strom Pipeline'!R7="Evaluation")+('MiT Strom Pipeline'!R7="tbd")+('MiT Strom Pipeline'!R7="In evaluation")>0,IF(ISNUMBER('MiT Strom Pipeline'!A7),'MiT Strom Pipeline'!A7,""),"") | B140: =IF(('MiT Strom Pipeline'!R7="follow-up")+('MiT Strom Pipeline'!R7="Evaluation")+('MiT Strom Pipeline'!R7="tbd")+('MiT Strom Pipeline'!R7="In evaluation")>0,'MiT Strom Pipeline'!B7,"") | C140: =IF(('MiT Strom Pipeline'!R7="follow-up")+('MiT Strom Pipeline'!R7="Evaluation")+('MiT Strom Pipeline'!R7="tbd")+('MiT Strom Pipeline'!R7="In evaluation")>0,'MiT Strom Pipeline'!C7,"") | D140: =IF(('MiT Strom Pipeline'!R7="follow-up")+('MiT Strom Pipeline'!R7="Evaluation")+('MiT Strom Pipeline'!R7="tbd")+('MiT Strom Pipeline'!R7="In evaluation")>0,'MiT Strom Pipeline'!D7,"") | E140: =IF(('MiT Strom Pipeline'!R7="follow-up")+('MiT Strom Pipeline'!R7="Evaluation")+('MiT Strom Pipeline'!R7="tbd")+('MiT Strom Pipeline'!R7="In evaluation")>0,'MiT Strom Pipeline'!E7,"") | F140: =IF(('MiT Strom Pipeline'!R7="follow-up")+('MiT Strom Pipeline'!R7="Evaluation")+('MiT Strom Pipeline'!R7="tbd")+('MiT Strom Pipeline'!R7="In evaluation")>0,IF(ISNUMBER('MiT Strom Pipeline'!I7),'MiT Strom Pipeline'!I7,0),"") | G140: =IF(('MiT Strom Pipeline'!R7="follow-up")+('MiT Strom Pipeline'!R7="Evaluation")+('MiT Strom Pipeline'!R7="tbd")+('MiT Strom Pipeline'!R7="In evaluation")>0,IF(ISNUMBER('MiT Strom Pipeline'!Q7),'MiT Strom Pipeline'!Q7,0),"") | H140: =IF(('MiT Strom Pipeline'!R7="follow-up")+('MiT Strom Pipeline'!R7="Evaluation")+('MiT Strom Pipeline'!R7="tbd")+('MiT Strom Pipeline'!R7="In evaluation")>0,'MiT Strom Pipeline'!R7,"") | I140: =IF(('MiT Strom Pipeline'!R7="follow-up")+('MiT Strom Pipeline'!R7="Evaluation")+('MiT Strom Pipeline'!R7="tbd")+('MiT Strom Pipeline'!R7="In evaluation")>0,'MiT Strom Pipeline'!S7,"") | J140: =IF(('MiT Strom Pipeline'!R7="follow-up")+('MiT Strom Pipeline'!R7="Evaluation")+('MiT Strom Pipeline'!R7="tbd")+('MiT Strom Pipeline'!R7="In evaluation")>0,IF(LEN('MiT Strom Pipeline'!V7)>0,LEFT('MiT Strom Pipeline'!V7,55),""),"")
A141: =IF(('MiT Strom Pipeline'!R8="follow-up")+('MiT Strom Pipeline'!R8="Evaluation")+('MiT Strom Pipeline'!R8="tbd")+('MiT Strom Pipeline'!R8="In evaluation")>0,IF(ISNUMBER('MiT Strom Pipeline'!A8),'MiT Strom Pipeline'!A8,""),"") | B141: =IF(('MiT Strom Pipeline'!R8="follow-up")+('MiT Strom Pipeline'!R8="Evaluation")+('MiT Strom Pipeline'!R8="tbd")+('MiT Strom Pipeline'!R8="In evaluation")>0,'MiT Strom Pipeline'!B8,"") | C141: =IF(('MiT Strom Pipeline'!R8="follow-up")+('MiT Strom Pipeline'!R8="Evaluation")+('MiT Strom Pipeline'!R8="tbd")+('MiT Strom Pipeline'!R8="In evaluation")>0,'MiT Strom Pipeline'!C8,"") | D141: =IF(('MiT Strom Pipeline'!R8="follow-up")+('MiT Strom Pipeline'!R8="Evaluation")+('MiT Strom Pipeline'!R8="tbd")+('MiT Strom Pipeline'!R8="In evaluation")>0,'MiT Strom Pipeline'!D8,"") | E141: =IF(('MiT Strom Pipeline'!R8="follow-up")+('MiT Strom Pipeline'!R8="Evaluation")+('MiT Strom Pipeline'!R8="tbd")+('MiT Strom Pipeline'!R8="In evaluation")>0,'MiT Strom Pipeline'!E8,"") | F141: =IF(('MiT Strom Pipeline'!R8="follow-up")+('MiT Strom Pipeline'!R8="Evaluation")+('MiT Strom Pipeline'!R8="tbd")+('MiT Strom Pipeline'!R8="In evaluation")>0,IF(ISNUMBER('MiT Strom Pipeline'!I8),'MiT Strom Pipeline'!I8,0),"") | G141: =IF(('MiT Strom Pipeline'!R8="follow-up")+('MiT Strom Pipeline'!R8="Evaluation")+('MiT Strom Pipeline'!R8="tbd")+('MiT Strom Pipeline'!R8="In evaluation")>0,IF(ISNUMBER('MiT Strom Pipeline'!Q8),'MiT Strom Pipeline'!Q8,0),"") | H141: =IF(('MiT Strom Pipeline'!R8="follow-up")+('MiT Strom Pipeline'!R8="Evaluation")+('MiT Strom Pipeline'!R8="tbd")+('MiT Strom Pipeline'!R8="In evaluation")>0,'MiT Strom Pipeline'!R8,"") | I141: =IF(('MiT Strom Pipeline'!R8="follow-up")+('MiT Strom Pipeline'!R8="Evaluation")+('MiT Strom Pipeline'!R8="tbd")+('MiT Strom Pipeline'!R8="In evaluation")>0,'MiT Strom Pipeline'!S8,"") | J141: =IF(('MiT Strom Pipeline'!R8="follow-up")+('MiT Strom Pipeline'!R8="Evaluation")+('MiT Strom Pipeline'!R8="tbd")+('MiT Strom Pipeline'!R8="In evaluation")>0,IF(LEN('MiT Strom Pipeline'!V8)>0,LEFT('MiT Strom Pipeline'!V8,55),""),"")
A142: =IF(('MiT Strom Pipeline'!R9="follow-up")+('MiT Strom Pipeline'!R9="Evaluation")+('MiT Strom Pipeline'!R9="tbd")+('MiT Strom Pipeline'!R9="In evaluation")>0,IF(ISNUMBER('MiT Strom Pipeline'!A9),'MiT Strom Pipeline'!A9,""),"") | B142: =IF(('MiT Strom Pipeline'!R9="follow-up")+('MiT Strom Pipeline'!R9="Evaluation")+('MiT Strom Pipeline'!R9="tbd")+('MiT Strom Pipeline'!R9="In evaluation")>0,'MiT Strom Pipeline'!B9,"") | C142: =IF(('MiT Strom Pipeline'!R9="follow-up")+('MiT Strom Pipeline'!R9="Evaluation")+('MiT Strom Pipeline'!R9="tbd")+('MiT Strom Pipeline'!R9="In evaluation")>0,'MiT Strom Pipeline'!C9,"") | D142: =IF(('MiT Strom Pipeline'!R9="follow-up")+('MiT Strom Pipeline'!R9="Evaluation")+('MiT Strom Pipeline'!R9="tbd")+('MiT Strom Pipeline'!R9="In evaluation")>0,'MiT Strom Pipeline'!D9,"") | E142: =IF(('MiT Strom Pipeline'!R9="follow-up")+('MiT Strom Pipeline'!R9="Evaluation")+('MiT Strom Pipeline'!R9="tbd")+('MiT Strom Pipeline'!R9="In evaluation")>0,'MiT Strom Pipeline'!E9,"") | F142: =IF(('MiT Strom Pipeline'!R9="follow-up")+('MiT Strom Pipeline'!R9="Evaluation")+('MiT Strom Pipeline'!R9="tbd")+('MiT Strom Pipeline'!R9="In evaluation")>0,IF(ISNUMBER('MiT Strom Pipeline'!I9),'MiT Strom Pipeline'!I9,0),"") | G142: =IF(('MiT Strom Pipeline'!R9="follow-up")+('MiT Strom Pipeline'!R9="Evaluation")+('MiT Strom Pipeline'!R9="tbd")+('MiT Strom Pipeline'!R9="In evaluation")>0,IF(ISNUMBER('MiT Strom Pipeline'!Q9),'MiT Strom Pipeline'!Q9,0),"") | H142: =IF(('MiT Strom Pipeline'!R9="follow-up")+('MiT Strom Pipeline'!R9="Evaluation")+('MiT Strom Pipeline'!R9="tbd")+('MiT Strom Pipeline'!R9="In evaluation")>0,'MiT Strom Pipeline'!R9,"") | I142: =IF(('MiT Strom Pipeline'!R9="follow-up")+('MiT Strom Pipeline'!R9="Evaluation")+('MiT Strom Pipeline'!R9="tbd")+('MiT Strom Pipeline'!R9="In evaluation")>0,'MiT Strom Pipeline'!S9,"") | J142: =IF(('MiT Strom Pipeline'!R9="follow-up")+('MiT Strom Pipeline'!R9="Evaluation")+('MiT Strom Pipeline'!R9="tbd")+('MiT Strom Pipeline'!R9="In evaluation")>0,IF(LEN('MiT Strom Pipeline'!V9)>0,LEFT('MiT Strom Pipeline'!V9,55),""),"")
A143: =IF(('MiT Strom Pipeline'!R10="follow-up")+('MiT Strom Pipeline'!R10="Evaluation")+('MiT Strom Pipeline'!R10="tbd")+('MiT Strom Pipeline'!R10="In evaluation")>0,IF(ISNUMBER('MiT Strom Pipeline'!A10),'MiT Strom Pipeline'!A10,""),"") | B143: =IF(('MiT Strom Pipeline'!R10="follow-up")+('MiT Strom Pipeline'!R10="Evaluation")+('MiT Strom Pipeline'!R10="tbd")+('MiT Strom Pipeline'!R10="In evaluation")>0,'MiT Strom Pipeline'!B10,"") | C143: =IF(('MiT Strom Pipeline'!R10="follow-up")+('MiT Strom Pipeline'!R10="Evaluation")+('MiT Strom Pipeline'!R10="tbd")+('MiT Strom Pipeline'!R10="In evaluation")>0,'MiT Strom Pipeline'!C10,"") | D143: =IF(('MiT Strom Pipeline'!R10="follow-up")+('MiT Strom Pipeline'!R10="Evaluation")+('MiT Strom Pipeline'!R10="tbd")+('MiT Strom Pipeline'!R10="In evaluation")>0,'MiT Strom Pipeline'!D10,"") | E143: =IF(('MiT Strom Pipeline'!R10="follow-up")+('MiT Strom Pipeline'!R10="Evaluation")+('MiT Strom Pipeline'!R10="tbd")+('MiT Strom Pipeline'!R10="In evaluation")>0,'MiT Strom Pipeline'!E10,"") | F143: =IF(('MiT Strom Pipeline'!R10="follow-up")+('MiT Strom Pipeline'!R10="Evaluation")+('MiT Strom Pipeline'!R10="tbd")+('MiT Strom Pipeline'!R10="In evaluation")>0,IF(ISNUMBER('MiT Strom Pipeline'!I10),'MiT Strom Pipeline'!I10,0),"") | G143: =IF(('MiT Strom Pipeline'!R10="follow-up")+('MiT Strom Pipeline'!R10="Evaluation")+('MiT Strom Pipeline'!R10="tbd")+('MiT Strom Pipeline'!R10="In evaluation")>0,IF(ISNUMBER('MiT Strom Pipeline'!Q10),'MiT Strom Pipeline'!Q10,0),"") | H143: =IF(('MiT Strom Pipeline'!R10="follow-up")+('MiT Strom Pipeline'!R10="Evaluation")+('MiT Strom Pipeline'!R10="tbd")+('MiT Strom Pipeline'!R10="In evaluation")>0,'MiT Strom Pipeline'!R10,"") | I143: =IF(('MiT Strom Pipeline'!R10="follow-up")+('MiT Strom Pipeline'!R10="Evaluation")+('MiT Strom Pipeline'!R10="tbd")+('MiT Strom Pipeline'!R10="In evaluation")>0,'MiT Strom Pipeline'!S10,"") | J143: =IF(('MiT Strom Pipeline'!R10="follow-up")+('MiT Strom Pipeline'!R10="Evaluation")+('MiT Strom Pipeline'!R10="tbd")+('MiT Strom Pipeline'!R10="In evaluation")>0,IF(LEN('MiT Strom Pipeline'!V10)>0,LEFT('MiT Strom Pipeline'!V10,55),""),"")
A144: =IF(('MiT Strom Pipeline'!R11="follow-up")+('MiT Strom Pipeline'!R11="Evaluation")+('MiT Strom Pipeline'!R11="tbd")+('MiT Strom Pipeline'!R11="In evaluation")>0,IF(ISNUMBER('MiT Strom Pipeline'!A11),'MiT Strom Pipeline'!A11,""),"") | B144: =IF(('MiT Strom Pipeline'!R11="follow-up")+('MiT Strom Pipeline'!R11="Evaluation")+('MiT Strom Pipeline'!R11="tbd")+('MiT Strom Pipeline'!R11="In evaluation")>0,'MiT Strom Pipeline'!B11,"") | C144: =IF(('MiT Strom Pipeline'!R11="follow-up")+('MiT Strom Pipeline'!R11="Evaluation")+('MiT Strom Pipeline'!R11="tbd")+('MiT Strom Pipeline'!R11="In evaluation")>0,'MiT Strom Pipeline'!C11,"") | D144: =IF(('MiT Strom Pipeline'!R11="follow-up")+('MiT Strom Pipeline'!R11="Evaluation")+('MiT Strom Pipeline'!R11="tbd")+('MiT Strom Pipeline'!R11="In evaluation")>0,'MiT Strom Pipeline'!D11,"") | E144: =IF(('MiT Strom Pipeline'!R11="follow-up")+('MiT Strom Pipeline'!R11="Evaluation")+('MiT Strom Pipeline'!R11="tbd")+('MiT Strom Pipeline'!R11="In evaluation")>0,'MiT Strom Pipeline'!E11,"") | F144: =IF(('MiT Strom Pipeline'!R11="follow-up")+('MiT Strom Pipeline'!R11="Evaluation")+('MiT Strom Pipeline'!R11="tbd")+('MiT Strom Pipeline'!R11="In evaluation")>0,IF(ISNUMBER('MiT Strom Pipeline'!I11),'MiT Strom Pipeline'!I11,0),"") | G144: =IF(('MiT Strom Pipeline'!R11="follow-up")+('MiT Strom Pipeline'!R11="Evaluation")+('MiT Strom Pipeline'!R11="tbd")+('MiT Strom Pipeline'!R11="In evaluation")>0,IF(ISNUMBER('MiT Strom Pipeline'!Q11),'MiT Strom Pipeline'!Q11,0),"") | H144: =IF(('MiT Strom Pipeline'!R11="follow-up")+('MiT Strom Pipeline'!R11="Evaluation")+('MiT Strom Pipeline'!R11="tbd")+('MiT Strom Pipeline'!R11="In evaluation")>0,'MiT Strom Pipeline'!R11,"") | I144: =IF(('MiT Strom Pipeline'!R11="follow-up")+('MiT Strom Pipeline'!R11="Evaluation")+('MiT Strom Pipeline'!R11="tbd")+('MiT Strom Pipeline'!R11="In evaluation")>0,'MiT Strom Pipeline'!S11,"") | J144: =IF(('MiT Strom Pipeline'!R11="follow-up")+('MiT Strom Pipeline'!R11="Evaluation")+('MiT Strom Pipeline'!R11="tbd")+('MiT Strom Pipeline'!R11="In evaluation")>0,IF(LEN('MiT Strom Pipeline'!V11)>0,LEFT('MiT Strom Pipeline'!V11,55),""),"")
A145: =IF(('MiT Strom Pipeline'!R12="follow-up")+('MiT Strom Pipeline'!R12="Evaluation")+('MiT Strom Pipeline'!R12="tbd")+('MiT Strom Pipeline'!R12="In evaluation")>0,IF(ISNUMBER('MiT Strom Pipeline'!A12),'MiT Strom Pipeline'!A12,""),"") -> 8 | B145: =IF(('MiT Strom Pipeline'!R12="follow-up")+('MiT Strom Pipeline'!R12="Evaluation")+('MiT Strom Pipeline'!R12="tbd")+('MiT Strom Pipeline'!R12="In evaluation")>0,'MiT Strom Pipeline'!B12,"") -> Sade CGTH (Schweiz) | C145: =IF(('MiT Strom Pipeline'!R12="follow-up")+('MiT Strom Pipeline'!R12="Evaluation")+('MiT Strom Pipeline'!R12="tbd")+('MiT Strom Pipeline'!R12="In evaluation")>0,'MiT Strom Pipeline'!C12,"") -> GE | D145: =IF(('MiT Strom Pipeline'!R12="follow-up")+('MiT Strom Pipeline'!R12="Evaluation")+('MiT Strom Pipeline'!R12="tbd")+('MiT Strom Pipeline'!R12="In evaluation")>0,'MiT Strom Pipeline'!D12,"") -> Infrastruktur / Bau | E145: =IF(('MiT Strom Pipeline'!R12="follow-up")+('MiT Strom Pipeline'!R12="Evaluation")+('MiT Strom Pipeline'!R12="tbd")+('MiT Strom Pipeline'!R12="In evaluation")>0,'MiT Strom Pipeline'!E12,"") -> 750 kVA Generator | F145: =IF(('MiT Strom Pipeline'!R12="follow-up")+('MiT Strom Pipeline'!R12="Evaluation")+('MiT Strom Pipeline'!R12="tbd")+('MiT Strom Pipeline'!R12="In evaluation")>0,IF(ISNUMBER('MiT Strom Pipeline'!I12),'MiT Strom Pipeline'!I12,0),"") -> 38885 | G145: =IF(('MiT Strom Pipeline'!R12="follow-up")+('MiT Strom Pipeline'!R12="Evaluation")+('MiT Strom Pipeline'!R12="tbd")+('MiT Strom Pipeline'!R12="In evaluation")>0,IF(ISNUMBER('MiT Strom Pipeline'!Q12),'MiT Strom Pipeline'!Q12,0),"") -> 19442.5 | H145: =IF(('MiT Strom Pipeline'!R12="follow-up")+('MiT Strom Pipeline'!R12="Evaluation")+('MiT Strom Pipeline'!R12="tbd")+('MiT Strom Pipeline'!R12="In evaluation")>0,'MiT Strom Pipeline'!R12,"") -> follow-up | I145: =IF(('MiT Strom Pipeline'!R12="follow-up")+('MiT Strom Pipeline'!R12="Evaluation")+('MiT Strom Pipeline'!R12="tbd")+('MiT Strom Pipeline'!R12="In evaluation")>0,'MiT Strom Pipeline'!S12,"") -> 50 | J145: =IF(('MiT Strom Pipeline'!R12="follow-up")+('MiT Strom Pipeline'!R12="Evaluation")+('MiT Strom Pipeline'!R12="tbd")+('MiT Strom Pipeline'!R12="In evaluation")>0,IF(LEN('MiT Strom Pipeline'!V12)>0,LEFT('MiT Strom Pipeline'!V12,55),""),"") -> Auftragsbestätigung anfordern – Entscheid steht bevor
A146: =IF(('MiT Strom Pipeline'!R13="follow-up")+('MiT Strom Pipeline'!R13="Evaluation")+('MiT Strom Pipeline'!R13="tbd")+('MiT Strom Pipeline'!R13="In evaluation")>0,IF(ISNUMBER('MiT Strom Pipeline'!A13),'MiT Strom Pipeline'!A13,""),"") -> 9 | B146: =IF(('MiT Strom Pipeline'!R13="follow-up")+('MiT Strom Pipeline'!R13="Evaluation")+('MiT Strom Pipeline'!R13="tbd")+('MiT Strom Pipeline'!R13="In evaluation")>0,'MiT Strom Pipeline'!B13,"") -> Badermetaux Sàrl (Schweiz) | C146: =IF(('MiT Strom Pipeline'!R13="follow-up")+('MiT Strom Pipeline'!R13="Evaluation")+('MiT Strom Pipeline'!R13="tbd")+('MiT Strom Pipeline'!R13="In evaluation")>0,'MiT Strom Pipeline'!C13,"") -> ZH | D146: =IF(('MiT Strom Pipeline'!R13="follow-up")+('MiT Strom Pipeline'!R13="Evaluation")+('MiT Strom Pipeline'!R13="tbd")+('MiT Strom Pipeline'!R13="In evaluation")>0,'MiT Strom Pipeline'!D13,"") -> Industrie / Metall | E146: =IF(('MiT Strom Pipeline'!R13="follow-up")+('MiT Strom Pipeline'!R13="Evaluation")+('MiT Strom Pipeline'!R13="tbd")+('MiT Strom Pipeline'!R13="In evaluation")>0,'MiT Strom Pipeline'!E13,"") -> 600 kVA Langzeitmiete | F146: =IF(('MiT Strom Pipeline'!R13="follow-up")+('MiT Strom Pipeline'!R13="Evaluation")+('MiT Strom Pipeline'!R13="tbd")+('MiT Strom Pipeline'!R13="In evaluation")>0,IF(ISNUMBER('MiT Strom Pipeline'!I13),'MiT Strom Pipeline'!I13,0),"") -> 500000 | G146: =IF(('MiT Strom Pipeline'!R13="follow-up")+('MiT Strom Pipeline'!R13="Evaluation")+('MiT Strom Pipeline'!R13="tbd")+('MiT Strom Pipeline'!R13="In evaluation")>0,IF(ISNUMBER('MiT Strom Pipeline'!Q13),'MiT Strom Pipeline'!Q13,0),"") -> 50000 | H146: =IF(('MiT Strom Pipeline'!R13="follow-up")+('MiT Strom Pipeline'!R13="Evaluation")+('MiT Strom Pipeline'!R13="tbd")+('MiT Strom Pipeline'!R13="In evaluation")>0,'MiT Strom Pipeline'!R13,"") -> follow-up | I146: =IF(('MiT Strom Pipeline'!R13="follow-up")+('MiT Strom Pipeline'!R13="Evaluation")+('MiT Strom Pipeline'!R13="tbd")+('MiT Strom Pipeline'!R13="In evaluation")>0,'MiT Strom Pipeline'!S13,"") -> 10 | J146: =IF(('MiT Strom Pipeline'!R13="follow-up")+('MiT Strom Pipeline'!R13="Evaluation")+('MiT Strom Pipeline'!R13="tbd")+('MiT Strom Pipeline'!R13="In evaluation")>0,IF(LEN('MiT Strom Pipeline'!V13)>0,LEFT('MiT Strom Pipeline'!V13,55),""),"") -> PQ-Analyse + Langzeitkonzept vorlegen
A147: =IF(('MiT Strom Pipeline'!R14="follow-up")+('MiT Strom Pipeline'!R14="Evaluation")+('MiT Strom Pipeline'!R14="tbd")+('MiT Strom Pipeline'!R14="In evaluation")>0,IF(ISNUMBER('MiT Strom Pipeline'!A14),'MiT Strom Pipeline'!A14,""),"") -> 10 | B147: =IF(('MiT Strom Pipeline'!R14="follow-up")+('MiT Strom Pipeline'!R14="Evaluation")+('MiT Strom Pipeline'!R14="tbd")+('MiT Strom Pipeline'!R14="In evaluation")>0,'MiT Strom Pipeline'!B14,"") -> Murg Flums Energie | C147: =IF(('MiT Strom Pipeline'!R14="follow-up")+('MiT Strom Pipeline'!R14="Evaluation")+('MiT Strom Pipeline'!R14="tbd")+('MiT Strom Pipeline'!R14="In evaluation")>0,'MiT Strom Pipeline'!C14,"") -> SG | D147: =IF(('MiT Strom Pipeline'!R14="follow-up")+('MiT Strom Pipeline'!R14="Evaluation")+('MiT Strom Pipeline'!R14="tbd")+('MiT Strom Pipeline'!R14="In evaluation")>0,'MiT Strom Pipeline'!D14,"") -> EVU / Energie | E147: =IF(('MiT Strom Pipeline'!R14="follow-up")+('MiT Strom Pipeline'!R14="Evaluation")+('MiT Strom Pipeline'!R14="tbd")+('MiT Strom Pipeline'!R14="In evaluation")>0,'MiT Strom Pipeline'!E14,"") -> 250 kVA Generator | F147: =IF(('MiT Strom Pipeline'!R14="follow-up")+('MiT Strom Pipeline'!R14="Evaluation")+('MiT Strom Pipeline'!R14="tbd")+('MiT Strom Pipeline'!R14="In evaluation")>0,IF(ISNUMBER('MiT Strom Pipeline'!I14),'MiT Strom Pipeline'!I14,0),"") -> 96658.69 | G147: =IF(('MiT Strom Pipeline'!R14="follow-up")+('MiT Strom Pipeline'!R14="Evaluation")+('MiT Strom Pipeline'!R14="tbd")+('MiT Strom Pipeline'!R14="In evaluation")>0,IF(ISNUMBER('MiT Strom Pipeline'!Q14),'MiT Strom Pipeline'!Q14,0),"") -> 48329.345 | H147: =IF(('MiT Strom Pipeline'!R14="follow-up")+('MiT Strom Pipeline'!R14="Evaluation")+('MiT Strom Pipeline'!R14="tbd")+('MiT Strom Pipeline'!R14="In evaluation")>0,'MiT Strom Pipeline'!R14,"") -> follow-up | I147: =IF(('MiT Strom Pipeline'!R14="follow-up")+('MiT Strom Pipeline'!R14="Evaluation")+('MiT Strom Pipeline'!R14="tbd")+('MiT Strom Pipeline'!R14="In evaluation")>0,'MiT Strom Pipeline'!S14,"") -> 0.5 | J147: =IF(('MiT Strom Pipeline'!R14="follow-up")+('MiT Strom Pipeline'!R14="Evaluation")+('MiT Strom Pipeline'!R14="tbd")+('MiT Strom Pipeline'!R14="In evaluation")>0,IF(LEN('MiT Strom Pipeline'!V14)>0,LEFT('MiT Strom Pipeline'!V14,55),""),"") -> Bedarfsanalyse, NEA-Konzept vorschlagen, Termin vor Ort
A148: =IF(('MiT Strom Pipeline'!R15="follow-up")+('MiT Strom Pipeline'!R15="Evaluation")+('MiT Strom Pipeline'!R15="tbd")+('MiT Strom Pipeline'!R15="In evaluation")>0,IF(ISNUMBER('MiT Strom Pipeline'!A15),'MiT Strom Pipeline'!A15,""),"") -> 11 | B148: =IF(('MiT Strom Pipeline'!R15="follow-up")+('MiT Strom Pipeline'!R15="Evaluation")+('MiT Strom Pipeline'!R15="tbd")+('MiT Strom Pipeline'!R15="In evaluation")>0,'MiT Strom Pipeline'!B15,"") -> Burkhalter Technics AG | C148: =IF(('MiT Strom Pipeline'!R15="follow-up")+('MiT Strom Pipeline'!R15="Evaluation")+('MiT Strom Pipeline'!R15="tbd")+('MiT Strom Pipeline'!R15="In evaluation")>0,'MiT Strom Pipeline'!C15,"") -> ZH | D148: =IF(('MiT Strom Pipeline'!R15="follow-up")+('MiT Strom Pipeline'!R15="Evaluation")+('MiT Strom Pipeline'!R15="tbd")+('MiT Strom Pipeline'!R15="In evaluation")>0,'MiT Strom Pipeline'!D15,"") -> Elektroinstallation | E148: =IF(('MiT Strom Pipeline'!R15="follow-up")+('MiT Strom Pipeline'!R15="Evaluation")+('MiT Strom Pipeline'!R15="tbd")+('MiT Strom Pipeline'!R15="In evaluation")>0,'MiT Strom Pipeline'!E15,"") -> 150 kVA Generator | F148: =IF(('MiT Strom Pipeline'!R15="follow-up")+('MiT Strom Pipeline'!R15="Evaluation")+('MiT Strom Pipeline'!R15="tbd")+('MiT Strom Pipeline'!R15="In evaluation")>0,IF(ISNUMBER('MiT Strom Pipeline'!I15),'MiT Strom Pipeline'!I15,0),"") -> 0 | G148: =IF(('MiT Strom Pipeline'!R15="follow-up")+('MiT Strom Pipeline'!R15="Evaluation")+('MiT Strom Pipeline'!R15="tbd")+('MiT Strom Pipeline'!R15="In evaluation")>0,IF(ISNUMBER('MiT Strom Pipeline'!Q15),'MiT Strom Pipeline'!Q15,0),"") -> 0 | H148: =IF(('MiT Strom Pipeline'!R15="follow-up")+('MiT Strom Pipeline'!R15="Evaluation")+('MiT Strom Pipeline'!R15="tbd")+('MiT Strom Pipeline'!R15="In evaluation")>0,'MiT Strom Pipeline'!R15,"") -> Evaluation | I148: =IF(('MiT Strom Pipeline'!R15="follow-up")+('MiT Strom Pipeline'!R15="Evaluation")+('MiT Strom Pipeline'!R15="tbd")+('MiT Strom Pipeline'!R15="In evaluation")>0,'MiT Strom Pipeline'!S15,"") -> 40% | J148: =IF(('MiT Strom Pipeline'!R15="follow-up")+('MiT Strom Pipeline'!R15="Evaluation")+('MiT Strom Pipeline'!R15="tbd")+('MiT Strom Pipeline'!R15="In evaluation")>0,IF(LEN('MiT Strom Pipeline'!V15)>0,LEFT('MiT Strom Pipeline'!V15,55),""),"") -> Angebot finalisieren – CBM-Beziehung nutzen, Abrufberei
A149: =IF(('MiT Strom Pipeline'!R16="follow-up")+('MiT Strom Pipeline'!R16="Evaluation")+('MiT Strom Pipeline'!R16="tbd")+('MiT Strom Pipeline'!R16="In evaluation")>0,IF(ISNUMBER('MiT Strom Pipeline'!A16),'MiT Strom Pipeline'!A16,""),"") -> 12 | B149: =IF(('MiT Strom Pipeline'!R16="follow-up")+('MiT Strom Pipeline'!R16="Evaluation")+('MiT Strom Pipeline'!R16="tbd")+('MiT Strom Pipeline'!R16="In evaluation")>0,'MiT Strom Pipeline'!B16,"") -> Show-Concept.ch AG | C149: =IF(('MiT Strom Pipeline'!R16="follow-up")+('MiT Strom Pipeline'!R16="Evaluation")+('MiT Strom Pipeline'!R16="tbd")+('MiT Strom Pipeline'!R16="In evaluation")>0,'MiT Strom Pipeline'!C16,"") -> ZH | D149: =IF(('MiT Strom Pipeline'!R16="follow-up")+('MiT Strom Pipeline'!R16="Evaluation")+('MiT Strom Pipeline'!R16="tbd")+('MiT Strom Pipeline'!R16="In evaluation")>0,'MiT Strom Pipeline'!D16,"") -> Events / Medien | E149: =IF(('MiT Strom Pipeline'!R16="follow-up")+('MiT Strom Pipeline'!R16="Evaluation")+('MiT Strom Pipeline'!R16="tbd")+('MiT Strom Pipeline'!R16="In evaluation")>0,'MiT Strom Pipeline'!E16,"") -> 200 kW Lastbank | F149: =IF(('MiT Strom Pipeline'!R16="follow-up")+('MiT Strom Pipeline'!R16="Evaluation")+('MiT Strom Pipeline'!R16="tbd")+('MiT Strom Pipeline'!R16="In evaluation")>0,IF(ISNUMBER('MiT Strom Pipeline'!I16),'MiT Strom Pipeline'!I16,0),"") -> 0 | G149: =IF(('MiT Strom Pipeline'!R16="follow-up")+('MiT Strom Pipeline'!R16="Evaluation")+('MiT Strom Pipeline'!R16="tbd")+('MiT Strom Pipeline'!R16="In evaluation")>0,IF(ISNUMBER('MiT Strom Pipeline'!Q16),'MiT Strom Pipeline'!Q16,0),"") -> 0 | H149: =IF(('MiT Strom Pipeline'!R16="follow-up")+('MiT Strom Pipeline'!R16="Evaluation")+('MiT Strom Pipeline'!R16="tbd")+('MiT Strom Pipeline'!R16="In evaluation")>0,'MiT Strom Pipeline'!R16,"") -> Evaluation | I149: =IF(('MiT Strom Pipeline'!R16="follow-up")+('MiT Strom Pipeline'!R16="Evaluation")+('MiT Strom Pipeline'!R16="tbd")+('MiT Strom Pipeline'!R16="In evaluation")>0,'MiT Strom Pipeline'!S16,"") -> 35% | J149: =IF(('MiT Strom Pipeline'!R16="follow-up")+('MiT Strom Pipeline'!R16="Evaluation")+('MiT Strom Pipeline'!R16="tbd")+('MiT Strom Pipeline'!R16="In evaluation")>0,IF(LEN('MiT Strom Pipeline'!V16)>0,LEFT('MiT Strom Pipeline'!V16,55),""),"") -> Use-Case klären – Lastbank oder Generator?
A150: =IF(('MiT Strom Pipeline'!R17="follow-up")+('MiT Strom Pipeline'!R17="Evaluation")+('MiT Strom Pipeline'!R17="tbd")+('MiT Strom Pipeline'!R17="In evaluation")>0,IF(ISNUMBER('MiT Strom Pipeline'!A17),'MiT Strom Pipeline'!A17,""),"") | B150: =IF(('MiT Strom Pipeline'!R17="follow-up")+('MiT Strom Pipeline'!R17="Evaluation")+('MiT Strom Pipeline'!R17="tbd")+('MiT Strom Pipeline'!R17="In evaluation")>0,'MiT Strom Pipeline'!B17,"") | C150: =IF(('MiT Strom Pipeline'!R17="follow-up")+('MiT Strom Pipeline'!R17="Evaluation")+('MiT Strom Pipeline'!R17="tbd")+('MiT Strom Pipeline'!R17="In evaluation")>0,'MiT Strom Pipeline'!C17,"") | D150: =IF(('MiT Strom Pipeline'!R17="follow-up")+('MiT Strom Pipeline'!R17="Evaluation")+('MiT Strom Pipeline'!R17="tbd")+('MiT Strom Pipeline'!R17="In evaluation")>0,'MiT Strom Pipeline'!D17,"") | E150: =IF(('MiT Strom Pipeline'!R17="follow-up")+('MiT Strom Pipeline'!R17="Evaluation")+('MiT Strom Pipeline'!R17="tbd")+('MiT Strom Pipeline'!R17="In evaluation")>0,'MiT Strom Pipeline'!E17,"") | F150: =IF(('MiT Strom Pipeline'!R17="follow-up")+('MiT Strom Pipeline'!R17="Evaluation")+('MiT Strom Pipeline'!R17="tbd")+('MiT Strom Pipeline'!R17="In evaluation")>0,IF(ISNUMBER('MiT Strom Pipeline'!I17),'MiT Strom Pipeline'!I17,0),"") | G150: =IF(('MiT Strom Pipeline'!R17="follow-up")+('MiT Strom Pipeline'!R17="Evaluation")+('MiT Strom Pipeline'!R17="tbd")+('MiT Strom Pipeline'!R17="In evaluation")>0,IF(ISNUMBER('MiT Strom Pipeline'!Q17),'MiT Strom Pipeline'!Q17,0),"") | H150: =IF(('MiT Strom Pipeline'!R17="follow-up")+('MiT Strom Pipeline'!R17="Evaluation")+('MiT Strom Pipeline'!R17="tbd")+('MiT Strom Pipeline'!R17="In evaluation")>0,'MiT Strom Pipeline'!R17,"") | I150: =IF(('MiT Strom Pipeline'!R17="follow-up")+('MiT Strom Pipeline'!R17="Evaluation")+('MiT Strom Pipeline'!R17="tbd")+('MiT Strom Pipeline'!R17="In evaluation")>0,'MiT Strom Pipeline'!S17,"") | J150: =IF(('MiT Strom Pipeline'!R17="follow-up")+('MiT Strom Pipeline'!R17="Evaluation")+('MiT Strom Pipeline'!R17="tbd")+('MiT Strom Pipeline'!R17="In evaluation")>0,IF(LEN('MiT Strom Pipeline'!V17)>0,LEFT('MiT Strom Pipeline'!V17,55),""),"")
... A198: =IF(('MiT Strom Pipeline'!R65="follow-up")+('MiT Strom Pipeline'!R65="Evaluation")+('MiT Strom Pipeline'!R65="tbd")+('MiT Strom Pipeline'!R65="In evaluation")>0,IF(ISNUMBER('MiT Strom Pipeline'!A65),'MiT Strom Pipeline'!A65,""),"") | B198: =IF(('MiT Strom Pipeline'!R65="follow-up")+('MiT Strom Pipeline'!R65="Evaluation")+('MiT Strom Pipeline'!R65="tbd")+('MiT Strom Pipeline'!R65="In evaluation")>0,'MiT Strom Pipeline'!B65,"") | C198: =IF(('MiT Strom Pipeline'!R65="follow-up")+('MiT Strom Pipeline'!R65="Evaluation")+('MiT Strom Pipeline'!R65="tbd")+('MiT Strom Pipeline'!R65="In evaluation")>0,'MiT Strom Pipeline'!C65,"") | D198: =IF(('MiT Strom Pipeline'!R65="follow-up")+('MiT Strom Pipeline'!R65="Evaluation")+('MiT Strom Pipeline'!R65="tbd")+('MiT Strom Pipeline'!R65="In evaluation")>0,'MiT Strom Pipeline'!D65,"") | E198: =IF(('MiT Strom Pipeline'!R65="follow-up")+('MiT Strom Pipeline'!R65="Evaluation")+('MiT Strom Pipeline'!R65="tbd")+('MiT Strom Pipeline'!R65="In evaluation")>0,'MiT Strom Pipeline'!E65,"") | F198: =IF(('MiT Strom Pipeline'!R65="follow-up")+('MiT Strom Pipeline'!R65="Evaluation")+('MiT Strom Pipeline'!R65="tbd")+('MiT Strom Pipeline'!R65="In evaluation")>0,IF(ISNUMBER('MiT Strom Pipeline'!I65),'MiT Strom Pipeline'!I65,0),"") | G198: =IF(('MiT Strom Pipeline'!R65="follow-up")+('MiT Strom Pipeline'!R65="Evaluation")+('MiT Strom Pipeline'!R65="tbd")+('MiT Strom Pipeline'!R65="In evaluation")>0,IF(ISNUMBER('MiT Strom Pipeline'!Q65),'MiT Strom Pipeline'!Q65,0),"") | H198: =IF(('MiT Strom Pipeline'!R65="follow-up")+('MiT Strom Pipeline'!R65="Evaluation")+('MiT Strom Pipeline'!R65="tbd")+('MiT Strom Pipeline'!R65="In evaluation")>0,'MiT Strom Pipeline'!R65,"") | I198: =IF(('MiT Strom Pipeline'!R65="follow-up")+('MiT Strom Pipeline'!R65="Evaluation")+('MiT Strom Pipeline'!R65="tbd")+('MiT Strom Pipeline'!R65="In evaluation")>0,'MiT Strom Pipeline'!S65,"") | J198: =IF(('MiT Strom Pipeline'!R65="follow-up")+('MiT Strom Pipeline'!R65="Evaluation")+('MiT Strom Pipeline'!R65="tbd")+('MiT Strom Pipeline'!R65="In evaluation")>0,IF(LEN('MiT Strom Pipeline'!V65)>0,LEFT('MiT Strom Pipeline'!V65,55),""),"")
A199: =IF(('MiT Strom Pipeline'!R66="follow-up")+('MiT Strom Pipeline'!R66="Evaluation")+('MiT Strom Pipeline'!R66="tbd")+('MiT Strom Pipeline'!R66="In evaluation")>0,IF(ISNUMBER('MiT Strom Pipeline'!A66),'MiT Strom Pipeline'!A66,""),"") | B199: =IF(('MiT Strom Pipeline'!R66="follow-up")+('MiT Strom Pipeline'!R66="Evaluation")+('MiT Strom Pipeline'!R66="tbd")+('MiT Strom Pipeline'!R66="In evaluation")>0,'MiT Strom Pipeline'!B66,"") | F199: =IF(('MiT Strom Pipeline'!R66="follow-up")+('MiT Strom Pipeline'!R66="Evaluation")+('MiT Strom Pipeline'!R66="tbd")+('MiT Strom Pipeline'!R66="In evaluation")>0,IF(ISNUMBER('MiT Strom Pipeline'!I66),'MiT Strom Pipeline'!I66,0),"") | G199: =IF(('MiT Strom Pipeline'!R66="follow-up")+('MiT Strom Pipeline'!R66="Evaluation")+('MiT Strom Pipeline'!R66="tbd")+('MiT Strom Pipeline'!R66="In evaluation")>0,IF(ISNUMBER('MiT Strom Pipeline'!Q66),'MiT Strom Pipeline'!Q66,0),"") | H199: =IF(('MiT Strom Pipeline'!R66="follow-up")+('MiT Strom Pipeline'!R66="Evaluation")+('MiT Strom Pipeline'!R66="tbd")+('MiT Strom Pipeline'!R66="In evaluation")>0,'MiT Strom Pipeline'!R66,"") | I199: =IF(('MiT Strom Pipeline'!R66="follow-up")+('MiT Strom Pipeline'!R66="Evaluation")+('MiT Strom Pipeline'!R66="tbd")+('MiT Strom Pipeline'!R66="In evaluation")>0,'MiT Strom Pipeline'!S66,"") | J199: =IF(('MiT Strom Pipeline'!R66="follow-up")+('MiT Strom Pipeline'!R66="Evaluation")+('MiT Strom Pipeline'!R66="tbd")+('MiT Strom Pipeline'!R66="In evaluation")>0,IF(LEN('MiT Strom Pipeline'!V66)>0,LEFT('MiT Strom Pipeline'!V66,55),""),"")
A200: =IF(('MiT Strom Pipeline'!R67="follow-up")+('MiT Strom Pipeline'!R67="Evaluation")+('MiT Strom Pipeline'!R67="tbd")+('MiT Strom Pipeline'!R67="In evaluation")>0,IF(ISNUMBER('MiT Strom Pipeline'!A67),'MiT Strom Pipeline'!A67,""),"") | B200: =IF(('MiT Strom Pipeline'!R67="follow-up")+('MiT Strom Pipeline'!R67="Evaluation")+('MiT Strom Pipeline'!R67="tbd")+('MiT Strom Pipeline'!R67="In evaluation")>0,'MiT Strom Pipeline'!B67,"") | C200: =IF(('MiT Strom Pipeline'!R67="follow-up")+('MiT Strom Pipeline'!R67="Evaluation")+('MiT Strom Pipeline'!R67="tbd")+('MiT Strom Pipeline'!R67="In evaluation")>0,'MiT Strom Pipeline'!C67,"") | D200: =IF(('MiT Strom Pipeline'!R67="follow-up")+('MiT Strom Pipeline'!R67="Evaluation")+('MiT Strom Pipeline'!R67="tbd")+('MiT Strom Pipeline'!R67="In evaluation")>0,'MiT Strom Pipeline'!D67,"") | E200: =IF(('MiT Strom Pipeline'!R67="follow-up")+('MiT Strom Pipeline'!R67="Evaluation")+('MiT Strom Pipeline'!R67="tbd")+('MiT Strom Pipeline'!R67="In evaluation")>0,'MiT Strom Pipeline'!E67,"") | F200: =IF(('MiT Strom Pipeline'!R67="follow-up")+('MiT Strom Pipeline'!R67="Evaluation")+('MiT Strom Pipeline'!R67="tbd")+('MiT Strom Pipeline'!R67="In evaluation")>0,IF(ISNUMBER('MiT Strom Pipeline'!I67),'MiT Strom Pipeline'!I67,0),"") | G200: =IF(('MiT Strom Pipeline'!R67="follow-up")+('MiT Strom Pipeline'!R67="Evaluation")+('MiT Strom Pipeline'!R67="tbd")+('MiT Strom Pipeline'!R67="In evaluation")>0,IF(ISNUMBER('MiT Strom Pipeline'!Q67),'MiT Strom Pipeline'!Q67,0),"") | H200: =IF(('MiT Strom Pipeline'!R67="follow-up")+('MiT Strom Pipeline'!R67="Evaluation")+('MiT Strom Pipeline'!R67="tbd")+('MiT Strom Pipeline'!R67="In evaluation")>0,'MiT Strom Pipeline'!R67,"") | I200: =IF(('MiT Strom Pipeline'!R67="follow-up")+('MiT Strom Pipeline'!R67="Evaluation")+('MiT Strom Pipeline'!R67="tbd")+('MiT Strom Pipeline'!R67="In evaluation")>0,'MiT Strom Pipeline'!S67,"") | J200: =IF(('MiT Strom Pipeline'!R67="follow-up")+('MiT Strom Pipeline'!R67="Evaluation")+('MiT Strom Pipeline'!R67="tbd")+('MiT Strom Pipeline'!R67="In evaluation")>0,IF(LEN('MiT Strom Pipeline'!V67)>0,LEFT('MiT Strom Pipeline'!V67,55),""),"")
A201: 📊 GESAMTTOTAL — Aktive Pipeline (exkl. Declined / LOST) | F201: =SUMIFS('MiT Strom Pipeline'!I$6:I$904,'MiT Strom Pipeline'!R$6:R$904,"WON")+SUMIFS('MiT Strom Pipeline'!I$6:I$904,'MiT Strom Pipeline'!R$6:R$904,"offered")+SUMIFS('MiT Strom Pipeline'!I$6:I$904,'MiT Strom Pipeline'!R$6:R$904,"to be offered")+SUMIFS('MiT Strom Pipeline'!I$6:I$904,'MiT Strom Pipeline'!R$6:R$904,"on hold")+SUMIFS('MiT Strom Pipeline'!I$6:I$904,'MiT Strom Pipeline'!R$6:R$904,"follow-up")+SUMIFS('MiT Strom Pipeline'!I$6:I$904,'MiT Strom Pipeline'!R$6:R$904,"Evaluation")+SUMIFS('MiT Strom Pipeline'!I$6:I$904,'MiT Strom Pipeline'!R$6:R$904,"tbd")+SUMIFS('MiT Strom Pipeline'!I$6:I$904,'MiT Strom Pipeline'!R$6:R$904,"In evaluation") -> 4872116.3
A202: → WON | F202: =SUMIFS('MiT Strom Pipeline'!I$6:I$904,'MiT Strom Pipeline'!R$6:R$904,"WON") -> 333100
A203: → Offerte | F203: =SUMIFS('MiT Strom Pipeline'!I$6:I$904,'MiT Strom Pipeline'!R$6:R$904,"offered")+SUMIFS('MiT Strom Pipeline'!I$6:I$904,'MiT Strom Pipeline'!R$6:R$904,"to be offered")+SUMIFS('MiT Strom Pipeline'!I$6:I$904,'MiT Strom Pipeline'!R$6:R$904,"on hold") -> 3866028.6
A204: → Opportunität | F204: =SUMIFS('MiT Strom Pipeline'!I$6:I$904,'MiT Strom Pipeline'!R$6:R$904,"follow-up")+SUMIFS('MiT Strom Pipeline'!I$6:I$904,'MiT Strom Pipeline'!R$6:R$904,"Evaluation")+SUMIFS('MiT Strom Pipeline'!I$6:I$904,'MiT Strom Pipeline'!R$6:R$904,"tbd")+SUMIFS('MiT Strom Pipeline'!I$6:I$904,'MiT Strom Pipeline'!R$6:R$904,"In evaluation") -> 672987.69
A206: Stand: Mai 2026 | Burak Ücöz | Mobil in Time AG – An Aggreko Company | VERTRAULICH

Sheet 📊 Diagramme
A1: 📊 MiT Strom Schweiz — Diagramme & Visualisierungen
A2: Auto-Update aus «MiT Strom Pipeline» — keine Datenpflege hier nötig
A20: Status-Übersicht | E20: Volumen nach Kanton | I20: Volumen nach Segment
A21: Status | B21: Anzahl | C21: Volumen CHF | E21: Kanton | F21: Volumen CHF | G21: Deals | I21: Segment | J21: Volumen CHF | K21: Deals
A22: ✅ WON | B22: =COUNTIF('MiT Strom Pipeline'!R$6:R$904,"WON") -> 4 | C22: =SUMIFS('MiT Strom Pipeline'!I$6:I$904,'MiT Strom Pipeline'!R$6:R$904,"WON") -> 333100 | E22: AG | F22: =SUMIFS('MiT Strom Pipeline'!I$6:I$904,'MiT Strom Pipeline'!C$6:C$904,"AG") -> 282710 | G22: =COUNTIF('MiT Strom Pipeline'!C$6:C$904,"AG") -> 4 | I22: Events & Kultur | J22: =SUMIFS('MiT Strom Pipeline'!I$6:I$904,'MiT Strom Pipeline'!D$6:D$904,"Events & Kultur") -> 150000 | K22: =COUNTIF('MiT Strom Pipeline'!D$6:D$904,"Events & Kultur") -> 1
A23: 📄 Offerte | B23: =COUNTIF('MiT Strom Pipeline'!R$6:R$904,"offered") -> 11 | C23: =SUMIFS('MiT Strom Pipeline'!I$6:I$904,'MiT Strom Pipeline'!R$6:R$904,"offered") -> 3476028.6 | E23: BE | F23: =SUMIFS('MiT Strom Pipeline'!I$6:I$904,'MiT Strom Pipeline'!C$6:C$904,"BE") -> 39000 | G23: =COUNTIF('MiT Strom Pipeline'!C$6:C$904,"BE") -> 2 | I23: Events & Kongress | J23: =SUMIFS('MiT Strom Pipeline'!I$6:I$904,'MiT Strom Pipeline'!D$6:D$904,"Events & Kongress") -> 0 | K23: =COUNTIF('MiT Strom Pipeline'!D$6:D$904,"Events & Kongress") -> 0
A24: 📝 To Offer | B24: =COUNTIF('MiT Strom Pipeline'!R$6:R$904,"to be offered") -> 0 | C24: =SUMIFS('MiT Strom Pipeline'!I$6:I$904,'MiT Strom Pipeline'!R$6:R$904,"to be offered") -> 0 | E24: BS | F24: =SUMIFS('MiT Strom Pipeline'!I$6:I$904,'MiT Strom Pipeline'!C$6:C$904,"BS") -> 0 | G24: =COUNTIF('MiT Strom Pipeline'!C$6:C$904,"BS") -> 0 | I24: Events / Medien | J24: =SUMIFS('MiT Strom Pipeline'!I$6:I$904,'MiT Strom Pipeline'!D$6:D$904,"Events / Medien") -> 0 | K24: =COUNTIF('MiT Strom Pipeline'!D$6:D$904,"Events / Medien") -> 2
A25: 🎯 Follow-Up | B25: =COUNTIF('MiT Strom Pipeline'!R$6:R$904,"follow-up") -> 3 | C25: =SUMIFS('MiT Strom Pipeline'!I$6:I$904,'MiT Strom Pipeline'!R$6:R$904,"follow-up") -> 635543.69 | E25: GE | F25: =SUMIFS('MiT Strom Pipeline'!I$6:I$904,'MiT Strom Pipeline'!C$6:C$904,"GE") -> 38885 | G25: =COUNTIF('MiT Strom Pipeline'!C$6:C$904,"GE") -> 1 | I25: EVU / Energie | J25: =SUMIFS('MiT Strom Pipeline'!I$6:I$904,'MiT Strom Pipeline'!D$6:D$904,"EVU / Energie") -> 137658.69 | K25: =COUNTIF('MiT Strom Pipeline'!D$6:D$904,"EVU / Energie") -> 2
A26: 🔍 Evaluation (gesamt) | B26: =COUNTIF('MiT Strom Pipeline'!R$6:R$904,"Evaluation")+COUNTIF('MiT Strom Pipeline'!R$6:R$904,"In evaluation") -> 6 | C26: =SUMIFS('MiT Strom Pipeline'!I$6:I$904,'MiT Strom Pipeline'!R$6:R$904,"Evaluation")+SUMIFS('MiT Strom Pipeline'!I$6:I$904,'MiT Strom Pipeline'!R$6:R$904,"In evaluation") -> 37444 | E26: GR | F26: =SUMIFS('MiT Strom Pipeline'!I$6:I$904,'MiT Strom Pipeline'!C$6:C$904,"GR") -> 77325.62 | G26: =COUNTIF('MiT Strom Pipeline'!C$6:C$904,"GR") -> 2 | I26: Industrie / Elektro | J26: =SUMIFS('MiT Strom Pipeline'!I$6:I$904,'MiT Strom Pipeline'!D$6:D$904,"Industrie / Elektro") -> 10000 | K26: =COUNTIF('MiT Strom Pipeline'!D$6:D$904,"Industrie / Elektro") -> 1
A27: 🔍 In Eval. | B27: =COUNTIF('MiT Strom Pipeline'!R$6:R$904,"In evaluation") -> 1 | C27: =SUMIFS('MiT Strom Pipeline'!I$6:I$904,'MiT Strom Pipeline'!R$6:R$904,"In evaluation") -> 0 | E27: LU | F27: =SUMIFS('MiT Strom Pipeline'!I$6:I$904,'MiT Strom Pipeline'!C$6:C$904,"LU") -> 0 | G27: =COUNTIF('MiT Strom Pipeline'!C$6:C$904,"LU") -> 0 | I27: Industrie / Messtechnik | J27: =SUMIFS('MiT Strom Pipeline'!I$6:I$904,'MiT Strom Pipeline'!D$6:D$904,"Industrie / Messtechnik") -> 75769 | K27: =COUNTIF('MiT Strom Pipeline'!D$6:D$904,"Industrie / Messtechnik") -> 3
A28: ⏸ On Hold | B28: =COUNTIF('MiT Strom Pipeline'!R$6:R$904,"on hold") -> 1 | C28: =SUMIFS('MiT Strom Pipeline'!I$6:I$904,'MiT Strom Pipeline'!R$6:R$904,"on hold") -> 390000 | E28: SG | F28: =SUMIFS('MiT Strom Pipeline'!I$6:I$904,'MiT Strom Pipeline'!C$6:C$904,"SG") -> 96658.69 | G28: =COUNTIF('MiT Strom Pipeline'!C$6:C$904,"SG") -> 2 | I28: Industrie / Metall | J28: =SUMIFS('MiT Strom Pipeline'!I$6:I$904,'MiT Strom Pipeline'!D$6:D$904,"Industrie / Metall") -> 500000 | K28: =COUNTIF('MiT Strom Pipeline'!D$6:D$904,"Industrie / Metall") -> 1
A29: ❓ TBD | B29: =COUNTIF('MiT Strom Pipeline'!R$6:R$904,"tbd") -> 7 | C29: =SUMIFS('MiT Strom Pipeline'!I$6:I$904,'MiT Strom Pipeline'!R$6:R$904,"tbd") -> 0 | E29: SH | F29: =SUMIFS('MiT Strom Pipeline'!I$6:I$904,'MiT Strom Pipeline'!C$6:C$904,"SH") -> 2624715 | G29: =COUNTIF('MiT Strom Pipeline'!C$6:C$904,"SH") -> 5 | I29: Industrie / Oberfläche | J29: =SUMIFS('MiT Strom Pipeline'!I$6:I$904,'MiT Strom Pipeline'!D$6:D$904,"Industrie / Oberfläche") -> 13100 | K29: =COUNTIF('MiT Strom Pipeline'!D$6:D$904,"Industrie / Oberfläche") -> 1
A30: ❌ LOST | B30: =COUNTIF('MiT Strom Pipeline'!R$6:R$904,"LOST") -> 1 | C30: =SUMIFS('MiT Strom Pipeline'!I$6:I$904,'MiT Strom Pipeline'!R$6:R$904,"LOST") -> 39000 | E30: SO | F30: =SUMIFS('MiT Strom Pipeline'!I$6:I$904,'MiT Strom Pipeline'!C$6:C$904,"SO") -> 390000 | G30: =COUNTIF('MiT Strom Pipeline'!C$6:C$904,"SO") -> 1 | I30: Industrie | J30: =SUMIFS('MiT Strom Pipeline'!I$6:I$904,'MiT Strom Pipeline'!D$6:D$904,"Industrie") -> 2624715 | K30: =COUNTIF('MiT Strom Pipeline'!D$6:D$904,"Industrie") -> 6
A31: 🚫 Declined | B31: =COUNTIF('MiT Strom Pipeline'!R$6:R$904,"Declined") -> 3 | C31: =SUMIFS('MiT Strom Pipeline'!I$6:I$904,'MiT Strom Pipeline'!R$6:R$904,"Declined") -> 89950 | E31: TG | F31: =SUMIFS('MiT Strom Pipeline'!I$6:I$904,'MiT Strom Pipeline'!C$6:C$904,"TG") -> 150000 | G31: =COUNTIF('MiT Strom Pipeline'!C$6:C$904,"TG") -> 1 | I31: Infrastruktur / Bau | J31: =SUMIFS('MiT Strom Pipeline'!I$6:I$904,'MiT Strom Pipeline'!D$6:D$904,"Infrastruktur / Bau") -> 38885 | K31: =COUNTIF('MiT Strom Pipeline'!D$6:D$904,"Infrastruktur / Bau") -> 1
E32: UR | F32: =SUMIFS('MiT Strom Pipeline'!I$6:I$904,'MiT Strom Pipeline'!C$6:C$904,"UR") -> 0 | G32: =COUNTIF('MiT Strom Pipeline'!C$6:C$904,"UR") -> 1 | I32: Infrastruktur / Bahn | J32: =SUMIFS('MiT Strom Pipeline'!I$6:I$904,'MiT Strom Pipeline'!D$6:D$904,"Infrastruktur / Bahn") -> 0 | K32: =COUNTIF('MiT Strom Pipeline'!D$6:D$904,"Infrastruktur / Bahn") -> 1
E33: VD | F33: =SUMIFS('MiT Strom Pipeline'!I$6:I$904,'MiT Strom Pipeline'!C$6:C$904,"VD") -> 0 | G33: =COUNTIF('MiT Strom Pipeline'!C$6:C$904,"VD") -> 2 | I33: Forschung / Hightech | J33: =SUMIFS('MiT Strom Pipeline'!I$6:I$904,'MiT Strom Pipeline'!D$6:D$904,"Forschung / Hightech") -> 365003 | K33: =COUNTIF('MiT Strom Pipeline'!D$6:D$904,"Forschung / Hightech") -> 1
E34: VS | F34: =SUMIFS('MiT Strom Pipeline'!I$6:I$904,'MiT Strom Pipeline'!C$6:C$904,"VS") -> 0 | G34: =COUNTIF('MiT Strom Pipeline'!C$6:C$904,"VS") -> 1 | I34: Elektroinstallation | J34: =SUMIFS('MiT Strom Pipeline'!I$6:I$904,'MiT Strom Pipeline'!D$6:D$904,"Elektroinstallation") -> 220660 | K34: =COUNTIF('MiT Strom Pipeline'!D$6:D$904,"Elektroinstallation") -> 5
E35: ZG | F35: =SUMIFS('MiT Strom Pipeline'!I$6:I$904,'MiT Strom Pipeline'!C$6:C$904,"ZG") -> 0 | G35: =COUNTIF('MiT Strom Pipeline'!C$6:C$904,"ZG") -> 0 | I35: Hochschule | J35: =SUMIFS('MiT Strom Pipeline'!I$6:I$904,'MiT Strom Pipeline'!D$6:D$904,"Hochschule") -> 0 | K35: =COUNTIF('MiT Strom Pipeline'!D$6:D$904,"Hochschule") -> 1
E36: ZH | F36: =SUMIFS('MiT Strom Pipeline'!I$6:I$904,'MiT Strom Pipeline'!C$6:C$904,"ZH") -> 1301772 | G36: =COUNTIF('MiT Strom Pipeline'!C$6:C$904,"ZH") -> 13 | I36: Kühlung / Konkurrenz | J36: =SUMIFS('MiT Strom Pipeline'!I$6:I$904,'MiT Strom Pipeline'!D$6:D$904,"Kühlung / Konkurrenz") -> 0 | K36: =COUNTIF('MiT Strom Pipeline'!D$6:D$904,"Kühlung / Konkurrenz") -> 1
I37: Immobilien / FM | J37: =SUMIFS('MiT Strom Pipeline'!I$6:I$904,'MiT Strom Pipeline'!D$6:D$904,"Immobilien / FM") -> 390000 | K37: =COUNTIF('MiT Strom Pipeline'!D$6:D$904,"Immobilien / FM") -> 1
I38: Gemeinde | J38: =SUMIFS('MiT Strom Pipeline'!I$6:I$904,'MiT Strom Pipeline'!D$6:D$904,"Gemeinde") -> 0 | K38: =COUNTIF('MiT Strom Pipeline'!D$6:D$904,"Gemeinde") -> 1
I39: Bildung / Forschung | J39: =SUMIFS('MiT Strom Pipeline'!I$6:I$904,'MiT Strom Pipeline'!D$6:D$904,"Bildung / Forschung") -> 0 | K39: =COUNTIF('MiT Strom Pipeline'!D$6:D$904,"Bildung / Forschung") -> 1
I40: Events & Sport | J40: =SUMIFS('MiT Strom Pipeline'!$I$6:$I$904,'MiT Strom Pipeline'!$D$6:$D$904,"Events & Sport") -> 310000 | K40: =COUNTIF('MiT Strom Pipeline'!$D$6:$D$904,"Events & Sport") -> 1
I41: Industrie / Allgemein | J41: =SUMIFS('MiT Strom Pipeline'!$I$6:$I$904,'MiT Strom Pipeline'!$D$6:$D$904,"Industrie / Allgemein") -> 0 | K41: =COUNTIF('MiT Strom Pipeline'!$D$6:$D$904,"Industrie / Allgemein") -> 0
I42: Industrie / Generatoren | J42: =SUMIFS('MiT Strom Pipeline'!$I$6:$I$904,'MiT Strom Pipeline'!$D$6:$D$904,"Industrie / Generatoren") -> 48950 | K42: =COUNTIF('MiT Strom Pipeline'!$D$6:$D$904,"Industrie / Generatoren") -> 1
I43: Ingenieure / Planung | J43: =SUMIFS('MiT Strom Pipeline'!$I$6:$I$904,'MiT Strom Pipeline'!$D$6:$D$904,"Ingenieure / Planung") -> 39000 | K43: =COUNTIF('MiT Strom Pipeline'!$D$6:$D$904,"Ingenieure / Planung") -> 1
I44: Event | J44: =SUMIFS('MiT Strom Pipeline'!$I$6:$I$904,'MiT Strom Pipeline'!$D$6:$D$904,"Event") -> 77325.62 | K44: =COUNTIF('MiT Strom Pipeline'!$D$6:$D$904,"Event") -> 2
I45: tbd | J45: =SUMIFS('MiT Strom Pipeline'!$I$6:$I$904,'MiT Strom Pipeline'!$D$6:$D$904,"tbd") -> 0 | K45: =COUNTIF('MiT Strom Pipeline'!$D$6:$D$904,"tbd") -> 1

Sheet 📄 Report
A1: MiT Strom Schweiz — Sales-Report
A2: Mobil in Time AG · An Aggreko Company · Burak Ücöz
A3: ="Stand: "&TEXT(TODAY(),"DD.MM.YYYY")&" · Auto-Update via Pipeline-Daten" -> Stand: 29.05.2026 · Auto-Update via Pipeline-Daten
A5: Key Performance Indicators
A6: KPI | B6: Wert CHF | C6: Anzahl | D6: Anteil
A7: ✅ WON | B7: =Dashboard!A6 -> 333100 | C7: =Dashboard!A7 -> 4 | D7: =IFERROR(B7/$B$10,0) -> 0.068368647
A8: 📄 Offerte | B8: =Dashboard!D6 -> 3866028.6 | C8: =Dashboard!D7 -> 12 | D8: =IFERROR(B8/$B$10,0) -> 0.79350089
A9: 🎯 Opportunität | B9: =Dashboard!G6 -> 672987.69 | C9: =Dashboard!G7 -> 16 | D9: =IFERROR(B9/$B$10,0) -> 0.13813046
A10: 📊 TOTAL Pipeline | B10: =Dashboard!I6 -> 4872116.3 | C10: =Dashboard!I7 -> 32 | D10: =IFERROR(B10/$B$10,0) -> 1
A13: Top Kantone (nach Volumen)
A14: Rang | B14: Kanton | C14: Volumen CHF | D14: Anzahl Deals | E14: WON-Rate
A15: 1 | B15: =IFERROR(INDEX('Kantone & Segmente'!$A$5:$A$25,MATCH(C15,'Kantone & Segmente'!$D$5:$D$25,0)),"") -> SH | C15: =IFERROR(LARGE('Kantone & Segmente'!$D$5:$D$25,1),0) -> 2624715 | D15: =IFERROR(INDEX('Kantone & Segmente'!$B$5:$B$25,MATCH(C15,'Kantone & Segmente'!$D$5:$D$25,0)),"") -> 5 | E15: =IFERROR(INDEX('Kantone & Segmente'!$G$5:$G$25,MATCH(C15,'Kantone & Segmente'!$D$5:$D$25,0)),"") -> 20% WON
A16: 2 | B16: =IFERROR(INDEX('Kantone & Segmente'!$A$5:$A$25,MATCH(C16,'Kantone & Segmente'!$D$5:$D$25,0)),"") -> ZH | C16: =IFERROR(LARGE('Kantone & Segmente'!$D$5:$D$25,2),0) -> 1301772 | D16: =IFERROR(INDEX('Kantone & Segmente'!$B$5:$B$25,MATCH(C16,'Kantone & Segmente'!$D$5:$D$25,0)),"") -> 13 | E16: =IFERROR(INDEX('Kantone & Segmente'!$G$5:$G$25,MATCH(C16,'Kantone & Segmente'!$D$5:$D$25,0)),"") -> 15% WON
A17: 3 | B17: =IFERROR(INDEX('Kantone & Segmente'!$A$5:$A$25,MATCH(C17,'Kantone & Segmente'!$D$5:$D$25,0)),"") -> SO | C17: =IFERROR(LARGE('Kantone & Segmente'!$D$5:$D$25,3),0) -> 390000 | D17: =IFERROR(INDEX('Kantone & Segmente'!$B$5:$B$25,MATCH(C17,'Kantone & Segmente'!$D$5:$D$25,0)),"") -> 1 | E17: =IFERROR(INDEX('Kantone & Segmente'!$G$5:$G$25,MATCH(C17,'Kantone & Segmente'!$D$5:$D$25,0)),"") -> 0% WON
A18: 4 | B18: =IFERROR(INDEX('Kantone & Segmente'!$A$5:$A$25,MATCH(C18,'Kantone & Segmente'!$D$5:$D$25,0)),"") -> AG | C18: =IFERROR(LARGE('Kantone & Segmente'!$D$5:$D$25,4),0) -> 282710 | D18: =IFERROR(INDEX('Kantone & Segmente'!$B$5:$B$25,MATCH(C18,'Kantone & Segmente'!$D$5:$D$25,0)),"") -> 4 | E18: =IFERROR(INDEX('Kantone & Segmente'!$G$5:$G$25,MATCH(C18,'Kantone & Segmente'!$D$5:$D$25,0)),"") -> 25% WON
A19: 5 | B19: =IFERROR(INDEX('Kantone & Segmente'!$A$5:$A$25,MATCH(C19,'Kantone & Segmente'!$D$5:$D$25,0)),"") -> TG | C19: =IFERROR(LARGE('Kantone & Segmente'!$D$5:$D$25,5),0) -> 150000 | D19: =IFERROR(INDEX('Kantone & Segmente'!$B$5:$B$25,MATCH(C19,'Kantone & Segmente'!$D$5:$D$25,0)),"") -> 1 | E19: =IFERROR(INDEX('Kantone & Segmente'!$G$5:$G$25,MATCH(C19,'Kantone & Segmente'!$D$5:$D$25,0)),"") -> 0% WON
A20: 6 | B20: =IFERROR(INDEX('Kantone & Segmente'!$A$5:$A$25,MATCH(C20,'Kantone & Segmente'!$D$5:$D$25,0)),"") -> SG | C20: =IFERROR(LARGE('Kantone & Segmente'!$D$5:$D$25,6),0) -> 96658.69 | D20: =IFERROR(INDEX('Kantone & Segmente'!$B$5:$B$25,MATCH(C20,'Kantone & Segmente'!$D$5:$D$25,0)),"") -> 2 | E20: =IFERROR(INDEX('Kantone & Segmente'!$G$5:$G$25,MATCH(C20,'Kantone & Segmente'!$D$5:$D$25,0)),"") -> 0% WON
A21: 7 | B21: =IFERROR(INDEX('Kantone & Segmente'!$A$5:$A$25,MATCH(C21,'Kantone & Segmente'!$D$5:$D$25,0)),"") -> GR | C21: =IFERROR(LARGE('Kantone & Segmente'!$D$5:$D$25,7),0) -> 77325.62 | D21: =IFERROR(INDEX('Kantone & Segmente'!$B$5:$B$25,MATCH(C21,'Kantone & Segmente'!$D$5:$D$25,0)),"") -> 2 | E21: =IFERROR(INDEX('Kantone & Segmente'!$G$5:$G$25,MATCH(C21,'Kantone & Segmente'!$D$5:$D$25,0)),"") -> 0% WON
A22: 8 | B22: =IFERROR(INDEX('Kantone & Segmente'!$A$5:$A$25,MATCH(C22,'Kantone & Segmente'!$D$5:$D$25,0)),"") -> BE | C22: =IFERROR(LARGE('Kantone & Segmente'!$D$5:$D$25,8),0) -> 39000 | D22: =IFERROR(INDEX('Kantone & Segmente'!$B$5:$B$25,MATCH(C22,'Kantone & Segmente'!$D$5:$D$25,0)),"") -> 2 | E22: =IFERROR(INDEX('Kantone & Segmente'!$G$5:$G$25,MATCH(C22,'Kantone & Segmente'!$D$5:$D$25,0)),"") -> 0% WON
A23: 9 | B23: =IFERROR(INDEX('Kantone & Segmente'!$A$5:$A$25,MATCH(C23,'Kantone & Segmente'!$D$5:$D$25,0)),"") -> GE | C23: =IFERROR(LARGE('Kantone & Segmente'!$D$5:$D$25,9),0) -> 38885 | D23: =IFERROR(INDEX('Kantone & Segmente'!$B$5:$B$25,MATCH(C23,'Kantone & Segmente'!$D$5:$D$25,0)),"") -> 1 | E23: =IFERROR(INDEX('Kantone & Segmente'!$G$5:$G$25,MATCH(C23,'Kantone & Segmente'!$D$5:$D$25,0)),"") -> 0% WON
A24: 10 | B24: =IFERROR(INDEX('Kantone & Segmente'!$A$5:$A$25,MATCH(C24,'Kantone & Segmente'!$D$5:$D$25,0)),"") -> UR | C24: =IFERROR(LARGE('Kantone & Segmente'!$D$5:$D$25,10),0) -> 0 | D24: =IFERROR(INDEX('Kantone & Segmente'!$B$5:$B$25,MATCH(C24,'Kantone & Segmente'!$D$5:$D$25,0)),"") -> 1 | E24: =IFERROR(INDEX('Kantone & Segmente'!$G$5:$G$25,MATCH(C24,'Kantone & Segmente'!$D$5:$D$25,0)),"") -> 0% WON
A27: Top WON-Deals
A28: Rang | B28: Kunde | C28: Kanton | D28: Segment | E28: Volumen CHF | F28: Marge CHF
A29: 1 | B29: =IFERROR(INDEX('MiT Strom Pipeline'!$B$6:$B$904,MATCH(LARGE('MiT Strom Pipeline'!$Z$6:$Z$904,1),'MiT Strom Pipeline'!$Z$6:$Z$904,0)),"") -> Ice Hockey Championship | C29: =IFERROR(INDEX('MiT Strom Pipeline'!$C$6:$C$904,MATCH(LARGE('MiT Strom Pipeline'!$Z$6:$Z$904,1),'MiT Strom Pipeline'!$Z$6:$Z$904,0)),"") -> ZH | D29: =IFERROR(INDEX('MiT Strom Pipeline'!$D$6:$D$904,MATCH(LARGE('MiT Strom Pipeline'!$Z$6:$Z$904,1),'MiT Strom Pipeline'!$Z$6:$Z$904,0)),"") -> Events & Sport | E29: =IFERROR(LARGE('MiT Strom Pipeline'!$Z$6:$Z$904,1),"") -> 310000 | F29: =IFERROR(INDEX('MiT Strom Pipeline'!$O$6:$O$904,MATCH(LARGE('MiT Strom Pipeline'!$Z$6:$Z$904,1),'MiT Strom Pipeline'!$Z$6:$Z$904,0)),"") -> 75000
A30: 2 | B30: =IFERROR(INDEX('MiT Strom Pipeline'!$B$6:$B$904,MATCH(LARGE('MiT Strom Pipeline'!$Z$6:$Z$904,2),'MiT Strom Pipeline'!$Z$6:$Z$904,0)),"") -> Oerlikon Metco Wohlen | C30: =IFERROR(INDEX('MiT Strom Pipeline'!$C$6:$C$904,MATCH(LARGE('MiT Strom Pipeline'!$Z$6:$Z$904,2),'MiT Strom Pipeline'!$Z$6:$Z$904,0)),"") -> AG | D30: =IFERROR(INDEX('MiT Strom Pipeline'!$D$6:$D$904,MATCH(LARGE('MiT Strom Pipeline'!$Z$6:$Z$904,2),'MiT Strom Pipeline'!$Z$6:$Z$904,0)),"") -> Industrie / Oberfläche | E30: =IFERROR(LARGE('MiT Strom Pipeline'!$Z$6:$Z$904,2),"") -> 13100 | F30: =IFERROR(INDEX('MiT Strom Pipeline'!$O$6:$O$904,MATCH(LARGE('MiT Strom Pipeline'!$Z$6:$Z$904,2),'MiT Strom Pipeline'!$Z$6:$Z$904,0)),"") -> 3000
A31: 3 | B31: =IFERROR(INDEX('MiT Strom Pipeline'!$B$6:$B$904,MATCH(LARGE('MiT Strom Pipeline'!$Z$6:$Z$904,3),'MiT Strom Pipeline'!$Z$6:$Z$904,0)),"") -> Siemens | C31: =IFERROR(INDEX('MiT Strom Pipeline'!$C$6:$C$904,MATCH(LARGE('MiT Strom Pipeline'!$Z$6:$Z$904,3),'MiT Strom Pipeline'!$Z$6:$Z$904,0)),"") -> ZH | D31: =IFERROR(INDEX('MiT Strom Pipeline'!$D$6:$D$904,MATCH(LARGE('MiT Strom Pipeline'!$Z$6:$Z$904,3),'MiT Strom Pipeline'!$Z$6:$Z$904,0)),"") -> Industrie / Elektro | E31: =IFERROR(LARGE('MiT Strom Pipeline'!$Z$6:$Z$904,3),"") -> 10000 | F31: =IFERROR(INDEX('MiT Strom Pipeline'!$O$6:$O$904,MATCH(LARGE('MiT Strom Pipeline'!$Z$6:$Z$904,3),'MiT Strom Pipeline'!$Z$6:$Z$904,0)),"") -> 10000
A32: 4 | B32: =IFERROR(INDEX('MiT Strom Pipeline'!$B$6:$B$904,MATCH(LARGE('MiT Strom Pipeline'!$Z$6:$Z$904,4),'MiT Strom Pipeline'!$Z$6:$Z$904,0)),"") | C32: =IFERROR(INDEX('MiT Strom Pipeline'!$C$6:$C$904,MATCH(LARGE('MiT Strom Pipeline'!$Z$6:$Z$904,4),'MiT Strom Pipeline'!$Z$6:$Z$904,0)),"") | D32: =IFERROR(INDEX('MiT Strom Pipeline'!$D$6:$D$904,MATCH(LARGE('MiT Strom Pipeline'!$Z$6:$Z$904,4),'MiT Strom Pipeline'!$Z$6:$Z$904,0)),"") | E32: =IFERROR(LARGE('MiT Strom Pipeline'!$Z$6:$Z$904,4),"") | F32: =IFERROR(INDEX('MiT Strom Pipeline'!$O$6:$O$904,MATCH(LARGE('MiT Strom Pipeline'!$Z$6:$Z$904,4),'MiT Strom Pipeline'!$Z$6:$Z$904,0)),"")
A33: 5 | B33: =IFERROR(INDEX('MiT Strom Pipeline'!$B$6:$B$904,MATCH(LARGE('MiT Strom Pipeline'!$Z$6:$Z$904,5),'MiT Strom Pipeline'!$Z$6:$Z$904,0)),"") | C33: =IFERROR(INDEX('MiT Strom Pipeline'!$C$6:$C$904,MATCH(LARGE('MiT Strom Pipeline'!$Z$6:$Z$904,5),'MiT Strom Pipeline'!$Z$6:$Z$904,0)),"") | D33: =IFERROR(INDEX('MiT Strom Pipeline'!$D$6:$D$904,MATCH(LARGE('MiT Strom Pipeline'!$Z$6:$Z$904,5),'MiT Strom Pipeline'!$Z$6:$Z$904,0)),"") | E33: =IFERROR(LARGE('MiT Strom Pipeline'!$Z$6:$Z$904,5),"") | F33: =IFERROR(INDEX('MiT Strom Pipeline'!$O$6:$O$904,MATCH(LARGE('MiT Strom Pipeline'!$Z$6:$Z$904,5),'MiT Strom Pipeline'!$Z$6:$Z$904,0)),"")
A34: 6 | B34: =IFERROR(INDEX('MiT Strom Pipeline'!$B$6:$B$904,MATCH(LARGE('MiT Strom Pipeline'!$Z$6:$Z$904,6),'MiT Strom Pipeline'!$Z$6:$Z$904,0)),"") | C34: =IFERROR(INDEX('MiT Strom Pipeline'!$C$6:$C$904,MATCH(LARGE('MiT Strom Pipeline'!$Z$6:$Z$904,6),'MiT Strom Pipeline'!$Z$6:$Z$904,0)),"") | D34: =IFERROR(INDEX('MiT Strom Pipeline'!$D$6:$D$904,MATCH(LARGE('MiT Strom Pipeline'!$Z$6:$Z$904,6),'MiT Strom Pipeline'!$Z$6:$Z$904,0)),"") | E34: =IFERROR(LARGE('MiT Strom Pipeline'!$Z$6:$Z$904,6),"") | F34: =IFERROR(INDEX('MiT Strom Pipeline'!$O$6:$O$904,MATCH(LARGE('MiT Strom Pipeline'!$Z$6:$Z$904,6),'MiT Strom Pipeline'!$Z$6:$Z$904,0)),"")
A35: 7 | B35: =IFERROR(INDEX('MiT Strom Pipeline'!$B$6:$B$904,MATCH(LARGE('MiT Strom Pipeline'!$Z$6:$Z$904,7),'MiT Strom Pipeline'!$Z$6:$Z$904,0)),"") | C35: =IFERROR(INDEX('MiT Strom Pipeline'!$C$6:$C$904,MATCH(LARGE('MiT Strom Pipeline'!$Z$6:$Z$904,7),'MiT Strom Pipeline'!$Z$6:$Z$904,0)),"") | D35: =IFERROR(INDEX('MiT Strom Pipeline'!$D$6:$D$904,MATCH(LARGE('MiT Strom Pipeline'!$Z$6:$Z$904,7),'MiT Strom Pipeline'!$Z$6:$Z$904,0)),"") | E35: =IFERROR(LARGE('MiT Strom Pipeline'!$Z$6:$Z$904,7),"") | F35: =IFERROR(INDEX('MiT Strom Pipeline'!$O$6:$O$904,MATCH(LARGE('MiT Strom Pipeline'!$Z$6:$Z$904,7),'MiT Strom Pipeline'!$Z$6:$Z$904,0)),"")
A36: 8 | B36: =IFERROR(INDEX('MiT Strom Pipeline'!$B$6:$B$904,MATCH(LARGE('MiT Strom Pipeline'!$Z$6:$Z$904,8),'MiT Strom Pipeline'!$Z$6:$Z$904,0)),"") | C36: =IFERROR(INDEX('MiT Strom Pipeline'!$C$6:$C$904,MATCH(LARGE('MiT Strom Pipeline'!$Z$6:$Z$904,8),'MiT Strom Pipeline'!$Z$6:$Z$904,0)),"") | D36: =IFERROR(INDEX('MiT Strom Pipeline'!$D$6:$D$904,MATCH(LARGE('MiT Strom Pipeline'!$Z$6:$Z$904,8),'MiT Strom Pipeline'!$Z$6:$Z$904,0)),"") | E36: =IFERROR(LARGE('MiT Strom Pipeline'!$Z$6:$Z$904,8),"") | F36: =IFERROR(INDEX('MiT Strom Pipeline'!$O$6:$O$904,MATCH(LARGE('MiT Strom Pipeline'!$Z$6:$Z$904,8),'MiT Strom Pipeline'!$Z$6:$Z$904,0)),"")
A37: 9 | B37: =IFERROR(INDEX('MiT Strom Pipeline'!$B$6:$B$904,MATCH(LARGE('MiT Strom Pipeline'!$Z$6:$Z$904,9),'MiT Strom Pipeline'!$Z$6:$Z$904,0)),"") | C37: =IFERROR(INDEX('MiT Strom Pipeline'!$C$6:$C$904,MATCH(LARGE('MiT Strom Pipeline'!$Z$6:$Z$904,9),'MiT Strom Pipeline'!$Z$6:$Z$904,0)),"") | D37: =IFERROR(INDEX('MiT Strom Pipeline'!$D$6:$D$904,MATCH(LARGE('MiT Strom Pipeline'!$Z$6:$Z$904,9),'MiT Strom Pipeline'!$Z$6:$Z$904,0)),"") | E37: =IFERROR(LARGE('MiT Strom Pipeline'!$Z$6:$Z$904,9),"") | F37: =IFERROR(INDEX('MiT Strom Pipeline'!$O$6:$O$904,MATCH(LARGE('MiT Strom Pipeline'!$Z$6:$Z$904,9),'MiT Strom Pipeline'!$Z$6:$Z$904,0)),"")
A38: 10 | B38: =IFERROR(INDEX('MiT Strom Pipeline'!$B$6:$B$904,MATCH(LARGE('MiT Strom Pipeline'!$Z$6:$Z$904,10),'MiT Strom Pipeline'!$Z$6:$Z$904,0)),"") | C38: =IFERROR(INDEX('MiT Strom Pipeline'!$C$6:$C$904,MATCH(LARGE('MiT Strom Pipeline'!$Z$6:$Z$904,10),'MiT Strom Pipeline'!$Z$6:$Z$904,0)),"") | D38: =IFERROR(INDEX('MiT Strom Pipeline'!$D$6:$D$904,MATCH(LARGE('MiT Strom Pipeline'!$Z$6:$Z$904,10),'MiT Strom Pipeline'!$Z$6:$Z$904,0)),"") | E38: =IFERROR(LARGE('MiT Strom Pipeline'!$Z$6:$Z$904,10),"") | F38: =IFERROR(INDEX('MiT Strom Pipeline'!$O$6:$O$904,MATCH(LARGE('MiT Strom Pipeline'!$Z$6:$Z$904,10),'MiT Strom Pipeline'!$Z$6:$Z$904,0)),"")
A40: ↻ Auto-Update aus Pipeline · Sortiert nach Volumen ↓ · Nur WON mit numerischem Volumen
A41: Aktionen (siehe Setup-Sheet für VBA-Buttons in Excel)

Sheet MiT Strom Pipeline
A1: ⚡ MiT Strom Schweiz — Pipeline & Deal Tracking | Mobil in Time AG – An Aggreko Company
A2: ✏️ Nur in diesem Sheet Daten erfassen — Dashboard, CEO Report und Kantone aktualisieren sich automatisch.
A4: ✅ WON Umsatz | C4: =SUMIFS(I$6:I$904,R$6:R$904,"WON") -> 333100 | G4: 📋 Anzahl Deals (aktiv) | I4: =COUNTIF(R$6:R$904,"WON")+COUNTIF(R$6:R$904,"offered")+COUNTIF(R$6:R$904,"to be offered")+COUNTIF(R$6:R$904,"on hold")+COUNTIF(R$6:R$904,"follow-up")+COUNTIF(R$6:R$904,"Evaluation")+COUNTIF(R$6:R$904,"tbd")+COUNTIF(R$6:R$904,"In evaluation") -> 32 | M4: 💼 Offene Pipeline | O4: =SUMIFS(I$6:I$904,R$6:R$904,"offered")+SUMIFS(I$6:I$904,R$6:R$904,"to be offered")+SUMIFS(I$6:I$904,R$6:R$904,"on hold") -> 3866028.6 | S4: ⚖️ Gewichteter Wert | U4: =SUMIFS(I$6:I$904,R$6:R$904,"follow-up")+SUMIFS(I$6:I$904,R$6:R$904,"Evaluation")+SUMIFS(I$6:I$904,R$6:R$904,"tbd")+SUMIFS(I$6:I$904,R$6:R$904,"In evaluation") -> 672987.69
A5: # | B5: Kunde / Unternehmen | C5: Kt. | D5: Segment | E5: Leistung / Fleet | F5: kW | G5: Dauer | H5: Start | I5: Volumen CHF | J5: Equip. CHF | K5: Transport CHF | L5: Treibst. CHF | M5: Technik. CHF | N5: Übrige CHF | O5: Marge CHF | P5: Marge % | Q5: Gew.Wert CHF | R5: Status | S5: Wahr. % | T5: Akquise Typ | U5: USP-Argument | V5: Nächster Schritt | W5: Follow-Up | X5: Notiz intern | Z5: _WON_Sort | AA5: _I_Num
A6: 1 | B6: Ice Hockey Championship | C6: ZH | D6: Events & Sport | E6: 2×600+2×200 kVA | F6: 1600 | G6: 4 Wochen | H6: 02.05.2026 | I6: 310000 | J6: 195000 | K6: 8000 | L6: 12000 | M6: 15000 | N6: 5000 | O6: =IFERROR(I6-(J6+K6+L6+M6+N6),"") -> 75000 | P6: =IFERROR(O6/I6,"") -> 0.24193548 | Q6: =IFERROR(IF(OR(I6="",S6="",S6="tbd"),"tbd",I6*IF(S6<=1,S6,S6/100)),"–") -> 3100 | R6: WON | S6: 100% | T6: Warm – Aggreko | U6: Aggreko Event-Power + Redundanz | V6: ✅ Einsatzplanung läuft – Logistik finalisieren | W6: – | X6: Grossreferenz CH Events – öffentlich nutzbar | Z6: =IF(AND(R6="WON",ISNUMBER(I6)),AA6,"") -> 310000 | AA6: =IFERROR(I6*1,0) -> 310000
A7: 2 | B7: Oerlikon Metco Wohlen | C7: AG | D7: Industrie / Oberfläche | E7: 240 kVA Generator | F7: 240 | G7: 21 Tage | H7: 08.04.2026 | I7: 13100 | J7: 7500 | K7: 800 | L7: 600 | M7: 900 | N7: 300 | O7: =IFERROR(I7-(J7+K7+L7+M7+N7),"") -> 3000 | P7: =IFERROR(O7/I7,"") -> 0.22900763 | Q7: =IFERROR(IF(OR(I7="",S7="",S7="tbd"),"tbd",I7*IF(S7<=1,S7,S7/100)),"–") -> 131 | R7: WON | S7: 100% | T7: Kalt | U7: Schnelle Lieferung 24/7 | V7: ✅ Abgeschlossen – Invoice prüfen, Referenz sichern | W7: – | X7: Erste Referenz Kanton AG | Z7: =IF(AND(R7="WON",ISNUMBER(I7)),AA7,"") -> 13100 | AA7: =IFERROR(I7*1,0) -> 13100
A8: 3 | B8: Siemens | C8: ZH | D8: Industrie / Elektro | E8: 600 kVA Generator | F8: 600 | G8: 21 Tage | H8: tbd | I8: 10000 | O8: =IFERROR(I8-(J8+K8+L8+M8+N8),"") -> 10000 | P8: =IFERROR(O8/I8,"") -> 1 | Q8: =IFERROR(IF(OR(I8="",S8="",S8="tbd"),"tbd",I8*IF(S8<=1,S8,S8/100)),"–") -> 100 | R8: WON | S8: 100% | T8: Warm | U8: Aggreko-Backbone + Verfügbarkeit | V8: ✅ Referenzschreiben anfordern | W8: – | X8: Referenz Industriebereich – sehr wertvoll | Z8: =IF(AND(R8="WON",ISNUMBER(I8)),AA8,"") -> 10000 | AA8: =IFERROR(I8*1,0) -> 10000
A9: 4 | B9: Stagelight – OpenAir Frauenfeld | C9: TG | D9: Events & Kultur | E9: ~500 kVA Generator | F9: 500 | G9: 2 Wochen | H9: Jul. 2026 | I9: 150000 | J9: 88000 | K9: 4500 | L9: 7000 | M9: 9000 | N9: 2000 | O9: =IFERROR(I9-(J9+K9+L9+M9+N9),"") -> 39500 | P9: =IFERROR(O9/I9,"") -> 0.26333333 | Q9: =IFERROR(IF(OR(I9="",S9="",S9="tbd"),"tbd",I9*IF(S9<=1,S9,S9/100)),"–") -> 1350 | R9: offered | S9: 90% | T9: Kalt | U9: Reaktionszeit < 24h, Zuverlässigkeit | V9: Follow-up + Vertragsverhandlung initiieren | W9: 46143 | X9: OpenAir Festival – jährlich → Rahmenvertrag prüfen, Nicht umgehen den Ansprechpartner, Teams Meeting mit Aggreko Deutschland | Z9: =IF(AND(R9="WON",ISNUMBER(I9)),AA9,"") | AA9: =IFERROR(I9*1,0) -> 150000
A10: 6 | B10: Wincasa Solothurn | C10: SO | D10: Immobilien / FM | E10: BESS 1 MWh | F10: 1000 | G10: 365 Tage | H10: 01.05.2026 | I10: 390000 | J10: 240000 | K10: 6000 | M10: 18000 | N10: 8000 | O10: =IFERROR(I10-(J10+K10+L10+M10+N10),"") -> 118000 | P10: =IFERROR(O10/I10,"") -> 0.3025641 | Q10: =IFERROR(IF(OR(I10="",S10="",S10="tbd"),"tbd",I10*IF(S10<=1,S10,S10/100)),"–") -> 1950 | R10: on hold | S10: 50% | T10: Kalt | U10: BESS-Hybridlösung, Energiekostensenkung | V10: Entscheider-Meeting anfordern, Businesscase Energie-ROI | W10: 46143 | X10: Grösster offener Lead – Geduld + ROI-Argumentation | Z10: =IF(AND(R10="WON",ISNUMBER(I10)),AA10,"") | AA10: =IFERROR(I10*1,0) -> 390000
A11: 7 | B11: Avia Volt Suisse AG | C11: ZH | D11: EVU / Energie | E11: 5×200 kVA Generator | F11: 1000 | G11: 30 Tage | H11: 01.05.2026 | I11: 41000 | J11: 24000 | K11: 2000 | L11: 2500 | M11: 3000 | N11: 500 | O11: =IFERROR(I11-(J11+K11+L11+M11+N11),"") -> 9000 | P11: =IFERROR(O11/I11,"") -> 0.2195122 | Q11: =IFERROR(IF(OR(I11="",S11="",S11="tbd"),"tbd",I11*IF(S11<=1,S11,S11/100)),"–") -> 20500 | R11: Declined | S11: 50 | T11: Warm | U11: PQ-Monitoring inkl. – einzigartig in CH | V11: Angebotspräsentation Termin diese Woche | W11: 46143 | X11: EVU mit PQ-Bedarf – USP passt perfekt, Kunde hat kein bedarf zur Zeit | Z11: =IF(AND(R11="WON",ISNUMBER(I11)),AA11,"") | AA11: =IFERROR(I11*1,0) -> 41000
A12: 8 | B12: Sade CGTH (Schweiz) | C12: GE | D12: Infrastruktur / Bau | E12: 750 kVA Generator | F12: 750 | G12: 42 Tage | H12: 06.04.2026 | I12: 38885 | J12: 22000 | K12: 2500 | L12: 3500 | M12: 3000 | N12: 800 | O12: =IFERROR(I12-(J12+K12+L12+M12+N12),"") -> 7085 | P12: =IFERROR(O12/I12,"") -> 0.18220393 | Q12: =IFERROR(IF(OR(I12="",S12="",S12="tbd"),"tbd",I12*IF(S12<=1,S12,S12/100)),"–") -> 19442.5 | R12: follow-up | S12: 50 | T12: Kalt | U12: 24/7 Service, Aggreko-Zuverlässigkeit | V12: Auftragsbestätigung anfordern – Entscheid steht bevor | W12: 46143 | X12: Infrastrukturprojekt Romandie – Türöffner GE/VD | Z12: =IF(AND(R12="WON",ISNUMBER(I12)),AA12,"") | AA12: =IFERROR(I12*1,0) -> 38885
A13: 9 | B13: Badermetaux Sàrl (Schweiz) | C13: ZH | D13: Industrie / Metall | E13: 600 kVA Langzeitmiete | F13: 600 | G13: 5 Jahre | H13: Apr./Mai 2026 | I13: 500000 | J13: 300000 | K13: 5000 | L13: 25000 | M13: 30000 | N13: 10000 | O13: =IFERROR(I13-(J13+K13+L13+M13+N13),"") -> 130000 | P13: =IFERROR(O13/I13,"") -> 0.26 | Q13: =IFERROR(IF(OR(I13="",S13="",S13="tbd"),"tbd",I13*IF(S13<=1,S13,S13/100)),"–") -> 50000 | R13: follow-up | S13: 10 | T13: Kalt | U13: EN 50160-Zertifizierung, all-inclusive | V13: PQ-Analyse + Langzeitkonzept vorlegen | W13: 46143 | X13: 500k CHF Potenzial – langer Zyklus, jetzt Vertrauen aufbauen | Z13: =IF(AND(R13="WON",ISNUMBER(I13)),AA13,"") | AA13: =IFERROR(I13*1,0) -> 500000
A14: 10 | B14: Murg Flums Energie | C14: SG | D14: EVU / Energie | E14: 250 kVA Generator | F14: 250 | G14: 6-12 Monate | H14: Auf Abruf | I14: 96658.69 | J14: 83232 | K14: 3100 | L14: tbd | M14: 870 | N14: 2214 | O14: =IFERROR(I14-(J14+K14+L14+M14+N14),"") | P14: =IFERROR(O14/I14,"") | Q14: =IFERROR(IF(OR(I14="",S14="",S14="tbd"),"tbd",I14*IF(S14<=1,S14,S14/100)),"–") -> 48329.345 | R14: follow-up | S14: 0.5 | T14: Kalt | U14: PQ-Expertise, NIV Art. 13 Compliance | V14: Bedarfsanalyse, NEA-Konzept vorschlagen, Termin vor Ort, Termin vor Ort wahrgenommen | W14: 46136 | X14: EVU SG – NEA-Bedarf qualifizieren, Alles ermittelt und Konzept erstellt und nur noch Offerte schicken mit dem Konzept | Z14: =IF(AND(R14="WON",ISNUMBER(I14)),AA14,"") | AA14: =IFERROR(I14*1,0) -> 96658.69
A15: 11 | B15: Burkhalter Technics AG | C15: ZH | D15: Elektroinstallation | E15: 150 kVA Generator | F15: 150 | G15: 14 Tage | H15: 10.05.2026 | O15: =IFERROR(I15-(J15+K15+L15+M15+N15),"") -> 0 | P15: =IFERROR(O15/I15,"") | Q15: =IFERROR(IF(OR(I15="",S15="",S15="tbd"),"tbd",I15*IF(S15<=1,S15,S15/100)),"–") -> tbd | R15: Evaluation | S15: 40% | T15: Warm – CBM | U15: Bestehende Beziehung, schnelle Lieferung | V15: Angebot finalisieren – CBM-Beziehung nutzen, Abrufbereit und Vertrag unterschreiben | W15: 46143 | X15: Bekannt aus CBM – Cross-Sell PQ-Monitoring möglich | Z15: =IF(AND(R15="WON",ISNUMBER(I15)),AA15,"") | AA15: =IFERROR(I15*1,0) -> 0
A16: 12 | B16: Show-Concept.ch AG | C16: ZH | D16: Events / Medien | E16: 200 kW Lastbank | F16: 200 | G16: tbd | H16: tbd | O16: =IFERROR(I16-(J16+K16+L16+M16+N16),"") -> 0 | P16: =IFERROR(O16/I16,"") | Q16: =IFERROR(IF(OR(I16="",S16="",S16="tbd"),"tbd",I16*IF(S16<=1,S16,S16/100)),"–") -> tbd | R16: Evaluation | S16: 35% | T16: Kalt | U16: Lastbank-Testing – Spezialprodukt MiT | V16: Use-Case klären – Lastbank oder Generator? | W16: 46143 | X16: Spezialanfrage – konkreten Bedarf erst verstehen | Z16: =IF(AND(R16="WON",ISNUMBER(I16)),AA16,"") | AA16: =IFERROR(I16*1,0) -> 0
A17: 13 | B17: Proxima Fusion AG | C17: ZH | D17: Forschung / Hightech | E17: BESS 1 MWh | F17: 1000 | G17: 6-12 Monate | H17: 46204 | I17: 365003 | J17: 326376 | K17: 6900 | L17: - | M17: 1160 | N17: 480 | O17: =IFERROR(I17-(J17+K17+L17+M17+N17),"") | P17: =IFERROR(O17/I17,"") | Q17: =IFERROR(IF(OR(I17="",S17="",S17="tbd"),"tbd",I17*IF(S17<=1,S17,S17/100)),"–") -> 182501.5 | R17: offered | S17: 50 | T17: Kalt | U17: USV + PQ-Monitoring für Präzisionsanlagen | V17: Technisches Gespräch – USV + PQ-Anforderungen klären, Kunde hat Angebot und Technische Ausführung erhalten warten auf Feedback | W17: 46143 | X17: Fusionsforschung – sehr sensibler Strombedarf | Z17: =IF(AND(R17="WON",ISNUMBER(I17)),AA17,"") | AA17: =IFERROR(I17*1,0) -> 365003
A18: 14 | B18: Trafag AG | C18: ZH | D18: Industrie / Messtechnik | E18: 450 kVA Generator | F18: 450 | G18: tbd | H18: tbd | I18: 17300 | O18: =IFERROR(I18-(J18+K18+L18+M18+N18),"") -> 17300 | P18: =IFERROR(O18/I18,"") -> 1 | Q18: =IFERROR(IF(OR(I18="",S18="",S18="tbd"),"tbd",I18*IF(S18<=1,S18,S18/100)),"–") -> 8650 | R18: offered | S18: 0.5 | T18: Kalt | U18: PQ-zertifiziert für sensible Messtechnik | V18: Angebot vorbereiten – PQ-Argument für Messtechnik, Stefanie Hintermann kontaktieren für weiteren Ablauf, Kontakt aufgenommen und warten für die Zusage / Preisklärung | W18: 46143 | X18: Messtechnikhersteller – PQ-Argument optimal, Kunde hat alle Daten und Offerten | Z18: =IF(AND(R18="WON",ISNUMBER(I18)),AA18,"") | AA18: =IFERROR(I18*1,0) -> 17300
A19: 14 | B19: Trafag AG | C19: ZH | D19: Industrie / Messtechnik | E19: BESS 500 kVA | F19: 450 | G19: tbd | H19: tbd | I19: 21025 | O19: =IFERROR(I19-(J19+K19+L19+M19+N19),"") -> 21025 | P19: =IFERROR(O19/I19,"") -> 1 | Q19: =IFERROR(IF(OR(I19="",S19="",S19="tbd"),"tbd",I19*IF(S19<=1,S19,S19/100)),"–") -> 10512.5 | R19: offered | S19: 0.5 | T19: Kalt | U19: PQ-zertifiziert für sensible Messtechnik | V19: Angebot vorbereiten – PQ-Argument für Messtechnik, Stefanie Hintermann kontaktieren für weiteren Ablauf, Kontakt aufgenommen und warten für die Zusage / Preisklärung | W19: 46143 | X19: Messtechnikhersteller – PQ-Argument optimal, Kunde hat alle Daten und Offerten | Z19: =IF(AND(R19="WON",ISNUMBER(I19)),AA19,"") | AA19: =IFERROR(I19*1,0) -> 21025
A20: 14 | B20: Trafag AG | C20: ZH | D20: Industrie / Messtechnik | E20: Kombi 450 kVA Generator / BESS 500 kVA | F20: 450 | G20: tbd | H20: tbd | I20: 37444 | O20: =IFERROR(I20-(J20+K20+L20+M20+N20),"") -> 37444 | P20: =IFERROR(O20/I20,"") -> 1 | Q20: =IFERROR(IF(OR(I20="",S20="",S20="tbd"),"tbd",I20*IF(S20<=1,S20,S20/100)),"–") -> 18722 | R20: Evaluation | S20: 0.5 | T20: Kalt | U20: PQ-zertifiziert für sensible Messtechnik | V20: Angebot vorbereiten – PQ-Argument für Messtechnik, Stefanie Hintermann kontaktieren für weiteren Ablauf, Kontakt aufgenommen und warten für die Zusage / Preisklärung | W20: 46143 | X20: Messtechnikhersteller – PQ-Argument optimal, Kunde hat alle Daten und Offerten | Z20: =IF(AND(R20="WON",ISNUMBER(I20)),AA20,"") | AA20: =IFERROR(I20*1,0) -> 37444
A21: 15 | B21: Gotthard Base Tunnel | C21: UR | D21: Infrastruktur / Bahn | E21: Grossanlage tbd | G21: Jahre | H21: tbd | O21: =IFERROR(I21-(J21+K21+L21+M21+N21),"") -> 0 | P21: =IFERROR(O21/I21,"") | Q21: =IFERROR(IF(OR(I21="",S21="",S21="tbd"),"tbd",I21*IF(S21<=1,S21,S21/100)),"–") -> tbd | R21: In evaluation | S21: 20% | T21: Kalt | U21: NEA-Pflicht, kritische Infra (NIV Art. 13) | V21: Stakeholder identifizieren – AlpTransit/SBB kontaktieren | W21: 46143 | X21: Langfristig strategisch – Türöffner Bahnbereich | Z21: =IF(AND(R21="WON",ISNUMBER(I21)),AA21,"") | AA21: =IFERROR(I21*1,0) -> 0
A22: 16 | B22: Etavis Gossenbacher AG | C22: ZH | D22: Elektroinstallation | E22: 30 kVA USV/Generator | F22: 30 | G22: 90 Tage | H22: tbd | O22: =IFERROR(I22-(J22+K22+L22+M22+N22),"") -> 0 | P22: =IFERROR(O22/I22,"") | Q22: =IFERROR(IF(OR(I22="",S22="",S22="tbd"),"tbd",I22*IF(S22<=1,S22,S22/100)),"–") -> tbd | R22: tbd | S22: 30% | T22: Kalt | U22: Flexibilität, kleines Setup schnell verfügbar | V22: Erstkontakt vertiefen – Bedarf qualifizieren | W22: 46143 | X22: Kleiner Lead – ausbaufähig prüfen | Z22: =IF(AND(R22="WON",ISNUMBER(I22)),AA22,"") | AA22: =IFERROR(I22*1,0) -> 0
A23: 17 | B23: MAS ETH Architektur | C23: ZH | D23: Bildung / Forschung | E23: tbd | G23: tbd | H23: tbd | O23: =IFERROR(I23-(J23+K23+L23+M23+N23),"") -> 0 | P23: =IFERROR(O23/I23,"") | Q23: =IFERROR(IF(OR(I23="",S23="",S23="tbd"),"tbd",I23*IF(S23<=1,S23,S23/100)),"–") -> tbd | R23: tbd | S23: 20% | T23: Kalt | U23: tbd | V23: Bedarf qualifizieren oder disqualifizieren | W23: 46143 | X23: Lead aus Netzwerk – konkreter Bedarf noch unklar | Z23: =IF(AND(R23="WON",ISNUMBER(I23)),AA23,"") | AA23: =IFERROR(I23*1,0) -> 0
A24: 18 | B24: FIP ISA | C24: tbd | D24: tbd | E24: tbd | G24: tbd | H24: tbd | O24: =IFERROR(I24-(J24+K24+L24+M24+N24),"") -> 0 | P24: =IFERROR(O24/I24,"") | Q24: =IFERROR(IF(OR(I24="",S24="",S24="tbd"),"tbd",I24*IF(S24<=1,S24,S24/100)),"–") -> tbd | R24: tbd | S24: 20% | T24: Kalt | U24: tbd | V24: Recherche + Erstkontakt – Firma und Bedarf verstehen | W24: 46143 | X24: Noch nicht qualifiziert | Z24: =IF(AND(R24="WON",ISNUMBER(I24)),AA24,"") | AA24: =IFERROR(I24*1,0) -> 0
A25: 19 | B25: AKSA Würenlos | C25: AG | D25: Industrie / Generatoren | E25: 1500 kVA Generator | F25: 1500 | G25: 19 Tage | H25: 20.04.2026 | I25: 48950 | O25: =IFERROR(I25-(J25+K25+L25+M25+N25),"") -> 48950 | P25: =IFERROR(O25/I25,"") -> 1 | Q25: =IFERROR(IF(OR(I25="",S25="",S25="tbd"),"tbd",I25*IF(S25<=1,S25,S25/100)),"–") -> 0 | R25: Declined | S25: 0% | T25: Kalt | U25: – | V25: Kunden angeschrieben 27.04.2026 | W25: 46143 | X25: Wirtschaftlich nicht tragbar laut Kunde / Warten auf Rückmeldung | Z25: =IF(AND(R25="WON",ISNUMBER(I25)),AA25,"") | AA25: =IFERROR(I25*1,0) -> 48950
A26: 20 | B26: Holinger | C26: BE | D26: Ingenieure / Planung | E26: 250 kVA Generator | F26: 250 | G26: 90 Tage | H26: 07.05.2026 | I26: 39000 | O26: =IFERROR(I26-(J26+K26+L26+M26+N26),"") -> 39000 | P26: =IFERROR(O26/I26,"") -> 1 | Q26: =IFERROR(IF(OR(I26="",S26="",S26="tbd"),"tbd",I26*IF(S26<=1,S26,S26/100)),"–") -> 0 | R26: LOST | S26: 0% | T26: Kalt | U26: – | V26: ❌ Closed – in 12 Monaten wieder kontaktieren | W26: 46143 | X26: Bauherr Entscheid gegen MiT – kein Preisproblem | Z26: =IF(AND(R26="WON",ISNUMBER(I26)),AA26,"") | AA26: =IFERROR(I26*1,0) -> 39000
A27: 21 | B27: X-Event | C27: SH | D27: Events / Medien | E27: 100 kVA Generator | F27: 150 | G27: 1 Tag | H27: 46179 | I27: Sponsoring | J27: Sponsoring | K27: Sponsoring | L27: Sponsoring | M27: Sponsoring | N27: Sponsoring | O27: =IFERROR(I27-(J27+K27+L27+M27+N27),"") | P27: =IFERROR(O27/I27,"") | Q27: =IFERROR(IF(OR(I27="",S27="",S27="tbd"),"tbd",I27*IF(S27<=1,S27,S27/100)),"–") -> – | R27: WON | S27: 1 | T27: Kalt | U27: Flexibilität, kleines Setup schnell verfügbar | V27: Kunde Telefon Kontaktiert und Vor Ort Besichtigung und Aufbauort | W27: 46113 | X27: Kunde hat Angebot angenommen, im Gegenzug Starte er eine Social Media Kampagne für uns und sind jetzt ein Partner für seine Events | Z27: =IF(AND(R27="WON",ISNUMBER(I27)),AA27,"") | AA27: =IFERROR(I27*1,0) -> 0
A28: 22 | B28: Coolworld Rentals | C28: SH | D28: Kühlung / Konkurrenz | E28: 400 kVA Generator | F28: 400 | G28: 21 Tage | H28: 46204 | O28: =IFERROR(I28-(J28+K28+L28+M28+N28),"") -> 0 | P28: =IFERROR(O28/I28,"") | Q28: =IFERROR(IF(OR(I28="",S28="",S28="tbd"),"tbd",I28*IF(S28<=1,S28,S28/100)),"–") -> tbd | R28: offered | S28: 0.5 | T28: Kalt | U28: Flexibilität, Einfaches Setup | V28: Email Kontaktiert, Telefoniert | W28: 46143 | X28: Kunde klärt ab und meldet sich was der Kunde sagt | Z28: =IF(AND(R28="WON",ISNUMBER(I28)),AA28,"") | AA28: =IFERROR(I28*1,0) -> 0
A29: 23 | B29: Etavis Chur | C29: GR | D29: Elektroinstallation | E29: 30 kVA Generator | F29: 30 | G29: tbd | H29: tbd | O29: =IFERROR(I29-(J29+K29+L29+M29+N29),"") -> 0 | P29: =IFERROR(O29/I29,"") | Q29: =IFERROR(IF(OR(I29="",S29="",S29="tbd"),"tbd",I29*IF(S29<=1,S29,S29/100)),"–") -> tbd | R29: Evaluation | S29: 0.1 | T29: Warm – Aggreko | V29: Email Kontaktiert | W29: 46143 | X29: Kunde angeschrieben | Z29: =IF(AND(R29="WON",ISNUMBER(I29)),AA29,"") | AA29: =IFERROR(I29*1,0) -> 0
A30: 24 | B30: Wetzikon | C30: ZH | D30: Gemeinde | E30: tbd (PQ-kritisch) | F30: tbd | G30: tbd | H30: tbd | O30: =IFERROR(I30-(J30+K30+L30+M30+N30),"") -> 0 | P30: =IFERROR(O30/I30,"") | Q30: =IFERROR(IF(OR(I30="",S30="",S30="tbd"),"tbd",I30*IF(S30<=1,S30,S30/100)),"–") -> tbd | R30: Evaluation | S30: tbd | T30: Warm – Aggreko | U30: Machbarkeitsstudei | V30: Email Kontaktiert | W30: 46143 | X30: Kunde angeschrieben | Z30: =IF(AND(R30="WON",ISNUMBER(I30)),AA30,"") | AA30: =IFERROR(I30*1,0) -> 0
