Workbook

Sheet 📊 Dashboard
A1: MiT CRM — Live Dashboard
A2: Auswertungen werden bei jeder Datenänderung in 'Kunden-Datenbank' automatisch aktualisiert.
A4: 📈 Kennzahlen
A5: Kontakte gesamt | B5: Prio A | C5: Prio B | D5: Prio C | E5: Mit E-Mail | F5: Mit Telefon
A6: =COUNTA('📋 Kunden-Datenbank'!$D$4:$D$817) | B6: =COUNTIF('📋 Kunden-Datenbank'!$B$4:$B$817,"A") | C6: =COUNTIF('📋 Kunden-Datenbank'!$B$4:$B$817,"B") | D6: =COUNTIF('📋 Kunden-Datenbank'!$B$4:$B$817,"C") | E6: =COUNTIF('📋 Kunden-Datenbank'!$J$4:$J$817,"?*@?*.?*") | F6: =COUNTA('📋 Kunden-Datenbank'!$K$4:$K$817)
A8: 🏷️ Segment-Verteilung
A9: Segment | B9: Anzahl | C9: % Anteil
A10: EVU/Netzbetreiber | B10: =COUNTIF('📋 Kunden-Datenbank'!$C$4:$C$817,A10) | C10: =IFERROR(B10/COUNTA('📋 Kunden-Datenbank'!$D$4:$D$817),0)
A11: Spital/Klinik | B11: =COUNTIF('📋 Kunden-Datenbank'!$C$4:$C$817,A11) | C11: =IFERROR(B11/COUNTA('📋 Kunden-Datenbank'!$D$4:$D$817),0)
A12: Pharma/Chemie | B12: =COUNTIF('📋 Kunden-Datenbank'!$C$4:$C$817,A12) | C12: =IFERROR(B12/COUNTA('📋 Kunden-Datenbank'!$D$4:$D$817),0)
A13: Rechenzentrum/IT | B13: =COUNTIF('📋 Kunden-Datenbank'!$C$4:$C$817,A13) | C13: =IFERROR(B13/COUNTA('📋 Kunden-Datenbank'!$D$4:$D$817),0)
A14: Industrie/Maschinenbau | B14: =COUNTIF('📋 Kunden-Datenbank'!$C$4:$C$817,A14) | C14: =IFERROR(B14/COUNTA('📋 Kunden-Datenbank'!$D$4:$D$817),0)
A15: Bau/Infrastruktur | B15: =COUNTIF('📋 Kunden-Datenbank'!$C$4:$C$817,A15) | C15: =IFERROR(B15/COUNTA('📋 Kunden-Datenbank'!$D$4:$D$817),0)
A16: Gemeinde/Öffentlich | B16: =COUNTIF('📋 Kunden-Datenbank'!$C$4:$C$817,A16) | C16: =IFERROR(B16/COUNTA('📋 Kunden-Datenbank'!$D$4:$D$817),0)
A17: Bergbahn/Tourismus | B17: =COUNTIF('📋 Kunden-Datenbank'!$C$4:$C$817,A17) | C17: =IFERROR(B17/COUNTA('📋 Kunden-Datenbank'!$D$4:$D$817),0)
A18: Events/Messen | B18: =COUNTIF('📋 Kunden-Datenbank'!$C$4:$C$817,A18) | C18: =IFERROR(B18/COUNTA('📋 Kunden-Datenbank'!$D$4:$D$817),0)
A19: Elektroplaner/Engineering | B19: =COUNTIF('📋 Kunden-Datenbank'!$C$4:$C$817,A19) | C19: =IFERROR(B19/COUNTA('📋 Kunden-Datenbank'!$D$4:$D$817),0)
A20: Forschung/Bildung | B20: =COUNTIF('📋 Kunden-Datenbank'!$C$4:$C$817,A20) | C20: =IFERROR(B20/COUNTA('📋 Kunden-Datenbank'!$D$4:$D$817),0)
A21: Lebensmittel/Food | B21: =COUNTIF('📋 Kunden-Datenbank'!$C$4:$C$817,A21) | C21: =IFERROR(B21/COUNTA('📋 Kunden-Datenbank'!$D$4:$D$817),0)
A23: 🏔️ Kanton-Verteilung
A24: Kanton | B24: Anzahl
A25: ZH | B25: =COUNTIF('📋 Kunden-Datenbank'!$G$4:$G$817,A25)
A26: BE | B26: =COUNTIF('📋 Kunden-Datenbank'!$G$4:$G$817,A26)
A27: LU | B27: =COUNTIF('📋 Kunden-Datenbank'!$G$4:$G$817,A27)
A28: AG | B28: =COUNTIF('📋 Kunden-Datenbank'!$G$4:$G$817,A28)
A29: SG | B29: =COUNTIF('📋 Kunden-Datenbank'!$G$4:$G$817,A29)
A30: GE | B30: =COUNTIF('📋 Kunden-Datenbank'!$G$4:$G$817,A30)
A31: BS | B31: =COUNTIF('📋 Kunden-Datenbank'!$G$4:$G$817,A31)
A32: BL | B32: =COUNTIF('📋 Kunden-Datenbank'!$G$4:$G$817,A32)
A33: SO | B33: =COUNTIF('📋 Kunden-Datenbank'!$G$4:$G$817,A33)
A34: TG | B34: =COUNTIF('📋 Kunden-Datenbank'!$G$4:$G$817,A34)
A35: VS | B35: =COUNTIF('📋 Kunden-Datenbank'!$G$4:$G$817,A35)
A36: VD | B36: =COUNTIF('📋 Kunden-Datenbank'!$G$4:$G$817,A36)
... A50: JU | B50: =COUNTIF('📋 Kunden-Datenbank'!$G$4:$G$817,A50)
D52: 🎯 Pipeline-Status
D53: Status | E53: Anzahl | G53: ⏰ Follow-ups
D54: offen | E54: =COUNTIF('📋 Kunden-Datenbank'!$M$4:$M$817,D54) | G54: Überfällig | H54: =SUMPRODUCT(('📋 Kunden-Datenbank'!$Q$4:$Q$817<TODAY())*('📋 Kunden-Datenbank'!$Q$4:$Q$817<>""))
D55: kontaktiert | E55: =COUNTIF('📋 Kunden-Datenbank'!$M$4:$M$817,D55) | G55: Diese Woche | H55: =SUMPRODUCT(('📋 Kunden-Datenbank'!$Q$4:$Q$817>=TODAY())*('📋 Kunden-Datenbank'!$Q$4:$Q$817<=TODAY()+7))
D56: in Gespräch | E56: =COUNTIF('📋 Kunden-Datenbank'!$M$4:$M$817,D56) | G56: Nächste 30 Tage | H56: =SUMPRODUCT(('📋 Kunden-Datenbank'!$Q$4:$Q$817>=TODAY())*('📋 Kunden-Datenbank'!$Q$4:$Q$817<=TODAY()+30))
D57: Angebot gesendet | E57: =COUNTIF('📋 Kunden-Datenbank'!$M$4:$M$817,D57)
D58: aktiv | E58: =COUNTIF('📋 Kunden-Datenbank'!$M$4:$M$817,D58)
D59: inaktiv | E59: =COUNTIF('📋 Kunden-Datenbank'!$M$4:$M$817,D59)

Sheet 📋 Kunden-Datenbank
A1: MiT CRM — Kunden-Datenbank Vorlage | Mobil in Time AG
A2: → Diese Datei direkt in MiT CRM importieren: Header > '📥 Importieren' > Datei wählen. Spalten werden automatisch erkannt.
A3: Nr. | B3: Prio | C3: Segment | D3: Firmenname * | E3: Ort | F3: PLZ | G3: Kanton | H3: Ansprechpartner | I3: Funktion / Titel | J3: E-Mail | K3: Telefon | L3: Website | M3: Status | N3: Nächster Schritt | O3: Bedarf / kVA | P3: Hauptprodukt | Q3: Follow-up Datum | R3: Notizen | S3: Internes
A4: 1 | B4: A | C4: EVU/Netzbetreiber | D4: AEW Energie AG | E4: Aarau | F4: 5001 | G4: AG | H4: Leiter Netzbetrieb | I4: Dipl. El.-Ing. | J4: info@aew.ch | K4: +41 62 834 21 11 | M4: offen | N4: Netzbetrieb AEW; Revisionskalender anfragen | O4: 0.5 Mio. Kunden; 15 Unterwerke; MS/HS-Revisionen; BESS | P4: BESS | R4: Adr: Obere Vorstadt 2, 5001 Aarau | Kantonaler EVU AG; 0.5 Mio. Kunden | S4: Kantonaler EVU
A5: 2 | B5: A | C5: EVU/Netzbetreiber | D5: Axpo Group AG | E5: Baden | F5: 5401 | G5: AG | H5: Leiter Netzoperationen CH | I5: MSc El.-Ing. | J5: info@axpo.com | K5: +41 56 200 21 11 | M5: offen | N5: Netzbetrieb Axpo Baden; Aggreko-Synergien ansprechen | O5: MS/HS-Revisionen Kraftwerke; Netzersatz 5–20 MVA; BESS; CHF 1'261 Mio. EBIT 2024 | P5: BESS | R5: Adr: Parkstrasse 23, 5401 Baden | Grösstes Energieunternehmen CH | S5: Energiekonzern
A6: 3 | B6: A | C6: EVU/Netzbetreiber | D6: Swissgrid AG | E6: Laufenburg | F6: 5242 | G6: AG | H6: Leiter Grid Operations | I6: MSc El.-Ing. | J6: info@swissgrid.ch | K6: +41 58 580 21 11 | M6: offen | N6: Grid Operations Swissgrid Laufenburg kontaktieren | O6: Übertragungsnetz CH; HS-Revisionen; CHF 317 Mio. Invest 2024 | R6: Adr: Neumattstrasse 19, 5242 Laufenburg | CH-Übertragungsnetzbetreiber | S6: Übertragungsnetz
A7: 4 | B7: A | C7: EVU/Netzbetreiber | D7: Stadtwerk Aarau AG | E7: Aarau | F7: 5001 | G7: AG | H7: Betriebsleiter | I7: Dipl. El.-Ing. | J7: info@stadtwerk-aarau.ch | K7: +41 62 834 41 41 | M7: offen | N7: Betriebsleiter Stadtwerk Aarau kontaktieren | O7: Stadtversorgung Aarau: MS-Revisionen; NEA Stadtgebäude | P7: Wärme | R7: Adr: Buchserstrasse 26, 5001 Aarau | Stadtwerk Aarau; Strom+Gas+Wärme | S7: Stadtwerk
A8: 5 | B8: A | C8: Pharma/Chemie | D8: ABB Schweiz AG (Werke Baden/Dättwil) | E8: Baden | F8: 5400 | G8: AG | H8: Energiemanager Schweiz | I8: MSc El.-Ing. | J8: info@ch.abb.com | K8: +41 58 585 00 00 | M8: offen | N8: Energiemanager ABB Baden; FU-PQ-Pitch Q2 2026 | O8: FU-Prüfstände 5 MVA; 3'850 MA CH; PQ; EMV; ISO 50001; 8 CH-Standorte | P8: Generator | R8: Adr: Bruggerstrasse 72, 5400 Baden | USD 32.85 Mrd. 2024; 104'400 MA ww | S8: Elektrotechnik
A9: 6 | B9: A | C9: Pharma/Chemie | D9: Alstom Schweiz AG (Werk Birr) | E9: Birr | F9: 5242 | G9: AG | H9: Betriebsleiter Elektro | I9: Dipl. El.-Ing. | J9: contact-birr@alstom.com | K9: +41 56 205 20 00 | M9: offen | N9: Betriebsleiter Alstom Birr; Schweiss-PQ-Pitch | O9: Lokomotivbau: Schweissanlagen + Prüfstände 2 MVA; PQ; EMV | R9: Adr: Birmigstrasse 73, 5242 Birr | Schweissen = stärkste NRW CH | S9: Bahnfahrzeuge
A10: 7 | B10: A | C10: Spital/Klinik | D10: Kantonsspital Aarau AG (KSA) | E10: Aarau | F10: 5001 | G10: AG | H10: Leiter TGM | I10: MSc El.-Ing. | J10: info@ksa.ch | K10: +41 62 838 41 41 | M10: offen | N10: TGM KSA; Neubau Dreiklang = Baustrom | O10: NEA 4× 500 kVA; USV OP/ICU; 5'300 MA; Neubau Dreiklang 2026 | P10: USV | R10: Adr: Tellstrasse 25, 5001 Aarau | 5'300 MA; Neubau Dreiklang läuft | S10: Kantonsspital
A11: 8 | B11: A | C11: Spital/Klinik | D11: Kantonsspital Baden AG (KSB) | E11: Baden | F11: 5404 | G11: AG | H11: Betriebsleiter Technik | I11: Dipl. El.-Ing. | J11: info@ksb.ch | K11: +41 56 486 11 11 | M11: offen | N11: Betriebsleiter KSB; Betriebsphase-Vertrag anstreben | O11: NEA 3× 400 kVA; USV OP; Neubau Gesundheitscampus 2023 | P11: USV | R11: Adr: Im Ergel 1, 5404 Baden | Neubau 2023; ETH-Kooperation | S11: Kantonsspital
A12: 9 | B12: A | C12: Bau/Infrastruktur | D12: Kernkraftwerk Beznau AG | E12: Döttingen | F12: 5312 | G12: AG | H12: Technischer Leiter | I12: MSc El.-Ing. | J12: info@beznau.ch | K12: +41 56 268 91 11 | M12: offen | N12: Technischen Leiter KKW Beznau; Revisionsplanung anfragen | O12: Revisionen KKW 1+2; mobile MS-Einspeisung 50–100 MVA; Netzersatz | P12: Generator | R12: Adr: Werkstrasse 1, 5312 Döttingen | Ältestes KKW Welt; grösster MS-Bedarf CH | S12: Kernkraftwerk
A13: 10 | B13: A | C13: Bau/Infrastruktur | D13: Kernkraftwerk Leibstadt AG | E13: Leibstadt | F13: 5325 | G13: AG | H13: Technischer Leiter | I13: MSc El.-Ing. | J13: info@kkl.ch | K13: +41 56 267 71 11 | M13: offen | N13: Technischen Leiter KKL; Revisionsplanung anfragen | O13: Revisionen KKW; mobile MS-Einspeisung 100+ MVA; Netzersatz | P13: Generator | R13: Adr: Kernkraftwerk, 5325 Leibstadt | Leistungsstärkstes KKW CH (1'220 MW) | S13: Kernkraftwerk
A14: 11 | B14: A | C14: Forschung/Bildung | D14: Paul Scherrer Institut (PSI) | E14: Villigen | F14: 5232 | G14: AG | H14: Betriebsleiter Energie | I14: MSc El.-Ing. | J14: info@psi.ch | K14: +41 56 310 21 11 | M14: offen | N14: Betriebsleiter Energie PSI; Forschungsstrasse 111 Villigen | O14: Synchrotron: NEA 10 MVA; USV Beschleuniger; PQ Spezial | P14: USV | R14: Adr: Forschungsstrasse 111, 5232 Villigen | Grösstes Forschungsinstitut CH | S14: Forschungsinstitut
A15: 12 | B15: A | C15: Pharma/Chemie | D15: Siegfried AG (Werk Zofingen) | E15: Zofingen | F15: 4800 | G15: AG | H15: Energiemanager | I15: MSc Chemie | J15: info@siegfried.ch | K15: +41 62 746 11 11 | M15: offen | N15: Energiemanager Siegfried Zofingen; GMP-Pitch | O15: Wirkstoff GMP: NEA 2 MVA; USV; PQ Reinraum; ISO 50001 | P15: USV | R15: Adr: Untere Brühlstrasse 4, 4800 Zofingen | GMP Wirkstoff | S15: Spezialchemie
A16: 13 | B16: A | C16: Pharma/Chemie | D16: DSM-Firmenich (Werk Sisseln) | E16: Sisseln | F16: 4334 | G16: AG | H16: Betriebsleiter Technik | I16: MSc Chemie | J16: info@dsm-firmenich.com | K16: +41 62 866 11 11 | M16: offen | N16: Betriebsleiter DSM Sisseln; Kälte-CRM prüfen | O16: Vitamin GMP: NEA 3 MVA; USV; PQ Reinraum; ISO 50001 | P16: USV | R16: Adr: Hauptstrasse 4, 4334 Sisseln | Vitamin-Weltproduktion; GMP | S16: Vitamine/Pharma
A17: 14 | B17: A | C17: Pharma/Chemie | D17: Dottikon ES Holding AG | E17: Dottikon | F17: 5605 | G17: AG | H17: Betriebsleiter Elektro | I17: MSc Chemie | J17: info@dottikon.com | K17: +41 56 616 81 11 | M17: offen | N17: Betriebsleiter Dottikon ES; GMP-Pitch | O17: Feinchemie GMP: NEA 1.5 MVA; USV; PQ Reaktoren; +18% Wachstum 2024 | P17: USV | R17: Adr: Industriestrasse 17, 5605 Dottikon | CHF 385 Mio. Umsatz; 18% Wachstum | S17: Feinchemie
A18: 15 | B18: A | C18: Pharma/Chemie | D18: Franke Holding AG | E18: Aarburg | F18: 4663 | G18: AG | H18: Betriebsleiter Technik | I18: Dipl. El.-Ing. | J18: info@franke.com | K18: +41 62 787 31 31 | M18: offen | N18: Betriebsleiter Franke Aarburg; FU-PQ-Pitch | O18: Küchensysteme: NEA 1 MVA; FU-Pressanlagen; PQ; ISO 50001 | R18: Adr: Franke-Strasse 2, 4663 Aarburg | Weltführer Küchensysteme | S18: Küchen/Kaffee
A19: 16 | B19: A | C19: Pharma/Chemie | D19: Delica AG (Nestlé FREY) | E19: Buchs AG | F19: 5033 | G19: AG | H19: Betriebsleiter Technik | I19: Techniker | J19: info@delica.ch | K19: +41 62 837 61 11 | M19: offen | N19: MiT-CRM: Delica als Kältekunde prüfen | O19: Schokolade FREY: NEA Kühlkette 1 MVA; FU-Temperierer; ISO 50001 | P19: Kälte | R19: Adr: Javastrasse 20, 5033 Buchs AG | Grösster Schokoladenproduzent CH | S19: Schokolade
A20: 17 | B20: A | C20: Pharma/Chemie | D20: Feldschlösschen Getränke AG | E20: Rheinfelden | F20: 4310 | G20: AG | H20: Betriebsleiter Technik | I20: Dipl. El.-Ing. | J20: info@feldschloesschen.ch | K20: +41 61 835 22 22 | M20: offen | N20: MiT-CRM: Feldschlösschen als Kältekunde prüfen | O20: Brauerei: NEA Kühlkette 2 MVA; FU-Abfüller; ISO 50001 | P20: Kälte | R20: Adr: Theophil Roniger-Strasse, 4310 Rheinfelden | Grösste Brauerei CH | S20: Brauerei
A21: 18 | B21: A | C21: Pharma/Chemie | D21: Lonza AG (Kaiseraugst) | E21: Kaiseraugst | F21: 4303 | G21: AG | H21: Energiemanager | I21: MSc Chemie | J21: energy@lonza.com | K21: +41 61 316 12 34 | M21: offen | N21: Energiemanager Lonza Kaiseraugst; GMP-Pitch | O21: Biopharma GMP: NEA 4 MVA; USV; PQ Reinräume | P21: USV | R21: Adr: Lonzastrasse 1, 4303 Kaiseraugst | GMP-Biopharma; AG/BL-Grenze | S21: Biopharma
A22: 19 | B22: A | C22: Bau/Infrastruktur | D22: ARA Region Aarau AG | E22: Aarau | F22: 5000 | G22: AG | H22: Betriebsleiter ARA | I22: Techniker | J22: info@ara-aarau.ch | K22: +41 62 824 44 80 | M22: offen | N22: Betriebsleiter ARA Aarau; simap.ch Alert AG | O22: NEA-Pflicht 1× 500 kVA; Aare-Gewässerschutz; 24h | P22: Generator | R22: Adr: Aarestrasse 130, 5000 Aarau | Aare-Schutz; Ausschreibungspflicht | S22: ARA
A23: 20 | B23: B | C23: Pharma/Chemie | D23: Rivella AG | E23: Rothrist | F23: 4852 | G23: AG | H23: Betriebsleiter Technik | I23: Techniker | J23: info@rivella.ch | K23: +41 62 785 41 11 | M23: offen | N23: MiT-CRM: Rivella als Kältekunde prüfen | O23: Getränke: NEA Kühlkette 300 kVA; FU-Abfüllanlagen | P23: Kälte | R23: Adr: Sportstrasse 2, 4852 Rothrist | Nationalgetränk CH; Kühlkette | S23: Nahrungsmittel
A24: 21 | B24: B | C24: Pharma/Chemie | D24: Hero AG | E24: Brugg | F24: 5201 | G24: AG | H24: Betriebsleiter Technik | I24: Techniker | J24: info@hero.ch | K24: +41 56 441 21 21 | M24: offen | N24: MiT-CRM: Hero Brugg als Kältekunde prüfen | O24: Nahrungsmittel: NEA Kühlkette 300 kVA; FU-Abfüller | P24: Kälte | R24: Adr: Lindenstrasse 33, 5201 Brugg | Babynahrung+Konfitüren; Kühlkette | S24: Nahrungsmittel
A25: 22 | B25: B | C25: Pharma/Chemie | D25: Novartis F&E Stein AG | E25: Stein AG | F25: 4153 | G25: AG | H25: Facility Manager | I25: MSc El.-Ing. | J25: info@novartis.com | K25: +41 61 705 11 11 | M25: offen | N25: Facility Manager Novartis Stein; GMP-Pitch | O25: F&E GMP: NEA 2 MVA; USV Labors; PQ Reinräume | P25: USV | R25: Adr: Lichstrasse 35, 4153 Stein AG | Novartis F&E; GMP | S25: Forschung Pharma
A26: 23 | B26: B | C26: Rechenzentrum/IT | D26: Aargauische Kantonalbank (AKB) | E26: Aarau | F26: 5001 | G26: AG | H26: Leiter IT-Infrastruktur | I26: MSc Inf. | J26: info@akb.ch | K26: +41 62 835 77 77 | M26: offen | N26: IT-Infrastruktur AKB; FINMA-Argument | O26: USV RZ 2× 200 kVA; NEA; PQ FINMA | P26: USV | R26: Adr: Bahnhofstrasse 58, 5001 Aarau | Kantonalbank AG; FINMA | S26: Kantonalbank
A27: 24 | B27: B | C27: Spital/Klinik | D27: Spital Zofingen AG | E27: Zofingen | F27: 4800 | G27: AG | H27: Betriebsleiter | I27: Techniker | J27: info@spitalzofingen.ch | K27: +41 62 746 15 15 | M27: offen | N27: Betriebsleiter Spital Zofingen; simap.ch AG | O27: NEA 1× 300 kVA; USV; Swiss Medical Network | P27: USV | R27: Adr: Mühlethalstrasse 27, 4800 Zofingen | Swiss Medical Network | S27: Spital
A28: 25 | B28: B | C28: Gemeinde/Öffentlich | D28: Kanton Aargau (Hochbauamt) | E28: Aarau | F28: 5001 | G28: AG | H28: Leiter Hochbauamt | I28: Kantonsbauingenieur | J28: hba@ag.ch | K28: +41 62 835 24 00 | M28: offen | N28: Hochbauamt AG; simap.ch Alert Kanton AG | O28: NEA kantonale Gebäude; 200+ Liegenschaften; Rahmenvertrag | R28: Adr: Entfelderstrasse 22, 5001 Aarau | Industriekanton Nr. 1 CH | S28: Kanton
A29: 26 | B29: B | C29: Bau/Infrastruktur | D29: Eniwa AG RZ Buchs | E29: Aarau | F29: 5000 | G29: AG | H29: Betriebsleiter RZ | I29: Techniker | J29: info@eniwa.ch | K29: +41 62 838 91 11 | M29: offen | N29: Betriebsleiter Eniwa RZ Buchs kontaktieren | O29: RZ Buchs: 200 m² ausgebaut 2023; NEA; USV; PQ | P29: USV | R29: Adr: Obere Vorstadt 2, 5000 Aarau | RZ auf 200 m² ausgebaut 2023 | S29: Rechenzentrum
A30: 27 | B30: B | C30: Spital/Klinik | D30: RehaClinic AG Baden | E30: Baden | F30: 5404 | G30: AG | H30: Betriebsleiter | I30: Techniker | J30: info@rehaclinic.ch | K30: +41 56 485 00 00 | M30: offen | N30: Betriebsleiter RehaClinic Baden kontaktieren | O30: Reha-Klinik: NEA 1× 200 kVA; USV; mehrere AG-Standorte | P30: USV | R30: Adr: Mellingerstrasse 2, 5404 Baden | RehaClinic AG; mehrere Standorte | S30: Rehaklinik
A31: 28 | B31: C | C31: EVU/Netzbetreiber | D31: EW Baden AG | E31: Baden | F31: 5400 | G31: AG | H31: Betriebsleiter | I31: Dipl. El.-Ing. | J31: info@ewbaden.ch | K31: +41 56 200 80 00 | M31: offen | N31: EW Baden; simap.ch Alert Baden AG | O31: Stadtversorgung Baden: MS-Revisionen; NEA Stadtgebäude | R31: Adr: Mellingerstrasse 207, 5400 Baden | Stadtwerk Baden | S31: Stadtwerk Baden
A32: 29 | B32: C | C32: Pharma/Chemie | D32: Zweifel Pomy-Chips AG | E32: Zürich-Höngg | F32: 8049 | G32: AG | H32: Betriebsleiter Technik | I32: Techniker | J32: info@zweifel.ch | K32: +41 44 344 71 11 | M32: offen | N32: MiT-CRM: Zweifel als Kältekunde prüfen | O32: Chips-Produktion: NEA Kühlkette 300 kVA; FU-Frittieranlagen | P32: Kälte | R32: Adr: Erlenmattstrasse 6, 8049 ZH | Zweifel Chips; Kühlkette | S32: Nahrungsmittel
A33: 30 | B33: C | C33: Bau/Infrastruktur | D33: ARA Limeco AG | E33: Dietikon | F33: 8953 | G33: AG | H33: Betriebsleiter | I33: Techniker | J33: info@limeco.ch | K33: +41 43 322 55 00 | M33: offen | N33: Betriebsleiter Limeco; simap.ch Alert | O33: NEA-Pflicht 1× 400 kVA; Limmat-Schutz; interkantonal AG/ZH | P33: Generator | R33: Adr: Reussinsel 1, 8953 Dietikon | ARA Limeco; Limmat-Schutz | S33: ARA
A34: 31 | B34: C | C34: Spital/Klinik | D34: Kantonsspital Muri AG | E34: Muri | F34: 5630 | G34: AG | H34: Betriebsleiter | I34: Techniker | J34: info@spital-muri.ch | K34: +41 56 675 11 11 | M34: offen | N34: Betriebsleiter Spital Muri kontaktieren | O34: NEA 1× 250 kVA; USV; alpine Lage Freiamt | P34: USV | R34: Adr: Kantonsstrasse 32, 5630 Muri | Regionalspital Freiamt AG | S34: Bezirksspital
A35: 32 | B35: C | C35: Pharma/Chemie | D35: Huntsman Advanced Materials (AG-Region) | E35: Dürrenäsch | F35: 5606 | G35: AG | H35: Betriebsleiter Elektro | I35: MSc Chemie | J35: info@huntsman.com | K35: +41 62 768 11 11 | M35: offen | N35: Betriebsleiter Huntsman AG kontaktieren | O35: Chemieproduktion: NEA 1 MVA; FU-Antriebe; PQ; EMV | R35: Adr: Dürrenäsch, 5606 AG | Spezialchemie; FU-Antriebe intensiv | S35: Chemie/Wirkstoffe
A36: 33 | B36: C | C36: Gemeinde/Öffentlich | D36: [MiT AG-Kältekunde Nr. 1] | E36: Aarau | F36: 5000 | G36: AG | H36: Energieverantwortlicher | I36: Betriebsleiter | K36: (MiT-CRM) | M36: offen | N36: MiT-CRM Roberto/Stefan: AG-Kunden ohne Strom sofort prüfen | O36: Strom-Add-on zu MiT-Wärme/Kälte AG | R36: Schnellster Weg: AG-Warmlead Bestandsbasis | S36: Cross-Sell MiT
A37: 34 | B37: A | C37: EVU/Netzbetreiber | D37: EW Appenzell AG (Innerrhoden) | E37: Appenzell | F37: 9050 | G37: AI | H37: Leiter Netzbetrieb | I37: Dipl. El.-Ing. | J37: info@ewa-ai.ch | K37: +41 71 788 16 16 | M37: offen | N37: Netzbetrieb EWA AI; Burgstrasse 1 Appenzell; Revisionskalender | O37: Stromversorgung AI; MS-Revisionen; NEA Gemeindegebäude; Netz AI; Wasserkraft Sitter | P37: Generator | R37: Adr: Burgstrasse 1, 9050 Appenzell | Kantonaler EVU AI; Wasserkraft Sitter | S37: Kantonaler EVU
A38: 35 | B38: A | C38: Spital/Klinik | D38: Kantonsspital AI (Spital Appenzell) | E38: Appenzell | F38: 9050 | G38: AI | H38: Betriebsleiter Technik | I38: Techniker | J38: info@ksai.ch | K38: +41 71 788 41 11 | M38: offen | N38: Betriebsleiter KSAI; Spitalstrasse 4 Appenzell; NIV Art. 13 | O38: NEA 1× 250 kVA; USV OP/ICU; 400 MA; einziges Spital AI; NIV Art. 13 | P38: USV | R38: Adr: Spitalstrasse 4, 9050 Appenzell | Einziges Spital AI; 400 MA; NIV Art. 13 | S38: Kantonsspital
A39: 36 | B39: A | C39: Pharma/Chemie | D39: Brauerei Locher AG (Appenzeller Bier) | E39: Appenzell | F39: 9050 | G39: AI | H39: Betriebsleiter Technik | I39: Dipl. El.-Ing. | J39: info@locher.ch | K39: +41 71 788 01 40 | M39: offen | N39: MiT-CRM: Locher Brauerei als Kältekunde prüfen; Strom+Kälte | O39: Brauerei + Destillerie: NEA Kühlkette 400 kVA; FU-Abfüllanlagen; ISO 50001 | P39: Kälte | R39: Adr: Brauereiplatz 1, 9050 Appenzell | Appenzeller Bier + Alpstein; Kühlkette; 200 MA | S39: Brauerei
A40: 37 | B40: A | C40: Pharma/Chemie | D40: Sennerei Schwende AI (Appenzeller Käse) | E40: Schwende | F40: 9057 | G40: AI | H40: Betriebsleiter | I40: Techniker | J40: info@appenzeller.com | K40: +41 71 799 11 90 | M40: offen | N40: MiT-CRM: Sennerei AI als Kältekunde prüfen | O40: Käse-Produktion AI: NEA Kühlkette 200 kVA; ISO 50001; Appenzeller Sorte | P40: Kälte | R40: Adr: Schwende, 9057 AI | Appenzeller Käse Sorte; Kühlkette; Handcheese | S40: Käserei/Dairy
A41: 38 | B41: A | C41: Bergbahn/Tourismus | D41: Bergbahn Ebenalp AG (AI-Seite) | E41: Weissbad | F41: 9057 | G41: AI | H41: Betriebsleiter | I41: Techniker | J41: info@ebenalp.ch | K41: +41 71 799 11 64 | M41: offen | N41: Betriebsleiter Ebenalp; Herbst-Revisionsfenster AI | O41: Ebenalp Bergbahn 1'644 m: NEA + Generator 150 kVA; FU-Gondeln; alpine AI-Lage | P41: Generator | R41: Adr: Talstation Weissbad, 9057 AI | Ebenalp 1'644 m; Wildkirchli; alpine AI-Lage | S41: Bergbahn Ebenalp
A42: 39 | B42: A | C42: Bergbahn/Tourismus | D42: Hotel Hof Weissbad (Kneipp-Kur) | E42: Weissbad | F42: 9057 | G42: AI | H42: Facility Manager | I42: Ing. | J42: info@hofweissbad.ch | K42: +41 71 798 89 89 | M42: offen | N42: Facility Manager Hotel Hof Weissbad; alpine Isolation-Pitch | O42: 4-Sterne Kurhotel alpine Lage: NEA 1× 200 kVA; USV; Kneipp-Tradition AI | P42: USV | R42: Adr: Weissbad 110, 9057 AI | 4-Sterne Kurhotel; Kneipp; alpine AI-Lage | S42: Hotel/Kur
A43: 40 | B43: A | C43: Gemeinde/Öffentlich | D43: Kanton Appenzell Innerrhoden (Bauamt) | E43: Appenzell | F43: 9050 | G43: AI | H43: Leiter Bauamt | I43: Kantonsbauingenieur | J43: info@ai.ch | K43: +41 71 788 95 11 | M43: offen | N43: Bauamt AI; Hauptgasse 4 Appenzell; simap.ch Alert AI | O43: NEA kantonale Gebäude AI; 50+ Liegenschaften; Rahmenvertrag AI | R43: Adr: Hauptgasse 4, 9050 Appenzell | Kanton AI; kleinster Kanton CH; 50+ Liegenschaften | S43: Kanton AI
A44: 41 | B44: A | C44: Bau/Infrastruktur | D44: ARA AI (Sitter-Schutz) | E44: Appenzell | F44: 9050 | G44: AI | H44: Betriebsleiter ARA | I44: Techniker | J44: info@ara-ai.ch | K44: +41 71 788 40 22 | M44: offen | N44: Betriebsleiter ARA AI; simap.ch Alert AI | O44: NEA-Pflicht 1× 150 kVA; Sitter-Gewässerschutz; 24h | P44: Generator | R44: Adr: Appenzell, 9050 AI | Sitter-Schutz; Ausschreibungspflicht | S44: ARA Sitter
A45: 42 | B45: B | C45: Pharma/Chemie | D45: Sturzenegger Stickerei AG (AI-Tradition) | E45: Appenzell | F45: 9050 | G45: AI | H45: Betriebsleiter | I45: Techniker | J45: info@sturzenegger.ch | K45: +41 71 787 43 43 | M45: offen | N45: Betriebsleiter Sturzenegger; Stickerei AI; FU-PQ-Pitch | O45: Stickerei-Produktion: NEA 200 kVA; FU-Stickmaschinen; PQ; EMV; UNESCO-Immateriell | R45: Adr: Appenzell, 9050 AI | Appenzeller Stickerei; UNESCO-Immateriell; FU-Stickmaschinen | S45: Textil/Stickerei
A46: 43 | B46: B | C46: Bergbahn/Tourismus | D46: Kronbergbahn AG | E46: Jakobsbad | F46: 9108 | G46: AI | H46: Betriebsleiter | I46: Techniker | J46: info@kronberg.ch | K46: +41 71 798 11 11 | M46: offen | N46: Betriebsleiter Kronberg; Herbst-Revisionsfenster AI | O46: Kronberg 1'663 m: NEA + Generator 150 kVA; FU-Gondeln; alpine AI-Lage; Kletterwald | P46: Generator | R46: Adr: Jakobsbad, 9108 AI | Kronberg 1'663 m; alpine AI-Lage; Kletterwald | S46: Bergbahn Kronberg
A47: 44 | B47: B | C47: Pharma/Chemie | D47: Möhl AG (Appenzeller Most) | E47: Arbon | F47: 9320 | G47: AI | H47: Betriebsleiter Technik | I47: Techniker | J47: info@moehl.ch | K47: +41 71 447 40 74 | M47: offen | N47: MiT-CRM: Möhl als Kältekunde prüfen; Strom+Kälte | O47: Most + Säfte Produktion: NEA Kühlkette 200 kVA; FU-Abfüller; ISO 50001 | P47: Kälte | R47: Adr: Arbon TG (AI-Region) | Appenzeller Most; Kühlkette; Cross-Sell | S47: Nahrungsmittel
A48: 45 | B48: C | C48: Pharma/Chemie | D48: Zimmerei Manser AG (AI-Tradition) | E48: Appenzell | F48: 9050 | G48: AI | H48: Betriebsleiter | I48: Techniker | J48: info@manser.ch | K48: +41 71 787 42 42 | M48: offen | N48: Betriebsleiter Manser AI; Holzbau-Pitch | O48: Holzbau-Produktion AI: NEA 150 kVA; FU-Hobelmaschinen; PQ | P48: Generator | R48: Adr: Appenzell, 9050 AI | Appenzeller Holzbau; FU-Hobelmaschinen | S48: Holzverarbeitung
A49: 46 | B49: C | C49: Gemeinde/Öffentlich | D49: [MiT AI-Kältekunde Nr. 1] | E49: Appenzell | F49: 9050 | G49: AI | H49: Energieverantwortlicher | I49: Betriebsleiter | K49: (MiT-CRM) | M49: offen | N49: MiT-CRM Roberto/Stefan: AI-Kunden ohne Strom prüfen | O49: Strom-Add-on MiT-Wärme/Kälte AI | R49: Locher Brauerei + Sennerei AI = Kühlkette Cross-Sell = schnellster Einstieg AI | S49: Cross-Sell MiT
A50: 47 | B50: A | C50: Bergbahn/Tourismus | D50: Säntisbahn AG (AI-Seite) | E50: Schwägalp | F50: 9107 | G50: AI | H50: Betriebsleiter Technik | I50: Techniker | J50: info@saentisbahn.ch | K50: +41 71 365 65 65 | M50: offen | N50: Betriebsleiter Säntisbahn; Herbst-Revisionsfenster; alpine Pitch AI/AR | O50: Säntis 2'502 m: NEA + Generator 300 kVA; FU-Gondeln; alpine Isolation AI/AR-Grenze | P50: Generator | R50: Adr: Schwägalp, 9107 AI/AR | Säntis 2'502 m; bekanntester Berg Ostschweiz | S50: Gonten / Appenzell
A51: 48 | B51: A | C51: Pharma/Chemie | D51: Stickerei-Werkstätten Appenzell (Cluster) | E51: Appenzell | F51: 9050 | G51: AI | H51: Betriebsleiter | I51: Techniker | J51: info@stickereicluster.ch | K51: +41 71 787 40 40 | M51: offen | N51: Betriebsleiter Stickerei-Cluster; Appenzell; UNESCO-Argument; FU-PQ | O51: Stickerei-Cluster: FU-Stickmaschinen 300 kVA; PQ; EMV; UNESCO-Immaterielles Erbe | R51: Adr: Appenzell, 9050 AI | Stickerei UNESCO-Erbe; FU-Stickmaschinen intensiv | S51: Stickerei UNESCO
A52: 49 | B52: A | C52: Bergbahn/Tourismus | D52: Hotel Appenzell (4-Sterne Marktplatz) | E52: Appenzell | F52: 9050 | G52: AI | H52: Facility Manager | I52: Techniker | J52: info@hotel-appenzell.ch | K52: +41 71 788 15 15 | M52: offen | N52: Facility Manager Hotel Appenzell; Hauptgasse 37 Appenzell; 4-Sterne-Pitch | O52: 4-Sterne Hotel Appenzell: NEA 1× 150 kVA; USV; Marktplatz; 50 Zimmer | P52: USV | R52: Adr: Hauptgasse 37, 9050 Appenzell | 4-Sterne Marktplatz; 50 Zimmer; AI-Tourismus | S52: Hotel Appenzell
A53: 50 | B53: B | C53: Elektroplaner/Engineering | D53: Elektro Sutter AG (Appenzell AI) | E53: Appenzell | F53: 9050 | G53: AI | H53: Inhaber | I53: Elektroinstallateur EFZ | J53: info@sutter-elektro.ch | K53: +41 71 787 55 55 | M53: offen | N53: Inhaber Elektro Sutter Appenzell; Partnerschaft AI besprechen | O53: Elektrounternehmen Appenzell: Industrie+Gewerbe+Hotellerie; AI-Marktführer | R53: Adr: Appenzell, 9050 AI | Elektrounternehmen AI; Türöffner Brauerei+KS | S53: Elektrounternehmen AI
A54: 51 | B54: B | C54: Pharma/Chemie | D54: Sennerei Gonten (Appenzeller Käse) | E54: Gonten | F54: 9108 | G54: AI | H54: Betriebsleiter | I54: Techniker | J54: info@sennerei-gonten.ch | K54: +41 71 795 30 80 | M54: offen | N54: MiT-CRM: Sennerei Gonten als Kältekunde prüfen | O54: Sennerei Gonten: NEA Kühlkette 150 kVA; ISO 50001; Cross-Sell Kälte | P54: Kälte | R54: Adr: Gonten, 9108 AI | Sennerei Gonten; Appenzeller Käse; Kühlkette | S54: Käserei AI
A55: 52 | B55: C | C55: Gemeinde/Öffentlich | D55: [MiT AI-Kältekunde Nr. 2] | E55: Appenzell | F55: 9050 | G55: AI | H55: Energieverantwortlicher | I55: Betriebsleiter | K55: (MiT-CRM) | M55: offen | N55: MiT-CRM Roberto/Stefan: AI-Kunden ohne Strom prüfen | O55: Strom-Add-on MiT-Wärme/Kälte AI | R55: Locher Brauerei + Säntis 2'502 m = 2 Top-Warmleads AI | S55: Cross-Sell MiT
A56: 53 | B56: A | C56: EVU/Netzbetreiber | D56: AEW Energie AR AG (Regionale EVU) | E56: Herisau | F56: 9100 | G56: AR | H56: Leiter Netzbetrieb | I56: Dipl. El.-Ing. | J56: info@aewag.ch | K56: +41 71 353 21 21 | M56: offen | N56: Netzbetrieb AEW AR; Urnäscherstrasse 39 Herisau; Revisionskalender | O56: Stromversorgung AR; MS-Revisionen; NEA Gemeindegebäude; Netz AR | P56: Generator | R56: Adr: Urnäscherstrasse 39, 9100 Herisau | Kantonaler EVU AR; Netz AR | S56: Kantonaler EVU
A57: 54 | B57: A | C57: Spital/Klinik | D57: Kantonsspital AR (Spital Heiden + Herisau) | E57: Heiden | F57: 9410 | G57: AR | H57: Betriebsleiter Technik | I57: Dipl. El.-Ing. | J57: info@ksar.ch | K57: +41 71 891 10 00 | M57: offen | N57: Betriebsleiter KSAR; Spitalstrasse 1 Heiden; KSSG-Verbindung | O57: NEA 2× 250 kVA; USV OP/ICU; 700 MA; 2 Standorte AR; KSSG-Kooperation | P57: USV | R57: Adr: Spitalstrasse 1, 9410 Heiden | 2 Standorte AR; KSSG-Kooperation; NIV Art. 13 | S57: Kantonsspital
A58: 55 | B58: A | C58: Pharma/Chemie | D58: Cilander AG (Oberveredlung Herisau) | E58: Herisau | F58: 9100 | G58: AR | H58: Betriebsleiter Elektro | I58: Dipl. El.-Ing. | J58: info@cilander.com | K58: +41 71 353 61 11 | M58: offen | N58: Betriebsleiter Cilander; Kasernenstrasse 27 Herisau; FU-PQ-Pitch | O58: Textilveredlung: NEA 500 kVA; FU-Textilmaschinen intensiv; PQ; Färberei; 500 MA | R58: Adr: Kasernenstrasse 27, 9100 Herisau | Textilveredlung; 500 MA; FU-intensiv | S58: Textilveredlung
A59: 56 | B59: A | C59: Pharma/Chemie | D59: Maschinenfabrik Güdel AG (AR-Werk) | E59: Herisau | F59: 9100 | G59: AR | H59: Betriebsleiter Technik | I59: Dipl. El.-Ing. | J59: info@guedel.com | K59: +41 71 354 22 11 | M59: offen | N59: Betriebsleiter Güdel AR; FU-PQ-Pitch; AR-Maschinenind. | O59: Automatisierung: Prüfstände FU 500 kVA; PQ; EMV; Robotik | R59: Adr: Herisau, 9100 AR | Automatisierung + Robotik; FU-Prüfstände | S59: Maschinenind.
A60: 57 | B60: A | C60: Rechenzentrum/IT | D60: Appenzeller Kantonalbank (AKB-AR) | E60: Appenzell | F60: 9050 | G60: AR | H60: Leiter IT-Infrastruktur | I60: MSc Inf. | J60: info@akb-ar.ch | K60: +41 71 788 13 13 | M60: offen | N60: IT-Infrastruktur AKB AR; Hauptgasse 1 Appenzell; FINMA | O60: USV RZ 1× 200 kVA; NEA; PQ FINMA; HQ Appenzell | P60: USV | R60: Adr: Hauptgasse 1, 9050 Appenzell | Kantonalbank AR; FINMA | S60: Kantonalbank
A61: 58 | B61: A | C61: Bergbahn/Tourismus | D61: Bergbahn Ebenalp AG (Weissbad) | E61: Weissbad | F61: 9057 | G61: AR | H61: Betriebsleiter | I61: Techniker | J61: info@ebenalp.ch | K61: +41 71 799 11 64 | M61: offen | N61: Betriebsleiter Ebenalp; Herbst-Revisionsfenster AR | O61: Ebenalp Bergbahn + Wildkirchli: NEA + Generator 150 kVA; FU; alpine Lage AR | P61: Generator | R61: Adr: Talstation Weissbad, 9057 AR | Ebenalp + Wildkirchli; alpine AR-Lage | S61: Bergbahn Ebenalp
A62: 59 | B62: A | C62: Bergbahn/Tourismus | D62: Appenzeller Bahnen AG (AB) | E62: Herisau | F62: 9100 | G62: AR | H62: Betriebsleiter Technik | I62: Dipl. El.-Ing. | J62: info@ab-ar.ch | K62: +41 71 354 50 60 | M62: offen | N62: Betriebsleiter AB; Urnäscherstrasse 1 Herisau; simap.ch AR | O62: Schmalspurbahn AR: NEA + Baustrom 300 kVA; FU-Antriebe Triebwagen; Revisionen Strecke AR | R62: Adr: Urnäscherstrasse 1, 9100 Herisau | Appenzeller Bahnen; Schmalspurbahn AR | S62: Appenzeller Bahnen
A63: 60 | B63: A | C63: Gemeinde/Öffentlich | D63: Kanton Appenzell AR (Hochbauamt) | E63: Herisau | F63: 9100 | G63: AR | H63: Leiter Hochbauamt | I63: Kantonsbauingenieur | J63: info@ar.ch | K63: +41 71 353 61 11 | M63: offen | N63: Hochbauamt AR; Regierungsgebäude Herisau; simap.ch Alert AR | O63: NEA kantonale Gebäude AR; 70+ Liegenschaften; Rahmenvertrag AR | R63: Adr: Regierungsgebäude, 9100 Herisau | Kanton AR; 70+ Liegenschaften | S63: Kanton AR
A64: 61 | B64: A | C64: Bau/Infrastruktur | D64: ARA Herisau (Glatt-Schutz) | E64: Herisau | F64: 9100 | G64: AR | H64: Betriebsleiter ARA | I64: Techniker | J64: info@ara-ar.ch | K64: +41 71 353 10 10 | M64: offen | N64: Betriebsleiter ARA Herisau; simap.ch Alert AR | O64: NEA-Pflicht 1× 200 kVA; Glatt-Gewässerschutz; 24h | P64: Generator | R64: Adr: Herisau, 9100 AR | Glatt-Schutz; Ausschreibungspflicht | S64: ARA Herisau
A65: 62 | B65: B | C65: Pharma/Chemie | D65: Rüegg Nahrungsmittel AG (AR) | E65: Stein AR | F65: 9063 | G65: AR | H65: Betriebsleiter | I65: Techniker | J65: info@ruegg-nahrungsmittel.ch | K65: +41 71 368 11 11 | M65: offen | N65: MiT-CRM: Rüegg AR als Kältekunde prüfen; Strom+Kälte | O65: Nahrungsmittelproduktion: NEA Kühlkette 200 kVA; FU-Abfüller; ISO 50001 | P65: Kälte | R65: Adr: Stein AR, 9063 AR | Nahrungsmittel; Kühlkette; Cross-Sell | S65: Nahrungsmittel/Senf
A66: 63 | B66: B | C66: Pharma/Chemie | D66: Optrel AG (Schweisshelme) | E66: Wattwil | F66: 9630 | G66: AR | H66: Betriebsleiter Technik | I66: Techniker | J66: info@optrel.com | K66: +41 71 987 41 41 | M66: offen | N66: Betriebsleiter Optrel; Berghofstrasse 1 Wattwil | O66: Optik/Elektronik Produktion: NEA 200 kVA; PQ; EMV; Schweisshelme | R66: Adr: Berghofstrasse 1, 9630 Wattwil (AR-Region) | Schweisshelme; Elektronik | S66: Optik
A67: 64 | B67: B | C67: Bergbahn/Tourismus | D67: Kurhotel Heiden AG | E67: Heiden | F67: 9410 | G67: AR | H67: Facility Manager | I67: Techniker | J67: info@kurhotel-heiden.ch | K67: +41 71 891 12 12 | M67: offen | N67: Facility Manager Kurhotel Heiden; alpine Lage-Pitch | O67: Kurhotel alpine Lage: NEA 1× 150 kVA; USV; Bodensee-Panorama | P67: USV | R67: Adr: Seestrasse 2, 9410 Heiden | Kurhotel; Bodensee-Panorama AR | S67: Hotel Heiden
A68: 65 | B68: C | C68: Pharma/Chemie | D68: Käserei AR (Appenzeller Käse) | E68: Stein AR | F68: 9063 | G68: AR | H68: Betriebsleiter | I68: Techniker | J68: info@appenzeller.com | K68: +41 71 368 11 11 | M68: offen | N68: MiT-CRM: Appenzeller Käserei als Kältekunde prüfen | O68: Appenzeller Käse Produktion: NEA Kühlkette 300 kVA; ISO 50001 | P68: Kälte | R68: Adr: Stein AR, 9063 AR | Appenzeller Käse; Kühlkette; Cross-Sell | S68: Käserei
A69: 66 | B69: C | C69: Gemeinde/Öffentlich | D69: [MiT AR-Kältekunde Nr. 1] | E69: Herisau | F69: 9100 | G69: AR | H69: Energieverantwortlicher | I69: Betriebsleiter | K69: (MiT-CRM) | M69: offen | N69: MiT-CRM Roberto/Stefan: AR-Kunden ohne Strom prüfen | O69: Strom-Add-on MiT-Wärme/Kälte AR | R69: AEW AR = Türöffner AR; Cilander + KS AR = Top-Accounts | S69: Cross-Sell MiT
A70: 67 | B70: A | C70: Pharma/Chemie | D70: Saurer Group (Arbon AR/TG) | E70: Herisau | F70: 9100 | G70: AR | H70: Betriebsleiter Elektro | I70: MSc El.-Ing. | J70: info@saurer.com | K70: +41 71 354 85 00 | M70: offen | N70: Betriebsleiter Saurer AR; Arbon AR/TG; FU-PQ-Pitch | O70: Textilmaschinen Prüfstände: FU 1 MVA; PQ; EMV; 3'500 MA ww; AR/TG-Cluster | R70: Adr: Herisau/Arbon, 9100 AR | Saurer Textilmaschinen; 3'500 MA ww | S70: Textilmaschinen
A71: 68 | B71: A | C71: Pharma/Chemie | D71: Huhtamaki AG (Werk Heiden AR) | E71: Heiden | F71: 9410 | G71: AR | H71: Betriebsleiter Technik | I71: Dipl. El.-Ing. | J71: info@huhtamaki.com | K71: +41 71 898 88 88 | M71: offen | N71: Betriebsleiter Huhtamaki Heiden; FU-PQ-Pitch AR | O71: Verpackungsproduktion: NEA 500 kVA; FU-Tiefziehmaschinen; PQ; ISO 50001 | R71: Adr: Heiden, 9410 AR | Huhtamaki Verpackung; FU-Tiefziehmaschinen | S71: Verpackung
A72: 69 | B72: A | C72: Spital/Klinik | D72: Psychiatrische Klinik Herisau (ARA-Verbund) | E72: Herisau | F72: 9100 | G72: AR | H72: Betriebsleiter Technik | I72: Techniker | J72: info@pkar.ch | K72: +41 71 353 26 26 | M72: offen | N72: Betriebsleiter Psychiatrie AR; Herisau; NIV Art. 13 | O72: Psychiatrieklinik: NEA 1× 200 kVA; USV; 24h; 250 MA | P72: USV | R72: Adr: Herisau, 9100 AR | Psychiatrische Klinik; 24h; NIV Art. 13 | S72: Psychiatrie AR
A73: 70 | B73: B | C73: Bergbahn/Tourismus | D73: Kurhotel Heiden (Bodensee-Panorama) | E73: Heiden | F73: 9410 | G73: AR | H73: Facility Manager | I73: Techniker | J73: info@kurhotel-heiden.ch | K73: +41 71 891 12 12 | M73: offen | N73: Facility Manager Kurhotel Heiden; Bodensee-Panorama-Pitch | O73: Kurhotel 4-Sterne: NEA 1× 200 kVA; USV; Bodensee-Panorama AR | P73: USV | R73: Adr: Seestrasse 2, 9410 Heiden | 4-Sterne Kurhotel; Bodensee-Panorama AR | S73: Wellness Heiden
A74: 71 | B74: B | C74: Elektroplaner/Engineering | D74: EKZ Eltop Herisau AR | E74: Herisau | F74: 9100 | G74: AR | H74: Filialleiter | I74: Elektroinstallateur EFZ | J74: herisau@ekzeltop.ch | K74: +41 71 354 20 00 | M74: offen | N74: Filialleiter Eltop Herisau; EKZ-Verbindung nutzen; AR+SG-Partnerschaft | O74: Elektrounternehmen Herisau: Industrie+Gewerbe; EKZ-Tochter AR; AR-Marktführer | R74: Adr: Herisau, 9100 AR | EKZ Eltop; AR-Marktführer; EKZ-Netz AR+SG | S74: Elektrounternehmen AR
A75: 72 | B75: C | C75: Gemeinde/Öffentlich | D75: [MiT AR-Kältekunde Nr. 2] | E75: Herisau | F75: 9100 | G75: AR | H75: Energieverantwortlicher | I75: Betriebsleiter | K75: (MiT-CRM) | M75: offen | N75: MiT-CRM Roberto/Stefan: AR-Kunden ohne Strom prüfen | O75: Strom-Add-on MiT-Wärme/Kälte AR | R75: Saurer 3'500 MA + KSAR 2 Standorte = schnellste Warmleads AR | S75: Cross-Sell MiT
A76: 73 | B76: A | C76: EVU/Netzbetreiber | D76: BKW Energie AG | E76: Bern | F76: 3013 | G76: BE | H76: Leiter Netzbetrieb | I76: Dipl. El.-Ing. | J76: info@bkw.ch | K76: +41 58 477 51 11 | M76: offen | N76: Netzbetrieb BKW; Revisionskalender + Ingenieurdienstl. anfragen | O76: 700'000 Kunden; MS/HS-Revisionen; BESS; Ingenieurdienstleistungen | P76: BESS | R76: Adr: Viktoriaplatz 2, 3013 Bern | Grösster Energiekonzern BE; 700'000 Kunden | S76: Kantonaler EVU
A77: 74 | B77: A | C77: EVU/Netzbetreiber | D77: Energie Wasser Bern (ewb) | E77: Bern | F77: 3001 | G77: BE | H77: Betriebsleiter Netz | I77: Dipl. El.-Ing. | J77: info@ewb.ch | K77: +41 31 321 31 11 | M77: offen | N77: Netzverantwortlichen ewb; simap.ch Alert Bern | O77: Netzersatz Bundesstadt; MS-Revisionen; NEA Bundesgebäude; Fernwärme | R77: Adr: Monbijoustrasse 11, 3001 Bern | Stadtwerk Bern; Strom+Wasser+Wärme+Bus | S77: Stadtwerk Bern
A78: 75 | B78: A | C78: Spital/Klinik | D78: Inselspital Bern (INO-Neubau 2024) | E78: Bern | F78: 3010 | G78: BE | H78: Leiter TGM | I78: MSc El.-Ing. | J78: info@insel.ch | K78: +41 31 632 21 11 | M78: offen | N78: TGM Inselspital; INO-Betriebsphase-Vertrag anstreben | O78: NEA 6× 500 kVA; USV OP/ICU; 9'000 MA; INO-Neubau 2024 bezogen | P78: USV | R78: Adr: Freiburgstrasse 15, 3010 Bern | 9'000 MA; Grösstes Spital BE | S78: Universitätsspital
A79: 76 | B79: A | C79: Spital/Klinik | D79: Hirslanden Beau-Site/Salem Bern | E79: Bern | F79: 3013 | G79: BE | H79: Regionalleiter Technik | I79: Dipl. El.-Ing. | J79: info.bern@hirslanden.ch | K79: +41 31 335 33 11 | M79: offen | N79: Regionaltechnik Hirslanden Bern identifizieren | O79: NEA 2× 350 kVA; USV OP; 2 Standorte Bern; Aevis | P79: USV | R79: Adr: Schänzlihalde 11, 3013 Bern | 2 Standorte BE; Aevis Victoria | S79: Privatklinikgruppe
A80: 77 | B80: A | C80: Gemeinde/Öffentlich | D80: Bundesamt BBL (CH-weit) | E80: Bern | F80: 3003 | G80: BE | H80: Leiter Immobilien | I80: Bundesbauingenieur | J80: info@bbl.admin.ch | K80: +41 58 462 55 00 | M80: offen | N80: BBL Rahmenvertrag Bund; simap.ch Alert 'BBL Bern' | O80: NEA Bundesgebäude CH-weit; 3'000+ Liegenschaften; Rahmenvertrag Bund | R80: Adr: Fellerstrasse 21, 3003 Bern | Bundesrahmenvertrag = grösstes öffentliches Volumen CH | S80: Bundesgebäude
A81: 78 | B81: A | C81: Bau/Infrastruktur | D81: SBB AG (HQ Bern) | E81: Bern | F81: 3000 | G81: BE | H81: Leiter Infra Energie CH | I81: MSc El.-Ing. | J81: kontakt@sbb.ch | K81: +41 58 333 33 33 | M81: offen | N81: Infra Energie SBB HQ; simap.ch 'SBB Netzersatz' | O81: Baustellen CH-weit 200–2'000 kVA; NEA Bahnhöfe; NEAT; HQ Bern | R81: Adr: Hilfikerstrasse 3, 3000 Bern | HQ SBB; Rahmenvertrag national | S81: Bundesbahn
A82: 79 | B82: A | C82: Pharma/Chemie | D82: Swatch Group AG (HQ Biel) | E82: Biel/Bienne | F82: 2501 | G82: BE | H82: Betriebsleiter Technik | I82: Dipl. El.-Ing. | J82: info@swatchgroup.com | K82: +41 32 343 68 11 | M82: offen | N82: Betriebsleiter Swatch Group HQ; 18 Uhrenmarken ansprechen | O82: Uhrenproduktion 18 Standorte: PQ + NEA + USV; 17'500 MA ww | R82: Adr: Seevorstadt 6, 2501 Biel | 17'500 MA ww; 18 Uhrenmarken | S82: Uhren/Konglomerat
A83: 80 | B83: A | C83: Pharma/Chemie | D83: Rolex SA (Werk Biel/Bienne) | E83: Biel/Bienne | F83: 2500 | G83: BE | H83: Facility Manager Biel | I83: Ingénieur | J83: info@rolex.com | K83: +41 32 343 81 11 | M83: offen | N83: Facility Manager Rolex Biel identifizieren | O83: Uhrenwerkproduktion Biel: PQ + NEA + USV 300 kVA; EMV | R83: Adr: Rue du Village 11, 2500 Biel | Rolex Werk Biel; Haute Horlogerie | S83: Uhren/Luxus
A84: 81 | B84: A | C84: Bau/Infrastruktur | D84: Kraftwerke Oberhasli AG (KWO) | E84: Innertkirchen | F84: 3862 | G84: BE | H84: Technischer Leiter | I84: MSc El.-Ing. | J84: info@kwo.ch | K84: +41 33 982 21 11 | M84: offen | N84: Technischen Leiter KWO; Revisionskalender anfragen | O84: Wasserkraft-Revisionen BE; mobile MS-Einspeisung 50 MVA; BESS | P84: Generator | R84: Adr: Grimselweg 12, 3862 Innertkirchen | Grimsel-Stauseen; Revisionen | S84: Staudamm/Kraftwerk
A85: 82 | B85: A | C85: Bau/Infrastruktur | D85: Jungfraubahnen Management AG | E85: Interlaken | F85: 3800 | G85: BE | H85: Technischer Direktor | I85: MSc El.-Ing. | J85: info@jungfrau.ch | K85: +41 33 828 71 11 | M85: offen | N85: Techn. Direktor JBM; Revisionsfenster Herbst | O85: Revisionen Jungfrau: NEA + Generator 1 MVA; FU-Antriebe; Höhenlage | P85: Generator | R85: Adr: Harderstrasse 14, 3800 Interlaken | Weltbekannte Jungfraubahnen | S85: Bergbahn
A86: 83 | B86: A | C86: Spital/Klinik | D86: Spitalzentrum Biel AG (SZB) | E86: Biel/Bienne | F86: 2501 | G86: BE | H86: Betriebsleiter Technik | I86: Dipl. El.-Ing. | J86: info@szb.ch | K86: +41 32 324 22 22 | M86: offen | N86: Betriebsleiter SZB; DE/FR-Erstanschreiben | O86: NEA 3× 400 kVA; USV; 2 Standorte Biel; DE/FR | P86: USV | R86: Adr: Vogelsang 84, 2501 Biel | 2 Standorte; zweisprachig; NEA-Pflicht | S86: Spitalzentrum
A87: 84 | B87: A | C87: Spital/Klinik | D87: Spital Emmental (Burgdorf) | E87: Burgdorf | F87: 3400 | G87: BE | H87: Betriebsleiter Technik | I87: Techniker | J87: info@spital-emmental.ch | K87: +41 34 421 21 21 | M87: offen | N87: Betriebsleiter Spital Emmental kontaktieren | O87: NEA 2× 300 kVA; USV; Emmental-Region | P87: USV | R87: Adr: Oberburgstrasse 54, 3400 Burgdorf | Versorgungsspital Emmental | S87: Kantonsspital
A88: 85 | B88: A | C88: Rechenzentrum/IT | D88: Berner Kantonalbank AG (BEKB) | E88: Bern | F88: 3001 | G88: BE | H88: Leiter IT-Infrastruktur | I88: MSc Inf. | J88: info@bekb.ch | K88: +41 31 666 11 11 | M88: offen | N88: IT-Infrastruktur BEKB; FINMA-Argument | O88: USV RZ 2× 300 kVA; NEA; PQ FINMA | P88: USV | R88: Adr: Bundesplatz 8, 3001 Bern | Kantonalbank BE; FINMA | S88: Kantonalbank
A89: 86 | B89: A | C89: Events/Messen | D89: Bernexpo AG | E89: Bern | F89: 3014 | G89: BE | H89: Technische Leitung | I89: Veranstaltungstechniker | J89: info@bernexpo.ch | K89: +41 31 340 11 11 | M89: offen | N89: Technische Leitung Bernexpo kontaktieren | O89: Temporary Power 500 kVA–2 MVA; USV; Messe Bern | P89: USV | R89: Adr: Mingerstrasse 6, 3014 Bern | Grösste Messe BE | S89: Messe/Kongress
A90: 87 | B90: A | C90: Bau/Infrastruktur | D90: ARA Region Bern | E90: Bern | F90: 3018 | G90: BE | H90: Betriebsleiter ARA | I90: Techniker | J90: info@arb.ch | K90: +41 31 992 48 40 | M90: offen | N90: Betriebsleiter ARA Bern; simap.ch Alert BE | O90: NEA-Pflicht 2× 500 kVA; Aare-Schutz Bundesstadt | P90: Generator | R90: Adr: Morgenstrasse 130, 3018 Bern | Aare-Schutz; Bundesstadt | S90: ARA
A91: 88 | B91: B | C91: Pharma/Chemie | D91: Feintool International AG | E91: Lyss | F91: 3250 | G91: BE | H91: Betriebsleiter Elektro | I91: Dipl. El.-Ing. | J91: info@feintool.com | K91: +41 32 387 51 11 | M91: offen | N91: Betriebsleiter Feintool Lyss kontaktieren | O91: Feinschneidtechnik: Pressen FU 1 MVA; PQ; EMV | R91: Adr: Industriering 8, 3250 Lyss | Weltmarktführer Feinschneidtechnik | S91: Maschinenind.
A92: 89 | B92: B | C92: Pharma/Chemie | D92: Swatch Manufacturing SA Biel | E92: Biel/Bienne | F92: 2500 | G92: BE | H92: Betriebsleiter Technik | I92: Dipl. El.-Ing. | J92: info@swatch.com | K92: +41 32 343 68 11 | M92: offen | N92: Betriebsleiter Swatch Manufacturing Biel | O92: Uhrenmontage: PQ + NEA + USV 200 kVA; EMV; Reinraum | R92: Adr: Rue Nicolas Hayek 6, 2500 Biel | Swatch Gruppe; PQ sensitiv | S92: Uhren
A93: 90 | B93: B | C93: Gemeinde/Öffentlich | D93: Kanton Bern Hochbauamt | E93: Bern | F93: 3011 | G93: BE | H93: Leiter Hochbauamt | I93: Kantonsbauingenieur | J93: hochbauamt@be.ch | K93: +41 31 633 33 33 | M93: offen | N93: Hochbauamt BE; simap.ch Alert Kanton BE | O93: NEA kantonale Gebäude; 400+ Liegenschaften; Rahmenvertrag | R93: Adr: Reiterstrasse 11, 3011 Bern | 400+ Liegenschaften; Rahmenvertrag | S93: Kanton
A94: 91 | B94: B | C94: Pharma/Chemie | D94: Kambly SA | E94: Trubschachen | F94: 3555 | G94: BE | H94: Betriebsleiter Technik | I94: Techniker | J94: info@kambly.ch | K94: +41 34 495 80 80 | M94: offen | N94: MiT-CRM: Kambly als Kältekunde prüfen | O94: Biscuit: NEA Kühlkette 300 kVA; FU-Öfen; ISO 50001 | P94: Kälte | R94: Adr: Kamblystrasse 1, 3555 Trubschachen | Schweizer Biscuits-Ikone | S94: Nahrungsmittel
A95: 92 | B95: B | C95: Bau/Infrastruktur | D95: Schilthornbahn AG | E95: Mürren | F95: 3825 | G95: BE | H95: Betriebsleiter | I95: Techniker | J95: info@schilthornbahn.ch | K95: +41 33 826 00 07 | M95: offen | N95: Betriebsleiter Schilthornbahn; Herbstkontakt | O95: James-Bond-Bergbahn: NEA + Generator 300 kVA; FU; alpine Isolation | P95: Generator | R95: Adr: Infobüro Mürren, 3825 Mürren | James-Bond; autofreies Mürren | S95: Bergbahn
A96: 93 | B96: B | C96: EVU/Netzbetreiber | D96: IB Thun (Industrielle Betriebe) | E96: Thun | F96: 3600 | G96: BE | H96: Betriebsleiter | I96: Dipl. El.-Ing. | J96: info@ib-thun.ch | K96: +41 33 225 22 22 | M96: offen | N96: Betriebsleiter IB Thun; simap.ch Alert Thun | O96: Stadtwerk Thun: MS-Revisionen; NEA Stadtgebäude | R96: Adr: Untere Hauptgasse 22, 3600 Thun | Stadtwerk Thun | S96: Stadtwerk Thun
A97: 94 | B97: B | C97: Pharma/Chemie | D97: Nestlé Suisse SA (Vevey-Produktion) | E97: Vevey | F97: 1800 | G97: BE | H97: Betriebsleiter Technik | I97: Dipl. El.-Ing. | J97: info@nestle.com | K97: +41 21 924 21 11 | M97: offen | N97: MiT-CRM: Nestlé als Kältekunde prüfen; ISO 50001 | O97: Nahrungsmittel: NEA 2 MVA; ISO 50001; Kühlkette; Nestlé-Gruppe | P97: Kälte | R97: Adr: Avenue Nestlé 55, 1800 Vevey | Nestlé-Gruppe; Kühlkette | S97: Nahrungsmittel
A98: 95 | B98: B | C98: Bau/Infrastruktur | D98: Niesen-Bahn AG | E98: Mülenen | F98: 3714 | G98: BE | H98: Betriebsleiter | I98: Techniker | J98: info@niesen.ch | K98: +41 33 676 11 12 | M98: offen | N98: Betriebsleiter Niesen-Bahn Mülenen; Herbst-Revisionsfenster | O98: Bergbahn Revision: Generator 150 kVA; FU; alpine Lage | P98: Generator | R98: Adr: Bahnstation Mülenen, 3714 Mülenen | Steilste Standseilbahn CH | S98: Bergbahn
A99: 96 | B99: B | C99: Spital/Klinik | D99: Regionalspital Emmental Langenthal | E99: Langenthal | F99: 4900 | G99: BE | H99: Betriebsleiter | I99: Techniker | J99: info@rse.ch | K99: +41 62 916 41 41 | M99: offen | N99: Betriebsleiter RSE Langenthal; simap.ch Alert | O99: NEA 1× 300 kVA; USV; BE/AG-Grenzregion | P99: USV | R99: Adr: Bern-Zürich-Korridor, 4900 Langenthal | Regionalspital BE/AG | S99: Spital
A100: 97 | B100: C | C100: Bau/Infrastruktur | D100: BERNMOBIL | E100: Bern | F100: 3000 | G100: BE | H100: Betriebsleiter Technik | I100: Dipl. El.-Ing. | J100: info@bernmobil.ch | K100: +41 31 321 88 44 | M100: offen | N100: Betriebsleiter BERNMOBIL; simap.ch Alert | O100: Baustrom Depots; FU-Antriebe Tram; 1'200 MA | R100: Adr: Eigerplatz 3, 3000 Bern | BERNMOBIL; Tram+Bus; FU-Antriebe | S100: Tram/Bus
...

Sheet 📖 Anleitung
B1: MiT CRM — Import-Anleitung & Feldbeschreibungen
B3: 🚀 Import-Schritte
B4: Schritt 1 | C4: Daten in Tabelle 'Kunden-Datenbank' eintragen
B5: Schritt 2 | C5: Datei speichern als .xlsx oder .csv
B6: Schritt 3 | C6: MiT CRM öffnen → Header-Button '📥 Importieren' klicken
B7: Schritt 4 | C7: Datei hineinziehen oder auswählen
B8: Schritt 5 | C8: KI erkennt Spalten automatisch — Vorschau prüfen
B9: Schritt 6 | C9: 'Importieren' klicken → Daten verteilen sich auf alle Tabs
B11: 📋 Pflichtfelder & Dropdown-Werte
B12: Firmenname * | C12: Pflichtfeld — Import schlägt fehl wenn leer
B13: Prio | C13: Werte: A · B · C (A=hoch, B=mittel, C=niedrig)
B14: Segment | C14: EVU/Netzbetreiber · Spital/Klinik · Pharma/Chemie · Rechenzentrum/IT · Industrie/Maschinenbau · Bau/Infrastruktur · Gemeinde/Öffentlich · Bergbahn/Tourismus · Events/Messen · Elektroplaner/Engineering · Forschung/Bildung · Lebensmittel/Food
B15: Kanton | C15: Zweistelliges Kürzel: ZH, BE, LU, AG, SG, GE, BS, BL, SO, TG, VS, VD, FR, GR, AR, AI, SZ, ZG, TI, NE, UR, OW, NW, GL, SH, JU
B16: Status | C16: offen · kontaktiert · in Gespräch · Angebot gesendet · aktiv · inaktiv
B17: Hauptprodukt | C17: Generator · BESS · Notstrom/USV · USV · BESS + Generator · PQ-Analyse · Wärme · Kälte · Trafo · Mobile MS-Verteilung · Kabel · Baustromverteiler
B18: Follow-up Datum | C18: Format: TT.MM.JJJJ — überfällige Termine werden rot markiert
B20: 🗺️ Karte: Standort-Koordinaten
B21: Ort (Stadt) | C21: → Karte zeigt exakten Stadtpin statt Kantonshauptort
B22: PLZ | C22: → Feinere Geocodierung bei mehreren Firmen in einer Stadt
B23: Kanton | C23: → Fallback wenn Ort nicht erkannt wird
B24: Tipp | C24: Je mehr Felder ausgefüllt, desto präziser die Kartenposition
B26: ⚡ Auto-Verteilung auf CRM-Tabs
B27: 👥 Kontakte | C27: Alle importierten Zeilen als Kontakte
B28: 🗺️ Karte | C28: Pins an exakter Stadt-Position
B29: 🏔️ Kantone | C29: 26 Kantone mit Kontakt-Anzahl befüllt
B30: 🎯 Pipeline | C30: Prio A+B mit Nächstem Schritt → Deals
B31: ✅ Aufgaben | C31: Nächster Schritt + Follow-up Datum → Aufgaben
B32: 🏷️ Tags | C32: Segment + Prio automatisch als Tags
B33: 📞 Dialer | C33: Alle Kontakte mit Telefon → Kaltakquise Queue
B35: 🛡️ Eingebaute Validierung
B36: Dropdowns | C36: Prio, Segment, Kanton, Status, Hauptprodukt sind Dropdown-gesteuert
B37: Farbcodes | C37: Prio A/B/C, Status und überfällige Follow-ups werden automatisch eingefärbt
B38: Dashboard | C38: Tab '📊 Dashboard' enthält Live-Auswertungen aller Stammdaten

Sheet 🏷️ Segmente & Produkte
B1: Segment-Referenz & Produkt-Matrix
B3: Segment | C3: Unterbereich (Beispiele) | D3: Empfohlene MiT-Produkte | E3: Prio-Tendenz
B4: EVU/Netzbetreiber | C4: Kantonale EVU, Stadtwerke, Verteilnetzbetreiber | D4: Generator, Mobile MS-Verteilung, BESS, PQ-Analyse | E4: A
B5: Spital/Klinik | C5: Akutspitäler, Kliniken, Pflegeheime, Reha | D5: Notstrom NIV Art.13, USV, Generator, BESS | E5: A
B6: Pharma/Chemie | C6: Wirkstoff, Galenik, Biotech, Labore | D6: Generator Stage V, BESS, PQ-Monitoring Kl.A | E6: A
B7: Rechenzentrum/IT | C7: Colocation, Enterprise RZ, Telekom-Infra | D7: BESS + Generator, USV, PQ-Analyse IEC 61000-4-30 | E7: A
B8: Industrie/Maschinenbau | C8: CNC-Fertigung, Giesserei, Automobilzulieferer | D8: Generator, Parallelschaltung, Kabel, Trafo | E8: B
B9: Bau/Infrastruktur | C9: Hochbau, Tiefbau, Tunnel, Sanierung | D9: Generator, Baustromverteiler, Kabel, IBC Tank | E9: B
B10: Gemeinde/Öffentlich | C10: Gemeinden, Kantone, Wasserversorgung, Kläranlage | D10: Generator, Notstrom, BESS | E10: B
B11: Bergbahn/Tourismus | C11: Ski-Resorts, Hotels, Seilbahnen, Events | D11: Generator, Wärme, Kälte, BESS | E11: B
B12: Events/Messen | C12: Messen, Festivals, Grossevents, Konzerte | D12: Generator, Kälte, Wärme, Kabel, Verteiler | E12: B/C
B13: Elektroplaner/Engineering | C13: Ingenieurbüros, TGA-Planer, Architekten | D13: Alle Produkte (Planungsunterstützung) | E13: C
B14: Forschung/Bildung | C14: ETH/EPFL, Fachhochschulen, Forschungsinstitute | D14: USV, BESS, Generator, PQ-Analyse | E14: B
B15: Lebensmittel/Food | C15: Molkereien, Fleischverarbeitung, Bäckereien | D15: Generator, Kälte, BESS | E15: B
