Workbook

Sheet 📑 Executive PDF
A1: ⚡ MiT Strom Schweiz — Executive Sales Summary
A2: Mobil in Time AG · An Aggreko Company · Burak Ücöz
A3: ="Stand: "&TEXT(TODAY(),"DD.MM.YYYY")&" · Live aus Pipeline" -> Stand: 10.08.2026 · Live aus Pipeline
B5: ✅ WON | E5: 📄 OFFERTE | G5: 🎯 OPPORTUNITÄT
B6: =Dashboard!A6 -> 1428553.1 | E6: =Dashboard!D6 -> 5433596.1 | G6: =Dashboard!G6 -> 0
B8: =Dashboard!A7&IF(Dashboard!A7=1," Deal"," Deals") -> 12 Deals | E8: =Dashboard!D7&IF(Dashboard!D7=1," Deal"," Deals") -> 33 Deals | G8: =Dashboard!G7&IF(Dashboard!G7=1," Deal"," Deals") -> 1 Deal
B10: ="📊 PIPELINE: "&TEXT(Dashboard!I6,"#,##0")&" CHF · "&Dashboard!I7&" Deals · ⚖️ GEWICHTET: "&TEXT('⚖️ Wahrscheinlichkeit'!$G$22,"#,##0")&" CHF" -> 📊 PIPELINE: 6,862,149 CHF · 46 Deals · ⚖️ GEWICHTET: 1,628,426 CHF
B12: 🏆 Top 5 WON-Deals (nach Volumen)
B13: # | C13: Kunde | D13: Kt. | E13: Projektstart | F13: Segment | G13: Volumen | H13: Projektende
B14: 1 | C14: =IFERROR(INDEX('MiT Strom Pipeline'!B6:B860,MATCH(LARGE('MiT Strom Pipeline'!AK6:AK860,1),'MiT Strom Pipeline'!AK6:AK860,0)),"") -> Ice Hockey Championship | D14: =IFERROR(INDEX('MiT Strom Pipeline'!C6:C860,MATCH(LARGE('MiT Strom Pipeline'!AK6:AK860,1),'MiT Strom Pipeline'!AK6:AK860,0)),"") -> ZH | E14: =IFERROR(IF(ISNUMBER(INDEX('MiT Strom Pipeline'!$O$6:$O$860,MATCH(LARGE('MiT Strom Pipeline'!$AK$6:$AK$860,1),'MiT Strom Pipeline'!$AK$6:$AK$860,0))),INDEX('MiT Strom Pipeline'!$O$6:$O$860,MATCH(LARGE('MiT Strom Pipeline'!$AK$6:$AK$860,1),'MiT Strom Pipeline'!$AK$6:$AK$860,0)),IF(INDEX('MiT Strom Pipeline'!$H$6:$H$860,MATCH(LARGE('MiT Strom Pipeline'!$AK$6:$AK$860,1),'MiT Strom Pipeline'!$AK$6:$AK$860,0))="","",INDEX('MiT Strom Pipeline'!$H$6:$H$860,MATCH(LARGE('MiT Strom Pipeline'!$AK$6:$AK$860,1),'MiT Strom Pipeline'!$AK$6:$AK$860,0)))),"") -> Mai | F14: =IFERROR(INDEX('MiT Strom Pipeline'!D6:D860,MATCH(LARGE('MiT Strom Pipeline'!AK6:AK860,1),'MiT Strom Pipeline'!AK6:AK860,0)),"") -> Events & Sport | G14: =IFERROR(INDEX('MiT Strom Pipeline'!I6:I860,MATCH(LARGE('MiT Strom Pipeline'!AK6:AK860,1),'MiT Strom Pipeline'!AK6:AK860,0)),"") -> 380000 | H14: =IFERROR(IF(ISNUMBER(INDEX('MiT Strom Pipeline'!$P$6:$P$860,MATCH(LARGE('MiT Strom Pipeline'!$AK$6:$AK$860,1),'MiT Strom Pipeline'!$AK$6:$AK$860,0))),INDEX('MiT Strom Pipeline'!$P$6:$P$860,MATCH(LARGE('MiT Strom Pipeline'!$AK$6:$AK$860,1),'MiT Strom Pipeline'!$AK$6:$AK$860,0)),""),"")
B15: 2 | C15: =IFERROR(INDEX('MiT Strom Pipeline'!B6:B860,MATCH(LARGE('MiT Strom Pipeline'!AK6:AK860,2),'MiT Strom Pipeline'!AK6:AK860,0)),"") -> DPR Heat Loadbank | D15: =IFERROR(INDEX('MiT Strom Pipeline'!C6:C860,MATCH(LARGE('MiT Strom Pipeline'!AK6:AK860,2),'MiT Strom Pipeline'!AK6:AK860,0)),"") -> ZH | E15: =IFERROR(IF(ISNUMBER(INDEX('MiT Strom Pipeline'!$O$6:$O$860,MATCH(LARGE('MiT Strom Pipeline'!$AK$6:$AK$860,2),'MiT Strom Pipeline'!$AK$6:$AK$860,0))),INDEX('MiT Strom Pipeline'!$O$6:$O$860,MATCH(LARGE('MiT Strom Pipeline'!$AK$6:$AK$860,2),'MiT Strom Pipeline'!$AK$6:$AK$860,0)),IF(INDEX('MiT Strom Pipeline'!$H$6:$H$860,MATCH(LARGE('MiT Strom Pipeline'!$AK$6:$AK$860,2),'MiT Strom Pipeline'!$AK$6:$AK$860,0))="","",INDEX('MiT Strom Pipeline'!$H$6:$H$860,MATCH(LARGE('MiT Strom Pipeline'!$AK$6:$AK$860,2),'MiT Strom Pipeline'!$AK$6:$AK$860,0)))),"") -> Aug | F15: =IFERROR(INDEX('MiT Strom Pipeline'!D6:D860,MATCH(LARGE('MiT Strom Pipeline'!AK6:AK860,2),'MiT Strom Pipeline'!AK6:AK860,0)),"") -> Datacenter | G15: =IFERROR(INDEX('MiT Strom Pipeline'!I6:I860,MATCH(LARGE('MiT Strom Pipeline'!AK6:AK860,2),'MiT Strom Pipeline'!AK6:AK860,0)),"") -> 333790 | H15: =IFERROR(IF(ISNUMBER(INDEX('MiT Strom Pipeline'!$P$6:$P$860,MATCH(LARGE('MiT Strom Pipeline'!$AK$6:$AK$860,2),'MiT Strom Pipeline'!$AK$6:$AK$860,0))),INDEX('MiT Strom Pipeline'!$P$6:$P$860,MATCH(LARGE('MiT Strom Pipeline'!$AK$6:$AK$860,2),'MiT Strom Pipeline'!$AK$6:$AK$860,0)),""),"")
B16: 3 | C16: =IFERROR(INDEX('MiT Strom Pipeline'!B6:B860,MATCH(LARGE('MiT Strom Pipeline'!AK6:AK860,3),'MiT Strom Pipeline'!AK6:AK860,0)),"") -> DPR Generator Loadbank Test | D16: =IFERROR(INDEX('MiT Strom Pipeline'!C6:C860,MATCH(LARGE('MiT Strom Pipeline'!AK6:AK860,3),'MiT Strom Pipeline'!AK6:AK860,0)),"") -> ZH | E16: =IFERROR(IF(ISNUMBER(INDEX('MiT Strom Pipeline'!$O$6:$O$860,MATCH(LARGE('MiT Strom Pipeline'!$AK$6:$AK$860,3),'MiT Strom Pipeline'!$AK$6:$AK$860,0))),INDEX('MiT Strom Pipeline'!$O$6:$O$860,MATCH(LARGE('MiT Strom Pipeline'!$AK$6:$AK$860,3),'MiT Strom Pipeline'!$AK$6:$AK$860,0)),IF(INDEX('MiT Strom Pipeline'!$H$6:$H$860,MATCH(LARGE('MiT Strom Pipeline'!$AK$6:$AK$860,3),'MiT Strom Pipeline'!$AK$6:$AK$860,0))="","",INDEX('MiT Strom Pipeline'!$H$6:$H$860,MATCH(LARGE('MiT Strom Pipeline'!$AK$6:$AK$860,3),'MiT Strom Pipeline'!$AK$6:$AK$860,0)))),"") -> Aug | F16: =IFERROR(INDEX('MiT Strom Pipeline'!D6:D860,MATCH(LARGE('MiT Strom Pipeline'!AK6:AK860,3),'MiT Strom Pipeline'!AK6:AK860,0)),"") -> Datacenter | G16: =IFERROR(INDEX('MiT Strom Pipeline'!I6:I860,MATCH(LARGE('MiT Strom Pipeline'!AK6:AK860,3),'MiT Strom Pipeline'!AK6:AK860,0)),"") -> 331889.15 | H16: =IFERROR(IF(ISNUMBER(INDEX('MiT Strom Pipeline'!$P$6:$P$860,MATCH(LARGE('MiT Strom Pipeline'!$AK$6:$AK$860,3),'MiT Strom Pipeline'!$AK$6:$AK$860,0))),INDEX('MiT Strom Pipeline'!$P$6:$P$860,MATCH(LARGE('MiT Strom Pipeline'!$AK$6:$AK$860,3),'MiT Strom Pipeline'!$AK$6:$AK$860,0)),""),"")
B17: 4 | C17: =IFERROR(INDEX('MiT Strom Pipeline'!B6:B860,MATCH(LARGE('MiT Strom Pipeline'!AK6:AK860,4),'MiT Strom Pipeline'!AK6:AK860,0)),"") -> Stagelight – OpenAir Frauenfeld | D17: =IFERROR(INDEX('MiT Strom Pipeline'!C6:C860,MATCH(LARGE('MiT Strom Pipeline'!AK6:AK860,4),'MiT Strom Pipeline'!AK6:AK860,0)),"") -> TG | E17: =IFERROR(IF(ISNUMBER(INDEX('MiT Strom Pipeline'!$O$6:$O$860,MATCH(LARGE('MiT Strom Pipeline'!$AK$6:$AK$860,4),'MiT Strom Pipeline'!$AK$6:$AK$860,0))),INDEX('MiT Strom Pipeline'!$O$6:$O$860,MATCH(LARGE('MiT Strom Pipeline'!$AK$6:$AK$860,4),'MiT Strom Pipeline'!$AK$6:$AK$860,0)),IF(INDEX('MiT Strom Pipeline'!$H$6:$H$860,MATCH(LARGE('MiT Strom Pipeline'!$AK$6:$AK$860,4),'MiT Strom Pipeline'!$AK$6:$AK$860,0))="","",INDEX('MiT Strom Pipeline'!$H$6:$H$860,MATCH(LARGE('MiT Strom Pipeline'!$AK$6:$AK$860,4),'MiT Strom Pipeline'!$AK$6:$AK$860,0)))),"") -> Juli | F17: =IFERROR(INDEX('MiT Strom Pipeline'!D6:D860,MATCH(LARGE('MiT Strom Pipeline'!AK6:AK860,4),'MiT Strom Pipeline'!AK6:AK860,0)),"") -> Events & Kultur | G17: =IFERROR(INDEX('MiT Strom Pipeline'!I6:I860,MATCH(LARGE('MiT Strom Pipeline'!AK6:AK860,4),'MiT Strom Pipeline'!AK6:AK860,0)),"") -> 150000 | H17: =IFERROR(IF(ISNUMBER(INDEX('MiT Strom Pipeline'!$P$6:$P$860,MATCH(LARGE('MiT Strom Pipeline'!$AK$6:$AK$860,4),'MiT Strom Pipeline'!$AK$6:$AK$860,0))),INDEX('MiT Strom Pipeline'!$P$6:$P$860,MATCH(LARGE('MiT Strom Pipeline'!$AK$6:$AK$860,4),'MiT Strom Pipeline'!$AK$6:$AK$860,0)),""),"")
B18: 5 | C18: =IFERROR(INDEX('MiT Strom Pipeline'!B6:B860,MATCH(LARGE('MiT Strom Pipeline'!AK6:AK860,5),'MiT Strom Pipeline'!AK6:AK860,0)),"") -> Murg Flums Energie | D18: =IFERROR(INDEX('MiT Strom Pipeline'!C6:C860,MATCH(LARGE('MiT Strom Pipeline'!AK6:AK860,5),'MiT Strom Pipeline'!AK6:AK860,0)),"") -> SG | E18: =IFERROR(IF(ISNUMBER(INDEX('MiT Strom Pipeline'!$O$6:$O$860,MATCH(LARGE('MiT Strom Pipeline'!$AK$6:$AK$860,5),'MiT Strom Pipeline'!$AK$6:$AK$860,0))),INDEX('MiT Strom Pipeline'!$O$6:$O$860,MATCH(LARGE('MiT Strom Pipeline'!$AK$6:$AK$860,5),'MiT Strom Pipeline'!$AK$6:$AK$860,0)),IF(INDEX('MiT Strom Pipeline'!$H$6:$H$860,MATCH(LARGE('MiT Strom Pipeline'!$AK$6:$AK$860,5),'MiT Strom Pipeline'!$AK$6:$AK$860,0))="","",INDEX('MiT Strom Pipeline'!$H$6:$H$860,MATCH(LARGE('MiT Strom Pipeline'!$AK$6:$AK$860,5),'MiT Strom Pipeline'!$AK$6:$AK$860,0)))),"") -> Auf Abruf | F18: =IFERROR(INDEX('MiT Strom Pipeline'!D6:D860,MATCH(LARGE('MiT Strom Pipeline'!AK6:AK860,5),'MiT Strom Pipeline'!AK6:AK860,0)),"") -> EVU / Energie | G18: =IFERROR(INDEX('MiT Strom Pipeline'!I6:I860,MATCH(LARGE('MiT Strom Pipeline'!AK6:AK860,5),'MiT Strom Pipeline'!AK6:AK860,0)),"") -> 96658.69 | H18: =IFERROR(IF(ISNUMBER(INDEX('MiT Strom Pipeline'!$P$6:$P$860,MATCH(LARGE('MiT Strom Pipeline'!$AK$6:$AK$860,5),'MiT Strom Pipeline'!$AK$6:$AK$860,0))),INDEX('MiT Strom Pipeline'!$P$6:$P$860,MATCH(LARGE('MiT Strom Pipeline'!$AK$6:$AK$860,5),'MiT Strom Pipeline'!$AK$6:$AK$860,0)),""),"")
B21: 📊 Status-Verteilung Pipeline
B22: Status | D22: Anzahl | E22: Volumen CHF | G22: Anteil %
B23: ✅ WON | D23: =COUNTIF('MiT Strom Pipeline'!R6:R860,"WON") -> 12 | E23: =SUMIFS('MiT Strom Pipeline'!I6:I860,'MiT Strom Pipeline'!R6:R860,"WON") -> 1428553.1 | G23: =IFERROR(E23/Dashboard!I6,0) -> 0.20817867
B24: 📄 Offerte (inkl. To Offer) | D24: =COUNTIF('MiT Strom Pipeline'!R6:R860,"offered")+COUNTIF('MiT Strom Pipeline'!R6:R860,"to be offered") -> 29 | E24: =SUMIFS('MiT Strom Pipeline'!I6:I860,'MiT Strom Pipeline'!R6:R860,"offered")+SUMIFS('MiT Strom Pipeline'!I6:I860,'MiT Strom Pipeline'!R6:R860,"to be offered") -> 4887938.3 | G24: =IFERROR(E24/Dashboard!I6,0) -> 0.71230428
B25: 🎯 Follow-Up | D25: =COUNTIF('MiT Strom Pipeline'!R6:R860,"follow-up") -> 0 | E25: =SUMIFS('MiT Strom Pipeline'!I6:I860,'MiT Strom Pipeline'!R6:R860,"follow-up") -> 0 | G25: =IFERROR(E25/Dashboard!I6,0) -> 0
B26: 🔍 Evaluation (inkl. In Eval) | D26: =COUNTIF('MiT Strom Pipeline'!R6:R860,"Evaluation")+COUNTIF('MiT Strom Pipeline'!R6:R860,"In evaluation") -> 0 | E26: =SUMIFS('MiT Strom Pipeline'!I6:I860,'MiT Strom Pipeline'!R6:R860,"Evaluation")+SUMIFS('MiT Strom Pipeline'!I6:I860,'MiT Strom Pipeline'!R6:R860,"In evaluation") -> 0 | G26: =IFERROR(E26/Dashboard!I6,0) -> 0
B27: ⏸ On Hold | D27: =COUNTIF('MiT Strom Pipeline'!R6:R860,"on hold") -> 4 | E27: =SUMIFS('MiT Strom Pipeline'!I6:I860,'MiT Strom Pipeline'!R6:R860,"on hold") -> 545657.8 | G27: =IFERROR(E27/Dashboard!I6,0) -> 0.079517041
B28: ❓ TBD | D28: =COUNTIF('MiT Strom Pipeline'!R6:R860,"tbd") -> 1 | E28: =SUMIFS('MiT Strom Pipeline'!I6:I860,'MiT Strom Pipeline'!R6:R860,"tbd") -> 0 | G28: =IFERROR(E28/Dashboard!I6,0) -> 0
B29: ❌ LOST | D29: =COUNTIF('MiT Strom Pipeline'!R6:R860,"LOST") -> 7 | E29: =SUMIFS('MiT Strom Pipeline'!I6:I860,'MiT Strom Pipeline'!R6:R860,"LOST") -> 78251.62 | G29: =IFERROR(E29/Dashboard!I6,0) -> 0.011403369
B30: 🚫 Declined | D30: =COUNTIF('MiT Strom Pipeline'!R6:R860,"Declined") -> 13 | E30: =SUMIFS('MiT Strom Pipeline'!I6:I860,'MiT Strom Pipeline'!R6:R860,"Declined") -> 96029.01 | G30: =IFERROR(E30/Dashboard!I6,0) -> 0.013994014
B32: ⚖️ Gewichtete Pipeline nach Aggreko-Bewertung
B33: Wahrsch.-Band | D33: Faktor | E33: Umsatz CHF | G33: Gewichtet CHF
B34: ='⚖️ Wahrscheinlichkeit'!$A$17 -> 0 – 44 % | D34: ='⚖️ Wahrscheinlichkeit'!$D$17 -> 0 | E34: ='⚖️ Wahrscheinlichkeit'!$F$17 -> 5092182.2 | G34: ='⚖️ Wahrscheinlichkeit'!$G$17 -> 0
B35: ='⚖️ Wahrscheinlichkeit'!$A$18 -> 45 – 59 % | D35: ='⚖️ Wahrscheinlichkeit'!$D$18 -> 0.3 | E35: ='⚖️ Wahrscheinlichkeit'!$F$18 -> 0 | G35: ='⚖️ Wahrscheinlichkeit'!$G$18 -> 0
B36: ='⚖️ Wahrscheinlichkeit'!$A$19 -> 60 – 89 % | D36: ='⚖️ Wahrscheinlichkeit'!$D$19 -> 0.5 | E36: ='⚖️ Wahrscheinlichkeit'!$F$19 -> 268500.23 | G36: ='⚖️ Wahrscheinlichkeit'!$G$19 -> 134250.11
B37: ='⚖️ Wahrscheinlichkeit'!$A$20 -> 90 – 99 % | D37: ='⚖️ Wahrscheinlichkeit'!$D$20 -> 0.9 | E37: ='⚖️ Wahrscheinlichkeit'!$F$20 -> 72913.72 | G37: ='⚖️ Wahrscheinlichkeit'!$G$20 -> 65622.348
B38: ='⚖️ Wahrscheinlichkeit'!$A$21 -> 100 % · WON | D38: ='⚖️ Wahrscheinlichkeit'!$D$21 -> 1 | E38: ='⚖️ Wahrscheinlichkeit'!$F$21 -> 1428553.1 | G38: ='⚖️ Wahrscheinlichkeit'!$G$21 -> 1428553.1
B39: TOTAL aktiv | E39: ='⚖️ Wahrscheinlichkeit'!$F$22 -> 6862149.2 | G39: ='⚖️ Wahrscheinlichkeit'!$G$22 -> 1628425.6
B40: ="Faktoren: 0–44 % → 0 % | 45–59 % → 30 % | 60–89 % → 50 % | 90–99 % → 90 % | 100 % → 100 % · Gewichtungsgrad: "&TEXT('⚖️ Wahrscheinlichkeit'!$H$22,"0.0%") -> Faktoren: 0–44 % → 0 % | 45–59 % → 30 % | 60–89 % → 50 % | 90–99 % → 90 % | 100 % → 100 % · Gewichtungsgrad: 23.7%
B42: 📋 Nachweis & Zeitraum — wie die Zahlen zu lesen sind
B43: WON netto (ohne MwSt) | E43: =SUMPRODUCT(--('MiT Strom Pipeline'!$R$6:$R$860="WON"),'MiT Strom Pipeline'!$AZ$6:$AZ$860) -> 1321510.8
B44: davon durch Auftrag/PO belegt | E44: =SUMPRODUCT('MiT Strom Pipeline'!$AT$6:$AT$860,'MiT Strom Pipeline'!$AL$6:$AL$860) -> 0
B45: Nachweisquote | E45: =IFERROR(SUMPRODUCT('MiT Strom Pipeline'!$AT$6:$AT$860,'MiT Strom Pipeline'!$AL$6:$AL$860)/SUMIFS('MiT Strom Pipeline'!$I$6:$I$860,'MiT Strom Pipeline'!$R$6:$R$860,"WON"),0) -> 0
B46: Deals mit erfasstem Projektzeitraum | E46: =SUMPRODUCT('MiT Strom Pipeline'!$AP$6:$AP$860,'MiT Strom Pipeline'!$AY$6:$AY$860)&" von "&SUMPRODUCT('MiT Strom Pipeline'!$AP$6:$AP$860) -> 0 von 46
B47: ="Offene Pflichtangaben: "&'📋 Definitionen & Klärung'!$C$23&" · Definitionen und offene Punkte: Blatt «📋 Definitionen & Klärung»" -> Offene Pflichtangaben: 101 · Definitionen und offene Punkte: Blatt «📋 Definitionen & Klärung»
A49: 🖨 Strg+P → Als PDF speichern · Druckbereich ist bereits gesetzt (A4 Hochformat)

Sheet 📄 Report
A1: MiT Strom Schweiz — Sales-Report
A2: Mobil in Time AG · An Aggreko Company · Burak Ücöz
A3: ="Stand: "&TEXT(TODAY(),"DD.MM.YYYY")&" · Auto-Update via Pipeline-Daten" -> Stand: 10.08.2026 · Auto-Update via Pipeline-Daten
A5: Key Performance Indicators
A6: KPI | B6: Wert CHF | C6: Anzahl | D6: Anteil
A7: ✅ WON | B7: =Dashboard!A6 -> 1428553.1 | C7: =Dashboard!A7 -> 12 | D7: =IFERROR(B7/$B$10,0) -> 0.20817867
A8: 📄 Offerte | B8: =Dashboard!D6 -> 5433596.1 | C8: =Dashboard!D7 -> 33 | D8: =IFERROR(B8/$B$10,0) -> 0.79182133
A9: 🎯 Opportunität | B9: =Dashboard!G6 -> 0 | C9: =Dashboard!G7 -> 1 | D9: =IFERROR(B9/$B$10,0) -> 0
A10: 📊 TOTAL Pipeline | B10: =Dashboard!I6 -> 6862149.2 | C10: =Dashboard!I7 -> 46 | D10: =IFERROR(B10/$B$10,0) -> 1
A11: ⚖️ Gewichtet | B11: ='⚖️ Wahrscheinlichkeit'!$G$22 -> 1628425.6 | C11: ='⚖️ Wahrscheinlichkeit'!$E$22 -> 46 | D11: =IFERROR(B11/$B$10,0) -> 0.23730548
A12: 📋 WON belegt | B12: =SUMPRODUCT('MiT Strom Pipeline'!$AT$6:$AT$860,'MiT Strom Pipeline'!$AL$6:$AL$860) -> 0 | C12: =SUMPRODUCT('MiT Strom Pipeline'!$AT$6:$AT$860) -> 0 | D12: =IFERROR(SUMPRODUCT('MiT Strom Pipeline'!$AT$6:$AT$860,'MiT Strom Pipeline'!$AL$6:$AL$860)/SUMIFS('MiT Strom Pipeline'!$I$6:$I$860,'MiT Strom Pipeline'!$R$6:$R$860,"WON"),0) -> 0 | E12: =IFERROR(SUMPRODUCT('MiT Strom Pipeline'!$AT$6:$AT$860,'MiT Strom Pipeline'!$AL$6:$AL$860)/SUMIFS('MiT Strom Pipeline'!$I$6:$I$860,'MiT Strom Pipeline'!$R$6:$R$860,"WON"),0) -> 0
A13: Top Kantone (nach Volumen) | J13: _kt | K13: _vol | L13: _rankkey
A14: Rang | B14: Kanton | C14: Volumen CHF | D14: Anzahl Deals | E14: WON-Rate | J14: AG | K14: =SUMIF('MiT Strom Pipeline'!$C$6:$C$860,J14,'MiT Strom Pipeline'!$I$6:$I$860) -> 444672.95 | L14: =K14+(26-ROW())*0.0001 -> 444672.95
A15: 1 | B15: =IFERROR(INDEX($J$14:$J$39,MATCH(LARGE($L$14:$L$39,1),$L$14:$L$39,0)),"") -> ZH | C15: =IF(B15="","",SUMIF('MiT Strom Pipeline'!$C$6:$C$860,B15,'MiT Strom Pipeline'!$I$6:$I$860)) -> 2732239 | D15: =IF(B15="","",COUNTIF('MiT Strom Pipeline'!$C$6:$C$860,B15)) -> 25 | E15: =IF(OR(B15="",D15=0),"",COUNTIFS('MiT Strom Pipeline'!$C$6:$C$860,B15,'MiT Strom Pipeline'!$R$6:$R$860,"WON")/D15) -> 0.2 | J15: AI | K15: =SUMIF('MiT Strom Pipeline'!$C$6:$C$860,J15,'MiT Strom Pipeline'!$I$6:$I$860) -> 0 | L15: =K15+(26-ROW())*0.0001 -> 0.0011
A16: 2 | B16: =IFERROR(INDEX($J$14:$J$39,MATCH(LARGE($L$14:$L$39,2),$L$14:$L$39,0)),"") -> SH | C16: =IF(B16="","",SUMIF('MiT Strom Pipeline'!$C$6:$C$860,B16,'MiT Strom Pipeline'!$I$6:$I$860)) -> 2637287.6 | D16: =IF(B16="","",COUNTIF('MiT Strom Pipeline'!$C$6:$C$860,B16)) -> 5 | E16: =IF(OR(B16="",D16=0),"",COUNTIFS('MiT Strom Pipeline'!$C$6:$C$860,B16,'MiT Strom Pipeline'!$R$6:$R$860,"WON")/D16) -> 0.2 | J16: AR | K16: =SUMIF('MiT Strom Pipeline'!$C$6:$C$860,J16,'MiT Strom Pipeline'!$I$6:$I$860) -> 0 | L16: =K16+(26-ROW())*0.0001 -> 0.001
A17: 3 | B17: =IFERROR(INDEX($J$14:$J$39,MATCH(LARGE($L$14:$L$39,3),$L$14:$L$39,0)),"") -> AG | C17: =IF(B17="","",SUMIF('MiT Strom Pipeline'!$C$6:$C$860,B17,'MiT Strom Pipeline'!$I$6:$I$860)) -> 444672.95 | D17: =IF(B17="","",COUNTIF('MiT Strom Pipeline'!$C$6:$C$860,B17)) -> 7 | E17: =IF(OR(B17="",D17=0),"",COUNTIFS('MiT Strom Pipeline'!$C$6:$C$860,B17,'MiT Strom Pipeline'!$R$6:$R$860,"WON")/D17) -> 0.14285714 | J17: BE | K17: =SUMIF('MiT Strom Pipeline'!$C$6:$C$860,J17,'MiT Strom Pipeline'!$I$6:$I$860) -> 58012.12 | L17: =K17+(26-ROW())*0.0001 -> 58012.121
A18: 4 | B18: =IFERROR(INDEX($J$14:$J$39,MATCH(LARGE($L$14:$L$39,4),$L$14:$L$39,0)),"") -> SO | C18: =IF(B18="","",SUMIF('MiT Strom Pipeline'!$C$6:$C$860,B18,'MiT Strom Pipeline'!$I$6:$I$860)) -> 390750.65 | D18: =IF(B18="","",COUNTIF('MiT Strom Pipeline'!$C$6:$C$860,B18)) -> 2 | E18: =IF(OR(B18="",D18=0),"",COUNTIFS('MiT Strom Pipeline'!$C$6:$C$860,B18,'MiT Strom Pipeline'!$R$6:$R$860,"WON")/D18) -> 0 | J18: BL | K18: =SUMIF('MiT Strom Pipeline'!$C$6:$C$860,J18,'MiT Strom Pipeline'!$I$6:$I$860) -> 13472.18 | L18: =K18+(26-ROW())*0.0001 -> 13472.181
A19: 5 | B19: =IFERROR(INDEX($J$14:$J$39,MATCH(LARGE($L$14:$L$39,5),$L$14:$L$39,0)),"") -> VS | C19: =IF(B19="","",SUMIF('MiT Strom Pipeline'!$C$6:$C$860,B19,'MiT Strom Pipeline'!$I$6:$I$860)) -> 303790.2 | D19: =IF(B19="","",COUNTIF('MiT Strom Pipeline'!$C$6:$C$860,B19)) -> 3 | E19: =IF(OR(B19="",D19=0),"",COUNTIFS('MiT Strom Pipeline'!$C$6:$C$860,B19,'MiT Strom Pipeline'!$R$6:$R$860,"WON")/D19) -> 0.33333333 | J19: BS | K19: =SUMIF('MiT Strom Pipeline'!$C$6:$C$860,J19,'MiT Strom Pipeline'!$I$6:$I$860) -> 13866.21 | L19: =K19+(26-ROW())*0.0001 -> 13866.211
A20: 6 | B20: =IFERROR(INDEX($J$14:$J$39,MATCH(LARGE($L$14:$L$39,6),$L$14:$L$39,0)),"") -> TG | C20: =IF(B20="","",SUMIF('MiT Strom Pipeline'!$C$6:$C$860,B20,'MiT Strom Pipeline'!$I$6:$I$860)) -> 160817.26 | D20: =IF(B20="","",COUNTIF('MiT Strom Pipeline'!$C$6:$C$860,B20)) -> 3 | E20: =IF(OR(B20="",D20=0),"",COUNTIFS('MiT Strom Pipeline'!$C$6:$C$860,B20,'MiT Strom Pipeline'!$R$6:$R$860,"WON")/D20) -> 0.66666667 | J20: FR | K20: =SUMIF('MiT Strom Pipeline'!$C$6:$C$860,J20,'MiT Strom Pipeline'!$I$6:$I$860) -> 0 | L20: =K20+(26-ROW())*0.0001 -> 0.0006
A21: 7 | B21: =IFERROR(INDEX($J$14:$J$39,MATCH(LARGE($L$14:$L$39,7),$L$14:$L$39,0)),"") -> SG | C21: =IF(B21="","",SUMIF('MiT Strom Pipeline'!$C$6:$C$860,B21,'MiT Strom Pipeline'!$I$6:$I$860)) -> 101192.62 | D21: =IF(B21="","",COUNTIF('MiT Strom Pipeline'!$C$6:$C$860,B21)) -> 3 | E21: =IF(OR(B21="",D21=0),"",COUNTIFS('MiT Strom Pipeline'!$C$6:$C$860,B21,'MiT Strom Pipeline'!$R$6:$R$860,"WON")/D21) -> 0.33333333 | J21: GE | K21: =SUMIF('MiT Strom Pipeline'!$C$6:$C$860,J21,'MiT Strom Pipeline'!$I$6:$I$860) -> 38885 | L21: =K21+(26-ROW())*0.0001 -> 38885.001
A22: 8 | B22: =IFERROR(INDEX($J$14:$J$39,MATCH(LARGE($L$14:$L$39,8),$L$14:$L$39,0)),"") -> GR | C22: =IF(B22="","",SUMIF('MiT Strom Pipeline'!$C$6:$C$860,B22,'MiT Strom Pipeline'!$I$6:$I$860)) -> 77325.62 | D22: =IF(B22="","",COUNTIF('MiT Strom Pipeline'!$C$6:$C$860,B22)) -> 2 | E22: =IF(OR(B22="",D22=0),"",COUNTIFS('MiT Strom Pipeline'!$C$6:$C$860,B22,'MiT Strom Pipeline'!$R$6:$R$860,"WON")/D22) -> 0 | J22: GL | K22: =SUMIF('MiT Strom Pipeline'!$C$6:$C$860,J22,'MiT Strom Pipeline'!$I$6:$I$860) -> 0 | L22: =K22+(26-ROW())*0.0001 -> 0.0004
A23: 9 | B23: =IFERROR(INDEX($J$14:$J$39,MATCH(LARGE($L$14:$L$39,9),$L$14:$L$39,0)),"") -> BE | C23: =IF(B23="","",SUMIF('MiT Strom Pipeline'!$C$6:$C$860,B23,'MiT Strom Pipeline'!$I$6:$I$860)) -> 58012.12 | D23: =IF(B23="","",COUNTIF('MiT Strom Pipeline'!$C$6:$C$860,B23)) -> 5 | E23: =IF(OR(B23="",D23=0),"",COUNTIFS('MiT Strom Pipeline'!$C$6:$C$860,B23,'MiT Strom Pipeline'!$R$6:$R$860,"WON")/D23) -> 0 | J23: GR | K23: =SUMIF('MiT Strom Pipeline'!$C$6:$C$860,J23,'MiT Strom Pipeline'!$I$6:$I$860) -> 77325.62 | L23: =K23+(26-ROW())*0.0001 -> 77325.62
A24: 10 | B24: =IFERROR(INDEX($J$14:$J$39,MATCH(LARGE($L$14:$L$39,10),$L$14:$L$39,0)),"") -> ZG | C24: =IF(B24="","",SUMIF('MiT Strom Pipeline'!$C$6:$C$860,B24,'MiT Strom Pipeline'!$I$6:$I$860)) -> 40491.67 | D24: =IF(B24="","",COUNTIF('MiT Strom Pipeline'!$C$6:$C$860,B24)) -> 1 | E24: =IF(OR(B24="",D24=0),"",COUNTIFS('MiT Strom Pipeline'!$C$6:$C$860,B24,'MiT Strom Pipeline'!$R$6:$R$860,"WON")/D24) -> 0 | J24: JU | K24: =SUMIF('MiT Strom Pipeline'!$C$6:$C$860,J24,'MiT Strom Pipeline'!$I$6:$I$860) -> 0 | L24: =K24+(26-ROW())*0.0001 -> 0.0002
J25: LU | K25: =SUMIF('MiT Strom Pipeline'!$C$6:$C$860,J25,'MiT Strom Pipeline'!$I$6:$I$860) -> 23626.77 | L25: =K25+(26-ROW())*0.0001 -> 23626.77
J26: NE | K26: =SUMIF('MiT Strom Pipeline'!$C$6:$C$860,J26,'MiT Strom Pipeline'!$I$6:$I$860) -> 0 | L26: =K26+(26-ROW())*0.0001 -> 0
A27: Top WON-Deals | J27: NW | K27: =SUMIF('MiT Strom Pipeline'!$C$6:$C$860,J27,'MiT Strom Pipeline'!$I$6:$I$860) -> 0 | L27: =K27+(26-ROW())*0.0001 -> -0.0001
A28: Rang | B28: Kunde | C28: Kanton | D28: Segment | E28: Volumen CHF | F28: Projektstart | G28: Projektende | J28: OW | K28: =SUMIF('MiT Strom Pipeline'!$C$6:$C$860,J28,'MiT Strom Pipeline'!$I$6:$I$860) -> 0 | L28: =K28+(26-ROW())*0.0001 -> -0.0002
A29: 1 | B29: =IFERROR(INDEX('MiT Strom Pipeline'!$B$6:$B$860,MATCH(LARGE('MiT Strom Pipeline'!$AK$6:$AK$860,1),'MiT Strom Pipeline'!$AK$6:$AK$860,0)),"") -> Ice Hockey Championship | C29: =IFERROR(INDEX('MiT Strom Pipeline'!$C$6:$C$860,MATCH(LARGE('MiT Strom Pipeline'!$AK$6:$AK$860,1),'MiT Strom Pipeline'!$AK$6:$AK$860,0)),"") -> ZH | D29: =IFERROR(INDEX('MiT Strom Pipeline'!$D$6:$D$860,MATCH(LARGE('MiT Strom Pipeline'!$AK$6:$AK$860,1),'MiT Strom Pipeline'!$AK$6:$AK$860,0)),"") -> Events & Sport | E29: =IFERROR(INDEX('MiT Strom Pipeline'!$I$6:$I$860,MATCH(LARGE('MiT Strom Pipeline'!$AK$6:$AK$860,1),'MiT Strom Pipeline'!$AK$6:$AK$860,0)),"") -> 380000 | F29: =IFERROR(IF(ISNUMBER(INDEX('MiT Strom Pipeline'!$O$6:$O$860,MATCH(LARGE('MiT Strom Pipeline'!$AK$6:$AK$860,1),'MiT Strom Pipeline'!$AK$6:$AK$860,0))),INDEX('MiT Strom Pipeline'!$O$6:$O$860,MATCH(LARGE('MiT Strom Pipeline'!$AK$6:$AK$860,1),'MiT Strom Pipeline'!$AK$6:$AK$860,0)),IF(INDEX('MiT Strom Pipeline'!$H$6:$H$860,MATCH(LARGE('MiT Strom Pipeline'!$AK$6:$AK$860,1),'MiT Strom Pipeline'!$AK$6:$AK$860,0))="","",INDEX('MiT Strom Pipeline'!$H$6:$H$860,MATCH(LARGE('MiT Strom Pipeline'!$AK$6:$AK$860,1),'MiT Strom Pipeline'!$AK$6:$AK$860,0)))),"") -> Mai | G29: =IFERROR(IF(ISNUMBER(INDEX('MiT Strom Pipeline'!$P$6:$P$860,MATCH(LARGE('MiT Strom Pipeline'!$AK$6:$AK$860,1),'MiT Strom Pipeline'!$AK$6:$AK$860,0))),INDEX('MiT Strom Pipeline'!$P$6:$P$860,MATCH(LARGE('MiT Strom Pipeline'!$AK$6:$AK$860,1),'MiT Strom Pipeline'!$AK$6:$AK$860,0)),""),"") | J29: SG | K29: =SUMIF('MiT Strom Pipeline'!$C$6:$C$860,J29,'MiT Strom Pipeline'!$I$6:$I$860) -> 101192.62 | L29: =K29+(26-ROW())*0.0001 -> 101192.62
A30: 2 | B30: =IFERROR(INDEX('MiT Strom Pipeline'!$B$6:$B$860,MATCH(LARGE('MiT Strom Pipeline'!$AK$6:$AK$860,2),'MiT Strom Pipeline'!$AK$6:$AK$860,0)),"") -> DPR Heat Loadbank | C30: =IFERROR(INDEX('MiT Strom Pipeline'!$C$6:$C$860,MATCH(LARGE('MiT Strom Pipeline'!$AK$6:$AK$860,2),'MiT Strom Pipeline'!$AK$6:$AK$860,0)),"") -> ZH | D30: =IFERROR(INDEX('MiT Strom Pipeline'!$D$6:$D$860,MATCH(LARGE('MiT Strom Pipeline'!$AK$6:$AK$860,2),'MiT Strom Pipeline'!$AK$6:$AK$860,0)),"") -> Datacenter | E30: =IFERROR(INDEX('MiT Strom Pipeline'!$I$6:$I$860,MATCH(LARGE('MiT Strom Pipeline'!$AK$6:$AK$860,2),'MiT Strom Pipeline'!$AK$6:$AK$860,0)),"") -> 333790 | F30: =IFERROR(IF(ISNUMBER(INDEX('MiT Strom Pipeline'!$O$6:$O$860,MATCH(LARGE('MiT Strom Pipeline'!$AK$6:$AK$860,2),'MiT Strom Pipeline'!$AK$6:$AK$860,0))),INDEX('MiT Strom Pipeline'!$O$6:$O$860,MATCH(LARGE('MiT Strom Pipeline'!$AK$6:$AK$860,2),'MiT Strom Pipeline'!$AK$6:$AK$860,0)),IF(INDEX('MiT Strom Pipeline'!$H$6:$H$860,MATCH(LARGE('MiT Strom Pipeline'!$AK$6:$AK$860,2),'MiT Strom Pipeline'!$AK$6:$AK$860,0))="","",INDEX('MiT Strom Pipeline'!$H$6:$H$860,MATCH(LARGE('MiT Strom Pipeline'!$AK$6:$AK$860,2),'MiT Strom Pipeline'!$AK$6:$AK$860,0)))),"") -> Aug | G30: =IFERROR(IF(ISNUMBER(INDEX('MiT Strom Pipeline'!$P$6:$P$860,MATCH(LARGE('MiT Strom Pipeline'!$AK$6:$AK$860,2),'MiT Strom Pipeline'!$AK$6:$AK$860,0))),INDEX('MiT Strom Pipeline'!$P$6:$P$860,MATCH(LARGE('MiT Strom Pipeline'!$AK$6:$AK$860,2),'MiT Strom Pipeline'!$AK$6:$AK$860,0)),""),"") | J30: SH | K30: =SUMIF('MiT Strom Pipeline'!$C$6:$C$860,J30,'MiT Strom Pipeline'!$I$6:$I$860) -> 2637287.6 | L30: =K30+(26-ROW())*0.0001 -> 2637287.6
A31: 3 | B31: =IFERROR(INDEX('MiT Strom Pipeline'!$B$6:$B$860,MATCH(LARGE('MiT Strom Pipeline'!$AK$6:$AK$860,3),'MiT Strom Pipeline'!$AK$6:$AK$860,0)),"") -> DPR Generator Loadbank Test | C31: =IFERROR(INDEX('MiT Strom Pipeline'!$C$6:$C$860,MATCH(LARGE('MiT Strom Pipeline'!$AK$6:$AK$860,3),'MiT Strom Pipeline'!$AK$6:$AK$860,0)),"") -> ZH | D31: =IFERROR(INDEX('MiT Strom Pipeline'!$D$6:$D$860,MATCH(LARGE('MiT Strom Pipeline'!$AK$6:$AK$860,3),'MiT Strom Pipeline'!$AK$6:$AK$860,0)),"") -> Datacenter | E31: =IFERROR(INDEX('MiT Strom Pipeline'!$I$6:$I$860,MATCH(LARGE('MiT Strom Pipeline'!$AK$6:$AK$860,3),'MiT Strom Pipeline'!$AK$6:$AK$860,0)),"") -> 331889.15 | F31: =IFERROR(IF(ISNUMBER(INDEX('MiT Strom Pipeline'!$O$6:$O$860,MATCH(LARGE('MiT Strom Pipeline'!$AK$6:$AK$860,3),'MiT Strom Pipeline'!$AK$6:$AK$860,0))),INDEX('MiT Strom Pipeline'!$O$6:$O$860,MATCH(LARGE('MiT Strom Pipeline'!$AK$6:$AK$860,3),'MiT Strom Pipeline'!$AK$6:$AK$860,0)),IF(INDEX('MiT Strom Pipeline'!$H$6:$H$860,MATCH(LARGE('MiT Strom Pipeline'!$AK$6:$AK$860,3),'MiT Strom Pipeline'!$AK$6:$AK$860,0))="","",INDEX('MiT Strom Pipeline'!$H$6:$H$860,MATCH(LARGE('MiT Strom Pipeline'!$AK$6:$AK$860,3),'MiT Strom Pipeline'!$AK$6:$AK$860,0)))),"") -> Aug | G31: =IFERROR(IF(ISNUMBER(INDEX('MiT Strom Pipeline'!$P$6:$P$860,MATCH(LARGE('MiT Strom Pipeline'!$AK$6:$AK$860,3),'MiT Strom Pipeline'!$AK$6:$AK$860,0))),INDEX('MiT Strom Pipeline'!$P$6:$P$860,MATCH(LARGE('MiT Strom Pipeline'!$AK$6:$AK$860,3),'MiT Strom Pipeline'!$AK$6:$AK$860,0)),""),"") | J31: SO | K31: =SUMIF('MiT Strom Pipeline'!$C$6:$C$860,J31,'MiT Strom Pipeline'!$I$6:$I$860) -> 390750.65 | L31: =K31+(26-ROW())*0.0001 -> 390750.65
A32: 4 | B32: =IFERROR(INDEX('MiT Strom Pipeline'!$B$6:$B$860,MATCH(LARGE('MiT Strom Pipeline'!$AK$6:$AK$860,4),'MiT Strom Pipeline'!$AK$6:$AK$860,0)),"") -> Stagelight – OpenAir Frauenfeld | C32: =IFERROR(INDEX('MiT Strom Pipeline'!$C$6:$C$860,MATCH(LARGE('MiT Strom Pipeline'!$AK$6:$AK$860,4),'MiT Strom Pipeline'!$AK$6:$AK$860,0)),"") -> TG | D32: =IFERROR(INDEX('MiT Strom Pipeline'!$D$6:$D$860,MATCH(LARGE('MiT Strom Pipeline'!$AK$6:$AK$860,4),'MiT Strom Pipeline'!$AK$6:$AK$860,0)),"") -> Events & Kultur | E32: =IFERROR(INDEX('MiT Strom Pipeline'!$I$6:$I$860,MATCH(LARGE('MiT Strom Pipeline'!$AK$6:$AK$860,4),'MiT Strom Pipeline'!$AK$6:$AK$860,0)),"") -> 150000 | F32: =IFERROR(IF(ISNUMBER(INDEX('MiT Strom Pipeline'!$O$6:$O$860,MATCH(LARGE('MiT Strom Pipeline'!$AK$6:$AK$860,4),'MiT Strom Pipeline'!$AK$6:$AK$860,0))),INDEX('MiT Strom Pipeline'!$O$6:$O$860,MATCH(LARGE('MiT Strom Pipeline'!$AK$6:$AK$860,4),'MiT Strom Pipeline'!$AK$6:$AK$860,0)),IF(INDEX('MiT Strom Pipeline'!$H$6:$H$860,MATCH(LARGE('MiT Strom Pipeline'!$AK$6:$AK$860,4),'MiT Strom Pipeline'!$AK$6:$AK$860,0))="","",INDEX('MiT Strom Pipeline'!$H$6:$H$860,MATCH(LARGE('MiT Strom Pipeline'!$AK$6:$AK$860,4),'MiT Strom Pipeline'!$AK$6:$AK$860,0)))),"") -> Juli | G32: =IFERROR(IF(ISNUMBER(INDEX('MiT Strom Pipeline'!$P$6:$P$860,MATCH(LARGE('MiT Strom Pipeline'!$AK$6:$AK$860,4),'MiT Strom Pipeline'!$AK$6:$AK$860,0))),INDEX('MiT Strom Pipeline'!$P$6:$P$860,MATCH(LARGE('MiT Strom Pipeline'!$AK$6:$AK$860,4),'MiT Strom Pipeline'!$AK$6:$AK$860,0)),""),"") | J32: SZ | K32: =SUMIF('MiT Strom Pipeline'!$C$6:$C$860,J32,'MiT Strom Pipeline'!$I$6:$I$860) -> 0 | L32: =K32+(26-ROW())*0.0001 -> -0.0006
A33: 5 | B33: =IFERROR(INDEX('MiT Strom Pipeline'!$B$6:$B$860,MATCH(LARGE('MiT Strom Pipeline'!$AK$6:$AK$860,5),'MiT Strom Pipeline'!$AK$6:$AK$860,0)),"") -> Murg Flums Energie | C33: =IFERROR(INDEX('MiT Strom Pipeline'!$C$6:$C$860,MATCH(LARGE('MiT Strom Pipeline'!$AK$6:$AK$860,5),'MiT Strom Pipeline'!$AK$6:$AK$860,0)),"") -> SG | D33: =IFERROR(INDEX('MiT Strom Pipeline'!$D$6:$D$860,MATCH(LARGE('MiT Strom Pipeline'!$AK$6:$AK$860,5),'MiT Strom Pipeline'!$AK$6:$AK$860,0)),"") -> EVU / Energie | E33: =IFERROR(INDEX('MiT Strom Pipeline'!$I$6:$I$860,MATCH(LARGE('MiT Strom Pipeline'!$AK$6:$AK$860,5),'MiT Strom Pipeline'!$AK$6:$AK$860,0)),"") -> 96658.69 | F33: =IFERROR(IF(ISNUMBER(INDEX('MiT Strom Pipeline'!$O$6:$O$860,MATCH(LARGE('MiT Strom Pipeline'!$AK$6:$AK$860,5),'MiT Strom Pipeline'!$AK$6:$AK$860,0))),INDEX('MiT Strom Pipeline'!$O$6:$O$860,MATCH(LARGE('MiT Strom Pipeline'!$AK$6:$AK$860,5),'MiT Strom Pipeline'!$AK$6:$AK$860,0)),IF(INDEX('MiT Strom Pipeline'!$H$6:$H$860,MATCH(LARGE('MiT Strom Pipeline'!$AK$6:$AK$860,5),'MiT Strom Pipeline'!$AK$6:$AK$860,0))="","",INDEX('MiT Strom Pipeline'!$H$6:$H$860,MATCH(LARGE('MiT Strom Pipeline'!$AK$6:$AK$860,5),'MiT Strom Pipeline'!$AK$6:$AK$860,0)))),"") -> Auf Abruf | G33: =IFERROR(IF(ISNUMBER(INDEX('MiT Strom Pipeline'!$P$6:$P$860,MATCH(LARGE('MiT Strom Pipeline'!$AK$6:$AK$860,5),'MiT Strom Pipeline'!$AK$6:$AK$860,0))),INDEX('MiT Strom Pipeline'!$P$6:$P$860,MATCH(LARGE('MiT Strom Pipeline'!$AK$6:$AK$860,5),'MiT Strom Pipeline'!$AK$6:$AK$860,0)),""),"") | J33: TG | K33: =SUMIF('MiT Strom Pipeline'!$C$6:$C$860,J33,'MiT Strom Pipeline'!$I$6:$I$860) -> 160817.26 | L33: =K33+(26-ROW())*0.0001 -> 160817.26
A34: 6 | B34: =IFERROR(INDEX('MiT Strom Pipeline'!$B$6:$B$860,MATCH(LARGE('MiT Strom Pipeline'!$AK$6:$AK$860,6),'MiT Strom Pipeline'!$AK$6:$AK$860,0)),"") -> Gampeln | C34: =IFERROR(INDEX('MiT Strom Pipeline'!$C$6:$C$860,MATCH(LARGE('MiT Strom Pipeline'!$AK$6:$AK$860,6),'MiT Strom Pipeline'!$AK$6:$AK$860,0)),"") -> VS | D34: =IFERROR(INDEX('MiT Strom Pipeline'!$D$6:$D$860,MATCH(LARGE('MiT Strom Pipeline'!$AK$6:$AK$860,6),'MiT Strom Pipeline'!$AK$6:$AK$860,0)),"") -> Event | E34: =IFERROR(INDEX('MiT Strom Pipeline'!$I$6:$I$860,MATCH(LARGE('MiT Strom Pipeline'!$AK$6:$AK$860,6),'MiT Strom Pipeline'!$AK$6:$AK$860,0)),"") -> 80621.21 | F34: =IFERROR(IF(ISNUMBER(INDEX('MiT Strom Pipeline'!$O$6:$O$860,MATCH(LARGE('MiT Strom Pipeline'!$AK$6:$AK$860,6),'MiT Strom Pipeline'!$AK$6:$AK$860,0))),INDEX('MiT Strom Pipeline'!$O$6:$O$860,MATCH(LARGE('MiT Strom Pipeline'!$AK$6:$AK$860,6),'MiT Strom Pipeline'!$AK$6:$AK$860,0)),IF(INDEX('MiT Strom Pipeline'!$H$6:$H$860,MATCH(LARGE('MiT Strom Pipeline'!$AK$6:$AK$860,6),'MiT Strom Pipeline'!$AK$6:$AK$860,0))="","",INDEX('MiT Strom Pipeline'!$H$6:$H$860,MATCH(LARGE('MiT Strom Pipeline'!$AK$6:$AK$860,6),'MiT Strom Pipeline'!$AK$6:$AK$860,0)))),"") -> Aug | G34: =IFERROR(IF(ISNUMBER(INDEX('MiT Strom Pipeline'!$P$6:$P$860,MATCH(LARGE('MiT Strom Pipeline'!$AK$6:$AK$860,6),'MiT Strom Pipeline'!$AK$6:$AK$860,0))),INDEX('MiT Strom Pipeline'!$P$6:$P$860,MATCH(LARGE('MiT Strom Pipeline'!$AK$6:$AK$860,6),'MiT Strom Pipeline'!$AK$6:$AK$860,0)),""),"") | J34: TI | K34: =SUMIF('MiT Strom Pipeline'!$C$6:$C$860,J34,'MiT Strom Pipeline'!$I$6:$I$860) -> 0 | L34: =K34+(26-ROW())*0.0001 -> -0.0008
A35: 7 | B35: =IFERROR(INDEX('MiT Strom Pipeline'!$B$6:$B$860,MATCH(LARGE('MiT Strom Pipeline'!$AK$6:$AK$860,7),'MiT Strom Pipeline'!$AK$6:$AK$860,0)),"") -> EIDG AMT Agroscope | C35: =IFERROR(INDEX('MiT Strom Pipeline'!$C$6:$C$860,MATCH(LARGE('MiT Strom Pipeline'!$AK$6:$AK$860,7),'MiT Strom Pipeline'!$AK$6:$AK$860,0)),"") -> ZH | D35: =IFERROR(INDEX('MiT Strom Pipeline'!$D$6:$D$860,MATCH(LARGE('MiT Strom Pipeline'!$AK$6:$AK$860,7),'MiT Strom Pipeline'!$AK$6:$AK$860,0)),"") -> Forschung | E35: =IFERROR(INDEX('MiT Strom Pipeline'!$I$6:$I$860,MATCH(LARGE('MiT Strom Pipeline'!$AK$6:$AK$860,7),'MiT Strom Pipeline'!$AK$6:$AK$860,0)),"") -> 13533 | F35: =IFERROR(IF(ISNUMBER(INDEX('MiT Strom Pipeline'!$O$6:$O$860,MATCH(LARGE('MiT Strom Pipeline'!$AK$6:$AK$860,7),'MiT Strom Pipeline'!$AK$6:$AK$860,0))),INDEX('MiT Strom Pipeline'!$O$6:$O$860,MATCH(LARGE('MiT Strom Pipeline'!$AK$6:$AK$860,7),'MiT Strom Pipeline'!$AK$6:$AK$860,0)),IF(INDEX('MiT Strom Pipeline'!$H$6:$H$860,MATCH(LARGE('MiT Strom Pipeline'!$AK$6:$AK$860,7),'MiT Strom Pipeline'!$AK$6:$AK$860,0))="","",INDEX('MiT Strom Pipeline'!$H$6:$H$860,MATCH(LARGE('MiT Strom Pipeline'!$AK$6:$AK$860,7),'MiT Strom Pipeline'!$AK$6:$AK$860,0)))),"") -> Aug | G35: =IFERROR(IF(ISNUMBER(INDEX('MiT Strom Pipeline'!$P$6:$P$860,MATCH(LARGE('MiT Strom Pipeline'!$AK$6:$AK$860,7),'MiT Strom Pipeline'!$AK$6:$AK$860,0))),INDEX('MiT Strom Pipeline'!$P$6:$P$860,MATCH(LARGE('MiT Strom Pipeline'!$AK$6:$AK$860,7),'MiT Strom Pipeline'!$AK$6:$AK$860,0)),""),"") | J35: UR | K35: =SUMIF('MiT Strom Pipeline'!$C$6:$C$860,J35,'MiT Strom Pipeline'!$I$6:$I$860) -> 0 | L35: =K35+(26-ROW())*0.0001 -> -0.0009
A36: 8 | B36: =IFERROR(INDEX('MiT Strom Pipeline'!$B$6:$B$860,MATCH(LARGE('MiT Strom Pipeline'!$AK$6:$AK$860,8),'MiT Strom Pipeline'!$AK$6:$AK$860,0)),"") -> GETEC Park.Swiss AG | C36: =IFERROR(INDEX('MiT Strom Pipeline'!$C$6:$C$860,MATCH(LARGE('MiT Strom Pipeline'!$AK$6:$AK$860,8),'MiT Strom Pipeline'!$AK$6:$AK$860,0)),"") -> BL | D36: =IFERROR(INDEX('MiT Strom Pipeline'!$D$6:$D$860,MATCH(LARGE('MiT Strom Pipeline'!$AK$6:$AK$860,8),'MiT Strom Pipeline'!$AK$6:$AK$860,0)),"") -> Industrie | E36: =IFERROR(INDEX('MiT Strom Pipeline'!$I$6:$I$860,MATCH(LARGE('MiT Strom Pipeline'!$AK$6:$AK$860,8),'MiT Strom Pipeline'!$AK$6:$AK$860,0)),"") -> 13472.18 | F36: =IFERROR(IF(ISNUMBER(INDEX('MiT Strom Pipeline'!$O$6:$O$860,MATCH(LARGE('MiT Strom Pipeline'!$AK$6:$AK$860,8),'MiT Strom Pipeline'!$AK$6:$AK$860,0))),INDEX('MiT Strom Pipeline'!$O$6:$O$860,MATCH(LARGE('MiT Strom Pipeline'!$AK$6:$AK$860,8),'MiT Strom Pipeline'!$AK$6:$AK$860,0)),IF(INDEX('MiT Strom Pipeline'!$H$6:$H$860,MATCH(LARGE('MiT Strom Pipeline'!$AK$6:$AK$860,8),'MiT Strom Pipeline'!$AK$6:$AK$860,0))="","",INDEX('MiT Strom Pipeline'!$H$6:$H$860,MATCH(LARGE('MiT Strom Pipeline'!$AK$6:$AK$860,8),'MiT Strom Pipeline'!$AK$6:$AK$860,0)))),"") -> August | G36: =IFERROR(IF(ISNUMBER(INDEX('MiT Strom Pipeline'!$P$6:$P$860,MATCH(LARGE('MiT Strom Pipeline'!$AK$6:$AK$860,8),'MiT Strom Pipeline'!$AK$6:$AK$860,0))),INDEX('MiT Strom Pipeline'!$P$6:$P$860,MATCH(LARGE('MiT Strom Pipeline'!$AK$6:$AK$860,8),'MiT Strom Pipeline'!$AK$6:$AK$860,0)),""),"") | J36: VD | K36: =SUMIF('MiT Strom Pipeline'!$C$6:$C$860,J36,'MiT Strom Pipeline'!$I$6:$I$860) -> 0 | L36: =K36+(26-ROW())*0.0001 -> -0.001
A37: 9 | B37: =IFERROR(INDEX('MiT Strom Pipeline'!$B$6:$B$860,MATCH(LARGE('MiT Strom Pipeline'!$AK$6:$AK$860,9),'MiT Strom Pipeline'!$AK$6:$AK$860,0)),"") -> Oerlikon Metco Wohlen | C37: =IFERROR(INDEX('MiT Strom Pipeline'!$C$6:$C$860,MATCH(LARGE('MiT Strom Pipeline'!$AK$6:$AK$860,9),'MiT Strom Pipeline'!$AK$6:$AK$860,0)),"") -> AG | D37: =IFERROR(INDEX('MiT Strom Pipeline'!$D$6:$D$860,MATCH(LARGE('MiT Strom Pipeline'!$AK$6:$AK$860,9),'MiT Strom Pipeline'!$AK$6:$AK$860,0)),"") -> Industrie / Oberfläche | E37: =IFERROR(INDEX('MiT Strom Pipeline'!$I$6:$I$860,MATCH(LARGE('MiT Strom Pipeline'!$AK$6:$AK$860,9),'MiT Strom Pipeline'!$AK$6:$AK$860,0)),"") -> 13100 | F37: =IFERROR(IF(ISNUMBER(INDEX('MiT Strom Pipeline'!$O$6:$O$860,MATCH(LARGE('MiT Strom Pipeline'!$AK$6:$AK$860,9),'MiT Strom Pipeline'!$AK$6:$AK$860,0))),INDEX('MiT Strom Pipeline'!$O$6:$O$860,MATCH(LARGE('MiT Strom Pipeline'!$AK$6:$AK$860,9),'MiT Strom Pipeline'!$AK$6:$AK$860,0)),IF(INDEX('MiT Strom Pipeline'!$H$6:$H$860,MATCH(LARGE('MiT Strom Pipeline'!$AK$6:$AK$860,9),'MiT Strom Pipeline'!$AK$6:$AK$860,0))="","",INDEX('MiT Strom Pipeline'!$H$6:$H$860,MATCH(LARGE('MiT Strom Pipeline'!$AK$6:$AK$860,9),'MiT Strom Pipeline'!$AK$6:$AK$860,0)))),"") -> April | G37: =IFERROR(IF(ISNUMBER(INDEX('MiT Strom Pipeline'!$P$6:$P$860,MATCH(LARGE('MiT Strom Pipeline'!$AK$6:$AK$860,9),'MiT Strom Pipeline'!$AK$6:$AK$860,0))),INDEX('MiT Strom Pipeline'!$P$6:$P$860,MATCH(LARGE('MiT Strom Pipeline'!$AK$6:$AK$860,9),'MiT Strom Pipeline'!$AK$6:$AK$860,0)),""),"") | J37: VS | K37: =SUMIF('MiT Strom Pipeline'!$C$6:$C$860,J37,'MiT Strom Pipeline'!$I$6:$I$860) -> 303790.2 | L37: =K37+(26-ROW())*0.0001 -> 303790.2
A38: 10 | B38: =IFERROR(INDEX('MiT Strom Pipeline'!$B$6:$B$860,MATCH(LARGE('MiT Strom Pipeline'!$AK$6:$AK$860,10),'MiT Strom Pipeline'!$AK$6:$AK$860,0)),"") -> Siemens | C38: =IFERROR(INDEX('MiT Strom Pipeline'!$C$6:$C$860,MATCH(LARGE('MiT Strom Pipeline'!$AK$6:$AK$860,10),'MiT Strom Pipeline'!$AK$6:$AK$860,0)),"") -> ZH | D38: =IFERROR(INDEX('MiT Strom Pipeline'!$D$6:$D$860,MATCH(LARGE('MiT Strom Pipeline'!$AK$6:$AK$860,10),'MiT Strom Pipeline'!$AK$6:$AK$860,0)),"") -> Industrie / Elektro | E38: =IFERROR(INDEX('MiT Strom Pipeline'!$I$6:$I$860,MATCH(LARGE('MiT Strom Pipeline'!$AK$6:$AK$860,10),'MiT Strom Pipeline'!$AK$6:$AK$860,0)),"") -> 10000 | F38: =IFERROR(IF(ISNUMBER(INDEX('MiT Strom Pipeline'!$O$6:$O$860,MATCH(LARGE('MiT Strom Pipeline'!$AK$6:$AK$860,10),'MiT Strom Pipeline'!$AK$6:$AK$860,0))),INDEX('MiT Strom Pipeline'!$O$6:$O$860,MATCH(LARGE('MiT Strom Pipeline'!$AK$6:$AK$860,10),'MiT Strom Pipeline'!$AK$6:$AK$860,0)),IF(INDEX('MiT Strom Pipeline'!$H$6:$H$860,MATCH(LARGE('MiT Strom Pipeline'!$AK$6:$AK$860,10),'MiT Strom Pipeline'!$AK$6:$AK$860,0))="","",INDEX('MiT Strom Pipeline'!$H$6:$H$860,MATCH(LARGE('MiT Strom Pipeline'!$AK$6:$AK$860,10),'MiT Strom Pipeline'!$AK$6:$AK$860,0)))),"") -> tbd | G38: =IFERROR(IF(ISNUMBER(INDEX('MiT Strom Pipeline'!$P$6:$P$860,MATCH(LARGE('MiT Strom Pipeline'!$AK$6:$AK$860,10),'MiT Strom Pipeline'!$AK$6:$AK$860,0))),INDEX('MiT Strom Pipeline'!$P$6:$P$860,MATCH(LARGE('MiT Strom Pipeline'!$AK$6:$AK$860,10),'MiT Strom Pipeline'!$AK$6:$AK$860,0)),""),"") | J38: ZG | K38: =SUMIF('MiT Strom Pipeline'!$C$6:$C$860,J38,'MiT Strom Pipeline'!$I$6:$I$860) -> 40491.67 | L38: =K38+(26-ROW())*0.0001 -> 40491.669
J39: ZH | K39: =SUMIF('MiT Strom Pipeline'!$C$6:$C$860,J39,'MiT Strom Pipeline'!$I$6:$I$860) -> 2732239 | L39: =K39+(26-ROW())*0.0001 -> 2732239
A40: ↻ Auto-Update aus Pipeline · Sortiert nach Volumen ↓ · Nur WON mit numerischem Volumen
A43: ⚖️ Wahrscheinlichkeits-Bewertung (Aggreko-Modell)
A44: Band | B44: Faktor | C44: Anzahl Deals | D44: Umsatz CHF | E44: Gewichtet CHF
A45: ='⚖️ Wahrscheinlichkeit'!$A$17 -> 0 – 44 % | B45: ='⚖️ Wahrscheinlichkeit'!$D$17 -> 0 | C45: ='⚖️ Wahrscheinlichkeit'!$E$17 -> 30 | D45: ='⚖️ Wahrscheinlichkeit'!$F$17 -> 5092182.2 | E45: ='⚖️ Wahrscheinlichkeit'!$G$17 -> 0
A46: ='⚖️ Wahrscheinlichkeit'!$A$18 -> 45 – 59 % | B46: ='⚖️ Wahrscheinlichkeit'!$D$18 -> 0.3 | C46: ='⚖️ Wahrscheinlichkeit'!$E$18 -> 0 | D46: ='⚖️ Wahrscheinlichkeit'!$F$18 -> 0 | E46: ='⚖️ Wahrscheinlichkeit'!$G$18 -> 0
A47: ='⚖️ Wahrscheinlichkeit'!$A$19 -> 60 – 89 % | B47: ='⚖️ Wahrscheinlichkeit'!$D$19 -> 0.5 | C47: ='⚖️ Wahrscheinlichkeit'!$E$19 -> 2 | D47: ='⚖️ Wahrscheinlichkeit'!$F$19 -> 268500.23 | E47: ='⚖️ Wahrscheinlichkeit'!$G$19 -> 134250.11
A48: ='⚖️ Wahrscheinlichkeit'!$A$20 -> 90 – 99 % | B48: ='⚖️ Wahrscheinlichkeit'!$D$20 -> 0.9 | C48: ='⚖️ Wahrscheinlichkeit'!$E$20 -> 2 | D48: ='⚖️ Wahrscheinlichkeit'!$F$20 -> 72913.72 | E48: ='⚖️ Wahrscheinlichkeit'!$G$20 -> 65622.348
A49: ='⚖️ Wahrscheinlichkeit'!$A$21 -> 100 % · WON | B49: ='⚖️ Wahrscheinlichkeit'!$D$21 -> 1 | C49: ='⚖️ Wahrscheinlichkeit'!$E$21 -> 12 | D49: ='⚖️ Wahrscheinlichkeit'!$F$21 -> 1428553.1 | E49: ='⚖️ Wahrscheinlichkeit'!$G$21 -> 1428553.1
A50: TOTAL aktiv | C50: ='⚖️ Wahrscheinlichkeit'!$E$22 -> 46 | D50: ='⚖️ Wahrscheinlichkeit'!$F$22 -> 6862149.2 | E50: ='⚖️ Wahrscheinlichkeit'!$G$22 -> 1628425.6
A51: ="Faktoren: 0–44 % → 0 % | 45–59 % → 30 % | 60–89 % → 50 % | 90–99 % → 90 % | 100 % → 100 %. Gewichtungsgrad gesamt: "&TEXT('⚖️ Wahrscheinlichkeit'!$H$22,"0.0%")&" · Modell: Blatt «⚖️ Wahrscheinlichkeit»" -> Faktoren: 0–44 % → 0 % | 45–59 % → 30 % | 60–89 % → 50 % | 90–99 % → 90 % | 100 % → 100 %. Gewichtungsgrad gesamt: 23.7% · Modell: Blatt «⚖️ Wahrscheinlichkeit»
A53: 📅 Zeitliche Verteilung nach Monat des Projektstarts
A54: Bezugsjahr | B54: =YEAR(TODAY()) -> 2026
A55: Monat | B55: Quartal | C55: Anzahl | D55: Volumen CHF | E55: Anteil
A56: Januar | B56: Q1 | C56: =SUMPRODUCT('MiT Strom Pipeline'!$AP$6:$AP$860,--('MiT Strom Pipeline'!$AX$6:$AX$860=DATE($B$54,1,1))) -> 0 | D56: =SUMPRODUCT('MiT Strom Pipeline'!$AP$6:$AP$860,--('MiT Strom Pipeline'!$AX$6:$AX$860=DATE($B$54,1,1)),'MiT Strom Pipeline'!$AL$6:$AL$860) -> 0 | E56: =IFERROR(SUMPRODUCT('MiT Strom Pipeline'!$AP$6:$AP$860,--('MiT Strom Pipeline'!$AX$6:$AX$860=DATE($B$54,1,1)),'MiT Strom Pipeline'!$AL$6:$AL$860)/SUMPRODUCT('MiT Strom Pipeline'!$AP$6:$AP$860,'MiT Strom Pipeline'!$AL$6:$AL$860),0) -> 0
A57: Februar | B57: Q1 | C57: =SUMPRODUCT('MiT Strom Pipeline'!$AP$6:$AP$860,--('MiT Strom Pipeline'!$AX$6:$AX$860=DATE($B$54,2,1))) -> 0 | D57: =SUMPRODUCT('MiT Strom Pipeline'!$AP$6:$AP$860,--('MiT Strom Pipeline'!$AX$6:$AX$860=DATE($B$54,2,1)),'MiT Strom Pipeline'!$AL$6:$AL$860) -> 0 | E57: =IFERROR(SUMPRODUCT('MiT Strom Pipeline'!$AP$6:$AP$860,--('MiT Strom Pipeline'!$AX$6:$AX$860=DATE($B$54,2,1)),'MiT Strom Pipeline'!$AL$6:$AL$860)/SUMPRODUCT('MiT Strom Pipeline'!$AP$6:$AP$860,'MiT Strom Pipeline'!$AL$6:$AL$860),0) -> 0
A58: März | B58: Q1 | C58: =SUMPRODUCT('MiT Strom Pipeline'!$AP$6:$AP$860,--('MiT Strom Pipeline'!$AX$6:$AX$860=DATE($B$54,3,1))) -> 0 | D58: =SUMPRODUCT('MiT Strom Pipeline'!$AP$6:$AP$860,--('MiT Strom Pipeline'!$AX$6:$AX$860=DATE($B$54,3,1)),'MiT Strom Pipeline'!$AL$6:$AL$860) -> 0 | E58: =IFERROR(SUMPRODUCT('MiT Strom Pipeline'!$AP$6:$AP$860,--('MiT Strom Pipeline'!$AX$6:$AX$860=DATE($B$54,3,1)),'MiT Strom Pipeline'!$AL$6:$AL$860)/SUMPRODUCT('MiT Strom Pipeline'!$AP$6:$AP$860,'MiT Strom Pipeline'!$AL$6:$AL$860),0) -> 0
A59: April | B59: Q2 | C59: =SUMPRODUCT('MiT Strom Pipeline'!$AP$6:$AP$860,--('MiT Strom Pipeline'!$AX$6:$AX$860=DATE($B$54,4,1))) -> 0 | D59: =SUMPRODUCT('MiT Strom Pipeline'!$AP$6:$AP$860,--('MiT Strom Pipeline'!$AX$6:$AX$860=DATE($B$54,4,1)),'MiT Strom Pipeline'!$AL$6:$AL$860) -> 0 | E59: =IFERROR(SUMPRODUCT('MiT Strom Pipeline'!$AP$6:$AP$860,--('MiT Strom Pipeline'!$AX$6:$AX$860=DATE($B$54,4,1)),'MiT Strom Pipeline'!$AL$6:$AL$860)/SUMPRODUCT('MiT Strom Pipeline'!$AP$6:$AP$860,'MiT Strom Pipeline'!$AL$6:$AL$860),0) -> 0
A60: Mai | B60: Q2 | C60: =SUMPRODUCT('MiT Strom Pipeline'!$AP$6:$AP$860,--('MiT Strom Pipeline'!$AX$6:$AX$860=DATE($B$54,5,1))) -> 0 | D60: =SUMPRODUCT('MiT Strom Pipeline'!$AP$6:$AP$860,--('MiT Strom Pipeline'!$AX$6:$AX$860=DATE($B$54,5,1)),'MiT Strom Pipeline'!$AL$6:$AL$860) -> 0 | E60: =IFERROR(SUMPRODUCT('MiT Strom Pipeline'!$AP$6:$AP$860,--('MiT Strom Pipeline'!$AX$6:$AX$860=DATE($B$54,5,1)),'MiT Strom Pipeline'!$AL$6:$AL$860)/SUMPRODUCT('MiT Strom Pipeline'!$AP$6:$AP$860,'MiT Strom Pipeline'!$AL$6:$AL$860),0) -> 0
A61: Juni | B61: Q2 | C61: =SUMPRODUCT('MiT Strom Pipeline'!$AP$6:$AP$860,--('MiT Strom Pipeline'!$AX$6:$AX$860=DATE($B$54,6,1))) -> 0 | D61: =SUMPRODUCT('MiT Strom Pipeline'!$AP$6:$AP$860,--('MiT Strom Pipeline'!$AX$6:$AX$860=DATE($B$54,6,1)),'MiT Strom Pipeline'!$AL$6:$AL$860) -> 0 | E61: =IFERROR(SUMPRODUCT('MiT Strom Pipeline'!$AP$6:$AP$860,--('MiT Strom Pipeline'!$AX$6:$AX$860=DATE($B$54,6,1)),'MiT Strom Pipeline'!$AL$6:$AL$860)/SUMPRODUCT('MiT Strom Pipeline'!$AP$6:$AP$860,'MiT Strom Pipeline'!$AL$6:$AL$860),0) -> 0
A62: Juli | B62: Q3 | C62: =SUMPRODUCT('MiT Strom Pipeline'!$AP$6:$AP$860,--('MiT Strom Pipeline'!$AX$6:$AX$860=DATE($B$54,7,1))) -> 0 | D62: =SUMPRODUCT('MiT Strom Pipeline'!$AP$6:$AP$860,--('MiT Strom Pipeline'!$AX$6:$AX$860=DATE($B$54,7,1)),'MiT Strom Pipeline'!$AL$6:$AL$860) -> 0 | E62: =IFERROR(SUMPRODUCT('MiT Strom Pipeline'!$AP$6:$AP$860,--('MiT Strom Pipeline'!$AX$6:$AX$860=DATE($B$54,7,1)),'MiT Strom Pipeline'!$AL$6:$AL$860)/SUMPRODUCT('MiT Strom Pipeline'!$AP$6:$AP$860,'MiT Strom Pipeline'!$AL$6:$AL$860),0) -> 0
A63: August | B63: Q3 | C63: =SUMPRODUCT('MiT Strom Pipeline'!$AP$6:$AP$860,--('MiT Strom Pipeline'!$AX$6:$AX$860=DATE($B$54,8,1))) -> 0 | D63: =SUMPRODUCT('MiT Strom Pipeline'!$AP$6:$AP$860,--('MiT Strom Pipeline'!$AX$6:$AX$860=DATE($B$54,8,1)),'MiT Strom Pipeline'!$AL$6:$AL$860) -> 0 | E63: =IFERROR(SUMPRODUCT('MiT Strom Pipeline'!$AP$6:$AP$860,--('MiT Strom Pipeline'!$AX$6:$AX$860=DATE($B$54,8,1)),'MiT Strom Pipeline'!$AL$6:$AL$860)/SUMPRODUCT('MiT Strom Pipeline'!$AP$6:$AP$860,'MiT Strom Pipeline'!$AL$6:$AL$860),0) -> 0
A64: September | B64: Q3 | C64: =SUMPRODUCT('MiT Strom Pipeline'!$AP$6:$AP$860,--('MiT Strom Pipeline'!$AX$6:$AX$860=DATE($B$54,9,1))) -> 0 | D64: =SUMPRODUCT('MiT Strom Pipeline'!$AP$6:$AP$860,--('MiT Strom Pipeline'!$AX$6:$AX$860=DATE($B$54,9,1)),'MiT Strom Pipeline'!$AL$6:$AL$860) -> 0 | E64: =IFERROR(SUMPRODUCT('MiT Strom Pipeline'!$AP$6:$AP$860,--('MiT Strom Pipeline'!$AX$6:$AX$860=DATE($B$54,9,1)),'MiT Strom Pipeline'!$AL$6:$AL$860)/SUMPRODUCT('MiT Strom Pipeline'!$AP$6:$AP$860,'MiT Strom Pipeline'!$AL$6:$AL$860),0) -> 0
A65: Oktober | B65: Q4 | C65: =SUMPRODUCT('MiT Strom Pipeline'!$AP$6:$AP$860,--('MiT Strom Pipeline'!$AX$6:$AX$860=DATE($B$54,10,1))) -> 0 | D65: =SUMPRODUCT('MiT Strom Pipeline'!$AP$6:$AP$860,--('MiT Strom Pipeline'!$AX$6:$AX$860=DATE($B$54,10,1)),'MiT Strom Pipeline'!$AL$6:$AL$860) -> 0 | E65: =IFERROR(SUMPRODUCT('MiT Strom Pipeline'!$AP$6:$AP$860,--('MiT Strom Pipeline'!$AX$6:$AX$860=DATE($B$54,10,1)),'MiT Strom Pipeline'!$AL$6:$AL$860)/SUMPRODUCT('MiT Strom Pipeline'!$AP$6:$AP$860,'MiT Strom Pipeline'!$AL$6:$AL$860),0) -> 0
A66: November | B66: Q4 | C66: =SUMPRODUCT('MiT Strom Pipeline'!$AP$6:$AP$860,--('MiT Strom Pipeline'!$AX$6:$AX$860=DATE($B$54,11,1))) -> 0 | D66: =SUMPRODUCT('MiT Strom Pipeline'!$AP$6:$AP$860,--('MiT Strom Pipeline'!$AX$6:$AX$860=DATE($B$54,11,1)),'MiT Strom Pipeline'!$AL$6:$AL$860) -> 0 | E66: =IFERROR(SUMPRODUCT('MiT Strom Pipeline'!$AP$6:$AP$860,--('MiT Strom Pipeline'!$AX$6:$AX$860=DATE($B$54,11,1)),'MiT Strom Pipeline'!$AL$6:$AL$860)/SUMPRODUCT('MiT Strom Pipeline'!$AP$6:$AP$860,'MiT Strom Pipeline'!$AL$6:$AL$860),0) -> 0
A67: Dezember | B67: Q4 | C67: =SUMPRODUCT('MiT Strom Pipeline'!$AP$6:$AP$860,--('MiT Strom Pipeline'!$AX$6:$AX$860=DATE($B$54,12,1))) -> 0 | D67: =SUMPRODUCT('MiT Strom Pipeline'!$AP$6:$AP$860,--('MiT Strom Pipeline'!$AX$6:$AX$860=DATE($B$54,12,1)),'MiT Strom Pipeline'!$AL$6:$AL$860) -> 0 | E67: =IFERROR(SUMPRODUCT('MiT Strom Pipeline'!$AP$6:$AP$860,--('MiT Strom Pipeline'!$AX$6:$AX$860=DATE($B$54,12,1)),'MiT Strom Pipeline'!$AL$6:$AL$860)/SUMPRODUCT('MiT Strom Pipeline'!$AP$6:$AP$860,'MiT Strom Pipeline'!$AL$6:$AL$860),0) -> 0
A68: andere Jahre | B68: — | C68: =SUMPRODUCT('MiT Strom Pipeline'!$AP$6:$AP$860,'MiT Strom Pipeline'!$AY$6:$AY$860,--('MiT Strom Pipeline'!$AX$6:$AX$860<DATE($B$54,1,1))+--('MiT Strom Pipeline'!$AX$6:$AX$860>DATE($B$54,12,1))) -> 0 | D68: =SUMPRODUCT('MiT Strom Pipeline'!$AP$6:$AP$860,'MiT Strom Pipeline'!$AY$6:$AY$860,--('MiT Strom Pipeline'!$AX$6:$AX$860<DATE($B$54,1,1))+--('MiT Strom Pipeline'!$AX$6:$AX$860>DATE($B$54,12,1)),'MiT Strom Pipeline'!$AL$6:$AL$860) -> 0 | E68: =IFERROR(SUMPRODUCT('MiT Strom Pipeline'!$AP$6:$AP$860,'MiT Strom Pipeline'!$AY$6:$AY$860,--('MiT Strom Pipeline'!$AX$6:$AX$860<DATE($B$54,1,1))+--('MiT Strom Pipeline'!$AX$6:$AX$860>DATE($B$54,12,1)),'MiT Strom Pipeline'!$AL$6:$AL$860)/SUMPRODUCT('MiT Strom Pipeline'!$AP$6:$AP$860,'MiT Strom Pipeline'!$AL$6:$AL$860),0) -> 0
A69: ohne erfassten Zeitraum | B69: — | C69: =SUMPRODUCT('MiT Strom Pipeline'!$AP$6:$AP$860,--('MiT Strom Pipeline'!$AY$6:$AY$860=0)) -> 46 | D69: =SUMPRODUCT('MiT Strom Pipeline'!$AP$6:$AP$860,--('MiT Strom Pipeline'!$AY$6:$AY$860=0),'MiT Strom Pipeline'!$AL$6:$AL$860) -> 6862149.2 | E69: =IFERROR(SUMPRODUCT('MiT Strom Pipeline'!$AP$6:$AP$860,--('MiT Strom Pipeline'!$AY$6:$AY$860=0),'MiT Strom Pipeline'!$AL$6:$AL$860)/SUMPRODUCT('MiT Strom Pipeline'!$AP$6:$AP$860,'MiT Strom Pipeline'!$AL$6:$AL$860),0) -> 1
A70: TOTAL aktiv | C70: =SUM(C56:C69) -> 46 | D70: =SUM(D56:D69) -> 6862149.2 | E70: =SUM(E56:E69) -> 1
A72: 🖨 Strg+P → «Als PDF speichern» · Druckbereich A4 ist gesetzt

Sheet CEO Report
A1: ="⚡ MiT Strom Schweiz — CEO Sales Report · "&TEXT(TODAY(),"MMMM YYYY") -> ⚡ MiT Strom Schweiz — CEO Sales Report · August 2026
A2: Mobil in Time AG · An Aggreko Company · Burak Ücöz · Neue Einträge in «MiT Strom Pipeline» erscheinen automatisch.
A5: ✅ AUFTRAGSEINGANG (WON) | E5: 📄 OFFERTE — Laufend | I5: 🎯 OPPORTUNITÄT
A6: =SUMIFS('MiT Strom Pipeline'!I$6:I$860,'MiT Strom Pipeline'!R$6:R$860,"WON") -> 1428553.1 | E6: =SUMIFS('MiT Strom Pipeline'!I$6:I$860,'MiT Strom Pipeline'!R$6:R$860,"offered")+SUMIFS('MiT Strom Pipeline'!I$6:I$860,'MiT Strom Pipeline'!R$6:R$860,"to be offered")+SUMIFS('MiT Strom Pipeline'!I$6:I$860,'MiT Strom Pipeline'!R$6:R$860,"on hold") -> 5433596.1 | I6: =SUMIFS('MiT Strom Pipeline'!I$6:I$860,'MiT Strom Pipeline'!R$6:R$860,"follow-up")+SUMIFS('MiT Strom Pipeline'!I$6:I$860,'MiT Strom Pipeline'!R$6:R$860,"Evaluation")+SUMIFS('MiT Strom Pipeline'!I$6:I$860,'MiT Strom Pipeline'!R$6:R$860,"tbd")+SUMIFS('MiT Strom Pipeline'!I$6:I$860,'MiT Strom Pipeline'!R$6:R$860,"In evaluation") -> 0
A7: =COUNTIF('MiT Strom Pipeline'!R$6:R$860,"WON") -> 12 | E7: =COUNTIF('MiT Strom Pipeline'!R$6:R$860,"offered")+COUNTIF('MiT Strom Pipeline'!R$6:R$860,"to be offered")+COUNTIF('MiT Strom Pipeline'!R$6:R$860,"on hold") -> 33 | I7: =COUNTIF('MiT Strom Pipeline'!R$6:R$860,"follow-up")+COUNTIF('MiT Strom Pipeline'!R$6:R$860,"Evaluation")+COUNTIF('MiT Strom Pipeline'!R$6:R$860,"tbd")+COUNTIF('MiT Strom Pipeline'!R$6:R$860,"In evaluation") -> 1
A8: ="⚖️ Gewichtete Pipeline (Aggreko-Faktoren 0 / 30 / 50 / 90 %): "&TEXT(SUMIFS('MiT Strom Pipeline'!$Q$6:$Q$860,'MiT Strom Pipeline'!$R$6:$R$860,"WON")+SUMIFS('MiT Strom Pipeline'!$Q$6:$Q$860,'MiT Strom Pipeline'!$R$6:$R$860,"offered")+SUMIFS('MiT Strom Pipeline'!$Q$6:$Q$860,'MiT Strom Pipeline'!$R$6:$R$860,"to be offered")+SUMIFS('MiT Strom Pipeline'!$Q$6:$Q$860,'MiT Strom Pipeline'!$R$6:$R$860,"on hold")+SUMIFS('MiT Strom Pipeline'!$Q$6:$Q$860,'MiT Strom Pipeline'!$R$6:$R$860,"follow-up")+SUMIFS('MiT Strom Pipeline'!$Q$6:$Q$860,'MiT Strom Pipeline'!$R$6:$R$860,"Evaluation")+SUMIFS('MiT Strom Pipeline'!$Q$6:$Q$860,'MiT Strom Pipeline'!$R$6:$R$860,"In evaluation")+SUMIFS('MiT Strom Pipeline'!$Q$6:$Q$860,'MiT Strom Pipeline'!$R$6:$R$860,"tbd"),"#,##0")&" CHF · davon Offerte: "&TEXT(SUMIFS('MiT Strom Pipeline'!$Q$6:$Q$860,'MiT Strom Pipeline'!$R$6:$R$860,"offered")+SUMIFS('MiT Strom Pipeline'!$Q$6:$Q$860,'MiT Strom Pipeline'!$R$6:$R$860,"to be offered")+SUMIFS('MiT Strom Pipeline'!$Q$6:$Q$860,'MiT Strom Pipeline'!$R$6:$R$860,"on hold"),"#,##0")&" CHF · Opportunität: "&TEXT(SUMIFS('MiT Strom Pipeline'!$Q$6:$Q$860,'MiT Strom Pipeline'!$R$6:$R$860,"follow-up")+SUMIFS('MiT Strom Pipeline'!$Q$6:$Q$860,'MiT Strom Pipeline'!$R$6:$R$860,"Evaluation")+SUMIFS('MiT Strom Pipeline'!$Q$6:$Q$860,'MiT Strom Pipeline'!$R$6:$R$860,"In evaluation")+SUMIFS('MiT Strom Pipeline'!$Q$6:$Q$860,'MiT Strom Pipeline'!$R$6:$R$860,"tbd"),"#,##0")&" CHF · Modell: Blatt «⚖️ Wahrscheinlichkeit»" -> ⚖️ Gewichtete Pipeline (Aggreko-Faktoren 0 / 30 / 50 / 90 %): 1,628,426 CHF · davon Offerte: 199,872 CHF · Opportunität: 0 CHF · Modell: Blatt «⚖️ Wahrscheinlichkeit»
A9: ✅ 1. AUFTRAGSEINGANG (WON) — Bestätigte Aufträge
A10: # | B10: Kunde / Unternehmen | C10: Kt. | D10: Segment | E10: Projektstart | F10: Projektende | G10: Volumen CHF | H10: Gew.Wert CHF | I10: Leistung / Fleet | J10: Status | K10: Wahr.% | L10: Nächster Schritt | M10: Auftrag / PO-Nr. | N10: Prüfstatus
A11: =IF($U11="","",IF(ISNUMBER(INDEX('MiT Strom Pipeline'!$A$1:$A$860,$U11)),INDEX('MiT Strom Pipeline'!$A$1:$A$860,$U11),"")) -> 1 | B11: =IF($U11="","",IF(INDEX('MiT Strom Pipeline'!$B$1:$B$860,$U11)="","",INDEX('MiT Strom Pipeline'!$B$1:$B$860,$U11))) -> Ice Hockey Championship | C11: =IF($U11="","",IF(INDEX('MiT Strom Pipeline'!$C$1:$C$860,$U11)="","",INDEX('MiT Strom Pipeline'!$C$1:$C$860,$U11))) -> ZH | D11: =IF($U11="","",IF(INDEX('MiT Strom Pipeline'!$D$1:$D$860,$U11)="","",INDEX('MiT Strom Pipeline'!$D$1:$D$860,$U11))) -> Events & Sport | E11: =IF($U11="","",IF(ISNUMBER(INDEX('MiT Strom Pipeline'!$O$1:$O$860,$U11)),INDEX('MiT Strom Pipeline'!$O$1:$O$860,$U11),IF(INDEX('MiT Strom Pipeline'!$H$1:$H$860,$U11)="","",INDEX('MiT Strom Pipeline'!$H$1:$H$860,$U11)))) -> Mai | F11: =IF($U11="","",IF(ISNUMBER(INDEX('MiT Strom Pipeline'!$P$1:$P$860,$U11)),INDEX('MiT Strom Pipeline'!$P$1:$P$860,$U11),"")) | G11: =IF($U11="","",IF(ISNUMBER(INDEX('MiT Strom Pipeline'!$I$1:$I$860,$U11)),INDEX('MiT Strom Pipeline'!$I$1:$I$860,$U11),0)) -> 380000 | H11: =IF($U11="","",IF(ISNUMBER(INDEX('MiT Strom Pipeline'!$Q$1:$Q$860,$U11)),INDEX('MiT Strom Pipeline'!$Q$1:$Q$860,$U11),0)) -> 380000 | I11: =IF($U11="","",IF(INDEX('MiT Strom Pipeline'!$E$1:$E$860,$U11)="","",INDEX('MiT Strom Pipeline'!$E$1:$E$860,$U11))) -> 2×600+2×200 kVA | J11: =IF($U11="","",INDEX('MiT Strom Pipeline'!$R$1:$R$860,$U11)) -> WON | K11: =IF($U11="","",IF(ISNUMBER(INDEX('MiT Strom Pipeline'!$S$1:$S$860,$U11)),INDEX('MiT Strom Pipeline'!$S$1:$S$860,$U11),"")) -> 1 | L11: =IF($U11="","",IF(LEN(INDEX('MiT Strom Pipeline'!$V$1:$V$860,$U11))>0,LEFT(INDEX('MiT Strom Pipeline'!$V$1:$V$860,$U11),55),"")) -> Abgeschlossen | M11: =IF($U11="","",IF(INDEX('MiT Strom Pipeline'!$AF$1:$AF$860,$U11)="","",INDEX('MiT Strom Pipeline'!$AF$1:$AF$860,$U11))) | N11: =IF($U11="","",IF(INDEX('MiT Strom Pipeline'!$BB$1:$BB$860,$U11)="","",INDEX('MiT Strom Pipeline'!$BB$1:$BB$860,$U11))) -> ⛔ Nachweis fehlt | U11: =IFERROR(MATCH(1,'MiT Strom Pipeline'!$AM$6:$AM$860,0)+5,"") -> 9
A12: =IF($U12="","",IF(ISNUMBER(INDEX('MiT Strom Pipeline'!$A$1:$A$860,$U12)),INDEX('MiT Strom Pipeline'!$A$1:$A$860,$U12),"")) -> 2 | B12: =IF($U12="","",IF(INDEX('MiT Strom Pipeline'!$B$1:$B$860,$U12)="","",INDEX('MiT Strom Pipeline'!$B$1:$B$860,$U12))) -> Oerlikon Metco Wohlen | C12: =IF($U12="","",IF(INDEX('MiT Strom Pipeline'!$C$1:$C$860,$U12)="","",INDEX('MiT Strom Pipeline'!$C$1:$C$860,$U12))) -> AG | D12: =IF($U12="","",IF(INDEX('MiT Strom Pipeline'!$D$1:$D$860,$U12)="","",INDEX('MiT Strom Pipeline'!$D$1:$D$860,$U12))) -> Industrie / Oberfläche | E12: =IF($U12="","",IF(ISNUMBER(INDEX('MiT Strom Pipeline'!$O$1:$O$860,$U12)),INDEX('MiT Strom Pipeline'!$O$1:$O$860,$U12),IF(INDEX('MiT Strom Pipeline'!$H$1:$H$860,$U12)="","",INDEX('MiT Strom Pipeline'!$H$1:$H$860,$U12)))) -> April | F12: =IF($U12="","",IF(ISNUMBER(INDEX('MiT Strom Pipeline'!$P$1:$P$860,$U12)),INDEX('MiT Strom Pipeline'!$P$1:$P$860,$U12),"")) | G12: =IF($U12="","",IF(ISNUMBER(INDEX('MiT Strom Pipeline'!$I$1:$I$860,$U12)),INDEX('MiT Strom Pipeline'!$I$1:$I$860,$U12),0)) -> 13100 | H12: =IF($U12="","",IF(ISNUMBER(INDEX('MiT Strom Pipeline'!$Q$1:$Q$860,$U12)),INDEX('MiT Strom Pipeline'!$Q$1:$Q$860,$U12),0)) -> 13100 | I12: =IF($U12="","",IF(INDEX('MiT Strom Pipeline'!$E$1:$E$860,$U12)="","",INDEX('MiT Strom Pipeline'!$E$1:$E$860,$U12))) -> 240 kVA Generator | J12: =IF($U12="","",INDEX('MiT Strom Pipeline'!$R$1:$R$860,$U12)) -> WON | K12: =IF($U12="","",IF(ISNUMBER(INDEX('MiT Strom Pipeline'!$S$1:$S$860,$U12)),INDEX('MiT Strom Pipeline'!$S$1:$S$860,$U12),"")) -> 1 | L12: =IF($U12="","",IF(LEN(INDEX('MiT Strom Pipeline'!$V$1:$V$860,$U12))>0,LEFT(INDEX('MiT Strom Pipeline'!$V$1:$V$860,$U12),55),"")) -> Abgeschlossen | M12: =IF($U12="","",IF(INDEX('MiT Strom Pipeline'!$AF$1:$AF$860,$U12)="","",INDEX('MiT Strom Pipeline'!$AF$1:$AF$860,$U12))) | N12: =IF($U12="","",IF(INDEX('MiT Strom Pipeline'!$BB$1:$BB$860,$U12)="","",INDEX('MiT Strom Pipeline'!$BB$1:$BB$860,$U12))) -> ⛔ Nachweis fehlt | U12: =IFERROR(MATCH(2,'MiT Strom Pipeline'!$AM$6:$AM$860,0)+5,"") -> 10
A13: =IF($U13="","",IF(ISNUMBER(INDEX('MiT Strom Pipeline'!$A$1:$A$860,$U13)),INDEX('MiT Strom Pipeline'!$A$1:$A$860,$U13),"")) -> 3 | B13: =IF($U13="","",IF(INDEX('MiT Strom Pipeline'!$B$1:$B$860,$U13)="","",INDEX('MiT Strom Pipeline'!$B$1:$B$860,$U13))) -> Siemens | C13: =IF($U13="","",IF(INDEX('MiT Strom Pipeline'!$C$1:$C$860,$U13)="","",INDEX('MiT Strom Pipeline'!$C$1:$C$860,$U13))) -> ZH | D13: =IF($U13="","",IF(INDEX('MiT Strom Pipeline'!$D$1:$D$860,$U13)="","",INDEX('MiT Strom Pipeline'!$D$1:$D$860,$U13))) -> Industrie / Elektro | E13: =IF($U13="","",IF(ISNUMBER(INDEX('MiT Strom Pipeline'!$O$1:$O$860,$U13)),INDEX('MiT Strom Pipeline'!$O$1:$O$860,$U13),IF(INDEX('MiT Strom Pipeline'!$H$1:$H$860,$U13)="","",INDEX('MiT Strom Pipeline'!$H$1:$H$860,$U13)))) -> tbd | F13: =IF($U13="","",IF(ISNUMBER(INDEX('MiT Strom Pipeline'!$P$1:$P$860,$U13)),INDEX('MiT Strom Pipeline'!$P$1:$P$860,$U13),"")) | G13: =IF($U13="","",IF(ISNUMBER(INDEX('MiT Strom Pipeline'!$I$1:$I$860,$U13)),INDEX('MiT Strom Pipeline'!$I$1:$I$860,$U13),0)) -> 10000 | H13: =IF($U13="","",IF(ISNUMBER(INDEX('MiT Strom Pipeline'!$Q$1:$Q$860,$U13)),INDEX('MiT Strom Pipeline'!$Q$1:$Q$860,$U13),0)) -> 10000 | I13: =IF($U13="","",IF(INDEX('MiT Strom Pipeline'!$E$1:$E$860,$U13)="","",INDEX('MiT Strom Pipeline'!$E$1:$E$860,$U13))) -> 600 kVA Generator | J13: =IF($U13="","",INDEX('MiT Strom Pipeline'!$R$1:$R$860,$U13)) -> WON | K13: =IF($U13="","",IF(ISNUMBER(INDEX('MiT Strom Pipeline'!$S$1:$S$860,$U13)),INDEX('MiT Strom Pipeline'!$S$1:$S$860,$U13),"")) -> 1 | L13: =IF($U13="","",IF(LEN(INDEX('MiT Strom Pipeline'!$V$1:$V$860,$U13))>0,LEFT(INDEX('MiT Strom Pipeline'!$V$1:$V$860,$U13),55),"")) -> Abgeschlossen | M13: =IF($U13="","",IF(INDEX('MiT Strom Pipeline'!$AF$1:$AF$860,$U13)="","",INDEX('MiT Strom Pipeline'!$AF$1:$AF$860,$U13))) | N13: =IF($U13="","",IF(INDEX('MiT Strom Pipeline'!$BB$1:$BB$860,$U13)="","",INDEX('MiT Strom Pipeline'!$BB$1:$BB$860,$U13))) -> ⛔ Nachweis fehlt | U13: =IFERROR(MATCH(3,'MiT Strom Pipeline'!$AM$6:$AM$860,0)+5,"") -> 12
A14: =IF($U14="","",IF(ISNUMBER(INDEX('MiT Strom Pipeline'!$A$1:$A$860,$U14)),INDEX('MiT Strom Pipeline'!$A$1:$A$860,$U14),"")) -> 4 | B14: =IF($U14="","",IF(INDEX('MiT Strom Pipeline'!$B$1:$B$860,$U14)="","",INDEX('MiT Strom Pipeline'!$B$1:$B$860,$U14))) -> Stagelight – OpenAir Frauenfeld | C14: =IF($U14="","",IF(INDEX('MiT Strom Pipeline'!$C$1:$C$860,$U14)="","",INDEX('MiT Strom Pipeline'!$C$1:$C$860,$U14))) -> TG | D14: =IF($U14="","",IF(INDEX('MiT Strom Pipeline'!$D$1:$D$860,$U14)="","",INDEX('MiT Strom Pipeline'!$D$1:$D$860,$U14))) -> Events & Kultur | E14: =IF($U14="","",IF(ISNUMBER(INDEX('MiT Strom Pipeline'!$O$1:$O$860,$U14)),INDEX('MiT Strom Pipeline'!$O$1:$O$860,$U14),IF(INDEX('MiT Strom Pipeline'!$H$1:$H$860,$U14)="","",INDEX('MiT Strom Pipeline'!$H$1:$H$860,$U14)))) -> Juli | F14: =IF($U14="","",IF(ISNUMBER(INDEX('MiT Strom Pipeline'!$P$1:$P$860,$U14)),INDEX('MiT Strom Pipeline'!$P$1:$P$860,$U14),"")) | G14: =IF($U14="","",IF(ISNUMBER(INDEX('MiT Strom Pipeline'!$I$1:$I$860,$U14)),INDEX('MiT Strom Pipeline'!$I$1:$I$860,$U14),0)) -> 150000 | H14: =IF($U14="","",IF(ISNUMBER(INDEX('MiT Strom Pipeline'!$Q$1:$Q$860,$U14)),INDEX('MiT Strom Pipeline'!$Q$1:$Q$860,$U14),0)) -> 150000 | I14: =IF($U14="","",IF(INDEX('MiT Strom Pipeline'!$E$1:$E$860,$U14)="","",INDEX('MiT Strom Pipeline'!$E$1:$E$860,$U14))) -> ~500 kVA Generator | J14: =IF($U14="","",INDEX('MiT Strom Pipeline'!$R$1:$R$860,$U14)) -> WON | K14: =IF($U14="","",IF(ISNUMBER(INDEX('MiT Strom Pipeline'!$S$1:$S$860,$U14)),INDEX('MiT Strom Pipeline'!$S$1:$S$860,$U14),"")) -> 1 | L14: =IF($U14="","",IF(LEN(INDEX('MiT Strom Pipeline'!$V$1:$V$860,$U14))>0,LEFT(INDEX('MiT Strom Pipeline'!$V$1:$V$860,$U14),55),"")) -> Abgeschlossen | M14: =IF($U14="","",IF(INDEX('MiT Strom Pipeline'!$AF$1:$AF$860,$U14)="","",INDEX('MiT Strom Pipeline'!$AF$1:$AF$860,$U14))) | N14: =IF($U14="","",IF(INDEX('MiT Strom Pipeline'!$BB$1:$BB$860,$U14)="","",INDEX('MiT Strom Pipeline'!$BB$1:$BB$860,$U14))) -> ⛔ Nachweis fehlt | U14: =IFERROR(MATCH(4,'MiT Strom Pipeline'!$AM$6:$AM$860,0)+5,"") -> 13
A15: =IF($U15="","",IF(ISNUMBER(INDEX('MiT Strom Pipeline'!$A$1:$A$860,$U15)),INDEX('MiT Strom Pipeline'!$A$1:$A$860,$U15),"")) -> 10 | B15: =IF($U15="","",IF(INDEX('MiT Strom Pipeline'!$B$1:$B$860,$U15)="","",INDEX('MiT Strom Pipeline'!$B$1:$B$860,$U15))) -> Murg Flums Energie | C15: =IF($U15="","",IF(INDEX('MiT Strom Pipeline'!$C$1:$C$860,$U15)="","",INDEX('MiT Strom Pipeline'!$C$1:$C$860,$U15))) -> SG | D15: =IF($U15="","",IF(INDEX('MiT Strom Pipeline'!$D$1:$D$860,$U15)="","",INDEX('MiT Strom Pipeline'!$D$1:$D$860,$U15))) -> EVU / Energie | E15: =IF($U15="","",IF(ISNUMBER(INDEX('MiT Strom Pipeline'!$O$1:$O$860,$U15)),INDEX('MiT Strom Pipeline'!$O$1:$O$860,$U15),IF(INDEX('MiT Strom Pipeline'!$H$1:$H$860,$U15)="","",INDEX('MiT Strom Pipeline'!$H$1:$H$860,$U15)))) -> Auf Abruf | F15: =IF($U15="","",IF(ISNUMBER(INDEX('MiT Strom Pipeline'!$P$1:$P$860,$U15)),INDEX('MiT Strom Pipeline'!$P$1:$P$860,$U15),"")) | G15: =IF($U15="","",IF(ISNUMBER(INDEX('MiT Strom Pipeline'!$I$1:$I$860,$U15)),INDEX('MiT Strom Pipeline'!$I$1:$I$860,$U15),0)) -> 96658.69 | H15: =IF($U15="","",IF(ISNUMBER(INDEX('MiT Strom Pipeline'!$Q$1:$Q$860,$U15)),INDEX('MiT Strom Pipeline'!$Q$1:$Q$860,$U15),0)) -> 96658.69 | I15: =IF($U15="","",IF(INDEX('MiT Strom Pipeline'!$E$1:$E$860,$U15)="","",INDEX('MiT Strom Pipeline'!$E$1:$E$860,$U15))) -> 250 kVA Generator | J15: =IF($U15="","",INDEX('MiT Strom Pipeline'!$R$1:$R$860,$U15)) -> WON | K15: =IF($U15="","",IF(ISNUMBER(INDEX('MiT Strom Pipeline'!$S$1:$S$860,$U15)),INDEX('MiT Strom Pipeline'!$S$1:$S$860,$U15),"")) -> 1 | L15: =IF($U15="","",IF(LEN(INDEX('MiT Strom Pipeline'!$V$1:$V$860,$U15))>0,LEFT(INDEX('MiT Strom Pipeline'!$V$1:$V$860,$U15),55),"")) -> Abrufbereitschaft | M15: =IF($U15="","",IF(INDEX('MiT Strom Pipeline'!$AF$1:$AF$860,$U15)="","",INDEX('MiT Strom Pipeline'!$AF$1:$AF$860,$U15))) | N15: =IF($U15="","",IF(INDEX('MiT Strom Pipeline'!$BB$1:$BB$860,$U15)="","",INDEX('MiT Strom Pipeline'!$BB$1:$BB$860,$U15))) -> ⛔ Nachweis fehlt | U15: =IFERROR(MATCH(5,'MiT Strom Pipeline'!$AM$6:$AM$860,0)+5,"") -> 14
A16: =IF($U16="","",IF(ISNUMBER(INDEX('MiT Strom Pipeline'!$A$1:$A$860,$U16)),INDEX('MiT Strom Pipeline'!$A$1:$A$860,$U16),"")) -> 21 | B16: =IF($U16="","",IF(INDEX('MiT Strom Pipeline'!$B$1:$B$860,$U16)="","",INDEX('MiT Strom Pipeline'!$B$1:$B$860,$U16))) -> X-Event | C16: =IF($U16="","",IF(INDEX('MiT Strom Pipeline'!$C$1:$C$860,$U16)="","",INDEX('MiT Strom Pipeline'!$C$1:$C$860,$U16))) -> SH | D16: =IF($U16="","",IF(INDEX('MiT Strom Pipeline'!$D$1:$D$860,$U16)="","",INDEX('MiT Strom Pipeline'!$D$1:$D$860,$U16))) -> Events / Medien | E16: =IF($U16="","",IF(ISNUMBER(INDEX('MiT Strom Pipeline'!$O$1:$O$860,$U16)),INDEX('MiT Strom Pipeline'!$O$1:$O$860,$U16),IF(INDEX('MiT Strom Pipeline'!$H$1:$H$860,$U16)="","",INDEX('MiT Strom Pipeline'!$H$1:$H$860,$U16)))) -> Juni | F16: =IF($U16="","",IF(ISNUMBER(INDEX('MiT Strom Pipeline'!$P$1:$P$860,$U16)),INDEX('MiT Strom Pipeline'!$P$1:$P$860,$U16),"")) | G16: =IF($U16="","",IF(ISNUMBER(INDEX('MiT Strom Pipeline'!$I$1:$I$860,$U16)),INDEX('MiT Strom Pipeline'!$I$1:$I$860,$U16),0)) -> 0 | H16: =IF($U16="","",IF(ISNUMBER(INDEX('MiT Strom Pipeline'!$Q$1:$Q$860,$U16)),INDEX('MiT Strom Pipeline'!$Q$1:$Q$860,$U16),0)) -> 0 | I16: =IF($U16="","",IF(INDEX('MiT Strom Pipeline'!$E$1:$E$860,$U16)="","",INDEX('MiT Strom Pipeline'!$E$1:$E$860,$U16))) -> 100 kVA Generator | J16: =IF($U16="","",INDEX('MiT Strom Pipeline'!$R$1:$R$860,$U16)) -> WON | K16: =IF($U16="","",IF(ISNUMBER(INDEX('MiT Strom Pipeline'!$S$1:$S$860,$U16)),INDEX('MiT Strom Pipeline'!$S$1:$S$860,$U16),"")) -> 1 | L16: =IF($U16="","",IF(LEN(INDEX('MiT Strom Pipeline'!$V$1:$V$860,$U16))>0,LEFT(INDEX('MiT Strom Pipeline'!$V$1:$V$860,$U16),55),"")) -> Abgeschlossen | M16: =IF($U16="","",IF(INDEX('MiT Strom Pipeline'!$AF$1:$AF$860,$U16)="","",INDEX('MiT Strom Pipeline'!$AF$1:$AF$860,$U16))) | N16: =IF($U16="","",IF(INDEX('MiT Strom Pipeline'!$BB$1:$BB$860,$U16)="","",INDEX('MiT Strom Pipeline'!$BB$1:$BB$860,$U16))) -> ⛔ Nachweis fehlt | U16: =IFERROR(MATCH(6,'MiT Strom Pipeline'!$AM$6:$AM$860,0)+5,"") -> 15
A17: =IF($U17="","",IF(ISNUMBER(INDEX('MiT Strom Pipeline'!$A$1:$A$860,$U17)),INDEX('MiT Strom Pipeline'!$A$1:$A$860,$U17),"")) -> 29 | B17: =IF($U17="","",IF(INDEX('MiT Strom Pipeline'!$B$1:$B$860,$U17)="","",INDEX('MiT Strom Pipeline'!$B$1:$B$860,$U17))) -> Gampeln | C17: =IF($U17="","",IF(INDEX('MiT Strom Pipeline'!$C$1:$C$860,$U17)="","",INDEX('MiT Strom Pipeline'!$C$1:$C$860,$U17))) -> VS | D17: =IF($U17="","",IF(INDEX('MiT Strom Pipeline'!$D$1:$D$860,$U17)="","",INDEX('MiT Strom Pipeline'!$D$1:$D$860,$U17))) -> Event | E17: =IF($U17="","",IF(ISNUMBER(INDEX('MiT Strom Pipeline'!$O$1:$O$860,$U17)),INDEX('MiT Strom Pipeline'!$O$1:$O$860,$U17),IF(INDEX('MiT Strom Pipeline'!$H$1:$H$860,$U17)="","",INDEX('MiT Strom Pipeline'!$H$1:$H$860,$U17)))) -> Aug | F17: =IF($U17="","",IF(ISNUMBER(INDEX('MiT Strom Pipeline'!$P$1:$P$860,$U17)),INDEX('MiT Strom Pipeline'!$P$1:$P$860,$U17),"")) | G17: =IF($U17="","",IF(ISNUMBER(INDEX('MiT Strom Pipeline'!$I$1:$I$860,$U17)),INDEX('MiT Strom Pipeline'!$I$1:$I$860,$U17),0)) -> 80621.21 | H17: =IF($U17="","",IF(ISNUMBER(INDEX('MiT Strom Pipeline'!$Q$1:$Q$860,$U17)),INDEX('MiT Strom Pipeline'!$Q$1:$Q$860,$U17),0)) -> 80621.21 | I17: =IF($U17="","",IF(INDEX('MiT Strom Pipeline'!$E$1:$E$860,$U17)="","",INDEX('MiT Strom Pipeline'!$E$1:$E$860,$U17))) -> 6x300 kVA, 9x200 kVA Generator ,1x150 kWH BESS | J17: =IF($U17="","",INDEX('MiT Strom Pipeline'!$R$1:$R$860,$U17)) -> WON | K17: =IF($U17="","",IF(ISNUMBER(INDEX('MiT Strom Pipeline'!$S$1:$S$860,$U17)),INDEX('MiT Strom Pipeline'!$S$1:$S$860,$U17),"")) -> 1 | L17: =IF($U17="","",IF(LEN(INDEX('MiT Strom Pipeline'!$V$1:$V$860,$U17))>0,LEFT(INDEX('MiT Strom Pipeline'!$V$1:$V$860,$U17),55),"")) -> Abgeschlossen | M17: =IF($U17="","",IF(INDEX('MiT Strom Pipeline'!$AF$1:$AF$860,$U17)="","",INDEX('MiT Strom Pipeline'!$AF$1:$AF$860,$U17))) | N17: =IF($U17="","",IF(INDEX('MiT Strom Pipeline'!$BB$1:$BB$860,$U17)="","",INDEX('MiT Strom Pipeline'!$BB$1:$BB$860,$U17))) -> ⛔ Nachweis fehlt | U17: =IFERROR(MATCH(7,'MiT Strom Pipeline'!$AM$6:$AM$860,0)+5,"") -> 22
A18: =IF($U18="","",IF(ISNUMBER(INDEX('MiT Strom Pipeline'!$A$1:$A$860,$U18)),INDEX('MiT Strom Pipeline'!$A$1:$A$860,$U18),"")) -> 50 | B18: =IF($U18="","",IF(INDEX('MiT Strom Pipeline'!$B$1:$B$860,$U18)="","",INDEX('MiT Strom Pipeline'!$B$1:$B$860,$U18))) -> EIDG AMT Agroscope | C18: =IF($U18="","",IF(INDEX('MiT Strom Pipeline'!$C$1:$C$860,$U18)="","",INDEX('MiT Strom Pipeline'!$C$1:$C$860,$U18))) -> ZH | D18: =IF($U18="","",IF(INDEX('MiT Strom Pipeline'!$D$1:$D$860,$U18)="","",INDEX('MiT Strom Pipeline'!$D$1:$D$860,$U18))) -> Forschung | E18: =IF($U18="","",IF(ISNUMBER(INDEX('MiT Strom Pipeline'!$O$1:$O$860,$U18)),INDEX('MiT Strom Pipeline'!$O$1:$O$860,$U18),IF(INDEX('MiT Strom Pipeline'!$H$1:$H$860,$U18)="","",INDEX('MiT Strom Pipeline'!$H$1:$H$860,$U18)))) -> Aug | F18: =IF($U18="","",IF(ISNUMBER(INDEX('MiT Strom Pipeline'!$P$1:$P$860,$U18)),INDEX('MiT Strom Pipeline'!$P$1:$P$860,$U18),"")) | G18: =IF($U18="","",IF(ISNUMBER(INDEX('MiT Strom Pipeline'!$I$1:$I$860,$U18)),INDEX('MiT Strom Pipeline'!$I$1:$I$860,$U18),0)) -> 13533 | H18: =IF($U18="","",IF(ISNUMBER(INDEX('MiT Strom Pipeline'!$Q$1:$Q$860,$U18)),INDEX('MiT Strom Pipeline'!$Q$1:$Q$860,$U18),0)) -> 13533 | I18: =IF($U18="","",IF(INDEX('MiT Strom Pipeline'!$E$1:$E$860,$U18)="","",INDEX('MiT Strom Pipeline'!$E$1:$E$860,$U18))) -> 450 kVA | J18: =IF($U18="","",INDEX('MiT Strom Pipeline'!$R$1:$R$860,$U18)) -> WON | K18: =IF($U18="","",IF(ISNUMBER(INDEX('MiT Strom Pipeline'!$S$1:$S$860,$U18)),INDEX('MiT Strom Pipeline'!$S$1:$S$860,$U18),"")) -> 1 | L18: =IF($U18="","",IF(LEN(INDEX('MiT Strom Pipeline'!$V$1:$V$860,$U18))>0,LEFT(INDEX('MiT Strom Pipeline'!$V$1:$V$860,$U18),55),"")) -> Abgeschlossen | M18: =IF($U18="","",IF(INDEX('MiT Strom Pipeline'!$AF$1:$AF$860,$U18)="","",INDEX('MiT Strom Pipeline'!$AF$1:$AF$860,$U18))) | N18: =IF($U18="","",IF(INDEX('MiT Strom Pipeline'!$BB$1:$BB$860,$U18)="","",INDEX('MiT Strom Pipeline'!$BB$1:$BB$860,$U18))) -> ⛔ Nachweis fehlt | U18: =IFERROR(MATCH(8,'MiT Strom Pipeline'!$AM$6:$AM$860,0)+5,"") -> 60
A19: =IF($U19="","",IF(ISNUMBER(INDEX('MiT Strom Pipeline'!$A$1:$A$860,$U19)),INDEX('MiT Strom Pipeline'!$A$1:$A$860,$U19),"")) -> 51 | B19: =IF($U19="","",IF(INDEX('MiT Strom Pipeline'!$B$1:$B$860,$U19)="","",INDEX('MiT Strom Pipeline'!$B$1:$B$860,$U19))) -> (Megger) Power Diagnostix Service GmbH | C19: =IF($U19="","",IF(INDEX('MiT Strom Pipeline'!$C$1:$C$860,$U19)="","",INDEX('MiT Strom Pipeline'!$C$1:$C$860,$U19))) -> TG | D19: =IF($U19="","",IF(INDEX('MiT Strom Pipeline'!$D$1:$D$860,$U19)="","",INDEX('MiT Strom Pipeline'!$D$1:$D$860,$U19))) -> EVU | E19: =IF($U19="","",IF(ISNUMBER(INDEX('MiT Strom Pipeline'!$O$1:$O$860,$U19)),INDEX('MiT Strom Pipeline'!$O$1:$O$860,$U19),IF(INDEX('MiT Strom Pipeline'!$H$1:$H$860,$U19)="","",INDEX('MiT Strom Pipeline'!$H$1:$H$860,$U19)))) -> Juli | F19: =IF($U19="","",IF(ISNUMBER(INDEX('MiT Strom Pipeline'!$P$1:$P$860,$U19)),INDEX('MiT Strom Pipeline'!$P$1:$P$860,$U19),"")) | G19: =IF($U19="","",IF(ISNUMBER(INDEX('MiT Strom Pipeline'!$I$1:$I$860,$U19)),INDEX('MiT Strom Pipeline'!$I$1:$I$860,$U19),0)) -> 5488.9 | H19: =IF($U19="","",IF(ISNUMBER(INDEX('MiT Strom Pipeline'!$Q$1:$Q$860,$U19)),INDEX('MiT Strom Pipeline'!$Q$1:$Q$860,$U19),0)) -> 5488.9 | I19: =IF($U19="","",IF(INDEX('MiT Strom Pipeline'!$E$1:$E$860,$U19)="","",INDEX('MiT Strom Pipeline'!$E$1:$E$860,$U19))) -> 600 kVA | J19: =IF($U19="","",INDEX('MiT Strom Pipeline'!$R$1:$R$860,$U19)) -> WON | K19: =IF($U19="","",IF(ISNUMBER(INDEX('MiT Strom Pipeline'!$S$1:$S$860,$U19)),INDEX('MiT Strom Pipeline'!$S$1:$S$860,$U19),"")) -> 1 | L19: =IF($U19="","",IF(LEN(INDEX('MiT Strom Pipeline'!$V$1:$V$860,$U19))>0,LEFT(INDEX('MiT Strom Pipeline'!$V$1:$V$860,$U19),55),"")) -> Abgeschlossen | M19: =IF($U19="","",IF(INDEX('MiT Strom Pipeline'!$AF$1:$AF$860,$U19)="","",INDEX('MiT Strom Pipeline'!$AF$1:$AF$860,$U19))) | N19: =IF($U19="","",IF(INDEX('MiT Strom Pipeline'!$BB$1:$BB$860,$U19)="","",INDEX('MiT Strom Pipeline'!$BB$1:$BB$860,$U19))) -> ⛔ Nachweis fehlt | U19: =IFERROR(MATCH(9,'MiT Strom Pipeline'!$AM$6:$AM$860,0)+5,"") -> 61
A20: =IF($U20="","",IF(ISNUMBER(INDEX('MiT Strom Pipeline'!$A$1:$A$860,$U20)),INDEX('MiT Strom Pipeline'!$A$1:$A$860,$U20),"")) -> 52 | B20: =IF($U20="","",IF(INDEX('MiT Strom Pipeline'!$B$1:$B$860,$U20)="","",INDEX('MiT Strom Pipeline'!$B$1:$B$860,$U20))) -> DPR Heat Loadbank | C20: =IF($U20="","",IF(INDEX('MiT Strom Pipeline'!$C$1:$C$860,$U20)="","",INDEX('MiT Strom Pipeline'!$C$1:$C$860,$U20))) -> ZH | D20: =IF($U20="","",IF(INDEX('MiT Strom Pipeline'!$D$1:$D$860,$U20)="","",INDEX('MiT Strom Pipeline'!$D$1:$D$860,$U20))) -> Datacenter | E20: =IF($U20="","",IF(ISNUMBER(INDEX('MiT Strom Pipeline'!$O$1:$O$860,$U20)),INDEX('MiT Strom Pipeline'!$O$1:$O$860,$U20),IF(INDEX('MiT Strom Pipeline'!$H$1:$H$860,$U20)="","",INDEX('MiT Strom Pipeline'!$H$1:$H$860,$U20)))) -> Aug | F20: =IF($U20="","",IF(ISNUMBER(INDEX('MiT Strom Pipeline'!$P$1:$P$860,$U20)),INDEX('MiT Strom Pipeline'!$P$1:$P$860,$U20),"")) | G20: =IF($U20="","",IF(ISNUMBER(INDEX('MiT Strom Pipeline'!$I$1:$I$860,$U20)),INDEX('MiT Strom Pipeline'!$I$1:$I$860,$U20),0)) -> 333790 | H20: =IF($U20="","",IF(ISNUMBER(INDEX('MiT Strom Pipeline'!$Q$1:$Q$860,$U20)),INDEX('MiT Strom Pipeline'!$Q$1:$Q$860,$U20),0)) -> 333790 | I20: =IF($U20="","",IF(INDEX('MiT Strom Pipeline'!$E$1:$E$860,$U20)="","",INDEX('MiT Strom Pipeline'!$E$1:$E$860,$U20))) -> 54x200 kVA Loadbank | J20: =IF($U20="","",INDEX('MiT Strom Pipeline'!$R$1:$R$860,$U20)) -> WON | K20: =IF($U20="","",IF(ISNUMBER(INDEX('MiT Strom Pipeline'!$S$1:$S$860,$U20)),INDEX('MiT Strom Pipeline'!$S$1:$S$860,$U20),"")) -> 1 | L20: =IF($U20="","",IF(LEN(INDEX('MiT Strom Pipeline'!$V$1:$V$860,$U20))>0,LEFT(INDEX('MiT Strom Pipeline'!$V$1:$V$860,$U20),55),"")) -> Kunde angeschrieben auf MiT seite mit aktueller CHF Pre | M20: =IF($U20="","",IF(INDEX('MiT Strom Pipeline'!$AF$1:$AF$860,$U20)="","",INDEX('MiT Strom Pipeline'!$AF$1:$AF$860,$U20))) | N20: =IF($U20="","",IF(INDEX('MiT Strom Pipeline'!$BB$1:$BB$860,$U20)="","",INDEX('MiT Strom Pipeline'!$BB$1:$BB$860,$U20))) -> ⛔ Nachweis fehlt | U20: =IFERROR(MATCH(10,'MiT Strom Pipeline'!$AM$6:$AM$860,0)+5,"") -> 62
A21: =IF($U21="","",IF(ISNUMBER(INDEX('MiT Strom Pipeline'!$A$1:$A$860,$U21)),INDEX('MiT Strom Pipeline'!$A$1:$A$860,$U21),"")) -> 53 | B21: =IF($U21="","",IF(INDEX('MiT Strom Pipeline'!$B$1:$B$860,$U21)="","",INDEX('MiT Strom Pipeline'!$B$1:$B$860,$U21))) -> DPR Generator Loadbank Test | C21: =IF($U21="","",IF(INDEX('MiT Strom Pipeline'!$C$1:$C$860,$U21)="","",INDEX('MiT Strom Pipeline'!$C$1:$C$860,$U21))) -> ZH | D21: =IF($U21="","",IF(INDEX('MiT Strom Pipeline'!$D$1:$D$860,$U21)="","",INDEX('MiT Strom Pipeline'!$D$1:$D$860,$U21))) -> Datacenter | E21: =IF($U21="","",IF(ISNUMBER(INDEX('MiT Strom Pipeline'!$O$1:$O$860,$U21)),INDEX('MiT Strom Pipeline'!$O$1:$O$860,$U21),IF(INDEX('MiT Strom Pipeline'!$H$1:$H$860,$U21)="","",INDEX('MiT Strom Pipeline'!$H$1:$H$860,$U21)))) -> Aug | F21: =IF($U21="","",IF(ISNUMBER(INDEX('MiT Strom Pipeline'!$P$1:$P$860,$U21)),INDEX('MiT Strom Pipeline'!$P$1:$P$860,$U21),"")) | G21: =IF($U21="","",IF(ISNUMBER(INDEX('MiT Strom Pipeline'!$I$1:$I$860,$U21)),INDEX('MiT Strom Pipeline'!$I$1:$I$860,$U21),0)) -> 331889.15 | H21: =IF($U21="","",IF(ISNUMBER(INDEX('MiT Strom Pipeline'!$Q$1:$Q$860,$U21)),INDEX('MiT Strom Pipeline'!$Q$1:$Q$860,$U21),0)) -> 331889.15 | I21: =IF($U21="","",IF(INDEX('MiT Strom Pipeline'!$E$1:$E$860,$U21)="","",INDEX('MiT Strom Pipeline'!$E$1:$E$860,$U21))) -> 6000 kVA Loadbank | J21: =IF($U21="","",INDEX('MiT Strom Pipeline'!$R$1:$R$860,$U21)) -> WON | K21: =IF($U21="","",IF(ISNUMBER(INDEX('MiT Strom Pipeline'!$S$1:$S$860,$U21)),INDEX('MiT Strom Pipeline'!$S$1:$S$860,$U21),"")) -> 1 | L21: =IF($U21="","",IF(LEN(INDEX('MiT Strom Pipeline'!$V$1:$V$860,$U21))>0,LEFT(INDEX('MiT Strom Pipeline'!$V$1:$V$860,$U21),55),"")) -> Kunde angeschrieben auf MiT seite mit aktueller CHF Pre | M21: =IF($U21="","",IF(INDEX('MiT Strom Pipeline'!$AF$1:$AF$860,$U21)="","",INDEX('MiT Strom Pipeline'!$AF$1:$AF$860,$U21))) | N21: =IF($U21="","",IF(INDEX('MiT Strom Pipeline'!$BB$1:$BB$860,$U21)="","",INDEX('MiT Strom Pipeline'!$BB$1:$BB$860,$U21))) -> ⛔ Nachweis fehlt | U21: =IFERROR(MATCH(11,'MiT Strom Pipeline'!$AM$6:$AM$860,0)+5,"") -> 63
A22: =IF($U22="","",IF(ISNUMBER(INDEX('MiT Strom Pipeline'!$A$1:$A$860,$U22)),INDEX('MiT Strom Pipeline'!$A$1:$A$860,$U22),"")) -> 61 | B22: =IF($U22="","",IF(INDEX('MiT Strom Pipeline'!$B$1:$B$860,$U22)="","",INDEX('MiT Strom Pipeline'!$B$1:$B$860,$U22))) -> GETEC Park.Swiss AG | C22: =IF($U22="","",IF(INDEX('MiT Strom Pipeline'!$C$1:$C$860,$U22)="","",INDEX('MiT Strom Pipeline'!$C$1:$C$860,$U22))) -> BL | D22: =IF($U22="","",IF(INDEX('MiT Strom Pipeline'!$D$1:$D$860,$U22)="","",INDEX('MiT Strom Pipeline'!$D$1:$D$860,$U22))) -> Industrie | E22: =IF($U22="","",IF(ISNUMBER(INDEX('MiT Strom Pipeline'!$O$1:$O$860,$U22)),INDEX('MiT Strom Pipeline'!$O$1:$O$860,$U22),IF(INDEX('MiT Strom Pipeline'!$H$1:$H$860,$U22)="","",INDEX('MiT Strom Pipeline'!$H$1:$H$860,$U22)))) -> August | F22: =IF($U22="","",IF(ISNUMBER(INDEX('MiT Strom Pipeline'!$P$1:$P$860,$U22)),INDEX('MiT Strom Pipeline'!$P$1:$P$860,$U22),"")) | G22: =IF($U22="","",IF(ISNUMBER(INDEX('MiT Strom Pipeline'!$I$1:$I$860,$U22)),INDEX('MiT Strom Pipeline'!$I$1:$I$860,$U22),0)) -> 13472.18 | H22: =IF($U22="","",IF(ISNUMBER(INDEX('MiT Strom Pipeline'!$Q$1:$Q$860,$U22)),INDEX('MiT Strom Pipeline'!$Q$1:$Q$860,$U22),0)) -> 13472.18 | I22: =IF($U22="","",IF(INDEX('MiT Strom Pipeline'!$E$1:$E$860,$U22)="","",INDEX('MiT Strom Pipeline'!$E$1:$E$860,$U22))) -> 600 kVA | J22: =IF($U22="","",INDEX('MiT Strom Pipeline'!$R$1:$R$860,$U22)) -> WON | K22: =IF($U22="","",IF(ISNUMBER(INDEX('MiT Strom Pipeline'!$S$1:$S$860,$U22)),INDEX('MiT Strom Pipeline'!$S$1:$S$860,$U22),"")) -> 1 | L22: =IF($U22="","",IF(LEN(INDEX('MiT Strom Pipeline'!$V$1:$V$860,$U22))>0,LEFT(INDEX('MiT Strom Pipeline'!$V$1:$V$860,$U22),55),"")) -> Kunde angeschrieben, Offerte erstellt, Kunde hat Offert | M22: =IF($U22="","",IF(INDEX('MiT Strom Pipeline'!$AF$1:$AF$860,$U22)="","",INDEX('MiT Strom Pipeline'!$AF$1:$AF$860,$U22))) | N22: =IF($U22="","",IF(INDEX('MiT Strom Pipeline'!$BB$1:$BB$860,$U22)="","",INDEX('MiT Strom Pipeline'!$BB$1:$BB$860,$U22))) -> ⛔ Nachweis fehlt | U22: =IFERROR(MATCH(12,'MiT Strom Pipeline'!$AM$6:$AM$860,0)+5,"") -> 71
A23: =IF($U23="","",IF(ISNUMBER(INDEX('MiT Strom Pipeline'!$A$1:$A$860,$U23)),INDEX('MiT Strom Pipeline'!$A$1:$A$860,$U23),"")) | B23: =IF($U23="","",IF(INDEX('MiT Strom Pipeline'!$B$1:$B$860,$U23)="","",INDEX('MiT Strom Pipeline'!$B$1:$B$860,$U23))) | C23: =IF($U23="","",IF(INDEX('MiT Strom Pipeline'!$C$1:$C$860,$U23)="","",INDEX('MiT Strom Pipeline'!$C$1:$C$860,$U23))) | D23: =IF($U23="","",IF(INDEX('MiT Strom Pipeline'!$D$1:$D$860,$U23)="","",INDEX('MiT Strom Pipeline'!$D$1:$D$860,$U23))) | E23: =IF($U23="","",IF(ISNUMBER(INDEX('MiT Strom Pipeline'!$O$1:$O$860,$U23)),INDEX('MiT Strom Pipeline'!$O$1:$O$860,$U23),IF(INDEX('MiT Strom Pipeline'!$H$1:$H$860,$U23)="","",INDEX('MiT Strom Pipeline'!$H$1:$H$860,$U23)))) | F23: =IF($U23="","",IF(ISNUMBER(INDEX('MiT Strom Pipeline'!$P$1:$P$860,$U23)),INDEX('MiT Strom Pipeline'!$P$1:$P$860,$U23),"")) | G23: =IF($U23="","",IF(ISNUMBER(INDEX('MiT Strom Pipeline'!$I$1:$I$860,$U23)),INDEX('MiT Strom Pipeline'!$I$1:$I$860,$U23),0)) | H23: =IF($U23="","",IF(ISNUMBER(INDEX('MiT Strom Pipeline'!$Q$1:$Q$860,$U23)),INDEX('MiT Strom Pipeline'!$Q$1:$Q$860,$U23),0)) | I23: =IF($U23="","",IF(INDEX('MiT Strom Pipeline'!$E$1:$E$860,$U23)="","",INDEX('MiT Strom Pipeline'!$E$1:$E$860,$U23))) | J23: =IF($U23="","",INDEX('MiT Strom Pipeline'!$R$1:$R$860,$U23)) | K23: =IF($U23="","",IF(ISNUMBER(INDEX('MiT Strom Pipeline'!$S$1:$S$860,$U23)),INDEX('MiT Strom Pipeline'!$S$1:$S$860,$U23),"")) | L23: =IF($U23="","",IF(LEN(INDEX('MiT Strom Pipeline'!$V$1:$V$860,$U23))>0,LEFT(INDEX('MiT Strom Pipeline'!$V$1:$V$860,$U23),55),"")) | M23: =IF($U23="","",IF(INDEX('MiT Strom Pipeline'!$AF$1:$AF$860,$U23)="","",INDEX('MiT Strom Pipeline'!$AF$1:$AF$860,$U23))) | N23: =IF($U23="","",IF(INDEX('MiT Strom Pipeline'!$BB$1:$BB$860,$U23)="","",INDEX('MiT Strom Pipeline'!$BB$1:$BB$860,$U23))) | U23: =IFERROR(MATCH(13,'MiT Strom Pipeline'!$AM$6:$AM$860,0)+5,"")
A24: =IF($U24="","",IF(ISNUMBER(INDEX('MiT Strom Pipeline'!$A$1:$A$860,$U24)),INDEX('MiT Strom Pipeline'!$A$1:$A$860,$U24),"")) | B24: =IF($U24="","",IF(INDEX('MiT Strom Pipeline'!$B$1:$B$860,$U24)="","",INDEX('MiT Strom Pipeline'!$B$1:$B$860,$U24))) | C24: =IF($U24="","",IF(INDEX('MiT Strom Pipeline'!$C$1:$C$860,$U24)="","",INDEX('MiT Strom Pipeline'!$C$1:$C$860,$U24))) | D24: =IF($U24="","",IF(INDEX('MiT Strom Pipeline'!$D$1:$D$860,$U24)="","",INDEX('MiT Strom Pipeline'!$D$1:$D$860,$U24))) | E24: =IF($U24="","",IF(ISNUMBER(INDEX('MiT Strom Pipeline'!$O$1:$O$860,$U24)),INDEX('MiT Strom Pipeline'!$O$1:$O$860,$U24),IF(INDEX('MiT Strom Pipeline'!$H$1:$H$860,$U24)="","",INDEX('MiT Strom Pipeline'!$H$1:$H$860,$U24)))) | F24: =IF($U24="","",IF(ISNUMBER(INDEX('MiT Strom Pipeline'!$P$1:$P$860,$U24)),INDEX('MiT Strom Pipeline'!$P$1:$P$860,$U24),"")) | G24: =IF($U24="","",IF(ISNUMBER(INDEX('MiT Strom Pipeline'!$I$1:$I$860,$U24)),INDEX('MiT Strom Pipeline'!$I$1:$I$860,$U24),0)) | H24: =IF($U24="","",IF(ISNUMBER(INDEX('MiT Strom Pipeline'!$Q$1:$Q$860,$U24)),INDEX('MiT Strom Pipeline'!$Q$1:$Q$860,$U24),0)) | I24: =IF($U24="","",IF(INDEX('MiT Strom Pipeline'!$E$1:$E$860,$U24)="","",INDEX('MiT Strom Pipeline'!$E$1:$E$860,$U24))) | J24: =IF($U24="","",INDEX('MiT Strom Pipeline'!$R$1:$R$860,$U24)) | K24: =IF($U24="","",IF(ISNUMBER(INDEX('MiT Strom Pipeline'!$S$1:$S$860,$U24)),INDEX('MiT Strom Pipeline'!$S$1:$S$860,$U24),"")) | L24: =IF($U24="","",IF(LEN(INDEX('MiT Strom Pipeline'!$V$1:$V$860,$U24))>0,LEFT(INDEX('MiT Strom Pipeline'!$V$1:$V$860,$U24),55),"")) | M24: =IF($U24="","",IF(INDEX('MiT Strom Pipeline'!$AF$1:$AF$860,$U24)="","",INDEX('MiT Strom Pipeline'!$AF$1:$AF$860,$U24))) | N24: =IF($U24="","",IF(INDEX('MiT Strom Pipeline'!$BB$1:$BB$860,$U24)="","",INDEX('MiT Strom Pipeline'!$BB$1:$BB$860,$U24))) | U24: =IFERROR(MATCH(14,'MiT Strom Pipeline'!$AM$6:$AM$860,0)+5,"")
A25: =IF($U25="","",IF(ISNUMBER(INDEX('MiT Strom Pipeline'!$A$1:$A$860,$U25)),INDEX('MiT Strom Pipeline'!$A$1:$A$860,$U25),"")) | B25: =IF($U25="","",IF(INDEX('MiT Strom Pipeline'!$B$1:$B$860,$U25)="","",INDEX('MiT Strom Pipeline'!$B$1:$B$860,$U25))) | C25: =IF($U25="","",IF(INDEX('MiT Strom Pipeline'!$C$1:$C$860,$U25)="","",INDEX('MiT Strom Pipeline'!$C$1:$C$860,$U25))) | D25: =IF($U25="","",IF(INDEX('MiT Strom Pipeline'!$D$1:$D$860,$U25)="","",INDEX('MiT Strom Pipeline'!$D$1:$D$860,$U25))) | E25: =IF($U25="","",IF(ISNUMBER(INDEX('MiT Strom Pipeline'!$O$1:$O$860,$U25)),INDEX('MiT Strom Pipeline'!$O$1:$O$860,$U25),IF(INDEX('MiT Strom Pipeline'!$H$1:$H$860,$U25)="","",INDEX('MiT Strom Pipeline'!$H$1:$H$860,$U25)))) | F25: =IF($U25="","",IF(ISNUMBER(INDEX('MiT Strom Pipeline'!$P$1:$P$860,$U25)),INDEX('MiT Strom Pipeline'!$P$1:$P$860,$U25),"")) | G25: =IF($U25="","",IF(ISNUMBER(INDEX('MiT Strom Pipeline'!$I$1:$I$860,$U25)),INDEX('MiT Strom Pipeline'!$I$1:$I$860,$U25),0)) | H25: =IF($U25="","",IF(ISNUMBER(INDEX('MiT Strom Pipeline'!$Q$1:$Q$860,$U25)),INDEX('MiT Strom Pipeline'!$Q$1:$Q$860,$U25),0)) | I25: =IF($U25="","",IF(INDEX('MiT Strom Pipeline'!$E$1:$E$860,$U25)="","",INDEX('MiT Strom Pipeline'!$E$1:$E$860,$U25))) | J25: =IF($U25="","",INDEX('MiT Strom Pipeline'!$R$1:$R$860,$U25)) | K25: =IF($U25="","",IF(ISNUMBER(INDEX('MiT Strom Pipeline'!$S$1:$S$860,$U25)),INDEX('MiT Strom Pipeline'!$S$1:$S$860,$U25),"")) | L25: =IF($U25="","",IF(LEN(INDEX('MiT Strom Pipeline'!$V$1:$V$860,$U25))>0,LEFT(INDEX('MiT Strom Pipeline'!$V$1:$V$860,$U25),55),"")) | M25: =IF($U25="","",IF(INDEX('MiT Strom Pipeline'!$AF$1:$AF$860,$U25)="","",INDEX('MiT Strom Pipeline'!$AF$1:$AF$860,$U25))) | N25: =IF($U25="","",IF(INDEX('MiT Strom Pipeline'!$BB$1:$BB$860,$U25)="","",INDEX('MiT Strom Pipeline'!$BB$1:$BB$860,$U25))) | U25: =IFERROR(MATCH(15,'MiT Strom Pipeline'!$AM$6:$AM$860,0)+5,"")
A26: =IF($U26="","",IF(ISNUMBER(INDEX('MiT Strom Pipeline'!$A$1:$A$860,$U26)),INDEX('MiT Strom Pipeline'!$A$1:$A$860,$U26),"")) | B26: =IF($U26="","",IF(INDEX('MiT Strom Pipeline'!$B$1:$B$860,$U26)="","",INDEX('MiT Strom Pipeline'!$B$1:$B$860,$U26))) | C26: =IF($U26="","",IF(INDEX('MiT Strom Pipeline'!$C$1:$C$860,$U26)="","",INDEX('MiT Strom Pipeline'!$C$1:$C$860,$U26))) | D26: =IF($U26="","",IF(INDEX('MiT Strom Pipeline'!$D$1:$D$860,$U26)="","",INDEX('MiT Strom Pipeline'!$D$1:$D$860,$U26))) | E26: =IF($U26="","",IF(ISNUMBER(INDEX('MiT Strom Pipeline'!$O$1:$O$860,$U26)),INDEX('MiT Strom Pipeline'!$O$1:$O$860,$U26),IF(INDEX('MiT Strom Pipeline'!$H$1:$H$860,$U26)="","",INDEX('MiT Strom Pipeline'!$H$1:$H$860,$U26)))) | F26: =IF($U26="","",IF(ISNUMBER(INDEX('MiT Strom Pipeline'!$P$1:$P$860,$U26)),INDEX('MiT Strom Pipeline'!$P$1:$P$860,$U26),"")) | G26: =IF($U26="","",IF(ISNUMBER(INDEX('MiT Strom Pipeline'!$I$1:$I$860,$U26)),INDEX('MiT Strom Pipeline'!$I$1:$I$860,$U26),0)) | H26: =IF($U26="","",IF(ISNUMBER(INDEX('MiT Strom Pipeline'!$Q$1:$Q$860,$U26)),INDEX('MiT Strom Pipeline'!$Q$1:$Q$860,$U26),0)) | I26: =IF($U26="","",IF(INDEX('MiT Strom Pipeline'!$E$1:$E$860,$U26)="","",INDEX('MiT Strom Pipeline'!$E$1:$E$860,$U26))) | J26: =IF($U26="","",INDEX('MiT Strom Pipeline'!$R$1:$R$860,$U26)) | K26: =IF($U26="","",IF(ISNUMBER(INDEX('MiT Strom Pipeline'!$S$1:$S$860,$U26)),INDEX('MiT Strom Pipeline'!$S$1:$S$860,$U26),"")) | L26: =IF($U26="","",IF(LEN(INDEX('MiT Strom Pipeline'!$V$1:$V$860,$U26))>0,LEFT(INDEX('MiT Strom Pipeline'!$V$1:$V$860,$U26),55),"")) | M26: =IF($U26="","",IF(INDEX('MiT Strom Pipeline'!$AF$1:$AF$860,$U26)="","",INDEX('MiT Strom Pipeline'!$AF$1:$AF$860,$U26))) | N26: =IF($U26="","",IF(INDEX('MiT Strom Pipeline'!$BB$1:$BB$860,$U26)="","",INDEX('MiT Strom Pipeline'!$BB$1:$BB$860,$U26))) | U26: =IFERROR(MATCH(16,'MiT Strom Pipeline'!$AM$6:$AM$860,0)+5,"")
A27: =IF($U27="","",IF(ISNUMBER(INDEX('MiT Strom Pipeline'!$A$1:$A$860,$U27)),INDEX('MiT Strom Pipeline'!$A$1:$A$860,$U27),"")) | B27: =IF($U27="","",IF(INDEX('MiT Strom Pipeline'!$B$1:$B$860,$U27)="","",INDEX('MiT Strom Pipeline'!$B$1:$B$860,$U27))) | C27: =IF($U27="","",IF(INDEX('MiT Strom Pipeline'!$C$1:$C$860,$U27)="","",INDEX('MiT Strom Pipeline'!$C$1:$C$860,$U27))) | D27: =IF($U27="","",IF(INDEX('MiT Strom Pipeline'!$D$1:$D$860,$U27)="","",INDEX('MiT Strom Pipeline'!$D$1:$D$860,$U27))) | E27: =IF($U27="","",IF(ISNUMBER(INDEX('MiT Strom Pipeline'!$O$1:$O$860,$U27)),INDEX('MiT Strom Pipeline'!$O$1:$O$860,$U27),IF(INDEX('MiT Strom Pipeline'!$H$1:$H$860,$U27)="","",INDEX('MiT Strom Pipeline'!$H$1:$H$860,$U27)))) | F27: =IF($U27="","",IF(ISNUMBER(INDEX('MiT Strom Pipeline'!$P$1:$P$860,$U27)),INDEX('MiT Strom Pipeline'!$P$1:$P$860,$U27),"")) | G27: =IF($U27="","",IF(ISNUMBER(INDEX('MiT Strom Pipeline'!$I$1:$I$860,$U27)),INDEX('MiT Strom Pipeline'!$I$1:$I$860,$U27),0)) | H27: =IF($U27="","",IF(ISNUMBER(INDEX('MiT Strom Pipeline'!$Q$1:$Q$860,$U27)),INDEX('MiT Strom Pipeline'!$Q$1:$Q$860,$U27),0)) | I27: =IF($U27="","",IF(INDEX('MiT Strom Pipeline'!$E$1:$E$860,$U27)="","",INDEX('MiT Strom Pipeline'!$E$1:$E$860,$U27))) | J27: =IF($U27="","",INDEX('MiT Strom Pipeline'!$R$1:$R$860,$U27)) | K27: =IF($U27="","",IF(ISNUMBER(INDEX('MiT Strom Pipeline'!$S$1:$S$860,$U27)),INDEX('MiT Strom Pipeline'!$S$1:$S$860,$U27),"")) | L27: =IF($U27="","",IF(LEN(INDEX('MiT Strom Pipeline'!$V$1:$V$860,$U27))>0,LEFT(INDEX('MiT Strom Pipeline'!$V$1:$V$860,$U27),55),"")) | M27: =IF($U27="","",IF(INDEX('MiT Strom Pipeline'!$AF$1:$AF$860,$U27)="","",INDEX('MiT Strom Pipeline'!$AF$1:$AF$860,$U27))) | N27: =IF($U27="","",IF(INDEX('MiT Strom Pipeline'!$BB$1:$BB$860,$U27)="","",INDEX('MiT Strom Pipeline'!$BB$1:$BB$860,$U27))) | U27: =IFERROR(MATCH(17,'MiT Strom Pipeline'!$AM$6:$AM$860,0)+5,"")
A28: =IF($U28="","",IF(ISNUMBER(INDEX('MiT Strom Pipeline'!$A$1:$A$860,$U28)),INDEX('MiT Strom Pipeline'!$A$1:$A$860,$U28),"")) | B28: =IF($U28="","",IF(INDEX('MiT Strom Pipeline'!$B$1:$B$860,$U28)="","",INDEX('MiT Strom Pipeline'!$B$1:$B$860,$U28))) | C28: =IF($U28="","",IF(INDEX('MiT Strom Pipeline'!$C$1:$C$860,$U28)="","",INDEX('MiT Strom Pipeline'!$C$1:$C$860,$U28))) | D28: =IF($U28="","",IF(INDEX('MiT Strom Pipeline'!$D$1:$D$860,$U28)="","",INDEX('MiT Strom Pipeline'!$D$1:$D$860,$U28))) | E28: =IF($U28="","",IF(ISNUMBER(INDEX('MiT Strom Pipeline'!$O$1:$O$860,$U28)),INDEX('MiT Strom Pipeline'!$O$1:$O$860,$U28),IF(INDEX('MiT Strom Pipeline'!$H$1:$H$860,$U28)="","",INDEX('MiT Strom Pipeline'!$H$1:$H$860,$U28)))) | F28: =IF($U28="","",IF(ISNUMBER(INDEX('MiT Strom Pipeline'!$P$1:$P$860,$U28)),INDEX('MiT Strom Pipeline'!$P$1:$P$860,$U28),"")) | G28: =IF($U28="","",IF(ISNUMBER(INDEX('MiT Strom Pipeline'!$I$1:$I$860,$U28)),INDEX('MiT Strom Pipeline'!$I$1:$I$860,$U28),0)) | H28: =IF($U28="","",IF(ISNUMBER(INDEX('MiT Strom Pipeline'!$Q$1:$Q$860,$U28)),INDEX('MiT Strom Pipeline'!$Q$1:$Q$860,$U28),0)) | I28: =IF($U28="","",IF(INDEX('MiT Strom Pipeline'!$E$1:$E$860,$U28)="","",INDEX('MiT Strom Pipeline'!$E$1:$E$860,$U28))) | J28: =IF($U28="","",INDEX('MiT Strom Pipeline'!$R$1:$R$860,$U28)) | K28: =IF($U28="","",IF(ISNUMBER(INDEX('MiT Strom Pipeline'!$S$1:$S$860,$U28)),INDEX('MiT Strom Pipeline'!$S$1:$S$860,$U28),"")) | L28: =IF($U28="","",IF(LEN(INDEX('MiT Strom Pipeline'!$V$1:$V$860,$U28))>0,LEFT(INDEX('MiT Strom Pipeline'!$V$1:$V$860,$U28),55),"")) | M28: =IF($U28="","",IF(INDEX('MiT Strom Pipeline'!$AF$1:$AF$860,$U28)="","",INDEX('MiT Strom Pipeline'!$AF$1:$AF$860,$U28))) | N28: =IF($U28="","",IF(INDEX('MiT Strom Pipeline'!$BB$1:$BB$860,$U28)="","",INDEX('MiT Strom Pipeline'!$BB$1:$BB$860,$U28))) | U28: =IFERROR(MATCH(18,'MiT Strom Pipeline'!$AM$6:$AM$860,0)+5,"")
A29: =IF($U29="","",IF(ISNUMBER(INDEX('MiT Strom Pipeline'!$A$1:$A$860,$U29)),INDEX('MiT Strom Pipeline'!$A$1:$A$860,$U29),"")) | B29: =IF($U29="","",IF(INDEX('MiT Strom Pipeline'!$B$1:$B$860,$U29)="","",INDEX('MiT Strom Pipeline'!$B$1:$B$860,$U29))) | C29: =IF($U29="","",IF(INDEX('MiT Strom Pipeline'!$C$1:$C$860,$U29)="","",INDEX('MiT Strom Pipeline'!$C$1:$C$860,$U29))) | D29: =IF($U29="","",IF(INDEX('MiT Strom Pipeline'!$D$1:$D$860,$U29)="","",INDEX('MiT Strom Pipeline'!$D$1:$D$860,$U29))) | E29: =IF($U29="","",IF(ISNUMBER(INDEX('MiT Strom Pipeline'!$O$1:$O$860,$U29)),INDEX('MiT Strom Pipeline'!$O$1:$O$860,$U29),IF(INDEX('MiT Strom Pipeline'!$H$1:$H$860,$U29)="","",INDEX('MiT Strom Pipeline'!$H$1:$H$860,$U29)))) | F29: =IF($U29="","",IF(ISNUMBER(INDEX('MiT Strom Pipeline'!$P$1:$P$860,$U29)),INDEX('MiT Strom Pipeline'!$P$1:$P$860,$U29),"")) | G29: =IF($U29="","",IF(ISNUMBER(INDEX('MiT Strom Pipeline'!$I$1:$I$860,$U29)),INDEX('MiT Strom Pipeline'!$I$1:$I$860,$U29),0)) | H29: =IF($U29="","",IF(ISNUMBER(INDEX('MiT Strom Pipeline'!$Q$1:$Q$860,$U29)),INDEX('MiT Strom Pipeline'!$Q$1:$Q$860,$U29),0)) | I29: =IF($U29="","",IF(INDEX('MiT Strom Pipeline'!$E$1:$E$860,$U29)="","",INDEX('MiT Strom Pipeline'!$E$1:$E$860,$U29))) | J29: =IF($U29="","",INDEX('MiT Strom Pipeline'!$R$1:$R$860,$U29)) | K29: =IF($U29="","",IF(ISNUMBER(INDEX('MiT Strom Pipeline'!$S$1:$S$860,$U29)),INDEX('MiT Strom Pipeline'!$S$1:$S$860,$U29),"")) | L29: =IF($U29="","",IF(LEN(INDEX('MiT Strom Pipeline'!$V$1:$V$860,$U29))>0,LEFT(INDEX('MiT Strom Pipeline'!$V$1:$V$860,$U29),55),"")) | M29: =IF($U29="","",IF(INDEX('MiT Strom Pipeline'!$AF$1:$AF$860,$U29)="","",INDEX('MiT Strom Pipeline'!$AF$1:$AF$860,$U29))) | N29: =IF($U29="","",IF(INDEX('MiT Strom Pipeline'!$BB$1:$BB$860,$U29)="","",INDEX('MiT Strom Pipeline'!$BB$1:$BB$860,$U29))) | U29: =IFERROR(MATCH(19,'MiT Strom Pipeline'!$AM$6:$AM$860,0)+5,"")
A30: =IF($U30="","",IF(ISNUMBER(INDEX('MiT Strom Pipeline'!$A$1:$A$860,$U30)),INDEX('MiT Strom Pipeline'!$A$1:$A$860,$U30),"")) | B30: =IF($U30="","",IF(INDEX('MiT Strom Pipeline'!$B$1:$B$860,$U30)="","",INDEX('MiT Strom Pipeline'!$B$1:$B$860,$U30))) | C30: =IF($U30="","",IF(INDEX('MiT Strom Pipeline'!$C$1:$C$860,$U30)="","",INDEX('MiT Strom Pipeline'!$C$1:$C$860,$U30))) | D30: =IF($U30="","",IF(INDEX('MiT Strom Pipeline'!$D$1:$D$860,$U30)="","",INDEX('MiT Strom Pipeline'!$D$1:$D$860,$U30))) | E30: =IF($U30="","",IF(ISNUMBER(INDEX('MiT Strom Pipeline'!$O$1:$O$860,$U30)),INDEX('MiT Strom Pipeline'!$O$1:$O$860,$U30),IF(INDEX('MiT Strom Pipeline'!$H$1:$H$860,$U30)="","",INDEX('MiT Strom Pipeline'!$H$1:$H$860,$U30)))) | F30: =IF($U30="","",IF(ISNUMBER(INDEX('MiT Strom Pipeline'!$P$1:$P$860,$U30)),INDEX('MiT Strom Pipeline'!$P$1:$P$860,$U30),"")) | G30: =IF($U30="","",IF(ISNUMBER(INDEX('MiT Strom Pipeline'!$I$1:$I$860,$U30)),INDEX('MiT Strom Pipeline'!$I$1:$I$860,$U30),0)) | H30: =IF($U30="","",IF(ISNUMBER(INDEX('MiT Strom Pipeline'!$Q$1:$Q$860,$U30)),INDEX('MiT Strom Pipeline'!$Q$1:$Q$860,$U30),0)) | I30: =IF($U30="","",IF(INDEX('MiT Strom Pipeline'!$E$1:$E$860,$U30)="","",INDEX('MiT Strom Pipeline'!$E$1:$E$860,$U30))) | J30: =IF($U30="","",INDEX('MiT Strom Pipeline'!$R$1:$R$860,$U30)) | K30: =IF($U30="","",IF(ISNUMBER(INDEX('MiT Strom Pipeline'!$S$1:$S$860,$U30)),INDEX('MiT Strom Pipeline'!$S$1:$S$860,$U30),"")) | L30: =IF($U30="","",IF(LEN(INDEX('MiT Strom Pipeline'!$V$1:$V$860,$U30))>0,LEFT(INDEX('MiT Strom Pipeline'!$V$1:$V$860,$U30),55),"")) | M30: =IF($U30="","",IF(INDEX('MiT Strom Pipeline'!$AF$1:$AF$860,$U30)="","",INDEX('MiT Strom Pipeline'!$AF$1:$AF$860,$U30))) | N30: =IF($U30="","",IF(INDEX('MiT Strom Pipeline'!$BB$1:$BB$860,$U30)="","",INDEX('MiT Strom Pipeline'!$BB$1:$BB$860,$U30))) | U30: =IFERROR(MATCH(20,'MiT Strom Pipeline'!$AM$6:$AM$860,0)+5,"")
A31: =IF($U31="","",IF(ISNUMBER(INDEX('MiT Strom Pipeline'!$A$1:$A$860,$U31)),INDEX('MiT Strom Pipeline'!$A$1:$A$860,$U31),"")) | B31: =IF($U31="","",IF(INDEX('MiT Strom Pipeline'!$B$1:$B$860,$U31)="","",INDEX('MiT Strom Pipeline'!$B$1:$B$860,$U31))) | C31: =IF($U31="","",IF(INDEX('MiT Strom Pipeline'!$C$1:$C$860,$U31)="","",INDEX('MiT Strom Pipeline'!$C$1:$C$860,$U31))) | D31: =IF($U31="","",IF(INDEX('MiT Strom Pipeline'!$D$1:$D$860,$U31)="","",INDEX('MiT Strom Pipeline'!$D$1:$D$860,$U31))) | E31: =IF($U31="","",IF(ISNUMBER(INDEX('MiT Strom Pipeline'!$O$1:$O$860,$U31)),INDEX('MiT Strom Pipeline'!$O$1:$O$860,$U31),IF(INDEX('MiT Strom Pipeline'!$H$1:$H$860,$U31)="","",INDEX('MiT Strom Pipeline'!$H$1:$H$860,$U31)))) | F31: =IF($U31="","",IF(ISNUMBER(INDEX('MiT Strom Pipeline'!$P$1:$P$860,$U31)),INDEX('MiT Strom Pipeline'!$P$1:$P$860,$U31),"")) | G31: =IF($U31="","",IF(ISNUMBER(INDEX('MiT Strom Pipeline'!$I$1:$I$860,$U31)),INDEX('MiT Strom Pipeline'!$I$1:$I$860,$U31),0)) | H31: =IF($U31="","",IF(ISNUMBER(INDEX('MiT Strom Pipeline'!$Q$1:$Q$860,$U31)),INDEX('MiT Strom Pipeline'!$Q$1:$Q$860,$U31),0)) | I31: =IF($U31="","",IF(INDEX('MiT Strom Pipeline'!$E$1:$E$860,$U31)="","",INDEX('MiT Strom Pipeline'!$E$1:$E$860,$U31))) | J31: =IF($U31="","",INDEX('MiT Strom Pipeline'!$R$1:$R$860,$U31)) | K31: =IF($U31="","",IF(ISNUMBER(INDEX('MiT Strom Pipeline'!$S$1:$S$860,$U31)),INDEX('MiT Strom Pipeline'!$S$1:$S$860,$U31),"")) | L31: =IF($U31="","",IF(LEN(INDEX('MiT Strom Pipeline'!$V$1:$V$860,$U31))>0,LEFT(INDEX('MiT Strom Pipeline'!$V$1:$V$860,$U31),55),"")) | M31: =IF($U31="","",IF(INDEX('MiT Strom Pipeline'!$AF$1:$AF$860,$U31)="","",INDEX('MiT Strom Pipeline'!$AF$1:$AF$860,$U31))) | N31: =IF($U31="","",IF(INDEX('MiT Strom Pipeline'!$BB$1:$BB$860,$U31)="","",INDEX('MiT Strom Pipeline'!$BB$1:$BB$860,$U31))) | U31: =IFERROR(MATCH(21,'MiT Strom Pipeline'!$AM$6:$AM$860,0)+5,"")
A32: =IF($U32="","",IF(ISNUMBER(INDEX('MiT Strom Pipeline'!$A$1:$A$860,$U32)),INDEX('MiT Strom Pipeline'!$A$1:$A$860,$U32),"")) | B32: =IF($U32="","",IF(INDEX('MiT Strom Pipeline'!$B$1:$B$860,$U32)="","",INDEX('MiT Strom Pipeline'!$B$1:$B$860,$U32))) | C32: =IF($U32="","",IF(INDEX('MiT Strom Pipeline'!$C$1:$C$860,$U32)="","",INDEX('MiT Strom Pipeline'!$C$1:$C$860,$U32))) | D32: =IF($U32="","",IF(INDEX('MiT Strom Pipeline'!$D$1:$D$860,$U32)="","",INDEX('MiT Strom Pipeline'!$D$1:$D$860,$U32))) | E32: =IF($U32="","",IF(ISNUMBER(INDEX('MiT Strom Pipeline'!$O$1:$O$860,$U32)),INDEX('MiT Strom Pipeline'!$O$1:$O$860,$U32),IF(INDEX('MiT Strom Pipeline'!$H$1:$H$860,$U32)="","",INDEX('MiT Strom Pipeline'!$H$1:$H$860,$U32)))) | F32: =IF($U32="","",IF(ISNUMBER(INDEX('MiT Strom Pipeline'!$P$1:$P$860,$U32)),INDEX('MiT Strom Pipeline'!$P$1:$P$860,$U32),"")) | G32: =IF($U32="","",IF(ISNUMBER(INDEX('MiT Strom Pipeline'!$I$1:$I$860,$U32)),INDEX('MiT Strom Pipeline'!$I$1:$I$860,$U32),0)) | H32: =IF($U32="","",IF(ISNUMBER(INDEX('MiT Strom Pipeline'!$Q$1:$Q$860,$U32)),INDEX('MiT Strom Pipeline'!$Q$1:$Q$860,$U32),0)) | I32: =IF($U32="","",IF(INDEX('MiT Strom Pipeline'!$E$1:$E$860,$U32)="","",INDEX('MiT Strom Pipeline'!$E$1:$E$860,$U32))) | J32: =IF($U32="","",INDEX('MiT Strom Pipeline'!$R$1:$R$860,$U32)) | K32: =IF($U32="","",IF(ISNUMBER(INDEX('MiT Strom Pipeline'!$S$1:$S$860,$U32)),INDEX('MiT Strom Pipeline'!$S$1:$S$860,$U32),"")) | L32: =IF($U32="","",IF(LEN(INDEX('MiT Strom Pipeline'!$V$1:$V$860,$U32))>0,LEFT(INDEX('MiT Strom Pipeline'!$V$1:$V$860,$U32),55),"")) | M32: =IF($U32="","",IF(INDEX('MiT Strom Pipeline'!$AF$1:$AF$860,$U32)="","",INDEX('MiT Strom Pipeline'!$AF$1:$AF$860,$U32))) | N32: =IF($U32="","",IF(INDEX('MiT Strom Pipeline'!$BB$1:$BB$860,$U32)="","",INDEX('MiT Strom Pipeline'!$BB$1:$BB$860,$U32))) | U32: =IFERROR(MATCH(22,'MiT Strom Pipeline'!$AM$6:$AM$860,0)+5,"")
A33: =IF($U33="","",IF(ISNUMBER(INDEX('MiT Strom Pipeline'!$A$1:$A$860,$U33)),INDEX('MiT Strom Pipeline'!$A$1:$A$860,$U33),"")) | B33: =IF($U33="","",IF(INDEX('MiT Strom Pipeline'!$B$1:$B$860,$U33)="","",INDEX('MiT Strom Pipeline'!$B$1:$B$860,$U33))) | C33: =IF($U33="","",IF(INDEX('MiT Strom Pipeline'!$C$1:$C$860,$U33)="","",INDEX('MiT Strom Pipeline'!$C$1:$C$860,$U33))) | D33: =IF($U33="","",IF(INDEX('MiT Strom Pipeline'!$D$1:$D$860,$U33)="","",INDEX('MiT Strom Pipeline'!$D$1:$D$860,$U33))) | E33: =IF($U33="","",IF(ISNUMBER(INDEX('MiT Strom Pipeline'!$O$1:$O$860,$U33)),INDEX('MiT Strom Pipeline'!$O$1:$O$860,$U33),IF(INDEX('MiT Strom Pipeline'!$H$1:$H$860,$U33)="","",INDEX('MiT Strom Pipeline'!$H$1:$H$860,$U33)))) | F33: =IF($U33="","",IF(ISNUMBER(INDEX('MiT Strom Pipeline'!$P$1:$P$860,$U33)),INDEX('MiT Strom Pipeline'!$P$1:$P$860,$U33),"")) | G33: =IF($U33="","",IF(ISNUMBER(INDEX('MiT Strom Pipeline'!$I$1:$I$860,$U33)),INDEX('MiT Strom Pipeline'!$I$1:$I$860,$U33),0)) | H33: =IF($U33="","",IF(ISNUMBER(INDEX('MiT Strom Pipeline'!$Q$1:$Q$860,$U33)),INDEX('MiT Strom Pipeline'!$Q$1:$Q$860,$U33),0)) | I33: =IF($U33="","",IF(INDEX('MiT Strom Pipeline'!$E$1:$E$860,$U33)="","",INDEX('MiT Strom Pipeline'!$E$1:$E$860,$U33))) | J33: =IF($U33="","",INDEX('MiT Strom Pipeline'!$R$1:$R$860,$U33)) | K33: =IF($U33="","",IF(ISNUMBER(INDEX('MiT Strom Pipeline'!$S$1:$S$860,$U33)),INDEX('MiT Strom Pipeline'!$S$1:$S$860,$U33),"")) | L33: =IF($U33="","",IF(LEN(INDEX('MiT Strom Pipeline'!$V$1:$V$860,$U33))>0,LEFT(INDEX('MiT Strom Pipeline'!$V$1:$V$860,$U33),55),"")) | M33: =IF($U33="","",IF(INDEX('MiT Strom Pipeline'!$AF$1:$AF$860,$U33)="","",INDEX('MiT Strom Pipeline'!$AF$1:$AF$860,$U33))) | N33: =IF($U33="","",IF(INDEX('MiT Strom Pipeline'!$BB$1:$BB$860,$U33)="","",INDEX('MiT Strom Pipeline'!$BB$1:$BB$860,$U33))) | U33: =IFERROR(MATCH(23,'MiT Strom Pipeline'!$AM$6:$AM$860,0)+5,"")
A34: =IF($U34="","",IF(ISNUMBER(INDEX('MiT Strom Pipeline'!$A$1:$A$860,$U34)),INDEX('MiT Strom Pipeline'!$A$1:$A$860,$U34),"")) | B34: =IF($U34="","",IF(INDEX('MiT Strom Pipeline'!$B$1:$B$860,$U34)="","",INDEX('MiT Strom Pipeline'!$B$1:$B$860,$U34))) | C34: =IF($U34="","",IF(INDEX('MiT Strom Pipeline'!$C$1:$C$860,$U34)="","",INDEX('MiT Strom Pipeline'!$C$1:$C$860,$U34))) | D34: =IF($U34="","",IF(INDEX('MiT Strom Pipeline'!$D$1:$D$860,$U34)="","",INDEX('MiT Strom Pipeline'!$D$1:$D$860,$U34))) | E34: =IF($U34="","",IF(ISNUMBER(INDEX('MiT Strom Pipeline'!$O$1:$O$860,$U34)),INDEX('MiT Strom Pipeline'!$O$1:$O$860,$U34),IF(INDEX('MiT Strom Pipeline'!$H$1:$H$860,$U34)="","",INDEX('MiT Strom Pipeline'!$H$1:$H$860,$U34)))) | F34: =IF($U34="","",IF(ISNUMBER(INDEX('MiT Strom Pipeline'!$P$1:$P$860,$U34)),INDEX('MiT Strom Pipeline'!$P$1:$P$860,$U34),"")) | G34: =IF($U34="","",IF(ISNUMBER(INDEX('MiT Strom Pipeline'!$I$1:$I$860,$U34)),INDEX('MiT Strom Pipeline'!$I$1:$I$860,$U34),0)) | H34: =IF($U34="","",IF(ISNUMBER(INDEX('MiT Strom Pipeline'!$Q$1:$Q$860,$U34)),INDEX('MiT Strom Pipeline'!$Q$1:$Q$860,$U34),0)) | I34: =IF($U34="","",IF(INDEX('MiT Strom Pipeline'!$E$1:$E$860,$U34)="","",INDEX('MiT Strom Pipeline'!$E$1:$E$860,$U34))) | J34: =IF($U34="","",INDEX('MiT Strom Pipeline'!$R$1:$R$860,$U34)) | K34: =IF($U34="","",IF(ISNUMBER(INDEX('MiT Strom Pipeline'!$S$1:$S$860,$U34)),INDEX('MiT Strom Pipeline'!$S$1:$S$860,$U34),"")) | L34: =IF($U34="","",IF(LEN(INDEX('MiT Strom Pipeline'!$V$1:$V$860,$U34))>0,LEFT(INDEX('MiT Strom Pipeline'!$V$1:$V$860,$U34),55),"")) | M34: =IF($U34="","",IF(INDEX('MiT Strom Pipeline'!$AF$1:$AF$860,$U34)="","",INDEX('MiT Strom Pipeline'!$AF$1:$AF$860,$U34))) | N34: =IF($U34="","",IF(INDEX('MiT Strom Pipeline'!$BB$1:$BB$860,$U34)="","",INDEX('MiT Strom Pipeline'!$BB$1:$BB$860,$U34))) | U34: =IFERROR(MATCH(24,'MiT Strom Pipeline'!$AM$6:$AM$860,0)+5,"")
A35: =IF($U35="","",IF(ISNUMBER(INDEX('MiT Strom Pipeline'!$A$1:$A$860,$U35)),INDEX('MiT Strom Pipeline'!$A$1:$A$860,$U35),"")) | B35: =IF($U35="","",IF(INDEX('MiT Strom Pipeline'!$B$1:$B$860,$U35)="","",INDEX('MiT Strom Pipeline'!$B$1:$B$860,$U35))) | C35: =IF($U35="","",IF(INDEX('MiT Strom Pipeline'!$C$1:$C$860,$U35)="","",INDEX('MiT Strom Pipeline'!$C$1:$C$860,$U35))) | D35: =IF($U35="","",IF(INDEX('MiT Strom Pipeline'!$D$1:$D$860,$U35)="","",INDEX('MiT Strom Pipeline'!$D$1:$D$860,$U35))) | E35: =IF($U35="","",IF(ISNUMBER(INDEX('MiT Strom Pipeline'!$O$1:$O$860,$U35)),INDEX('MiT Strom Pipeline'!$O$1:$O$860,$U35),IF(INDEX('MiT Strom Pipeline'!$H$1:$H$860,$U35)="","",INDEX('MiT Strom Pipeline'!$H$1:$H$860,$U35)))) | F35: =IF($U35="","",IF(ISNUMBER(INDEX('MiT Strom Pipeline'!$P$1:$P$860,$U35)),INDEX('MiT Strom Pipeline'!$P$1:$P$860,$U35),"")) | G35: =IF($U35="","",IF(ISNUMBER(INDEX('MiT Strom Pipeline'!$I$1:$I$860,$U35)),INDEX('MiT Strom Pipeline'!$I$1:$I$860,$U35),0)) | H35: =IF($U35="","",IF(ISNUMBER(INDEX('MiT Strom Pipeline'!$Q$1:$Q$860,$U35)),INDEX('MiT Strom Pipeline'!$Q$1:$Q$860,$U35),0)) | I35: =IF($U35="","",IF(INDEX('MiT Strom Pipeline'!$E$1:$E$860,$U35)="","",INDEX('MiT Strom Pipeline'!$E$1:$E$860,$U35))) | J35: =IF($U35="","",INDEX('MiT Strom Pipeline'!$R$1:$R$860,$U35)) | K35: =IF($U35="","",IF(ISNUMBER(INDEX('MiT Strom Pipeline'!$S$1:$S$860,$U35)),INDEX('MiT Strom Pipeline'!$S$1:$S$860,$U35),"")) | L35: =IF($U35="","",IF(LEN(INDEX('MiT Strom Pipeline'!$V$1:$V$860,$U35))>0,LEFT(INDEX('MiT Strom Pipeline'!$V$1:$V$860,$U35),55),"")) | M35: =IF($U35="","",IF(INDEX('MiT Strom Pipeline'!$AF$1:$AF$860,$U35)="","",INDEX('MiT Strom Pipeline'!$AF$1:$AF$860,$U35))) | N35: =IF($U35="","",IF(INDEX('MiT Strom Pipeline'!$BB$1:$BB$860,$U35)="","",INDEX('MiT Strom Pipeline'!$BB$1:$BB$860,$U35))) | U35: =IFERROR(MATCH(25,'MiT Strom Pipeline'!$AM$6:$AM$860,0)+5,"")
A36: =IF($U36="","",IF(ISNUMBER(INDEX('MiT Strom Pipeline'!$A$1:$A$860,$U36)),INDEX('MiT Strom Pipeline'!$A$1:$A$860,$U36),"")) | B36: =IF($U36="","",IF(INDEX('MiT Strom Pipeline'!$B$1:$B$860,$U36)="","",INDEX('MiT Strom Pipeline'!$B$1:$B$860,$U36))) | C36: =IF($U36="","",IF(INDEX('MiT Strom Pipeline'!$C$1:$C$860,$U36)="","",INDEX('MiT Strom Pipeline'!$C$1:$C$860,$U36))) | D36: =IF($U36="","",IF(INDEX('MiT Strom Pipeline'!$D$1:$D$860,$U36)="","",INDEX('MiT Strom Pipeline'!$D$1:$D$860,$U36))) | E36: =IF($U36="","",IF(ISNUMBER(INDEX('MiT Strom Pipeline'!$O$1:$O$860,$U36)),INDEX('MiT Strom Pipeline'!$O$1:$O$860,$U36),IF(INDEX('MiT Strom Pipeline'!$H$1:$H$860,$U36)="","",INDEX('MiT Strom Pipeline'!$H$1:$H$860,$U36)))) | F36: =IF($U36="","",IF(ISNUMBER(INDEX('MiT Strom Pipeline'!$P$1:$P$860,$U36)),INDEX('MiT Strom Pipeline'!$P$1:$P$860,$U36),"")) | G36: =IF($U36="","",IF(ISNUMBER(INDEX('MiT Strom Pipeline'!$I$1:$I$860,$U36)),INDEX('MiT Strom Pipeline'!$I$1:$I$860,$U36),0)) | H36: =IF($U36="","",IF(ISNUMBER(INDEX('MiT Strom Pipeline'!$Q$1:$Q$860,$U36)),INDEX('MiT Strom Pipeline'!$Q$1:$Q$860,$U36),0)) | I36: =IF($U36="","",IF(INDEX('MiT Strom Pipeline'!$E$1:$E$860,$U36)="","",INDEX('MiT Strom Pipeline'!$E$1:$E$860,$U36))) | J36: =IF($U36="","",INDEX('MiT Strom Pipeline'!$R$1:$R$860,$U36)) | K36: =IF($U36="","",IF(ISNUMBER(INDEX('MiT Strom Pipeline'!$S$1:$S$860,$U36)),INDEX('MiT Strom Pipeline'!$S$1:$S$860,$U36),"")) | L36: =IF($U36="","",IF(LEN(INDEX('MiT Strom Pipeline'!$V$1:$V$860,$U36))>0,LEFT(INDEX('MiT Strom Pipeline'!$V$1:$V$860,$U36),55),"")) | M36: =IF($U36="","",IF(INDEX('MiT Strom Pipeline'!$AF$1:$AF$860,$U36)="","",INDEX('MiT Strom Pipeline'!$AF$1:$AF$860,$U36))) | N36: =IF($U36="","",IF(INDEX('MiT Strom Pipeline'!$BB$1:$BB$860,$U36)="","",INDEX('MiT Strom Pipeline'!$BB$1:$BB$860,$U36))) | U36: =IFERROR(MATCH(26,'MiT Strom Pipeline'!$AM$6:$AM$860,0)+5,"")
A37: =IF($U37="","",IF(ISNUMBER(INDEX('MiT Strom Pipeline'!$A$1:$A$860,$U37)),INDEX('MiT Strom Pipeline'!$A$1:$A$860,$U37),"")) | B37: =IF($U37="","",IF(INDEX('MiT Strom Pipeline'!$B$1:$B$860,$U37)="","",INDEX('MiT Strom Pipeline'!$B$1:$B$860,$U37))) | C37: =IF($U37="","",IF(INDEX('MiT Strom Pipeline'!$C$1:$C$860,$U37)="","",INDEX('MiT Strom Pipeline'!$C$1:$C$860,$U37))) | D37: =IF($U37="","",IF(INDEX('MiT Strom Pipeline'!$D$1:$D$860,$U37)="","",INDEX('MiT Strom Pipeline'!$D$1:$D$860,$U37))) | E37: =IF($U37="","",IF(ISNUMBER(INDEX('MiT Strom Pipeline'!$O$1:$O$860,$U37)),INDEX('MiT Strom Pipeline'!$O$1:$O$860,$U37),IF(INDEX('MiT Strom Pipeline'!$H$1:$H$860,$U37)="","",INDEX('MiT Strom Pipeline'!$H$1:$H$860,$U37)))) | F37: =IF($U37="","",IF(ISNUMBER(INDEX('MiT Strom Pipeline'!$P$1:$P$860,$U37)),INDEX('MiT Strom Pipeline'!$P$1:$P$860,$U37),"")) | G37: =IF($U37="","",IF(ISNUMBER(INDEX('MiT Strom Pipeline'!$I$1:$I$860,$U37)),INDEX('MiT Strom Pipeline'!$I$1:$I$860,$U37),0)) | H37: =IF($U37="","",IF(ISNUMBER(INDEX('MiT Strom Pipeline'!$Q$1:$Q$860,$U37)),INDEX('MiT Strom Pipeline'!$Q$1:$Q$860,$U37),0)) | I37: =IF($U37="","",IF(INDEX('MiT Strom Pipeline'!$E$1:$E$860,$U37)="","",INDEX('MiT Strom Pipeline'!$E$1:$E$860,$U37))) | J37: =IF($U37="","",INDEX('MiT Strom Pipeline'!$R$1:$R$860,$U37)) | K37: =IF($U37="","",IF(ISNUMBER(INDEX('MiT Strom Pipeline'!$S$1:$S$860,$U37)),INDEX('MiT Strom Pipeline'!$S$1:$S$860,$U37),"")) | L37: =IF($U37="","",IF(LEN(INDEX('MiT Strom Pipeline'!$V$1:$V$860,$U37))>0,LEFT(INDEX('MiT Strom Pipeline'!$V$1:$V$860,$U37),55),"")) | M37: =IF($U37="","",IF(INDEX('MiT Strom Pipeline'!$AF$1:$AF$860,$U37)="","",INDEX('MiT Strom Pipeline'!$AF$1:$AF$860,$U37))) | N37: =IF($U37="","",IF(INDEX('MiT Strom Pipeline'!$BB$1:$BB$860,$U37)="","",INDEX('MiT Strom Pipeline'!$BB$1:$BB$860,$U37))) | U37: =IFERROR(MATCH(27,'MiT Strom Pipeline'!$AM$6:$AM$860,0)+5,"")
A38: =IF($U38="","",IF(ISNUMBER(INDEX('MiT Strom Pipeline'!$A$1:$A$860,$U38)),INDEX('MiT Strom Pipeline'!$A$1:$A$860,$U38),"")) | B38: =IF($U38="","",IF(INDEX('MiT Strom Pipeline'!$B$1:$B$860,$U38)="","",INDEX('MiT Strom Pipeline'!$B$1:$B$860,$U38))) | C38: =IF($U38="","",IF(INDEX('MiT Strom Pipeline'!$C$1:$C$860,$U38)="","",INDEX('MiT Strom Pipeline'!$C$1:$C$860,$U38))) | D38: =IF($U38="","",IF(INDEX('MiT Strom Pipeline'!$D$1:$D$860,$U38)="","",INDEX('MiT Strom Pipeline'!$D$1:$D$860,$U38))) | E38: =IF($U38="","",IF(ISNUMBER(INDEX('MiT Strom Pipeline'!$O$1:$O$860,$U38)),INDEX('MiT Strom Pipeline'!$O$1:$O$860,$U38),IF(INDEX('MiT Strom Pipeline'!$H$1:$H$860,$U38)="","",INDEX('MiT Strom Pipeline'!$H$1:$H$860,$U38)))) | F38: =IF($U38="","",IF(ISNUMBER(INDEX('MiT Strom Pipeline'!$P$1:$P$860,$U38)),INDEX('MiT Strom Pipeline'!$P$1:$P$860,$U38),"")) | G38: =IF($U38="","",IF(ISNUMBER(INDEX('MiT Strom Pipeline'!$I$1:$I$860,$U38)),INDEX('MiT Strom Pipeline'!$I$1:$I$860,$U38),0)) | H38: =IF($U38="","",IF(ISNUMBER(INDEX('MiT Strom Pipeline'!$Q$1:$Q$860,$U38)),INDEX('MiT Strom Pipeline'!$Q$1:$Q$860,$U38),0)) | I38: =IF($U38="","",IF(INDEX('MiT Strom Pipeline'!$E$1:$E$860,$U38)="","",INDEX('MiT Strom Pipeline'!$E$1:$E$860,$U38))) | J38: =IF($U38="","",INDEX('MiT Strom Pipeline'!$R$1:$R$860,$U38)) | K38: =IF($U38="","",IF(ISNUMBER(INDEX('MiT Strom Pipeline'!$S$1:$S$860,$U38)),INDEX('MiT Strom Pipeline'!$S$1:$S$860,$U38),"")) | L38: =IF($U38="","",IF(LEN(INDEX('MiT Strom Pipeline'!$V$1:$V$860,$U38))>0,LEFT(INDEX('MiT Strom Pipeline'!$V$1:$V$860,$U38),55),"")) | M38: =IF($U38="","",IF(INDEX('MiT Strom Pipeline'!$AF$1:$AF$860,$U38)="","",INDEX('MiT Strom Pipeline'!$AF$1:$AF$860,$U38))) | N38: =IF($U38="","",IF(INDEX('MiT Strom Pipeline'!$BB$1:$BB$860,$U38)="","",INDEX('MiT Strom Pipeline'!$BB$1:$BB$860,$U38))) | U38: =IFERROR(MATCH(28,'MiT Strom Pipeline'!$AM$6:$AM$860,0)+5,"")
A39: =IF($U39="","",IF(ISNUMBER(INDEX('MiT Strom Pipeline'!$A$1:$A$860,$U39)),INDEX('MiT Strom Pipeline'!$A$1:$A$860,$U39),"")) | B39: =IF($U39="","",IF(INDEX('MiT Strom Pipeline'!$B$1:$B$860,$U39)="","",INDEX('MiT Strom Pipeline'!$B$1:$B$860,$U39))) | C39: =IF($U39="","",IF(INDEX('MiT Strom Pipeline'!$C$1:$C$860,$U39)="","",INDEX('MiT Strom Pipeline'!$C$1:$C$860,$U39))) | D39: =IF($U39="","",IF(INDEX('MiT Strom Pipeline'!$D$1:$D$860,$U39)="","",INDEX('MiT Strom Pipeline'!$D$1:$D$860,$U39))) | E39: =IF($U39="","",IF(ISNUMBER(INDEX('MiT Strom Pipeline'!$O$1:$O$860,$U39)),INDEX('MiT Strom Pipeline'!$O$1:$O$860,$U39),IF(INDEX('MiT Strom Pipeline'!$H$1:$H$860,$U39)="","",INDEX('MiT Strom Pipeline'!$H$1:$H$860,$U39)))) | F39: =IF($U39="","",IF(ISNUMBER(INDEX('MiT Strom Pipeline'!$P$1:$P$860,$U39)),INDEX('MiT Strom Pipeline'!$P$1:$P$860,$U39),"")) | G39: =IF($U39="","",IF(ISNUMBER(INDEX('MiT Strom Pipeline'!$I$1:$I$860,$U39)),INDEX('MiT Strom Pipeline'!$I$1:$I$860,$U39),0)) | H39: =IF($U39="","",IF(ISNUMBER(INDEX('MiT Strom Pipeline'!$Q$1:$Q$860,$U39)),INDEX('MiT Strom Pipeline'!$Q$1:$Q$860,$U39),0)) | I39: =IF($U39="","",IF(INDEX('MiT Strom Pipeline'!$E$1:$E$860,$U39)="","",INDEX('MiT Strom Pipeline'!$E$1:$E$860,$U39))) | J39: =IF($U39="","",INDEX('MiT Strom Pipeline'!$R$1:$R$860,$U39)) | K39: =IF($U39="","",IF(ISNUMBER(INDEX('MiT Strom Pipeline'!$S$1:$S$860,$U39)),INDEX('MiT Strom Pipeline'!$S$1:$S$860,$U39),"")) | L39: =IF($U39="","",IF(LEN(INDEX('MiT Strom Pipeline'!$V$1:$V$860,$U39))>0,LEFT(INDEX('MiT Strom Pipeline'!$V$1:$V$860,$U39),55),"")) | M39: =IF($U39="","",IF(INDEX('MiT Strom Pipeline'!$AF$1:$AF$860,$U39)="","",INDEX('MiT Strom Pipeline'!$AF$1:$AF$860,$U39))) | N39: =IF($U39="","",IF(INDEX('MiT Strom Pipeline'!$BB$1:$BB$860,$U39)="","",INDEX('MiT Strom Pipeline'!$BB$1:$BB$860,$U39))) | U39: =IFERROR(MATCH(29,'MiT Strom Pipeline'!$AM$6:$AM$860,0)+5,"")
A40: =IF($U40="","",IF(ISNUMBER(INDEX('MiT Strom Pipeline'!$A$1:$A$860,$U40)),INDEX('MiT Strom Pipeline'!$A$1:$A$860,$U40),"")) | B40: =IF($U40="","",IF(INDEX('MiT Strom Pipeline'!$B$1:$B$860,$U40)="","",INDEX('MiT Strom Pipeline'!$B$1:$B$860,$U40))) | C40: =IF($U40="","",IF(INDEX('MiT Strom Pipeline'!$C$1:$C$860,$U40)="","",INDEX('MiT Strom Pipeline'!$C$1:$C$860,$U40))) | D40: =IF($U40="","",IF(INDEX('MiT Strom Pipeline'!$D$1:$D$860,$U40)="","",INDEX('MiT Strom Pipeline'!$D$1:$D$860,$U40))) | E40: =IF($U40="","",IF(ISNUMBER(INDEX('MiT Strom Pipeline'!$O$1:$O$860,$U40)),INDEX('MiT Strom Pipeline'!$O$1:$O$860,$U40),IF(INDEX('MiT Strom Pipeline'!$H$1:$H$860,$U40)="","",INDEX('MiT Strom Pipeline'!$H$1:$H$860,$U40)))) | F40: =IF($U40="","",IF(ISNUMBER(INDEX('MiT Strom Pipeline'!$P$1:$P$860,$U40)),INDEX('MiT Strom Pipeline'!$P$1:$P$860,$U40),"")) | G40: =IF($U40="","",IF(ISNUMBER(INDEX('MiT Strom Pipeline'!$I$1:$I$860,$U40)),INDEX('MiT Strom Pipeline'!$I$1:$I$860,$U40),0)) | H40: =IF($U40="","",IF(ISNUMBER(INDEX('MiT Strom Pipeline'!$Q$1:$Q$860,$U40)),INDEX('MiT Strom Pipeline'!$Q$1:$Q$860,$U40),0)) | I40: =IF($U40="","",IF(INDEX('MiT Strom Pipeline'!$E$1:$E$860,$U40)="","",INDEX('MiT Strom Pipeline'!$E$1:$E$860,$U40))) | J40: =IF($U40="","",INDEX('MiT Strom Pipeline'!$R$1:$R$860,$U40)) | K40: =IF($U40="","",IF(ISNUMBER(INDEX('MiT Strom Pipeline'!$S$1:$S$860,$U40)),INDEX('MiT Strom Pipeline'!$S$1:$S$860,$U40),"")) | L40: =IF($U40="","",IF(LEN(INDEX('MiT Strom Pipeline'!$V$1:$V$860,$U40))>0,LEFT(INDEX('MiT Strom Pipeline'!$V$1:$V$860,$U40),55),"")) | M40: =IF($U40="","",IF(INDEX('MiT Strom Pipeline'!$AF$1:$AF$860,$U40)="","",INDEX('MiT Strom Pipeline'!$AF$1:$AF$860,$U40))) | N40: =IF($U40="","",IF(INDEX('MiT Strom Pipeline'!$BB$1:$BB$860,$U40)="","",INDEX('MiT Strom Pipeline'!$BB$1:$BB$860,$U40))) | U40: =IFERROR(MATCH(30,'MiT Strom Pipeline'!$AM$6:$AM$860,0)+5,"")
A41: =IF($U41="","",IF(ISNUMBER(INDEX('MiT Strom Pipeline'!$A$1:$A$860,$U41)),INDEX('MiT Strom Pipeline'!$A$1:$A$860,$U41),"")) | B41: =IF($U41="","",IF(INDEX('MiT Strom Pipeline'!$B$1:$B$860,$U41)="","",INDEX('MiT Strom Pipeline'!$B$1:$B$860,$U41))) | C41: =IF($U41="","",IF(INDEX('MiT Strom Pipeline'!$C$1:$C$860,$U41)="","",INDEX('MiT Strom Pipeline'!$C$1:$C$860,$U41))) | D41: =IF($U41="","",IF(INDEX('MiT Strom Pipeline'!$D$1:$D$860,$U41)="","",INDEX('MiT Strom Pipeline'!$D$1:$D$860,$U41))) | E41: =IF($U41="","",IF(ISNUMBER(INDEX('MiT Strom Pipeline'!$O$1:$O$860,$U41)),INDEX('MiT Strom Pipeline'!$O$1:$O$860,$U41),IF(INDEX('MiT Strom Pipeline'!$H$1:$H$860,$U41)="","",INDEX('MiT Strom Pipeline'!$H$1:$H$860,$U41)))) | F41: =IF($U41="","",IF(ISNUMBER(INDEX('MiT Strom Pipeline'!$P$1:$P$860,$U41)),INDEX('MiT Strom Pipeline'!$P$1:$P$860,$U41),"")) | G41: =IF($U41="","",IF(ISNUMBER(INDEX('MiT Strom Pipeline'!$I$1:$I$860,$U41)),INDEX('MiT Strom Pipeline'!$I$1:$I$860,$U41),0)) | H41: =IF($U41="","",IF(ISNUMBER(INDEX('MiT Strom Pipeline'!$Q$1:$Q$860,$U41)),INDEX('MiT Strom Pipeline'!$Q$1:$Q$860,$U41),0)) | I41: =IF($U41="","",IF(INDEX('MiT Strom Pipeline'!$E$1:$E$860,$U41)="","",INDEX('MiT Strom Pipeline'!$E$1:$E$860,$U41))) | J41: =IF($U41="","",INDEX('MiT Strom Pipeline'!$R$1:$R$860,$U41)) | K41: =IF($U41="","",IF(ISNUMBER(INDEX('MiT Strom Pipeline'!$S$1:$S$860,$U41)),INDEX('MiT Strom Pipeline'!$S$1:$S$860,$U41),"")) | L41: =IF($U41="","",IF(LEN(INDEX('MiT Strom Pipeline'!$V$1:$V$860,$U41))>0,LEFT(INDEX('MiT Strom Pipeline'!$V$1:$V$860,$U41),55),"")) | M41: =IF($U41="","",IF(INDEX('MiT Strom Pipeline'!$AF$1:$AF$860,$U41)="","",INDEX('MiT Strom Pipeline'!$AF$1:$AF$860,$U41))) | N41: =IF($U41="","",IF(INDEX('MiT Strom Pipeline'!$BB$1:$BB$860,$U41)="","",INDEX('MiT Strom Pipeline'!$BB$1:$BB$860,$U41))) | U41: =IFERROR(MATCH(31,'MiT Strom Pipeline'!$AM$6:$AM$860,0)+5,"")
A42: =IF($U42="","",IF(ISNUMBER(INDEX('MiT Strom Pipeline'!$A$1:$A$860,$U42)),INDEX('MiT Strom Pipeline'!$A$1:$A$860,$U42),"")) | B42: =IF($U42="","",IF(INDEX('MiT Strom Pipeline'!$B$1:$B$860,$U42)="","",INDEX('MiT Strom Pipeline'!$B$1:$B$860,$U42))) | C42: =IF($U42="","",IF(INDEX('MiT Strom Pipeline'!$C$1:$C$860,$U42)="","",INDEX('MiT Strom Pipeline'!$C$1:$C$860,$U42))) | D42: =IF($U42="","",IF(INDEX('MiT Strom Pipeline'!$D$1:$D$860,$U42)="","",INDEX('MiT Strom Pipeline'!$D$1:$D$860,$U42))) | E42: =IF($U42="","",IF(ISNUMBER(INDEX('MiT Strom Pipeline'!$O$1:$O$860,$U42)),INDEX('MiT Strom Pipeline'!$O$1:$O$860,$U42),IF(INDEX('MiT Strom Pipeline'!$H$1:$H$860,$U42)="","",INDEX('MiT Strom Pipeline'!$H$1:$H$860,$U42)))) | F42: =IF($U42="","",IF(ISNUMBER(INDEX('MiT Strom Pipeline'!$P$1:$P$860,$U42)),INDEX('MiT Strom Pipeline'!$P$1:$P$860,$U42),"")) | G42: =IF($U42="","",IF(ISNUMBER(INDEX('MiT Strom Pipeline'!$I$1:$I$860,$U42)),INDEX('MiT Strom Pipeline'!$I$1:$I$860,$U42),0)) | H42: =IF($U42="","",IF(ISNUMBER(INDEX('MiT Strom Pipeline'!$Q$1:$Q$860,$U42)),INDEX('MiT Strom Pipeline'!$Q$1:$Q$860,$U42),0)) | I42: =IF($U42="","",IF(INDEX('MiT Strom Pipeline'!$E$1:$E$860,$U42)="","",INDEX('MiT Strom Pipeline'!$E$1:$E$860,$U42))) | J42: =IF($U42="","",INDEX('MiT Strom Pipeline'!$R$1:$R$860,$U42)) | K42: =IF($U42="","",IF(ISNUMBER(INDEX('MiT Strom Pipeline'!$S$1:$S$860,$U42)),INDEX('MiT Strom Pipeline'!$S$1:$S$860,$U42),"")) | L42: =IF($U42="","",IF(LEN(INDEX('MiT Strom Pipeline'!$V$1:$V$860,$U42))>0,LEFT(INDEX('MiT Strom Pipeline'!$V$1:$V$860,$U42),55),"")) | M42: =IF($U42="","",IF(INDEX('MiT Strom Pipeline'!$AF$1:$AF$860,$U42)="","",INDEX('MiT Strom Pipeline'!$AF$1:$AF$860,$U42))) | N42: =IF($U42="","",IF(INDEX('MiT Strom Pipeline'!$BB$1:$BB$860,$U42)="","",INDEX('MiT Strom Pipeline'!$BB$1:$BB$860,$U42))) | U42: =IFERROR(MATCH(32,'MiT Strom Pipeline'!$AM$6:$AM$860,0)+5,"")
A43: =IF($U43="","",IF(ISNUMBER(INDEX('MiT Strom Pipeline'!$A$1:$A$860,$U43)),INDEX('MiT Strom Pipeline'!$A$1:$A$860,$U43),"")) | B43: =IF($U43="","",IF(INDEX('MiT Strom Pipeline'!$B$1:$B$860,$U43)="","",INDEX('MiT Strom Pipeline'!$B$1:$B$860,$U43))) | C43: =IF($U43="","",IF(INDEX('MiT Strom Pipeline'!$C$1:$C$860,$U43)="","",INDEX('MiT Strom Pipeline'!$C$1:$C$860,$U43))) | D43: =IF($U43="","",IF(INDEX('MiT Strom Pipeline'!$D$1:$D$860,$U43)="","",INDEX('MiT Strom Pipeline'!$D$1:$D$860,$U43))) | E43: =IF($U43="","",IF(ISNUMBER(INDEX('MiT Strom Pipeline'!$O$1:$O$860,$U43)),INDEX('MiT Strom Pipeline'!$O$1:$O$860,$U43),IF(INDEX('MiT Strom Pipeline'!$H$1:$H$860,$U43)="","",INDEX('MiT Strom Pipeline'!$H$1:$H$860,$U43)))) | F43: =IF($U43="","",IF(ISNUMBER(INDEX('MiT Strom Pipeline'!$P$1:$P$860,$U43)),INDEX('MiT Strom Pipeline'!$P$1:$P$860,$U43),"")) | G43: =IF($U43="","",IF(ISNUMBER(INDEX('MiT Strom Pipeline'!$I$1:$I$860,$U43)),INDEX('MiT Strom Pipeline'!$I$1:$I$860,$U43),0)) | H43: =IF($U43="","",IF(ISNUMBER(INDEX('MiT Strom Pipeline'!$Q$1:$Q$860,$U43)),INDEX('MiT Strom Pipeline'!$Q$1:$Q$860,$U43),0)) | I43: =IF($U43="","",IF(INDEX('MiT Strom Pipeline'!$E$1:$E$860,$U43)="","",INDEX('MiT Strom Pipeline'!$E$1:$E$860,$U43))) | J43: =IF($U43="","",INDEX('MiT Strom Pipeline'!$R$1:$R$860,$U43)) | K43: =IF($U43="","",IF(ISNUMBER(INDEX('MiT Strom Pipeline'!$S$1:$S$860,$U43)),INDEX('MiT Strom Pipeline'!$S$1:$S$860,$U43),"")) | L43: =IF($U43="","",IF(LEN(INDEX('MiT Strom Pipeline'!$V$1:$V$860,$U43))>0,LEFT(INDEX('MiT Strom Pipeline'!$V$1:$V$860,$U43),55),"")) | M43: =IF($U43="","",IF(INDEX('MiT Strom Pipeline'!$AF$1:$AF$860,$U43)="","",INDEX('MiT Strom Pipeline'!$AF$1:$AF$860,$U43))) | N43: =IF($U43="","",IF(INDEX('MiT Strom Pipeline'!$BB$1:$BB$860,$U43)="","",INDEX('MiT Strom Pipeline'!$BB$1:$BB$860,$U43))) | U43: =IFERROR(MATCH(33,'MiT Strom Pipeline'!$AM$6:$AM$860,0)+5,"")
A44: =IF($U44="","",IF(ISNUMBER(INDEX('MiT Strom Pipeline'!$A$1:$A$860,$U44)),INDEX('MiT Strom Pipeline'!$A$1:$A$860,$U44),"")) | B44: =IF($U44="","",IF(INDEX('MiT Strom Pipeline'!$B$1:$B$860,$U44)="","",INDEX('MiT Strom Pipeline'!$B$1:$B$860,$U44))) | C44: =IF($U44="","",IF(INDEX('MiT Strom Pipeline'!$C$1:$C$860,$U44)="","",INDEX('MiT Strom Pipeline'!$C$1:$C$860,$U44))) | D44: =IF($U44="","",IF(INDEX('MiT Strom Pipeline'!$D$1:$D$860,$U44)="","",INDEX('MiT Strom Pipeline'!$D$1:$D$860,$U44))) | E44: =IF($U44="","",IF(ISNUMBER(INDEX('MiT Strom Pipeline'!$O$1:$O$860,$U44)),INDEX('MiT Strom Pipeline'!$O$1:$O$860,$U44),IF(INDEX('MiT Strom Pipeline'!$H$1:$H$860,$U44)="","",INDEX('MiT Strom Pipeline'!$H$1:$H$860,$U44)))) | F44: =IF($U44="","",IF(ISNUMBER(INDEX('MiT Strom Pipeline'!$P$1:$P$860,$U44)),INDEX('MiT Strom Pipeline'!$P$1:$P$860,$U44),"")) | G44: =IF($U44="","",IF(ISNUMBER(INDEX('MiT Strom Pipeline'!$I$1:$I$860,$U44)),INDEX('MiT Strom Pipeline'!$I$1:$I$860,$U44),0)) | H44: =IF($U44="","",IF(ISNUMBER(INDEX('MiT Strom Pipeline'!$Q$1:$Q$860,$U44)),INDEX('MiT Strom Pipeline'!$Q$1:$Q$860,$U44),0)) | I44: =IF($U44="","",IF(INDEX('MiT Strom Pipeline'!$E$1:$E$860,$U44)="","",INDEX('MiT Strom Pipeline'!$E$1:$E$860,$U44))) | J44: =IF($U44="","",INDEX('MiT Strom Pipeline'!$R$1:$R$860,$U44)) | K44: =IF($U44="","",IF(ISNUMBER(INDEX('MiT Strom Pipeline'!$S$1:$S$860,$U44)),INDEX('MiT Strom Pipeline'!$S$1:$S$860,$U44),"")) | L44: =IF($U44="","",IF(LEN(INDEX('MiT Strom Pipeline'!$V$1:$V$860,$U44))>0,LEFT(INDEX('MiT Strom Pipeline'!$V$1:$V$860,$U44),55),"")) | M44: =IF($U44="","",IF(INDEX('MiT Strom Pipeline'!$AF$1:$AF$860,$U44)="","",INDEX('MiT Strom Pipeline'!$AF$1:$AF$860,$U44))) | N44: =IF($U44="","",IF(INDEX('MiT Strom Pipeline'!$BB$1:$BB$860,$U44)="","",INDEX('MiT Strom Pipeline'!$BB$1:$BB$860,$U44))) | U44: =IFERROR(MATCH(34,'MiT Strom Pipeline'!$AM$6:$AM$860,0)+5,"")
A45: =IF($U45="","",IF(ISNUMBER(INDEX('MiT Strom Pipeline'!$A$1:$A$860,$U45)),INDEX('MiT Strom Pipeline'!$A$1:$A$860,$U45),"")) | B45: =IF($U45="","",IF(INDEX('MiT Strom Pipeline'!$B$1:$B$860,$U45)="","",INDEX('MiT Strom Pipeline'!$B$1:$B$860,$U45))) | C45: =IF($U45="","",IF(INDEX('MiT Strom Pipeline'!$C$1:$C$860,$U45)="","",INDEX('MiT Strom Pipeline'!$C$1:$C$860,$U45))) | D45: =IF($U45="","",IF(INDEX('MiT Strom Pipeline'!$D$1:$D$860,$U45)="","",INDEX('MiT Strom Pipeline'!$D$1:$D$860,$U45))) | E45: =IF($U45="","",IF(ISNUMBER(INDEX('MiT Strom Pipeline'!$O$1:$O$860,$U45)),INDEX('MiT Strom Pipeline'!$O$1:$O$860,$U45),IF(INDEX('MiT Strom Pipeline'!$H$1:$H$860,$U45)="","",INDEX('MiT Strom Pipeline'!$H$1:$H$860,$U45)))) | F45: =IF($U45="","",IF(ISNUMBER(INDEX('MiT Strom Pipeline'!$P$1:$P$860,$U45)),INDEX('MiT Strom Pipeline'!$P$1:$P$860,$U45),"")) | G45: =IF($U45="","",IF(ISNUMBER(INDEX('MiT Strom Pipeline'!$I$1:$I$860,$U45)),INDEX('MiT Strom Pipeline'!$I$1:$I$860,$U45),0)) | H45: =IF($U45="","",IF(ISNUMBER(INDEX('MiT Strom Pipeline'!$Q$1:$Q$860,$U45)),INDEX('MiT Strom Pipeline'!$Q$1:$Q$860,$U45),0)) | I45: =IF($U45="","",IF(INDEX('MiT Strom Pipeline'!$E$1:$E$860,$U45)="","",INDEX('MiT Strom Pipeline'!$E$1:$E$860,$U45))) | J45: =IF($U45="","",INDEX('MiT Strom Pipeline'!$R$1:$R$860,$U45)) | K45: =IF($U45="","",IF(ISNUMBER(INDEX('MiT Strom Pipeline'!$S$1:$S$860,$U45)),INDEX('MiT Strom Pipeline'!$S$1:$S$860,$U45),"")) | L45: =IF($U45="","",IF(LEN(INDEX('MiT Strom Pipeline'!$V$1:$V$860,$U45))>0,LEFT(INDEX('MiT Strom Pipeline'!$V$1:$V$860,$U45),55),"")) | M45: =IF($U45="","",IF(INDEX('MiT Strom Pipeline'!$AF$1:$AF$860,$U45)="","",INDEX('MiT Strom Pipeline'!$AF$1:$AF$860,$U45))) | N45: =IF($U45="","",IF(INDEX('MiT Strom Pipeline'!$BB$1:$BB$860,$U45)="","",INDEX('MiT Strom Pipeline'!$BB$1:$BB$860,$U45))) | U45: =IFERROR(MATCH(35,'MiT Strom Pipeline'!$AM$6:$AM$860,0)+5,"")
A46: =IF($U46="","",IF(ISNUMBER(INDEX('MiT Strom Pipeline'!$A$1:$A$860,$U46)),INDEX('MiT Strom Pipeline'!$A$1:$A$860,$U46),"")) | B46: =IF($U46="","",IF(INDEX('MiT Strom Pipeline'!$B$1:$B$860,$U46)="","",INDEX('MiT Strom Pipeline'!$B$1:$B$860,$U46))) | C46: =IF($U46="","",IF(INDEX('MiT Strom Pipeline'!$C$1:$C$860,$U46)="","",INDEX('MiT Strom Pipeline'!$C$1:$C$860,$U46))) | D46: =IF($U46="","",IF(INDEX('MiT Strom Pipeline'!$D$1:$D$860,$U46)="","",INDEX('MiT Strom Pipeline'!$D$1:$D$860,$U46))) | E46: =IF($U46="","",IF(ISNUMBER(INDEX('MiT Strom Pipeline'!$O$1:$O$860,$U46)),INDEX('MiT Strom Pipeline'!$O$1:$O$860,$U46),IF(INDEX('MiT Strom Pipeline'!$H$1:$H$860,$U46)="","",INDEX('MiT Strom Pipeline'!$H$1:$H$860,$U46)))) | F46: =IF($U46="","",IF(ISNUMBER(INDEX('MiT Strom Pipeline'!$P$1:$P$860,$U46)),INDEX('MiT Strom Pipeline'!$P$1:$P$860,$U46),"")) | G46: =IF($U46="","",IF(ISNUMBER(INDEX('MiT Strom Pipeline'!$I$1:$I$860,$U46)),INDEX('MiT Strom Pipeline'!$I$1:$I$860,$U46),0)) | H46: =IF($U46="","",IF(ISNUMBER(INDEX('MiT Strom Pipeline'!$Q$1:$Q$860,$U46)),INDEX('MiT Strom Pipeline'!$Q$1:$Q$860,$U46),0)) | I46: =IF($U46="","",IF(INDEX('MiT Strom Pipeline'!$E$1:$E$860,$U46)="","",INDEX('MiT Strom Pipeline'!$E$1:$E$860,$U46))) | J46: =IF($U46="","",INDEX('MiT Strom Pipeline'!$R$1:$R$860,$U46)) | K46: =IF($U46="","",IF(ISNUMBER(INDEX('MiT Strom Pipeline'!$S$1:$S$860,$U46)),INDEX('MiT Strom Pipeline'!$S$1:$S$860,$U46),"")) | L46: =IF($U46="","",IF(LEN(INDEX('MiT Strom Pipeline'!$V$1:$V$860,$U46))>0,LEFT(INDEX('MiT Strom Pipeline'!$V$1:$V$860,$U46),55),"")) | M46: =IF($U46="","",IF(INDEX('MiT Strom Pipeline'!$AF$1:$AF$860,$U46)="","",INDEX('MiT Strom Pipeline'!$AF$1:$AF$860,$U46))) | N46: =IF($U46="","",IF(INDEX('MiT Strom Pipeline'!$BB$1:$BB$860,$U46)="","",INDEX('MiT Strom Pipeline'!$BB$1:$BB$860,$U46))) | U46: =IFERROR(MATCH(36,'MiT Strom Pipeline'!$AM$6:$AM$860,0)+5,"")
A47: =IF($U47="","",IF(ISNUMBER(INDEX('MiT Strom Pipeline'!$A$1:$A$860,$U47)),INDEX('MiT Strom Pipeline'!$A$1:$A$860,$U47),"")) | B47: =IF($U47="","",IF(INDEX('MiT Strom Pipeline'!$B$1:$B$860,$U47)="","",INDEX('MiT Strom Pipeline'!$B$1:$B$860,$U47))) | C47: =IF($U47="","",IF(INDEX('MiT Strom Pipeline'!$C$1:$C$860,$U47)="","",INDEX('MiT Strom Pipeline'!$C$1:$C$860,$U47))) | D47: =IF($U47="","",IF(INDEX('MiT Strom Pipeline'!$D$1:$D$860,$U47)="","",INDEX('MiT Strom Pipeline'!$D$1:$D$860,$U47))) | E47: =IF($U47="","",IF(ISNUMBER(INDEX('MiT Strom Pipeline'!$O$1:$O$860,$U47)),INDEX('MiT Strom Pipeline'!$O$1:$O$860,$U47),IF(INDEX('MiT Strom Pipeline'!$H$1:$H$860,$U47)="","",INDEX('MiT Strom Pipeline'!$H$1:$H$860,$U47)))) | F47: =IF($U47="","",IF(ISNUMBER(INDEX('MiT Strom Pipeline'!$P$1:$P$860,$U47)),INDEX('MiT Strom Pipeline'!$P$1:$P$860,$U47),"")) | G47: =IF($U47="","",IF(ISNUMBER(INDEX('MiT Strom Pipeline'!$I$1:$I$860,$U47)),INDEX('MiT Strom Pipeline'!$I$1:$I$860,$U47),0)) | H47: =IF($U47="","",IF(ISNUMBER(INDEX('MiT Strom Pipeline'!$Q$1:$Q$860,$U47)),INDEX('MiT Strom Pipeline'!$Q$1:$Q$860,$U47),0)) | I47: =IF($U47="","",IF(INDEX('MiT Strom Pipeline'!$E$1:$E$860,$U47)="","",INDEX('MiT Strom Pipeline'!$E$1:$E$860,$U47))) | J47: =IF($U47="","",INDEX('MiT Strom Pipeline'!$R$1:$R$860,$U47)) | K47: =IF($U47="","",IF(ISNUMBER(INDEX('MiT Strom Pipeline'!$S$1:$S$860,$U47)),INDEX('MiT Strom Pipeline'!$S$1:$S$860,$U47),"")) | L47: =IF($U47="","",IF(LEN(INDEX('MiT Strom Pipeline'!$V$1:$V$860,$U47))>0,LEFT(INDEX('MiT Strom Pipeline'!$V$1:$V$860,$U47),55),"")) | M47: =IF($U47="","",IF(INDEX('MiT Strom Pipeline'!$AF$1:$AF$860,$U47)="","",INDEX('MiT Strom Pipeline'!$AF$1:$AF$860,$U47))) | N47: =IF($U47="","",IF(INDEX('MiT Strom Pipeline'!$BB$1:$BB$860,$U47)="","",INDEX('MiT Strom Pipeline'!$BB$1:$BB$860,$U47))) | U47: =IFERROR(MATCH(37,'MiT Strom Pipeline'!$AM$6:$AM$860,0)+5,"")
A48: =IF($U48="","",IF(ISNUMBER(INDEX('MiT Strom Pipeline'!$A$1:$A$860,$U48)),INDEX('MiT Strom Pipeline'!$A$1:$A$860,$U48),"")) | B48: =IF($U48="","",IF(INDEX('MiT Strom Pipeline'!$B$1:$B$860,$U48)="","",INDEX('MiT Strom Pipeline'!$B$1:$B$860,$U48))) | C48: =IF($U48="","",IF(INDEX('MiT Strom Pipeline'!$C$1:$C$860,$U48)="","",INDEX('MiT Strom Pipeline'!$C$1:$C$860,$U48))) | D48: =IF($U48="","",IF(INDEX('MiT Strom Pipeline'!$D$1:$D$860,$U48)="","",INDEX('MiT Strom Pipeline'!$D$1:$D$860,$U48))) | E48: =IF($U48="","",IF(ISNUMBER(INDEX('MiT Strom Pipeline'!$O$1:$O$860,$U48)),INDEX('MiT Strom Pipeline'!$O$1:$O$860,$U48),IF(INDEX('MiT Strom Pipeline'!$H$1:$H$860,$U48)="","",INDEX('MiT Strom Pipeline'!$H$1:$H$860,$U48)))) | F48: =IF($U48="","",IF(ISNUMBER(INDEX('MiT Strom Pipeline'!$P$1:$P$860,$U48)),INDEX('MiT Strom Pipeline'!$P$1:$P$860,$U48),"")) | G48: =IF($U48="","",IF(ISNUMBER(INDEX('MiT Strom Pipeline'!$I$1:$I$860,$U48)),INDEX('MiT Strom Pipeline'!$I$1:$I$860,$U48),0)) | H48: =IF($U48="","",IF(ISNUMBER(INDEX('MiT Strom Pipeline'!$Q$1:$Q$860,$U48)),INDEX('MiT Strom Pipeline'!$Q$1:$Q$860,$U48),0)) | I48: =IF($U48="","",IF(INDEX('MiT Strom Pipeline'!$E$1:$E$860,$U48)="","",INDEX('MiT Strom Pipeline'!$E$1:$E$860,$U48))) | J48: =IF($U48="","",INDEX('MiT Strom Pipeline'!$R$1:$R$860,$U48)) | K48: =IF($U48="","",IF(ISNUMBER(INDEX('MiT Strom Pipeline'!$S$1:$S$860,$U48)),INDEX('MiT Strom Pipeline'!$S$1:$S$860,$U48),"")) | L48: =IF($U48="","",IF(LEN(INDEX('MiT Strom Pipeline'!$V$1:$V$860,$U48))>0,LEFT(INDEX('MiT Strom Pipeline'!$V$1:$V$860,$U48),55),"")) | M48: =IF($U48="","",IF(INDEX('MiT Strom Pipeline'!$AF$1:$AF$860,$U48)="","",INDEX('MiT Strom Pipeline'!$AF$1:$AF$860,$U48))) | N48: =IF($U48="","",IF(INDEX('MiT Strom Pipeline'!$BB$1:$BB$860,$U48)="","",INDEX('MiT Strom Pipeline'!$BB$1:$BB$860,$U48))) | U48: =IFERROR(MATCH(38,'MiT Strom Pipeline'!$AM$6:$AM$860,0)+5,"")
A49: =IF($U49="","",IF(ISNUMBER(INDEX('MiT Strom Pipeline'!$A$1:$A$860,$U49)),INDEX('MiT Strom Pipeline'!$A$1:$A$860,$U49),"")) | B49: =IF($U49="","",IF(INDEX('MiT Strom Pipeline'!$B$1:$B$860,$U49)="","",INDEX('MiT Strom Pipeline'!$B$1:$B$860,$U49))) | C49: =IF($U49="","",IF(INDEX('MiT Strom Pipeline'!$C$1:$C$860,$U49)="","",INDEX('MiT Strom Pipeline'!$C$1:$C$860,$U49))) | D49: =IF($U49="","",IF(INDEX('MiT Strom Pipeline'!$D$1:$D$860,$U49)="","",INDEX('MiT Strom Pipeline'!$D$1:$D$860,$U49))) | E49: =IF($U49="","",IF(ISNUMBER(INDEX('MiT Strom Pipeline'!$O$1:$O$860,$U49)),INDEX('MiT Strom Pipeline'!$O$1:$O$860,$U49),IF(INDEX('MiT Strom Pipeline'!$H$1:$H$860,$U49)="","",INDEX('MiT Strom Pipeline'!$H$1:$H$860,$U49)))) | F49: =IF($U49="","",IF(ISNUMBER(INDEX('MiT Strom Pipeline'!$P$1:$P$860,$U49)),INDEX('MiT Strom Pipeline'!$P$1:$P$860,$U49),"")) | G49: =IF($U49="","",IF(ISNUMBER(INDEX('MiT Strom Pipeline'!$I$1:$I$860,$U49)),INDEX('MiT Strom Pipeline'!$I$1:$I$860,$U49),0)) | H49: =IF($U49="","",IF(ISNUMBER(INDEX('MiT Strom Pipeline'!$Q$1:$Q$860,$U49)),INDEX('MiT Strom Pipeline'!$Q$1:$Q$860,$U49),0)) | I49: =IF($U49="","",IF(INDEX('MiT Strom Pipeline'!$E$1:$E$860,$U49)="","",INDEX('MiT Strom Pipeline'!$E$1:$E$860,$U49))) | J49: =IF($U49="","",INDEX('MiT Strom Pipeline'!$R$1:$R$860,$U49)) | K49: =IF($U49="","",IF(ISNUMBER(INDEX('MiT Strom Pipeline'!$S$1:$S$860,$U49)),INDEX('MiT Strom Pipeline'!$S$1:$S$860,$U49),"")) | L49: =IF($U49="","",IF(LEN(INDEX('MiT Strom Pipeline'!$V$1:$V$860,$U49))>0,LEFT(INDEX('MiT Strom Pipeline'!$V$1:$V$860,$U49),55),"")) | M49: =IF($U49="","",IF(INDEX('MiT Strom Pipeline'!$AF$1:$AF$860,$U49)="","",INDEX('MiT Strom Pipeline'!$AF$1:$AF$860,$U49))) | N49: =IF($U49="","",IF(INDEX('MiT Strom Pipeline'!$BB$1:$BB$860,$U49)="","",INDEX('MiT Strom Pipeline'!$BB$1:$BB$860,$U49))) | U49: =IFERROR(MATCH(39,'MiT Strom Pipeline'!$AM$6:$AM$860,0)+5,"")
A50: =IF($U50="","",IF(ISNUMBER(INDEX('MiT Strom Pipeline'!$A$1:$A$860,$U50)),INDEX('MiT Strom Pipeline'!$A$1:$A$860,$U50),"")) | B50: =IF($U50="","",IF(INDEX('MiT Strom Pipeline'!$B$1:$B$860,$U50)="","",INDEX('MiT Strom Pipeline'!$B$1:$B$860,$U50))) | C50: =IF($U50="","",IF(INDEX('MiT Strom Pipeline'!$C$1:$C$860,$U50)="","",INDEX('MiT Strom Pipeline'!$C$1:$C$860,$U50))) | D50: =IF($U50="","",IF(INDEX('MiT Strom Pipeline'!$D$1:$D$860,$U50)="","",INDEX('MiT Strom Pipeline'!$D$1:$D$860,$U50))) | E50: =IF($U50="","",IF(ISNUMBER(INDEX('MiT Strom Pipeline'!$O$1:$O$860,$U50)),INDEX('MiT Strom Pipeline'!$O$1:$O$860,$U50),IF(INDEX('MiT Strom Pipeline'!$H$1:$H$860,$U50)="","",INDEX('MiT Strom Pipeline'!$H$1:$H$860,$U50)))) | F50: =IF($U50="","",IF(ISNUMBER(INDEX('MiT Strom Pipeline'!$P$1:$P$860,$U50)),INDEX('MiT Strom Pipeline'!$P$1:$P$860,$U50),"")) | G50: =IF($U50="","",IF(ISNUMBER(INDEX('MiT Strom Pipeline'!$I$1:$I$860,$U50)),INDEX('MiT Strom Pipeline'!$I$1:$I$860,$U50),0)) | H50: =IF($U50="","",IF(ISNUMBER(INDEX('MiT Strom Pipeline'!$Q$1:$Q$860,$U50)),INDEX('MiT Strom Pipeline'!$Q$1:$Q$860,$U50),0)) | I50: =IF($U50="","",IF(INDEX('MiT Strom Pipeline'!$E$1:$E$860,$U50)="","",INDEX('MiT Strom Pipeline'!$E$1:$E$860,$U50))) | J50: =IF($U50="","",INDEX('MiT Strom Pipeline'!$R$1:$R$860,$U50)) | K50: =IF($U50="","",IF(ISNUMBER(INDEX('MiT Strom Pipeline'!$S$1:$S$860,$U50)),INDEX('MiT Strom Pipeline'!$S$1:$S$860,$U50),"")) | L50: =IF($U50="","",IF(LEN(INDEX('MiT Strom Pipeline'!$V$1:$V$860,$U50))>0,LEFT(INDEX('MiT Strom Pipeline'!$V$1:$V$860,$U50),55),"")) | M50: =IF($U50="","",IF(INDEX('MiT Strom Pipeline'!$AF$1:$AF$860,$U50)="","",INDEX('MiT Strom Pipeline'!$AF$1:$AF$860,$U50))) | N50: =IF($U50="","",IF(INDEX('MiT Strom Pipeline'!$BB$1:$BB$860,$U50)="","",INDEX('MiT Strom Pipeline'!$BB$1:$BB$860,$U50))) | U50: =IFERROR(MATCH(40,'MiT Strom Pipeline'!$AM$6:$AM$860,0)+5,"")
A51: =IF($U51="","",IF(ISNUMBER(INDEX('MiT Strom Pipeline'!$A$1:$A$860,$U51)),INDEX('MiT Strom Pipeline'!$A$1:$A$860,$U51),"")) | B51: =IF($U51="","",IF(INDEX('MiT Strom Pipeline'!$B$1:$B$860,$U51)="","",INDEX('MiT Strom Pipeline'!$B$1:$B$860,$U51))) | C51: =IF($U51="","",IF(INDEX('MiT Strom Pipeline'!$C$1:$C$860,$U51)="","",INDEX('MiT Strom Pipeline'!$C$1:$C$860,$U51))) | D51: =IF($U51="","",IF(INDEX('MiT Strom Pipeline'!$D$1:$D$860,$U51)="","",INDEX('MiT Strom Pipeline'!$D$1:$D$860,$U51))) | E51: =IF($U51="","",IF(ISNUMBER(INDEX('MiT Strom Pipeline'!$O$1:$O$860,$U51)),INDEX('MiT Strom Pipeline'!$O$1:$O$860,$U51),IF(INDEX('MiT Strom Pipeline'!$H$1:$H$860,$U51)="","",INDEX('MiT Strom Pipeline'!$H$1:$H$860,$U51)))) | F51: =IF($U51="","",IF(ISNUMBER(INDEX('MiT Strom Pipeline'!$P$1:$P$860,$U51)),INDEX('MiT Strom Pipeline'!$P$1:$P$860,$U51),"")) | G51: =IF($U51="","",IF(ISNUMBER(INDEX('MiT Strom Pipeline'!$I$1:$I$860,$U51)),INDEX('MiT Strom Pipeline'!$I$1:$I$860,$U51),0)) | H51: =IF($U51="","",IF(ISNUMBER(INDEX('MiT Strom Pipeline'!$Q$1:$Q$860,$U51)),INDEX('MiT Strom Pipeline'!$Q$1:$Q$860,$U51),0)) | I51: =IF($U51="","",IF(INDEX('MiT Strom Pipeline'!$E$1:$E$860,$U51)="","",INDEX('MiT Strom Pipeline'!$E$1:$E$860,$U51))) | J51: =IF($U51="","",INDEX('MiT Strom Pipeline'!$R$1:$R$860,$U51)) | K51: =IF($U51="","",IF(ISNUMBER(INDEX('MiT Strom Pipeline'!$S$1:$S$860,$U51)),INDEX('MiT Strom Pipeline'!$S$1:$S$860,$U51),"")) | L51: =IF($U51="","",IF(LEN(INDEX('MiT Strom Pipeline'!$V$1:$V$860,$U51))>0,LEFT(INDEX('MiT Strom Pipeline'!$V$1:$V$860,$U51),55),"")) | M51: =IF($U51="","",IF(INDEX('MiT Strom Pipeline'!$AF$1:$AF$860,$U51)="","",INDEX('MiT Strom Pipeline'!$AF$1:$AF$860,$U51))) | N51: =IF($U51="","",IF(INDEX('MiT Strom Pipeline'!$BB$1:$BB$860,$U51)="","",INDEX('MiT Strom Pipeline'!$BB$1:$BB$860,$U51))) | U51: =IFERROR(MATCH(41,'MiT Strom Pipeline'!$AM$6:$AM$860,0)+5,"")
A52: =IF($U52="","",IF(ISNUMBER(INDEX('MiT Strom Pipeline'!$A$1:$A$860,$U52)),INDEX('MiT Strom Pipeline'!$A$1:$A$860,$U52),"")) | B52: =IF($U52="","",IF(INDEX('MiT Strom Pipeline'!$B$1:$B$860,$U52)="","",INDEX('MiT Strom Pipeline'!$B$1:$B$860,$U52))) | C52: =IF($U52="","",IF(INDEX('MiT Strom Pipeline'!$C$1:$C$860,$U52)="","",INDEX('MiT Strom Pipeline'!$C$1:$C$860,$U52))) | D52: =IF($U52="","",IF(INDEX('MiT Strom Pipeline'!$D$1:$D$860,$U52)="","",INDEX('MiT Strom Pipeline'!$D$1:$D$860,$U52))) | E52: =IF($U52="","",IF(ISNUMBER(INDEX('MiT Strom Pipeline'!$O$1:$O$860,$U52)),INDEX('MiT Strom Pipeline'!$O$1:$O$860,$U52),IF(INDEX('MiT Strom Pipeline'!$H$1:$H$860,$U52)="","",INDEX('MiT Strom Pipeline'!$H$1:$H$860,$U52)))) | F52: =IF($U52="","",IF(ISNUMBER(INDEX('MiT Strom Pipeline'!$P$1:$P$860,$U52)),INDEX('MiT Strom Pipeline'!$P$1:$P$860,$U52),"")) | G52: =IF($U52="","",IF(ISNUMBER(INDEX('MiT Strom Pipeline'!$I$1:$I$860,$U52)),INDEX('MiT Strom Pipeline'!$I$1:$I$860,$U52),0)) | H52: =IF($U52="","",IF(ISNUMBER(INDEX('MiT Strom Pipeline'!$Q$1:$Q$860,$U52)),INDEX('MiT Strom Pipeline'!$Q$1:$Q$860,$U52),0)) | I52: =IF($U52="","",IF(INDEX('MiT Strom Pipeline'!$E$1:$E$860,$U52)="","",INDEX('MiT Strom Pipeline'!$E$1:$E$860,$U52))) | J52: =IF($U52="","",INDEX('MiT Strom Pipeline'!$R$1:$R$860,$U52)) | K52: =IF($U52="","",IF(ISNUMBER(INDEX('MiT Strom Pipeline'!$S$1:$S$860,$U52)),INDEX('MiT Strom Pipeline'!$S$1:$S$860,$U52),"")) | L52: =IF($U52="","",IF(LEN(INDEX('MiT Strom Pipeline'!$V$1:$V$860,$U52))>0,LEFT(INDEX('MiT Strom Pipeline'!$V$1:$V$860,$U52),55),"")) | M52: =IF($U52="","",IF(INDEX('MiT Strom Pipeline'!$AF$1:$AF$860,$U52)="","",INDEX('MiT Strom Pipeline'!$AF$1:$AF$860,$U52))) | N52: =IF($U52="","",IF(INDEX('MiT Strom Pipeline'!$BB$1:$BB$860,$U52)="","",INDEX('MiT Strom Pipeline'!$BB$1:$BB$860,$U52))) | U52: =IFERROR(MATCH(42,'MiT Strom Pipeline'!$AM$6:$AM$860,0)+5,"")
A53: =IF($U53="","",IF(ISNUMBER(INDEX('MiT Strom Pipeline'!$A$1:$A$860,$U53)),INDEX('MiT Strom Pipeline'!$A$1:$A$860,$U53),"")) | B53: =IF($U53="","",IF(INDEX('MiT Strom Pipeline'!$B$1:$B$860,$U53)="","",INDEX('MiT Strom Pipeline'!$B$1:$B$860,$U53))) | C53: =IF($U53="","",IF(INDEX('MiT Strom Pipeline'!$C$1:$C$860,$U53)="","",INDEX('MiT Strom Pipeline'!$C$1:$C$860,$U53))) | D53: =IF($U53="","",IF(INDEX('MiT Strom Pipeline'!$D$1:$D$860,$U53)="","",INDEX('MiT Strom Pipeline'!$D$1:$D$860,$U53))) | E53: =IF($U53="","",IF(ISNUMBER(INDEX('MiT Strom Pipeline'!$O$1:$O$860,$U53)),INDEX('MiT Strom Pipeline'!$O$1:$O$860,$U53),IF(INDEX('MiT Strom Pipeline'!$H$1:$H$860,$U53)="","",INDEX('MiT Strom Pipeline'!$H$1:$H$860,$U53)))) | F53: =IF($U53="","",IF(ISNUMBER(INDEX('MiT Strom Pipeline'!$P$1:$P$860,$U53)),INDEX('MiT Strom Pipeline'!$P$1:$P$860,$U53),"")) | G53: =IF($U53="","",IF(ISNUMBER(INDEX('MiT Strom Pipeline'!$I$1:$I$860,$U53)),INDEX('MiT Strom Pipeline'!$I$1:$I$860,$U53),0)) | H53: =IF($U53="","",IF(ISNUMBER(INDEX('MiT Strom Pipeline'!$Q$1:$Q$860,$U53)),INDEX('MiT Strom Pipeline'!$Q$1:$Q$860,$U53),0)) | I53: =IF($U53="","",IF(INDEX('MiT Strom Pipeline'!$E$1:$E$860,$U53)="","",INDEX('MiT Strom Pipeline'!$E$1:$E$860,$U53))) | J53: =IF($U53="","",INDEX('MiT Strom Pipeline'!$R$1:$R$860,$U53)) | K53: =IF($U53="","",IF(ISNUMBER(INDEX('MiT Strom Pipeline'!$S$1:$S$860,$U53)),INDEX('MiT Strom Pipeline'!$S$1:$S$860,$U53),"")) | L53: =IF($U53="","",IF(LEN(INDEX('MiT Strom Pipeline'!$V$1:$V$860,$U53))>0,LEFT(INDEX('MiT Strom Pipeline'!$V$1:$V$860,$U53),55),"")) | M53: =IF($U53="","",IF(INDEX('MiT Strom Pipeline'!$AF$1:$AF$860,$U53)="","",INDEX('MiT Strom Pipeline'!$AF$1:$AF$860,$U53))) | N53: =IF($U53="","",IF(INDEX('MiT Strom Pipeline'!$BB$1:$BB$860,$U53)="","",INDEX('MiT Strom Pipeline'!$BB$1:$BB$860,$U53))) | U53: =IFERROR(MATCH(43,'MiT Strom Pipeline'!$AM$6:$AM$860,0)+5,"")
A54: =IF($U54="","",IF(ISNUMBER(INDEX('MiT Strom Pipeline'!$A$1:$A$860,$U54)),INDEX('MiT Strom Pipeline'!$A$1:$A$860,$U54),"")) | B54: =IF($U54="","",IF(INDEX('MiT Strom Pipeline'!$B$1:$B$860,$U54)="","",INDEX('MiT Strom Pipeline'!$B$1:$B$860,$U54))) | C54: =IF($U54="","",IF(INDEX('MiT Strom Pipeline'!$C$1:$C$860,$U54)="","",INDEX('MiT Strom Pipeline'!$C$1:$C$860,$U54))) | D54: =IF($U54="","",IF(INDEX('MiT Strom Pipeline'!$D$1:$D$860,$U54)="","",INDEX('MiT Strom Pipeline'!$D$1:$D$860,$U54))) | E54: =IF($U54="","",IF(ISNUMBER(INDEX('MiT Strom Pipeline'!$O$1:$O$860,$U54)),INDEX('MiT Strom Pipeline'!$O$1:$O$860,$U54),IF(INDEX('MiT Strom Pipeline'!$H$1:$H$860,$U54)="","",INDEX('MiT Strom Pipeline'!$H$1:$H$860,$U54)))) | F54: =IF($U54="","",IF(ISNUMBER(INDEX('MiT Strom Pipeline'!$P$1:$P$860,$U54)),INDEX('MiT Strom Pipeline'!$P$1:$P$860,$U54),"")) | G54: =IF($U54="","",IF(ISNUMBER(INDEX('MiT Strom Pipeline'!$I$1:$I$860,$U54)),INDEX('MiT Strom Pipeline'!$I$1:$I$860,$U54),0)) | H54: =IF($U54="","",IF(ISNUMBER(INDEX('MiT Strom Pipeline'!$Q$1:$Q$860,$U54)),INDEX('MiT Strom Pipeline'!$Q$1:$Q$860,$U54),0)) | I54: =IF($U54="","",IF(INDEX('MiT Strom Pipeline'!$E$1:$E$860,$U54)="","",INDEX('MiT Strom Pipeline'!$E$1:$E$860,$U54))) | J54: =IF($U54="","",INDEX('MiT Strom Pipeline'!$R$1:$R$860,$U54)) | K54: =IF($U54="","",IF(ISNUMBER(INDEX('MiT Strom Pipeline'!$S$1:$S$860,$U54)),INDEX('MiT Strom Pipeline'!$S$1:$S$860,$U54),"")) | L54: =IF($U54="","",IF(LEN(INDEX('MiT Strom Pipeline'!$V$1:$V$860,$U54))>0,LEFT(INDEX('MiT Strom Pipeline'!$V$1:$V$860,$U54),55),"")) | M54: =IF($U54="","",IF(INDEX('MiT Strom Pipeline'!$AF$1:$AF$860,$U54)="","",INDEX('MiT Strom Pipeline'!$AF$1:$AF$860,$U54))) | N54: =IF($U54="","",IF(INDEX('MiT Strom Pipeline'!$BB$1:$BB$860,$U54)="","",INDEX('MiT Strom Pipeline'!$BB$1:$BB$860,$U54))) | U54: =IFERROR(MATCH(44,'MiT Strom Pipeline'!$AM$6:$AM$860,0)+5,"")
A55: =IF($U55="","",IF(ISNUMBER(INDEX('MiT Strom Pipeline'!$A$1:$A$860,$U55)),INDEX('MiT Strom Pipeline'!$A$1:$A$860,$U55),"")) | B55: =IF($U55="","",IF(INDEX('MiT Strom Pipeline'!$B$1:$B$860,$U55)="","",INDEX('MiT Strom Pipeline'!$B$1:$B$860,$U55))) | C55: =IF($U55="","",IF(INDEX('MiT Strom Pipeline'!$C$1:$C$860,$U55)="","",INDEX('MiT Strom Pipeline'!$C$1:$C$860,$U55))) | D55: =IF($U55="","",IF(INDEX('MiT Strom Pipeline'!$D$1:$D$860,$U55)="","",INDEX('MiT Strom Pipeline'!$D$1:$D$860,$U55))) | E55: =IF($U55="","",IF(ISNUMBER(INDEX('MiT Strom Pipeline'!$O$1:$O$860,$U55)),INDEX('MiT Strom Pipeline'!$O$1:$O$860,$U55),IF(INDEX('MiT Strom Pipeline'!$H$1:$H$860,$U55)="","",INDEX('MiT Strom Pipeline'!$H$1:$H$860,$U55)))) | F55: =IF($U55="","",IF(ISNUMBER(INDEX('MiT Strom Pipeline'!$P$1:$P$860,$U55)),INDEX('MiT Strom Pipeline'!$P$1:$P$860,$U55),"")) | G55: =IF($U55="","",IF(ISNUMBER(INDEX('MiT Strom Pipeline'!$I$1:$I$860,$U55)),INDEX('MiT Strom Pipeline'!$I$1:$I$860,$U55),0)) | H55: =IF($U55="","",IF(ISNUMBER(INDEX('MiT Strom Pipeline'!$Q$1:$Q$860,$U55)),INDEX('MiT Strom Pipeline'!$Q$1:$Q$860,$U55),0)) | I55: =IF($U55="","",IF(INDEX('MiT Strom Pipeline'!$E$1:$E$860,$U55)="","",INDEX('MiT Strom Pipeline'!$E$1:$E$860,$U55))) | J55: =IF($U55="","",INDEX('MiT Strom Pipeline'!$R$1:$R$860,$U55)) | K55: =IF($U55="","",IF(ISNUMBER(INDEX('MiT Strom Pipeline'!$S$1:$S$860,$U55)),INDEX('MiT Strom Pipeline'!$S$1:$S$860,$U55),"")) | L55: =IF($U55="","",IF(LEN(INDEX('MiT Strom Pipeline'!$V$1:$V$860,$U55))>0,LEFT(INDEX('MiT Strom Pipeline'!$V$1:$V$860,$U55),55),"")) | M55: =IF($U55="","",IF(INDEX('MiT Strom Pipeline'!$AF$1:$AF$860,$U55)="","",INDEX('MiT Strom Pipeline'!$AF$1:$AF$860,$U55))) | N55: =IF($U55="","",IF(INDEX('MiT Strom Pipeline'!$BB$1:$BB$860,$U55)="","",INDEX('MiT Strom Pipeline'!$BB$1:$BB$860,$U55))) | U55: =IFERROR(MATCH(45,'MiT Strom Pipeline'!$AM$6:$AM$860,0)+5,"")
A56: =IF($U56="","",IF(ISNUMBER(INDEX('MiT Strom Pipeline'!$A$1:$A$860,$U56)),INDEX('MiT Strom Pipeline'!$A$1:$A$860,$U56),"")) | B56: =IF($U56="","",IF(INDEX('MiT Strom Pipeline'!$B$1:$B$860,$U56)="","",INDEX('MiT Strom Pipeline'!$B$1:$B$860,$U56))) | C56: =IF($U56="","",IF(INDEX('MiT Strom Pipeline'!$C$1:$C$860,$U56)="","",INDEX('MiT Strom Pipeline'!$C$1:$C$860,$U56))) | D56: =IF($U56="","",IF(INDEX('MiT Strom Pipeline'!$D$1:$D$860,$U56)="","",INDEX('MiT Strom Pipeline'!$D$1:$D$860,$U56))) | E56: =IF($U56="","",IF(ISNUMBER(INDEX('MiT Strom Pipeline'!$O$1:$O$860,$U56)),INDEX('MiT Strom Pipeline'!$O$1:$O$860,$U56),IF(INDEX('MiT Strom Pipeline'!$H$1:$H$860,$U56)="","",INDEX('MiT Strom Pipeline'!$H$1:$H$860,$U56)))) | F56: =IF($U56="","",IF(ISNUMBER(INDEX('MiT Strom Pipeline'!$P$1:$P$860,$U56)),INDEX('MiT Strom Pipeline'!$P$1:$P$860,$U56),"")) | G56: =IF($U56="","",IF(ISNUMBER(INDEX('MiT Strom Pipeline'!$I$1:$I$860,$U56)),INDEX('MiT Strom Pipeline'!$I$1:$I$860,$U56),0)) | H56: =IF($U56="","",IF(ISNUMBER(INDEX('MiT Strom Pipeline'!$Q$1:$Q$860,$U56)),INDEX('MiT Strom Pipeline'!$Q$1:$Q$860,$U56),0)) | I56: =IF($U56="","",IF(INDEX('MiT Strom Pipeline'!$E$1:$E$860,$U56)="","",INDEX('MiT Strom Pipeline'!$E$1:$E$860,$U56))) | J56: =IF($U56="","",INDEX('MiT Strom Pipeline'!$R$1:$R$860,$U56)) | K56: =IF($U56="","",IF(ISNUMBER(INDEX('MiT Strom Pipeline'!$S$1:$S$860,$U56)),INDEX('MiT Strom Pipeline'!$S$1:$S$860,$U56),"")) | L56: =IF($U56="","",IF(LEN(INDEX('MiT Strom Pipeline'!$V$1:$V$860,$U56))>0,LEFT(INDEX('MiT Strom Pipeline'!$V$1:$V$860,$U56),55),"")) | M56: =IF($U56="","",IF(INDEX('MiT Strom Pipeline'!$AF$1:$AF$860,$U56)="","",INDEX('MiT Strom Pipeline'!$AF$1:$AF$860,$U56))) | N56: =IF($U56="","",IF(INDEX('MiT Strom Pipeline'!$BB$1:$BB$860,$U56)="","",INDEX('MiT Strom Pipeline'!$BB$1:$BB$860,$U56))) | U56: =IFERROR(MATCH(46,'MiT Strom Pipeline'!$AM$6:$AM$860,0)+5,"")
A57: =IF($U57="","",IF(ISNUMBER(INDEX('MiT Strom Pipeline'!$A$1:$A$860,$U57)),INDEX('MiT Strom Pipeline'!$A$1:$A$860,$U57),"")) | B57: =IF($U57="","",IF(INDEX('MiT Strom Pipeline'!$B$1:$B$860,$U57)="","",INDEX('MiT Strom Pipeline'!$B$1:$B$860,$U57))) | C57: =IF($U57="","",IF(INDEX('MiT Strom Pipeline'!$C$1:$C$860,$U57)="","",INDEX('MiT Strom Pipeline'!$C$1:$C$860,$U57))) | D57: =IF($U57="","",IF(INDEX('MiT Strom Pipeline'!$D$1:$D$860,$U57)="","",INDEX('MiT Strom Pipeline'!$D$1:$D$860,$U57))) | E57: =IF($U57="","",IF(ISNUMBER(INDEX('MiT Strom Pipeline'!$O$1:$O$860,$U57)),INDEX('MiT Strom Pipeline'!$O$1:$O$860,$U57),IF(INDEX('MiT Strom Pipeline'!$H$1:$H$860,$U57)="","",INDEX('MiT Strom Pipeline'!$H$1:$H$860,$U57)))) | F57: =IF($U57="","",IF(ISNUMBER(INDEX('MiT Strom Pipeline'!$P$1:$P$860,$U57)),INDEX('MiT Strom Pipeline'!$P$1:$P$860,$U57),"")) | G57: =IF($U57="","",IF(ISNUMBER(INDEX('MiT Strom Pipeline'!$I$1:$I$860,$U57)),INDEX('MiT Strom Pipeline'!$I$1:$I$860,$U57),0)) | H57: =IF($U57="","",IF(ISNUMBER(INDEX('MiT Strom Pipeline'!$Q$1:$Q$860,$U57)),INDEX('MiT Strom Pipeline'!$Q$1:$Q$860,$U57),0)) | I57: =IF($U57="","",IF(INDEX('MiT Strom Pipeline'!$E$1:$E$860,$U57)="","",INDEX('MiT Strom Pipeline'!$E$1:$E$860,$U57))) | J57: =IF($U57="","",INDEX('MiT Strom Pipeline'!$R$1:$R$860,$U57)) | K57: =IF($U57="","",IF(ISNUMBER(INDEX('MiT Strom Pipeline'!$S$1:$S$860,$U57)),INDEX('MiT Strom Pipeline'!$S$1:$S$860,$U57),"")) | L57: =IF($U57="","",IF(LEN(INDEX('MiT Strom Pipeline'!$V$1:$V$860,$U57))>0,LEFT(INDEX('MiT Strom Pipeline'!$V$1:$V$860,$U57),55),"")) | M57: =IF($U57="","",IF(INDEX('MiT Strom Pipeline'!$AF$1:$AF$860,$U57)="","",INDEX('MiT Strom Pipeline'!$AF$1:$AF$860,$U57))) | N57: =IF($U57="","",IF(INDEX('MiT Strom Pipeline'!$BB$1:$BB$860,$U57)="","",INDEX('MiT Strom Pipeline'!$BB$1:$BB$860,$U57))) | U57: =IFERROR(MATCH(47,'MiT Strom Pipeline'!$AM$6:$AM$860,0)+5,"")
A58: =IF($U58="","",IF(ISNUMBER(INDEX('MiT Strom Pipeline'!$A$1:$A$860,$U58)),INDEX('MiT Strom Pipeline'!$A$1:$A$860,$U58),"")) | B58: =IF($U58="","",IF(INDEX('MiT Strom Pipeline'!$B$1:$B$860,$U58)="","",INDEX('MiT Strom Pipeline'!$B$1:$B$860,$U58))) | C58: =IF($U58="","",IF(INDEX('MiT Strom Pipeline'!$C$1:$C$860,$U58)="","",INDEX('MiT Strom Pipeline'!$C$1:$C$860,$U58))) | D58: =IF($U58="","",IF(INDEX('MiT Strom Pipeline'!$D$1:$D$860,$U58)="","",INDEX('MiT Strom Pipeline'!$D$1:$D$860,$U58))) | E58: =IF($U58="","",IF(ISNUMBER(INDEX('MiT Strom Pipeline'!$O$1:$O$860,$U58)),INDEX('MiT Strom Pipeline'!$O$1:$O$860,$U58),IF(INDEX('MiT Strom Pipeline'!$H$1:$H$860,$U58)="","",INDEX('MiT Strom Pipeline'!$H$1:$H$860,$U58)))) | F58: =IF($U58="","",IF(ISNUMBER(INDEX('MiT Strom Pipeline'!$P$1:$P$860,$U58)),INDEX('MiT Strom Pipeline'!$P$1:$P$860,$U58),"")) | G58: =IF($U58="","",IF(ISNUMBER(INDEX('MiT Strom Pipeline'!$I$1:$I$860,$U58)),INDEX('MiT Strom Pipeline'!$I$1:$I$860,$U58),0)) | H58: =IF($U58="","",IF(ISNUMBER(INDEX('MiT Strom Pipeline'!$Q$1:$Q$860,$U58)),INDEX('MiT Strom Pipeline'!$Q$1:$Q$860,$U58),0)) | I58: =IF($U58="","",IF(INDEX('MiT Strom Pipeline'!$E$1:$E$860,$U58)="","",INDEX('MiT Strom Pipeline'!$E$1:$E$860,$U58))) | J58: =IF($U58="","",INDEX('MiT Strom Pipeline'!$R$1:$R$860,$U58)) | K58: =IF($U58="","",IF(ISNUMBER(INDEX('MiT Strom Pipeline'!$S$1:$S$860,$U58)),INDEX('MiT Strom Pipeline'!$S$1:$S$860,$U58),"")) | L58: =IF($U58="","",IF(LEN(INDEX('MiT Strom Pipeline'!$V$1:$V$860,$U58))>0,LEFT(INDEX('MiT Strom Pipeline'!$V$1:$V$860,$U58),55),"")) | M58: =IF($U58="","",IF(INDEX('MiT Strom Pipeline'!$AF$1:$AF$860,$U58)="","",INDEX('MiT Strom Pipeline'!$AF$1:$AF$860,$U58))) | N58: =IF($U58="","",IF(INDEX('MiT Strom Pipeline'!$BB$1:$BB$860,$U58)="","",INDEX('MiT Strom Pipeline'!$BB$1:$BB$860,$U58))) | U58: =IFERROR(MATCH(48,'MiT Strom Pipeline'!$AM$6:$AM$860,0)+5,"")
A59: =IF($U59="","",IF(ISNUMBER(INDEX('MiT Strom Pipeline'!$A$1:$A$860,$U59)),INDEX('MiT Strom Pipeline'!$A$1:$A$860,$U59),"")) | B59: =IF($U59="","",IF(INDEX('MiT Strom Pipeline'!$B$1:$B$860,$U59)="","",INDEX('MiT Strom Pipeline'!$B$1:$B$860,$U59))) | C59: =IF($U59="","",IF(INDEX('MiT Strom Pipeline'!$C$1:$C$860,$U59)="","",INDEX('MiT Strom Pipeline'!$C$1:$C$860,$U59))) | D59: =IF($U59="","",IF(INDEX('MiT Strom Pipeline'!$D$1:$D$860,$U59)="","",INDEX('MiT Strom Pipeline'!$D$1:$D$860,$U59))) | E59: =IF($U59="","",IF(ISNUMBER(INDEX('MiT Strom Pipeline'!$O$1:$O$860,$U59)),INDEX('MiT Strom Pipeline'!$O$1:$O$860,$U59),IF(INDEX('MiT Strom Pipeline'!$H$1:$H$860,$U59)="","",INDEX('MiT Strom Pipeline'!$H$1:$H$860,$U59)))) | F59: =IF($U59="","",IF(ISNUMBER(INDEX('MiT Strom Pipeline'!$P$1:$P$860,$U59)),INDEX('MiT Strom Pipeline'!$P$1:$P$860,$U59),"")) | G59: =IF($U59="","",IF(ISNUMBER(INDEX('MiT Strom Pipeline'!$I$1:$I$860,$U59)),INDEX('MiT Strom Pipeline'!$I$1:$I$860,$U59),0)) | H59: =IF($U59="","",IF(ISNUMBER(INDEX('MiT Strom Pipeline'!$Q$1:$Q$860,$U59)),INDEX('MiT Strom Pipeline'!$Q$1:$Q$860,$U59),0)) | I59: =IF($U59="","",IF(INDEX('MiT Strom Pipeline'!$E$1:$E$860,$U59)="","",INDEX('MiT Strom Pipeline'!$E$1:$E$860,$U59))) | J59: =IF($U59="","",INDEX('MiT Strom Pipeline'!$R$1:$R$860,$U59)) | K59: =IF($U59="","",IF(ISNUMBER(INDEX('MiT Strom Pipeline'!$S$1:$S$860,$U59)),INDEX('MiT Strom Pipeline'!$S$1:$S$860,$U59),"")) | L59: =IF($U59="","",IF(LEN(INDEX('MiT Strom Pipeline'!$V$1:$V$860,$U59))>0,LEFT(INDEX('MiT Strom Pipeline'!$V$1:$V$860,$U59),55),"")) | M59: =IF($U59="","",IF(INDEX('MiT Strom Pipeline'!$AF$1:$AF$860,$U59)="","",INDEX('MiT Strom Pipeline'!$AF$1:$AF$860,$U59))) | N59: =IF($U59="","",IF(INDEX('MiT Strom Pipeline'!$BB$1:$BB$860,$U59)="","",INDEX('MiT Strom Pipeline'!$BB$1:$BB$860,$U59))) | U59: =IFERROR(MATCH(49,'MiT Strom Pipeline'!$AM$6:$AM$860,0)+5,"")
A60: =IF($U60="","",IF(ISNUMBER(INDEX('MiT Strom Pipeline'!$A$1:$A$860,$U60)),INDEX('MiT Strom Pipeline'!$A$1:$A$860,$U60),"")) | B60: =IF($U60="","",IF(INDEX('MiT Strom Pipeline'!$B$1:$B$860,$U60)="","",INDEX('MiT Strom Pipeline'!$B$1:$B$860,$U60))) | C60: =IF($U60="","",IF(INDEX('MiT Strom Pipeline'!$C$1:$C$860,$U60)="","",INDEX('MiT Strom Pipeline'!$C$1:$C$860,$U60))) | D60: =IF($U60="","",IF(INDEX('MiT Strom Pipeline'!$D$1:$D$860,$U60)="","",INDEX('MiT Strom Pipeline'!$D$1:$D$860,$U60))) | E60: =IF($U60="","",IF(ISNUMBER(INDEX('MiT Strom Pipeline'!$O$1:$O$860,$U60)),INDEX('MiT Strom Pipeline'!$O$1:$O$860,$U60),IF(INDEX('MiT Strom Pipeline'!$H$1:$H$860,$U60)="","",INDEX('MiT Strom Pipeline'!$H$1:$H$860,$U60)))) | F60: =IF($U60="","",IF(ISNUMBER(INDEX('MiT Strom Pipeline'!$P$1:$P$860,$U60)),INDEX('MiT Strom Pipeline'!$P$1:$P$860,$U60),"")) | G60: =IF($U60="","",IF(ISNUMBER(INDEX('MiT Strom Pipeline'!$I$1:$I$860,$U60)),INDEX('MiT Strom Pipeline'!$I$1:$I$860,$U60),0)) | H60: =IF($U60="","",IF(ISNUMBER(INDEX('MiT Strom Pipeline'!$Q$1:$Q$860,$U60)),INDEX('MiT Strom Pipeline'!$Q$1:$Q$860,$U60),0)) | I60: =IF($U60="","",IF(INDEX('MiT Strom Pipeline'!$E$1:$E$860,$U60)="","",INDEX('MiT Strom Pipeline'!$E$1:$E$860,$U60))) | J60: =IF($U60="","",INDEX('MiT Strom Pipeline'!$R$1:$R$860,$U60)) | K60: =IF($U60="","",IF(ISNUMBER(INDEX('MiT Strom Pipeline'!$S$1:$S$860,$U60)),INDEX('MiT Strom Pipeline'!$S$1:$S$860,$U60),"")) | L60: =IF($U60="","",IF(LEN(INDEX('MiT Strom Pipeline'!$V$1:$V$860,$U60))>0,LEFT(INDEX('MiT Strom Pipeline'!$V$1:$V$860,$U60),55),"")) | M60: =IF($U60="","",IF(INDEX('MiT Strom Pipeline'!$AF$1:$AF$860,$U60)="","",INDEX('MiT Strom Pipeline'!$AF$1:$AF$860,$U60))) | N60: =IF($U60="","",IF(INDEX('MiT Strom Pipeline'!$BB$1:$BB$860,$U60)="","",INDEX('MiT Strom Pipeline'!$BB$1:$BB$860,$U60))) | U60: =IFERROR(MATCH(50,'MiT Strom Pipeline'!$AM$6:$AM$860,0)+5,"")
A61: =IF($U61="","",IF(ISNUMBER(INDEX('MiT Strom Pipeline'!$A$1:$A$860,$U61)),INDEX('MiT Strom Pipeline'!$A$1:$A$860,$U61),"")) | B61: =IF($U61="","",IF(INDEX('MiT Strom Pipeline'!$B$1:$B$860,$U61)="","",INDEX('MiT Strom Pipeline'!$B$1:$B$860,$U61))) | C61: =IF($U61="","",IF(INDEX('MiT Strom Pipeline'!$C$1:$C$860,$U61)="","",INDEX('MiT Strom Pipeline'!$C$1:$C$860,$U61))) | D61: =IF($U61="","",IF(INDEX('MiT Strom Pipeline'!$D$1:$D$860,$U61)="","",INDEX('MiT Strom Pipeline'!$D$1:$D$860,$U61))) | E61: =IF($U61="","",IF(ISNUMBER(INDEX('MiT Strom Pipeline'!$O$1:$O$860,$U61)),INDEX('MiT Strom Pipeline'!$O$1:$O$860,$U61),IF(INDEX('MiT Strom Pipeline'!$H$1:$H$860,$U61)="","",INDEX('MiT Strom Pipeline'!$H$1:$H$860,$U61)))) | F61: =IF($U61="","",IF(ISNUMBER(INDEX('MiT Strom Pipeline'!$P$1:$P$860,$U61)),INDEX('MiT Strom Pipeline'!$P$1:$P$860,$U61),"")) | G61: =IF($U61="","",IF(ISNUMBER(INDEX('MiT Strom Pipeline'!$I$1:$I$860,$U61)),INDEX('MiT Strom Pipeline'!$I$1:$I$860,$U61),0)) | H61: =IF($U61="","",IF(ISNUMBER(INDEX('MiT Strom Pipeline'!$Q$1:$Q$860,$U61)),INDEX('MiT Strom Pipeline'!$Q$1:$Q$860,$U61),0)) | I61: =IF($U61="","",IF(INDEX('MiT Strom Pipeline'!$E$1:$E$860,$U61)="","",INDEX('MiT Strom Pipeline'!$E$1:$E$860,$U61))) | J61: =IF($U61="","",INDEX('MiT Strom Pipeline'!$R$1:$R$860,$U61)) | K61: =IF($U61="","",IF(ISNUMBER(INDEX('MiT Strom Pipeline'!$S$1:$S$860,$U61)),INDEX('MiT Strom Pipeline'!$S$1:$S$860,$U61),"")) | L61: =IF($U61="","",IF(LEN(INDEX('MiT Strom Pipeline'!$V$1:$V$860,$U61))>0,LEFT(INDEX('MiT Strom Pipeline'!$V$1:$V$860,$U61),55),"")) | M61: =IF($U61="","",IF(INDEX('MiT Strom Pipeline'!$AF$1:$AF$860,$U61)="","",INDEX('MiT Strom Pipeline'!$AF$1:$AF$860,$U61))) | N61: =IF($U61="","",IF(INDEX('MiT Strom Pipeline'!$BB$1:$BB$860,$U61)="","",INDEX('MiT Strom Pipeline'!$BB$1:$BB$860,$U61))) | U61: =IFERROR(MATCH(51,'MiT Strom Pipeline'!$AM$6:$AM$860,0)+5,"")
A62: =IF($U62="","",IF(ISNUMBER(INDEX('MiT Strom Pipeline'!$A$1:$A$860,$U62)),INDEX('MiT Strom Pipeline'!$A$1:$A$860,$U62),"")) | B62: =IF($U62="","",IF(INDEX('MiT Strom Pipeline'!$B$1:$B$860,$U62)="","",INDEX('MiT Strom Pipeline'!$B$1:$B$860,$U62))) | C62: =IF($U62="","",IF(INDEX('MiT Strom Pipeline'!$C$1:$C$860,$U62)="","",INDEX('MiT Strom Pipeline'!$C$1:$C$860,$U62))) | D62: =IF($U62="","",IF(INDEX('MiT Strom Pipeline'!$D$1:$D$860,$U62)="","",INDEX('MiT Strom Pipeline'!$D$1:$D$860,$U62))) | E62: =IF($U62="","",IF(ISNUMBER(INDEX('MiT Strom Pipeline'!$O$1:$O$860,$U62)),INDEX('MiT Strom Pipeline'!$O$1:$O$860,$U62),IF(INDEX('MiT Strom Pipeline'!$H$1:$H$860,$U62)="","",INDEX('MiT Strom Pipeline'!$H$1:$H$860,$U62)))) | F62: =IF($U62="","",IF(ISNUMBER(INDEX('MiT Strom Pipeline'!$P$1:$P$860,$U62)),INDEX('MiT Strom Pipeline'!$P$1:$P$860,$U62),"")) | G62: =IF($U62="","",IF(ISNUMBER(INDEX('MiT Strom Pipeline'!$I$1:$I$860,$U62)),INDEX('MiT Strom Pipeline'!$I$1:$I$860,$U62),0)) | H62: =IF($U62="","",IF(ISNUMBER(INDEX('MiT Strom Pipeline'!$Q$1:$Q$860,$U62)),INDEX('MiT Strom Pipeline'!$Q$1:$Q$860,$U62),0)) | I62: =IF($U62="","",IF(INDEX('MiT Strom Pipeline'!$E$1:$E$860,$U62)="","",INDEX('MiT Strom Pipeline'!$E$1:$E$860,$U62))) | J62: =IF($U62="","",INDEX('MiT Strom Pipeline'!$R$1:$R$860,$U62)) | K62: =IF($U62="","",IF(ISNUMBER(INDEX('MiT Strom Pipeline'!$S$1:$S$860,$U62)),INDEX('MiT Strom Pipeline'!$S$1:$S$860,$U62),"")) | L62: =IF($U62="","",IF(LEN(INDEX('MiT Strom Pipeline'!$V$1:$V$860,$U62))>0,LEFT(INDEX('MiT Strom Pipeline'!$V$1:$V$860,$U62),55),"")) | M62: =IF($U62="","",IF(INDEX('MiT Strom Pipeline'!$AF$1:$AF$860,$U62)="","",INDEX('MiT Strom Pipeline'!$AF$1:$AF$860,$U62))) | N62: =IF($U62="","",IF(INDEX('MiT Strom Pipeline'!$BB$1:$BB$860,$U62)="","",INDEX('MiT Strom Pipeline'!$BB$1:$BB$860,$U62))) | U62: =IFERROR(MATCH(52,'MiT Strom Pipeline'!$AM$6:$AM$860,0)+5,"")
A63: =IF($U63="","",IF(ISNUMBER(INDEX('MiT Strom Pipeline'!$A$1:$A$860,$U63)),INDEX('MiT Strom Pipeline'!$A$1:$A$860,$U63),"")) | B63: =IF($U63="","",IF(INDEX('MiT Strom Pipeline'!$B$1:$B$860,$U63)="","",INDEX('MiT Strom Pipeline'!$B$1:$B$860,$U63))) | C63: =IF($U63="","",IF(INDEX('MiT Strom Pipeline'!$C$1:$C$860,$U63)="","",INDEX('MiT Strom Pipeline'!$C$1:$C$860,$U63))) | D63: =IF($U63="","",IF(INDEX('MiT Strom Pipeline'!$D$1:$D$860,$U63)="","",INDEX('MiT Strom Pipeline'!$D$1:$D$860,$U63))) | E63: =IF($U63="","",IF(ISNUMBER(INDEX('MiT Strom Pipeline'!$O$1:$O$860,$U63)),INDEX('MiT Strom Pipeline'!$O$1:$O$860,$U63),IF(INDEX('MiT Strom Pipeline'!$H$1:$H$860,$U63)="","",INDEX('MiT Strom Pipeline'!$H$1:$H$860,$U63)))) | F63: =IF($U63="","",IF(ISNUMBER(INDEX('MiT Strom Pipeline'!$P$1:$P$860,$U63)),INDEX('MiT Strom Pipeline'!$P$1:$P$860,$U63),"")) | G63: =IF($U63="","",IF(ISNUMBER(INDEX('MiT Strom Pipeline'!$I$1:$I$860,$U63)),INDEX('MiT Strom Pipeline'!$I$1:$I$860,$U63),0)) | H63: =IF($U63="","",IF(ISNUMBER(INDEX('MiT Strom Pipeline'!$Q$1:$Q$860,$U63)),INDEX('MiT Strom Pipeline'!$Q$1:$Q$860,$U63),0)) | I63: =IF($U63="","",IF(INDEX('MiT Strom Pipeline'!$E$1:$E$860,$U63)="","",INDEX('MiT Strom Pipeline'!$E$1:$E$860,$U63))) | J63: =IF($U63="","",INDEX('MiT Strom Pipeline'!$R$1:$R$860,$U63)) | K63: =IF($U63="","",IF(ISNUMBER(INDEX('MiT Strom Pipeline'!$S$1:$S$860,$U63)),INDEX('MiT Strom Pipeline'!$S$1:$S$860,$U63),"")) | L63: =IF($U63="","",IF(LEN(INDEX('MiT Strom Pipeline'!$V$1:$V$860,$U63))>0,LEFT(INDEX('MiT Strom Pipeline'!$V$1:$V$860,$U63),55),"")) | M63: =IF($U63="","",IF(INDEX('MiT Strom Pipeline'!$AF$1:$AF$860,$U63)="","",INDEX('MiT Strom Pipeline'!$AF$1:$AF$860,$U63))) | N63: =IF($U63="","",IF(INDEX('MiT Strom Pipeline'!$BB$1:$BB$860,$U63)="","",INDEX('MiT Strom Pipeline'!$BB$1:$BB$860,$U63))) | U63: =IFERROR(MATCH(53,'MiT Strom Pipeline'!$AM$6:$AM$860,0)+5,"")
A64: =IF($U64="","",IF(ISNUMBER(INDEX('MiT Strom Pipeline'!$A$1:$A$860,$U64)),INDEX('MiT Strom Pipeline'!$A$1:$A$860,$U64),"")) | B64: =IF($U64="","",IF(INDEX('MiT Strom Pipeline'!$B$1:$B$860,$U64)="","",INDEX('MiT Strom Pipeline'!$B$1:$B$860,$U64))) | C64: =IF($U64="","",IF(INDEX('MiT Strom Pipeline'!$C$1:$C$860,$U64)="","",INDEX('MiT Strom Pipeline'!$C$1:$C$860,$U64))) | D64: =IF($U64="","",IF(INDEX('MiT Strom Pipeline'!$D$1:$D$860,$U64)="","",INDEX('MiT Strom Pipeline'!$D$1:$D$860,$U64))) | E64: =IF($U64="","",IF(ISNUMBER(INDEX('MiT Strom Pipeline'!$O$1:$O$860,$U64)),INDEX('MiT Strom Pipeline'!$O$1:$O$860,$U64),IF(INDEX('MiT Strom Pipeline'!$H$1:$H$860,$U64)="","",INDEX('MiT Strom Pipeline'!$H$1:$H$860,$U64)))) | F64: =IF($U64="","",IF(ISNUMBER(INDEX('MiT Strom Pipeline'!$P$1:$P$860,$U64)),INDEX('MiT Strom Pipeline'!$P$1:$P$860,$U64),"")) | G64: =IF($U64="","",IF(ISNUMBER(INDEX('MiT Strom Pipeline'!$I$1:$I$860,$U64)),INDEX('MiT Strom Pipeline'!$I$1:$I$860,$U64),0)) | H64: =IF($U64="","",IF(ISNUMBER(INDEX('MiT Strom Pipeline'!$Q$1:$Q$860,$U64)),INDEX('MiT Strom Pipeline'!$Q$1:$Q$860,$U64),0)) | I64: =IF($U64="","",IF(INDEX('MiT Strom Pipeline'!$E$1:$E$860,$U64)="","",INDEX('MiT Strom Pipeline'!$E$1:$E$860,$U64))) | J64: =IF($U64="","",INDEX('MiT Strom Pipeline'!$R$1:$R$860,$U64)) | K64: =IF($U64="","",IF(ISNUMBER(INDEX('MiT Strom Pipeline'!$S$1:$S$860,$U64)),INDEX('MiT Strom Pipeline'!$S$1:$S$860,$U64),"")) | L64: =IF($U64="","",IF(LEN(INDEX('MiT Strom Pipeline'!$V$1:$V$860,$U64))>0,LEFT(INDEX('MiT Strom Pipeline'!$V$1:$V$860,$U64),55),"")) | M64: =IF($U64="","",IF(INDEX('MiT Strom Pipeline'!$AF$1:$AF$860,$U64)="","",INDEX('MiT Strom Pipeline'!$AF$1:$AF$860,$U64))) | N64: =IF($U64="","",IF(INDEX('MiT Strom Pipeline'!$BB$1:$BB$860,$U64)="","",INDEX('MiT Strom Pipeline'!$BB$1:$BB$860,$U64))) | U64: =IFERROR(MATCH(54,'MiT Strom Pipeline'!$AM$6:$AM$860,0)+5,"")
A65: =IF($U65="","",IF(ISNUMBER(INDEX('MiT Strom Pipeline'!$A$1:$A$860,$U65)),INDEX('MiT Strom Pipeline'!$A$1:$A$860,$U65),"")) | B65: =IF($U65="","",IF(INDEX('MiT Strom Pipeline'!$B$1:$B$860,$U65)="","",INDEX('MiT Strom Pipeline'!$B$1:$B$860,$U65))) | C65: =IF($U65="","",IF(INDEX('MiT Strom Pipeline'!$C$1:$C$860,$U65)="","",INDEX('MiT Strom Pipeline'!$C$1:$C$860,$U65))) | D65: =IF($U65="","",IF(INDEX('MiT Strom Pipeline'!$D$1:$D$860,$U65)="","",INDEX('MiT Strom Pipeline'!$D$1:$D$860,$U65))) | E65: =IF($U65="","",IF(ISNUMBER(INDEX('MiT Strom Pipeline'!$O$1:$O$860,$U65)),INDEX('MiT Strom Pipeline'!$O$1:$O$860,$U65),IF(INDEX('MiT Strom Pipeline'!$H$1:$H$860,$U65)="","",INDEX('MiT Strom Pipeline'!$H$1:$H$860,$U65)))) | F65: =IF($U65="","",IF(ISNUMBER(INDEX('MiT Strom Pipeline'!$P$1:$P$860,$U65)),INDEX('MiT Strom Pipeline'!$P$1:$P$860,$U65),"")) | G65: =IF($U65="","",IF(ISNUMBER(INDEX('MiT Strom Pipeline'!$I$1:$I$860,$U65)),INDEX('MiT Strom Pipeline'!$I$1:$I$860,$U65),0)) | H65: =IF($U65="","",IF(ISNUMBER(INDEX('MiT Strom Pipeline'!$Q$1:$Q$860,$U65)),INDEX('MiT Strom Pipeline'!$Q$1:$Q$860,$U65),0)) | I65: =IF($U65="","",IF(INDEX('MiT Strom Pipeline'!$E$1:$E$860,$U65)="","",INDEX('MiT Strom Pipeline'!$E$1:$E$860,$U65))) | J65: =IF($U65="","",INDEX('MiT Strom Pipeline'!$R$1:$R$860,$U65)) | K65: =IF($U65="","",IF(ISNUMBER(INDEX('MiT Strom Pipeline'!$S$1:$S$860,$U65)),INDEX('MiT Strom Pipeline'!$S$1:$S$860,$U65),"")) | L65: =IF($U65="","",IF(LEN(INDEX('MiT Strom Pipeline'!$V$1:$V$860,$U65))>0,LEFT(INDEX('MiT Strom Pipeline'!$V$1:$V$860,$U65),55),"")) | M65: =IF($U65="","",IF(INDEX('MiT Strom Pipeline'!$AF$1:$AF$860,$U65)="","",INDEX('MiT Strom Pipeline'!$AF$1:$AF$860,$U65))) | N65: =IF($U65="","",IF(INDEX('MiT Strom Pipeline'!$BB$1:$BB$860,$U65)="","",INDEX('MiT Strom Pipeline'!$BB$1:$BB$860,$U65))) | U65: =IFERROR(MATCH(55,'MiT Strom Pipeline'!$AM$6:$AM$860,0)+5,"")
A66: =IF($U66="","",IF(ISNUMBER(INDEX('MiT Strom Pipeline'!$A$1:$A$860,$U66)),INDEX('MiT Strom Pipeline'!$A$1:$A$860,$U66),"")) | B66: =IF($U66="","",IF(INDEX('MiT Strom Pipeline'!$B$1:$B$860,$U66)="","",INDEX('MiT Strom Pipeline'!$B$1:$B$860,$U66))) | C66: =IF($U66="","",IF(INDEX('MiT Strom Pipeline'!$C$1:$C$860,$U66)="","",INDEX('MiT Strom Pipeline'!$C$1:$C$860,$U66))) | D66: =IF($U66="","",IF(INDEX('MiT Strom Pipeline'!$D$1:$D$860,$U66)="","",INDEX('MiT Strom Pipeline'!$D$1:$D$860,$U66))) | E66: =IF($U66="","",IF(ISNUMBER(INDEX('MiT Strom Pipeline'!$O$1:$O$860,$U66)),INDEX('MiT Strom Pipeline'!$O$1:$O$860,$U66),IF(INDEX('MiT Strom Pipeline'!$H$1:$H$860,$U66)="","",INDEX('MiT Strom Pipeline'!$H$1:$H$860,$U66)))) | F66: =IF($U66="","",IF(ISNUMBER(INDEX('MiT Strom Pipeline'!$P$1:$P$860,$U66)),INDEX('MiT Strom Pipeline'!$P$1:$P$860,$U66),"")) | G66: =IF($U66="","",IF(ISNUMBER(INDEX('MiT Strom Pipeline'!$I$1:$I$860,$U66)),INDEX('MiT Strom Pipeline'!$I$1:$I$860,$U66),0)) | H66: =IF($U66="","",IF(ISNUMBER(INDEX('MiT Strom Pipeline'!$Q$1:$Q$860,$U66)),INDEX('MiT Strom Pipeline'!$Q$1:$Q$860,$U66),0)) | I66: =IF($U66="","",IF(INDEX('MiT Strom Pipeline'!$E$1:$E$860,$U66)="","",INDEX('MiT Strom Pipeline'!$E$1:$E$860,$U66))) | J66: =IF($U66="","",INDEX('MiT Strom Pipeline'!$R$1:$R$860,$U66)) | K66: =IF($U66="","",IF(ISNUMBER(INDEX('MiT Strom Pipeline'!$S$1:$S$860,$U66)),INDEX('MiT Strom Pipeline'!$S$1:$S$860,$U66),"")) | L66: =IF($U66="","",IF(LEN(INDEX('MiT Strom Pipeline'!$V$1:$V$860,$U66))>0,LEFT(INDEX('MiT Strom Pipeline'!$V$1:$V$860,$U66),55),"")) | M66: =IF($U66="","",IF(INDEX('MiT Strom Pipeline'!$AF$1:$AF$860,$U66)="","",INDEX('MiT Strom Pipeline'!$AF$1:$AF$860,$U66))) | N66: =IF($U66="","",IF(INDEX('MiT Strom Pipeline'!$BB$1:$BB$860,$U66)="","",INDEX('MiT Strom Pipeline'!$BB$1:$BB$860,$U66))) | U66: =IFERROR(MATCH(56,'MiT Strom Pipeline'!$AM$6:$AM$860,0)+5,"")
A67: =IF($U67="","",IF(ISNUMBER(INDEX('MiT Strom Pipeline'!$A$1:$A$860,$U67)),INDEX('MiT Strom Pipeline'!$A$1:$A$860,$U67),"")) | B67: =IF($U67="","",IF(INDEX('MiT Strom Pipeline'!$B$1:$B$860,$U67)="","",INDEX('MiT Strom Pipeline'!$B$1:$B$860,$U67))) | C67: =IF($U67="","",IF(INDEX('MiT Strom Pipeline'!$C$1:$C$860,$U67)="","",INDEX('MiT Strom Pipeline'!$C$1:$C$860,$U67))) | D67: =IF($U67="","",IF(INDEX('MiT Strom Pipeline'!$D$1:$D$860,$U67)="","",INDEX('MiT Strom Pipeline'!$D$1:$D$860,$U67))) | E67: =IF($U67="","",IF(ISNUMBER(INDEX('MiT Strom Pipeline'!$O$1:$O$860,$U67)),INDEX('MiT Strom Pipeline'!$O$1:$O$860,$U67),IF(INDEX('MiT Strom Pipeline'!$H$1:$H$860,$U67)="","",INDEX('MiT Strom Pipeline'!$H$1:$H$860,$U67)))) | F67: =IF($U67="","",IF(ISNUMBER(INDEX('MiT Strom Pipeline'!$P$1:$P$860,$U67)),INDEX('MiT Strom Pipeline'!$P$1:$P$860,$U67),"")) | G67: =IF($U67="","",IF(ISNUMBER(INDEX('MiT Strom Pipeline'!$I$1:$I$860,$U67)),INDEX('MiT Strom Pipeline'!$I$1:$I$860,$U67),0)) | H67: =IF($U67="","",IF(ISNUMBER(INDEX('MiT Strom Pipeline'!$Q$1:$Q$860,$U67)),INDEX('MiT Strom Pipeline'!$Q$1:$Q$860,$U67),0)) | I67: =IF($U67="","",IF(INDEX('MiT Strom Pipeline'!$E$1:$E$860,$U67)="","",INDEX('MiT Strom Pipeline'!$E$1:$E$860,$U67))) | J67: =IF($U67="","",INDEX('MiT Strom Pipeline'!$R$1:$R$860,$U67)) | K67: =IF($U67="","",IF(ISNUMBER(INDEX('MiT Strom Pipeline'!$S$1:$S$860,$U67)),INDEX('MiT Strom Pipeline'!$S$1:$S$860,$U67),"")) | L67: =IF($U67="","",IF(LEN(INDEX('MiT Strom Pipeline'!$V$1:$V$860,$U67))>0,LEFT(INDEX('MiT Strom Pipeline'!$V$1:$V$860,$U67),55),"")) | M67: =IF($U67="","",IF(INDEX('MiT Strom Pipeline'!$AF$1:$AF$860,$U67)="","",INDEX('MiT Strom Pipeline'!$AF$1:$AF$860,$U67))) | N67: =IF($U67="","",IF(INDEX('MiT Strom Pipeline'!$BB$1:$BB$860,$U67)="","",INDEX('MiT Strom Pipeline'!$BB$1:$BB$860,$U67))) | U67: =IFERROR(MATCH(57,'MiT Strom Pipeline'!$AM$6:$AM$860,0)+5,"")
A68: =IF($U68="","",IF(ISNUMBER(INDEX('MiT Strom Pipeline'!$A$1:$A$860,$U68)),INDEX('MiT Strom Pipeline'!$A$1:$A$860,$U68),"")) | B68: =IF($U68="","",IF(INDEX('MiT Strom Pipeline'!$B$1:$B$860,$U68)="","",INDEX('MiT Strom Pipeline'!$B$1:$B$860,$U68))) | C68: =IF($U68="","",IF(INDEX('MiT Strom Pipeline'!$C$1:$C$860,$U68)="","",INDEX('MiT Strom Pipeline'!$C$1:$C$860,$U68))) | D68: =IF($U68="","",IF(INDEX('MiT Strom Pipeline'!$D$1:$D$860,$U68)="","",INDEX('MiT Strom Pipeline'!$D$1:$D$860,$U68))) | E68: =IF($U68="","",IF(ISNUMBER(INDEX('MiT Strom Pipeline'!$O$1:$O$860,$U68)),INDEX('MiT Strom Pipeline'!$O$1:$O$860,$U68),IF(INDEX('MiT Strom Pipeline'!$H$1:$H$860,$U68)="","",INDEX('MiT Strom Pipeline'!$H$1:$H$860,$U68)))) | F68: =IF($U68="","",IF(ISNUMBER(INDEX('MiT Strom Pipeline'!$P$1:$P$860,$U68)),INDEX('MiT Strom Pipeline'!$P$1:$P$860,$U68),"")) | G68: =IF($U68="","",IF(ISNUMBER(INDEX('MiT Strom Pipeline'!$I$1:$I$860,$U68)),INDEX('MiT Strom Pipeline'!$I$1:$I$860,$U68),0)) | H68: =IF($U68="","",IF(ISNUMBER(INDEX('MiT Strom Pipeline'!$Q$1:$Q$860,$U68)),INDEX('MiT Strom Pipeline'!$Q$1:$Q$860,$U68),0)) | I68: =IF($U68="","",IF(INDEX('MiT Strom Pipeline'!$E$1:$E$860,$U68)="","",INDEX('MiT Strom Pipeline'!$E$1:$E$860,$U68))) | J68: =IF($U68="","",INDEX('MiT Strom Pipeline'!$R$1:$R$860,$U68)) | K68: =IF($U68="","",IF(ISNUMBER(INDEX('MiT Strom Pipeline'!$S$1:$S$860,$U68)),INDEX('MiT Strom Pipeline'!$S$1:$S$860,$U68),"")) | L68: =IF($U68="","",IF(LEN(INDEX('MiT Strom Pipeline'!$V$1:$V$860,$U68))>0,LEFT(INDEX('MiT Strom Pipeline'!$V$1:$V$860,$U68),55),"")) | M68: =IF($U68="","",IF(INDEX('MiT Strom Pipeline'!$AF$1:$AF$860,$U68)="","",INDEX('MiT Strom Pipeline'!$AF$1:$AF$860,$U68))) | N68: =IF($U68="","",IF(INDEX('MiT Strom Pipeline'!$BB$1:$BB$860,$U68)="","",INDEX('MiT Strom Pipeline'!$BB$1:$BB$860,$U68))) | U68: =IFERROR(MATCH(58,'MiT Strom Pipeline'!$AM$6:$AM$860,0)+5,"")
A69: =IF($U69="","",IF(ISNUMBER(INDEX('MiT Strom Pipeline'!$A$1:$A$860,$U69)),INDEX('MiT Strom Pipeline'!$A$1:$A$860,$U69),"")) | B69: =IF($U69="","",IF(INDEX('MiT Strom Pipeline'!$B$1:$B$860,$U69)="","",INDEX('MiT Strom Pipeline'!$B$1:$B$860,$U69))) | C69: =IF($U69="","",IF(INDEX('MiT Strom Pipeline'!$C$1:$C$860,$U69)="","",INDEX('MiT Strom Pipeline'!$C$1:$C$860,$U69))) | D69: =IF($U69="","",IF(INDEX('MiT Strom Pipeline'!$D$1:$D$860,$U69)="","",INDEX('MiT Strom Pipeline'!$D$1:$D$860,$U69))) | E69: =IF($U69="","",IF(ISNUMBER(INDEX('MiT Strom Pipeline'!$O$1:$O$860,$U69)),INDEX('MiT Strom Pipeline'!$O$1:$O$860,$U69),IF(INDEX('MiT Strom Pipeline'!$H$1:$H$860,$U69)="","",INDEX('MiT Strom Pipeline'!$H$1:$H$860,$U69)))) | F69: =IF($U69="","",IF(ISNUMBER(INDEX('MiT Strom Pipeline'!$P$1:$P$860,$U69)),INDEX('MiT Strom Pipeline'!$P$1:$P$860,$U69),"")) | G69: =IF($U69="","",IF(ISNUMBER(INDEX('MiT Strom Pipeline'!$I$1:$I$860,$U69)),INDEX('MiT Strom Pipeline'!$I$1:$I$860,$U69),0)) | H69: =IF($U69="","",IF(ISNUMBER(INDEX('MiT Strom Pipeline'!$Q$1:$Q$860,$U69)),INDEX('MiT Strom Pipeline'!$Q$1:$Q$860,$U69),0)) | I69: =IF($U69="","",IF(INDEX('MiT Strom Pipeline'!$E$1:$E$860,$U69)="","",INDEX('MiT Strom Pipeline'!$E$1:$E$860,$U69))) | J69: =IF($U69="","",INDEX('MiT Strom Pipeline'!$R$1:$R$860,$U69)) | K69: =IF($U69="","",IF(ISNUMBER(INDEX('MiT Strom Pipeline'!$S$1:$S$860,$U69)),INDEX('MiT Strom Pipeline'!$S$1:$S$860,$U69),"")) | L69: =IF($U69="","",IF(LEN(INDEX('MiT Strom Pipeline'!$V$1:$V$860,$U69))>0,LEFT(INDEX('MiT Strom Pipeline'!$V$1:$V$860,$U69),55),"")) | M69: =IF($U69="","",IF(INDEX('MiT Strom Pipeline'!$AF$1:$AF$860,$U69)="","",INDEX('MiT Strom Pipeline'!$AF$1:$AF$860,$U69))) | N69: =IF($U69="","",IF(INDEX('MiT Strom Pipeline'!$BB$1:$BB$860,$U69)="","",INDEX('MiT Strom Pipeline'!$BB$1:$BB$860,$U69))) | U69: =IFERROR(MATCH(59,'MiT Strom Pipeline'!$AM$6:$AM$860,0)+5,"")
A70: =IF($U70="","",IF(ISNUMBER(INDEX('MiT Strom Pipeline'!$A$1:$A$860,$U70)),INDEX('MiT Strom Pipeline'!$A$1:$A$860,$U70),"")) | B70: =IF($U70="","",IF(INDEX('MiT Strom Pipeline'!$B$1:$B$860,$U70)="","",INDEX('MiT Strom Pipeline'!$B$1:$B$860,$U70))) | C70: =IF($U70="","",IF(INDEX('MiT Strom Pipeline'!$C$1:$C$860,$U70)="","",INDEX('MiT Strom Pipeline'!$C$1:$C$860,$U70))) | D70: =IF($U70="","",IF(INDEX('MiT Strom Pipeline'!$D$1:$D$860,$U70)="","",INDEX('MiT Strom Pipeline'!$D$1:$D$860,$U70))) | E70: =IF($U70="","",IF(ISNUMBER(INDEX('MiT Strom Pipeline'!$O$1:$O$860,$U70)),INDEX('MiT Strom Pipeline'!$O$1:$O$860,$U70),IF(INDEX('MiT Strom Pipeline'!$H$1:$H$860,$U70)="","",INDEX('MiT Strom Pipeline'!$H$1:$H$860,$U70)))) | F70: =IF($U70="","",IF(ISNUMBER(INDEX('MiT Strom Pipeline'!$P$1:$P$860,$U70)),INDEX('MiT Strom Pipeline'!$P$1:$P$860,$U70),"")) | G70: =IF($U70="","",IF(ISNUMBER(INDEX('MiT Strom Pipeline'!$I$1:$I$860,$U70)),INDEX('MiT Strom Pipeline'!$I$1:$I$860,$U70),0)) | H70: =IF($U70="","",IF(ISNUMBER(INDEX('MiT Strom Pipeline'!$Q$1:$Q$860,$U70)),INDEX('MiT Strom Pipeline'!$Q$1:$Q$860,$U70),0)) | I70: =IF($U70="","",IF(INDEX('MiT Strom Pipeline'!$E$1:$E$860,$U70)="","",INDEX('MiT Strom Pipeline'!$E$1:$E$860,$U70))) | J70: =IF($U70="","",INDEX('MiT Strom Pipeline'!$R$1:$R$860,$U70)) | K70: =IF($U70="","",IF(ISNUMBER(INDEX('MiT Strom Pipeline'!$S$1:$S$860,$U70)),INDEX('MiT Strom Pipeline'!$S$1:$S$860,$U70),"")) | L70: =IF($U70="","",IF(LEN(INDEX('MiT Strom Pipeline'!$V$1:$V$860,$U70))>0,LEFT(INDEX('MiT Strom Pipeline'!$V$1:$V$860,$U70),55),"")) | M70: =IF($U70="","",IF(INDEX('MiT Strom Pipeline'!$AF$1:$AF$860,$U70)="","",INDEX('MiT Strom Pipeline'!$AF$1:$AF$860,$U70))) | N70: =IF($U70="","",IF(INDEX('MiT Strom Pipeline'!$BB$1:$BB$860,$U70)="","",INDEX('MiT Strom Pipeline'!$BB$1:$BB$860,$U70))) | U70: =IFERROR(MATCH(60,'MiT Strom Pipeline'!$AM$6:$AM$860,0)+5,"")
A71: =IF($U71="","",IF(ISNUMBER(INDEX('MiT Strom Pipeline'!$A$1:$A$860,$U71)),INDEX('MiT Strom Pipeline'!$A$1:$A$860,$U71),"")) | B71: =IF($U71="","",IF(INDEX('MiT Strom Pipeline'!$B$1:$B$860,$U71)="","",INDEX('MiT Strom Pipeline'!$B$1:$B$860,$U71))) | C71: =IF($U71="","",IF(INDEX('MiT Strom Pipeline'!$C$1:$C$860,$U71)="","",INDEX('MiT Strom Pipeline'!$C$1:$C$860,$U71))) | D71: =IF($U71="","",IF(INDEX('MiT Strom Pipeline'!$D$1:$D$860,$U71)="","",INDEX('MiT Strom Pipeline'!$D$1:$D$860,$U71))) | E71: =IF($U71="","",IF(ISNUMBER(INDEX('MiT Strom Pipeline'!$O$1:$O$860,$U71)),INDEX('MiT Strom Pipeline'!$O$1:$O$860,$U71),IF(INDEX('MiT Strom Pipeline'!$H$1:$H$860,$U71)="","",INDEX('MiT Strom Pipeline'!$H$1:$H$860,$U71)))) | F71: =IF($U71="","",IF(ISNUMBER(INDEX('MiT Strom Pipeline'!$P$1:$P$860,$U71)),INDEX('MiT Strom Pipeline'!$P$1:$P$860,$U71),"")) | G71: =IF($U71="","",IF(ISNUMBER(INDEX('MiT Strom Pipeline'!$I$1:$I$860,$U71)),INDEX('MiT Strom Pipeline'!$I$1:$I$860,$U71),0)) | H71: =IF($U71="","",IF(ISNUMBER(INDEX('MiT Strom Pipeline'!$Q$1:$Q$860,$U71)),INDEX('MiT Strom Pipeline'!$Q$1:$Q$860,$U71),0)) | I71: =IF($U71="","",IF(INDEX('MiT Strom Pipeline'!$E$1:$E$860,$U71)="","",INDEX('MiT Strom Pipeline'!$E$1:$E$860,$U71))) | J71: =IF($U71="","",INDEX('MiT Strom Pipeline'!$R$1:$R$860,$U71)) | K71: =IF($U71="","",IF(ISNUMBER(INDEX('MiT Strom Pipeline'!$S$1:$S$860,$U71)),INDEX('MiT Strom Pipeline'!$S$1:$S$860,$U71),"")) | L71: =IF($U71="","",IF(LEN(INDEX('MiT Strom Pipeline'!$V$1:$V$860,$U71))>0,LEFT(INDEX('MiT Strom Pipeline'!$V$1:$V$860,$U71),55),"")) | M71: =IF($U71="","",IF(INDEX('MiT Strom Pipeline'!$AF$1:$AF$860,$U71)="","",INDEX('MiT Strom Pipeline'!$AF$1:$AF$860,$U71))) | N71: =IF($U71="","",IF(INDEX('MiT Strom Pipeline'!$BB$1:$BB$860,$U71)="","",INDEX('MiT Strom Pipeline'!$BB$1:$BB$860,$U71))) | U71: =IFERROR(MATCH(61,'MiT Strom Pipeline'!$AM$6:$AM$860,0)+5,"")
A72: =IF($U72="","",IF(ISNUMBER(INDEX('MiT Strom Pipeline'!$A$1:$A$860,$U72)),INDEX('MiT Strom Pipeline'!$A$1:$A$860,$U72),"")) | B72: =IF($U72="","",IF(INDEX('MiT Strom Pipeline'!$B$1:$B$860,$U72)="","",INDEX('MiT Strom Pipeline'!$B$1:$B$860,$U72))) | C72: =IF($U72="","",IF(INDEX('MiT Strom Pipeline'!$C$1:$C$860,$U72)="","",INDEX('MiT Strom Pipeline'!$C$1:$C$860,$U72))) | D72: =IF($U72="","",IF(INDEX('MiT Strom Pipeline'!$D$1:$D$860,$U72)="","",INDEX('MiT Strom Pipeline'!$D$1:$D$860,$U72))) | E72: =IF($U72="","",IF(ISNUMBER(INDEX('MiT Strom Pipeline'!$O$1:$O$860,$U72)),INDEX('MiT Strom Pipeline'!$O$1:$O$860,$U72),IF(INDEX('MiT Strom Pipeline'!$H$1:$H$860,$U72)="","",INDEX('MiT Strom Pipeline'!$H$1:$H$860,$U72)))) | F72: =IF($U72="","",IF(ISNUMBER(INDEX('MiT Strom Pipeline'!$P$1:$P$860,$U72)),INDEX('MiT Strom Pipeline'!$P$1:$P$860,$U72),"")) | G72: =IF($U72="","",IF(ISNUMBER(INDEX('MiT Strom Pipeline'!$I$1:$I$860,$U72)),INDEX('MiT Strom Pipeline'!$I$1:$I$860,$U72),0)) | H72: =IF($U72="","",IF(ISNUMBER(INDEX('MiT Strom Pipeline'!$Q$1:$Q$860,$U72)),INDEX('MiT Strom Pipeline'!$Q$1:$Q$860,$U72),0)) | I72: =IF($U72="","",IF(INDEX('MiT Strom Pipeline'!$E$1:$E$860,$U72)="","",INDEX('MiT Strom Pipeline'!$E$1:$E$860,$U72))) | J72: =IF($U72="","",INDEX('MiT Strom Pipeline'!$R$1:$R$860,$U72)) | K72: =IF($U72="","",IF(ISNUMBER(INDEX('MiT Strom Pipeline'!$S$1:$S$860,$U72)),INDEX('MiT Strom Pipeline'!$S$1:$S$860,$U72),"")) | L72: =IF($U72="","",IF(LEN(INDEX('MiT Strom Pipeline'!$V$1:$V$860,$U72))>0,LEFT(INDEX('MiT Strom Pipeline'!$V$1:$V$860,$U72),55),"")) | M72: =IF($U72="","",IF(INDEX('MiT Strom Pipeline'!$AF$1:$AF$860,$U72)="","",INDEX('MiT Strom Pipeline'!$AF$1:$AF$860,$U72))) | N72: =IF($U72="","",IF(INDEX('MiT Strom Pipeline'!$BB$1:$BB$860,$U72)="","",INDEX('MiT Strom Pipeline'!$BB$1:$BB$860,$U72))) | U72: =IFERROR(MATCH(62,'MiT Strom Pipeline'!$AM$6:$AM$860,0)+5,"")
A73: 📄 2. OFFERTE — Versendete & laufende Angebote
A74: # | B74: Kunde / Unternehmen | C74: Kt. | D74: Segment | E74: Projektstart | F74: Projektende | G74: Volumen CHF | H74: Gew.Wert CHF | I74: Leistung / Fleet | J74: Status | K74: Wahr.% | L74: Nächster Schritt | M74: Auftrag / PO-Nr. | N74: Prüfstatus
A75: =IF($U75="","",IF(ISNUMBER(INDEX('MiT Strom Pipeline'!$A$1:$A$860,$U75)),INDEX('MiT Strom Pipeline'!$A$1:$A$860,$U75),"")) -> 6 | B75: =IF($U75="","",IF(INDEX('MiT Strom Pipeline'!$B$1:$B$860,$U75)="","",INDEX('MiT Strom Pipeline'!$B$1:$B$860,$U75))) -> Wincasa Solothurn | C75: =IF($U75="","",IF(INDEX('MiT Strom Pipeline'!$C$1:$C$860,$U75)="","",INDEX('MiT Strom Pipeline'!$C$1:$C$860,$U75))) -> SO | D75: =IF($U75="","",IF(INDEX('MiT Strom Pipeline'!$D$1:$D$860,$U75)="","",INDEX('MiT Strom Pipeline'!$D$1:$D$860,$U75))) -> Immobilien / FM | E75: =IF($U75="","",IF(ISNUMBER(INDEX('MiT Strom Pipeline'!$O$1:$O$860,$U75)),INDEX('MiT Strom Pipeline'!$O$1:$O$860,$U75),IF(INDEX('MiT Strom Pipeline'!$H$1:$H$860,$U75)="","",INDEX('MiT Strom Pipeline'!$H$1:$H$860,$U75)))) -> Mai | F75: =IF($U75="","",IF(ISNUMBER(INDEX('MiT Strom Pipeline'!$P$1:$P$860,$U75)),INDEX('MiT Strom Pipeline'!$P$1:$P$860,$U75),"")) | G75: =IF($U75="","",IF(ISNUMBER(INDEX('MiT Strom Pipeline'!$I$1:$I$860,$U75)),INDEX('MiT Strom Pipeline'!$I$1:$I$860,$U75),0)) -> 390000 | H75: =IF($U75="","",IF(ISNUMBER(INDEX('MiT Strom Pipeline'!$Q$1:$Q$860,$U75)),INDEX('MiT Strom Pipeline'!$Q$1:$Q$860,$U75),0)) -> 0 | I75: =IF($U75="","",IF(INDEX('MiT Strom Pipeline'!$E$1:$E$860,$U75)="","",INDEX('MiT Strom Pipeline'!$E$1:$E$860,$U75))) -> BESS 1 MWh | J75: =IF($U75="","",INDEX('MiT Strom Pipeline'!$R$1:$R$860,$U75)) -> offered | K75: =IF($U75="","",IF(ISNUMBER(INDEX('MiT Strom Pipeline'!$S$1:$S$860,$U75)),INDEX('MiT Strom Pipeline'!$S$1:$S$860,$U75),"")) -> 0.3 | L75: =IF($U75="","",IF(LEN(INDEX('MiT Strom Pipeline'!$V$1:$V$860,$U75))>0,LEFT(INDEX('MiT Strom Pipeline'!$V$1:$V$860,$U75),55),"")) -> Entscheider-Meeting anfordern, Businesscase Energie-ROI | M75: =IF($U75="","",IF(INDEX('MiT Strom Pipeline'!$AF$1:$AF$860,$U75)="","",INDEX('MiT Strom Pipeline'!$AF$1:$AF$860,$U75))) | N75: =IF($U75="","",IF(INDEX('MiT Strom Pipeline'!$BB$1:$BB$860,$U75)="","",INDEX('MiT Strom Pipeline'!$BB$1:$BB$860,$U75))) -> ○ Zeitraum offen | U75: =IFERROR(MATCH(1,'MiT Strom Pipeline'!$AN$6:$AN$860,0)+5,"") -> 6
A76: =IF($U76="","",IF(ISNUMBER(INDEX('MiT Strom Pipeline'!$A$1:$A$860,$U76)),INDEX('MiT Strom Pipeline'!$A$1:$A$860,$U76),"")) -> 15 | B76: =IF($U76="","",IF(INDEX('MiT Strom Pipeline'!$B$1:$B$860,$U76)="","",INDEX('MiT Strom Pipeline'!$B$1:$B$860,$U76))) -> Gotthard Base Tunnel | C76: =IF($U76="","",IF(INDEX('MiT Strom Pipeline'!$C$1:$C$860,$U76)="","",INDEX('MiT Strom Pipeline'!$C$1:$C$860,$U76))) -> UR | D76: =IF($U76="","",IF(INDEX('MiT Strom Pipeline'!$D$1:$D$860,$U76)="","",INDEX('MiT Strom Pipeline'!$D$1:$D$860,$U76))) -> Infrastruktur / Bahn | E76: =IF($U76="","",IF(ISNUMBER(INDEX('MiT Strom Pipeline'!$O$1:$O$860,$U76)),INDEX('MiT Strom Pipeline'!$O$1:$O$860,$U76),IF(INDEX('MiT Strom Pipeline'!$H$1:$H$860,$U76)="","",INDEX('MiT Strom Pipeline'!$H$1:$H$860,$U76)))) -> tbd | F76: =IF($U76="","",IF(ISNUMBER(INDEX('MiT Strom Pipeline'!$P$1:$P$860,$U76)),INDEX('MiT Strom Pipeline'!$P$1:$P$860,$U76),"")) | G76: =IF($U76="","",IF(ISNUMBER(INDEX('MiT Strom Pipeline'!$I$1:$I$860,$U76)),INDEX('MiT Strom Pipeline'!$I$1:$I$860,$U76),0)) -> 0 | H76: =IF($U76="","",IF(ISNUMBER(INDEX('MiT Strom Pipeline'!$Q$1:$Q$860,$U76)),INDEX('MiT Strom Pipeline'!$Q$1:$Q$860,$U76),0)) -> 0 | I76: =IF($U76="","",IF(INDEX('MiT Strom Pipeline'!$E$1:$E$860,$U76)="","",INDEX('MiT Strom Pipeline'!$E$1:$E$860,$U76))) -> Grossanlage tbd | J76: =IF($U76="","",INDEX('MiT Strom Pipeline'!$R$1:$R$860,$U76)) -> on hold | K76: =IF($U76="","",IF(ISNUMBER(INDEX('MiT Strom Pipeline'!$S$1:$S$860,$U76)),INDEX('MiT Strom Pipeline'!$S$1:$S$860,$U76),"")) -> 0.1 | L76: =IF($U76="","",IF(LEN(INDEX('MiT Strom Pipeline'!$V$1:$V$860,$U76))>0,LEFT(INDEX('MiT Strom Pipeline'!$V$1:$V$860,$U76),55),"")) -> Stakeholder identifizieren – AlpTransit/SBB kontaktiere | M76: =IF($U76="","",IF(INDEX('MiT Strom Pipeline'!$AF$1:$AF$860,$U76)="","",INDEX('MiT Strom Pipeline'!$AF$1:$AF$860,$U76))) | N76: =IF($U76="","",IF(INDEX('MiT Strom Pipeline'!$BB$1:$BB$860,$U76)="","",INDEX('MiT Strom Pipeline'!$BB$1:$BB$860,$U76))) -> ○ Einstand offen | U76: =IFERROR(MATCH(2,'MiT Strom Pipeline'!$AN$6:$AN$860,0)+5,"") -> 8
A77: =IF($U77="","",IF(ISNUMBER(INDEX('MiT Strom Pipeline'!$A$1:$A$860,$U77)),INDEX('MiT Strom Pipeline'!$A$1:$A$860,$U77),"")) -> 33 | B77: =IF($U77="","",IF(INDEX('MiT Strom Pipeline'!$B$1:$B$860,$U77)="","",INDEX('MiT Strom Pipeline'!$B$1:$B$860,$U77))) -> Oerlikon Metco Wohlen | C77: =IF($U77="","",IF(INDEX('MiT Strom Pipeline'!$C$1:$C$860,$U77)="","",INDEX('MiT Strom Pipeline'!$C$1:$C$860,$U77))) -> AG | D77: =IF($U77="","",IF(INDEX('MiT Strom Pipeline'!$D$1:$D$860,$U77)="","",INDEX('MiT Strom Pipeline'!$D$1:$D$860,$U77))) -> Industrie | E77: =IF($U77="","",IF(ISNUMBER(INDEX('MiT Strom Pipeline'!$O$1:$O$860,$U77)),INDEX('MiT Strom Pipeline'!$O$1:$O$860,$U77),IF(INDEX('MiT Strom Pipeline'!$H$1:$H$860,$U77)="","",INDEX('MiT Strom Pipeline'!$H$1:$H$860,$U77)))) -> August | F77: =IF($U77="","",IF(ISNUMBER(INDEX('MiT Strom Pipeline'!$P$1:$P$860,$U77)),INDEX('MiT Strom Pipeline'!$P$1:$P$860,$U77),"")) | G77: =IF($U77="","",IF(ISNUMBER(INDEX('MiT Strom Pipeline'!$I$1:$I$860,$U77)),INDEX('MiT Strom Pipeline'!$I$1:$I$860,$U77),0)) -> 193598.12 | H77: =IF($U77="","",IF(ISNUMBER(INDEX('MiT Strom Pipeline'!$Q$1:$Q$860,$U77)),INDEX('MiT Strom Pipeline'!$Q$1:$Q$860,$U77),0)) -> 96799.06 | I77: =IF($U77="","",IF(INDEX('MiT Strom Pipeline'!$E$1:$E$860,$U77)="","",INDEX('MiT Strom Pipeline'!$E$1:$E$860,$U77))) -> 300 kVA | J77: =IF($U77="","",INDEX('MiT Strom Pipeline'!$R$1:$R$860,$U77)) -> offered | K77: =IF($U77="","",IF(ISNUMBER(INDEX('MiT Strom Pipeline'!$S$1:$S$860,$U77)),INDEX('MiT Strom Pipeline'!$S$1:$S$860,$U77),"")) -> 0.6 | L77: =IF($U77="","",IF(LEN(INDEX('MiT Strom Pipeline'!$V$1:$V$860,$U77))>0,LEFT(INDEX('MiT Strom Pipeline'!$V$1:$V$860,$U77),55),"")) -> Kunde wahr sehr Zufrieden mit dem 1. Auftrag und im Ans | M77: =IF($U77="","",IF(INDEX('MiT Strom Pipeline'!$AF$1:$AF$860,$U77)="","",INDEX('MiT Strom Pipeline'!$AF$1:$AF$860,$U77))) | N77: =IF($U77="","",IF(INDEX('MiT Strom Pipeline'!$BB$1:$BB$860,$U77)="","",INDEX('MiT Strom Pipeline'!$BB$1:$BB$860,$U77))) -> ○ Zeitraum offen | U77: =IFERROR(MATCH(3,'MiT Strom Pipeline'!$AN$6:$AN$860,0)+5,"") -> 16
A78: =IF($U78="","",IF(ISNUMBER(INDEX('MiT Strom Pipeline'!$A$1:$A$860,$U78)),INDEX('MiT Strom Pipeline'!$A$1:$A$860,$U78),"")) -> 33 | B78: =IF($U78="","",IF(INDEX('MiT Strom Pipeline'!$B$1:$B$860,$U78)="","",INDEX('MiT Strom Pipeline'!$B$1:$B$860,$U78))) -> Oerlikon Metco Wohlen | C78: =IF($U78="","",IF(INDEX('MiT Strom Pipeline'!$C$1:$C$860,$U78)="","",INDEX('MiT Strom Pipeline'!$C$1:$C$860,$U78))) -> AG | D78: =IF($U78="","",IF(INDEX('MiT Strom Pipeline'!$D$1:$D$860,$U78)="","",INDEX('MiT Strom Pipeline'!$D$1:$D$860,$U78))) -> Industrie | E78: =IF($U78="","",IF(ISNUMBER(INDEX('MiT Strom Pipeline'!$O$1:$O$860,$U78)),INDEX('MiT Strom Pipeline'!$O$1:$O$860,$U78),IF(INDEX('MiT Strom Pipeline'!$H$1:$H$860,$U78)="","",INDEX('MiT Strom Pipeline'!$H$1:$H$860,$U78)))) -> August | F78: =IF($U78="","",IF(ISNUMBER(INDEX('MiT Strom Pipeline'!$P$1:$P$860,$U78)),INDEX('MiT Strom Pipeline'!$P$1:$P$860,$U78),"")) | G78: =IF($U78="","",IF(ISNUMBER(INDEX('MiT Strom Pipeline'!$I$1:$I$860,$U78)),INDEX('MiT Strom Pipeline'!$I$1:$I$860,$U78),0)) -> 74902.11 | H78: =IF($U78="","",IF(ISNUMBER(INDEX('MiT Strom Pipeline'!$Q$1:$Q$860,$U78)),INDEX('MiT Strom Pipeline'!$Q$1:$Q$860,$U78),0)) -> 37451.055 | I78: =IF($U78="","",IF(INDEX('MiT Strom Pipeline'!$E$1:$E$860,$U78)="","",INDEX('MiT Strom Pipeline'!$E$1:$E$860,$U78))) -> Kaltwasser 100 kW | J78: =IF($U78="","",INDEX('MiT Strom Pipeline'!$R$1:$R$860,$U78)) -> offered | K78: =IF($U78="","",IF(ISNUMBER(INDEX('MiT Strom Pipeline'!$S$1:$S$860,$U78)),INDEX('MiT Strom Pipeline'!$S$1:$S$860,$U78),"")) -> 0.6 | L78: =IF($U78="","",IF(LEN(INDEX('MiT Strom Pipeline'!$V$1:$V$860,$U78))>0,LEFT(INDEX('MiT Strom Pipeline'!$V$1:$V$860,$U78),55),"")) -> Kunde wahr sehr Zufrieden mit dem 1. Auftrag und im Ans | M78: =IF($U78="","",IF(INDEX('MiT Strom Pipeline'!$AF$1:$AF$860,$U78)="","",INDEX('MiT Strom Pipeline'!$AF$1:$AF$860,$U78))) | N78: =IF($U78="","",IF(INDEX('MiT Strom Pipeline'!$BB$1:$BB$860,$U78)="","",INDEX('MiT Strom Pipeline'!$BB$1:$BB$860,$U78))) -> ○ Zeitraum offen | U78: =IFERROR(MATCH(4,'MiT Strom Pipeline'!$AN$6:$AN$860,0)+5,"") -> 17
A79: =IF($U79="","",IF(ISNUMBER(INDEX('MiT Strom Pipeline'!$A$1:$A$860,$U79)),INDEX('MiT Strom Pipeline'!$A$1:$A$860,$U79),"")) -> 13 | B79: =IF($U79="","",IF(INDEX('MiT Strom Pipeline'!$B$1:$B$860,$U79)="","",INDEX('MiT Strom Pipeline'!$B$1:$B$860,$U79))) -> Proxima Fusion AG | C79: =IF($U79="","",IF(INDEX('MiT Strom Pipeline'!$C$1:$C$860,$U79)="","",INDEX('MiT Strom Pipeline'!$C$1:$C$860,$U79))) -> ZH | D79: =IF($U79="","",IF(INDEX('MiT Strom Pipeline'!$D$1:$D$860,$U79)="","",INDEX('MiT Strom Pipeline'!$D$1:$D$860,$U79))) -> Forschung / Hightech | E79: =IF($U79="","",IF(ISNUMBER(INDEX('MiT Strom Pipeline'!$O$1:$O$860,$U79)),INDEX('MiT Strom Pipeline'!$O$1:$O$860,$U79),IF(INDEX('MiT Strom Pipeline'!$H$1:$H$860,$U79)="","",INDEX('MiT Strom Pipeline'!$H$1:$H$860,$U79)))) -> Juli | F79: =IF($U79="","",IF(ISNUMBER(INDEX('MiT Strom Pipeline'!$P$1:$P$860,$U79)),INDEX('MiT Strom Pipeline'!$P$1:$P$860,$U79),"")) | G79: =IF($U79="","",IF(ISNUMBER(INDEX('MiT Strom Pipeline'!$I$1:$I$860,$U79)),INDEX('MiT Strom Pipeline'!$I$1:$I$860,$U79),0)) -> 365003 | H79: =IF($U79="","",IF(ISNUMBER(INDEX('MiT Strom Pipeline'!$Q$1:$Q$860,$U79)),INDEX('MiT Strom Pipeline'!$Q$1:$Q$860,$U79),0)) -> 0 | I79: =IF($U79="","",IF(INDEX('MiT Strom Pipeline'!$E$1:$E$860,$U79)="","",INDEX('MiT Strom Pipeline'!$E$1:$E$860,$U79))) -> BESS 1 MWh | J79: =IF($U79="","",INDEX('MiT Strom Pipeline'!$R$1:$R$860,$U79)) -> offered | K79: =IF($U79="","",IF(ISNUMBER(INDEX('MiT Strom Pipeline'!$S$1:$S$860,$U79)),INDEX('MiT Strom Pipeline'!$S$1:$S$860,$U79),"")) -> 0.3 | L79: =IF($U79="","",IF(LEN(INDEX('MiT Strom Pipeline'!$V$1:$V$860,$U79))>0,LEFT(INDEX('MiT Strom Pipeline'!$V$1:$V$860,$U79),55),"")) -> Technisches Gespräch – USV + PQ-Anforderungen klären, K | M79: =IF($U79="","",IF(INDEX('MiT Strom Pipeline'!$AF$1:$AF$860,$U79)="","",INDEX('MiT Strom Pipeline'!$AF$1:$AF$860,$U79))) | N79: =IF($U79="","",IF(INDEX('MiT Strom Pipeline'!$BB$1:$BB$860,$U79)="","",INDEX('MiT Strom Pipeline'!$BB$1:$BB$860,$U79))) -> ○ Zeitraum offen | U79: =IFERROR(MATCH(5,'MiT Strom Pipeline'!$AN$6:$AN$860,0)+5,"") -> 18
A80: =IF($U80="","",IF(ISNUMBER(INDEX('MiT Strom Pipeline'!$A$1:$A$860,$U80)),INDEX('MiT Strom Pipeline'!$A$1:$A$860,$U80),"")) -> 25 | B80: =IF($U80="","",IF(INDEX('MiT Strom Pipeline'!$B$1:$B$860,$U80)="","",INDEX('MiT Strom Pipeline'!$B$1:$B$860,$U80))) -> Reto EKAG | C80: =IF($U80="","",IF(INDEX('MiT Strom Pipeline'!$C$1:$C$860,$U80)="","",INDEX('MiT Strom Pipeline'!$C$1:$C$860,$U80))) -> AG | D80: =IF($U80="","",IF(INDEX('MiT Strom Pipeline'!$D$1:$D$860,$U80)="","",INDEX('MiT Strom Pipeline'!$D$1:$D$860,$U80))) -> Elektroinstallation | E80: =IF($U80="","",IF(ISNUMBER(INDEX('MiT Strom Pipeline'!$O$1:$O$860,$U80)),INDEX('MiT Strom Pipeline'!$O$1:$O$860,$U80),IF(INDEX('MiT Strom Pipeline'!$H$1:$H$860,$U80)="","",INDEX('MiT Strom Pipeline'!$H$1:$H$860,$U80)))) -> Okt | F80: =IF($U80="","",IF(ISNUMBER(INDEX('MiT Strom Pipeline'!$P$1:$P$860,$U80)),INDEX('MiT Strom Pipeline'!$P$1:$P$860,$U80),"")) | G80: =IF($U80="","",IF(ISNUMBER(INDEX('MiT Strom Pipeline'!$I$1:$I$860,$U80)),INDEX('MiT Strom Pipeline'!$I$1:$I$860,$U80),0)) -> 57249.54 | H80: =IF($U80="","",IF(ISNUMBER(INDEX('MiT Strom Pipeline'!$Q$1:$Q$860,$U80)),INDEX('MiT Strom Pipeline'!$Q$1:$Q$860,$U80),0)) -> 51524.586 | I80: =IF($U80="","",IF(INDEX('MiT Strom Pipeline'!$E$1:$E$860,$U80)="","",INDEX('MiT Strom Pipeline'!$E$1:$E$860,$U80))) -> Option B 1x 6 kVA Trafo, 1x 3000 kVA Trafo, 1x 6000 kVA Lastbank, 1x 3300 kVA Lastbank | J80: =IF($U80="","",INDEX('MiT Strom Pipeline'!$R$1:$R$860,$U80)) -> offered | K80: =IF($U80="","",IF(ISNUMBER(INDEX('MiT Strom Pipeline'!$S$1:$S$860,$U80)),INDEX('MiT Strom Pipeline'!$S$1:$S$860,$U80),"")) -> 0.9 | L80: =IF($U80="","",IF(LEN(INDEX('MiT Strom Pipeline'!$V$1:$V$860,$U80))>0,LEFT(INDEX('MiT Strom Pipeline'!$V$1:$V$860,$U80),55),"")) -> Kunde Telefon Kontaktiert und Vor Ort Besichtigung und | M80: =IF($U80="","",IF(INDEX('MiT Strom Pipeline'!$AF$1:$AF$860,$U80)="","",INDEX('MiT Strom Pipeline'!$AF$1:$AF$860,$U80))) | N80: =IF($U80="","",IF(INDEX('MiT Strom Pipeline'!$BB$1:$BB$860,$U80)="","",INDEX('MiT Strom Pipeline'!$BB$1:$BB$860,$U80))) -> ○ Zeitraum offen | U80: =IFERROR(MATCH(6,'MiT Strom Pipeline'!$AN$6:$AN$860,0)+5,"") -> 19
A81: =IF($U81="","",IF(ISNUMBER(INDEX('MiT Strom Pipeline'!$A$1:$A$860,$U81)),INDEX('MiT Strom Pipeline'!$A$1:$A$860,$U81),"")) -> 25 | B81: =IF($U81="","",IF(INDEX('MiT Strom Pipeline'!$B$1:$B$860,$U81)="","",INDEX('MiT Strom Pipeline'!$B$1:$B$860,$U81))) -> Reto EKAG | C81: =IF($U81="","",IF(INDEX('MiT Strom Pipeline'!$C$1:$C$860,$U81)="","",INDEX('MiT Strom Pipeline'!$C$1:$C$860,$U81))) -> AG | D81: =IF($U81="","",IF(INDEX('MiT Strom Pipeline'!$D$1:$D$860,$U81)="","",INDEX('MiT Strom Pipeline'!$D$1:$D$860,$U81))) -> Elektroinstallation | E81: =IF($U81="","",IF(ISNUMBER(INDEX('MiT Strom Pipeline'!$O$1:$O$860,$U81)),INDEX('MiT Strom Pipeline'!$O$1:$O$860,$U81),IF(INDEX('MiT Strom Pipeline'!$H$1:$H$860,$U81)="","",INDEX('MiT Strom Pipeline'!$H$1:$H$860,$U81)))) -> Okt | F81: =IF($U81="","",IF(ISNUMBER(INDEX('MiT Strom Pipeline'!$P$1:$P$860,$U81)),INDEX('MiT Strom Pipeline'!$P$1:$P$860,$U81),"")) | G81: =IF($U81="","",IF(ISNUMBER(INDEX('MiT Strom Pipeline'!$I$1:$I$860,$U81)),INDEX('MiT Strom Pipeline'!$I$1:$I$860,$U81),0)) -> 15664.18 | H81: =IF($U81="","",IF(ISNUMBER(INDEX('MiT Strom Pipeline'!$Q$1:$Q$860,$U81)),INDEX('MiT Strom Pipeline'!$Q$1:$Q$860,$U81),0)) -> 14097.762 | I81: =IF($U81="","",IF(INDEX('MiT Strom Pipeline'!$E$1:$E$860,$U81)="","",INDEX('MiT Strom Pipeline'!$E$1:$E$860,$U81))) -> MS Kabel 95mm | J81: =IF($U81="","",INDEX('MiT Strom Pipeline'!$R$1:$R$860,$U81)) -> offered | K81: =IF($U81="","",IF(ISNUMBER(INDEX('MiT Strom Pipeline'!$S$1:$S$860,$U81)),INDEX('MiT Strom Pipeline'!$S$1:$S$860,$U81),"")) -> 0.9 | L81: =IF($U81="","",IF(LEN(INDEX('MiT Strom Pipeline'!$V$1:$V$860,$U81))>0,LEFT(INDEX('MiT Strom Pipeline'!$V$1:$V$860,$U81),55),"")) -> Kunde Telefon Kontaktiert und Vor Ort Besichtigung und | M81: =IF($U81="","",IF(INDEX('MiT Strom Pipeline'!$AF$1:$AF$860,$U81)="","",INDEX('MiT Strom Pipeline'!$AF$1:$AF$860,$U81))) | N81: =IF($U81="","",IF(INDEX('MiT Strom Pipeline'!$BB$1:$BB$860,$U81)="","",INDEX('MiT Strom Pipeline'!$BB$1:$BB$860,$U81))) -> ○ Zeitraum offen | U81: =IFERROR(MATCH(7,'MiT Strom Pipeline'!$AN$6:$AN$860,0)+5,"") -> 20
A82: =IF($U82="","",IF(ISNUMBER(INDEX('MiT Strom Pipeline'!$A$1:$A$860,$U82)),INDEX('MiT Strom Pipeline'!$A$1:$A$860,$U82),"")) -> 28 | B82: =IF($U82="","",IF(INDEX('MiT Strom Pipeline'!$B$1:$B$860,$U82)="","",INDEX('MiT Strom Pipeline'!$B$1:$B$860,$U82))) -> WEF | C82: =IF($U82="","",IF(INDEX('MiT Strom Pipeline'!$C$1:$C$860,$U82)="","",INDEX('MiT Strom Pipeline'!$C$1:$C$860,$U82))) -> GR | D82: =IF($U82="","",IF(INDEX('MiT Strom Pipeline'!$D$1:$D$860,$U82)="","",INDEX('MiT Strom Pipeline'!$D$1:$D$860,$U82))) -> Event | E82: =IF($U82="","",IF(ISNUMBER(INDEX('MiT Strom Pipeline'!$O$1:$O$860,$U82)),INDEX('MiT Strom Pipeline'!$O$1:$O$860,$U82),IF(INDEX('MiT Strom Pipeline'!$H$1:$H$860,$U82)="","",INDEX('MiT Strom Pipeline'!$H$1:$H$860,$U82)))) -> Jan | F82: =IF($U82="","",IF(ISNUMBER(INDEX('MiT Strom Pipeline'!$P$1:$P$860,$U82)),INDEX('MiT Strom Pipeline'!$P$1:$P$860,$U82),"")) | G82: =IF($U82="","",IF(ISNUMBER(INDEX('MiT Strom Pipeline'!$I$1:$I$860,$U82)),INDEX('MiT Strom Pipeline'!$I$1:$I$860,$U82),0)) -> 77325.62 | H82: =IF($U82="","",IF(ISNUMBER(INDEX('MiT Strom Pipeline'!$Q$1:$Q$860,$U82)),INDEX('MiT Strom Pipeline'!$Q$1:$Q$860,$U82),0)) -> 0 | I82: =IF($U82="","",IF(INDEX('MiT Strom Pipeline'!$E$1:$E$860,$U82)="","",INDEX('MiT Strom Pipeline'!$E$1:$E$860,$U82))) -> 1500 kVA, 600 kVA, 450 kVA, 450 kVA | J82: =IF($U82="","",INDEX('MiT Strom Pipeline'!$R$1:$R$860,$U82)) -> offered | K82: =IF($U82="","",IF(ISNUMBER(INDEX('MiT Strom Pipeline'!$S$1:$S$860,$U82)),INDEX('MiT Strom Pipeline'!$S$1:$S$860,$U82),"")) -> 0.3 | L82: =IF($U82="","",IF(LEN(INDEX('MiT Strom Pipeline'!$V$1:$V$860,$U82))>0,LEFT(INDEX('MiT Strom Pipeline'!$V$1:$V$860,$U82),55),"")) -> Offerte erstellt, Stefan hat die Offerte bekommen, Stef | M82: =IF($U82="","",IF(INDEX('MiT Strom Pipeline'!$AF$1:$AF$860,$U82)="","",INDEX('MiT Strom Pipeline'!$AF$1:$AF$860,$U82))) | N82: =IF($U82="","",IF(INDEX('MiT Strom Pipeline'!$BB$1:$BB$860,$U82)="","",INDEX('MiT Strom Pipeline'!$BB$1:$BB$860,$U82))) -> ○ Einstand offen | U82: =IFERROR(MATCH(8,'MiT Strom Pipeline'!$AN$6:$AN$860,0)+5,"") -> 21
A83: =IF($U83="","",IF(ISNUMBER(INDEX('MiT Strom Pipeline'!$A$1:$A$860,$U83)),INDEX('MiT Strom Pipeline'!$A$1:$A$860,$U83),"")) -> 8 | B83: =IF($U83="","",IF(INDEX('MiT Strom Pipeline'!$B$1:$B$860,$U83)="","",INDEX('MiT Strom Pipeline'!$B$1:$B$860,$U83))) -> Sade CGTH (Schweiz) | C83: =IF($U83="","",IF(INDEX('MiT Strom Pipeline'!$C$1:$C$860,$U83)="","",INDEX('MiT Strom Pipeline'!$C$1:$C$860,$U83))) -> GE | D83: =IF($U83="","",IF(INDEX('MiT Strom Pipeline'!$D$1:$D$860,$U83)="","",INDEX('MiT Strom Pipeline'!$D$1:$D$860,$U83))) -> Infrastruktur / Bau | E83: =IF($U83="","",IF(ISNUMBER(INDEX('MiT Strom Pipeline'!$O$1:$O$860,$U83)),INDEX('MiT Strom Pipeline'!$O$1:$O$860,$U83),IF(INDEX('MiT Strom Pipeline'!$H$1:$H$860,$U83)="","",INDEX('MiT Strom Pipeline'!$H$1:$H$860,$U83)))) -> April | F83: =IF($U83="","",IF(ISNUMBER(INDEX('MiT Strom Pipeline'!$P$1:$P$860,$U83)),INDEX('MiT Strom Pipeline'!$P$1:$P$860,$U83),"")) | G83: =IF($U83="","",IF(ISNUMBER(INDEX('MiT Strom Pipeline'!$I$1:$I$860,$U83)),INDEX('MiT Strom Pipeline'!$I$1:$I$860,$U83),0)) -> 38885 | H83: =IF($U83="","",IF(ISNUMBER(INDEX('MiT Strom Pipeline'!$Q$1:$Q$860,$U83)),INDEX('MiT Strom Pipeline'!$Q$1:$Q$860,$U83),0)) -> 0 | I83: =IF($U83="","",IF(INDEX('MiT Strom Pipeline'!$E$1:$E$860,$U83)="","",INDEX('MiT Strom Pipeline'!$E$1:$E$860,$U83))) -> 750 kVA Generator | J83: =IF($U83="","",INDEX('MiT Strom Pipeline'!$R$1:$R$860,$U83)) -> on hold | K83: =IF($U83="","",IF(ISNUMBER(INDEX('MiT Strom Pipeline'!$S$1:$S$860,$U83)),INDEX('MiT Strom Pipeline'!$S$1:$S$860,$U83),"")) -> 0.3 | L83: =IF($U83="","",IF(LEN(INDEX('MiT Strom Pipeline'!$V$1:$V$860,$U83))>0,LEFT(INDEX('MiT Strom Pipeline'!$V$1:$V$860,$U83),55),"")) -> Auftragsbestätigung anfordern – Entscheid steht bevor | M83: =IF($U83="","",IF(INDEX('MiT Strom Pipeline'!$AF$1:$AF$860,$U83)="","",INDEX('MiT Strom Pipeline'!$AF$1:$AF$860,$U83))) | N83: =IF($U83="","",IF(INDEX('MiT Strom Pipeline'!$BB$1:$BB$860,$U83)="","",INDEX('MiT Strom Pipeline'!$BB$1:$BB$860,$U83))) -> ○ Zeitraum offen | U83: =IFERROR(MATCH(9,'MiT Strom Pipeline'!$AN$6:$AN$860,0)+5,"") -> 28
A84: =IF($U84="","",IF(ISNUMBER(INDEX('MiT Strom Pipeline'!$A$1:$A$860,$U84)),INDEX('MiT Strom Pipeline'!$A$1:$A$860,$U84),"")) -> 14 | B84: =IF($U84="","",IF(INDEX('MiT Strom Pipeline'!$B$1:$B$860,$U84)="","",INDEX('MiT Strom Pipeline'!$B$1:$B$860,$U84))) -> Trafag AG | C84: =IF($U84="","",IF(INDEX('MiT Strom Pipeline'!$C$1:$C$860,$U84)="","",INDEX('MiT Strom Pipeline'!$C$1:$C$860,$U84))) -> ZH | D84: =IF($U84="","",IF(INDEX('MiT Strom Pipeline'!$D$1:$D$860,$U84)="","",INDEX('MiT Strom Pipeline'!$D$1:$D$860,$U84))) -> Industrie / Messtechnik | E84: =IF($U84="","",IF(ISNUMBER(INDEX('MiT Strom Pipeline'!$O$1:$O$860,$U84)),INDEX('MiT Strom Pipeline'!$O$1:$O$860,$U84),IF(INDEX('MiT Strom Pipeline'!$H$1:$H$860,$U84)="","",INDEX('MiT Strom Pipeline'!$H$1:$H$860,$U84)))) -> tbd | F84: =IF($U84="","",IF(ISNUMBER(INDEX('MiT Strom Pipeline'!$P$1:$P$860,$U84)),INDEX('MiT Strom Pipeline'!$P$1:$P$860,$U84),"")) | G84: =IF($U84="","",IF(ISNUMBER(INDEX('MiT Strom Pipeline'!$I$1:$I$860,$U84)),INDEX('MiT Strom Pipeline'!$I$1:$I$860,$U84),0)) -> 17300 | H84: =IF($U84="","",IF(ISNUMBER(INDEX('MiT Strom Pipeline'!$Q$1:$Q$860,$U84)),INDEX('MiT Strom Pipeline'!$Q$1:$Q$860,$U84),0)) -> 0 | I84: =IF($U84="","",IF(INDEX('MiT Strom Pipeline'!$E$1:$E$860,$U84)="","",INDEX('MiT Strom Pipeline'!$E$1:$E$860,$U84))) -> 450 kVA Generator | J84: =IF($U84="","",INDEX('MiT Strom Pipeline'!$R$1:$R$860,$U84)) -> offered | K84: =IF($U84="","",IF(ISNUMBER(INDEX('MiT Strom Pipeline'!$S$1:$S$860,$U84)),INDEX('MiT Strom Pipeline'!$S$1:$S$860,$U84),"")) -> 0.3 | L84: =IF($U84="","",IF(LEN(INDEX('MiT Strom Pipeline'!$V$1:$V$860,$U84))>0,LEFT(INDEX('MiT Strom Pipeline'!$V$1:$V$860,$U84),55),"")) -> Angebot vorbereiten – PQ-Argument für Messtechnik, Stef | M84: =IF($U84="","",IF(INDEX('MiT Strom Pipeline'!$AF$1:$AF$860,$U84)="","",INDEX('MiT Strom Pipeline'!$AF$1:$AF$860,$U84))) | N84: =IF($U84="","",IF(INDEX('MiT Strom Pipeline'!$BB$1:$BB$860,$U84)="","",INDEX('MiT Strom Pipeline'!$BB$1:$BB$860,$U84))) -> ○ Einstand offen | U84: =IFERROR(MATCH(10,'MiT Strom Pipeline'!$AN$6:$AN$860,0)+5,"") -> 33
A85: =IF($U85="","",IF(ISNUMBER(INDEX('MiT Strom Pipeline'!$A$1:$A$860,$U85)),INDEX('MiT Strom Pipeline'!$A$1:$A$860,$U85),"")) -> 14 | B85: =IF($U85="","",IF(INDEX('MiT Strom Pipeline'!$B$1:$B$860,$U85)="","",INDEX('MiT Strom Pipeline'!$B$1:$B$860,$U85))) -> Trafag AG | C85: =IF($U85="","",IF(INDEX('MiT Strom Pipeline'!$C$1:$C$860,$U85)="","",INDEX('MiT Strom Pipeline'!$C$1:$C$860,$U85))) -> ZH | D85: =IF($U85="","",IF(INDEX('MiT Strom Pipeline'!$D$1:$D$860,$U85)="","",INDEX('MiT Strom Pipeline'!$D$1:$D$860,$U85))) -> Industrie / Messtechnik | E85: =IF($U85="","",IF(ISNUMBER(INDEX('MiT Strom Pipeline'!$O$1:$O$860,$U85)),INDEX('MiT Strom Pipeline'!$O$1:$O$860,$U85),IF(INDEX('MiT Strom Pipeline'!$H$1:$H$860,$U85)="","",INDEX('MiT Strom Pipeline'!$H$1:$H$860,$U85)))) -> tbd | F85: =IF($U85="","",IF(ISNUMBER(INDEX('MiT Strom Pipeline'!$P$1:$P$860,$U85)),INDEX('MiT Strom Pipeline'!$P$1:$P$860,$U85),"")) | G85: =IF($U85="","",IF(ISNUMBER(INDEX('MiT Strom Pipeline'!$I$1:$I$860,$U85)),INDEX('MiT Strom Pipeline'!$I$1:$I$860,$U85),0)) -> 21025 | H85: =IF($U85="","",IF(ISNUMBER(INDEX('MiT Strom Pipeline'!$Q$1:$Q$860,$U85)),INDEX('MiT Strom Pipeline'!$Q$1:$Q$860,$U85),0)) -> 0 | I85: =IF($U85="","",IF(INDEX('MiT Strom Pipeline'!$E$1:$E$860,$U85)="","",INDEX('MiT Strom Pipeline'!$E$1:$E$860,$U85))) -> BESS 500 kVA | J85: =IF($U85="","",INDEX('MiT Strom Pipeline'!$R$1:$R$860,$U85)) -> offered | K85: =IF($U85="","",IF(ISNUMBER(INDEX('MiT Strom Pipeline'!$S$1:$S$860,$U85)),INDEX('MiT Strom Pipeline'!$S$1:$S$860,$U85),"")) -> 0.3 | L85: =IF($U85="","",IF(LEN(INDEX('MiT Strom Pipeline'!$V$1:$V$860,$U85))>0,LEFT(INDEX('MiT Strom Pipeline'!$V$1:$V$860,$U85),55),"")) -> Angebot vorbereiten – PQ-Argument für Messtechnik, Stef | M85: =IF($U85="","",IF(INDEX('MiT Strom Pipeline'!$AF$1:$AF$860,$U85)="","",INDEX('MiT Strom Pipeline'!$AF$1:$AF$860,$U85))) | N85: =IF($U85="","",IF(INDEX('MiT Strom Pipeline'!$BB$1:$BB$860,$U85)="","",INDEX('MiT Strom Pipeline'!$BB$1:$BB$860,$U85))) -> ○ Einstand offen | U85: =IFERROR(MATCH(11,'MiT Strom Pipeline'!$AN$6:$AN$860,0)+5,"") -> 35
A86: =IF($U86="","",IF(ISNUMBER(INDEX('MiT Strom Pipeline'!$A$1:$A$860,$U86)),INDEX('MiT Strom Pipeline'!$A$1:$A$860,$U86),"")) -> 14 | B86: =IF($U86="","",IF(INDEX('MiT Strom Pipeline'!$B$1:$B$860,$U86)="","",INDEX('MiT Strom Pipeline'!$B$1:$B$860,$U86))) -> Trafag AG | C86: =IF($U86="","",IF(INDEX('MiT Strom Pipeline'!$C$1:$C$860,$U86)="","",INDEX('MiT Strom Pipeline'!$C$1:$C$860,$U86))) -> ZH | D86: =IF($U86="","",IF(INDEX('MiT Strom Pipeline'!$D$1:$D$860,$U86)="","",INDEX('MiT Strom Pipeline'!$D$1:$D$860,$U86))) -> Industrie / Messtechnik | E86: =IF($U86="","",IF(ISNUMBER(INDEX('MiT Strom Pipeline'!$O$1:$O$860,$U86)),INDEX('MiT Strom Pipeline'!$O$1:$O$860,$U86),IF(INDEX('MiT Strom Pipeline'!$H$1:$H$860,$U86)="","",INDEX('MiT Strom Pipeline'!$H$1:$H$860,$U86)))) -> tbd | F86: =IF($U86="","",IF(ISNUMBER(INDEX('MiT Strom Pipeline'!$P$1:$P$860,$U86)),INDEX('MiT Strom Pipeline'!$P$1:$P$860,$U86),"")) | G86: =IF($U86="","",IF(ISNUMBER(INDEX('MiT Strom Pipeline'!$I$1:$I$860,$U86)),INDEX('MiT Strom Pipeline'!$I$1:$I$860,$U86),0)) -> 37444 | H86: =IF($U86="","",IF(ISNUMBER(INDEX('MiT Strom Pipeline'!$Q$1:$Q$860,$U86)),INDEX('MiT Strom Pipeline'!$Q$1:$Q$860,$U86),0)) -> 0 | I86: =IF($U86="","",IF(INDEX('MiT Strom Pipeline'!$E$1:$E$860,$U86)="","",INDEX('MiT Strom Pipeline'!$E$1:$E$860,$U86))) -> Kombi 450 kVA Generator / BESS 500 kVA | J86: =IF($U86="","",INDEX('MiT Strom Pipeline'!$R$1:$R$860,$U86)) -> offered | K86: =IF($U86="","",IF(ISNUMBER(INDEX('MiT Strom Pipeline'!$S$1:$S$860,$U86)),INDEX('MiT Strom Pipeline'!$S$1:$S$860,$U86),"")) -> 0.3 | L86: =IF($U86="","",IF(LEN(INDEX('MiT Strom Pipeline'!$V$1:$V$860,$U86))>0,LEFT(INDEX('MiT Strom Pipeline'!$V$1:$V$860,$U86),55),"")) -> Angebot vorbereiten – PQ-Argument für Messtechnik, Stef | M86: =IF($U86="","",IF(INDEX('MiT Strom Pipeline'!$AF$1:$AF$860,$U86)="","",INDEX('MiT Strom Pipeline'!$AF$1:$AF$860,$U86))) | N86: =IF($U86="","",IF(INDEX('MiT Strom Pipeline'!$BB$1:$BB$860,$U86)="","",INDEX('MiT Strom Pipeline'!$BB$1:$BB$860,$U86))) -> ○ Einstand offen | U86: =IFERROR(MATCH(12,'MiT Strom Pipeline'!$AN$6:$AN$860,0)+5,"") -> 36
A87: =IF($U87="","",IF(ISNUMBER(INDEX('MiT Strom Pipeline'!$A$1:$A$860,$U87)),INDEX('MiT Strom Pipeline'!$A$1:$A$860,$U87),"")) -> 27 | B87: =IF($U87="","",IF(INDEX('MiT Strom Pipeline'!$B$1:$B$860,$U87)="","",INDEX('MiT Strom Pipeline'!$B$1:$B$860,$U87))) -> Rimus & Sstrada | C87: =IF($U87="","",IF(INDEX('MiT Strom Pipeline'!$C$1:$C$860,$U87)="","",INDEX('MiT Strom Pipeline'!$C$1:$C$860,$U87))) -> SH | D87: =IF($U87="","",IF(INDEX('MiT Strom Pipeline'!$D$1:$D$860,$U87)="","",INDEX('MiT Strom Pipeline'!$D$1:$D$860,$U87))) -> Industrie | E87: =IF($U87="","",IF(ISNUMBER(INDEX('MiT Strom Pipeline'!$O$1:$O$860,$U87)),INDEX('MiT Strom Pipeline'!$O$1:$O$860,$U87),IF(INDEX('MiT Strom Pipeline'!$H$1:$H$860,$U87)="","",INDEX('MiT Strom Pipeline'!$H$1:$H$860,$U87)))) -> tbd | F87: =IF($U87="","",IF(ISNUMBER(INDEX('MiT Strom Pipeline'!$P$1:$P$860,$U87)),INDEX('MiT Strom Pipeline'!$P$1:$P$860,$U87),"")) | G87: =IF($U87="","",IF(ISNUMBER(INDEX('MiT Strom Pipeline'!$I$1:$I$860,$U87)),INDEX('MiT Strom Pipeline'!$I$1:$I$860,$U87),0)) -> 425955 | H87: =IF($U87="","",IF(ISNUMBER(INDEX('MiT Strom Pipeline'!$Q$1:$Q$860,$U87)),INDEX('MiT Strom Pipeline'!$Q$1:$Q$860,$U87),0)) -> 0 | I87: =IF($U87="","",IF(INDEX('MiT Strom Pipeline'!$E$1:$E$860,$U87)="","",INDEX('MiT Strom Pipeline'!$E$1:$E$860,$U87))) -> 500 kWh Small BESS | J87: =IF($U87="","",INDEX('MiT Strom Pipeline'!$R$1:$R$860,$U87)) -> offered | K87: =IF($U87="","",IF(ISNUMBER(INDEX('MiT Strom Pipeline'!$S$1:$S$860,$U87)),INDEX('MiT Strom Pipeline'!$S$1:$S$860,$U87),"")) -> 0.3 | L87: =IF($U87="","",IF(LEN(INDEX('MiT Strom Pipeline'!$V$1:$V$860,$U87))>0,LEFT(INDEX('MiT Strom Pipeline'!$V$1:$V$860,$U87),55),"")) -> Kunde Telefon Kontaktiert und Vor Ort Besichtigung und | M87: =IF($U87="","",IF(INDEX('MiT Strom Pipeline'!$AF$1:$AF$860,$U87)="","",INDEX('MiT Strom Pipeline'!$AF$1:$AF$860,$U87))) | N87: =IF($U87="","",IF(INDEX('MiT Strom Pipeline'!$BB$1:$BB$860,$U87)="","",INDEX('MiT Strom Pipeline'!$BB$1:$BB$860,$U87))) -> ○ Zeitraum offen | U87: =IFERROR(MATCH(13,'MiT Strom Pipeline'!$AN$6:$AN$860,0)+5,"") -> 37
