Workbook

Sheet 📑 Executive PDF
A1: ⚡ MiT Strom Schweiz — Executive Sales Summary
A2: Mobil in Time AG · An Aggreko Company · Burak Ücöz
A3: ="Stand: "&TEXT(TODAY(),"DD.MM.YYYY")&" · Live aus Pipeline" -> Stand: DD.08.YYYY · Live aus Pipeline
B5: ✅ WON | E5: 📄 OFFERTE | G5: 🎯 OPPORTUNITÄT
B6: =Dashboard!A6 -> 1428553.1 | E6: =Dashboard!D6 -> 5433596.1 | G6: =Dashboard!G6 -> 0
B8: =Dashboard!A7&" Deals" -> 12 Deals | E8: =Dashboard!D7&" Deals" -> 33 Deals | G8: =Dashboard!G7&" Deals" -> 1 Deals
B10: ="📊 GESAMT-PIPELINE: "&TEXT(Dashboard!I6,"#,##0")&" CHF · "&Dashboard!I7&" aktive Deals" -> 📊 GESAMT-PIPELINE: 6862149,230 CHF · 46 aktive Deals
B12: 🏆 Top 5 WON-Deals (nach Volumen)
B13: # | C13: Kunde | D13: Kt. | E13: Start | F13: Segment | G13: Volumen | H13: Marge
B14: 1 | C14: =IFERROR(INDEX('MiT Strom Pipeline'!B6:B860,MATCH(LARGE('MiT Strom Pipeline'!Z6:Z860,1),'MiT Strom Pipeline'!Z6:Z860,0)),"") -> Ice Hockey Championship | D14: =IFERROR(INDEX('MiT Strom Pipeline'!C6:C860,MATCH(LARGE('MiT Strom Pipeline'!Z6:Z860,1),'MiT Strom Pipeline'!Z6:Z860,0)),"") -> ZH | E14: =IFERROR(INDEX('MiT Strom Pipeline'!H6:H860,MATCH(LARGE('MiT Strom Pipeline'!Z6:Z860,1),'MiT Strom Pipeline'!Z6:Z860,0)),"") -> Mai | F14: =IFERROR(INDEX('MiT Strom Pipeline'!D6:D860,MATCH(LARGE('MiT Strom Pipeline'!Z6:Z860,1),'MiT Strom Pipeline'!Z6:Z860,0)),"") -> Events & Sport | G14: =IFERROR(INDEX('MiT Strom Pipeline'!I6:I860,MATCH(LARGE('MiT Strom Pipeline'!Z6:Z860,1),'MiT Strom Pipeline'!Z6:Z860,0)),"") -> 380000 | H14: =IFERROR(INDEX('MiT Strom Pipeline'!O6:O860,MATCH(LARGE('MiT Strom Pipeline'!Z6:Z860,1),'MiT Strom Pipeline'!Z6:Z860,0)),"") -> 145000
B15: 2 | C15: =IFERROR(INDEX('MiT Strom Pipeline'!B6:B860,MATCH(LARGE('MiT Strom Pipeline'!Z6:Z860,2),'MiT Strom Pipeline'!Z6:Z860,0)),"") -> DPR Heat Loadbank | D15: =IFERROR(INDEX('MiT Strom Pipeline'!C6:C860,MATCH(LARGE('MiT Strom Pipeline'!Z6:Z860,2),'MiT Strom Pipeline'!Z6:Z860,0)),"") -> ZH | E15: =IFERROR(INDEX('MiT Strom Pipeline'!H6:H860,MATCH(LARGE('MiT Strom Pipeline'!Z6:Z860,2),'MiT Strom Pipeline'!Z6:Z860,0)),"") -> Aug | F15: =IFERROR(INDEX('MiT Strom Pipeline'!D6:D860,MATCH(LARGE('MiT Strom Pipeline'!Z6:Z860,2),'MiT Strom Pipeline'!Z6:Z860,0)),"") -> Datacenter | G15: =IFERROR(INDEX('MiT Strom Pipeline'!I6:I860,MATCH(LARGE('MiT Strom Pipeline'!Z6:Z860,2),'MiT Strom Pipeline'!Z6:Z860,0)),"") -> 333790 | H15: =IFERROR(INDEX('MiT Strom Pipeline'!O6:O860,MATCH(LARGE('MiT Strom Pipeline'!Z6:Z860,2),'MiT Strom Pipeline'!Z6:Z860,0)),"") -> -25011.09
B16: 3 | C16: =IFERROR(INDEX('MiT Strom Pipeline'!B6:B860,MATCH(LARGE('MiT Strom Pipeline'!Z6:Z860,3),'MiT Strom Pipeline'!Z6:Z860,0)),"") -> DPR Generator Loadbank Test | D16: =IFERROR(INDEX('MiT Strom Pipeline'!C6:C860,MATCH(LARGE('MiT Strom Pipeline'!Z6:Z860,3),'MiT Strom Pipeline'!Z6:Z860,0)),"") -> ZH | E16: =IFERROR(INDEX('MiT Strom Pipeline'!H6:H860,MATCH(LARGE('MiT Strom Pipeline'!Z6:Z860,3),'MiT Strom Pipeline'!Z6:Z860,0)),"") -> Aug | F16: =IFERROR(INDEX('MiT Strom Pipeline'!D6:D860,MATCH(LARGE('MiT Strom Pipeline'!Z6:Z860,3),'MiT Strom Pipeline'!Z6:Z860,0)),"") -> Datacenter | G16: =IFERROR(INDEX('MiT Strom Pipeline'!I6:I860,MATCH(LARGE('MiT Strom Pipeline'!Z6:Z860,3),'MiT Strom Pipeline'!Z6:Z860,0)),"") -> 331889.15 | H16: =IFERROR(INDEX('MiT Strom Pipeline'!O6:O860,MATCH(LARGE('MiT Strom Pipeline'!Z6:Z860,3),'MiT Strom Pipeline'!Z6:Z860,0)),"") -> -24868.66
B17: 4 | C17: =IFERROR(INDEX('MiT Strom Pipeline'!B6:B860,MATCH(LARGE('MiT Strom Pipeline'!Z6:Z860,4),'MiT Strom Pipeline'!Z6:Z860,0)),"") -> Stagelight – OpenAir Frauenfeld | D17: =IFERROR(INDEX('MiT Strom Pipeline'!C6:C860,MATCH(LARGE('MiT Strom Pipeline'!Z6:Z860,4),'MiT Strom Pipeline'!Z6:Z860,0)),"") -> TG | E17: =IFERROR(INDEX('MiT Strom Pipeline'!H6:H860,MATCH(LARGE('MiT Strom Pipeline'!Z6:Z860,4),'MiT Strom Pipeline'!Z6:Z860,0)),"") -> Juli | F17: =IFERROR(INDEX('MiT Strom Pipeline'!D6:D860,MATCH(LARGE('MiT Strom Pipeline'!Z6:Z860,4),'MiT Strom Pipeline'!Z6:Z860,0)),"") -> Events & Kultur | G17: =IFERROR(INDEX('MiT Strom Pipeline'!I6:I860,MATCH(LARGE('MiT Strom Pipeline'!Z6:Z860,4),'MiT Strom Pipeline'!Z6:Z860,0)),"") -> 150000 | H17: =IFERROR(INDEX('MiT Strom Pipeline'!O6:O860,MATCH(LARGE('MiT Strom Pipeline'!Z6:Z860,4),'MiT Strom Pipeline'!Z6:Z860,0)),"") -> 39500
B18: 5 | C18: =IFERROR(INDEX('MiT Strom Pipeline'!B6:B860,MATCH(LARGE('MiT Strom Pipeline'!Z6:Z860,5),'MiT Strom Pipeline'!Z6:Z860,0)),"") -> Murg Flums Energie | D18: =IFERROR(INDEX('MiT Strom Pipeline'!C6:C860,MATCH(LARGE('MiT Strom Pipeline'!Z6:Z860,5),'MiT Strom Pipeline'!Z6:Z860,0)),"") -> SG | E18: =IFERROR(INDEX('MiT Strom Pipeline'!H6:H860,MATCH(LARGE('MiT Strom Pipeline'!Z6:Z860,5),'MiT Strom Pipeline'!Z6:Z860,0)),"") -> Auf Abruf | F18: =IFERROR(INDEX('MiT Strom Pipeline'!D6:D860,MATCH(LARGE('MiT Strom Pipeline'!Z6:Z860,5),'MiT Strom Pipeline'!Z6:Z860,0)),"") -> EVU / Energie | G18: =IFERROR(INDEX('MiT Strom Pipeline'!I6:I860,MATCH(LARGE('MiT Strom Pipeline'!Z6:Z860,5),'MiT Strom Pipeline'!Z6:Z860,0)),"") -> 96658.69 | H18: =IFERROR(INDEX('MiT Strom Pipeline'!O6:O860,MATCH(LARGE('MiT Strom Pipeline'!Z6:Z860,5),'MiT Strom Pipeline'!Z6:Z860,0)),"") -> 7242.69
B21: 📊 Status-Verteilung Pipeline
B22: Status | D22: Anzahl | E22: Volumen CHF | G22: Anteil %
B23: ✅ WON | D23: =COUNTIF('MiT Strom Pipeline'!R6:R860,"WON") -> 12 | E23: =SUMIFS('MiT Strom Pipeline'!I6:I860,'MiT Strom Pipeline'!R6:R860,"WON") -> 1428553.1 | G23: =IFERROR(E23/Dashboard!I6,0) -> 0.20817867
B24: 📄 Offerte (inkl. To Offer) | D24: =COUNTIF('MiT Strom Pipeline'!R6:R860,"offered")+COUNTIF('MiT Strom Pipeline'!R6:R860,"to be offered") -> 29 | E24: =SUMIFS('MiT Strom Pipeline'!I6:I860,'MiT Strom Pipeline'!R6:R860,"offered")+SUMIFS('MiT Strom Pipeline'!I6:I860,'MiT Strom Pipeline'!R6:R860,"to be offered") -> 4887938.3 | G24: =IFERROR(E24/Dashboard!I6,0) -> 0.71230428
B25: 🎯 Follow-Up | D25: =COUNTIF('MiT Strom Pipeline'!R6:R860,"follow-up") -> 0 | E25: =SUMIFS('MiT Strom Pipeline'!I6:I860,'MiT Strom Pipeline'!R6:R860,"follow-up") -> 0 | G25: =IFERROR(E25/Dashboard!I6,0) -> 0
B26: 🔍 Evaluation (inkl. In Eval) | D26: =COUNTIF('MiT Strom Pipeline'!R6:R860,"Evaluation")+COUNTIF('MiT Strom Pipeline'!R6:R860,"In evaluation") -> 0 | E26: =SUMIFS('MiT Strom Pipeline'!I6:I860,'MiT Strom Pipeline'!R6:R860,"Evaluation")+SUMIFS('MiT Strom Pipeline'!I6:I860,'MiT Strom Pipeline'!R6:R860,"In evaluation") -> 0 | G26: =IFERROR(E26/Dashboard!I6,0) -> 0
B27: ⏸ On Hold | D27: =COUNTIF('MiT Strom Pipeline'!R6:R860,"on hold") -> 4 | E27: =SUMIFS('MiT Strom Pipeline'!I6:I860,'MiT Strom Pipeline'!R6:R860,"on hold") -> 545657.8 | G27: =IFERROR(E27/Dashboard!I6,0) -> 0.079517041
B28: ❓ TBD | D28: =COUNTIF('MiT Strom Pipeline'!R6:R860,"tbd") -> 1 | E28: =SUMIFS('MiT Strom Pipeline'!I6:I860,'MiT Strom Pipeline'!R6:R860,"tbd") -> 0 | G28: =IFERROR(E28/Dashboard!I6,0) -> 0
B29: ❌ LOST | D29: =COUNTIF('MiT Strom Pipeline'!R6:R860,"LOST") -> 7 | E29: =SUMIFS('MiT Strom Pipeline'!I6:I860,'MiT Strom Pipeline'!R6:R860,"LOST") -> 78251.62 | G29: =IFERROR(E29/Dashboard!I6,0) -> 0.011403369
B30: 🚫 Declined | D30: =COUNTIF('MiT Strom Pipeline'!R6:R860,"Declined") -> 13 | E30: =SUMIFS('MiT Strom Pipeline'!I6:I860,'MiT Strom Pipeline'!R6:R860,"Declined") -> 96029.01 | G30: =IFERROR(E30/Dashboard!I6,0) -> 0.013994014
A35: 🖨 Strg+P → Als PDF speichern · Druckbereich ist bereits gesetzt (A4 Hochformat)

Sheet 📄 Report
A1: MiT Strom Schweiz — Sales-Report
A2: Mobil in Time AG · An Aggreko Company · Burak Ücöz
A3: ="Stand: "&TEXT(TODAY(),"DD.MM.YYYY")&" · Auto-Update via Pipeline-Daten" -> Stand: DD.08.YYYY · Auto-Update via Pipeline-Daten
A5: Key Performance Indicators
A6: KPI | B6: Wert CHF | C6: Anzahl | D6: Anteil
A7: ✅ WON | B7: =Dashboard!A6 -> 1428553.1 | C7: =Dashboard!A7 -> 12 | D7: =IFERROR(B7/$B$10,0) -> 0.20817867
A8: 📄 Offerte | B8: =Dashboard!D6 -> 5433596.1 | C8: =Dashboard!D7 -> 33 | D8: =IFERROR(B8/$B$10,0) -> 0.79182133
A9: 🎯 Opportunität | B9: =Dashboard!G6 -> 0 | C9: =Dashboard!G7 -> 1 | D9: =IFERROR(B9/$B$10,0) -> 0
A10: 📊 TOTAL Pipeline | B10: =Dashboard!I6 -> 6862149.2 | C10: =Dashboard!I7 -> 46 | D10: =IFERROR(B10/$B$10,0) -> 1
A13: Top Kantone (nach Volumen) | J13: _kt | K13: _vol | L13: _rankkey
A14: Rang | B14: Kanton | C14: Volumen CHF | D14: Anzahl Deals | E14: WON-Rate | J14: AG | K14: =SUMIF('MiT Strom Pipeline'!$C$6:$C$860,J14,'MiT Strom Pipeline'!$I$6:$I$860) -> 444672.95 | L14: =K14+(26-ROW())*0.0001 -> 444672.95
A15: 1 | B15: =IFERROR(INDEX($J$14:$J$39,MATCH(LARGE($L$14:$L$39,1),$L$14:$L$39,0)),"") -> ZH | C15: =IF(B15="","",SUMIF('MiT Strom Pipeline'!$C$6:$C$860,B15,'MiT Strom Pipeline'!$I$6:$I$860)) -> 2732239 | D15: =IF(B15="","",COUNTIF('MiT Strom Pipeline'!$C$6:$C$860,B15)) -> 25 | E15: =IF(OR(B15="",D15=0),"",COUNTIFS('MiT Strom Pipeline'!$C$6:$C$860,B15,'MiT Strom Pipeline'!$R$6:$R$860,"WON")/D15) -> 0.2 | J15: AI | K15: =SUMIF('MiT Strom Pipeline'!$C$6:$C$860,J15,'MiT Strom Pipeline'!$I$6:$I$860) -> 0 | L15: =K15+(26-ROW())*0.0001 -> 0.0011
A16: 2 | B16: =IFERROR(INDEX($J$14:$J$39,MATCH(LARGE($L$14:$L$39,2),$L$14:$L$39,0)),"") -> SH | C16: =IF(B16="","",SUMIF('MiT Strom Pipeline'!$C$6:$C$860,B16,'MiT Strom Pipeline'!$I$6:$I$860)) -> 2637287.6 | D16: =IF(B16="","",COUNTIF('MiT Strom Pipeline'!$C$6:$C$860,B16)) -> 5 | E16: =IF(OR(B16="",D16=0),"",COUNTIFS('MiT Strom Pipeline'!$C$6:$C$860,B16,'MiT Strom Pipeline'!$R$6:$R$860,"WON")/D16) -> 0.2 | J16: AR | K16: =SUMIF('MiT Strom Pipeline'!$C$6:$C$860,J16,'MiT Strom Pipeline'!$I$6:$I$860) -> 0 | L16: =K16+(26-ROW())*0.0001 -> 0.001
A17: 3 | B17: =IFERROR(INDEX($J$14:$J$39,MATCH(LARGE($L$14:$L$39,3),$L$14:$L$39,0)),"") -> AG | C17: =IF(B17="","",SUMIF('MiT Strom Pipeline'!$C$6:$C$860,B17,'MiT Strom Pipeline'!$I$6:$I$860)) -> 444672.95 | D17: =IF(B17="","",COUNTIF('MiT Strom Pipeline'!$C$6:$C$860,B17)) -> 7 | E17: =IF(OR(B17="",D17=0),"",COUNTIFS('MiT Strom Pipeline'!$C$6:$C$860,B17,'MiT Strom Pipeline'!$R$6:$R$860,"WON")/D17) -> 0.14285714 | J17: BE | K17: =SUMIF('MiT Strom Pipeline'!$C$6:$C$860,J17,'MiT Strom Pipeline'!$I$6:$I$860) -> 58012.12 | L17: =K17+(26-ROW())*0.0001 -> 58012.121
A18: 4 | B18: =IFERROR(INDEX($J$14:$J$39,MATCH(LARGE($L$14:$L$39,4),$L$14:$L$39,0)),"") -> SO | C18: =IF(B18="","",SUMIF('MiT Strom Pipeline'!$C$6:$C$860,B18,'MiT Strom Pipeline'!$I$6:$I$860)) -> 390750.65 | D18: =IF(B18="","",COUNTIF('MiT Strom Pipeline'!$C$6:$C$860,B18)) -> 2 | E18: =IF(OR(B18="",D18=0),"",COUNTIFS('MiT Strom Pipeline'!$C$6:$C$860,B18,'MiT Strom Pipeline'!$R$6:$R$860,"WON")/D18) -> 0 | J18: BL | K18: =SUMIF('MiT Strom Pipeline'!$C$6:$C$860,J18,'MiT Strom Pipeline'!$I$6:$I$860) -> 13472.18 | L18: =K18+(26-ROW())*0.0001 -> 13472.181
A19: 5 | B19: =IFERROR(INDEX($J$14:$J$39,MATCH(LARGE($L$14:$L$39,5),$L$14:$L$39,0)),"") -> VS | C19: =IF(B19="","",SUMIF('MiT Strom Pipeline'!$C$6:$C$860,B19,'MiT Strom Pipeline'!$I$6:$I$860)) -> 303790.2 | D19: =IF(B19="","",COUNTIF('MiT Strom Pipeline'!$C$6:$C$860,B19)) -> 3 | E19: =IF(OR(B19="",D19=0),"",COUNTIFS('MiT Strom Pipeline'!$C$6:$C$860,B19,'MiT Strom Pipeline'!$R$6:$R$860,"WON")/D19) -> 0.33333333 | J19: BS | K19: =SUMIF('MiT Strom Pipeline'!$C$6:$C$860,J19,'MiT Strom Pipeline'!$I$6:$I$860) -> 13866.21 | L19: =K19+(26-ROW())*0.0001 -> 13866.211
A20: 6 | B20: =IFERROR(INDEX($J$14:$J$39,MATCH(LARGE($L$14:$L$39,6),$L$14:$L$39,0)),"") -> TG | C20: =IF(B20="","",SUMIF('MiT Strom Pipeline'!$C$6:$C$860,B20,'MiT Strom Pipeline'!$I$6:$I$860)) -> 160817.26 | D20: =IF(B20="","",COUNTIF('MiT Strom Pipeline'!$C$6:$C$860,B20)) -> 3 | E20: =IF(OR(B20="",D20=0),"",COUNTIFS('MiT Strom Pipeline'!$C$6:$C$860,B20,'MiT Strom Pipeline'!$R$6:$R$860,"WON")/D20) -> 0.66666667 | J20: FR | K20: =SUMIF('MiT Strom Pipeline'!$C$6:$C$860,J20,'MiT Strom Pipeline'!$I$6:$I$860) -> 0 | L20: =K20+(26-ROW())*0.0001 -> 0.0006
A21: 7 | B21: =IFERROR(INDEX($J$14:$J$39,MATCH(LARGE($L$14:$L$39,7),$L$14:$L$39,0)),"") -> SG | C21: =IF(B21="","",SUMIF('MiT Strom Pipeline'!$C$6:$C$860,B21,'MiT Strom Pipeline'!$I$6:$I$860)) -> 101192.62 | D21: =IF(B21="","",COUNTIF('MiT Strom Pipeline'!$C$6:$C$860,B21)) -> 3 | E21: =IF(OR(B21="",D21=0),"",COUNTIFS('MiT Strom Pipeline'!$C$6:$C$860,B21,'MiT Strom Pipeline'!$R$6:$R$860,"WON")/D21) -> 0.33333333 | J21: GE | K21: =SUMIF('MiT Strom Pipeline'!$C$6:$C$860,J21,'MiT Strom Pipeline'!$I$6:$I$860) -> 38885 | L21: =K21+(26-ROW())*0.0001 -> 38885.001
A22: 8 | B22: =IFERROR(INDEX($J$14:$J$39,MATCH(LARGE($L$14:$L$39,8),$L$14:$L$39,0)),"") -> GR | C22: =IF(B22="","",SUMIF('MiT Strom Pipeline'!$C$6:$C$860,B22,'MiT Strom Pipeline'!$I$6:$I$860)) -> 77325.62 | D22: =IF(B22="","",COUNTIF('MiT Strom Pipeline'!$C$6:$C$860,B22)) -> 2 | E22: =IF(OR(B22="",D22=0),"",COUNTIFS('MiT Strom Pipeline'!$C$6:$C$860,B22,'MiT Strom Pipeline'!$R$6:$R$860,"WON")/D22) -> 0 | J22: GL | K22: =SUMIF('MiT Strom Pipeline'!$C$6:$C$860,J22,'MiT Strom Pipeline'!$I$6:$I$860) -> 0 | L22: =K22+(26-ROW())*0.0001 -> 0.0004
A23: 9 | B23: =IFERROR(INDEX($J$14:$J$39,MATCH(LARGE($L$14:$L$39,9),$L$14:$L$39,0)),"") -> BE | C23: =IF(B23="","",SUMIF('MiT Strom Pipeline'!$C$6:$C$860,B23,'MiT Strom Pipeline'!$I$6:$I$860)) -> 58012.12 | D23: =IF(B23="","",COUNTIF('MiT Strom Pipeline'!$C$6:$C$860,B23)) -> 5 | E23: =IF(OR(B23="",D23=0),"",COUNTIFS('MiT Strom Pipeline'!$C$6:$C$860,B23,'MiT Strom Pipeline'!$R$6:$R$860,"WON")/D23) -> 0 | J23: GR | K23: =SUMIF('MiT Strom Pipeline'!$C$6:$C$860,J23,'MiT Strom Pipeline'!$I$6:$I$860) -> 77325.62 | L23: =K23+(26-ROW())*0.0001 -> 77325.62
A24: 10 | B24: =IFERROR(INDEX($J$14:$J$39,MATCH(LARGE($L$14:$L$39,10),$L$14:$L$39,0)),"") -> ZG | C24: =IF(B24="","",SUMIF('MiT Strom Pipeline'!$C$6:$C$860,B24,'MiT Strom Pipeline'!$I$6:$I$860)) -> 40491.67 | D24: =IF(B24="","",COUNTIF('MiT Strom Pipeline'!$C$6:$C$860,B24)) -> 1 | E24: =IF(OR(B24="",D24=0),"",COUNTIFS('MiT Strom Pipeline'!$C$6:$C$860,B24,'MiT Strom Pipeline'!$R$6:$R$860,"WON")/D24) -> 0 | J24: JU | K24: =SUMIF('MiT Strom Pipeline'!$C$6:$C$860,J24,'MiT Strom Pipeline'!$I$6:$I$860) -> 0 | L24: =K24+(26-ROW())*0.0001 -> 0.0002
J25: LU | K25: =SUMIF('MiT Strom Pipeline'!$C$6:$C$860,J25,'MiT Strom Pipeline'!$I$6:$I$860) -> 23626.77 | L25: =K25+(26-ROW())*0.0001 -> 23626.77
J26: NE | K26: =SUMIF('MiT Strom Pipeline'!$C$6:$C$860,J26,'MiT Strom Pipeline'!$I$6:$I$860) -> 0 | L26: =K26+(26-ROW())*0.0001 -> 0
A27: Top WON-Deals | J27: NW | K27: =SUMIF('MiT Strom Pipeline'!$C$6:$C$860,J27,'MiT Strom Pipeline'!$I$6:$I$860) -> 0 | L27: =K27+(26-ROW())*0.0001 -> -0.0001
A28: Rang | B28: Kunde | C28: Kanton | D28: Segment | E28: Volumen CHF | F28: Marge CHF | G28: Start | J28: OW | K28: =SUMIF('MiT Strom Pipeline'!$C$6:$C$860,J28,'MiT Strom Pipeline'!$I$6:$I$860) -> 0 | L28: =K28+(26-ROW())*0.0001 -> -0.0002
A29: 1 | B29: =IFERROR(INDEX('MiT Strom Pipeline'!$B$6:$B$860,MATCH(LARGE('MiT Strom Pipeline'!$Z$6:$Z$860,1),'MiT Strom Pipeline'!$Z$6:$Z$860,0)),"") -> Ice Hockey Championship | C29: =IFERROR(INDEX('MiT Strom Pipeline'!$C$6:$C$860,MATCH(LARGE('MiT Strom Pipeline'!$Z$6:$Z$860,1),'MiT Strom Pipeline'!$Z$6:$Z$860,0)),"") -> ZH | D29: =IFERROR(INDEX('MiT Strom Pipeline'!$D$6:$D$860,MATCH(LARGE('MiT Strom Pipeline'!$Z$6:$Z$860,1),'MiT Strom Pipeline'!$Z$6:$Z$860,0)),"") -> Events & Sport | E29: =IFERROR(LARGE('MiT Strom Pipeline'!$Z$6:$Z$860,1),"") -> 380000 | F29: =IFERROR(INDEX('MiT Strom Pipeline'!$O$6:$O$860,MATCH(LARGE('MiT Strom Pipeline'!$Z$6:$Z$860,1),'MiT Strom Pipeline'!$Z$6:$Z$860,0)),"") -> 145000 | G29: =IFERROR(INDEX('MiT Strom Pipeline'!H6:H860,MATCH(LARGE('MiT Strom Pipeline'!Z6:Z860,1),'MiT Strom Pipeline'!Z6:Z860,0)),"") -> Mai | J29: SG | K29: =SUMIF('MiT Strom Pipeline'!$C$6:$C$860,J29,'MiT Strom Pipeline'!$I$6:$I$860) -> 101192.62 | L29: =K29+(26-ROW())*0.0001 -> 101192.62
A30: 2 | B30: =IFERROR(INDEX('MiT Strom Pipeline'!$B$6:$B$860,MATCH(LARGE('MiT Strom Pipeline'!$Z$6:$Z$860,2),'MiT Strom Pipeline'!$Z$6:$Z$860,0)),"") -> DPR Heat Loadbank | C30: =IFERROR(INDEX('MiT Strom Pipeline'!$C$6:$C$860,MATCH(LARGE('MiT Strom Pipeline'!$Z$6:$Z$860,2),'MiT Strom Pipeline'!$Z$6:$Z$860,0)),"") -> ZH | D30: =IFERROR(INDEX('MiT Strom Pipeline'!$D$6:$D$860,MATCH(LARGE('MiT Strom Pipeline'!$Z$6:$Z$860,2),'MiT Strom Pipeline'!$Z$6:$Z$860,0)),"") -> Datacenter | E30: =IFERROR(LARGE('MiT Strom Pipeline'!$Z$6:$Z$860,2),"") -> 333790 | F30: =IFERROR(INDEX('MiT Strom Pipeline'!$O$6:$O$860,MATCH(LARGE('MiT Strom Pipeline'!$Z$6:$Z$860,2),'MiT Strom Pipeline'!$Z$6:$Z$860,0)),"") -> -25011.09 | G30: =IFERROR(INDEX('MiT Strom Pipeline'!H6:H860,MATCH(LARGE('MiT Strom Pipeline'!Z6:Z860,2),'MiT Strom Pipeline'!Z6:Z860,0)),"") -> Aug | J30: SH | K30: =SUMIF('MiT Strom Pipeline'!$C$6:$C$860,J30,'MiT Strom Pipeline'!$I$6:$I$860) -> 2637287.6 | L30: =K30+(26-ROW())*0.0001 -> 2637287.6
A31: 3 | B31: =IFERROR(INDEX('MiT Strom Pipeline'!$B$6:$B$860,MATCH(LARGE('MiT Strom Pipeline'!$Z$6:$Z$860,3),'MiT Strom Pipeline'!$Z$6:$Z$860,0)),"") -> DPR Generator Loadbank Test | C31: =IFERROR(INDEX('MiT Strom Pipeline'!$C$6:$C$860,MATCH(LARGE('MiT Strom Pipeline'!$Z$6:$Z$860,3),'MiT Strom Pipeline'!$Z$6:$Z$860,0)),"") -> ZH | D31: =IFERROR(INDEX('MiT Strom Pipeline'!$D$6:$D$860,MATCH(LARGE('MiT Strom Pipeline'!$Z$6:$Z$860,3),'MiT Strom Pipeline'!$Z$6:$Z$860,0)),"") -> Datacenter | E31: =IFERROR(LARGE('MiT Strom Pipeline'!$Z$6:$Z$860,3),"") -> 331889.15 | F31: =IFERROR(INDEX('MiT Strom Pipeline'!$O$6:$O$860,MATCH(LARGE('MiT Strom Pipeline'!$Z$6:$Z$860,3),'MiT Strom Pipeline'!$Z$6:$Z$860,0)),"") -> -24868.66 | G31: =IFERROR(INDEX('MiT Strom Pipeline'!H6:H860,MATCH(LARGE('MiT Strom Pipeline'!Z6:Z860,3),'MiT Strom Pipeline'!Z6:Z860,0)),"") -> Aug | J31: SO | K31: =SUMIF('MiT Strom Pipeline'!$C$6:$C$860,J31,'MiT Strom Pipeline'!$I$6:$I$860) -> 390750.65 | L31: =K31+(26-ROW())*0.0001 -> 390750.65
A32: 4 | B32: =IFERROR(INDEX('MiT Strom Pipeline'!$B$6:$B$860,MATCH(LARGE('MiT Strom Pipeline'!$Z$6:$Z$860,4),'MiT Strom Pipeline'!$Z$6:$Z$860,0)),"") -> Stagelight – OpenAir Frauenfeld | C32: =IFERROR(INDEX('MiT Strom Pipeline'!$C$6:$C$860,MATCH(LARGE('MiT Strom Pipeline'!$Z$6:$Z$860,4),'MiT Strom Pipeline'!$Z$6:$Z$860,0)),"") -> TG | D32: =IFERROR(INDEX('MiT Strom Pipeline'!$D$6:$D$860,MATCH(LARGE('MiT Strom Pipeline'!$Z$6:$Z$860,4),'MiT Strom Pipeline'!$Z$6:$Z$860,0)),"") -> Events & Kultur | E32: =IFERROR(LARGE('MiT Strom Pipeline'!$Z$6:$Z$860,4),"") -> 150000 | F32: =IFERROR(INDEX('MiT Strom Pipeline'!$O$6:$O$860,MATCH(LARGE('MiT Strom Pipeline'!$Z$6:$Z$860,4),'MiT Strom Pipeline'!$Z$6:$Z$860,0)),"") -> 39500 | G32: =IFERROR(INDEX('MiT Strom Pipeline'!H6:H860,MATCH(LARGE('MiT Strom Pipeline'!Z6:Z860,4),'MiT Strom Pipeline'!Z6:Z860,0)),"") -> Juli | J32: SZ | K32: =SUMIF('MiT Strom Pipeline'!$C$6:$C$860,J32,'MiT Strom Pipeline'!$I$6:$I$860) -> 0 | L32: =K32+(26-ROW())*0.0001 -> -0.0006
A33: 5 | B33: =IFERROR(INDEX('MiT Strom Pipeline'!$B$6:$B$860,MATCH(LARGE('MiT Strom Pipeline'!$Z$6:$Z$860,5),'MiT Strom Pipeline'!$Z$6:$Z$860,0)),"") -> Murg Flums Energie | C33: =IFERROR(INDEX('MiT Strom Pipeline'!$C$6:$C$860,MATCH(LARGE('MiT Strom Pipeline'!$Z$6:$Z$860,5),'MiT Strom Pipeline'!$Z$6:$Z$860,0)),"") -> SG | D33: =IFERROR(INDEX('MiT Strom Pipeline'!$D$6:$D$860,MATCH(LARGE('MiT Strom Pipeline'!$Z$6:$Z$860,5),'MiT Strom Pipeline'!$Z$6:$Z$860,0)),"") -> EVU / Energie | E33: =IFERROR(LARGE('MiT Strom Pipeline'!$Z$6:$Z$860,5),"") -> 96658.69 | F33: =IFERROR(INDEX('MiT Strom Pipeline'!$O$6:$O$860,MATCH(LARGE('MiT Strom Pipeline'!$Z$6:$Z$860,5),'MiT Strom Pipeline'!$Z$6:$Z$860,0)),"") -> 7242.69 | G33: =IFERROR(INDEX('MiT Strom Pipeline'!H6:H860,MATCH(LARGE('MiT Strom Pipeline'!Z6:Z860,5),'MiT Strom Pipeline'!Z6:Z860,0)),"") -> Auf Abruf | J33: TG | K33: =SUMIF('MiT Strom Pipeline'!$C$6:$C$860,J33,'MiT Strom Pipeline'!$I$6:$I$860) -> 160817.26 | L33: =K33+(26-ROW())*0.0001 -> 160817.26
A34: 6 | B34: =IFERROR(INDEX('MiT Strom Pipeline'!$B$6:$B$860,MATCH(LARGE('MiT Strom Pipeline'!$Z$6:$Z$860,6),'MiT Strom Pipeline'!$Z$6:$Z$860,0)),"") -> Gampeln | C34: =IFERROR(INDEX('MiT Strom Pipeline'!$C$6:$C$860,MATCH(LARGE('MiT Strom Pipeline'!$Z$6:$Z$860,6),'MiT Strom Pipeline'!$Z$6:$Z$860,0)),"") -> VS | D34: =IFERROR(INDEX('MiT Strom Pipeline'!$D$6:$D$860,MATCH(LARGE('MiT Strom Pipeline'!$Z$6:$Z$860,6),'MiT Strom Pipeline'!$Z$6:$Z$860,0)),"") -> Event | E34: =IFERROR(LARGE('MiT Strom Pipeline'!$Z$6:$Z$860,6),"") -> 80621.21 | F34: =IFERROR(INDEX('MiT Strom Pipeline'!$O$6:$O$860,MATCH(LARGE('MiT Strom Pipeline'!$Z$6:$Z$860,6),'MiT Strom Pipeline'!$Z$6:$Z$860,0)),"") -> -10507.9 | G34: =IFERROR(INDEX('MiT Strom Pipeline'!H6:H860,MATCH(LARGE('MiT Strom Pipeline'!Z6:Z860,6),'MiT Strom Pipeline'!Z6:Z860,0)),"") -> Aug | J34: TI | K34: =SUMIF('MiT Strom Pipeline'!$C$6:$C$860,J34,'MiT Strom Pipeline'!$I$6:$I$860) -> 0 | L34: =K34+(26-ROW())*0.0001 -> -0.0008
A35: 7 | B35: =IFERROR(INDEX('MiT Strom Pipeline'!$B$6:$B$860,MATCH(LARGE('MiT Strom Pipeline'!$Z$6:$Z$860,7),'MiT Strom Pipeline'!$Z$6:$Z$860,0)),"") -> EIDG AMT Agroscope | C35: =IFERROR(INDEX('MiT Strom Pipeline'!$C$6:$C$860,MATCH(LARGE('MiT Strom Pipeline'!$Z$6:$Z$860,7),'MiT Strom Pipeline'!$Z$6:$Z$860,0)),"") -> ZH | D35: =IFERROR(INDEX('MiT Strom Pipeline'!$D$6:$D$860,MATCH(LARGE('MiT Strom Pipeline'!$Z$6:$Z$860,7),'MiT Strom Pipeline'!$Z$6:$Z$860,0)),"") -> Forschung | E35: =IFERROR(LARGE('MiT Strom Pipeline'!$Z$6:$Z$860,7),"") -> 13533 | F35: =IFERROR(INDEX('MiT Strom Pipeline'!$O$6:$O$860,MATCH(LARGE('MiT Strom Pipeline'!$Z$6:$Z$860,7),'MiT Strom Pipeline'!$Z$6:$Z$860,0)),"") -> 155.46 | G35: =IFERROR(INDEX('MiT Strom Pipeline'!H6:H860,MATCH(LARGE('MiT Strom Pipeline'!Z6:Z860,7),'MiT Strom Pipeline'!Z6:Z860,0)),"") -> Aug | J35: UR | K35: =SUMIF('MiT Strom Pipeline'!$C$6:$C$860,J35,'MiT Strom Pipeline'!$I$6:$I$860) -> 0 | L35: =K35+(26-ROW())*0.0001 -> -0.0009
A36: 8 | B36: =IFERROR(INDEX('MiT Strom Pipeline'!$B$6:$B$860,MATCH(LARGE('MiT Strom Pipeline'!$Z$6:$Z$860,8),'MiT Strom Pipeline'!$Z$6:$Z$860,0)),"") -> GETEC Park.Swiss AG | C36: =IFERROR(INDEX('MiT Strom Pipeline'!$C$6:$C$860,MATCH(LARGE('MiT Strom Pipeline'!$Z$6:$Z$860,8),'MiT Strom Pipeline'!$Z$6:$Z$860,0)),"") -> BL | D36: =IFERROR(INDEX('MiT Strom Pipeline'!$D$6:$D$860,MATCH(LARGE('MiT Strom Pipeline'!$Z$6:$Z$860,8),'MiT Strom Pipeline'!$Z$6:$Z$860,0)),"") -> Industrie | E36: =IFERROR(LARGE('MiT Strom Pipeline'!$Z$6:$Z$860,8),"") -> 13472.18 | F36: =IFERROR(INDEX('MiT Strom Pipeline'!$O$6:$O$860,MATCH(LARGE('MiT Strom Pipeline'!$Z$6:$Z$860,8),'MiT Strom Pipeline'!$Z$6:$Z$860,0)),"") -> 1.8189894e-12 | G36: =IFERROR(INDEX('MiT Strom Pipeline'!H6:H860,MATCH(LARGE('MiT Strom Pipeline'!Z6:Z860,8),'MiT Strom Pipeline'!Z6:Z860,0)),"") -> August | J36: VD | K36: =SUMIF('MiT Strom Pipeline'!$C$6:$C$860,J36,'MiT Strom Pipeline'!$I$6:$I$860) -> 0 | L36: =K36+(26-ROW())*0.0001 -> -0.001
A37: 9 | B37: =IFERROR(INDEX('MiT Strom Pipeline'!$B$6:$B$860,MATCH(LARGE('MiT Strom Pipeline'!$Z$6:$Z$860,9),'MiT Strom Pipeline'!$Z$6:$Z$860,0)),"") -> Oerlikon Metco Wohlen | C37: =IFERROR(INDEX('MiT Strom Pipeline'!$C$6:$C$860,MATCH(LARGE('MiT Strom Pipeline'!$Z$6:$Z$860,9),'MiT Strom Pipeline'!$Z$6:$Z$860,0)),"") -> AG | D37: =IFERROR(INDEX('MiT Strom Pipeline'!$D$6:$D$860,MATCH(LARGE('MiT Strom Pipeline'!$Z$6:$Z$860,9),'MiT Strom Pipeline'!$Z$6:$Z$860,0)),"") -> Industrie / Oberfläche | E37: =IFERROR(LARGE('MiT Strom Pipeline'!$Z$6:$Z$860,9),"") -> 13100 | F37: =IFERROR(INDEX('MiT Strom Pipeline'!$O$6:$O$860,MATCH(LARGE('MiT Strom Pipeline'!$Z$6:$Z$860,9),'MiT Strom Pipeline'!$Z$6:$Z$860,0)),"") -> 3000 | G37: =IFERROR(INDEX('MiT Strom Pipeline'!H6:H860,MATCH(LARGE('MiT Strom Pipeline'!Z6:Z860,9),'MiT Strom Pipeline'!Z6:Z860,0)),"") -> April | J37: VS | K37: =SUMIF('MiT Strom Pipeline'!$C$6:$C$860,J37,'MiT Strom Pipeline'!$I$6:$I$860) -> 303790.2 | L37: =K37+(26-ROW())*0.0001 -> 303790.2
A38: 10 | B38: =IFERROR(INDEX('MiT Strom Pipeline'!$B$6:$B$860,MATCH(LARGE('MiT Strom Pipeline'!$Z$6:$Z$860,10),'MiT Strom Pipeline'!$Z$6:$Z$860,0)),"") -> Siemens | C38: =IFERROR(INDEX('MiT Strom Pipeline'!$C$6:$C$860,MATCH(LARGE('MiT Strom Pipeline'!$Z$6:$Z$860,10),'MiT Strom Pipeline'!$Z$6:$Z$860,0)),"") -> ZH | D38: =IFERROR(INDEX('MiT Strom Pipeline'!$D$6:$D$860,MATCH(LARGE('MiT Strom Pipeline'!$Z$6:$Z$860,10),'MiT Strom Pipeline'!$Z$6:$Z$860,0)),"") -> Industrie / Elektro | E38: =IFERROR(LARGE('MiT Strom Pipeline'!$Z$6:$Z$860,10),"") -> 10000 | F38: =IFERROR(INDEX('MiT Strom Pipeline'!$O$6:$O$860,MATCH(LARGE('MiT Strom Pipeline'!$Z$6:$Z$860,10),'MiT Strom Pipeline'!$Z$6:$Z$860,0)),"") -> 10000 | G38: =IFERROR(INDEX('MiT Strom Pipeline'!H6:H860,MATCH(LARGE('MiT Strom Pipeline'!Z6:Z860,10),'MiT Strom Pipeline'!Z6:Z860,0)),"") -> tbd | J38: ZG | K38: =SUMIF('MiT Strom Pipeline'!$C$6:$C$860,J38,'MiT Strom Pipeline'!$I$6:$I$860) -> 40491.67 | L38: =K38+(26-ROW())*0.0001 -> 40491.669
J39: ZH | K39: =SUMIF('MiT Strom Pipeline'!$C$6:$C$860,J39,'MiT Strom Pipeline'!$I$6:$I$860) -> 2732239 | L39: =K39+(26-ROW())*0.0001 -> 2732239
A40: ↻ Auto-Update aus Pipeline · Sortiert nach Volumen ↓ · Nur WON mit numerischem Volumen
A41: 🖨 Strg+P → «Als PDF speichern» · Druckbereich A4 ist gesetzt

Sheet CEO Report
A1: ="⚡ MiT Strom Schweiz — CEO Sales Report · "&TEXT(TODAY(),"MMMM YYYY") -> ⚡ MiT Strom Schweiz — CEO Sales Report · August YYYY
A2: Mobil in Time AG · An Aggreko Company · Burak Ücöz · Neue Einträge in «MiT Strom Pipeline» erscheinen automatisch.
A5: ✅ AUFTRAGSEINGANG (WON) | E5: 📄 OFFERTE — Laufend | I5: 🎯 OPPORTUNITÄT
A6: =SUMIFS('MiT Strom Pipeline'!I$6:I$860,'MiT Strom Pipeline'!R$6:R$860,"WON") -> 1428553.1 | E6: =SUMIFS('MiT Strom Pipeline'!I$6:I$860,'MiT Strom Pipeline'!R$6:R$860,"offered")+SUMIFS('MiT Strom Pipeline'!I$6:I$860,'MiT Strom Pipeline'!R$6:R$860,"to be offered")+SUMIFS('MiT Strom Pipeline'!I$6:I$860,'MiT Strom Pipeline'!R$6:R$860,"on hold") -> 5433596.1 | I6: =SUMIFS('MiT Strom Pipeline'!I$6:I$860,'MiT Strom Pipeline'!R$6:R$860,"follow-up")+SUMIFS('MiT Strom Pipeline'!I$6:I$860,'MiT Strom Pipeline'!R$6:R$860,"Evaluation")+SUMIFS('MiT Strom Pipeline'!I$6:I$860,'MiT Strom Pipeline'!R$6:R$860,"tbd")+SUMIFS('MiT Strom Pipeline'!I$6:I$860,'MiT Strom Pipeline'!R$6:R$860,"In evaluation") -> 0
A7: =COUNTIF('MiT Strom Pipeline'!R$6:R$860,"WON") -> 12 | E7: =COUNTIF('MiT Strom Pipeline'!R$6:R$860,"offered")+COUNTIF('MiT Strom Pipeline'!R$6:R$860,"to be offered")+COUNTIF('MiT Strom Pipeline'!R$6:R$860,"on hold") -> 33 | I7: =COUNTIF('MiT Strom Pipeline'!R$6:R$860,"follow-up")+COUNTIF('MiT Strom Pipeline'!R$6:R$860,"Evaluation")+COUNTIF('MiT Strom Pipeline'!R$6:R$860,"tbd")+COUNTIF('MiT Strom Pipeline'!R$6:R$860,"In evaluation") -> 1
A9: ✅ 1. AUFTRAGSEINGANG (WON) — Bestätigte Aufträge
A10: # | B10: Kunde / Unternehmen | C10: Kt. | D10: Segment | E10: Start | F10: Leistung / Fleet | G10: Volumen CHF | H10: Gew.Wert CHF | I10: Marge CHF | J10: Status | K10: Wahr.% | L10: Nächster Schritt
A11: =IF($U11="","",IF(ISNUMBER(INDEX('MiT Strom Pipeline'!$A:$A,$U11)),INDEX('MiT Strom Pipeline'!$A:$A,$U11),"")) -> 1 | B11: =IF($U11="","",IF(INDEX('MiT Strom Pipeline'!$B:$B,$U11)="","",INDEX('MiT Strom Pipeline'!$B:$B,$U11))) -> Ice Hockey Championship | C11: =IF($U11="","",IF(INDEX('MiT Strom Pipeline'!$C:$C,$U11)="","",INDEX('MiT Strom Pipeline'!$C:$C,$U11))) -> ZH | D11: =IF($U11="","",IF(INDEX('MiT Strom Pipeline'!$D:$D,$U11)="","",INDEX('MiT Strom Pipeline'!$D:$D,$U11))) -> Events & Sport | E11: =IF($U11="","",IF(INDEX('MiT Strom Pipeline'!$H:$H,$U11)="","",INDEX('MiT Strom Pipeline'!$H:$H,$U11))) -> Mai | F11: =IF($U11="","",IF(INDEX('MiT Strom Pipeline'!$E:$E,$U11)="","",INDEX('MiT Strom Pipeline'!$E:$E,$U11))) -> 2×600+2×200 kVA | G11: =IF($U11="","",IF(ISNUMBER(INDEX('MiT Strom Pipeline'!$I:$I,$U11)),INDEX('MiT Strom Pipeline'!$I:$I,$U11),0)) -> 380000 | H11: =IF($U11="","",IF(ISNUMBER(INDEX('MiT Strom Pipeline'!$Q:$Q,$U11)),INDEX('MiT Strom Pipeline'!$Q:$Q,$U11),0)) -> 380000 | I11: =IF($U11="","",IF(ISNUMBER(INDEX('MiT Strom Pipeline'!$O:$O,$U11)),INDEX('MiT Strom Pipeline'!$O:$O,$U11),0)) -> 145000 | J11: =IF($U11="","",INDEX('MiT Strom Pipeline'!$R:$R,$U11)) -> WON | K11: =IF($U11="","",IF(ISNUMBER(INDEX('MiT Strom Pipeline'!$S:$S,$U11)),INDEX('MiT Strom Pipeline'!$S:$S,$U11),"")) -> 1 | L11: =IF($U11="","",IF(LEN(INDEX('MiT Strom Pipeline'!$V:$V,$U11))>0,LEFT(INDEX('MiT Strom Pipeline'!$V:$V,$U11),55),"")) -> Abgeschlossen | U11: =IFERROR(MATCH(1,'MiT Strom Pipeline'!$AB$6:$AB$860,0)+5,"") -> 9
A12: =IF($U12="","",IF(ISNUMBER(INDEX('MiT Strom Pipeline'!$A:$A,$U12)),INDEX('MiT Strom Pipeline'!$A:$A,$U12),"")) -> 2 | B12: =IF($U12="","",IF(INDEX('MiT Strom Pipeline'!$B:$B,$U12)="","",INDEX('MiT Strom Pipeline'!$B:$B,$U12))) -> Oerlikon Metco Wohlen | C12: =IF($U12="","",IF(INDEX('MiT Strom Pipeline'!$C:$C,$U12)="","",INDEX('MiT Strom Pipeline'!$C:$C,$U12))) -> AG | D12: =IF($U12="","",IF(INDEX('MiT Strom Pipeline'!$D:$D,$U12)="","",INDEX('MiT Strom Pipeline'!$D:$D,$U12))) -> Industrie / Oberfläche | E12: =IF($U12="","",IF(INDEX('MiT Strom Pipeline'!$H:$H,$U12)="","",INDEX('MiT Strom Pipeline'!$H:$H,$U12))) -> April | F12: =IF($U12="","",IF(INDEX('MiT Strom Pipeline'!$E:$E,$U12)="","",INDEX('MiT Strom Pipeline'!$E:$E,$U12))) -> 240 kVA Generator | G12: =IF($U12="","",IF(ISNUMBER(INDEX('MiT Strom Pipeline'!$I:$I,$U12)),INDEX('MiT Strom Pipeline'!$I:$I,$U12),0)) -> 13100 | H12: =IF($U12="","",IF(ISNUMBER(INDEX('MiT Strom Pipeline'!$Q:$Q,$U12)),INDEX('MiT Strom Pipeline'!$Q:$Q,$U12),0)) -> 13100 | I12: =IF($U12="","",IF(ISNUMBER(INDEX('MiT Strom Pipeline'!$O:$O,$U12)),INDEX('MiT Strom Pipeline'!$O:$O,$U12),0)) -> 3000 | J12: =IF($U12="","",INDEX('MiT Strom Pipeline'!$R:$R,$U12)) -> WON | K12: =IF($U12="","",IF(ISNUMBER(INDEX('MiT Strom Pipeline'!$S:$S,$U12)),INDEX('MiT Strom Pipeline'!$S:$S,$U12),"")) -> 1 | L12: =IF($U12="","",IF(LEN(INDEX('MiT Strom Pipeline'!$V:$V,$U12))>0,LEFT(INDEX('MiT Strom Pipeline'!$V:$V,$U12),55),"")) -> Abgeschlossen | U12: =IFERROR(MATCH(2,'MiT Strom Pipeline'!$AB$6:$AB$860,0)+5,"") -> 10
A13: =IF($U13="","",IF(ISNUMBER(INDEX('MiT Strom Pipeline'!$A:$A,$U13)),INDEX('MiT Strom Pipeline'!$A:$A,$U13),"")) -> 3 | B13: =IF($U13="","",IF(INDEX('MiT Strom Pipeline'!$B:$B,$U13)="","",INDEX('MiT Strom Pipeline'!$B:$B,$U13))) -> Siemens | C13: =IF($U13="","",IF(INDEX('MiT Strom Pipeline'!$C:$C,$U13)="","",INDEX('MiT Strom Pipeline'!$C:$C,$U13))) -> ZH | D13: =IF($U13="","",IF(INDEX('MiT Strom Pipeline'!$D:$D,$U13)="","",INDEX('MiT Strom Pipeline'!$D:$D,$U13))) -> Industrie / Elektro | E13: =IF($U13="","",IF(INDEX('MiT Strom Pipeline'!$H:$H,$U13)="","",INDEX('MiT Strom Pipeline'!$H:$H,$U13))) -> tbd | F13: =IF($U13="","",IF(INDEX('MiT Strom Pipeline'!$E:$E,$U13)="","",INDEX('MiT Strom Pipeline'!$E:$E,$U13))) -> 600 kVA Generator | G13: =IF($U13="","",IF(ISNUMBER(INDEX('MiT Strom Pipeline'!$I:$I,$U13)),INDEX('MiT Strom Pipeline'!$I:$I,$U13),0)) -> 10000 | H13: =IF($U13="","",IF(ISNUMBER(INDEX('MiT Strom Pipeline'!$Q:$Q,$U13)),INDEX('MiT Strom Pipeline'!$Q:$Q,$U13),0)) -> 10000 | I13: =IF($U13="","",IF(ISNUMBER(INDEX('MiT Strom Pipeline'!$O:$O,$U13)),INDEX('MiT Strom Pipeline'!$O:$O,$U13),0)) -> 10000 | J13: =IF($U13="","",INDEX('MiT Strom Pipeline'!$R:$R,$U13)) -> WON | K13: =IF($U13="","",IF(ISNUMBER(INDEX('MiT Strom Pipeline'!$S:$S,$U13)),INDEX('MiT Strom Pipeline'!$S:$S,$U13),"")) -> 1 | L13: =IF($U13="","",IF(LEN(INDEX('MiT Strom Pipeline'!$V:$V,$U13))>0,LEFT(INDEX('MiT Strom Pipeline'!$V:$V,$U13),55),"")) -> Abgeschlossen | U13: =IFERROR(MATCH(3,'MiT Strom Pipeline'!$AB$6:$AB$860,0)+5,"") -> 12
A14: =IF($U14="","",IF(ISNUMBER(INDEX('MiT Strom Pipeline'!$A:$A,$U14)),INDEX('MiT Strom Pipeline'!$A:$A,$U14),"")) -> 4 | B14: =IF($U14="","",IF(INDEX('MiT Strom Pipeline'!$B:$B,$U14)="","",INDEX('MiT Strom Pipeline'!$B:$B,$U14))) -> Stagelight – OpenAir Frauenfeld | C14: =IF($U14="","",IF(INDEX('MiT Strom Pipeline'!$C:$C,$U14)="","",INDEX('MiT Strom Pipeline'!$C:$C,$U14))) -> TG | D14: =IF($U14="","",IF(INDEX('MiT Strom Pipeline'!$D:$D,$U14)="","",INDEX('MiT Strom Pipeline'!$D:$D,$U14))) -> Events & Kultur | E14: =IF($U14="","",IF(INDEX('MiT Strom Pipeline'!$H:$H,$U14)="","",INDEX('MiT Strom Pipeline'!$H:$H,$U14))) -> Juli | F14: =IF($U14="","",IF(INDEX('MiT Strom Pipeline'!$E:$E,$U14)="","",INDEX('MiT Strom Pipeline'!$E:$E,$U14))) -> ~500 kVA Generator | G14: =IF($U14="","",IF(ISNUMBER(INDEX('MiT Strom Pipeline'!$I:$I,$U14)),INDEX('MiT Strom Pipeline'!$I:$I,$U14),0)) -> 150000 | H14: =IF($U14="","",IF(ISNUMBER(INDEX('MiT Strom Pipeline'!$Q:$Q,$U14)),INDEX('MiT Strom Pipeline'!$Q:$Q,$U14),0)) -> 0 | I14: =IF($U14="","",IF(ISNUMBER(INDEX('MiT Strom Pipeline'!$O:$O,$U14)),INDEX('MiT Strom Pipeline'!$O:$O,$U14),0)) -> 39500 | J14: =IF($U14="","",INDEX('MiT Strom Pipeline'!$R:$R,$U14)) -> WON | K14: =IF($U14="","",IF(ISNUMBER(INDEX('MiT Strom Pipeline'!$S:$S,$U14)),INDEX('MiT Strom Pipeline'!$S:$S,$U14),"")) -> 1 | L14: =IF($U14="","",IF(LEN(INDEX('MiT Strom Pipeline'!$V:$V,$U14))>0,LEFT(INDEX('MiT Strom Pipeline'!$V:$V,$U14),55),"")) -> Abgeschlossen | U14: =IFERROR(MATCH(4,'MiT Strom Pipeline'!$AB$6:$AB$860,0)+5,"") -> 13
A15: =IF($U15="","",IF(ISNUMBER(INDEX('MiT Strom Pipeline'!$A:$A,$U15)),INDEX('MiT Strom Pipeline'!$A:$A,$U15),"")) -> 10 | B15: =IF($U15="","",IF(INDEX('MiT Strom Pipeline'!$B:$B,$U15)="","",INDEX('MiT Strom Pipeline'!$B:$B,$U15))) -> Murg Flums Energie | C15: =IF($U15="","",IF(INDEX('MiT Strom Pipeline'!$C:$C,$U15)="","",INDEX('MiT Strom Pipeline'!$C:$C,$U15))) -> SG | D15: =IF($U15="","",IF(INDEX('MiT Strom Pipeline'!$D:$D,$U15)="","",INDEX('MiT Strom Pipeline'!$D:$D,$U15))) -> EVU / Energie | E15: =IF($U15="","",IF(INDEX('MiT Strom Pipeline'!$H:$H,$U15)="","",INDEX('MiT Strom Pipeline'!$H:$H,$U15))) -> Auf Abruf | F15: =IF($U15="","",IF(INDEX('MiT Strom Pipeline'!$E:$E,$U15)="","",INDEX('MiT Strom Pipeline'!$E:$E,$U15))) -> 250 kVA Generator | G15: =IF($U15="","",IF(ISNUMBER(INDEX('MiT Strom Pipeline'!$I:$I,$U15)),INDEX('MiT Strom Pipeline'!$I:$I,$U15),0)) -> 96658.69 | H15: =IF($U15="","",IF(ISNUMBER(INDEX('MiT Strom Pipeline'!$Q:$Q,$U15)),INDEX('MiT Strom Pipeline'!$Q:$Q,$U15),0)) -> 96658.69 | I15: =IF($U15="","",IF(ISNUMBER(INDEX('MiT Strom Pipeline'!$O:$O,$U15)),INDEX('MiT Strom Pipeline'!$O:$O,$U15),0)) -> 7242.69 | J15: =IF($U15="","",INDEX('MiT Strom Pipeline'!$R:$R,$U15)) -> WON | K15: =IF($U15="","",IF(ISNUMBER(INDEX('MiT Strom Pipeline'!$S:$S,$U15)),INDEX('MiT Strom Pipeline'!$S:$S,$U15),"")) -> 1 | L15: =IF($U15="","",IF(LEN(INDEX('MiT Strom Pipeline'!$V:$V,$U15))>0,LEFT(INDEX('MiT Strom Pipeline'!$V:$V,$U15),55),"")) -> Abrufbereitschaft | U15: =IFERROR(MATCH(5,'MiT Strom Pipeline'!$AB$6:$AB$860,0)+5,"") -> 14
A16: =IF($U16="","",IF(ISNUMBER(INDEX('MiT Strom Pipeline'!$A:$A,$U16)),INDEX('MiT Strom Pipeline'!$A:$A,$U16),"")) -> 21 | B16: =IF($U16="","",IF(INDEX('MiT Strom Pipeline'!$B:$B,$U16)="","",INDEX('MiT Strom Pipeline'!$B:$B,$U16))) -> X-Event | C16: =IF($U16="","",IF(INDEX('MiT Strom Pipeline'!$C:$C,$U16)="","",INDEX('MiT Strom Pipeline'!$C:$C,$U16))) -> SH | D16: =IF($U16="","",IF(INDEX('MiT Strom Pipeline'!$D:$D,$U16)="","",INDEX('MiT Strom Pipeline'!$D:$D,$U16))) -> Events / Medien | E16: =IF($U16="","",IF(INDEX('MiT Strom Pipeline'!$H:$H,$U16)="","",INDEX('MiT Strom Pipeline'!$H:$H,$U16))) -> Juni | F16: =IF($U16="","",IF(INDEX('MiT Strom Pipeline'!$E:$E,$U16)="","",INDEX('MiT Strom Pipeline'!$E:$E,$U16))) -> 100 kVA Generator | G16: =IF($U16="","",IF(ISNUMBER(INDEX('MiT Strom Pipeline'!$I:$I,$U16)),INDEX('MiT Strom Pipeline'!$I:$I,$U16),0)) -> 0 | H16: =IF($U16="","",IF(ISNUMBER(INDEX('MiT Strom Pipeline'!$Q:$Q,$U16)),INDEX('MiT Strom Pipeline'!$Q:$Q,$U16),0)) -> 0 | I16: =IF($U16="","",IF(ISNUMBER(INDEX('MiT Strom Pipeline'!$O:$O,$U16)),INDEX('MiT Strom Pipeline'!$O:$O,$U16),0)) -> 0 | J16: =IF($U16="","",INDEX('MiT Strom Pipeline'!$R:$R,$U16)) -> WON | K16: =IF($U16="","",IF(ISNUMBER(INDEX('MiT Strom Pipeline'!$S:$S,$U16)),INDEX('MiT Strom Pipeline'!$S:$S,$U16),"")) -> 1 | L16: =IF($U16="","",IF(LEN(INDEX('MiT Strom Pipeline'!$V:$V,$U16))>0,LEFT(INDEX('MiT Strom Pipeline'!$V:$V,$U16),55),"")) -> Abgeschlossen | U16: =IFERROR(MATCH(6,'MiT Strom Pipeline'!$AB$6:$AB$860,0)+5,"") -> 15
A17: =IF($U17="","",IF(ISNUMBER(INDEX('MiT Strom Pipeline'!$A:$A,$U17)),INDEX('MiT Strom Pipeline'!$A:$A,$U17),"")) -> 29 | B17: =IF($U17="","",IF(INDEX('MiT Strom Pipeline'!$B:$B,$U17)="","",INDEX('MiT Strom Pipeline'!$B:$B,$U17))) -> Gampeln | C17: =IF($U17="","",IF(INDEX('MiT Strom Pipeline'!$C:$C,$U17)="","",INDEX('MiT Strom Pipeline'!$C:$C,$U17))) -> VS | D17: =IF($U17="","",IF(INDEX('MiT Strom Pipeline'!$D:$D,$U17)="","",INDEX('MiT Strom Pipeline'!$D:$D,$U17))) -> Event | E17: =IF($U17="","",IF(INDEX('MiT Strom Pipeline'!$H:$H,$U17)="","",INDEX('MiT Strom Pipeline'!$H:$H,$U17))) -> Aug | F17: =IF($U17="","",IF(INDEX('MiT Strom Pipeline'!$E:$E,$U17)="","",INDEX('MiT Strom Pipeline'!$E:$E,$U17))) -> 6x300 kVA, 9x200 kVA Generator ,1x150 kWH BESS | G17: =IF($U17="","",IF(ISNUMBER(INDEX('MiT Strom Pipeline'!$I:$I,$U17)),INDEX('MiT Strom Pipeline'!$I:$I,$U17),0)) -> 80621.21 | H17: =IF($U17="","",IF(ISNUMBER(INDEX('MiT Strom Pipeline'!$Q:$Q,$U17)),INDEX('MiT Strom Pipeline'!$Q:$Q,$U17),0)) -> 80621.21 | I17: =IF($U17="","",IF(ISNUMBER(INDEX('MiT Strom Pipeline'!$O:$O,$U17)),INDEX('MiT Strom Pipeline'!$O:$O,$U17),0)) -> -10507.9 | J17: =IF($U17="","",INDEX('MiT Strom Pipeline'!$R:$R,$U17)) -> WON | K17: =IF($U17="","",IF(ISNUMBER(INDEX('MiT Strom Pipeline'!$S:$S,$U17)),INDEX('MiT Strom Pipeline'!$S:$S,$U17),"")) -> 1 | L17: =IF($U17="","",IF(LEN(INDEX('MiT Strom Pipeline'!$V:$V,$U17))>0,LEFT(INDEX('MiT Strom Pipeline'!$V:$V,$U17),55),"")) -> Abgeschlossen | U17: =IFERROR(MATCH(7,'MiT Strom Pipeline'!$AB$6:$AB$860,0)+5,"") -> 22
A18: =IF($U18="","",IF(ISNUMBER(INDEX('MiT Strom Pipeline'!$A:$A,$U18)),INDEX('MiT Strom Pipeline'!$A:$A,$U18),"")) -> 50 | B18: =IF($U18="","",IF(INDEX('MiT Strom Pipeline'!$B:$B,$U18)="","",INDEX('MiT Strom Pipeline'!$B:$B,$U18))) -> EIDG AMT Agroscope | C18: =IF($U18="","",IF(INDEX('MiT Strom Pipeline'!$C:$C,$U18)="","",INDEX('MiT Strom Pipeline'!$C:$C,$U18))) -> ZH | D18: =IF($U18="","",IF(INDEX('MiT Strom Pipeline'!$D:$D,$U18)="","",INDEX('MiT Strom Pipeline'!$D:$D,$U18))) -> Forschung | E18: =IF($U18="","",IF(INDEX('MiT Strom Pipeline'!$H:$H,$U18)="","",INDEX('MiT Strom Pipeline'!$H:$H,$U18))) -> Aug | F18: =IF($U18="","",IF(INDEX('MiT Strom Pipeline'!$E:$E,$U18)="","",INDEX('MiT Strom Pipeline'!$E:$E,$U18))) -> 450 kVA | G18: =IF($U18="","",IF(ISNUMBER(INDEX('MiT Strom Pipeline'!$I:$I,$U18)),INDEX('MiT Strom Pipeline'!$I:$I,$U18),0)) -> 13533 | H18: =IF($U18="","",IF(ISNUMBER(INDEX('MiT Strom Pipeline'!$Q:$Q,$U18)),INDEX('MiT Strom Pipeline'!$Q:$Q,$U18),0)) -> 13533 | I18: =IF($U18="","",IF(ISNUMBER(INDEX('MiT Strom Pipeline'!$O:$O,$U18)),INDEX('MiT Strom Pipeline'!$O:$O,$U18),0)) -> 155.46 | J18: =IF($U18="","",INDEX('MiT Strom Pipeline'!$R:$R,$U18)) -> WON | K18: =IF($U18="","",IF(ISNUMBER(INDEX('MiT Strom Pipeline'!$S:$S,$U18)),INDEX('MiT Strom Pipeline'!$S:$S,$U18),"")) -> 1 | L18: =IF($U18="","",IF(LEN(INDEX('MiT Strom Pipeline'!$V:$V,$U18))>0,LEFT(INDEX('MiT Strom Pipeline'!$V:$V,$U18),55),"")) -> Abgeschlossen | U18: =IFERROR(MATCH(8,'MiT Strom Pipeline'!$AB$6:$AB$860,0)+5,"") -> 60
A19: =IF($U19="","",IF(ISNUMBER(INDEX('MiT Strom Pipeline'!$A:$A,$U19)),INDEX('MiT Strom Pipeline'!$A:$A,$U19),"")) -> 51 | B19: =IF($U19="","",IF(INDEX('MiT Strom Pipeline'!$B:$B,$U19)="","",INDEX('MiT Strom Pipeline'!$B:$B,$U19))) -> (Megger) Power Diagnostix Service GmbH | C19: =IF($U19="","",IF(INDEX('MiT Strom Pipeline'!$C:$C,$U19)="","",INDEX('MiT Strom Pipeline'!$C:$C,$U19))) -> TG | D19: =IF($U19="","",IF(INDEX('MiT Strom Pipeline'!$D:$D,$U19)="","",INDEX('MiT Strom Pipeline'!$D:$D,$U19))) -> EVU | E19: =IF($U19="","",IF(INDEX('MiT Strom Pipeline'!$H:$H,$U19)="","",INDEX('MiT Strom Pipeline'!$H:$H,$U19))) -> Juli | F19: =IF($U19="","",IF(INDEX('MiT Strom Pipeline'!$E:$E,$U19)="","",INDEX('MiT Strom Pipeline'!$E:$E,$U19))) -> 600 kVA | G19: =IF($U19="","",IF(ISNUMBER(INDEX('MiT Strom Pipeline'!$I:$I,$U19)),INDEX('MiT Strom Pipeline'!$I:$I,$U19),0)) -> 5488.9 | H19: =IF($U19="","",IF(ISNUMBER(INDEX('MiT Strom Pipeline'!$Q:$Q,$U19)),INDEX('MiT Strom Pipeline'!$Q:$Q,$U19),0)) -> 5488.9 | I19: =IF($U19="","",IF(ISNUMBER(INDEX('MiT Strom Pipeline'!$O:$O,$U19)),INDEX('MiT Strom Pipeline'!$O:$O,$U19),0)) -> -411.29 | J19: =IF($U19="","",INDEX('MiT Strom Pipeline'!$R:$R,$U19)) -> WON | K19: =IF($U19="","",IF(ISNUMBER(INDEX('MiT Strom Pipeline'!$S:$S,$U19)),INDEX('MiT Strom Pipeline'!$S:$S,$U19),"")) -> 1 | L19: =IF($U19="","",IF(LEN(INDEX('MiT Strom Pipeline'!$V:$V,$U19))>0,LEFT(INDEX('MiT Strom Pipeline'!$V:$V,$U19),55),"")) -> Abgeschlossen | U19: =IFERROR(MATCH(9,'MiT Strom Pipeline'!$AB$6:$AB$860,0)+5,"") -> 61
A20: =IF($U20="","",IF(ISNUMBER(INDEX('MiT Strom Pipeline'!$A:$A,$U20)),INDEX('MiT Strom Pipeline'!$A:$A,$U20),"")) -> 52 | B20: =IF($U20="","",IF(INDEX('MiT Strom Pipeline'!$B:$B,$U20)="","",INDEX('MiT Strom Pipeline'!$B:$B,$U20))) -> DPR Heat Loadbank | C20: =IF($U20="","",IF(INDEX('MiT Strom Pipeline'!$C:$C,$U20)="","",INDEX('MiT Strom Pipeline'!$C:$C,$U20))) -> ZH | D20: =IF($U20="","",IF(INDEX('MiT Strom Pipeline'!$D:$D,$U20)="","",INDEX('MiT Strom Pipeline'!$D:$D,$U20))) -> Datacenter | E20: =IF($U20="","",IF(INDEX('MiT Strom Pipeline'!$H:$H,$U20)="","",INDEX('MiT Strom Pipeline'!$H:$H,$U20))) -> Aug | F20: =IF($U20="","",IF(INDEX('MiT Strom Pipeline'!$E:$E,$U20)="","",INDEX('MiT Strom Pipeline'!$E:$E,$U20))) -> 54x200 kVA Loadbank | G20: =IF($U20="","",IF(ISNUMBER(INDEX('MiT Strom Pipeline'!$I:$I,$U20)),INDEX('MiT Strom Pipeline'!$I:$I,$U20),0)) -> 333790 | H20: =IF($U20="","",IF(ISNUMBER(INDEX('MiT Strom Pipeline'!$Q:$Q,$U20)),INDEX('MiT Strom Pipeline'!$Q:$Q,$U20),0)) -> 333790 | I20: =IF($U20="","",IF(ISNUMBER(INDEX('MiT Strom Pipeline'!$O:$O,$U20)),INDEX('MiT Strom Pipeline'!$O:$O,$U20),0)) -> -25011.09 | J20: =IF($U20="","",INDEX('MiT Strom Pipeline'!$R:$R,$U20)) -> WON | K20: =IF($U20="","",IF(ISNUMBER(INDEX('MiT Strom Pipeline'!$S:$S,$U20)),INDEX('MiT Strom Pipeline'!$S:$S,$U20),"")) -> 1 | L20: =IF($U20="","",IF(LEN(INDEX('MiT Strom Pipeline'!$V:$V,$U20))>0,LEFT(INDEX('MiT Strom Pipeline'!$V:$V,$U20),55),"")) -> Kunde angeschrieben auf MiT seite mit aktueller CHF Pre | U20: =IFERROR(MATCH(10,'MiT Strom Pipeline'!$AB$6:$AB$860,0)+5,"") -> 62
A21: =IF($U21="","",IF(ISNUMBER(INDEX('MiT Strom Pipeline'!$A:$A,$U21)),INDEX('MiT Strom Pipeline'!$A:$A,$U21),"")) -> 53 | B21: =IF($U21="","",IF(INDEX('MiT Strom Pipeline'!$B:$B,$U21)="","",INDEX('MiT Strom Pipeline'!$B:$B,$U21))) -> DPR Generator Loadbank Test | C21: =IF($U21="","",IF(INDEX('MiT Strom Pipeline'!$C:$C,$U21)="","",INDEX('MiT Strom Pipeline'!$C:$C,$U21))) -> ZH | D21: =IF($U21="","",IF(INDEX('MiT Strom Pipeline'!$D:$D,$U21)="","",INDEX('MiT Strom Pipeline'!$D:$D,$U21))) -> Datacenter | E21: =IF($U21="","",IF(INDEX('MiT Strom Pipeline'!$H:$H,$U21)="","",INDEX('MiT Strom Pipeline'!$H:$H,$U21))) -> Aug | F21: =IF($U21="","",IF(INDEX('MiT Strom Pipeline'!$E:$E,$U21)="","",INDEX('MiT Strom Pipeline'!$E:$E,$U21))) -> 6000 kVA Loadbank | G21: =IF($U21="","",IF(ISNUMBER(INDEX('MiT Strom Pipeline'!$I:$I,$U21)),INDEX('MiT Strom Pipeline'!$I:$I,$U21),0)) -> 331889.15 | H21: =IF($U21="","",IF(ISNUMBER(INDEX('MiT Strom Pipeline'!$Q:$Q,$U21)),INDEX('MiT Strom Pipeline'!$Q:$Q,$U21),0)) -> 331889.15 | I21: =IF($U21="","",IF(ISNUMBER(INDEX('MiT Strom Pipeline'!$O:$O,$U21)),INDEX('MiT Strom Pipeline'!$O:$O,$U21),0)) -> -24868.66 | J21: =IF($U21="","",INDEX('MiT Strom Pipeline'!$R:$R,$U21)) -> WON | K21: =IF($U21="","",IF(ISNUMBER(INDEX('MiT Strom Pipeline'!$S:$S,$U21)),INDEX('MiT Strom Pipeline'!$S:$S,$U21),"")) -> 1 | L21: =IF($U21="","",IF(LEN(INDEX('MiT Strom Pipeline'!$V:$V,$U21))>0,LEFT(INDEX('MiT Strom Pipeline'!$V:$V,$U21),55),"")) -> Kunde angeschrieben auf MiT seite mit aktueller CHF Pre | U21: =IFERROR(MATCH(11,'MiT Strom Pipeline'!$AB$6:$AB$860,0)+5,"") -> 63
A22: =IF($U22="","",IF(ISNUMBER(INDEX('MiT Strom Pipeline'!$A:$A,$U22)),INDEX('MiT Strom Pipeline'!$A:$A,$U22),"")) -> 61 | B22: =IF($U22="","",IF(INDEX('MiT Strom Pipeline'!$B:$B,$U22)="","",INDEX('MiT Strom Pipeline'!$B:$B,$U22))) -> GETEC Park.Swiss AG | C22: =IF($U22="","",IF(INDEX('MiT Strom Pipeline'!$C:$C,$U22)="","",INDEX('MiT Strom Pipeline'!$C:$C,$U22))) -> BL | D22: =IF($U22="","",IF(INDEX('MiT Strom Pipeline'!$D:$D,$U22)="","",INDEX('MiT Strom Pipeline'!$D:$D,$U22))) -> Industrie | E22: =IF($U22="","",IF(INDEX('MiT Strom Pipeline'!$H:$H,$U22)="","",INDEX('MiT Strom Pipeline'!$H:$H,$U22))) -> August | F22: =IF($U22="","",IF(INDEX('MiT Strom Pipeline'!$E:$E,$U22)="","",INDEX('MiT Strom Pipeline'!$E:$E,$U22))) -> 600 kVA | G22: =IF($U22="","",IF(ISNUMBER(INDEX('MiT Strom Pipeline'!$I:$I,$U22)),INDEX('MiT Strom Pipeline'!$I:$I,$U22),0)) -> 13472.18 | H22: =IF($U22="","",IF(ISNUMBER(INDEX('MiT Strom Pipeline'!$Q:$Q,$U22)),INDEX('MiT Strom Pipeline'!$Q:$Q,$U22),0)) -> 13472.18 | I22: =IF($U22="","",IF(ISNUMBER(INDEX('MiT Strom Pipeline'!$O:$O,$U22)),INDEX('MiT Strom Pipeline'!$O:$O,$U22),0)) -> 1.8189894e-12 | J22: =IF($U22="","",INDEX('MiT Strom Pipeline'!$R:$R,$U22)) -> WON | K22: =IF($U22="","",IF(ISNUMBER(INDEX('MiT Strom Pipeline'!$S:$S,$U22)),INDEX('MiT Strom Pipeline'!$S:$S,$U22),"")) -> 1 | L22: =IF($U22="","",IF(LEN(INDEX('MiT Strom Pipeline'!$V:$V,$U22))>0,LEFT(INDEX('MiT Strom Pipeline'!$V:$V,$U22),55),"")) -> Kunde angeschrieben, Offerte erstellt, Kunde hat Offert | U22: =IFERROR(MATCH(12,'MiT Strom Pipeline'!$AB$6:$AB$860,0)+5,"") -> 71
A23: =IF($U23="","",IF(ISNUMBER(INDEX('MiT Strom Pipeline'!$A:$A,$U23)),INDEX('MiT Strom Pipeline'!$A:$A,$U23),"")) | B23: =IF($U23="","",IF(INDEX('MiT Strom Pipeline'!$B:$B,$U23)="","",INDEX('MiT Strom Pipeline'!$B:$B,$U23))) | C23: =IF($U23="","",IF(INDEX('MiT Strom Pipeline'!$C:$C,$U23)="","",INDEX('MiT Strom Pipeline'!$C:$C,$U23))) | D23: =IF($U23="","",IF(INDEX('MiT Strom Pipeline'!$D:$D,$U23)="","",INDEX('MiT Strom Pipeline'!$D:$D,$U23))) | E23: =IF($U23="","",IF(INDEX('MiT Strom Pipeline'!$H:$H,$U23)="","",INDEX('MiT Strom Pipeline'!$H:$H,$U23))) | F23: =IF($U23="","",IF(INDEX('MiT Strom Pipeline'!$E:$E,$U23)="","",INDEX('MiT Strom Pipeline'!$E:$E,$U23))) | G23: =IF($U23="","",IF(ISNUMBER(INDEX('MiT Strom Pipeline'!$I:$I,$U23)),INDEX('MiT Strom Pipeline'!$I:$I,$U23),0)) | H23: =IF($U23="","",IF(ISNUMBER(INDEX('MiT Strom Pipeline'!$Q:$Q,$U23)),INDEX('MiT Strom Pipeline'!$Q:$Q,$U23),0)) | I23: =IF($U23="","",IF(ISNUMBER(INDEX('MiT Strom Pipeline'!$O:$O,$U23)),INDEX('MiT Strom Pipeline'!$O:$O,$U23),0)) | J23: =IF($U23="","",INDEX('MiT Strom Pipeline'!$R:$R,$U23)) | K23: =IF($U23="","",IF(ISNUMBER(INDEX('MiT Strom Pipeline'!$S:$S,$U23)),INDEX('MiT Strom Pipeline'!$S:$S,$U23),"")) | L23: =IF($U23="","",IF(LEN(INDEX('MiT Strom Pipeline'!$V:$V,$U23))>0,LEFT(INDEX('MiT Strom Pipeline'!$V:$V,$U23),55),"")) | U23: =IFERROR(MATCH(13,'MiT Strom Pipeline'!$AB$6:$AB$860,0)+5,"")
A24: =IF($U24="","",IF(ISNUMBER(INDEX('MiT Strom Pipeline'!$A:$A,$U24)),INDEX('MiT Strom Pipeline'!$A:$A,$U24),"")) | B24: =IF($U24="","",IF(INDEX('MiT Strom Pipeline'!$B:$B,$U24)="","",INDEX('MiT Strom Pipeline'!$B:$B,$U24))) | C24: =IF($U24="","",IF(INDEX('MiT Strom Pipeline'!$C:$C,$U24)="","",INDEX('MiT Strom Pipeline'!$C:$C,$U24))) | D24: =IF($U24="","",IF(INDEX('MiT Strom Pipeline'!$D:$D,$U24)="","",INDEX('MiT Strom Pipeline'!$D:$D,$U24))) | E24: =IF($U24="","",IF(INDEX('MiT Strom Pipeline'!$H:$H,$U24)="","",INDEX('MiT Strom Pipeline'!$H:$H,$U24))) | F24: =IF($U24="","",IF(INDEX('MiT Strom Pipeline'!$E:$E,$U24)="","",INDEX('MiT Strom Pipeline'!$E:$E,$U24))) | G24: =IF($U24="","",IF(ISNUMBER(INDEX('MiT Strom Pipeline'!$I:$I,$U24)),INDEX('MiT Strom Pipeline'!$I:$I,$U24),0)) | H24: =IF($U24="","",IF(ISNUMBER(INDEX('MiT Strom Pipeline'!$Q:$Q,$U24)),INDEX('MiT Strom Pipeline'!$Q:$Q,$U24),0)) | I24: =IF($U24="","",IF(ISNUMBER(INDEX('MiT Strom Pipeline'!$O:$O,$U24)),INDEX('MiT Strom Pipeline'!$O:$O,$U24),0)) | J24: =IF($U24="","",INDEX('MiT Strom Pipeline'!$R:$R,$U24)) | K24: =IF($U24="","",IF(ISNUMBER(INDEX('MiT Strom Pipeline'!$S:$S,$U24)),INDEX('MiT Strom Pipeline'!$S:$S,$U24),"")) | L24: =IF($U24="","",IF(LEN(INDEX('MiT Strom Pipeline'!$V:$V,$U24))>0,LEFT(INDEX('MiT Strom Pipeline'!$V:$V,$U24),55),"")) | U24: =IFERROR(MATCH(14,'MiT Strom Pipeline'!$AB$6:$AB$860,0)+5,"")
A25: =IF($U25="","",IF(ISNUMBER(INDEX('MiT Strom Pipeline'!$A:$A,$U25)),INDEX('MiT Strom Pipeline'!$A:$A,$U25),"")) | B25: =IF($U25="","",IF(INDEX('MiT Strom Pipeline'!$B:$B,$U25)="","",INDEX('MiT Strom Pipeline'!$B:$B,$U25))) | C25: =IF($U25="","",IF(INDEX('MiT Strom Pipeline'!$C:$C,$U25)="","",INDEX('MiT Strom Pipeline'!$C:$C,$U25))) | D25: =IF($U25="","",IF(INDEX('MiT Strom Pipeline'!$D:$D,$U25)="","",INDEX('MiT Strom Pipeline'!$D:$D,$U25))) | E25: =IF($U25="","",IF(INDEX('MiT Strom Pipeline'!$H:$H,$U25)="","",INDEX('MiT Strom Pipeline'!$H:$H,$U25))) | F25: =IF($U25="","",IF(INDEX('MiT Strom Pipeline'!$E:$E,$U25)="","",INDEX('MiT Strom Pipeline'!$E:$E,$U25))) | G25: =IF($U25="","",IF(ISNUMBER(INDEX('MiT Strom Pipeline'!$I:$I,$U25)),INDEX('MiT Strom Pipeline'!$I:$I,$U25),0)) | H25: =IF($U25="","",IF(ISNUMBER(INDEX('MiT Strom Pipeline'!$Q:$Q,$U25)),INDEX('MiT Strom Pipeline'!$Q:$Q,$U25),0)) | I25: =IF($U25="","",IF(ISNUMBER(INDEX('MiT Strom Pipeline'!$O:$O,$U25)),INDEX('MiT Strom Pipeline'!$O:$O,$U25),0)) | J25: =IF($U25="","",INDEX('MiT Strom Pipeline'!$R:$R,$U25)) | K25: =IF($U25="","",IF(ISNUMBER(INDEX('MiT Strom Pipeline'!$S:$S,$U25)),INDEX('MiT Strom Pipeline'!$S:$S,$U25),"")) | L25: =IF($U25="","",IF(LEN(INDEX('MiT Strom Pipeline'!$V:$V,$U25))>0,LEFT(INDEX('MiT Strom Pipeline'!$V:$V,$U25),55),"")) | U25: =IFERROR(MATCH(15,'MiT Strom Pipeline'!$AB$6:$AB$860,0)+5,"")
A26: =IF($U26="","",IF(ISNUMBER(INDEX('MiT Strom Pipeline'!$A:$A,$U26)),INDEX('MiT Strom Pipeline'!$A:$A,$U26),"")) | B26: =IF($U26="","",IF(INDEX('MiT Strom Pipeline'!$B:$B,$U26)="","",INDEX('MiT Strom Pipeline'!$B:$B,$U26))) | C26: =IF($U26="","",IF(INDEX('MiT Strom Pipeline'!$C:$C,$U26)="","",INDEX('MiT Strom Pipeline'!$C:$C,$U26))) | D26: =IF($U26="","",IF(INDEX('MiT Strom Pipeline'!$D:$D,$U26)="","",INDEX('MiT Strom Pipeline'!$D:$D,$U26))) | E26: =IF($U26="","",IF(INDEX('MiT Strom Pipeline'!$H:$H,$U26)="","",INDEX('MiT Strom Pipeline'!$H:$H,$U26))) | F26: =IF($U26="","",IF(INDEX('MiT Strom Pipeline'!$E:$E,$U26)="","",INDEX('MiT Strom Pipeline'!$E:$E,$U26))) | G26: =IF($U26="","",IF(ISNUMBER(INDEX('MiT Strom Pipeline'!$I:$I,$U26)),INDEX('MiT Strom Pipeline'!$I:$I,$U26),0)) | H26: =IF($U26="","",IF(ISNUMBER(INDEX('MiT Strom Pipeline'!$Q:$Q,$U26)),INDEX('MiT Strom Pipeline'!$Q:$Q,$U26),0)) | I26: =IF($U26="","",IF(ISNUMBER(INDEX('MiT Strom Pipeline'!$O:$O,$U26)),INDEX('MiT Strom Pipeline'!$O:$O,$U26),0)) | J26: =IF($U26="","",INDEX('MiT Strom Pipeline'!$R:$R,$U26)) | K26: =IF($U26="","",IF(ISNUMBER(INDEX('MiT Strom Pipeline'!$S:$S,$U26)),INDEX('MiT Strom Pipeline'!$S:$S,$U26),"")) | L26: =IF($U26="","",IF(LEN(INDEX('MiT Strom Pipeline'!$V:$V,$U26))>0,LEFT(INDEX('MiT Strom Pipeline'!$V:$V,$U26),55),"")) | U26: =IFERROR(MATCH(16,'MiT Strom Pipeline'!$AB$6:$AB$860,0)+5,"")
A27: =IF($U27="","",IF(ISNUMBER(INDEX('MiT Strom Pipeline'!$A:$A,$U27)),INDEX('MiT Strom Pipeline'!$A:$A,$U27),"")) | B27: =IF($U27="","",IF(INDEX('MiT Strom Pipeline'!$B:$B,$U27)="","",INDEX('MiT Strom Pipeline'!$B:$B,$U27))) | C27: =IF($U27="","",IF(INDEX('MiT Strom Pipeline'!$C:$C,$U27)="","",INDEX('MiT Strom Pipeline'!$C:$C,$U27))) | D27: =IF($U27="","",IF(INDEX('MiT Strom Pipeline'!$D:$D,$U27)="","",INDEX('MiT Strom Pipeline'!$D:$D,$U27))) | E27: =IF($U27="","",IF(INDEX('MiT Strom Pipeline'!$H:$H,$U27)="","",INDEX('MiT Strom Pipeline'!$H:$H,$U27))) | F27: =IF($U27="","",IF(INDEX('MiT Strom Pipeline'!$E:$E,$U27)="","",INDEX('MiT Strom Pipeline'!$E:$E,$U27))) | G27: =IF($U27="","",IF(ISNUMBER(INDEX('MiT Strom Pipeline'!$I:$I,$U27)),INDEX('MiT Strom Pipeline'!$I:$I,$U27),0)) | H27: =IF($U27="","",IF(ISNUMBER(INDEX('MiT Strom Pipeline'!$Q:$Q,$U27)),INDEX('MiT Strom Pipeline'!$Q:$Q,$U27),0)) | I27: =IF($U27="","",IF(ISNUMBER(INDEX('MiT Strom Pipeline'!$O:$O,$U27)),INDEX('MiT Strom Pipeline'!$O:$O,$U27),0)) | J27: =IF($U27="","",INDEX('MiT Strom Pipeline'!$R:$R,$U27)) | K27: =IF($U27="","",IF(ISNUMBER(INDEX('MiT Strom Pipeline'!$S:$S,$U27)),INDEX('MiT Strom Pipeline'!$S:$S,$U27),"")) | L27: =IF($U27="","",IF(LEN(INDEX('MiT Strom Pipeline'!$V:$V,$U27))>0,LEFT(INDEX('MiT Strom Pipeline'!$V:$V,$U27),55),"")) | U27: =IFERROR(MATCH(17,'MiT Strom Pipeline'!$AB$6:$AB$860,0)+5,"")
A28: =IF($U28="","",IF(ISNUMBER(INDEX('MiT Strom Pipeline'!$A:$A,$U28)),INDEX('MiT Strom Pipeline'!$A:$A,$U28),"")) | B28: =IF($U28="","",IF(INDEX('MiT Strom Pipeline'!$B:$B,$U28)="","",INDEX('MiT Strom Pipeline'!$B:$B,$U28))) | C28: =IF($U28="","",IF(INDEX('MiT Strom Pipeline'!$C:$C,$U28)="","",INDEX('MiT Strom Pipeline'!$C:$C,$U28))) | D28: =IF($U28="","",IF(INDEX('MiT Strom Pipeline'!$D:$D,$U28)="","",INDEX('MiT Strom Pipeline'!$D:$D,$U28))) | E28: =IF($U28="","",IF(INDEX('MiT Strom Pipeline'!$H:$H,$U28)="","",INDEX('MiT Strom Pipeline'!$H:$H,$U28))) | F28: =IF($U28="","",IF(INDEX('MiT Strom Pipeline'!$E:$E,$U28)="","",INDEX('MiT Strom Pipeline'!$E:$E,$U28))) | G28: =IF($U28="","",IF(ISNUMBER(INDEX('MiT Strom Pipeline'!$I:$I,$U28)),INDEX('MiT Strom Pipeline'!$I:$I,$U28),0)) | H28: =IF($U28="","",IF(ISNUMBER(INDEX('MiT Strom Pipeline'!$Q:$Q,$U28)),INDEX('MiT Strom Pipeline'!$Q:$Q,$U28),0)) | I28: =IF($U28="","",IF(ISNUMBER(INDEX('MiT Strom Pipeline'!$O:$O,$U28)),INDEX('MiT Strom Pipeline'!$O:$O,$U28),0)) | J28: =IF($U28="","",INDEX('MiT Strom Pipeline'!$R:$R,$U28)) | K28: =IF($U28="","",IF(ISNUMBER(INDEX('MiT Strom Pipeline'!$S:$S,$U28)),INDEX('MiT Strom Pipeline'!$S:$S,$U28),"")) | L28: =IF($U28="","",IF(LEN(INDEX('MiT Strom Pipeline'!$V:$V,$U28))>0,LEFT(INDEX('MiT Strom Pipeline'!$V:$V,$U28),55),"")) | U28: =IFERROR(MATCH(18,'MiT Strom Pipeline'!$AB$6:$AB$860,0)+5,"")
A29: =IF($U29="","",IF(ISNUMBER(INDEX('MiT Strom Pipeline'!$A:$A,$U29)),INDEX('MiT Strom Pipeline'!$A:$A,$U29),"")) | B29: =IF($U29="","",IF(INDEX('MiT Strom Pipeline'!$B:$B,$U29)="","",INDEX('MiT Strom Pipeline'!$B:$B,$U29))) | C29: =IF($U29="","",IF(INDEX('MiT Strom Pipeline'!$C:$C,$U29)="","",INDEX('MiT Strom Pipeline'!$C:$C,$U29))) | D29: =IF($U29="","",IF(INDEX('MiT Strom Pipeline'!$D:$D,$U29)="","",INDEX('MiT Strom Pipeline'!$D:$D,$U29))) | E29: =IF($U29="","",IF(INDEX('MiT Strom Pipeline'!$H:$H,$U29)="","",INDEX('MiT Strom Pipeline'!$H:$H,$U29))) | F29: =IF($U29="","",IF(INDEX('MiT Strom Pipeline'!$E:$E,$U29)="","",INDEX('MiT Strom Pipeline'!$E:$E,$U29))) | G29: =IF($U29="","",IF(ISNUMBER(INDEX('MiT Strom Pipeline'!$I:$I,$U29)),INDEX('MiT Strom Pipeline'!$I:$I,$U29),0)) | H29: =IF($U29="","",IF(ISNUMBER(INDEX('MiT Strom Pipeline'!$Q:$Q,$U29)),INDEX('MiT Strom Pipeline'!$Q:$Q,$U29),0)) | I29: =IF($U29="","",IF(ISNUMBER(INDEX('MiT Strom Pipeline'!$O:$O,$U29)),INDEX('MiT Strom Pipeline'!$O:$O,$U29),0)) | J29: =IF($U29="","",INDEX('MiT Strom Pipeline'!$R:$R,$U29)) | K29: =IF($U29="","",IF(ISNUMBER(INDEX('MiT Strom Pipeline'!$S:$S,$U29)),INDEX('MiT Strom Pipeline'!$S:$S,$U29),"")) | L29: =IF($U29="","",IF(LEN(INDEX('MiT Strom Pipeline'!$V:$V,$U29))>0,LEFT(INDEX('MiT Strom Pipeline'!$V:$V,$U29),55),"")) | U29: =IFERROR(MATCH(19,'MiT Strom Pipeline'!$AB$6:$AB$860,0)+5,"")
A30: =IF($U30="","",IF(ISNUMBER(INDEX('MiT Strom Pipeline'!$A:$A,$U30)),INDEX('MiT Strom Pipeline'!$A:$A,$U30),"")) | B30: =IF($U30="","",IF(INDEX('MiT Strom Pipeline'!$B:$B,$U30)="","",INDEX('MiT Strom Pipeline'!$B:$B,$U30))) | C30: =IF($U30="","",IF(INDEX('MiT Strom Pipeline'!$C:$C,$U30)="","",INDEX('MiT Strom Pipeline'!$C:$C,$U30))) | D30: =IF($U30="","",IF(INDEX('MiT Strom Pipeline'!$D:$D,$U30)="","",INDEX('MiT Strom Pipeline'!$D:$D,$U30))) | E30: =IF($U30="","",IF(INDEX('MiT Strom Pipeline'!$H:$H,$U30)="","",INDEX('MiT Strom Pipeline'!$H:$H,$U30))) | F30: =IF($U30="","",IF(INDEX('MiT Strom Pipeline'!$E:$E,$U30)="","",INDEX('MiT Strom Pipeline'!$E:$E,$U30))) | G30: =IF($U30="","",IF(ISNUMBER(INDEX('MiT Strom Pipeline'!$I:$I,$U30)),INDEX('MiT Strom Pipeline'!$I:$I,$U30),0)) | H30: =IF($U30="","",IF(ISNUMBER(INDEX('MiT Strom Pipeline'!$Q:$Q,$U30)),INDEX('MiT Strom Pipeline'!$Q:$Q,$U30),0)) | I30: =IF($U30="","",IF(ISNUMBER(INDEX('MiT Strom Pipeline'!$O:$O,$U30)),INDEX('MiT Strom Pipeline'!$O:$O,$U30),0)) | J30: =IF($U30="","",INDEX('MiT Strom Pipeline'!$R:$R,$U30)) | K30: =IF($U30="","",IF(ISNUMBER(INDEX('MiT Strom Pipeline'!$S:$S,$U30)),INDEX('MiT Strom Pipeline'!$S:$S,$U30),"")) | L30: =IF($U30="","",IF(LEN(INDEX('MiT Strom Pipeline'!$V:$V,$U30))>0,LEFT(INDEX('MiT Strom Pipeline'!$V:$V,$U30),55),"")) | U30: =IFERROR(MATCH(20,'MiT Strom Pipeline'!$AB$6:$AB$860,0)+5,"")
A31: =IF($U31="","",IF(ISNUMBER(INDEX('MiT Strom Pipeline'!$A:$A,$U31)),INDEX('MiT Strom Pipeline'!$A:$A,$U31),"")) | B31: =IF($U31="","",IF(INDEX('MiT Strom Pipeline'!$B:$B,$U31)="","",INDEX('MiT Strom Pipeline'!$B:$B,$U31))) | C31: =IF($U31="","",IF(INDEX('MiT Strom Pipeline'!$C:$C,$U31)="","",INDEX('MiT Strom Pipeline'!$C:$C,$U31))) | D31: =IF($U31="","",IF(INDEX('MiT Strom Pipeline'!$D:$D,$U31)="","",INDEX('MiT Strom Pipeline'!$D:$D,$U31))) | E31: =IF($U31="","",IF(INDEX('MiT Strom Pipeline'!$H:$H,$U31)="","",INDEX('MiT Strom Pipeline'!$H:$H,$U31))) | F31: =IF($U31="","",IF(INDEX('MiT Strom Pipeline'!$E:$E,$U31)="","",INDEX('MiT Strom Pipeline'!$E:$E,$U31))) | G31: =IF($U31="","",IF(ISNUMBER(INDEX('MiT Strom Pipeline'!$I:$I,$U31)),INDEX('MiT Strom Pipeline'!$I:$I,$U31),0)) | H31: =IF($U31="","",IF(ISNUMBER(INDEX('MiT Strom Pipeline'!$Q:$Q,$U31)),INDEX('MiT Strom Pipeline'!$Q:$Q,$U31),0)) | I31: =IF($U31="","",IF(ISNUMBER(INDEX('MiT Strom Pipeline'!$O:$O,$U31)),INDEX('MiT Strom Pipeline'!$O:$O,$U31),0)) | J31: =IF($U31="","",INDEX('MiT Strom Pipeline'!$R:$R,$U31)) | K31: =IF($U31="","",IF(ISNUMBER(INDEX('MiT Strom Pipeline'!$S:$S,$U31)),INDEX('MiT Strom Pipeline'!$S:$S,$U31),"")) | L31: =IF($U31="","",IF(LEN(INDEX('MiT Strom Pipeline'!$V:$V,$U31))>0,LEFT(INDEX('MiT Strom Pipeline'!$V:$V,$U31),55),"")) | U31: =IFERROR(MATCH(21,'MiT Strom Pipeline'!$AB$6:$AB$860,0)+5,"")
A32: =IF($U32="","",IF(ISNUMBER(INDEX('MiT Strom Pipeline'!$A:$A,$U32)),INDEX('MiT Strom Pipeline'!$A:$A,$U32),"")) | B32: =IF($U32="","",IF(INDEX('MiT Strom Pipeline'!$B:$B,$U32)="","",INDEX('MiT Strom Pipeline'!$B:$B,$U32))) | C32: =IF($U32="","",IF(INDEX('MiT Strom Pipeline'!$C:$C,$U32)="","",INDEX('MiT Strom Pipeline'!$C:$C,$U32))) | D32: =IF($U32="","",IF(INDEX('MiT Strom Pipeline'!$D:$D,$U32)="","",INDEX('MiT Strom Pipeline'!$D:$D,$U32))) | E32: =IF($U32="","",IF(INDEX('MiT Strom Pipeline'!$H:$H,$U32)="","",INDEX('MiT Strom Pipeline'!$H:$H,$U32))) | F32: =IF($U32="","",IF(INDEX('MiT Strom Pipeline'!$E:$E,$U32)="","",INDEX('MiT Strom Pipeline'!$E:$E,$U32))) | G32: =IF($U32="","",IF(ISNUMBER(INDEX('MiT Strom Pipeline'!$I:$I,$U32)),INDEX('MiT Strom Pipeline'!$I:$I,$U32),0)) | H32: =IF($U32="","",IF(ISNUMBER(INDEX('MiT Strom Pipeline'!$Q:$Q,$U32)),INDEX('MiT Strom Pipeline'!$Q:$Q,$U32),0)) | I32: =IF($U32="","",IF(ISNUMBER(INDEX('MiT Strom Pipeline'!$O:$O,$U32)),INDEX('MiT Strom Pipeline'!$O:$O,$U32),0)) | J32: =IF($U32="","",INDEX('MiT Strom Pipeline'!$R:$R,$U32)) | K32: =IF($U32="","",IF(ISNUMBER(INDEX('MiT Strom Pipeline'!$S:$S,$U32)),INDEX('MiT Strom Pipeline'!$S:$S,$U32),"")) | L32: =IF($U32="","",IF(LEN(INDEX('MiT Strom Pipeline'!$V:$V,$U32))>0,LEFT(INDEX('MiT Strom Pipeline'!$V:$V,$U32),55),"")) | U32: =IFERROR(MATCH(22,'MiT Strom Pipeline'!$AB$6:$AB$860,0)+5,"")
A33: =IF($U33="","",IF(ISNUMBER(INDEX('MiT Strom Pipeline'!$A:$A,$U33)),INDEX('MiT Strom Pipeline'!$A:$A,$U33),"")) | B33: =IF($U33="","",IF(INDEX('MiT Strom Pipeline'!$B:$B,$U33)="","",INDEX('MiT Strom Pipeline'!$B:$B,$U33))) | C33: =IF($U33="","",IF(INDEX('MiT Strom Pipeline'!$C:$C,$U33)="","",INDEX('MiT Strom Pipeline'!$C:$C,$U33))) | D33: =IF($U33="","",IF(INDEX('MiT Strom Pipeline'!$D:$D,$U33)="","",INDEX('MiT Strom Pipeline'!$D:$D,$U33))) | E33: =IF($U33="","",IF(INDEX('MiT Strom Pipeline'!$H:$H,$U33)="","",INDEX('MiT Strom Pipeline'!$H:$H,$U33))) | F33: =IF($U33="","",IF(INDEX('MiT Strom Pipeline'!$E:$E,$U33)="","",INDEX('MiT Strom Pipeline'!$E:$E,$U33))) | G33: =IF($U33="","",IF(ISNUMBER(INDEX('MiT Strom Pipeline'!$I:$I,$U33)),INDEX('MiT Strom Pipeline'!$I:$I,$U33),0)) | H33: =IF($U33="","",IF(ISNUMBER(INDEX('MiT Strom Pipeline'!$Q:$Q,$U33)),INDEX('MiT Strom Pipeline'!$Q:$Q,$U33),0)) | I33: =IF($U33="","",IF(ISNUMBER(INDEX('MiT Strom Pipeline'!$O:$O,$U33)),INDEX('MiT Strom Pipeline'!$O:$O,$U33),0)) | J33: =IF($U33="","",INDEX('MiT Strom Pipeline'!$R:$R,$U33)) | K33: =IF($U33="","",IF(ISNUMBER(INDEX('MiT Strom Pipeline'!$S:$S,$U33)),INDEX('MiT Strom Pipeline'!$S:$S,$U33),"")) | L33: =IF($U33="","",IF(LEN(INDEX('MiT Strom Pipeline'!$V:$V,$U33))>0,LEFT(INDEX('MiT Strom Pipeline'!$V:$V,$U33),55),"")) | U33: =IFERROR(MATCH(23,'MiT Strom Pipeline'!$AB$6:$AB$860,0)+5,"")
A34: =IF($U34="","",IF(ISNUMBER(INDEX('MiT Strom Pipeline'!$A:$A,$U34)),INDEX('MiT Strom Pipeline'!$A:$A,$U34),"")) | B34: =IF($U34="","",IF(INDEX('MiT Strom Pipeline'!$B:$B,$U34)="","",INDEX('MiT Strom Pipeline'!$B:$B,$U34))) | C34: =IF($U34="","",IF(INDEX('MiT Strom Pipeline'!$C:$C,$U34)="","",INDEX('MiT Strom Pipeline'!$C:$C,$U34))) | D34: =IF($U34="","",IF(INDEX('MiT Strom Pipeline'!$D:$D,$U34)="","",INDEX('MiT Strom Pipeline'!$D:$D,$U34))) | E34: =IF($U34="","",IF(INDEX('MiT Strom Pipeline'!$H:$H,$U34)="","",INDEX('MiT Strom Pipeline'!$H:$H,$U34))) | F34: =IF($U34="","",IF(INDEX('MiT Strom Pipeline'!$E:$E,$U34)="","",INDEX('MiT Strom Pipeline'!$E:$E,$U34))) | G34: =IF($U34="","",IF(ISNUMBER(INDEX('MiT Strom Pipeline'!$I:$I,$U34)),INDEX('MiT Strom Pipeline'!$I:$I,$U34),0)) | H34: =IF($U34="","",IF(ISNUMBER(INDEX('MiT Strom Pipeline'!$Q:$Q,$U34)),INDEX('MiT Strom Pipeline'!$Q:$Q,$U34),0)) | I34: =IF($U34="","",IF(ISNUMBER(INDEX('MiT Strom Pipeline'!$O:$O,$U34)),INDEX('MiT Strom Pipeline'!$O:$O,$U34),0)) | J34: =IF($U34="","",INDEX('MiT Strom Pipeline'!$R:$R,$U34)) | K34: =IF($U34="","",IF(ISNUMBER(INDEX('MiT Strom Pipeline'!$S:$S,$U34)),INDEX('MiT Strom Pipeline'!$S:$S,$U34),"")) | L34: =IF($U34="","",IF(LEN(INDEX('MiT Strom Pipeline'!$V:$V,$U34))>0,LEFT(INDEX('MiT Strom Pipeline'!$V:$V,$U34),55),"")) | U34: =IFERROR(MATCH(24,'MiT Strom Pipeline'!$AB$6:$AB$860,0)+5,"")
A35: =IF($U35="","",IF(ISNUMBER(INDEX('MiT Strom Pipeline'!$A:$A,$U35)),INDEX('MiT Strom Pipeline'!$A:$A,$U35),"")) | B35: =IF($U35="","",IF(INDEX('MiT Strom Pipeline'!$B:$B,$U35)="","",INDEX('MiT Strom Pipeline'!$B:$B,$U35))) | C35: =IF($U35="","",IF(INDEX('MiT Strom Pipeline'!$C:$C,$U35)="","",INDEX('MiT Strom Pipeline'!$C:$C,$U35))) | D35: =IF($U35="","",IF(INDEX('MiT Strom Pipeline'!$D:$D,$U35)="","",INDEX('MiT Strom Pipeline'!$D:$D,$U35))) | E35: =IF($U35="","",IF(INDEX('MiT Strom Pipeline'!$H:$H,$U35)="","",INDEX('MiT Strom Pipeline'!$H:$H,$U35))) | F35: =IF($U35="","",IF(INDEX('MiT Strom Pipeline'!$E:$E,$U35)="","",INDEX('MiT Strom Pipeline'!$E:$E,$U35))) | G35: =IF($U35="","",IF(ISNUMBER(INDEX('MiT Strom Pipeline'!$I:$I,$U35)),INDEX('MiT Strom Pipeline'!$I:$I,$U35),0)) | H35: =IF($U35="","",IF(ISNUMBER(INDEX('MiT Strom Pipeline'!$Q:$Q,$U35)),INDEX('MiT Strom Pipeline'!$Q:$Q,$U35),0)) | I35: =IF($U35="","",IF(ISNUMBER(INDEX('MiT Strom Pipeline'!$O:$O,$U35)),INDEX('MiT Strom Pipeline'!$O:$O,$U35),0)) | J35: =IF($U35="","",INDEX('MiT Strom Pipeline'!$R:$R,$U35)) | K35: =IF($U35="","",IF(ISNUMBER(INDEX('MiT Strom Pipeline'!$S:$S,$U35)),INDEX('MiT Strom Pipeline'!$S:$S,$U35),"")) | L35: =IF($U35="","",IF(LEN(INDEX('MiT Strom Pipeline'!$V:$V,$U35))>0,LEFT(INDEX('MiT Strom Pipeline'!$V:$V,$U35),55),"")) | U35: =IFERROR(MATCH(25,'MiT Strom Pipeline'!$AB$6:$AB$860,0)+5,"")
A36: =IF($U36="","",IF(ISNUMBER(INDEX('MiT Strom Pipeline'!$A:$A,$U36)),INDEX('MiT Strom Pipeline'!$A:$A,$U36),"")) | B36: =IF($U36="","",IF(INDEX('MiT Strom Pipeline'!$B:$B,$U36)="","",INDEX('MiT Strom Pipeline'!$B:$B,$U36))) | C36: =IF($U36="","",IF(INDEX('MiT Strom Pipeline'!$C:$C,$U36)="","",INDEX('MiT Strom Pipeline'!$C:$C,$U36))) | D36: =IF($U36="","",IF(INDEX('MiT Strom Pipeline'!$D:$D,$U36)="","",INDEX('MiT Strom Pipeline'!$D:$D,$U36))) | E36: =IF($U36="","",IF(INDEX('MiT Strom Pipeline'!$H:$H,$U36)="","",INDEX('MiT Strom Pipeline'!$H:$H,$U36))) | F36: =IF($U36="","",IF(INDEX('MiT Strom Pipeline'!$E:$E,$U36)="","",INDEX('MiT Strom Pipeline'!$E:$E,$U36))) | G36: =IF($U36="","",IF(ISNUMBER(INDEX('MiT Strom Pipeline'!$I:$I,$U36)),INDEX('MiT Strom Pipeline'!$I:$I,$U36),0)) | H36: =IF($U36="","",IF(ISNUMBER(INDEX('MiT Strom Pipeline'!$Q:$Q,$U36)),INDEX('MiT Strom Pipeline'!$Q:$Q,$U36),0)) | I36: =IF($U36="","",IF(ISNUMBER(INDEX('MiT Strom Pipeline'!$O:$O,$U36)),INDEX('MiT Strom Pipeline'!$O:$O,$U36),0)) | J36: =IF($U36="","",INDEX('MiT Strom Pipeline'!$R:$R,$U36)) | K36: =IF($U36="","",IF(ISNUMBER(INDEX('MiT Strom Pipeline'!$S:$S,$U36)),INDEX('MiT Strom Pipeline'!$S:$S,$U36),"")) | L36: =IF($U36="","",IF(LEN(INDEX('MiT Strom Pipeline'!$V:$V,$U36))>0,LEFT(INDEX('MiT Strom Pipeline'!$V:$V,$U36),55),"")) | U36: =IFERROR(MATCH(26,'MiT Strom Pipeline'!$AB$6:$AB$860,0)+5,"")
A37: =IF($U37="","",IF(ISNUMBER(INDEX('MiT Strom Pipeline'!$A:$A,$U37)),INDEX('MiT Strom Pipeline'!$A:$A,$U37),"")) | B37: =IF($U37="","",IF(INDEX('MiT Strom Pipeline'!$B:$B,$U37)="","",INDEX('MiT Strom Pipeline'!$B:$B,$U37))) | C37: =IF($U37="","",IF(INDEX('MiT Strom Pipeline'!$C:$C,$U37)="","",INDEX('MiT Strom Pipeline'!$C:$C,$U37))) | D37: =IF($U37="","",IF(INDEX('MiT Strom Pipeline'!$D:$D,$U37)="","",INDEX('MiT Strom Pipeline'!$D:$D,$U37))) | E37: =IF($U37="","",IF(INDEX('MiT Strom Pipeline'!$H:$H,$U37)="","",INDEX('MiT Strom Pipeline'!$H:$H,$U37))) | F37: =IF($U37="","",IF(INDEX('MiT Strom Pipeline'!$E:$E,$U37)="","",INDEX('MiT Strom Pipeline'!$E:$E,$U37))) | G37: =IF($U37="","",IF(ISNUMBER(INDEX('MiT Strom Pipeline'!$I:$I,$U37)),INDEX('MiT Strom Pipeline'!$I:$I,$U37),0)) | H37: =IF($U37="","",IF(ISNUMBER(INDEX('MiT Strom Pipeline'!$Q:$Q,$U37)),INDEX('MiT Strom Pipeline'!$Q:$Q,$U37),0)) | I37: =IF($U37="","",IF(ISNUMBER(INDEX('MiT Strom Pipeline'!$O:$O,$U37)),INDEX('MiT Strom Pipeline'!$O:$O,$U37),0)) | J37: =IF($U37="","",INDEX('MiT Strom Pipeline'!$R:$R,$U37)) | K37: =IF($U37="","",IF(ISNUMBER(INDEX('MiT Strom Pipeline'!$S:$S,$U37)),INDEX('MiT Strom Pipeline'!$S:$S,$U37),"")) | L37: =IF($U37="","",IF(LEN(INDEX('MiT Strom Pipeline'!$V:$V,$U37))>0,LEFT(INDEX('MiT Strom Pipeline'!$V:$V,$U37),55),"")) | U37: =IFERROR(MATCH(27,'MiT Strom Pipeline'!$AB$6:$AB$860,0)+5,"")
A38: =IF($U38="","",IF(ISNUMBER(INDEX('MiT Strom Pipeline'!$A:$A,$U38)),INDEX('MiT Strom Pipeline'!$A:$A,$U38),"")) | B38: =IF($U38="","",IF(INDEX('MiT Strom Pipeline'!$B:$B,$U38)="","",INDEX('MiT Strom Pipeline'!$B:$B,$U38))) | C38: =IF($U38="","",IF(INDEX('MiT Strom Pipeline'!$C:$C,$U38)="","",INDEX('MiT Strom Pipeline'!$C:$C,$U38))) | D38: =IF($U38="","",IF(INDEX('MiT Strom Pipeline'!$D:$D,$U38)="","",INDEX('MiT Strom Pipeline'!$D:$D,$U38))) | E38: =IF($U38="","",IF(INDEX('MiT Strom Pipeline'!$H:$H,$U38)="","",INDEX('MiT Strom Pipeline'!$H:$H,$U38))) | F38: =IF($U38="","",IF(INDEX('MiT Strom Pipeline'!$E:$E,$U38)="","",INDEX('MiT Strom Pipeline'!$E:$E,$U38))) | G38: =IF($U38="","",IF(ISNUMBER(INDEX('MiT Strom Pipeline'!$I:$I,$U38)),INDEX('MiT Strom Pipeline'!$I:$I,$U38),0)) | H38: =IF($U38="","",IF(ISNUMBER(INDEX('MiT Strom Pipeline'!$Q:$Q,$U38)),INDEX('MiT Strom Pipeline'!$Q:$Q,$U38),0)) | I38: =IF($U38="","",IF(ISNUMBER(INDEX('MiT Strom Pipeline'!$O:$O,$U38)),INDEX('MiT Strom Pipeline'!$O:$O,$U38),0)) | J38: =IF($U38="","",INDEX('MiT Strom Pipeline'!$R:$R,$U38)) | K38: =IF($U38="","",IF(ISNUMBER(INDEX('MiT Strom Pipeline'!$S:$S,$U38)),INDEX('MiT Strom Pipeline'!$S:$S,$U38),"")) | L38: =IF($U38="","",IF(LEN(INDEX('MiT Strom Pipeline'!$V:$V,$U38))>0,LEFT(INDEX('MiT Strom Pipeline'!$V:$V,$U38),55),"")) | U38: =IFERROR(MATCH(28,'MiT Strom Pipeline'!$AB$6:$AB$860,0)+5,"")
A39: =IF($U39="","",IF(ISNUMBER(INDEX('MiT Strom Pipeline'!$A:$A,$U39)),INDEX('MiT Strom Pipeline'!$A:$A,$U39),"")) | B39: =IF($U39="","",IF(INDEX('MiT Strom Pipeline'!$B:$B,$U39)="","",INDEX('MiT Strom Pipeline'!$B:$B,$U39))) | C39: =IF($U39="","",IF(INDEX('MiT Strom Pipeline'!$C:$C,$U39)="","",INDEX('MiT Strom Pipeline'!$C:$C,$U39))) | D39: =IF($U39="","",IF(INDEX('MiT Strom Pipeline'!$D:$D,$U39)="","",INDEX('MiT Strom Pipeline'!$D:$D,$U39))) | E39: =IF($U39="","",IF(INDEX('MiT Strom Pipeline'!$H:$H,$U39)="","",INDEX('MiT Strom Pipeline'!$H:$H,$U39))) | F39: =IF($U39="","",IF(INDEX('MiT Strom Pipeline'!$E:$E,$U39)="","",INDEX('MiT Strom Pipeline'!$E:$E,$U39))) | G39: =IF($U39="","",IF(ISNUMBER(INDEX('MiT Strom Pipeline'!$I:$I,$U39)),INDEX('MiT Strom Pipeline'!$I:$I,$U39),0)) | H39: =IF($U39="","",IF(ISNUMBER(INDEX('MiT Strom Pipeline'!$Q:$Q,$U39)),INDEX('MiT Strom Pipeline'!$Q:$Q,$U39),0)) | I39: =IF($U39="","",IF(ISNUMBER(INDEX('MiT Strom Pipeline'!$O:$O,$U39)),INDEX('MiT Strom Pipeline'!$O:$O,$U39),0)) | J39: =IF($U39="","",INDEX('MiT Strom Pipeline'!$R:$R,$U39)) | K39: =IF($U39="","",IF(ISNUMBER(INDEX('MiT Strom Pipeline'!$S:$S,$U39)),INDEX('MiT Strom Pipeline'!$S:$S,$U39),"")) | L39: =IF($U39="","",IF(LEN(INDEX('MiT Strom Pipeline'!$V:$V,$U39))>0,LEFT(INDEX('MiT Strom Pipeline'!$V:$V,$U39),55),"")) | U39: =IFERROR(MATCH(29,'MiT Strom Pipeline'!$AB$6:$AB$860,0)+5,"")
A40: =IF($U40="","",IF(ISNUMBER(INDEX('MiT Strom Pipeline'!$A:$A,$U40)),INDEX('MiT Strom Pipeline'!$A:$A,$U40),"")) | B40: =IF($U40="","",IF(INDEX('MiT Strom Pipeline'!$B:$B,$U40)="","",INDEX('MiT Strom Pipeline'!$B:$B,$U40))) | C40: =IF($U40="","",IF(INDEX('MiT Strom Pipeline'!$C:$C,$U40)="","",INDEX('MiT Strom Pipeline'!$C:$C,$U40))) | D40: =IF($U40="","",IF(INDEX('MiT Strom Pipeline'!$D:$D,$U40)="","",INDEX('MiT Strom Pipeline'!$D:$D,$U40))) | E40: =IF($U40="","",IF(INDEX('MiT Strom Pipeline'!$H:$H,$U40)="","",INDEX('MiT Strom Pipeline'!$H:$H,$U40))) | F40: =IF($U40="","",IF(INDEX('MiT Strom Pipeline'!$E:$E,$U40)="","",INDEX('MiT Strom Pipeline'!$E:$E,$U40))) | G40: =IF($U40="","",IF(ISNUMBER(INDEX('MiT Strom Pipeline'!$I:$I,$U40)),INDEX('MiT Strom Pipeline'!$I:$I,$U40),0)) | H40: =IF($U40="","",IF(ISNUMBER(INDEX('MiT Strom Pipeline'!$Q:$Q,$U40)),INDEX('MiT Strom Pipeline'!$Q:$Q,$U40),0)) | I40: =IF($U40="","",IF(ISNUMBER(INDEX('MiT Strom Pipeline'!$O:$O,$U40)),INDEX('MiT Strom Pipeline'!$O:$O,$U40),0)) | J40: =IF($U40="","",INDEX('MiT Strom Pipeline'!$R:$R,$U40)) | K40: =IF($U40="","",IF(ISNUMBER(INDEX('MiT Strom Pipeline'!$S:$S,$U40)),INDEX('MiT Strom Pipeline'!$S:$S,$U40),"")) | L40: =IF($U40="","",IF(LEN(INDEX('MiT Strom Pipeline'!$V:$V,$U40))>0,LEFT(INDEX('MiT Strom Pipeline'!$V:$V,$U40),55),"")) | U40: =IFERROR(MATCH(30,'MiT Strom Pipeline'!$AB$6:$AB$860,0)+5,"")
A41: =IF($U41="","",IF(ISNUMBER(INDEX('MiT Strom Pipeline'!$A:$A,$U41)),INDEX('MiT Strom Pipeline'!$A:$A,$U41),"")) | B41: =IF($U41="","",IF(INDEX('MiT Strom Pipeline'!$B:$B,$U41)="","",INDEX('MiT Strom Pipeline'!$B:$B,$U41))) | C41: =IF($U41="","",IF(INDEX('MiT Strom Pipeline'!$C:$C,$U41)="","",INDEX('MiT Strom Pipeline'!$C:$C,$U41))) | D41: =IF($U41="","",IF(INDEX('MiT Strom Pipeline'!$D:$D,$U41)="","",INDEX('MiT Strom Pipeline'!$D:$D,$U41))) | E41: =IF($U41="","",IF(INDEX('MiT Strom Pipeline'!$H:$H,$U41)="","",INDEX('MiT Strom Pipeline'!$H:$H,$U41))) | F41: =IF($U41="","",IF(INDEX('MiT Strom Pipeline'!$E:$E,$U41)="","",INDEX('MiT Strom Pipeline'!$E:$E,$U41))) | G41: =IF($U41="","",IF(ISNUMBER(INDEX('MiT Strom Pipeline'!$I:$I,$U41)),INDEX('MiT Strom Pipeline'!$I:$I,$U41),0)) | H41: =IF($U41="","",IF(ISNUMBER(INDEX('MiT Strom Pipeline'!$Q:$Q,$U41)),INDEX('MiT Strom Pipeline'!$Q:$Q,$U41),0)) | I41: =IF($U41="","",IF(ISNUMBER(INDEX('MiT Strom Pipeline'!$O:$O,$U41)),INDEX('MiT Strom Pipeline'!$O:$O,$U41),0)) | J41: =IF($U41="","",INDEX('MiT Strom Pipeline'!$R:$R,$U41)) | K41: =IF($U41="","",IF(ISNUMBER(INDEX('MiT Strom Pipeline'!$S:$S,$U41)),INDEX('MiT Strom Pipeline'!$S:$S,$U41),"")) | L41: =IF($U41="","",IF(LEN(INDEX('MiT Strom Pipeline'!$V:$V,$U41))>0,LEFT(INDEX('MiT Strom Pipeline'!$V:$V,$U41),55),"")) | U41: =IFERROR(MATCH(31,'MiT Strom Pipeline'!$AB$6:$AB$860,0)+5,"")
A42: =IF($U42="","",IF(ISNUMBER(INDEX('MiT Strom Pipeline'!$A:$A,$U42)),INDEX('MiT Strom Pipeline'!$A:$A,$U42),"")) | B42: =IF($U42="","",IF(INDEX('MiT Strom Pipeline'!$B:$B,$U42)="","",INDEX('MiT Strom Pipeline'!$B:$B,$U42))) | C42: =IF($U42="","",IF(INDEX('MiT Strom Pipeline'!$C:$C,$U42)="","",INDEX('MiT Strom Pipeline'!$C:$C,$U42))) | D42: =IF($U42="","",IF(INDEX('MiT Strom Pipeline'!$D:$D,$U42)="","",INDEX('MiT Strom Pipeline'!$D:$D,$U42))) | E42: =IF($U42="","",IF(INDEX('MiT Strom Pipeline'!$H:$H,$U42)="","",INDEX('MiT Strom Pipeline'!$H:$H,$U42))) | F42: =IF($U42="","",IF(INDEX('MiT Strom Pipeline'!$E:$E,$U42)="","",INDEX('MiT Strom Pipeline'!$E:$E,$U42))) | G42: =IF($U42="","",IF(ISNUMBER(INDEX('MiT Strom Pipeline'!$I:$I,$U42)),INDEX('MiT Strom Pipeline'!$I:$I,$U42),0)) | H42: =IF($U42="","",IF(ISNUMBER(INDEX('MiT Strom Pipeline'!$Q:$Q,$U42)),INDEX('MiT Strom Pipeline'!$Q:$Q,$U42),0)) | I42: =IF($U42="","",IF(ISNUMBER(INDEX('MiT Strom Pipeline'!$O:$O,$U42)),INDEX('MiT Strom Pipeline'!$O:$O,$U42),0)) | J42: =IF($U42="","",INDEX('MiT Strom Pipeline'!$R:$R,$U42)) | K42: =IF($U42="","",IF(ISNUMBER(INDEX('MiT Strom Pipeline'!$S:$S,$U42)),INDEX('MiT Strom Pipeline'!$S:$S,$U42),"")) | L42: =IF($U42="","",IF(LEN(INDEX('MiT Strom Pipeline'!$V:$V,$U42))>0,LEFT(INDEX('MiT Strom Pipeline'!$V:$V,$U42),55),"")) | U42: =IFERROR(MATCH(32,'MiT Strom Pipeline'!$AB$6:$AB$860,0)+5,"")
A43: =IF($U43="","",IF(ISNUMBER(INDEX('MiT Strom Pipeline'!$A:$A,$U43)),INDEX('MiT Strom Pipeline'!$A:$A,$U43),"")) | B43: =IF($U43="","",IF(INDEX('MiT Strom Pipeline'!$B:$B,$U43)="","",INDEX('MiT Strom Pipeline'!$B:$B,$U43))) | C43: =IF($U43="","",IF(INDEX('MiT Strom Pipeline'!$C:$C,$U43)="","",INDEX('MiT Strom Pipeline'!$C:$C,$U43))) | D43: =IF($U43="","",IF(INDEX('MiT Strom Pipeline'!$D:$D,$U43)="","",INDEX('MiT Strom Pipeline'!$D:$D,$U43))) | E43: =IF($U43="","",IF(INDEX('MiT Strom Pipeline'!$H:$H,$U43)="","",INDEX('MiT Strom Pipeline'!$H:$H,$U43))) | F43: =IF($U43="","",IF(INDEX('MiT Strom Pipeline'!$E:$E,$U43)="","",INDEX('MiT Strom Pipeline'!$E:$E,$U43))) | G43: =IF($U43="","",IF(ISNUMBER(INDEX('MiT Strom Pipeline'!$I:$I,$U43)),INDEX('MiT Strom Pipeline'!$I:$I,$U43),0)) | H43: =IF($U43="","",IF(ISNUMBER(INDEX('MiT Strom Pipeline'!$Q:$Q,$U43)),INDEX('MiT Strom Pipeline'!$Q:$Q,$U43),0)) | I43: =IF($U43="","",IF(ISNUMBER(INDEX('MiT Strom Pipeline'!$O:$O,$U43)),INDEX('MiT Strom Pipeline'!$O:$O,$U43),0)) | J43: =IF($U43="","",INDEX('MiT Strom Pipeline'!$R:$R,$U43)) | K43: =IF($U43="","",IF(ISNUMBER(INDEX('MiT Strom Pipeline'!$S:$S,$U43)),INDEX('MiT Strom Pipeline'!$S:$S,$U43),"")) | L43: =IF($U43="","",IF(LEN(INDEX('MiT Strom Pipeline'!$V:$V,$U43))>0,LEFT(INDEX('MiT Strom Pipeline'!$V:$V,$U43),55),"")) | U43: =IFERROR(MATCH(33,'MiT Strom Pipeline'!$AB$6:$AB$860,0)+5,"")
A44: =IF($U44="","",IF(ISNUMBER(INDEX('MiT Strom Pipeline'!$A:$A,$U44)),INDEX('MiT Strom Pipeline'!$A:$A,$U44),"")) | B44: =IF($U44="","",IF(INDEX('MiT Strom Pipeline'!$B:$B,$U44)="","",INDEX('MiT Strom Pipeline'!$B:$B,$U44))) | C44: =IF($U44="","",IF(INDEX('MiT Strom Pipeline'!$C:$C,$U44)="","",INDEX('MiT Strom Pipeline'!$C:$C,$U44))) | D44: =IF($U44="","",IF(INDEX('MiT Strom Pipeline'!$D:$D,$U44)="","",INDEX('MiT Strom Pipeline'!$D:$D,$U44))) | E44: =IF($U44="","",IF(INDEX('MiT Strom Pipeline'!$H:$H,$U44)="","",INDEX('MiT Strom Pipeline'!$H:$H,$U44))) | F44: =IF($U44="","",IF(INDEX('MiT Strom Pipeline'!$E:$E,$U44)="","",INDEX('MiT Strom Pipeline'!$E:$E,$U44))) | G44: =IF($U44="","",IF(ISNUMBER(INDEX('MiT Strom Pipeline'!$I:$I,$U44)),INDEX('MiT Strom Pipeline'!$I:$I,$U44),0)) | H44: =IF($U44="","",IF(ISNUMBER(INDEX('MiT Strom Pipeline'!$Q:$Q,$U44)),INDEX('MiT Strom Pipeline'!$Q:$Q,$U44),0)) | I44: =IF($U44="","",IF(ISNUMBER(INDEX('MiT Strom Pipeline'!$O:$O,$U44)),INDEX('MiT Strom Pipeline'!$O:$O,$U44),0)) | J44: =IF($U44="","",INDEX('MiT Strom Pipeline'!$R:$R,$U44)) | K44: =IF($U44="","",IF(ISNUMBER(INDEX('MiT Strom Pipeline'!$S:$S,$U44)),INDEX('MiT Strom Pipeline'!$S:$S,$U44),"")) | L44: =IF($U44="","",IF(LEN(INDEX('MiT Strom Pipeline'!$V:$V,$U44))>0,LEFT(INDEX('MiT Strom Pipeline'!$V:$V,$U44),55),"")) | U44: =IFERROR(MATCH(34,'MiT Strom Pipeline'!$AB$6:$AB$860,0)+5,"")
A45: =IF($U45="","",IF(ISNUMBER(INDEX('MiT Strom Pipeline'!$A:$A,$U45)),INDEX('MiT Strom Pipeline'!$A:$A,$U45),"")) | B45: =IF($U45="","",IF(INDEX('MiT Strom Pipeline'!$B:$B,$U45)="","",INDEX('MiT Strom Pipeline'!$B:$B,$U45))) | C45: =IF($U45="","",IF(INDEX('MiT Strom Pipeline'!$C:$C,$U45)="","",INDEX('MiT Strom Pipeline'!$C:$C,$U45))) | D45: =IF($U45="","",IF(INDEX('MiT Strom Pipeline'!$D:$D,$U45)="","",INDEX('MiT Strom Pipeline'!$D:$D,$U45))) | E45: =IF($U45="","",IF(INDEX('MiT Strom Pipeline'!$H:$H,$U45)="","",INDEX('MiT Strom Pipeline'!$H:$H,$U45))) | F45: =IF($U45="","",IF(INDEX('MiT Strom Pipeline'!$E:$E,$U45)="","",INDEX('MiT Strom Pipeline'!$E:$E,$U45))) | G45: =IF($U45="","",IF(ISNUMBER(INDEX('MiT Strom Pipeline'!$I:$I,$U45)),INDEX('MiT Strom Pipeline'!$I:$I,$U45),0)) | H45: =IF($U45="","",IF(ISNUMBER(INDEX('MiT Strom Pipeline'!$Q:$Q,$U45)),INDEX('MiT Strom Pipeline'!$Q:$Q,$U45),0)) | I45: =IF($U45="","",IF(ISNUMBER(INDEX('MiT Strom Pipeline'!$O:$O,$U45)),INDEX('MiT Strom Pipeline'!$O:$O,$U45),0)) | J45: =IF($U45="","",INDEX('MiT Strom Pipeline'!$R:$R,$U45)) | K45: =IF($U45="","",IF(ISNUMBER(INDEX('MiT Strom Pipeline'!$S:$S,$U45)),INDEX('MiT Strom Pipeline'!$S:$S,$U45),"")) | L45: =IF($U45="","",IF(LEN(INDEX('MiT Strom Pipeline'!$V:$V,$U45))>0,LEFT(INDEX('MiT Strom Pipeline'!$V:$V,$U45),55),"")) | U45: =IFERROR(MATCH(35,'MiT Strom Pipeline'!$AB$6:$AB$860,0)+5,"")
A46: =IF($U46="","",IF(ISNUMBER(INDEX('MiT Strom Pipeline'!$A:$A,$U46)),INDEX('MiT Strom Pipeline'!$A:$A,$U46),"")) | B46: =IF($U46="","",IF(INDEX('MiT Strom Pipeline'!$B:$B,$U46)="","",INDEX('MiT Strom Pipeline'!$B:$B,$U46))) | C46: =IF($U46="","",IF(INDEX('MiT Strom Pipeline'!$C:$C,$U46)="","",INDEX('MiT Strom Pipeline'!$C:$C,$U46))) | D46: =IF($U46="","",IF(INDEX('MiT Strom Pipeline'!$D:$D,$U46)="","",INDEX('MiT Strom Pipeline'!$D:$D,$U46))) | E46: =IF($U46="","",IF(INDEX('MiT Strom Pipeline'!$H:$H,$U46)="","",INDEX('MiT Strom Pipeline'!$H:$H,$U46))) | F46: =IF($U46="","",IF(INDEX('MiT Strom Pipeline'!$E:$E,$U46)="","",INDEX('MiT Strom Pipeline'!$E:$E,$U46))) | G46: =IF($U46="","",IF(ISNUMBER(INDEX('MiT Strom Pipeline'!$I:$I,$U46)),INDEX('MiT Strom Pipeline'!$I:$I,$U46),0)) | H46: =IF($U46="","",IF(ISNUMBER(INDEX('MiT Strom Pipeline'!$Q:$Q,$U46)),INDEX('MiT Strom Pipeline'!$Q:$Q,$U46),0)) | I46: =IF($U46="","",IF(ISNUMBER(INDEX('MiT Strom Pipeline'!$O:$O,$U46)),INDEX('MiT Strom Pipeline'!$O:$O,$U46),0)) | J46: =IF($U46="","",INDEX('MiT Strom Pipeline'!$R:$R,$U46)) | K46: =IF($U46="","",IF(ISNUMBER(INDEX('MiT Strom Pipeline'!$S:$S,$U46)),INDEX('MiT Strom Pipeline'!$S:$S,$U46),"")) | L46: =IF($U46="","",IF(LEN(INDEX('MiT Strom Pipeline'!$V:$V,$U46))>0,LEFT(INDEX('MiT Strom Pipeline'!$V:$V,$U46),55),"")) | U46: =IFERROR(MATCH(36,'MiT Strom Pipeline'!$AB$6:$AB$860,0)+5,"")
A47: =IF($U47="","",IF(ISNUMBER(INDEX('MiT Strom Pipeline'!$A:$A,$U47)),INDEX('MiT Strom Pipeline'!$A:$A,$U47),"")) | B47: =IF($U47="","",IF(INDEX('MiT Strom Pipeline'!$B:$B,$U47)="","",INDEX('MiT Strom Pipeline'!$B:$B,$U47))) | C47: =IF($U47="","",IF(INDEX('MiT Strom Pipeline'!$C:$C,$U47)="","",INDEX('MiT Strom Pipeline'!$C:$C,$U47))) | D47: =IF($U47="","",IF(INDEX('MiT Strom Pipeline'!$D:$D,$U47)="","",INDEX('MiT Strom Pipeline'!$D:$D,$U47))) | E47: =IF($U47="","",IF(INDEX('MiT Strom Pipeline'!$H:$H,$U47)="","",INDEX('MiT Strom Pipeline'!$H:$H,$U47))) | F47: =IF($U47="","",IF(INDEX('MiT Strom Pipeline'!$E:$E,$U47)="","",INDEX('MiT Strom Pipeline'!$E:$E,$U47))) | G47: =IF($U47="","",IF(ISNUMBER(INDEX('MiT Strom Pipeline'!$I:$I,$U47)),INDEX('MiT Strom Pipeline'!$I:$I,$U47),0)) | H47: =IF($U47="","",IF(ISNUMBER(INDEX('MiT Strom Pipeline'!$Q:$Q,$U47)),INDEX('MiT Strom Pipeline'!$Q:$Q,$U47),0)) | I47: =IF($U47="","",IF(ISNUMBER(INDEX('MiT Strom Pipeline'!$O:$O,$U47)),INDEX('MiT Strom Pipeline'!$O:$O,$U47),0)) | J47: =IF($U47="","",INDEX('MiT Strom Pipeline'!$R:$R,$U47)) | K47: =IF($U47="","",IF(ISNUMBER(INDEX('MiT Strom Pipeline'!$S:$S,$U47)),INDEX('MiT Strom Pipeline'!$S:$S,$U47),"")) | L47: =IF($U47="","",IF(LEN(INDEX('MiT Strom Pipeline'!$V:$V,$U47))>0,LEFT(INDEX('MiT Strom Pipeline'!$V:$V,$U47),55),"")) | U47: =IFERROR(MATCH(37,'MiT Strom Pipeline'!$AB$6:$AB$860,0)+5,"")
A48: =IF($U48="","",IF(ISNUMBER(INDEX('MiT Strom Pipeline'!$A:$A,$U48)),INDEX('MiT Strom Pipeline'!$A:$A,$U48),"")) | B48: =IF($U48="","",IF(INDEX('MiT Strom Pipeline'!$B:$B,$U48)="","",INDEX('MiT Strom Pipeline'!$B:$B,$U48))) | C48: =IF($U48="","",IF(INDEX('MiT Strom Pipeline'!$C:$C,$U48)="","",INDEX('MiT Strom Pipeline'!$C:$C,$U48))) | D48: =IF($U48="","",IF(INDEX('MiT Strom Pipeline'!$D:$D,$U48)="","",INDEX('MiT Strom Pipeline'!$D:$D,$U48))) | E48: =IF($U48="","",IF(INDEX('MiT Strom Pipeline'!$H:$H,$U48)="","",INDEX('MiT Strom Pipeline'!$H:$H,$U48))) | F48: =IF($U48="","",IF(INDEX('MiT Strom Pipeline'!$E:$E,$U48)="","",INDEX('MiT Strom Pipeline'!$E:$E,$U48))) | G48: =IF($U48="","",IF(ISNUMBER(INDEX('MiT Strom Pipeline'!$I:$I,$U48)),INDEX('MiT Strom Pipeline'!$I:$I,$U48),0)) | H48: =IF($U48="","",IF(ISNUMBER(INDEX('MiT Strom Pipeline'!$Q:$Q,$U48)),INDEX('MiT Strom Pipeline'!$Q:$Q,$U48),0)) | I48: =IF($U48="","",IF(ISNUMBER(INDEX('MiT Strom Pipeline'!$O:$O,$U48)),INDEX('MiT Strom Pipeline'!$O:$O,$U48),0)) | J48: =IF($U48="","",INDEX('MiT Strom Pipeline'!$R:$R,$U48)) | K48: =IF($U48="","",IF(ISNUMBER(INDEX('MiT Strom Pipeline'!$S:$S,$U48)),INDEX('MiT Strom Pipeline'!$S:$S,$U48),"")) | L48: =IF($U48="","",IF(LEN(INDEX('MiT Strom Pipeline'!$V:$V,$U48))>0,LEFT(INDEX('MiT Strom Pipeline'!$V:$V,$U48),55),"")) | U48: =IFERROR(MATCH(38,'MiT Strom Pipeline'!$AB$6:$AB$860,0)+5,"")
A49: =IF($U49="","",IF(ISNUMBER(INDEX('MiT Strom Pipeline'!$A:$A,$U49)),INDEX('MiT Strom Pipeline'!$A:$A,$U49),"")) | B49: =IF($U49="","",IF(INDEX('MiT Strom Pipeline'!$B:$B,$U49)="","",INDEX('MiT Strom Pipeline'!$B:$B,$U49))) | C49: =IF($U49="","",IF(INDEX('MiT Strom Pipeline'!$C:$C,$U49)="","",INDEX('MiT Strom Pipeline'!$C:$C,$U49))) | D49: =IF($U49="","",IF(INDEX('MiT Strom Pipeline'!$D:$D,$U49)="","",INDEX('MiT Strom Pipeline'!$D:$D,$U49))) | E49: =IF($U49="","",IF(INDEX('MiT Strom Pipeline'!$H:$H,$U49)="","",INDEX('MiT Strom Pipeline'!$H:$H,$U49))) | F49: =IF($U49="","",IF(INDEX('MiT Strom Pipeline'!$E:$E,$U49)="","",INDEX('MiT Strom Pipeline'!$E:$E,$U49))) | G49: =IF($U49="","",IF(ISNUMBER(INDEX('MiT Strom Pipeline'!$I:$I,$U49)),INDEX('MiT Strom Pipeline'!$I:$I,$U49),0)) | H49: =IF($U49="","",IF(ISNUMBER(INDEX('MiT Strom Pipeline'!$Q:$Q,$U49)),INDEX('MiT Strom Pipeline'!$Q:$Q,$U49),0)) | I49: =IF($U49="","",IF(ISNUMBER(INDEX('MiT Strom Pipeline'!$O:$O,$U49)),INDEX('MiT Strom Pipeline'!$O:$O,$U49),0)) | J49: =IF($U49="","",INDEX('MiT Strom Pipeline'!$R:$R,$U49)) | K49: =IF($U49="","",IF(ISNUMBER(INDEX('MiT Strom Pipeline'!$S:$S,$U49)),INDEX('MiT Strom Pipeline'!$S:$S,$U49),"")) | L49: =IF($U49="","",IF(LEN(INDEX('MiT Strom Pipeline'!$V:$V,$U49))>0,LEFT(INDEX('MiT Strom Pipeline'!$V:$V,$U49),55),"")) | U49: =IFERROR(MATCH(39,'MiT Strom Pipeline'!$AB$6:$AB$860,0)+5,"")
A50: =IF($U50="","",IF(ISNUMBER(INDEX('MiT Strom Pipeline'!$A:$A,$U50)),INDEX('MiT Strom Pipeline'!$A:$A,$U50),"")) | B50: =IF($U50="","",IF(INDEX('MiT Strom Pipeline'!$B:$B,$U50)="","",INDEX('MiT Strom Pipeline'!$B:$B,$U50))) | C50: =IF($U50="","",IF(INDEX('MiT Strom Pipeline'!$C:$C,$U50)="","",INDEX('MiT Strom Pipeline'!$C:$C,$U50))) | D50: =IF($U50="","",IF(INDEX('MiT Strom Pipeline'!$D:$D,$U50)="","",INDEX('MiT Strom Pipeline'!$D:$D,$U50))) | E50: =IF($U50="","",IF(INDEX('MiT Strom Pipeline'!$H:$H,$U50)="","",INDEX('MiT Strom Pipeline'!$H:$H,$U50))) | F50: =IF($U50="","",IF(INDEX('MiT Strom Pipeline'!$E:$E,$U50)="","",INDEX('MiT Strom Pipeline'!$E:$E,$U50))) | G50: =IF($U50="","",IF(ISNUMBER(INDEX('MiT Strom Pipeline'!$I:$I,$U50)),INDEX('MiT Strom Pipeline'!$I:$I,$U50),0)) | H50: =IF($U50="","",IF(ISNUMBER(INDEX('MiT Strom Pipeline'!$Q:$Q,$U50)),INDEX('MiT Strom Pipeline'!$Q:$Q,$U50),0)) | I50: =IF($U50="","",IF(ISNUMBER(INDEX('MiT Strom Pipeline'!$O:$O,$U50)),INDEX('MiT Strom Pipeline'!$O:$O,$U50),0)) | J50: =IF($U50="","",INDEX('MiT Strom Pipeline'!$R:$R,$U50)) | K50: =IF($U50="","",IF(ISNUMBER(INDEX('MiT Strom Pipeline'!$S:$S,$U50)),INDEX('MiT Strom Pipeline'!$S:$S,$U50),"")) | L50: =IF($U50="","",IF(LEN(INDEX('MiT Strom Pipeline'!$V:$V,$U50))>0,LEFT(INDEX('MiT Strom Pipeline'!$V:$V,$U50),55),"")) | U50: =IFERROR(MATCH(40,'MiT Strom Pipeline'!$AB$6:$AB$860,0)+5,"")
A51: =IF($U51="","",IF(ISNUMBER(INDEX('MiT Strom Pipeline'!$A:$A,$U51)),INDEX('MiT Strom Pipeline'!$A:$A,$U51),"")) | B51: =IF($U51="","",IF(INDEX('MiT Strom Pipeline'!$B:$B,$U51)="","",INDEX('MiT Strom Pipeline'!$B:$B,$U51))) | C51: =IF($U51="","",IF(INDEX('MiT Strom Pipeline'!$C:$C,$U51)="","",INDEX('MiT Strom Pipeline'!$C:$C,$U51))) | D51: =IF($U51="","",IF(INDEX('MiT Strom Pipeline'!$D:$D,$U51)="","",INDEX('MiT Strom Pipeline'!$D:$D,$U51))) | E51: =IF($U51="","",IF(INDEX('MiT Strom Pipeline'!$H:$H,$U51)="","",INDEX('MiT Strom Pipeline'!$H:$H,$U51))) | F51: =IF($U51="","",IF(INDEX('MiT Strom Pipeline'!$E:$E,$U51)="","",INDEX('MiT Strom Pipeline'!$E:$E,$U51))) | G51: =IF($U51="","",IF(ISNUMBER(INDEX('MiT Strom Pipeline'!$I:$I,$U51)),INDEX('MiT Strom Pipeline'!$I:$I,$U51),0)) | H51: =IF($U51="","",IF(ISNUMBER(INDEX('MiT Strom Pipeline'!$Q:$Q,$U51)),INDEX('MiT Strom Pipeline'!$Q:$Q,$U51),0)) | I51: =IF($U51="","",IF(ISNUMBER(INDEX('MiT Strom Pipeline'!$O:$O,$U51)),INDEX('MiT Strom Pipeline'!$O:$O,$U51),0)) | J51: =IF($U51="","",INDEX('MiT Strom Pipeline'!$R:$R,$U51)) | K51: =IF($U51="","",IF(ISNUMBER(INDEX('MiT Strom Pipeline'!$S:$S,$U51)),INDEX('MiT Strom Pipeline'!$S:$S,$U51),"")) | L51: =IF($U51="","",IF(LEN(INDEX('MiT Strom Pipeline'!$V:$V,$U51))>0,LEFT(INDEX('MiT Strom Pipeline'!$V:$V,$U51),55),"")) | U51: =IFERROR(MATCH(41,'MiT Strom Pipeline'!$AB$6:$AB$860,0)+5,"")
A52: =IF($U52="","",IF(ISNUMBER(INDEX('MiT Strom Pipeline'!$A:$A,$U52)),INDEX('MiT Strom Pipeline'!$A:$A,$U52),"")) | B52: =IF($U52="","",IF(INDEX('MiT Strom Pipeline'!$B:$B,$U52)="","",INDEX('MiT Strom Pipeline'!$B:$B,$U52))) | C52: =IF($U52="","",IF(INDEX('MiT Strom Pipeline'!$C:$C,$U52)="","",INDEX('MiT Strom Pipeline'!$C:$C,$U52))) | D52: =IF($U52="","",IF(INDEX('MiT Strom Pipeline'!$D:$D,$U52)="","",INDEX('MiT Strom Pipeline'!$D:$D,$U52))) | E52: =IF($U52="","",IF(INDEX('MiT Strom Pipeline'!$H:$H,$U52)="","",INDEX('MiT Strom Pipeline'!$H:$H,$U52))) | F52: =IF($U52="","",IF(INDEX('MiT Strom Pipeline'!$E:$E,$U52)="","",INDEX('MiT Strom Pipeline'!$E:$E,$U52))) | G52: =IF($U52="","",IF(ISNUMBER(INDEX('MiT Strom Pipeline'!$I:$I,$U52)),INDEX('MiT Strom Pipeline'!$I:$I,$U52),0)) | H52: =IF($U52="","",IF(ISNUMBER(INDEX('MiT Strom Pipeline'!$Q:$Q,$U52)),INDEX('MiT Strom Pipeline'!$Q:$Q,$U52),0)) | I52: =IF($U52="","",IF(ISNUMBER(INDEX('MiT Strom Pipeline'!$O:$O,$U52)),INDEX('MiT Strom Pipeline'!$O:$O,$U52),0)) | J52: =IF($U52="","",INDEX('MiT Strom Pipeline'!$R:$R,$U52)) | K52: =IF($U52="","",IF(ISNUMBER(INDEX('MiT Strom Pipeline'!$S:$S,$U52)),INDEX('MiT Strom Pipeline'!$S:$S,$U52),"")) | L52: =IF($U52="","",IF(LEN(INDEX('MiT Strom Pipeline'!$V:$V,$U52))>0,LEFT(INDEX('MiT Strom Pipeline'!$V:$V,$U52),55),"")) | U52: =IFERROR(MATCH(42,'MiT Strom Pipeline'!$AB$6:$AB$860,0)+5,"")
A53: =IF($U53="","",IF(ISNUMBER(INDEX('MiT Strom Pipeline'!$A:$A,$U53)),INDEX('MiT Strom Pipeline'!$A:$A,$U53),"")) | B53: =IF($U53="","",IF(INDEX('MiT Strom Pipeline'!$B:$B,$U53)="","",INDEX('MiT Strom Pipeline'!$B:$B,$U53))) | C53: =IF($U53="","",IF(INDEX('MiT Strom Pipeline'!$C:$C,$U53)="","",INDEX('MiT Strom Pipeline'!$C:$C,$U53))) | D53: =IF($U53="","",IF(INDEX('MiT Strom Pipeline'!$D:$D,$U53)="","",INDEX('MiT Strom Pipeline'!$D:$D,$U53))) | E53: =IF($U53="","",IF(INDEX('MiT Strom Pipeline'!$H:$H,$U53)="","",INDEX('MiT Strom Pipeline'!$H:$H,$U53))) | F53: =IF($U53="","",IF(INDEX('MiT Strom Pipeline'!$E:$E,$U53)="","",INDEX('MiT Strom Pipeline'!$E:$E,$U53))) | G53: =IF($U53="","",IF(ISNUMBER(INDEX('MiT Strom Pipeline'!$I:$I,$U53)),INDEX('MiT Strom Pipeline'!$I:$I,$U53),0)) | H53: =IF($U53="","",IF(ISNUMBER(INDEX('MiT Strom Pipeline'!$Q:$Q,$U53)),INDEX('MiT Strom Pipeline'!$Q:$Q,$U53),0)) | I53: =IF($U53="","",IF(ISNUMBER(INDEX('MiT Strom Pipeline'!$O:$O,$U53)),INDEX('MiT Strom Pipeline'!$O:$O,$U53),0)) | J53: =IF($U53="","",INDEX('MiT Strom Pipeline'!$R:$R,$U53)) | K53: =IF($U53="","",IF(ISNUMBER(INDEX('MiT Strom Pipeline'!$S:$S,$U53)),INDEX('MiT Strom Pipeline'!$S:$S,$U53),"")) | L53: =IF($U53="","",IF(LEN(INDEX('MiT Strom Pipeline'!$V:$V,$U53))>0,LEFT(INDEX('MiT Strom Pipeline'!$V:$V,$U53),55),"")) | U53: =IFERROR(MATCH(43,'MiT Strom Pipeline'!$AB$6:$AB$860,0)+5,"")
A54: =IF($U54="","",IF(ISNUMBER(INDEX('MiT Strom Pipeline'!$A:$A,$U54)),INDEX('MiT Strom Pipeline'!$A:$A,$U54),"")) | B54: =IF($U54="","",IF(INDEX('MiT Strom Pipeline'!$B:$B,$U54)="","",INDEX('MiT Strom Pipeline'!$B:$B,$U54))) | C54: =IF($U54="","",IF(INDEX('MiT Strom Pipeline'!$C:$C,$U54)="","",INDEX('MiT Strom Pipeline'!$C:$C,$U54))) | D54: =IF($U54="","",IF(INDEX('MiT Strom Pipeline'!$D:$D,$U54)="","",INDEX('MiT Strom Pipeline'!$D:$D,$U54))) | E54: =IF($U54="","",IF(INDEX('MiT Strom Pipeline'!$H:$H,$U54)="","",INDEX('MiT Strom Pipeline'!$H:$H,$U54))) | F54: =IF($U54="","",IF(INDEX('MiT Strom Pipeline'!$E:$E,$U54)="","",INDEX('MiT Strom Pipeline'!$E:$E,$U54))) | G54: =IF($U54="","",IF(ISNUMBER(INDEX('MiT Strom Pipeline'!$I:$I,$U54)),INDEX('MiT Strom Pipeline'!$I:$I,$U54),0)) | H54: =IF($U54="","",IF(ISNUMBER(INDEX('MiT Strom Pipeline'!$Q:$Q,$U54)),INDEX('MiT Strom Pipeline'!$Q:$Q,$U54),0)) | I54: =IF($U54="","",IF(ISNUMBER(INDEX('MiT Strom Pipeline'!$O:$O,$U54)),INDEX('MiT Strom Pipeline'!$O:$O,$U54),0)) | J54: =IF($U54="","",INDEX('MiT Strom Pipeline'!$R:$R,$U54)) | K54: =IF($U54="","",IF(ISNUMBER(INDEX('MiT Strom Pipeline'!$S:$S,$U54)),INDEX('MiT Strom Pipeline'!$S:$S,$U54),"")) | L54: =IF($U54="","",IF(LEN(INDEX('MiT Strom Pipeline'!$V:$V,$U54))>0,LEFT(INDEX('MiT Strom Pipeline'!$V:$V,$U54),55),"")) | U54: =IFERROR(MATCH(44,'MiT Strom Pipeline'!$AB$6:$AB$860,0)+5,"")
A55: =IF($U55="","",IF(ISNUMBER(INDEX('MiT Strom Pipeline'!$A:$A,$U55)),INDEX('MiT Strom Pipeline'!$A:$A,$U55),"")) | B55: =IF($U55="","",IF(INDEX('MiT Strom Pipeline'!$B:$B,$U55)="","",INDEX('MiT Strom Pipeline'!$B:$B,$U55))) | C55: =IF($U55="","",IF(INDEX('MiT Strom Pipeline'!$C:$C,$U55)="","",INDEX('MiT Strom Pipeline'!$C:$C,$U55))) | D55: =IF($U55="","",IF(INDEX('MiT Strom Pipeline'!$D:$D,$U55)="","",INDEX('MiT Strom Pipeline'!$D:$D,$U55))) | E55: =IF($U55="","",IF(INDEX('MiT Strom Pipeline'!$H:$H,$U55)="","",INDEX('MiT Strom Pipeline'!$H:$H,$U55))) | F55: =IF($U55="","",IF(INDEX('MiT Strom Pipeline'!$E:$E,$U55)="","",INDEX('MiT Strom Pipeline'!$E:$E,$U55))) | G55: =IF($U55="","",IF(ISNUMBER(INDEX('MiT Strom Pipeline'!$I:$I,$U55)),INDEX('MiT Strom Pipeline'!$I:$I,$U55),0)) | H55: =IF($U55="","",IF(ISNUMBER(INDEX('MiT Strom Pipeline'!$Q:$Q,$U55)),INDEX('MiT Strom Pipeline'!$Q:$Q,$U55),0)) | I55: =IF($U55="","",IF(ISNUMBER(INDEX('MiT Strom Pipeline'!$O:$O,$U55)),INDEX('MiT Strom Pipeline'!$O:$O,$U55),0)) | J55: =IF($U55="","",INDEX('MiT Strom Pipeline'!$R:$R,$U55)) | K55: =IF($U55="","",IF(ISNUMBER(INDEX('MiT Strom Pipeline'!$S:$S,$U55)),INDEX('MiT Strom Pipeline'!$S:$S,$U55),"")) | L55: =IF($U55="","",IF(LEN(INDEX('MiT Strom Pipeline'!$V:$V,$U55))>0,LEFT(INDEX('MiT Strom Pipeline'!$V:$V,$U55),55),"")) | U55: =IFERROR(MATCH(45,'MiT Strom Pipeline'!$AB$6:$AB$860,0)+5,"")
A56: =IF($U56="","",IF(ISNUMBER(INDEX('MiT Strom Pipeline'!$A:$A,$U56)),INDEX('MiT Strom Pipeline'!$A:$A,$U56),"")) | B56: =IF($U56="","",IF(INDEX('MiT Strom Pipeline'!$B:$B,$U56)="","",INDEX('MiT Strom Pipeline'!$B:$B,$U56))) | C56: =IF($U56="","",IF(INDEX('MiT Strom Pipeline'!$C:$C,$U56)="","",INDEX('MiT Strom Pipeline'!$C:$C,$U56))) | D56: =IF($U56="","",IF(INDEX('MiT Strom Pipeline'!$D:$D,$U56)="","",INDEX('MiT Strom Pipeline'!$D:$D,$U56))) | E56: =IF($U56="","",IF(INDEX('MiT Strom Pipeline'!$H:$H,$U56)="","",INDEX('MiT Strom Pipeline'!$H:$H,$U56))) | F56: =IF($U56="","",IF(INDEX('MiT Strom Pipeline'!$E:$E,$U56)="","",INDEX('MiT Strom Pipeline'!$E:$E,$U56))) | G56: =IF($U56="","",IF(ISNUMBER(INDEX('MiT Strom Pipeline'!$I:$I,$U56)),INDEX('MiT Strom Pipeline'!$I:$I,$U56),0)) | H56: =IF($U56="","",IF(ISNUMBER(INDEX('MiT Strom Pipeline'!$Q:$Q,$U56)),INDEX('MiT Strom Pipeline'!$Q:$Q,$U56),0)) | I56: =IF($U56="","",IF(ISNUMBER(INDEX('MiT Strom Pipeline'!$O:$O,$U56)),INDEX('MiT Strom Pipeline'!$O:$O,$U56),0)) | J56: =IF($U56="","",INDEX('MiT Strom Pipeline'!$R:$R,$U56)) | K56: =IF($U56="","",IF(ISNUMBER(INDEX('MiT Strom Pipeline'!$S:$S,$U56)),INDEX('MiT Strom Pipeline'!$S:$S,$U56),"")) | L56: =IF($U56="","",IF(LEN(INDEX('MiT Strom Pipeline'!$V:$V,$U56))>0,LEFT(INDEX('MiT Strom Pipeline'!$V:$V,$U56),55),"")) | U56: =IFERROR(MATCH(46,'MiT Strom Pipeline'!$AB$6:$AB$860,0)+5,"")
A57: =IF($U57="","",IF(ISNUMBER(INDEX('MiT Strom Pipeline'!$A:$A,$U57)),INDEX('MiT Strom Pipeline'!$A:$A,$U57),"")) | B57: =IF($U57="","",IF(INDEX('MiT Strom Pipeline'!$B:$B,$U57)="","",INDEX('MiT Strom Pipeline'!$B:$B,$U57))) | C57: =IF($U57="","",IF(INDEX('MiT Strom Pipeline'!$C:$C,$U57)="","",INDEX('MiT Strom Pipeline'!$C:$C,$U57))) | D57: =IF($U57="","",IF(INDEX('MiT Strom Pipeline'!$D:$D,$U57)="","",INDEX('MiT Strom Pipeline'!$D:$D,$U57))) | E57: =IF($U57="","",IF(INDEX('MiT Strom Pipeline'!$H:$H,$U57)="","",INDEX('MiT Strom Pipeline'!$H:$H,$U57))) | F57: =IF($U57="","",IF(INDEX('MiT Strom Pipeline'!$E:$E,$U57)="","",INDEX('MiT Strom Pipeline'!$E:$E,$U57))) | G57: =IF($U57="","",IF(ISNUMBER(INDEX('MiT Strom Pipeline'!$I:$I,$U57)),INDEX('MiT Strom Pipeline'!$I:$I,$U57),0)) | H57: =IF($U57="","",IF(ISNUMBER(INDEX('MiT Strom Pipeline'!$Q:$Q,$U57)),INDEX('MiT Strom Pipeline'!$Q:$Q,$U57),0)) | I57: =IF($U57="","",IF(ISNUMBER(INDEX('MiT Strom Pipeline'!$O:$O,$U57)),INDEX('MiT Strom Pipeline'!$O:$O,$U57),0)) | J57: =IF($U57="","",INDEX('MiT Strom Pipeline'!$R:$R,$U57)) | K57: =IF($U57="","",IF(ISNUMBER(INDEX('MiT Strom Pipeline'!$S:$S,$U57)),INDEX('MiT Strom Pipeline'!$S:$S,$U57),"")) | L57: =IF($U57="","",IF(LEN(INDEX('MiT Strom Pipeline'!$V:$V,$U57))>0,LEFT(INDEX('MiT Strom Pipeline'!$V:$V,$U57),55),"")) | U57: =IFERROR(MATCH(47,'MiT Strom Pipeline'!$AB$6:$AB$860,0)+5,"")
A58: =IF($U58="","",IF(ISNUMBER(INDEX('MiT Strom Pipeline'!$A:$A,$U58)),INDEX('MiT Strom Pipeline'!$A:$A,$U58),"")) | B58: =IF($U58="","",IF(INDEX('MiT Strom Pipeline'!$B:$B,$U58)="","",INDEX('MiT Strom Pipeline'!$B:$B,$U58))) | C58: =IF($U58="","",IF(INDEX('MiT Strom Pipeline'!$C:$C,$U58)="","",INDEX('MiT Strom Pipeline'!$C:$C,$U58))) | D58: =IF($U58="","",IF(INDEX('MiT Strom Pipeline'!$D:$D,$U58)="","",INDEX('MiT Strom Pipeline'!$D:$D,$U58))) | E58: =IF($U58="","",IF(INDEX('MiT Strom Pipeline'!$H:$H,$U58)="","",INDEX('MiT Strom Pipeline'!$H:$H,$U58))) | F58: =IF($U58="","",IF(INDEX('MiT Strom Pipeline'!$E:$E,$U58)="","",INDEX('MiT Strom Pipeline'!$E:$E,$U58))) | G58: =IF($U58="","",IF(ISNUMBER(INDEX('MiT Strom Pipeline'!$I:$I,$U58)),INDEX('MiT Strom Pipeline'!$I:$I,$U58),0)) | H58: =IF($U58="","",IF(ISNUMBER(INDEX('MiT Strom Pipeline'!$Q:$Q,$U58)),INDEX('MiT Strom Pipeline'!$Q:$Q,$U58),0)) | I58: =IF($U58="","",IF(ISNUMBER(INDEX('MiT Strom Pipeline'!$O:$O,$U58)),INDEX('MiT Strom Pipeline'!$O:$O,$U58),0)) | J58: =IF($U58="","",INDEX('MiT Strom Pipeline'!$R:$R,$U58)) | K58: =IF($U58="","",IF(ISNUMBER(INDEX('MiT Strom Pipeline'!$S:$S,$U58)),INDEX('MiT Strom Pipeline'!$S:$S,$U58),"")) | L58: =IF($U58="","",IF(LEN(INDEX('MiT Strom Pipeline'!$V:$V,$U58))>0,LEFT(INDEX('MiT Strom Pipeline'!$V:$V,$U58),55),"")) | U58: =IFERROR(MATCH(48,'MiT Strom Pipeline'!$AB$6:$AB$860,0)+5,"")
A59: =IF($U59="","",IF(ISNUMBER(INDEX('MiT Strom Pipeline'!$A:$A,$U59)),INDEX('MiT Strom Pipeline'!$A:$A,$U59),"")) | B59: =IF($U59="","",IF(INDEX('MiT Strom Pipeline'!$B:$B,$U59)="","",INDEX('MiT Strom Pipeline'!$B:$B,$U59))) | C59: =IF($U59="","",IF(INDEX('MiT Strom Pipeline'!$C:$C,$U59)="","",INDEX('MiT Strom Pipeline'!$C:$C,$U59))) | D59: =IF($U59="","",IF(INDEX('MiT Strom Pipeline'!$D:$D,$U59)="","",INDEX('MiT Strom Pipeline'!$D:$D,$U59))) | E59: =IF($U59="","",IF(INDEX('MiT Strom Pipeline'!$H:$H,$U59)="","",INDEX('MiT Strom Pipeline'!$H:$H,$U59))) | F59: =IF($U59="","",IF(INDEX('MiT Strom Pipeline'!$E:$E,$U59)="","",INDEX('MiT Strom Pipeline'!$E:$E,$U59))) | G59: =IF($U59="","",IF(ISNUMBER(INDEX('MiT Strom Pipeline'!$I:$I,$U59)),INDEX('MiT Strom Pipeline'!$I:$I,$U59),0)) | H59: =IF($U59="","",IF(ISNUMBER(INDEX('MiT Strom Pipeline'!$Q:$Q,$U59)),INDEX('MiT Strom Pipeline'!$Q:$Q,$U59),0)) | I59: =IF($U59="","",IF(ISNUMBER(INDEX('MiT Strom Pipeline'!$O:$O,$U59)),INDEX('MiT Strom Pipeline'!$O:$O,$U59),0)) | J59: =IF($U59="","",INDEX('MiT Strom Pipeline'!$R:$R,$U59)) | K59: =IF($U59="","",IF(ISNUMBER(INDEX('MiT Strom Pipeline'!$S:$S,$U59)),INDEX('MiT Strom Pipeline'!$S:$S,$U59),"")) | L59: =IF($U59="","",IF(LEN(INDEX('MiT Strom Pipeline'!$V:$V,$U59))>0,LEFT(INDEX('MiT Strom Pipeline'!$V:$V,$U59),55),"")) | U59: =IFERROR(MATCH(49,'MiT Strom Pipeline'!$AB$6:$AB$860,0)+5,"")
A60: =IF($U60="","",IF(ISNUMBER(INDEX('MiT Strom Pipeline'!$A:$A,$U60)),INDEX('MiT Strom Pipeline'!$A:$A,$U60),"")) | B60: =IF($U60="","",IF(INDEX('MiT Strom Pipeline'!$B:$B,$U60)="","",INDEX('MiT Strom Pipeline'!$B:$B,$U60))) | C60: =IF($U60="","",IF(INDEX('MiT Strom Pipeline'!$C:$C,$U60)="","",INDEX('MiT Strom Pipeline'!$C:$C,$U60))) | D60: =IF($U60="","",IF(INDEX('MiT Strom Pipeline'!$D:$D,$U60)="","",INDEX('MiT Strom Pipeline'!$D:$D,$U60))) | E60: =IF($U60="","",IF(INDEX('MiT Strom Pipeline'!$H:$H,$U60)="","",INDEX('MiT Strom Pipeline'!$H:$H,$U60))) | F60: =IF($U60="","",IF(INDEX('MiT Strom Pipeline'!$E:$E,$U60)="","",INDEX('MiT Strom Pipeline'!$E:$E,$U60))) | G60: =IF($U60="","",IF(ISNUMBER(INDEX('MiT Strom Pipeline'!$I:$I,$U60)),INDEX('MiT Strom Pipeline'!$I:$I,$U60),0)) | H60: =IF($U60="","",IF(ISNUMBER(INDEX('MiT Strom Pipeline'!$Q:$Q,$U60)),INDEX('MiT Strom Pipeline'!$Q:$Q,$U60),0)) | I60: =IF($U60="","",IF(ISNUMBER(INDEX('MiT Strom Pipeline'!$O:$O,$U60)),INDEX('MiT Strom Pipeline'!$O:$O,$U60),0)) | J60: =IF($U60="","",INDEX('MiT Strom Pipeline'!$R:$R,$U60)) | K60: =IF($U60="","",IF(ISNUMBER(INDEX('MiT Strom Pipeline'!$S:$S,$U60)),INDEX('MiT Strom Pipeline'!$S:$S,$U60),"")) | L60: =IF($U60="","",IF(LEN(INDEX('MiT Strom Pipeline'!$V:$V,$U60))>0,LEFT(INDEX('MiT Strom Pipeline'!$V:$V,$U60),55),"")) | U60: =IFERROR(MATCH(50,'MiT Strom Pipeline'!$AB$6:$AB$860,0)+5,"")
A61: =IF($U61="","",IF(ISNUMBER(INDEX('MiT Strom Pipeline'!$A:$A,$U61)),INDEX('MiT Strom Pipeline'!$A:$A,$U61),"")) | B61: =IF($U61="","",IF(INDEX('MiT Strom Pipeline'!$B:$B,$U61)="","",INDEX('MiT Strom Pipeline'!$B:$B,$U61))) | C61: =IF($U61="","",IF(INDEX('MiT Strom Pipeline'!$C:$C,$U61)="","",INDEX('MiT Strom Pipeline'!$C:$C,$U61))) | D61: =IF($U61="","",IF(INDEX('MiT Strom Pipeline'!$D:$D,$U61)="","",INDEX('MiT Strom Pipeline'!$D:$D,$U61))) | E61: =IF($U61="","",IF(INDEX('MiT Strom Pipeline'!$H:$H,$U61)="","",INDEX('MiT Strom Pipeline'!$H:$H,$U61))) | F61: =IF($U61="","",IF(INDEX('MiT Strom Pipeline'!$E:$E,$U61)="","",INDEX('MiT Strom Pipeline'!$E:$E,$U61))) | G61: =IF($U61="","",IF(ISNUMBER(INDEX('MiT Strom Pipeline'!$I:$I,$U61)),INDEX('MiT Strom Pipeline'!$I:$I,$U61),0)) | H61: =IF($U61="","",IF(ISNUMBER(INDEX('MiT Strom Pipeline'!$Q:$Q,$U61)),INDEX('MiT Strom Pipeline'!$Q:$Q,$U61),0)) | I61: =IF($U61="","",IF(ISNUMBER(INDEX('MiT Strom Pipeline'!$O:$O,$U61)),INDEX('MiT Strom Pipeline'!$O:$O,$U61),0)) | J61: =IF($U61="","",INDEX('MiT Strom Pipeline'!$R:$R,$U61)) | K61: =IF($U61="","",IF(ISNUMBER(INDEX('MiT Strom Pipeline'!$S:$S,$U61)),INDEX('MiT Strom Pipeline'!$S:$S,$U61),"")) | L61: =IF($U61="","",IF(LEN(INDEX('MiT Strom Pipeline'!$V:$V,$U61))>0,LEFT(INDEX('MiT Strom Pipeline'!$V:$V,$U61),55),"")) | U61: =IFERROR(MATCH(51,'MiT Strom Pipeline'!$AB$6:$AB$860,0)+5,"")
A62: =IF($U62="","",IF(ISNUMBER(INDEX('MiT Strom Pipeline'!$A:$A,$U62)),INDEX('MiT Strom Pipeline'!$A:$A,$U62),"")) | B62: =IF($U62="","",IF(INDEX('MiT Strom Pipeline'!$B:$B,$U62)="","",INDEX('MiT Strom Pipeline'!$B:$B,$U62))) | C62: =IF($U62="","",IF(INDEX('MiT Strom Pipeline'!$C:$C,$U62)="","",INDEX('MiT Strom Pipeline'!$C:$C,$U62))) | D62: =IF($U62="","",IF(INDEX('MiT Strom Pipeline'!$D:$D,$U62)="","",INDEX('MiT Strom Pipeline'!$D:$D,$U62))) | E62: =IF($U62="","",IF(INDEX('MiT Strom Pipeline'!$H:$H,$U62)="","",INDEX('MiT Strom Pipeline'!$H:$H,$U62))) | F62: =IF($U62="","",IF(INDEX('MiT Strom Pipeline'!$E:$E,$U62)="","",INDEX('MiT Strom Pipeline'!$E:$E,$U62))) | G62: =IF($U62="","",IF(ISNUMBER(INDEX('MiT Strom Pipeline'!$I:$I,$U62)),INDEX('MiT Strom Pipeline'!$I:$I,$U62),0)) | H62: =IF($U62="","",IF(ISNUMBER(INDEX('MiT Strom Pipeline'!$Q:$Q,$U62)),INDEX('MiT Strom Pipeline'!$Q:$Q,$U62),0)) | I62: =IF($U62="","",IF(ISNUMBER(INDEX('MiT Strom Pipeline'!$O:$O,$U62)),INDEX('MiT Strom Pipeline'!$O:$O,$U62),0)) | J62: =IF($U62="","",INDEX('MiT Strom Pipeline'!$R:$R,$U62)) | K62: =IF($U62="","",IF(ISNUMBER(INDEX('MiT Strom Pipeline'!$S:$S,$U62)),INDEX('MiT Strom Pipeline'!$S:$S,$U62),"")) | L62: =IF($U62="","",IF(LEN(INDEX('MiT Strom Pipeline'!$V:$V,$U62))>0,LEFT(INDEX('MiT Strom Pipeline'!$V:$V,$U62),55),"")) | U62: =IFERROR(MATCH(52,'MiT Strom Pipeline'!$AB$6:$AB$860,0)+5,"")
A63: =IF($U63="","",IF(ISNUMBER(INDEX('MiT Strom Pipeline'!$A:$A,$U63)),INDEX('MiT Strom Pipeline'!$A:$A,$U63),"")) | B63: =IF($U63="","",IF(INDEX('MiT Strom Pipeline'!$B:$B,$U63)="","",INDEX('MiT Strom Pipeline'!$B:$B,$U63))) | C63: =IF($U63="","",IF(INDEX('MiT Strom Pipeline'!$C:$C,$U63)="","",INDEX('MiT Strom Pipeline'!$C:$C,$U63))) | D63: =IF($U63="","",IF(INDEX('MiT Strom Pipeline'!$D:$D,$U63)="","",INDEX('MiT Strom Pipeline'!$D:$D,$U63))) | E63: =IF($U63="","",IF(INDEX('MiT Strom Pipeline'!$H:$H,$U63)="","",INDEX('MiT Strom Pipeline'!$H:$H,$U63))) | F63: =IF($U63="","",IF(INDEX('MiT Strom Pipeline'!$E:$E,$U63)="","",INDEX('MiT Strom Pipeline'!$E:$E,$U63))) | G63: =IF($U63="","",IF(ISNUMBER(INDEX('MiT Strom Pipeline'!$I:$I,$U63)),INDEX('MiT Strom Pipeline'!$I:$I,$U63),0)) | H63: =IF($U63="","",IF(ISNUMBER(INDEX('MiT Strom Pipeline'!$Q:$Q,$U63)),INDEX('MiT Strom Pipeline'!$Q:$Q,$U63),0)) | I63: =IF($U63="","",IF(ISNUMBER(INDEX('MiT Strom Pipeline'!$O:$O,$U63)),INDEX('MiT Strom Pipeline'!$O:$O,$U63),0)) | J63: =IF($U63="","",INDEX('MiT Strom Pipeline'!$R:$R,$U63)) | K63: =IF($U63="","",IF(ISNUMBER(INDEX('MiT Strom Pipeline'!$S:$S,$U63)),INDEX('MiT Strom Pipeline'!$S:$S,$U63),"")) | L63: =IF($U63="","",IF(LEN(INDEX('MiT Strom Pipeline'!$V:$V,$U63))>0,LEFT(INDEX('MiT Strom Pipeline'!$V:$V,$U63),55),"")) | U63: =IFERROR(MATCH(53,'MiT Strom Pipeline'!$AB$6:$AB$860,0)+5,"")
A64: =IF($U64="","",IF(ISNUMBER(INDEX('MiT Strom Pipeline'!$A:$A,$U64)),INDEX('MiT Strom Pipeline'!$A:$A,$U64),"")) | B64: =IF($U64="","",IF(INDEX('MiT Strom Pipeline'!$B:$B,$U64)="","",INDEX('MiT Strom Pipeline'!$B:$B,$U64))) | C64: =IF($U64="","",IF(INDEX('MiT Strom Pipeline'!$C:$C,$U64)="","",INDEX('MiT Strom Pipeline'!$C:$C,$U64))) | D64: =IF($U64="","",IF(INDEX('MiT Strom Pipeline'!$D:$D,$U64)="","",INDEX('MiT Strom Pipeline'!$D:$D,$U64))) | E64: =IF($U64="","",IF(INDEX('MiT Strom Pipeline'!$H:$H,$U64)="","",INDEX('MiT Strom Pipeline'!$H:$H,$U64))) | F64: =IF($U64="","",IF(INDEX('MiT Strom Pipeline'!$E:$E,$U64)="","",INDEX('MiT Strom Pipeline'!$E:$E,$U64))) | G64: =IF($U64="","",IF(ISNUMBER(INDEX('MiT Strom Pipeline'!$I:$I,$U64)),INDEX('MiT Strom Pipeline'!$I:$I,$U64),0)) | H64: =IF($U64="","",IF(ISNUMBER(INDEX('MiT Strom Pipeline'!$Q:$Q,$U64)),INDEX('MiT Strom Pipeline'!$Q:$Q,$U64),0)) | I64: =IF($U64="","",IF(ISNUMBER(INDEX('MiT Strom Pipeline'!$O:$O,$U64)),INDEX('MiT Strom Pipeline'!$O:$O,$U64),0)) | J64: =IF($U64="","",INDEX('MiT Strom Pipeline'!$R:$R,$U64)) | K64: =IF($U64="","",IF(ISNUMBER(INDEX('MiT Strom Pipeline'!$S:$S,$U64)),INDEX('MiT Strom Pipeline'!$S:$S,$U64),"")) | L64: =IF($U64="","",IF(LEN(INDEX('MiT Strom Pipeline'!$V:$V,$U64))>0,LEFT(INDEX('MiT Strom Pipeline'!$V:$V,$U64),55),"")) | U64: =IFERROR(MATCH(54,'MiT Strom Pipeline'!$AB$6:$AB$860,0)+5,"")
A65: =IF($U65="","",IF(ISNUMBER(INDEX('MiT Strom Pipeline'!$A:$A,$U65)),INDEX('MiT Strom Pipeline'!$A:$A,$U65),"")) | B65: =IF($U65="","",IF(INDEX('MiT Strom Pipeline'!$B:$B,$U65)="","",INDEX('MiT Strom Pipeline'!$B:$B,$U65))) | C65: =IF($U65="","",IF(INDEX('MiT Strom Pipeline'!$C:$C,$U65)="","",INDEX('MiT Strom Pipeline'!$C:$C,$U65))) | D65: =IF($U65="","",IF(INDEX('MiT Strom Pipeline'!$D:$D,$U65)="","",INDEX('MiT Strom Pipeline'!$D:$D,$U65))) | E65: =IF($U65="","",IF(INDEX('MiT Strom Pipeline'!$H:$H,$U65)="","",INDEX('MiT Strom Pipeline'!$H:$H,$U65))) | F65: =IF($U65="","",IF(INDEX('MiT Strom Pipeline'!$E:$E,$U65)="","",INDEX('MiT Strom Pipeline'!$E:$E,$U65))) | G65: =IF($U65="","",IF(ISNUMBER(INDEX('MiT Strom Pipeline'!$I:$I,$U65)),INDEX('MiT Strom Pipeline'!$I:$I,$U65),0)) | H65: =IF($U65="","",IF(ISNUMBER(INDEX('MiT Strom Pipeline'!$Q:$Q,$U65)),INDEX('MiT Strom Pipeline'!$Q:$Q,$U65),0)) | I65: =IF($U65="","",IF(ISNUMBER(INDEX('MiT Strom Pipeline'!$O:$O,$U65)),INDEX('MiT Strom Pipeline'!$O:$O,$U65),0)) | J65: =IF($U65="","",INDEX('MiT Strom Pipeline'!$R:$R,$U65)) | K65: =IF($U65="","",IF(ISNUMBER(INDEX('MiT Strom Pipeline'!$S:$S,$U65)),INDEX('MiT Strom Pipeline'!$S:$S,$U65),"")) | L65: =IF($U65="","",IF(LEN(INDEX('MiT Strom Pipeline'!$V:$V,$U65))>0,LEFT(INDEX('MiT Strom Pipeline'!$V:$V,$U65),55),"")) | U65: =IFERROR(MATCH(55,'MiT Strom Pipeline'!$AB$6:$AB$860,0)+5,"")
A66: =IF($U66="","",IF(ISNUMBER(INDEX('MiT Strom Pipeline'!$A:$A,$U66)),INDEX('MiT Strom Pipeline'!$A:$A,$U66),"")) | B66: =IF($U66="","",IF(INDEX('MiT Strom Pipeline'!$B:$B,$U66)="","",INDEX('MiT Strom Pipeline'!$B:$B,$U66))) | C66: =IF($U66="","",IF(INDEX('MiT Strom Pipeline'!$C:$C,$U66)="","",INDEX('MiT Strom Pipeline'!$C:$C,$U66))) | D66: =IF($U66="","",IF(INDEX('MiT Strom Pipeline'!$D:$D,$U66)="","",INDEX('MiT Strom Pipeline'!$D:$D,$U66))) | E66: =IF($U66="","",IF(INDEX('MiT Strom Pipeline'!$H:$H,$U66)="","",INDEX('MiT Strom Pipeline'!$H:$H,$U66))) | F66: =IF($U66="","",IF(INDEX('MiT Strom Pipeline'!$E:$E,$U66)="","",INDEX('MiT Strom Pipeline'!$E:$E,$U66))) | G66: =IF($U66="","",IF(ISNUMBER(INDEX('MiT Strom Pipeline'!$I:$I,$U66)),INDEX('MiT Strom Pipeline'!$I:$I,$U66),0)) | H66: =IF($U66="","",IF(ISNUMBER(INDEX('MiT Strom Pipeline'!$Q:$Q,$U66)),INDEX('MiT Strom Pipeline'!$Q:$Q,$U66),0)) | I66: =IF($U66="","",IF(ISNUMBER(INDEX('MiT Strom Pipeline'!$O:$O,$U66)),INDEX('MiT Strom Pipeline'!$O:$O,$U66),0)) | J66: =IF($U66="","",INDEX('MiT Strom Pipeline'!$R:$R,$U66)) | K66: =IF($U66="","",IF(ISNUMBER(INDEX('MiT Strom Pipeline'!$S:$S,$U66)),INDEX('MiT Strom Pipeline'!$S:$S,$U66),"")) | L66: =IF($U66="","",IF(LEN(INDEX('MiT Strom Pipeline'!$V:$V,$U66))>0,LEFT(INDEX('MiT Strom Pipeline'!$V:$V,$U66),55),"")) | U66: =IFERROR(MATCH(56,'MiT Strom Pipeline'!$AB$6:$AB$860,0)+5,"")
A67: =IF($U67="","",IF(ISNUMBER(INDEX('MiT Strom Pipeline'!$A:$A,$U67)),INDEX('MiT Strom Pipeline'!$A:$A,$U67),"")) | B67: =IF($U67="","",IF(INDEX('MiT Strom Pipeline'!$B:$B,$U67)="","",INDEX('MiT Strom Pipeline'!$B:$B,$U67))) | C67: =IF($U67="","",IF(INDEX('MiT Strom Pipeline'!$C:$C,$U67)="","",INDEX('MiT Strom Pipeline'!$C:$C,$U67))) | D67: =IF($U67="","",IF(INDEX('MiT Strom Pipeline'!$D:$D,$U67)="","",INDEX('MiT Strom Pipeline'!$D:$D,$U67))) | E67: =IF($U67="","",IF(INDEX('MiT Strom Pipeline'!$H:$H,$U67)="","",INDEX('MiT Strom Pipeline'!$H:$H,$U67))) | F67: =IF($U67="","",IF(INDEX('MiT Strom Pipeline'!$E:$E,$U67)="","",INDEX('MiT Strom Pipeline'!$E:$E,$U67))) | G67: =IF($U67="","",IF(ISNUMBER(INDEX('MiT Strom Pipeline'!$I:$I,$U67)),INDEX('MiT Strom Pipeline'!$I:$I,$U67),0)) | H67: =IF($U67="","",IF(ISNUMBER(INDEX('MiT Strom Pipeline'!$Q:$Q,$U67)),INDEX('MiT Strom Pipeline'!$Q:$Q,$U67),0)) | I67: =IF($U67="","",IF(ISNUMBER(INDEX('MiT Strom Pipeline'!$O:$O,$U67)),INDEX('MiT Strom Pipeline'!$O:$O,$U67),0)) | J67: =IF($U67="","",INDEX('MiT Strom Pipeline'!$R:$R,$U67)) | K67: =IF($U67="","",IF(ISNUMBER(INDEX('MiT Strom Pipeline'!$S:$S,$U67)),INDEX('MiT Strom Pipeline'!$S:$S,$U67),"")) | L67: =IF($U67="","",IF(LEN(INDEX('MiT Strom Pipeline'!$V:$V,$U67))>0,LEFT(INDEX('MiT Strom Pipeline'!$V:$V,$U67),55),"")) | U67: =IFERROR(MATCH(57,'MiT Strom Pipeline'!$AB$6:$AB$860,0)+5,"")
A68: =IF($U68="","",IF(ISNUMBER(INDEX('MiT Strom Pipeline'!$A:$A,$U68)),INDEX('MiT Strom Pipeline'!$A:$A,$U68),"")) | B68: =IF($U68="","",IF(INDEX('MiT Strom Pipeline'!$B:$B,$U68)="","",INDEX('MiT Strom Pipeline'!$B:$B,$U68))) | C68: =IF($U68="","",IF(INDEX('MiT Strom Pipeline'!$C:$C,$U68)="","",INDEX('MiT Strom Pipeline'!$C:$C,$U68))) | D68: =IF($U68="","",IF(INDEX('MiT Strom Pipeline'!$D:$D,$U68)="","",INDEX('MiT Strom Pipeline'!$D:$D,$U68))) | E68: =IF($U68="","",IF(INDEX('MiT Strom Pipeline'!$H:$H,$U68)="","",INDEX('MiT Strom Pipeline'!$H:$H,$U68))) | F68: =IF($U68="","",IF(INDEX('MiT Strom Pipeline'!$E:$E,$U68)="","",INDEX('MiT Strom Pipeline'!$E:$E,$U68))) | G68: =IF($U68="","",IF(ISNUMBER(INDEX('MiT Strom Pipeline'!$I:$I,$U68)),INDEX('MiT Strom Pipeline'!$I:$I,$U68),0)) | H68: =IF($U68="","",IF(ISNUMBER(INDEX('MiT Strom Pipeline'!$Q:$Q,$U68)),INDEX('MiT Strom Pipeline'!$Q:$Q,$U68),0)) | I68: =IF($U68="","",IF(ISNUMBER(INDEX('MiT Strom Pipeline'!$O:$O,$U68)),INDEX('MiT Strom Pipeline'!$O:$O,$U68),0)) | J68: =IF($U68="","",INDEX('MiT Strom Pipeline'!$R:$R,$U68)) | K68: =IF($U68="","",IF(ISNUMBER(INDEX('MiT Strom Pipeline'!$S:$S,$U68)),INDEX('MiT Strom Pipeline'!$S:$S,$U68),"")) | L68: =IF($U68="","",IF(LEN(INDEX('MiT Strom Pipeline'!$V:$V,$U68))>0,LEFT(INDEX('MiT Strom Pipeline'!$V:$V,$U68),55),"")) | U68: =IFERROR(MATCH(58,'MiT Strom Pipeline'!$AB$6:$AB$860,0)+5,"")
A69: =IF($U69="","",IF(ISNUMBER(INDEX('MiT Strom Pipeline'!$A:$A,$U69)),INDEX('MiT Strom Pipeline'!$A:$A,$U69),"")) | B69: =IF($U69="","",IF(INDEX('MiT Strom Pipeline'!$B:$B,$U69)="","",INDEX('MiT Strom Pipeline'!$B:$B,$U69))) | C69: =IF($U69="","",IF(INDEX('MiT Strom Pipeline'!$C:$C,$U69)="","",INDEX('MiT Strom Pipeline'!$C:$C,$U69))) | D69: =IF($U69="","",IF(INDEX('MiT Strom Pipeline'!$D:$D,$U69)="","",INDEX('MiT Strom Pipeline'!$D:$D,$U69))) | E69: =IF($U69="","",IF(INDEX('MiT Strom Pipeline'!$H:$H,$U69)="","",INDEX('MiT Strom Pipeline'!$H:$H,$U69))) | F69: =IF($U69="","",IF(INDEX('MiT Strom Pipeline'!$E:$E,$U69)="","",INDEX('MiT Strom Pipeline'!$E:$E,$U69))) | G69: =IF($U69="","",IF(ISNUMBER(INDEX('MiT Strom Pipeline'!$I:$I,$U69)),INDEX('MiT Strom Pipeline'!$I:$I,$U69),0)) | H69: =IF($U69="","",IF(ISNUMBER(INDEX('MiT Strom Pipeline'!$Q:$Q,$U69)),INDEX('MiT Strom Pipeline'!$Q:$Q,$U69),0)) | I69: =IF($U69="","",IF(ISNUMBER(INDEX('MiT Strom Pipeline'!$O:$O,$U69)),INDEX('MiT Strom Pipeline'!$O:$O,$U69),0)) | J69: =IF($U69="","",INDEX('MiT Strom Pipeline'!$R:$R,$U69)) | K69: =IF($U69="","",IF(ISNUMBER(INDEX('MiT Strom Pipeline'!$S:$S,$U69)),INDEX('MiT Strom Pipeline'!$S:$S,$U69),"")) | L69: =IF($U69="","",IF(LEN(INDEX('MiT Strom Pipeline'!$V:$V,$U69))>0,LEFT(INDEX('MiT Strom Pipeline'!$V:$V,$U69),55),"")) | U69: =IFERROR(MATCH(59,'MiT Strom Pipeline'!$AB$6:$AB$860,0)+5,"")
A70: =IF($U70="","",IF(ISNUMBER(INDEX('MiT Strom Pipeline'!$A:$A,$U70)),INDEX('MiT Strom Pipeline'!$A:$A,$U70),"")) | B70: =IF($U70="","",IF(INDEX('MiT Strom Pipeline'!$B:$B,$U70)="","",INDEX('MiT Strom Pipeline'!$B:$B,$U70))) | C70: =IF($U70="","",IF(INDEX('MiT Strom Pipeline'!$C:$C,$U70)="","",INDEX('MiT Strom Pipeline'!$C:$C,$U70))) | D70: =IF($U70="","",IF(INDEX('MiT Strom Pipeline'!$D:$D,$U70)="","",INDEX('MiT Strom Pipeline'!$D:$D,$U70))) | E70: =IF($U70="","",IF(INDEX('MiT Strom Pipeline'!$H:$H,$U70)="","",INDEX('MiT Strom Pipeline'!$H:$H,$U70))) | F70: =IF($U70="","",IF(INDEX('MiT Strom Pipeline'!$E:$E,$U70)="","",INDEX('MiT Strom Pipeline'!$E:$E,$U70))) | G70: =IF($U70="","",IF(ISNUMBER(INDEX('MiT Strom Pipeline'!$I:$I,$U70)),INDEX('MiT Strom Pipeline'!$I:$I,$U70),0)) | H70: =IF($U70="","",IF(ISNUMBER(INDEX('MiT Strom Pipeline'!$Q:$Q,$U70)),INDEX('MiT Strom Pipeline'!$Q:$Q,$U70),0)) | I70: =IF($U70="","",IF(ISNUMBER(INDEX('MiT Strom Pipeline'!$O:$O,$U70)),INDEX('MiT Strom Pipeline'!$O:$O,$U70),0)) | J70: =IF($U70="","",INDEX('MiT Strom Pipeline'!$R:$R,$U70)) | K70: =IF($U70="","",IF(ISNUMBER(INDEX('MiT Strom Pipeline'!$S:$S,$U70)),INDEX('MiT Strom Pipeline'!$S:$S,$U70),"")) | L70: =IF($U70="","",IF(LEN(INDEX('MiT Strom Pipeline'!$V:$V,$U70))>0,LEFT(INDEX('MiT Strom Pipeline'!$V:$V,$U70),55),"")) | U70: =IFERROR(MATCH(60,'MiT Strom Pipeline'!$AB$6:$AB$860,0)+5,"")
A71: =IF($U71="","",IF(ISNUMBER(INDEX('MiT Strom Pipeline'!$A:$A,$U71)),INDEX('MiT Strom Pipeline'!$A:$A,$U71),"")) | B71: =IF($U71="","",IF(INDEX('MiT Strom Pipeline'!$B:$B,$U71)="","",INDEX('MiT Strom Pipeline'!$B:$B,$U71))) | C71: =IF($U71="","",IF(INDEX('MiT Strom Pipeline'!$C:$C,$U71)="","",INDEX('MiT Strom Pipeline'!$C:$C,$U71))) | D71: =IF($U71="","",IF(INDEX('MiT Strom Pipeline'!$D:$D,$U71)="","",INDEX('MiT Strom Pipeline'!$D:$D,$U71))) | E71: =IF($U71="","",IF(INDEX('MiT Strom Pipeline'!$H:$H,$U71)="","",INDEX('MiT Strom Pipeline'!$H:$H,$U71))) | F71: =IF($U71="","",IF(INDEX('MiT Strom Pipeline'!$E:$E,$U71)="","",INDEX('MiT Strom Pipeline'!$E:$E,$U71))) | G71: =IF($U71="","",IF(ISNUMBER(INDEX('MiT Strom Pipeline'!$I:$I,$U71)),INDEX('MiT Strom Pipeline'!$I:$I,$U71),0)) | H71: =IF($U71="","",IF(ISNUMBER(INDEX('MiT Strom Pipeline'!$Q:$Q,$U71)),INDEX('MiT Strom Pipeline'!$Q:$Q,$U71),0)) | I71: =IF($U71="","",IF(ISNUMBER(INDEX('MiT Strom Pipeline'!$O:$O,$U71)),INDEX('MiT Strom Pipeline'!$O:$O,$U71),0)) | J71: =IF($U71="","",INDEX('MiT Strom Pipeline'!$R:$R,$U71)) | K71: =IF($U71="","",IF(ISNUMBER(INDEX('MiT Strom Pipeline'!$S:$S,$U71)),INDEX('MiT Strom Pipeline'!$S:$S,$U71),"")) | L71: =IF($U71="","",IF(LEN(INDEX('MiT Strom Pipeline'!$V:$V,$U71))>0,LEFT(INDEX('MiT Strom Pipeline'!$V:$V,$U71),55),"")) | U71: =IFERROR(MATCH(61,'MiT Strom Pipeline'!$AB$6:$AB$860,0)+5,"")
A72: =IF($U72="","",IF(ISNUMBER(INDEX('MiT Strom Pipeline'!$A:$A,$U72)),INDEX('MiT Strom Pipeline'!$A:$A,$U72),"")) | B72: =IF($U72="","",IF(INDEX('MiT Strom Pipeline'!$B:$B,$U72)="","",INDEX('MiT Strom Pipeline'!$B:$B,$U72))) | C72: =IF($U72="","",IF(INDEX('MiT Strom Pipeline'!$C:$C,$U72)="","",INDEX('MiT Strom Pipeline'!$C:$C,$U72))) | D72: =IF($U72="","",IF(INDEX('MiT Strom Pipeline'!$D:$D,$U72)="","",INDEX('MiT Strom Pipeline'!$D:$D,$U72))) | E72: =IF($U72="","",IF(INDEX('MiT Strom Pipeline'!$H:$H,$U72)="","",INDEX('MiT Strom Pipeline'!$H:$H,$U72))) | F72: =IF($U72="","",IF(INDEX('MiT Strom Pipeline'!$E:$E,$U72)="","",INDEX('MiT Strom Pipeline'!$E:$E,$U72))) | G72: =IF($U72="","",IF(ISNUMBER(INDEX('MiT Strom Pipeline'!$I:$I,$U72)),INDEX('MiT Strom Pipeline'!$I:$I,$U72),0)) | H72: =IF($U72="","",IF(ISNUMBER(INDEX('MiT Strom Pipeline'!$Q:$Q,$U72)),INDEX('MiT Strom Pipeline'!$Q:$Q,$U72),0)) | I72: =IF($U72="","",IF(ISNUMBER(INDEX('MiT Strom Pipeline'!$O:$O,$U72)),INDEX('MiT Strom Pipeline'!$O:$O,$U72),0)) | J72: =IF($U72="","",INDEX('MiT Strom Pipeline'!$R:$R,$U72)) | K72: =IF($U72="","",IF(ISNUMBER(INDEX('MiT Strom Pipeline'!$S:$S,$U72)),INDEX('MiT Strom Pipeline'!$S:$S,$U72),"")) | L72: =IF($U72="","",IF(LEN(INDEX('MiT Strom Pipeline'!$V:$V,$U72))>0,LEFT(INDEX('MiT Strom Pipeline'!$V:$V,$U72),55),"")) | U72: =IFERROR(MATCH(62,'MiT Strom Pipeline'!$AB$6:$AB$860,0)+5,"")
A73: 📄 2. OFFERTE — Versendete & laufende Angebote
A74: # | B74: Kunde / Unternehmen | C74: Kt. | D74: Segment | E74: Start | F74: Leistung / Fleet | G74: Volumen CHF | H74: Gew.Wert CHF | I74: Marge CHF | J74: Status | K74: Wahr.% | L74: Nächster Schritt
A75: =IF($U75="","",IF(ISNUMBER(INDEX('MiT Strom Pipeline'!$A:$A,$U75)),INDEX('MiT Strom Pipeline'!$A:$A,$U75),"")) -> 6 | B75: =IF($U75="","",IF(INDEX('MiT Strom Pipeline'!$B:$B,$U75)="","",INDEX('MiT Strom Pipeline'!$B:$B,$U75))) -> Wincasa Solothurn | C75: =IF($U75="","",IF(INDEX('MiT Strom Pipeline'!$C:$C,$U75)="","",INDEX('MiT Strom Pipeline'!$C:$C,$U75))) -> SO | D75: =IF($U75="","",IF(INDEX('MiT Strom Pipeline'!$D:$D,$U75)="","",INDEX('MiT Strom Pipeline'!$D:$D,$U75))) -> Immobilien / FM | E75: =IF($U75="","",IF(INDEX('MiT Strom Pipeline'!$H:$H,$U75)="","",INDEX('MiT Strom Pipeline'!$H:$H,$U75))) -> Mai | F75: =IF($U75="","",IF(INDEX('MiT Strom Pipeline'!$E:$E,$U75)="","",INDEX('MiT Strom Pipeline'!$E:$E,$U75))) -> BESS 1 MWh | G75: =IF($U75="","",IF(ISNUMBER(INDEX('MiT Strom Pipeline'!$I:$I,$U75)),INDEX('MiT Strom Pipeline'!$I:$I,$U75),0)) -> 390000 | H75: =IF($U75="","",IF(ISNUMBER(INDEX('MiT Strom Pipeline'!$Q:$Q,$U75)),INDEX('MiT Strom Pipeline'!$Q:$Q,$U75),0)) -> 195000 | I75: =IF($U75="","",IF(ISNUMBER(INDEX('MiT Strom Pipeline'!$O:$O,$U75)),INDEX('MiT Strom Pipeline'!$O:$O,$U75),0)) -> 118000 | J75: =IF($U75="","",INDEX('MiT Strom Pipeline'!$R:$R,$U75)) -> offered | K75: =IF($U75="","",IF(ISNUMBER(INDEX('MiT Strom Pipeline'!$S:$S,$U75)),INDEX('MiT Strom Pipeline'!$S:$S,$U75),"")) -> 0.5 | L75: =IF($U75="","",IF(LEN(INDEX('MiT Strom Pipeline'!$V:$V,$U75))>0,LEFT(INDEX('MiT Strom Pipeline'!$V:$V,$U75),55),"")) -> Entscheider-Meeting anfordern, Businesscase Energie-ROI | U75: =IFERROR(MATCH(1,'MiT Strom Pipeline'!$AC$6:$AC$860,0)+5,"") -> 6
A76: =IF($U76="","",IF(ISNUMBER(INDEX('MiT Strom Pipeline'!$A:$A,$U76)),INDEX('MiT Strom Pipeline'!$A:$A,$U76),"")) -> 15 | B76: =IF($U76="","",IF(INDEX('MiT Strom Pipeline'!$B:$B,$U76)="","",INDEX('MiT Strom Pipeline'!$B:$B,$U76))) -> Gotthard Base Tunnel | C76: =IF($U76="","",IF(INDEX('MiT Strom Pipeline'!$C:$C,$U76)="","",INDEX('MiT Strom Pipeline'!$C:$C,$U76))) -> UR | D76: =IF($U76="","",IF(INDEX('MiT Strom Pipeline'!$D:$D,$U76)="","",INDEX('MiT Strom Pipeline'!$D:$D,$U76))) -> Infrastruktur / Bahn | E76: =IF($U76="","",IF(INDEX('MiT Strom Pipeline'!$H:$H,$U76)="","",INDEX('MiT Strom Pipeline'!$H:$H,$U76))) -> tbd | F76: =IF($U76="","",IF(INDEX('MiT Strom Pipeline'!$E:$E,$U76)="","",INDEX('MiT Strom Pipeline'!$E:$E,$U76))) -> Grossanlage tbd | G76: =IF($U76="","",IF(ISNUMBER(INDEX('MiT Strom Pipeline'!$I:$I,$U76)),INDEX('MiT Strom Pipeline'!$I:$I,$U76),0)) -> 0 | H76: =IF($U76="","",IF(ISNUMBER(INDEX('MiT Strom Pipeline'!$Q:$Q,$U76)),INDEX('MiT Strom Pipeline'!$Q:$Q,$U76),0)) -> 0 | I76: =IF($U76="","",IF(ISNUMBER(INDEX('MiT Strom Pipeline'!$O:$O,$U76)),INDEX('MiT Strom Pipeline'!$O:$O,$U76),0)) -> 0 | J76: =IF($U76="","",INDEX('MiT Strom Pipeline'!$R:$R,$U76)) -> on hold | K76: =IF($U76="","",IF(ISNUMBER(INDEX('MiT Strom Pipeline'!$S:$S,$U76)),INDEX('MiT Strom Pipeline'!$S:$S,$U76),"")) -> 0.1 | L76: =IF($U76="","",IF(LEN(INDEX('MiT Strom Pipeline'!$V:$V,$U76))>0,LEFT(INDEX('MiT Strom Pipeline'!$V:$V,$U76),55),"")) -> Stakeholder identifizieren – AlpTransit/SBB kontaktiere | U76: =IFERROR(MATCH(2,'MiT Strom Pipeline'!$AC$6:$AC$860,0)+5,"") -> 8
A77: =IF($U77="","",IF(ISNUMBER(INDEX('MiT Strom Pipeline'!$A:$A,$U77)),INDEX('MiT Strom Pipeline'!$A:$A,$U77),"")) -> 33 | B77: =IF($U77="","",IF(INDEX('MiT Strom Pipeline'!$B:$B,$U77)="","",INDEX('MiT Strom Pipeline'!$B:$B,$U77))) -> Oerlikon Metco Wohlen | C77: =IF($U77="","",IF(INDEX('MiT Strom Pipeline'!$C:$C,$U77)="","",INDEX('MiT Strom Pipeline'!$C:$C,$U77))) -> AG | D77: =IF($U77="","",IF(INDEX('MiT Strom Pipeline'!$D:$D,$U77)="","",INDEX('MiT Strom Pipeline'!$D:$D,$U77))) -> Industrie | E77: =IF($U77="","",IF(INDEX('MiT Strom Pipeline'!$H:$H,$U77)="","",INDEX('MiT Strom Pipeline'!$H:$H,$U77))) -> August | F77: =IF($U77="","",IF(INDEX('MiT Strom Pipeline'!$E:$E,$U77)="","",INDEX('MiT Strom Pipeline'!$E:$E,$U77))) -> 300 kVA | G77: =IF($U77="","",IF(ISNUMBER(INDEX('MiT Strom Pipeline'!$I:$I,$U77)),INDEX('MiT Strom Pipeline'!$I:$I,$U77),0)) -> 193598.12 | H77: =IF($U77="","",IF(ISNUMBER(INDEX('MiT Strom Pipeline'!$Q:$Q,$U77)),INDEX('MiT Strom Pipeline'!$Q:$Q,$U77),0)) -> 154878.5 | I77: =IF($U77="","",IF(ISNUMBER(INDEX('MiT Strom Pipeline'!$O:$O,$U77)),INDEX('MiT Strom Pipeline'!$O:$O,$U77),0)) -> 14506.42 | J77: =IF($U77="","",INDEX('MiT Strom Pipeline'!$R:$R,$U77)) -> offered | K77: =IF($U77="","",IF(ISNUMBER(INDEX('MiT Strom Pipeline'!$S:$S,$U77)),INDEX('MiT Strom Pipeline'!$S:$S,$U77),"")) -> 0.8 | L77: =IF($U77="","",IF(LEN(INDEX('MiT Strom Pipeline'!$V:$V,$U77))>0,LEFT(INDEX('MiT Strom Pipeline'!$V:$V,$U77),55),"")) -> Kunde wahr sehr Zufrieden mit dem 1. Auftrag und im Ans | U77: =IFERROR(MATCH(3,'MiT Strom Pipeline'!$AC$6:$AC$860,0)+5,"") -> 16
A78: =IF($U78="","",IF(ISNUMBER(INDEX('MiT Strom Pipeline'!$A:$A,$U78)),INDEX('MiT Strom Pipeline'!$A:$A,$U78),"")) -> 33 | B78: =IF($U78="","",IF(INDEX('MiT Strom Pipeline'!$B:$B,$U78)="","",INDEX('MiT Strom Pipeline'!$B:$B,$U78))) -> Oerlikon Metco Wohlen | C78: =IF($U78="","",IF(INDEX('MiT Strom Pipeline'!$C:$C,$U78)="","",INDEX('MiT Strom Pipeline'!$C:$C,$U78))) -> AG | D78: =IF($U78="","",IF(INDEX('MiT Strom Pipeline'!$D:$D,$U78)="","",INDEX('MiT Strom Pipeline'!$D:$D,$U78))) -> Industrie | E78: =IF($U78="","",IF(INDEX('MiT Strom Pipeline'!$H:$H,$U78)="","",INDEX('MiT Strom Pipeline'!$H:$H,$U78))) -> August | F78: =IF($U78="","",IF(INDEX('MiT Strom Pipeline'!$E:$E,$U78)="","",INDEX('MiT Strom Pipeline'!$E:$E,$U78))) -> Kaltwasser 100 kW | G78: =IF($U78="","",IF(ISNUMBER(INDEX('MiT Strom Pipeline'!$I:$I,$U78)),INDEX('MiT Strom Pipeline'!$I:$I,$U78),0)) -> 74902.11 | H78: =IF($U78="","",IF(ISNUMBER(INDEX('MiT Strom Pipeline'!$Q:$Q,$U78)),INDEX('MiT Strom Pipeline'!$Q:$Q,$U78),0)) -> 59921.688 | I78: =IF($U78="","",IF(ISNUMBER(INDEX('MiT Strom Pipeline'!$O:$O,$U78)),INDEX('MiT Strom Pipeline'!$O:$O,$U78),0)) -> 10935.08 | J78: =IF($U78="","",INDEX('MiT Strom Pipeline'!$R:$R,$U78)) -> offered | K78: =IF($U78="","",IF(ISNUMBER(INDEX('MiT Strom Pipeline'!$S:$S,$U78)),INDEX('MiT Strom Pipeline'!$S:$S,$U78),"")) -> 0.8 | L78: =IF($U78="","",IF(LEN(INDEX('MiT Strom Pipeline'!$V:$V,$U78))>0,LEFT(INDEX('MiT Strom Pipeline'!$V:$V,$U78),55),"")) -> Kunde wahr sehr Zufrieden mit dem 1. Auftrag und im Ans | U78: =IFERROR(MATCH(4,'MiT Strom Pipeline'!$AC$6:$AC$860,0)+5,"") -> 17
A79: =IF($U79="","",IF(ISNUMBER(INDEX('MiT Strom Pipeline'!$A:$A,$U79)),INDEX('MiT Strom Pipeline'!$A:$A,$U79),"")) -> 13 | B79: =IF($U79="","",IF(INDEX('MiT Strom Pipeline'!$B:$B,$U79)="","",INDEX('MiT Strom Pipeline'!$B:$B,$U79))) -> Proxima Fusion AG | C79: =IF($U79="","",IF(INDEX('MiT Strom Pipeline'!$C:$C,$U79)="","",INDEX('MiT Strom Pipeline'!$C:$C,$U79))) -> ZH | D79: =IF($U79="","",IF(INDEX('MiT Strom Pipeline'!$D:$D,$U79)="","",INDEX('MiT Strom Pipeline'!$D:$D,$U79))) -> Forschung / Hightech | E79: =IF($U79="","",IF(INDEX('MiT Strom Pipeline'!$H:$H,$U79)="","",INDEX('MiT Strom Pipeline'!$H:$H,$U79))) -> Juli | F79: =IF($U79="","",IF(INDEX('MiT Strom Pipeline'!$E:$E,$U79)="","",INDEX('MiT Strom Pipeline'!$E:$E,$U79))) -> BESS 1 MWh | G79: =IF($U79="","",IF(ISNUMBER(INDEX('MiT Strom Pipeline'!$I:$I,$U79)),INDEX('MiT Strom Pipeline'!$I:$I,$U79),0)) -> 365003 | H79: =IF($U79="","",IF(ISNUMBER(INDEX('MiT Strom Pipeline'!$Q:$Q,$U79)),INDEX('MiT Strom Pipeline'!$Q:$Q,$U79),0)) -> 182501.5 | I79: =IF($U79="","",IF(ISNUMBER(INDEX('MiT Strom Pipeline'!$O:$O,$U79)),INDEX('MiT Strom Pipeline'!$O:$O,$U79),0)) -> 30087 | J79: =IF($U79="","",INDEX('MiT Strom Pipeline'!$R:$R,$U79)) -> offered | K79: =IF($U79="","",IF(ISNUMBER(INDEX('MiT Strom Pipeline'!$S:$S,$U79)),INDEX('MiT Strom Pipeline'!$S:$S,$U79),"")) -> 0.5 | L79: =IF($U79="","",IF(LEN(INDEX('MiT Strom Pipeline'!$V:$V,$U79))>0,LEFT(INDEX('MiT Strom Pipeline'!$V:$V,$U79),55),"")) -> Technisches Gespräch – USV + PQ-Anforderungen klären, K | U79: =IFERROR(MATCH(5,'MiT Strom Pipeline'!$AC$6:$AC$860,0)+5,"") -> 18
A80: =IF($U80="","",IF(ISNUMBER(INDEX('MiT Strom Pipeline'!$A:$A,$U80)),INDEX('MiT Strom Pipeline'!$A:$A,$U80),"")) -> 25 | B80: =IF($U80="","",IF(INDEX('MiT Strom Pipeline'!$B:$B,$U80)="","",INDEX('MiT Strom Pipeline'!$B:$B,$U80))) -> Reto EKAG | C80: =IF($U80="","",IF(INDEX('MiT Strom Pipeline'!$C:$C,$U80)="","",INDEX('MiT Strom Pipeline'!$C:$C,$U80))) -> AG | D80: =IF($U80="","",IF(INDEX('MiT Strom Pipeline'!$D:$D,$U80)="","",INDEX('MiT Strom Pipeline'!$D:$D,$U80))) -> Elektroinstallation | E80: =IF($U80="","",IF(INDEX('MiT Strom Pipeline'!$H:$H,$U80)="","",INDEX('MiT Strom Pipeline'!$H:$H,$U80))) -> Okt | F80: =IF($U80="","",IF(INDEX('MiT Strom Pipeline'!$E:$E,$U80)="","",INDEX('MiT Strom Pipeline'!$E:$E,$U80))) -> Option B 1x 6 kVA Trafo, 1x 3000 kVA Trafo, 1x 6000 kVA Lastbank, 1x 3300 kVA Lastbank | G80: =IF($U80="","",IF(ISNUMBER(INDEX('MiT Strom Pipeline'!$I:$I,$U80)),INDEX('MiT Strom Pipeline'!$I:$I,$U80),0)) -> 57249.54 | H80: =IF($U80="","",IF(ISNUMBER(INDEX('MiT Strom Pipeline'!$Q:$Q,$U80)),INDEX('MiT Strom Pipeline'!$Q:$Q,$U80),0)) -> 51524.586 | I80: =IF($U80="","",IF(ISNUMBER(INDEX('MiT Strom Pipeline'!$O:$O,$U80)),INDEX('MiT Strom Pipeline'!$O:$O,$U80),0)) -> -21565.77 | J80: =IF($U80="","",INDEX('MiT Strom Pipeline'!$R:$R,$U80)) -> offered | K80: =IF($U80="","",IF(ISNUMBER(INDEX('MiT Strom Pipeline'!$S:$S,$U80)),INDEX('MiT Strom Pipeline'!$S:$S,$U80),"")) -> 0.9 | L80: =IF($U80="","",IF(LEN(INDEX('MiT Strom Pipeline'!$V:$V,$U80))>0,LEFT(INDEX('MiT Strom Pipeline'!$V:$V,$U80),55),"")) -> Kunde Telefon Kontaktiert und Vor Ort Besichtigung und | U80: =IFERROR(MATCH(6,'MiT Strom Pipeline'!$AC$6:$AC$860,0)+5,"") -> 19
A81: =IF($U81="","",IF(ISNUMBER(INDEX('MiT Strom Pipeline'!$A:$A,$U81)),INDEX('MiT Strom Pipeline'!$A:$A,$U81),"")) -> 25 | B81: =IF($U81="","",IF(INDEX('MiT Strom Pipeline'!$B:$B,$U81)="","",INDEX('MiT Strom Pipeline'!$B:$B,$U81))) -> Reto EKAG | C81: =IF($U81="","",IF(INDEX('MiT Strom Pipeline'!$C:$C,$U81)="","",INDEX('MiT Strom Pipeline'!$C:$C,$U81))) -> AG | D81: =IF($U81="","",IF(INDEX('MiT Strom Pipeline'!$D:$D,$U81)="","",INDEX('MiT Strom Pipeline'!$D:$D,$U81))) -> Elektroinstallation | E81: =IF($U81="","",IF(INDEX('MiT Strom Pipeline'!$H:$H,$U81)="","",INDEX('MiT Strom Pipeline'!$H:$H,$U81))) -> Okt | F81: =IF($U81="","",IF(INDEX('MiT Strom Pipeline'!$E:$E,$U81)="","",INDEX('MiT Strom Pipeline'!$E:$E,$U81))) -> MS Kabel 95mm | G81: =IF($U81="","",IF(ISNUMBER(INDEX('MiT Strom Pipeline'!$I:$I,$U81)),INDEX('MiT Strom Pipeline'!$I:$I,$U81),0)) -> 15664.18 | H81: =IF($U81="","",IF(ISNUMBER(INDEX('MiT Strom Pipeline'!$Q:$Q,$U81)),INDEX('MiT Strom Pipeline'!$Q:$Q,$U81),0)) -> 14097.762 | I81: =IF($U81="","",IF(ISNUMBER(INDEX('MiT Strom Pipeline'!$O:$O,$U81)),INDEX('MiT Strom Pipeline'!$O:$O,$U81),0)) -> 18 | J81: =IF($U81="","",INDEX('MiT Strom Pipeline'!$R:$R,$U81)) -> offered | K81: =IF($U81="","",IF(ISNUMBER(INDEX('MiT Strom Pipeline'!$S:$S,$U81)),INDEX('MiT Strom Pipeline'!$S:$S,$U81),"")) -> 0.9 | L81: =IF($U81="","",IF(LEN(INDEX('MiT Strom Pipeline'!$V:$V,$U81))>0,LEFT(INDEX('MiT Strom Pipeline'!$V:$V,$U81),55),"")) -> Kunde Telefon Kontaktiert und Vor Ort Besichtigung und | U81: =IFERROR(MATCH(7,'MiT Strom Pipeline'!$AC$6:$AC$860,0)+5,"") -> 20
A82: =IF($U82="","",IF(ISNUMBER(INDEX('MiT Strom Pipeline'!$A:$A,$U82)),INDEX('MiT Strom Pipeline'!$A:$A,$U82),"")) -> 28 | B82: =IF($U82="","",IF(INDEX('MiT Strom Pipeline'!$B:$B,$U82)="","",INDEX('MiT Strom Pipeline'!$B:$B,$U82))) -> WEF | C82: =IF($U82="","",IF(INDEX('MiT Strom Pipeline'!$C:$C,$U82)="","",INDEX('MiT Strom Pipeline'!$C:$C,$U82))) -> GR | D82: =IF($U82="","",IF(INDEX('MiT Strom Pipeline'!$D:$D,$U82)="","",INDEX('MiT Strom Pipeline'!$D:$D,$U82))) -> Event | E82: =IF($U82="","",IF(INDEX('MiT Strom Pipeline'!$H:$H,$U82)="","",INDEX('MiT Strom Pipeline'!$H:$H,$U82))) -> Jan | F82: =IF($U82="","",IF(INDEX('MiT Strom Pipeline'!$E:$E,$U82)="","",INDEX('MiT Strom Pipeline'!$E:$E,$U82))) -> 1500 kVA, 600 kVA, 450 kVA, 450 kVA | G82: =IF($U82="","",IF(ISNUMBER(INDEX('MiT Strom Pipeline'!$I:$I,$U82)),INDEX('MiT Strom Pipeline'!$I:$I,$U82),0)) -> 77325.62 | H82: =IF($U82="","",IF(ISNUMBER(INDEX('MiT Strom Pipeline'!$Q:$Q,$U82)),INDEX('MiT Strom Pipeline'!$Q:$Q,$U82),0)) -> 38662.81 | I82: =IF($U82="","",IF(ISNUMBER(INDEX('MiT Strom Pipeline'!$O:$O,$U82)),INDEX('MiT Strom Pipeline'!$O:$O,$U82),0)) -> 5794.06 | J82: =IF($U82="","",INDEX('MiT Strom Pipeline'!$R:$R,$U82)) -> offered | K82: =IF($U82="","",IF(ISNUMBER(INDEX('MiT Strom Pipeline'!$S:$S,$U82)),INDEX('MiT Strom Pipeline'!$S:$S,$U82),"")) -> 0.5 | L82: =IF($U82="","",IF(LEN(INDEX('MiT Strom Pipeline'!$V:$V,$U82))>0,LEFT(INDEX('MiT Strom Pipeline'!$V:$V,$U82),55),"")) -> Offerte erstellt, Stefan hat die Offerte bekommen, Stef | U82: =IFERROR(MATCH(8,'MiT Strom Pipeline'!$AC$6:$AC$860,0)+5,"") -> 21
A83: =IF($U83="","",IF(ISNUMBER(INDEX('MiT Strom Pipeline'!$A:$A,$U83)),INDEX('MiT Strom Pipeline'!$A:$A,$U83),"")) -> 8 | B83: =IF($U83="","",IF(INDEX('MiT Strom Pipeline'!$B:$B,$U83)="","",INDEX('MiT Strom Pipeline'!$B:$B,$U83))) -> Sade CGTH (Schweiz) | C83: =IF($U83="","",IF(INDEX('MiT Strom Pipeline'!$C:$C,$U83)="","",INDEX('MiT Strom Pipeline'!$C:$C,$U83))) -> GE | D83: =IF($U83="","",IF(INDEX('MiT Strom Pipeline'!$D:$D,$U83)="","",INDEX('MiT Strom Pipeline'!$D:$D,$U83))) -> Infrastruktur / Bau | E83: =IF($U83="","",IF(INDEX('MiT Strom Pipeline'!$H:$H,$U83)="","",INDEX('MiT Strom Pipeline'!$H:$H,$U83))) -> April | F83: =IF($U83="","",IF(INDEX('MiT Strom Pipeline'!$E:$E,$U83)="","",INDEX('MiT Strom Pipeline'!$E:$E,$U83))) -> 750 kVA Generator | G83: =IF($U83="","",IF(ISNUMBER(INDEX('MiT Strom Pipeline'!$I:$I,$U83)),INDEX('MiT Strom Pipeline'!$I:$I,$U83),0)) -> 38885 | H83: =IF($U83="","",IF(ISNUMBER(INDEX('MiT Strom Pipeline'!$Q:$Q,$U83)),INDEX('MiT Strom Pipeline'!$Q:$Q,$U83),0)) -> 19442.5 | I83: =IF($U83="","",IF(ISNUMBER(INDEX('MiT Strom Pipeline'!$O:$O,$U83)),INDEX('MiT Strom Pipeline'!$O:$O,$U83),0)) -> 7085 | J83: =IF($U83="","",INDEX('MiT Strom Pipeline'!$R:$R,$U83)) -> on hold | K83: =IF($U83="","",IF(ISNUMBER(INDEX('MiT Strom Pipeline'!$S:$S,$U83)),INDEX('MiT Strom Pipeline'!$S:$S,$U83),"")) -> 0.5 | L83: =IF($U83="","",IF(LEN(INDEX('MiT Strom Pipeline'!$V:$V,$U83))>0,LEFT(INDEX('MiT Strom Pipeline'!$V:$V,$U83),55),"")) -> Auftragsbestätigung anfordern – Entscheid steht bevor | U83: =IFERROR(MATCH(9,'MiT Strom Pipeline'!$AC$6:$AC$860,0)+5,"") -> 28
A84: =IF($U84="","",IF(ISNUMBER(INDEX('MiT Strom Pipeline'!$A:$A,$U84)),INDEX('MiT Strom Pipeline'!$A:$A,$U84),"")) -> 14 | B84: =IF($U84="","",IF(INDEX('MiT Strom Pipeline'!$B:$B,$U84)="","",INDEX('MiT Strom Pipeline'!$B:$B,$U84))) -> Trafag AG | C84: =IF($U84="","",IF(INDEX('MiT Strom Pipeline'!$C:$C,$U84)="","",INDEX('MiT Strom Pipeline'!$C:$C,$U84))) -> ZH | D84: =IF($U84="","",IF(INDEX('MiT Strom Pipeline'!$D:$D,$U84)="","",INDEX('MiT Strom Pipeline'!$D:$D,$U84))) -> Industrie / Messtechnik | E84: =IF($U84="","",IF(INDEX('MiT Strom Pipeline'!$H:$H,$U84)="","",INDEX('MiT Strom Pipeline'!$H:$H,$U84))) -> tbd | F84: =IF($U84="","",IF(INDEX('MiT Strom Pipeline'!$E:$E,$U84)="","",INDEX('MiT Strom Pipeline'!$E:$E,$U84))) -> 450 kVA Generator | G84: =IF($U84="","",IF(ISNUMBER(INDEX('MiT Strom Pipeline'!$I:$I,$U84)),INDEX('MiT Strom Pipeline'!$I:$I,$U84),0)) -> 17300 | H84: =IF($U84="","",IF(ISNUMBER(INDEX('MiT Strom Pipeline'!$Q:$Q,$U84)),INDEX('MiT Strom Pipeline'!$Q:$Q,$U84),0)) -> 3460 | I84: =IF($U84="","",IF(ISNUMBER(INDEX('MiT Strom Pipeline'!$O:$O,$U84)),INDEX('MiT Strom Pipeline'!$O:$O,$U84),0)) -> 17300 | J84: =IF($U84="","",INDEX('MiT Strom Pipeline'!$R:$R,$U84)) -> offered | K84: =IF($U84="","",IF(ISNUMBER(INDEX('MiT Strom Pipeline'!$S:$S,$U84)),INDEX('MiT Strom Pipeline'!$S:$S,$U84),"")) -> 0.2 | L84: =IF($U84="","",IF(LEN(INDEX('MiT Strom Pipeline'!$V:$V,$U84))>0,LEFT(INDEX('MiT Strom Pipeline'!$V:$V,$U84),55),"")) -> Angebot vorbereiten – PQ-Argument für Messtechnik, Stef | U84: =IFERROR(MATCH(10,'MiT Strom Pipeline'!$AC$6:$AC$860,0)+5,"") -> 33
A85: =IF($U85="","",IF(ISNUMBER(INDEX('MiT Strom Pipeline'!$A:$A,$U85)),INDEX('MiT Strom Pipeline'!$A:$A,$U85),"")) -> 14 | B85: =IF($U85="","",IF(INDEX('MiT Strom Pipeline'!$B:$B,$U85)="","",INDEX('MiT Strom Pipeline'!$B:$B,$U85))) -> Trafag AG | C85: =IF($U85="","",IF(INDEX('MiT Strom Pipeline'!$C:$C,$U85)="","",INDEX('MiT Strom Pipeline'!$C:$C,$U85))) -> ZH | D85: =IF($U85="","",IF(INDEX('MiT Strom Pipeline'!$D:$D,$U85)="","",INDEX('MiT Strom Pipeline'!$D:$D,$U85))) -> Industrie / Messtechnik | E85: =IF($U85="","",IF(INDEX('MiT Strom Pipeline'!$H:$H,$U85)="","",INDEX('MiT Strom Pipeline'!$H:$H,$U85))) -> tbd | F85: =IF($U85="","",IF(INDEX('MiT Strom Pipeline'!$E:$E,$U85)="","",INDEX('MiT Strom Pipeline'!$E:$E,$U85))) -> BESS 500 kVA | G85: =IF($U85="","",IF(ISNUMBER(INDEX('MiT Strom Pipeline'!$I:$I,$U85)),INDEX('MiT Strom Pipeline'!$I:$I,$U85),0)) -> 21025 | H85: =IF($U85="","",IF(ISNUMBER(INDEX('MiT Strom Pipeline'!$Q:$Q,$U85)),INDEX('MiT Strom Pipeline'!$Q:$Q,$U85),0)) -> 4205 | I85: =IF($U85="","",IF(ISNUMBER(INDEX('MiT Strom Pipeline'!$O:$O,$U85)),INDEX('MiT Strom Pipeline'!$O:$O,$U85),0)) -> 21025 | J85: =IF($U85="","",INDEX('MiT Strom Pipeline'!$R:$R,$U85)) -> offered | K85: =IF($U85="","",IF(ISNUMBER(INDEX('MiT Strom Pipeline'!$S:$S,$U85)),INDEX('MiT Strom Pipeline'!$S:$S,$U85),"")) -> 0.2 | L85: =IF($U85="","",IF(LEN(INDEX('MiT Strom Pipeline'!$V:$V,$U85))>0,LEFT(INDEX('MiT Strom Pipeline'!$V:$V,$U85),55),"")) -> Angebot vorbereiten – PQ-Argument für Messtechnik, Stef | U85: =IFERROR(MATCH(11,'MiT Strom Pipeline'!$AC$6:$AC$860,0)+5,"") -> 35
A86: =IF($U86="","",IF(ISNUMBER(INDEX('MiT Strom Pipeline'!$A:$A,$U86)),INDEX('MiT Strom Pipeline'!$A:$A,$U86),"")) -> 14 | B86: =IF($U86="","",IF(INDEX('MiT Strom Pipeline'!$B:$B,$U86)="","",INDEX('MiT Strom Pipeline'!$B:$B,$U86))) -> Trafag AG | C86: =IF($U86="","",IF(INDEX('MiT Strom Pipeline'!$C:$C,$U86)="","",INDEX('MiT Strom Pipeline'!$C:$C,$U86))) -> ZH | D86: =IF($U86="","",IF(INDEX('MiT Strom Pipeline'!$D:$D,$U86)="","",INDEX('MiT Strom Pipeline'!$D:$D,$U86))) -> Industrie / Messtechnik | E86: =IF($U86="","",IF(INDEX('MiT Strom Pipeline'!$H:$H,$U86)="","",INDEX('MiT Strom Pipeline'!$H:$H,$U86))) -> tbd | F86: =IF($U86="","",IF(INDEX('MiT Strom Pipeline'!$E:$E,$U86)="","",INDEX('MiT Strom Pipeline'!$E:$E,$U86))) -> Kombi 450 kVA Generator / BESS 500 kVA | G86: =IF($U86="","",IF(ISNUMBER(INDEX('MiT Strom Pipeline'!$I:$I,$U86)),INDEX('MiT Strom Pipeline'!$I:$I,$U86),0)) -> 37444 | H86: =IF($U86="","",IF(ISNUMBER(INDEX('MiT Strom Pipeline'!$Q:$Q,$U86)),INDEX('MiT Strom Pipeline'!$Q:$Q,$U86),0)) -> 7488.8 | I86: =IF($U86="","",IF(ISNUMBER(INDEX('MiT Strom Pipeline'!$O:$O,$U86)),INDEX('MiT Strom Pipeline'!$O:$O,$U86),0)) -> 37444 | J86: =IF($U86="","",INDEX('MiT Strom Pipeline'!$R:$R,$U86)) -> offered | K86: =IF($U86="","",IF(ISNUMBER(INDEX('MiT Strom Pipeline'!$S:$S,$U86)),INDEX('MiT Strom Pipeline'!$S:$S,$U86),"")) -> 0.2 | L86: =IF($U86="","",IF(LEN(INDEX('MiT Strom Pipeline'!$V:$V,$U86))>0,LEFT(INDEX('MiT Strom Pipeline'!$V:$V,$U86),55),"")) -> Angebot vorbereiten – PQ-Argument für Messtechnik, Stef | U86: =IFERROR(MATCH(12,'MiT Strom Pipeline'!$AC$6:$AC$860,0)+5,"") -> 36
A87: =IF($U87="","",IF(ISNUMBER(INDEX('MiT Strom Pipeline'!$A:$A,$U87)),INDEX('MiT Strom Pipeline'!$A:$A,$U87),"")) -> 27 | B87: =IF($U87="","",IF(INDEX('MiT Strom Pipeline'!$B:$B,$U87)="","",INDEX('MiT Strom Pipeline'!$B:$B,$U87))) -> Rimus & Sstrada | C87: =IF($U87="","",IF(INDEX('MiT Strom Pipeline'!$C:$C,$U87)="","",INDEX('MiT Strom Pipeline'!$C:$C,$U87))) -> SH | D87: =IF($U87="","",IF(INDEX('MiT Strom Pipeline'!$D:$D,$U87)="","",INDEX('MiT Strom Pipeline'!$D:$D,$U87))) -> Industrie | E87: =IF($U87="","",IF(INDEX('MiT Strom Pipeline'!$H:$H,$U87)="","",INDEX('MiT Strom Pipeline'!$H:$H,$U87))) -> tbd | F87: =IF($U87="","",IF(INDEX('MiT Strom Pipeline'!$E:$E,$U87)="","",INDEX('MiT Strom Pipeline'!$E:$E,$U87))) -> 500 kWh Small BESS | G87: =IF($U87="","",IF(ISNUMBER(INDEX('MiT Strom Pipeline'!$I:$I,$U87)),INDEX('MiT Strom Pipeline'!$I:$I,$U87),0)) -> 425955 | H87: =IF($U87="","",IF(ISNUMBER(INDEX('MiT Strom Pipeline'!$Q:$Q,$U87)),INDEX('MiT Strom Pipeline'!$Q:$Q,$U87),0)) -> 85191 | I87: =IF($U87="","",IF(ISNUMBER(INDEX('MiT Strom Pipeline'!$O:$O,$U87)),INDEX('MiT Strom Pipeline'!$O:$O,$U87),0)) -> 2235 | J87: =IF($U87="","",INDEX('MiT Strom Pipeline'!$R:$R,$U87)) -> offered | K87: =IF($U87="","",IF(ISNUMBER(INDEX('MiT Strom Pipeline'!$S:$S,$U87)),INDEX('MiT Strom Pipeline'!$S:$S,$U87),"")) -> 0.2 | L87: =IF($U87="","",IF(LEN(INDEX('MiT Strom Pipeline'!$V:$V,$U87))>0,LEFT(INDEX('MiT Strom Pipeline'!$V:$V,$U87),55),"")) -> Kunde Telefon Kontaktiert und Vor Ort Besichtigung und | U87: =IFERROR(MATCH(13,'MiT Strom Pipeline'!$AC$6:$AC$860,0)+5,"") -> 37
A88: =IF($U88="","",IF(ISNUMBER(INDEX('MiT Strom Pipeline'!$A:$A,$U88)),INDEX('MiT Strom Pipeline'!$A:$A,$U88),"")) -> 27 | B88: =IF($U88="","",IF(INDEX('MiT Strom Pipeline'!$B:$B,$U88)="","",INDEX('MiT Strom Pipeline'!$B:$B,$U88))) -> Rimus & Sstrada | C88: =IF($U88="","",IF(INDEX('MiT Strom Pipeline'!$C:$C,$U88)="","",INDEX('MiT Strom Pipeline'!$C:$C,$U88))) -> SH | D88: =IF($U88="","",IF(INDEX('MiT Strom Pipeline'!$D:$D,$U88)="","",INDEX('MiT Strom Pipeline'!$D:$D,$U88))) -> Industrie | E88: =IF($U88="","",IF(INDEX('MiT Strom Pipeline'!$H:$H,$U88)="","",INDEX('MiT Strom Pipeline'!$H:$H,$U88))) -> tbd | F88: =IF($U88="","",IF(INDEX('MiT Strom Pipeline'!$E:$E,$U88)="","",INDEX('MiT Strom Pipeline'!$E:$E,$U88))) -> 1 MWh Medium BESS | G88: =IF($U88="","",IF(ISNUMBER(INDEX('MiT Strom Pipeline'!$I:$I,$U88)),INDEX('MiT Strom Pipeline'!$I:$I,$U88),0)) -> 891330 | H88: =IF($U88="","",IF(ISNUMBER(INDEX('MiT Strom Pipeline'!$Q:$Q,$U88)),INDEX('MiT Strom Pipeline'!$Q:$Q,$U88),0)) -> 178266 | I88: =IF($U88="","",IF(ISNUMBER(INDEX('MiT Strom Pipeline'!$O:$O,$U88)),INDEX('MiT Strom Pipeline'!$O:$O,$U88),0)) -> 9900 | J88: =IF($U88="","",INDEX('MiT Strom Pipeline'!$R:$R,$U88)) -> offered | K88: =IF($U88="","",IF(ISNUMBER(INDEX('MiT Strom Pipeline'!$S:$S,$U88)),INDEX('MiT Strom Pipeline'!$S:$S,$U88),"")) -> 0.2 | L88: =IF($U88="","",IF(LEN(INDEX('MiT Strom Pipeline'!$V:$V,$U88))>0,LEFT(INDEX('MiT Strom Pipeline'!$V:$V,$U88),55),"")) -> Kunde Telefon Kontaktiert und Vor Ort Besichtigung und | U88: =IFERROR(MATCH(14,'MiT Strom Pipeline'!$AC$6:$AC$860,0)+5,"") -> 38
A89: =IF($U89="","",IF(ISNUMBER(INDEX('MiT Strom Pipeline'!$A:$A,$U89)),INDEX('MiT Strom Pipeline'!$A:$A,$U89),"")) -> 27 | B89: =IF($U89="","",IF(INDEX('MiT Strom Pipeline'!$B:$B,$U89)="","",INDEX('MiT Strom Pipeline'!$B:$B,$U89))) -> Rimus & Sstrada | C89: =IF($U89="","",IF(INDEX('MiT Strom Pipeline'!$C:$C,$U89)="","",INDEX('MiT Strom Pipeline'!$C:$C,$U89))) -> SH | D89: =IF($U89="","",IF(INDEX('MiT Strom Pipeline'!$D:$D,$U89)="","",INDEX('MiT Strom Pipeline'!$D:$D,$U89))) -> Industrie | E89: =IF($U89="","",IF(INDEX('MiT Strom Pipeline'!$H:$H,$U89)="","",INDEX('MiT Strom Pipeline'!$H:$H,$U89))) -> tbd | F89: =IF($U89="","",IF(INDEX('MiT Strom Pipeline'!$E:$E,$U89)="","",INDEX('MiT Strom Pipeline'!$E:$E,$U89))) -> 1,5 MWh Large BESS | G89: =IF($U89="","",IF(ISNUMBER(INDEX('MiT Strom Pipeline'!$I:$I,$U89)),INDEX('MiT Strom Pipeline'!$I:$I,$U89),0)) -> 1307430 | H89: =IF($U89="","",IF(ISNUMBER(INDEX('MiT Strom Pipeline'!$Q:$Q,$U89)),INDEX('MiT Strom Pipeline'!$Q:$Q,$U89),0)) -> 261486 | I89: =IF($U89="","",IF(ISNUMBER(INDEX('MiT Strom Pipeline'!$O:$O,$U89)),INDEX('MiT Strom Pipeline'!$O:$O,$U89),0)) -> 9900 | J89: =IF($U89="","",INDEX('MiT Strom Pipeline'!$R:$R,$U89)) -> offered | K89: =IF($U89="","",IF(ISNUMBER(INDEX('MiT Strom Pipeline'!$S:$S,$U89)),INDEX('MiT Strom Pipeline'!$S:$S,$U89),"")) -> 0.2 | L89: =IF($U89="","",IF(LEN(INDEX('MiT Strom Pipeline'!$V:$V,$U89))>0,LEFT(INDEX('MiT Strom Pipeline'!$V:$V,$U89),55),"")) -> Kunde Telefon Kontaktiert und Vor Ort Besichtigung und | U89: =IFERROR(MATCH(15,'MiT Strom Pipeline'!$AC$6:$AC$860,0)+5,"") -> 39
A90: =IF($U90="","",IF(ISNUMBER(INDEX('MiT Strom Pipeline'!$A:$A,$U90)),INDEX('MiT Strom Pipeline'!$A:$A,$U90),"")) -> 34 | B90: =IF($U90="","",IF(INDEX('MiT Strom Pipeline'!$B:$B,$U90)="","",INDEX('MiT Strom Pipeline'!$B:$B,$U90))) -> Creabeton | C90: =IF($U90="","",IF(INDEX('MiT Strom Pipeline'!$C:$C,$U90)="","",INDEX('MiT Strom Pipeline'!$C:$C,$U90))) -> BE | D90: =IF($U90="","",IF(INDEX('MiT Strom Pipeline'!$D:$D,$U90)="","",INDEX('MiT Strom Pipeline'!$D:$D,$U90))) -> Infrastruktur / Bau | E90: =IF($U90="","",IF(INDEX('MiT Strom Pipeline'!$H:$H,$U90)="","",INDEX('MiT Strom Pipeline'!$H:$H,$U90))) -> Juli | F90: =IF($U90="","",IF(INDEX('MiT Strom Pipeline'!$E:$E,$U90)="","",INDEX('MiT Strom Pipeline'!$E:$E,$U90))) -> 100 kVA Generator | G90: =IF($U90="","",IF(ISNUMBER(INDEX('MiT Strom Pipeline'!$I:$I,$U90)),INDEX('MiT Strom Pipeline'!$I:$I,$U90),0)) -> 3232.41 | H90: =IF($U90="","",IF(ISNUMBER(INDEX('MiT Strom Pipeline'!$Q:$Q,$U90)),INDEX('MiT Strom Pipeline'!$Q:$Q,$U90),0)) -> 1616.205 | I90: =IF($U90="","",IF(ISNUMBER(INDEX('MiT Strom Pipeline'!$O:$O,$U90)),INDEX('MiT Strom Pipeline'!$O:$O,$U90),0)) -> 370 | J90: =IF($U90="","",INDEX('MiT Strom Pipeline'!$R:$R,$U90)) -> offered | K90: =IF($U90="","",IF(ISNUMBER(INDEX('MiT Strom Pipeline'!$S:$S,$U90)),INDEX('MiT Strom Pipeline'!$S:$S,$U90),"")) -> 0.5 | L90: =IF($U90="","",IF(LEN(INDEX('MiT Strom Pipeline'!$V:$V,$U90))>0,LEFT(INDEX('MiT Strom Pipeline'!$V:$V,$U90),55),"")) -> Kunde angeschrieben, Warten auf Rückmeldung | U90: =IFERROR(MATCH(16,'MiT Strom Pipeline'!$AC$6:$AC$860,0)+5,"") -> 40
A91: =IF($U91="","",IF(ISNUMBER(INDEX('MiT Strom Pipeline'!$A:$A,$U91)),INDEX('MiT Strom Pipeline'!$A:$A,$U91),"")) -> 38 | B91: =IF($U91="","",IF(INDEX('MiT Strom Pipeline'!$B:$B,$U91)="","",INDEX('MiT Strom Pipeline'!$B:$B,$U91))) -> Linde Gas Schweiz AG | C91: =IF($U91="","",IF(INDEX('MiT Strom Pipeline'!$C:$C,$U91)="","",INDEX('MiT Strom Pipeline'!$C:$C,$U91))) -> LU | D91: =IF($U91="","",IF(INDEX('MiT Strom Pipeline'!$D:$D,$U91)="","",INDEX('MiT Strom Pipeline'!$D:$D,$U91))) -> Industrie | E91: =IF($U91="","",IF(INDEX('MiT Strom Pipeline'!$H:$H,$U91)="","",INDEX('MiT Strom Pipeline'!$H:$H,$U91))) -> Jan | F91: =IF($U91="","",IF(INDEX('MiT Strom Pipeline'!$E:$E,$U91)="","",INDEX('MiT Strom Pipeline'!$E:$E,$U91))) -> 60 kVA Generator | G91: =IF($U91="","",IF(ISNUMBER(INDEX('MiT Strom Pipeline'!$I:$I,$U91)),INDEX('MiT Strom Pipeline'!$I:$I,$U91),0)) -> 3686.2 | H91: =IF($U91="","",IF(ISNUMBER(INDEX('MiT Strom Pipeline'!$Q:$Q,$U91)),INDEX('MiT Strom Pipeline'!$Q:$Q,$U91),0)) -> 1843.1 | I91: =IF($U91="","",IF(ISNUMBER(INDEX('MiT Strom Pipeline'!$O:$O,$U91)),INDEX('MiT Strom Pipeline'!$O:$O,$U91),0)) -> 179.99 | J91: =IF($U91="","",INDEX('MiT Strom Pipeline'!$R:$R,$U91)) -> offered | K91: =IF($U91="","",IF(ISNUMBER(INDEX('MiT Strom Pipeline'!$S:$S,$U91)),INDEX('MiT Strom Pipeline'!$S:$S,$U91),"")) -> 0.5 | L91: =IF($U91="","",IF(LEN(INDEX('MiT Strom Pipeline'!$V:$V,$U91))>0,LEFT(INDEX('MiT Strom Pipeline'!$V:$V,$U91),55),"")) | U91: =IFERROR(MATCH(17,'MiT Strom Pipeline'!$AC$6:$AC$860,0)+5,"") -> 42
A92: =IF($U92="","",IF(ISNUMBER(INDEX('MiT Strom Pipeline'!$A:$A,$U92)),INDEX('MiT Strom Pipeline'!$A:$A,$U92),"")) -> 39 | B92: =IF($U92="","",IF(INDEX('MiT Strom Pipeline'!$B:$B,$U92)="","",INDEX('MiT Strom Pipeline'!$B:$B,$U92))) -> Baumeler Leitungsbau AG | C92: =IF($U92="","",IF(INDEX('MiT Strom Pipeline'!$C:$C,$U92)="","",INDEX('MiT Strom Pipeline'!$C:$C,$U92))) -> LU | D92: =IF($U92="","",IF(INDEX('MiT Strom Pipeline'!$D:$D,$U92)="","",INDEX('MiT Strom Pipeline'!$D:$D,$U92))) -> Industrie | E92: =IF($U92="","",IF(INDEX('MiT Strom Pipeline'!$H:$H,$U92)="","",INDEX('MiT Strom Pipeline'!$H:$H,$U92))) -> Juli | F92: =IF($U92="","",IF(INDEX('MiT Strom Pipeline'!$E:$E,$U92)="","",INDEX('MiT Strom Pipeline'!$E:$E,$U92))) -> 600 kVA | G92: =IF($U92="","",IF(ISNUMBER(INDEX('MiT Strom Pipeline'!$I:$I,$U92)),INDEX('MiT Strom Pipeline'!$I:$I,$U92),0)) -> 11559.36 | H92: =IF($U92="","",IF(ISNUMBER(INDEX('MiT Strom Pipeline'!$Q:$Q,$U92)),INDEX('MiT Strom Pipeline'!$Q:$Q,$U92),0)) -> 5779.68 | I92: =IF($U92="","",IF(ISNUMBER(INDEX('MiT Strom Pipeline'!$O:$O,$U92)),INDEX('MiT Strom Pipeline'!$O:$O,$U92),0)) -> 2200.01 | J92: =IF($U92="","",INDEX('MiT Strom Pipeline'!$R:$R,$U92)) -> offered | K92: =IF($U92="","",IF(ISNUMBER(INDEX('MiT Strom Pipeline'!$S:$S,$U92)),INDEX('MiT Strom Pipeline'!$S:$S,$U92),"")) -> 0.5 | L92: =IF($U92="","",IF(LEN(INDEX('MiT Strom Pipeline'!$V:$V,$U92))>0,LEFT(INDEX('MiT Strom Pipeline'!$V:$V,$U92),55),"")) -> Kunde angeschrieben, Offerte erstellt, Kunde hat Offert | U92: =IFERROR(MATCH(18,'MiT Strom Pipeline'!$AC$6:$AC$860,0)+5,"") -> 43
A93: =IF($U93="","",IF(ISNUMBER(INDEX('MiT Strom Pipeline'!$A:$A,$U93)),INDEX('MiT Strom Pipeline'!$A:$A,$U93),"")) -> 41 | B93: =IF($U93="","",IF(INDEX('MiT Strom Pipeline'!$B:$B,$U93)="","",INDEX('MiT Strom Pipeline'!$B:$B,$U93))) -> Verein Street Parade Zürich | C93: =IF($U93="","",IF(INDEX('MiT Strom Pipeline'!$C:$C,$U93)="","",INDEX('MiT Strom Pipeline'!$C:$C,$U93))) -> ZH | D93: =IF($U93="","",IF(INDEX('MiT Strom Pipeline'!$D:$D,$U93)="","",INDEX('MiT Strom Pipeline'!$D:$D,$U93))) -> Event | E93: =IF($U93="","",IF(INDEX('MiT Strom Pipeline'!$H:$H,$U93)="","",INDEX('MiT Strom Pipeline'!$H:$H,$U93))) -> Aug | F93: =IF($U93="","",IF(INDEX('MiT Strom Pipeline'!$E:$E,$U93)="","",INDEX('MiT Strom Pipeline'!$E:$E,$U93))) -> 100 kVA | G93: =IF($U93="","",IF(ISNUMBER(INDEX('MiT Strom Pipeline'!$I:$I,$U93)),INDEX('MiT Strom Pipeline'!$I:$I,$U93),0)) -> 3760.04 | H93: =IF($U93="","",IF(ISNUMBER(INDEX('MiT Strom Pipeline'!$Q:$Q,$U93)),INDEX('MiT Strom Pipeline'!$Q:$Q,$U93),0)) -> 1880.02 | I93: =IF($U93="","",IF(ISNUMBER(INDEX('MiT Strom Pipeline'!$O:$O,$U93)),INDEX('MiT Strom Pipeline'!$O:$O,$U93),0)) -> 0 | J93: =IF($U93="","",INDEX('MiT Strom Pipeline'!$R:$R,$U93)) -> offered | K93: =IF($U93="","",IF(ISNUMBER(INDEX('MiT Strom Pipeline'!$S:$S,$U93)),INDEX('MiT Strom Pipeline'!$S:$S,$U93),"")) -> 0.5 | L93: =IF($U93="","",IF(LEN(INDEX('MiT Strom Pipeline'!$V:$V,$U93))>0,LEFT(INDEX('MiT Strom Pipeline'!$V:$V,$U93),55),"")) -> Kunde angeschrieben, Offerte erstellt, Kunde hat Offert | U93: =IFERROR(MATCH(19,'MiT Strom Pipeline'!$AC$6:$AC$860,0)+5,"") -> 44
A94: =IF($U94="","",IF(ISNUMBER(INDEX('MiT Strom Pipeline'!$A:$A,$U94)),INDEX('MiT Strom Pipeline'!$A:$A,$U94),"")) -> 9 | B94: =IF($U94="","",IF(INDEX('MiT Strom Pipeline'!$B:$B,$U94)="","",INDEX('MiT Strom Pipeline'!$B:$B,$U94))) -> Badermetaux Sàrl (Schweiz) | C94: =IF($U94="","",IF(INDEX('MiT Strom Pipeline'!$C:$C,$U94)="","",INDEX('MiT Strom Pipeline'!$C:$C,$U94))) -> ZH | D94: =IF($U94="","",IF(INDEX('MiT Strom Pipeline'!$D:$D,$U94)="","",INDEX('MiT Strom Pipeline'!$D:$D,$U94))) -> Industrie / Metall | E94: =IF($U94="","",IF(INDEX('MiT Strom Pipeline'!$H:$H,$U94)="","",INDEX('MiT Strom Pipeline'!$H:$H,$U94))) -> Mai | F94: =IF($U94="","",IF(INDEX('MiT Strom Pipeline'!$E:$E,$U94)="","",INDEX('MiT Strom Pipeline'!$E:$E,$U94))) -> 600 kVA Langzeitmiete | G94: =IF($U94="","",IF(ISNUMBER(INDEX('MiT Strom Pipeline'!$I:$I,$U94)),INDEX('MiT Strom Pipeline'!$I:$I,$U94),0)) -> 500000 | H94: =IF($U94="","",IF(ISNUMBER(INDEX('MiT Strom Pipeline'!$Q:$Q,$U94)),INDEX('MiT Strom Pipeline'!$Q:$Q,$U94),0)) -> 250000 | I94: =IF($U94="","",IF(ISNUMBER(INDEX('MiT Strom Pipeline'!$O:$O,$U94)),INDEX('MiT Strom Pipeline'!$O:$O,$U94),0)) -> 130000 | J94: =IF($U94="","",INDEX('MiT Strom Pipeline'!$R:$R,$U94)) -> on hold | K94: =IF($U94="","",IF(ISNUMBER(INDEX('MiT Strom Pipeline'!$S:$S,$U94)),INDEX('MiT Strom Pipeline'!$S:$S,$U94),"")) -> 0.5 | L94: =IF($U94="","",IF(LEN(INDEX('MiT Strom Pipeline'!$V:$V,$U94))>0,LEFT(INDEX('MiT Strom Pipeline'!$V:$V,$U94),55),"")) -> PQ-Analyse + Langzeitkonzept vorlegen | U94: =IFERROR(MATCH(20,'MiT Strom Pipeline'!$AC$6:$AC$860,0)+5,"") -> 46
A95: =IF($U95="","",IF(ISNUMBER(INDEX('MiT Strom Pipeline'!$A:$A,$U95)),INDEX('MiT Strom Pipeline'!$A:$A,$U95),"")) -> 42 | B95: =IF($U95="","",IF(INDEX('MiT Strom Pipeline'!$B:$B,$U95)="","",INDEX('MiT Strom Pipeline'!$B:$B,$U95))) -> SMT | C95: =IF($U95="","",IF(INDEX('MiT Strom Pipeline'!$C:$C,$U95)="","",INDEX('MiT Strom Pipeline'!$C:$C,$U95))) -> ZH | D95: =IF($U95="","",IF(INDEX('MiT Strom Pipeline'!$D:$D,$U95)="","",INDEX('MiT Strom Pipeline'!$D:$D,$U95))) -> Industrie | E95: =IF($U95="","",IF(INDEX('MiT Strom Pipeline'!$H:$H,$U95)="","",INDEX('MiT Strom Pipeline'!$H:$H,$U95))) -> Aug | F95: =IF($U95="","",IF(INDEX('MiT Strom Pipeline'!$E:$E,$U95)="","",INDEX('MiT Strom Pipeline'!$E:$E,$U95))) -> 1000 kVA | G95: =IF($U95="","",IF(ISNUMBER(INDEX('MiT Strom Pipeline'!$I:$I,$U95)),INDEX('MiT Strom Pipeline'!$I:$I,$U95),0)) -> 6772.8 | H95: =IF($U95="","",IF(ISNUMBER(INDEX('MiT Strom Pipeline'!$Q:$Q,$U95)),INDEX('MiT Strom Pipeline'!$Q:$Q,$U95),0)) -> 3386.4 | I95: =IF($U95="","",IF(ISNUMBER(INDEX('MiT Strom Pipeline'!$O:$O,$U95)),INDEX('MiT Strom Pipeline'!$O:$O,$U95),0)) -> 0 | J95: =IF($U95="","",INDEX('MiT Strom Pipeline'!$R:$R,$U95)) -> on hold | K95: =IF($U95="","",IF(ISNUMBER(INDEX('MiT Strom Pipeline'!$S:$S,$U95)),INDEX('MiT Strom Pipeline'!$S:$S,$U95),"")) -> 0.5 | L95: =IF($U95="","",IF(LEN(INDEX('MiT Strom Pipeline'!$V:$V,$U95))>0,LEFT(INDEX('MiT Strom Pipeline'!$V:$V,$U95),55),"")) -> Kunde angeschrieben, Offerte erstellt, Kunde hat Offert | U95: =IFERROR(MATCH(21,'MiT Strom Pipeline'!$AC$6:$AC$860,0)+5,"") -> 52
A96: =IF($U96="","",IF(ISNUMBER(INDEX('MiT Strom Pipeline'!$A:$A,$U96)),INDEX('MiT Strom Pipeline'!$A:$A,$U96),"")) -> 43 | B96: =IF($U96="","",IF(INDEX('MiT Strom Pipeline'!$B:$B,$U96)="","",INDEX('MiT Strom Pipeline'!$B:$B,$U96))) -> Equans Switzerland Kloten | C96: =IF($U96="","",IF(INDEX('MiT Strom Pipeline'!$C:$C,$U96)="","",INDEX('MiT Strom Pipeline'!$C:$C,$U96))) -> ZH | D96: =IF($U96="","",IF(INDEX('MiT Strom Pipeline'!$D:$D,$U96)="","",INDEX('MiT Strom Pipeline'!$D:$D,$U96))) -> Industrie | E96: =IF($U96="","",IF(INDEX('MiT Strom Pipeline'!$H:$H,$U96)="","",INDEX('MiT Strom Pipeline'!$H:$H,$U96))) -> Dez | F96: =IF($U96="","",IF(INDEX('MiT Strom Pipeline'!$E:$E,$U96)="","",INDEX('MiT Strom Pipeline'!$E:$E,$U96))) -> 600 kVA | G96: =IF($U96="","",IF(ISNUMBER(INDEX('MiT Strom Pipeline'!$I:$I,$U96)),INDEX('MiT Strom Pipeline'!$I:$I,$U96),0)) -> 224236.15 | H96: =IF($U96="","",IF(ISNUMBER(INDEX('MiT Strom Pipeline'!$Q:$Q,$U96)),INDEX('MiT Strom Pipeline'!$Q:$Q,$U96),0)) -> 112118.07 | I96: =IF($U96="","",IF(ISNUMBER(INDEX('MiT Strom Pipeline'!$O:$O,$U96)),INDEX('MiT Strom Pipeline'!$O:$O,$U96),0)) -> 0 | J96: =IF($U96="","",INDEX('MiT Strom Pipeline'!$R:$R,$U96)) -> offered | K96: =IF($U96="","",IF(ISNUMBER(INDEX('MiT Strom Pipeline'!$S:$S,$U96)),INDEX('MiT Strom Pipeline'!$S:$S,$U96),"")) -> 0.5 | L96: =IF($U96="","",IF(LEN(INDEX('MiT Strom Pipeline'!$V:$V,$U96))>0,LEFT(INDEX('MiT Strom Pipeline'!$V:$V,$U96),55),"")) -> Kunde angeschrieben, Offerte erstellt, Kunde hat Offert | U96: =IFERROR(MATCH(22,'MiT Strom Pipeline'!$AC$6:$AC$860,0)+5,"") -> 53
A97: =IF($U97="","",IF(ISNUMBER(INDEX('MiT Strom Pipeline'!$A:$A,$U97)),INDEX('MiT Strom Pipeline'!$A:$A,$U97),"")) -> 44 | B97: =IF($U97="","",IF(INDEX('MiT Strom Pipeline'!$B:$B,$U97)="","",INDEX('MiT Strom Pipeline'!$B:$B,$U97))) -> Equans Switzerland Kloten | C97: =IF($U97="","",IF(INDEX('MiT Strom Pipeline'!$C:$C,$U97)="","",INDEX('MiT Strom Pipeline'!$C:$C,$U97))) -> ZH | D97: =IF($U97="","",IF(INDEX('MiT Strom Pipeline'!$D:$D,$U97)="","",INDEX('MiT Strom Pipeline'!$D:$D,$U97))) -> Industrie | E97: =IF($U97="","",IF(INDEX('MiT Strom Pipeline'!$H:$H,$U97)="","",INDEX('MiT Strom Pipeline'!$H:$H,$U97))) -> Juli | F97: =IF($U97="","",IF(INDEX('MiT Strom Pipeline'!$E:$E,$U97)="","",INDEX('MiT Strom Pipeline'!$E:$E,$U97))) -> 300 kVA | G97: =IF($U97="","",IF(ISNUMBER(INDEX('MiT Strom Pipeline'!$I:$I,$U97)),INDEX('MiT Strom Pipeline'!$I:$I,$U97),0)) -> 31077.89 | H97: =IF($U97="","",IF(ISNUMBER(INDEX('MiT Strom Pipeline'!$Q:$Q,$U97)),INDEX('MiT Strom Pipeline'!$Q:$Q,$U97),0)) -> 15538.945 | I97: =IF($U97="","",IF(ISNUMBER(INDEX('MiT Strom Pipeline'!$O:$O,$U97)),INDEX('MiT Strom Pipeline'!$O:$O,$U97),0)) -> 0 | J97: =IF($U97="","",INDEX('MiT Strom Pipeline'!$R:$R,$U97)) -> offered | K97: =IF($U97="","",IF(ISNUMBER(INDEX('MiT Strom Pipeline'!$S:$S,$U97)),INDEX('MiT Strom Pipeline'!$S:$S,$U97),"")) -> 0.5 | L97: =IF($U97="","",IF(LEN(INDEX('MiT Strom Pipeline'!$V:$V,$U97))>0,LEFT(INDEX('MiT Strom Pipeline'!$V:$V,$U97),55),"")) -> Kunde angeschrieben, Offerte erstellt, Kunde hat Offert | U97: =IFERROR(MATCH(23,'MiT Strom Pipeline'!$AC$6:$AC$860,0)+5,"") -> 54
A98: =IF($U98="","",IF(ISNUMBER(INDEX('MiT Strom Pipeline'!$A:$A,$U98)),INDEX('MiT Strom Pipeline'!$A:$A,$U98),"")) -> 45 | B98: =IF($U98="","",IF(INDEX('MiT Strom Pipeline'!$B:$B,$U98)="","",INDEX('MiT Strom Pipeline'!$B:$B,$U98))) -> ETAVIS Basel | C98: =IF($U98="","",IF(INDEX('MiT Strom Pipeline'!$C:$C,$U98)="","",INDEX('MiT Strom Pipeline'!$C:$C,$U98))) -> BS | D98: =IF($U98="","",IF(INDEX('MiT Strom Pipeline'!$D:$D,$U98)="","",INDEX('MiT Strom Pipeline'!$D:$D,$U98))) -> Elektroinstallation | E98: =IF($U98="","",IF(INDEX('MiT Strom Pipeline'!$H:$H,$U98)="","",INDEX('MiT Strom Pipeline'!$H:$H,$U98))) -> Juli | F98: =IF($U98="","",IF(INDEX('MiT Strom Pipeline'!$E:$E,$U98)="","",INDEX('MiT Strom Pipeline'!$E:$E,$U98))) -> 300 kVA | G98: =IF($U98="","",IF(ISNUMBER(INDEX('MiT Strom Pipeline'!$I:$I,$U98)),INDEX('MiT Strom Pipeline'!$I:$I,$U98),0)) -> 13866.21 | H98: =IF($U98="","",IF(ISNUMBER(INDEX('MiT Strom Pipeline'!$Q:$Q,$U98)),INDEX('MiT Strom Pipeline'!$Q:$Q,$U98),0)) -> 6933.105 | I98: =IF($U98="","",IF(ISNUMBER(INDEX('MiT Strom Pipeline'!$O:$O,$U98)),INDEX('MiT Strom Pipeline'!$O:$O,$U98),0)) -> 0.01 | J98: =IF($U98="","",INDEX('MiT Strom Pipeline'!$R:$R,$U98)) -> offered | K98: =IF($U98="","",IF(ISNUMBER(INDEX('MiT Strom Pipeline'!$S:$S,$U98)),INDEX('MiT Strom Pipeline'!$S:$S,$U98),"")) -> 0.5 | L98: =IF($U98="","",IF(LEN(INDEX('MiT Strom Pipeline'!$V:$V,$U98))>0,LEFT(INDEX('MiT Strom Pipeline'!$V:$V,$U98),55),"")) -> Kunde angeschrieben, Offerte erstellt, Kunde hat Offert | U98: =IFERROR(MATCH(24,'MiT Strom Pipeline'!$AC$6:$AC$860,0)+5,"") -> 55
A99: =IF($U99="","",IF(ISNUMBER(INDEX('MiT Strom Pipeline'!$A:$A,$U99)),INDEX('MiT Strom Pipeline'!$A:$A,$U99),"")) -> 48 | B99: =IF($U99="","",IF(INDEX('MiT Strom Pipeline'!$B:$B,$U99)="","",INDEX('MiT Strom Pipeline'!$B:$B,$U99))) -> Coutaz CVS SA | C99: =IF($U99="","",IF(INDEX('MiT Strom Pipeline'!$C:$C,$U99)="","",INDEX('MiT Strom Pipeline'!$C:$C,$U99))) -> VS | D99: =IF($U99="","",IF(INDEX('MiT Strom Pipeline'!$D:$D,$U99)="","",INDEX('MiT Strom Pipeline'!$D:$D,$U99))) -> EVU | E99: =IF($U99="","",IF(INDEX('MiT Strom Pipeline'!$H:$H,$U99)="","",INDEX('MiT Strom Pipeline'!$H:$H,$U99))) -> Okt | F99: =IF($U99="","",IF(INDEX('MiT Strom Pipeline'!$E:$E,$U99)="","",INDEX('MiT Strom Pipeline'!$E:$E,$U99))) -> 600 kVA, 200 kVA | G99: =IF($U99="","",IF(ISNUMBER(INDEX('MiT Strom Pipeline'!$I:$I,$U99)),INDEX('MiT Strom Pipeline'!$I:$I,$U99),0)) -> 190701.37 | H99: =IF($U99="","",IF(ISNUMBER(INDEX('MiT Strom Pipeline'!$Q:$Q,$U99)),INDEX('MiT Strom Pipeline'!$Q:$Q,$U99),0)) -> 95350.685 | I99: =IF($U99="","",IF(ISNUMBER(INDEX('MiT Strom Pipeline'!$O:$O,$U99)),INDEX('MiT Strom Pipeline'!$O:$O,$U99),0)) -> 10854 | J99: =IF($U99="","",INDEX('MiT Strom Pipeline'!$R:$R,$U99)) -> offered | K99: =IF($U99="","",IF(ISNUMBER(INDEX('MiT Strom Pipeline'!$S:$S,$U99)),INDEX('MiT Strom Pipeline'!$S:$S,$U99),"")) -> 0.5 | L99: =IF($U99="","",IF(LEN(INDEX('MiT Strom Pipeline'!$V:$V,$U99))>0,LEFT(INDEX('MiT Strom Pipeline'!$V:$V,$U99),55),"")) -> Kunde angeschrieben, Offerte erstellt, Kunde hat Offert | U99: =IFERROR(MATCH(25,'MiT Strom Pipeline'!$AC$6:$AC$860,0)+5,"") -> 58
A100: =IF($U100="","",IF(ISNUMBER(INDEX('MiT Strom Pipeline'!$A:$A,$U100)),INDEX('MiT Strom Pipeline'!$A:$A,$U100),"")) -> 49 | B100: =IF($U100="","",IF(INDEX('MiT Strom Pipeline'!$B:$B,$U100)="","",INDEX('MiT Strom Pipeline'!$B:$B,$U100))) -> Romand Energei SA | C100: =IF($U100="","",IF(INDEX('MiT Strom Pipeline'!$C:$C,$U100)="","",INDEX('MiT Strom Pipeline'!$C:$C,$U100))) -> VS | D100: =IF($U100="","",IF(INDEX('MiT Strom Pipeline'!$D:$D,$U100)="","",INDEX('MiT Strom Pipeline'!$D:$D,$U100))) -> EVU | E100: =IF($U100="","",IF(INDEX('MiT Strom Pipeline'!$H:$H,$U100)="","",INDEX('MiT Strom Pipeline'!$H:$H,$U100))) -> Aug | F100: =IF($U100="","",IF(INDEX('MiT Strom Pipeline'!$E:$E,$U100)="","",INDEX('MiT Strom Pipeline'!$E:$E,$U100))) -> 600 kVA | G100: =IF($U100="","",IF(ISNUMBER(INDEX('MiT Strom Pipeline'!$I:$I,$U100)),INDEX('MiT Strom Pipeline'!$I:$I,$U100),0)) -> 32467.62 | H100: =IF($U100="","",IF(ISNUMBER(INDEX('MiT Strom Pipeline'!$Q:$Q,$U100)),INDEX('MiT Strom Pipeline'!$Q:$Q,$U100),0)) -> 16233.81 | I100: =IF($U100="","",IF(ISNUMBER(INDEX('MiT Strom Pipeline'!$O:$O,$U100)),INDEX('MiT Strom Pipeline'!$O:$O,$U100),0)) -> 871 | J100: =IF($U100="","",INDEX('MiT Strom Pipeline'!$R:$R,$U100)) -> offered | K100: =IF($U100="","",IF(ISNUMBER(INDEX('MiT Strom Pipeline'!$S:$S,$U100)),INDEX('MiT Strom Pipeline'!$S:$S,$U100),"")) -> 0.5 | L100: =IF($U100="","",IF(LEN(INDEX('MiT Strom Pipeline'!$V:$V,$U100))>0,LEFT(INDEX('MiT Strom Pipeline'!$V:$V,$U100),55),"")) -> Kunde angeschrieben, Offerte erstellt, Kunde hat Offert | U100: =IFERROR(MATCH(26,'MiT Strom Pipeline'!$AC$6:$AC$860,0)+5,"") -> 59
A101: =IF($U101="","",IF(ISNUMBER(INDEX('MiT Strom Pipeline'!$A:$A,$U101)),INDEX('MiT Strom Pipeline'!$A:$A,$U101),"")) -> 54 | B101: =IF($U101="","",IF(INDEX('MiT Strom Pipeline'!$B:$B,$U101)="","",INDEX('MiT Strom Pipeline'!$B:$B,$U101))) -> Wyss Sound | C101: =IF($U101="","",IF(INDEX('MiT Strom Pipeline'!$C:$C,$U101)="","",INDEX('MiT Strom Pipeline'!$C:$C,$U101))) -> LU | D101: =IF($U101="","",IF(INDEX('MiT Strom Pipeline'!$D:$D,$U101)="","",INDEX('MiT Strom Pipeline'!$D:$D,$U101))) -> Event | E101: =IF($U101="","",IF(INDEX('MiT Strom Pipeline'!$H:$H,$U101)="","",INDEX('MiT Strom Pipeline'!$H:$H,$U101))) -> Juli | F101: =IF($U101="","",IF(INDEX('MiT Strom Pipeline'!$E:$E,$U101)="","",INDEX('MiT Strom Pipeline'!$E:$E,$U101))) -> 300 kVA | G101: =IF($U101="","",IF(ISNUMBER(INDEX('MiT Strom Pipeline'!$I:$I,$U101)),INDEX('MiT Strom Pipeline'!$I:$I,$U101),0)) -> 8381.21 | H101: =IF($U101="","",IF(ISNUMBER(INDEX('MiT Strom Pipeline'!$Q:$Q,$U101)),INDEX('MiT Strom Pipeline'!$Q:$Q,$U101),0)) -> 4190.605 | I101: =IF($U101="","",IF(ISNUMBER(INDEX('MiT Strom Pipeline'!$O:$O,$U101)),INDEX('MiT Strom Pipeline'!$O:$O,$U101),0)) -> 0 | J101: =IF($U101="","",INDEX('MiT Strom Pipeline'!$R:$R,$U101)) -> offered | K101: =IF($U101="","",IF(ISNUMBER(INDEX('MiT Strom Pipeline'!$S:$S,$U101)),INDEX('MiT Strom Pipeline'!$S:$S,$U101),"")) -> 0.5 | L101: =IF($U101="","",IF(LEN(INDEX('MiT Strom Pipeline'!$V:$V,$U101))>0,LEFT(INDEX('MiT Strom Pipeline'!$V:$V,$U101),55),"")) -> Kunde angeschrieben, Offerte erstellt, Kunde hat Offert | U101: =IFERROR(MATCH(27,'MiT Strom Pipeline'!$AC$6:$AC$860,0)+5,"") -> 64
A102: =IF($U102="","",IF(ISNUMBER(INDEX('MiT Strom Pipeline'!$A:$A,$U102)),INDEX('MiT Strom Pipeline'!$A:$A,$U102),"")) -> 55 | B102: =IF($U102="","",IF(INDEX('MiT Strom Pipeline'!$B:$B,$U102)="","",INDEX('MiT Strom Pipeline'!$B:$B,$U102))) -> Schmidiger + Rosasco AG | C102: =IF($U102="","",IF(INDEX('MiT Strom Pipeline'!$C:$C,$U102)="","",INDEX('MiT Strom Pipeline'!$C:$C,$U102))) -> ZH | D102: =IF($U102="","",IF(INDEX('MiT Strom Pipeline'!$D:$D,$U102)="","",INDEX('MiT Strom Pipeline'!$D:$D,$U102))) -> Elektroplaner | E102: =IF($U102="","",IF(INDEX('MiT Strom Pipeline'!$H:$H,$U102)="","",INDEX('MiT Strom Pipeline'!$H:$H,$U102))) -> Juli | F102: =IF($U102="","",IF(INDEX('MiT Strom Pipeline'!$E:$E,$U102)="","",INDEX('MiT Strom Pipeline'!$E:$E,$U102))) -> 200 kVA | G102: =IF($U102="","",IF(ISNUMBER(INDEX('MiT Strom Pipeline'!$I:$I,$U102)),INDEX('MiT Strom Pipeline'!$I:$I,$U102),0)) -> 6227.21 | H102: =IF($U102="","",IF(ISNUMBER(INDEX('MiT Strom Pipeline'!$Q:$Q,$U102)),INDEX('MiT Strom Pipeline'!$Q:$Q,$U102),0)) -> 3113.605 | I102: =IF($U102="","",IF(ISNUMBER(INDEX('MiT Strom Pipeline'!$O:$O,$U102)),INDEX('MiT Strom Pipeline'!$O:$O,$U102),0)) -> 0 | J102: =IF($U102="","",INDEX('MiT Strom Pipeline'!$R:$R,$U102)) -> offered | K102: =IF($U102="","",IF(ISNUMBER(INDEX('MiT Strom Pipeline'!$S:$S,$U102)),INDEX('MiT Strom Pipeline'!$S:$S,$U102),"")) -> 0.5 | L102: =IF($U102="","",IF(LEN(INDEX('MiT Strom Pipeline'!$V:$V,$U102))>0,LEFT(INDEX('MiT Strom Pipeline'!$V:$V,$U102),55),"")) -> Kunde angeschrieben, Offerte erstellt, Kunde hat Offert | U102: =IFERROR(MATCH(28,'MiT Strom Pipeline'!$AC$6:$AC$860,0)+5,"") -> 65
A103: =IF($U103="","",IF(ISNUMBER(INDEX('MiT Strom Pipeline'!$A:$A,$U103)),INDEX('MiT Strom Pipeline'!$A:$A,$U103),"")) -> 56 | B103: =IF($U103="","",IF(INDEX('MiT Strom Pipeline'!$B:$B,$U103)="","",INDEX('MiT Strom Pipeline'!$B:$B,$U103))) -> Winkler Livecom AG | C103: =IF($U103="","",IF(INDEX('MiT Strom Pipeline'!$C:$C,$U103)="","",INDEX('MiT Strom Pipeline'!$C:$C,$U103))) -> AG | D103: =IF($U103="","",IF(INDEX('MiT Strom Pipeline'!$D:$D,$U103)="","",INDEX('MiT Strom Pipeline'!$D:$D,$U103))) -> Event | E103: =IF($U103="","",IF(INDEX('MiT Strom Pipeline'!$H:$H,$U103)="","",INDEX('MiT Strom Pipeline'!$H:$H,$U103))) -> Nov | F103: =IF($U103="","",IF(INDEX('MiT Strom Pipeline'!$E:$E,$U103)="","",INDEX('MiT Strom Pipeline'!$E:$E,$U103))) -> 300 kVA, 300 kWh | G103: =IF($U103="","",IF(ISNUMBER(INDEX('MiT Strom Pipeline'!$I:$I,$U103)),INDEX('MiT Strom Pipeline'!$I:$I,$U103),0)) -> 41209 | H103: =IF($U103="","",IF(ISNUMBER(INDEX('MiT Strom Pipeline'!$Q:$Q,$U103)),INDEX('MiT Strom Pipeline'!$Q:$Q,$U103),0)) -> 20604.5 | I103: =IF($U103="","",IF(ISNUMBER(INDEX('MiT Strom Pipeline'!$O:$O,$U103)),INDEX('MiT Strom Pipeline'!$O:$O,$U103),0)) -> 2361.18 | J103: =IF($U103="","",INDEX('MiT Strom Pipeline'!$R:$R,$U103)) -> offered | K103: =IF($U103="","",IF(ISNUMBER(INDEX('MiT Strom Pipeline'!$S:$S,$U103)),INDEX('MiT Strom Pipeline'!$S:$S,$U103),"")) -> 0.5 | L103: =IF($U103="","",IF(LEN(INDEX('MiT Strom Pipeline'!$V:$V,$U103))>0,LEFT(INDEX('MiT Strom Pipeline'!$V:$V,$U103),55),"")) -> Kunde angeschrieben, Offerte erstellt, Kunde hat Offert | U103: =IFERROR(MATCH(29,'MiT Strom Pipeline'!$AC$6:$AC$860,0)+5,"") -> 66
...

Sheet Dashboard
A1: ="⚡ MiT Strom Schweiz | Sales Dashboard | "&TEXT(TODAY(),"MMMM YYYY") -> ⚡ MiT Strom Schweiz | Sales Dashboard | August YYYY
A2: Mobil in Time AG · An Aggreko Company · Burak Ücöz · Neue Einträge in «MiT Strom Pipeline» erscheinen automatisch.
A5: ✅ WON | D5: 📄 OFFERTE | G5: 🎯 OPP. | I5: 📊 GESAMT
A6: =SUMIFS('MiT Strom Pipeline'!I$6:I$860,'MiT Strom Pipeline'!R$6:R$860,"WON") -> 1428553.1 | D6: =SUMIFS('MiT Strom Pipeline'!I$6:I$860,'MiT Strom Pipeline'!R$6:R$860,"offered")+SUMIFS('MiT Strom Pipeline'!I$6:I$860,'MiT Strom Pipeline'!R$6:R$860,"to be offered")+SUMIFS('MiT Strom Pipeline'!I$6:I$860,'MiT Strom Pipeline'!R$6:R$860,"on hold") -> 5433596.1 | G6: =SUMIFS('MiT Strom Pipeline'!I$6:I$860,'MiT Strom Pipeline'!R$6:R$860,"follow-up")+SUMIFS('MiT Strom Pipeline'!I$6:I$860,'MiT Strom Pipeline'!R$6:R$860,"Evaluation")+SUMIFS('MiT Strom Pipeline'!I$6:I$860,'MiT Strom Pipeline'!R$6:R$860,"tbd")+SUMIFS('MiT Strom Pipeline'!I$6:I$860,'MiT Strom Pipeline'!R$6:R$860,"In evaluation") -> 0 | I6: =SUMIFS('MiT Strom Pipeline'!I$6:I$860,'MiT Strom Pipeline'!R$6:R$860,"WON")+SUMIFS('MiT Strom Pipeline'!I$6:I$860,'MiT Strom Pipeline'!R$6:R$860,"offered")+SUMIFS('MiT Strom Pipeline'!I$6:I$860,'MiT Strom Pipeline'!R$6:R$860,"to be offered")+SUMIFS('MiT Strom Pipeline'!I$6:I$860,'MiT Strom Pipeline'!R$6:R$860,"on hold")+SUMIFS('MiT Strom Pipeline'!I$6:I$860,'MiT Strom Pipeline'!R$6:R$860,"follow-up")+SUMIFS('MiT Strom Pipeline'!I$6:I$860,'MiT Strom Pipeline'!R$6:R$860,"Evaluation")+SUMIFS('MiT Strom Pipeline'!I$6:I$860,'MiT Strom Pipeline'!R$6:R$860,"tbd")+SUMIFS('MiT Strom Pipeline'!I$6:I$860,'MiT Strom Pipeline'!R$6:R$860,"In evaluation") -> 6862149.2
A7: =COUNTIF('MiT Strom Pipeline'!R$6:R$860,"WON") -> 12 | D7: =COUNTIF('MiT Strom Pipeline'!R$6:R$860,"offered")+COUNTIF('MiT Strom Pipeline'!R$6:R$860,"to be offered")+COUNTIF('MiT Strom Pipeline'!R$6:R$860,"on hold") -> 33 | G7: =COUNTIF('MiT Strom Pipeline'!R$6:R$860,"follow-up")+COUNTIF('MiT Strom Pipeline'!R$6:R$860,"Evaluation")+COUNTIF('MiT Strom Pipeline'!R$6:R$860,"tbd")+COUNTIF('MiT Strom Pipeline'!R$6:R$860,"In evaluation") -> 1 | I7: =COUNTIF('MiT Strom Pipeline'!R$6:R$860,"WON")+COUNTIF('MiT Strom Pipeline'!R$6:R$860,"offered")+COUNTIF('MiT Strom Pipeline'!R$6:R$860,"to be offered")+COUNTIF('MiT Strom Pipeline'!R$6:R$860,"on hold")+COUNTIF('MiT Strom Pipeline'!R$6:R$860,"follow-up")+COUNTIF('MiT Strom Pipeline'!R$6:R$860,"Evaluation")+COUNTIF('MiT Strom Pipeline'!R$6:R$860,"tbd")+COUNTIF('MiT Strom Pipeline'!R$6:R$860,"In evaluation") -> 46
A9: ✅ 1. AUFTRAGSEINGANG (WON) — Gewonnene Aufträge
A10: # | B10: Kunde / Unternehmen | C10: Kt. | D10: Segment | E10: Start | F10: Leistung / Fleet | G10: Volumen CHF | H10: Gew.Wert CHF | I10: Status | J10: Wahr.% | K10: Nächster Schritt
A11: =IF($U11="","",IF(ISNUMBER(INDEX('MiT Strom Pipeline'!$A:$A,$U11)),INDEX('MiT Strom Pipeline'!$A:$A,$U11),"")) -> 1 | B11: =IF($U11="","",IF(INDEX('MiT Strom Pipeline'!$B:$B,$U11)="","",INDEX('MiT Strom Pipeline'!$B:$B,$U11))) -> Ice Hockey Championship | C11: =IF($U11="","",IF(INDEX('MiT Strom Pipeline'!$C:$C,$U11)="","",INDEX('MiT Strom Pipeline'!$C:$C,$U11))) -> ZH | D11: =IF($U11="","",IF(INDEX('MiT Strom Pipeline'!$D:$D,$U11)="","",INDEX('MiT Strom Pipeline'!$D:$D,$U11))) -> Events & Sport | E11: =IF($U11="","",IF(INDEX('MiT Strom Pipeline'!$H:$H,$U11)="","",INDEX('MiT Strom Pipeline'!$H:$H,$U11))) -> Mai | F11: =IF($U11="","",IF(INDEX('MiT Strom Pipeline'!$E:$E,$U11)="","",INDEX('MiT Strom Pipeline'!$E:$E,$U11))) -> 2×600+2×200 kVA | G11: =IF($U11="","",IF(ISNUMBER(INDEX('MiT Strom Pipeline'!$I:$I,$U11)),INDEX('MiT Strom Pipeline'!$I:$I,$U11),0)) -> 380000 | H11: =IF($U11="","",IF(ISNUMBER(INDEX('MiT Strom Pipeline'!$Q:$Q,$U11)),INDEX('MiT Strom Pipeline'!$Q:$Q,$U11),0)) -> 380000 | I11: =IF($U11="","",INDEX('MiT Strom Pipeline'!$R:$R,$U11)) -> WON | J11: =IF($U11="","",IF(ISNUMBER(INDEX('MiT Strom Pipeline'!$S:$S,$U11)),INDEX('MiT Strom Pipeline'!$S:$S,$U11),"")) -> 1 | K11: =IF($U11="","",IF(LEN(INDEX('MiT Strom Pipeline'!$V:$V,$U11))>0,LEFT(INDEX('MiT Strom Pipeline'!$V:$V,$U11),55),"")) -> Abgeschlossen | U11: =IFERROR(MATCH(1,'MiT Strom Pipeline'!$AB$6:$AB$860,0)+5,"") -> 9
A12: =IF($U12="","",IF(ISNUMBER(INDEX('MiT Strom Pipeline'!$A:$A,$U12)),INDEX('MiT Strom Pipeline'!$A:$A,$U12),"")) -> 2 | B12: =IF($U12="","",IF(INDEX('MiT Strom Pipeline'!$B:$B,$U12)="","",INDEX('MiT Strom Pipeline'!$B:$B,$U12))) -> Oerlikon Metco Wohlen | C12: =IF($U12="","",IF(INDEX('MiT Strom Pipeline'!$C:$C,$U12)="","",INDEX('MiT Strom Pipeline'!$C:$C,$U12))) -> AG | D12: =IF($U12="","",IF(INDEX('MiT Strom Pipeline'!$D:$D,$U12)="","",INDEX('MiT Strom Pipeline'!$D:$D,$U12))) -> Industrie / Oberfläche | E12: =IF($U12="","",IF(INDEX('MiT Strom Pipeline'!$H:$H,$U12)="","",INDEX('MiT Strom Pipeline'!$H:$H,$U12))) -> April | F12: =IF($U12="","",IF(INDEX('MiT Strom Pipeline'!$E:$E,$U12)="","",INDEX('MiT Strom Pipeline'!$E:$E,$U12))) -> 240 kVA Generator | G12: =IF($U12="","",IF(ISNUMBER(INDEX('MiT Strom Pipeline'!$I:$I,$U12)),INDEX('MiT Strom Pipeline'!$I:$I,$U12),0)) -> 13100 | H12: =IF($U12="","",IF(ISNUMBER(INDEX('MiT Strom Pipeline'!$Q:$Q,$U12)),INDEX('MiT Strom Pipeline'!$Q:$Q,$U12),0)) -> 13100 | I12: =IF($U12="","",INDEX('MiT Strom Pipeline'!$R:$R,$U12)) -> WON | J12: =IF($U12="","",IF(ISNUMBER(INDEX('MiT Strom Pipeline'!$S:$S,$U12)),INDEX('MiT Strom Pipeline'!$S:$S,$U12),"")) -> 1 | K12: =IF($U12="","",IF(LEN(INDEX('MiT Strom Pipeline'!$V:$V,$U12))>0,LEFT(INDEX('MiT Strom Pipeline'!$V:$V,$U12),55),"")) -> Abgeschlossen | U12: =IFERROR(MATCH(2,'MiT Strom Pipeline'!$AB$6:$AB$860,0)+5,"") -> 10
A13: =IF($U13="","",IF(ISNUMBER(INDEX('MiT Strom Pipeline'!$A:$A,$U13)),INDEX('MiT Strom Pipeline'!$A:$A,$U13),"")) -> 3 | B13: =IF($U13="","",IF(INDEX('MiT Strom Pipeline'!$B:$B,$U13)="","",INDEX('MiT Strom Pipeline'!$B:$B,$U13))) -> Siemens | C13: =IF($U13="","",IF(INDEX('MiT Strom Pipeline'!$C:$C,$U13)="","",INDEX('MiT Strom Pipeline'!$C:$C,$U13))) -> ZH | D13: =IF($U13="","",IF(INDEX('MiT Strom Pipeline'!$D:$D,$U13)="","",INDEX('MiT Strom Pipeline'!$D:$D,$U13))) -> Industrie / Elektro | E13: =IF($U13="","",IF(INDEX('MiT Strom Pipeline'!$H:$H,$U13)="","",INDEX('MiT Strom Pipeline'!$H:$H,$U13))) -> tbd | F13: =IF($U13="","",IF(INDEX('MiT Strom Pipeline'!$E:$E,$U13)="","",INDEX('MiT Strom Pipeline'!$E:$E,$U13))) -> 600 kVA Generator | G13: =IF($U13="","",IF(ISNUMBER(INDEX('MiT Strom Pipeline'!$I:$I,$U13)),INDEX('MiT Strom Pipeline'!$I:$I,$U13),0)) -> 10000 | H13: =IF($U13="","",IF(ISNUMBER(INDEX('MiT Strom Pipeline'!$Q:$Q,$U13)),INDEX('MiT Strom Pipeline'!$Q:$Q,$U13),0)) -> 10000 | I13: =IF($U13="","",INDEX('MiT Strom Pipeline'!$R:$R,$U13)) -> WON | J13: =IF($U13="","",IF(ISNUMBER(INDEX('MiT Strom Pipeline'!$S:$S,$U13)),INDEX('MiT Strom Pipeline'!$S:$S,$U13),"")) -> 1 | K13: =IF($U13="","",IF(LEN(INDEX('MiT Strom Pipeline'!$V:$V,$U13))>0,LEFT(INDEX('MiT Strom Pipeline'!$V:$V,$U13),55),"")) -> Abgeschlossen | U13: =IFERROR(MATCH(3,'MiT Strom Pipeline'!$AB$6:$AB$860,0)+5,"") -> 12
A14: =IF($U14="","",IF(ISNUMBER(INDEX('MiT Strom Pipeline'!$A:$A,$U14)),INDEX('MiT Strom Pipeline'!$A:$A,$U14),"")) -> 4 | B14: =IF($U14="","",IF(INDEX('MiT Strom Pipeline'!$B:$B,$U14)="","",INDEX('MiT Strom Pipeline'!$B:$B,$U14))) -> Stagelight – OpenAir Frauenfeld | C14: =IF($U14="","",IF(INDEX('MiT Strom Pipeline'!$C:$C,$U14)="","",INDEX('MiT Strom Pipeline'!$C:$C,$U14))) -> TG | D14: =IF($U14="","",IF(INDEX('MiT Strom Pipeline'!$D:$D,$U14)="","",INDEX('MiT Strom Pipeline'!$D:$D,$U14))) -> Events & Kultur | E14: =IF($U14="","",IF(INDEX('MiT Strom Pipeline'!$H:$H,$U14)="","",INDEX('MiT Strom Pipeline'!$H:$H,$U14))) -> Juli | F14: =IF($U14="","",IF(INDEX('MiT Strom Pipeline'!$E:$E,$U14)="","",INDEX('MiT Strom Pipeline'!$E:$E,$U14))) -> ~500 kVA Generator | G14: =IF($U14="","",IF(ISNUMBER(INDEX('MiT Strom Pipeline'!$I:$I,$U14)),INDEX('MiT Strom Pipeline'!$I:$I,$U14),0)) -> 150000 | H14: =IF($U14="","",IF(ISNUMBER(INDEX('MiT Strom Pipeline'!$Q:$Q,$U14)),INDEX('MiT Strom Pipeline'!$Q:$Q,$U14),0)) -> 0 | I14: =IF($U14="","",INDEX('MiT Strom Pipeline'!$R:$R,$U14)) -> WON | J14: =IF($U14="","",IF(ISNUMBER(INDEX('MiT Strom Pipeline'!$S:$S,$U14)),INDEX('MiT Strom Pipeline'!$S:$S,$U14),"")) -> 1 | K14: =IF($U14="","",IF(LEN(INDEX('MiT Strom Pipeline'!$V:$V,$U14))>0,LEFT(INDEX('MiT Strom Pipeline'!$V:$V,$U14),55),"")) -> Abgeschlossen | U14: =IFERROR(MATCH(4,'MiT Strom Pipeline'!$AB$6:$AB$860,0)+5,"") -> 13
A15: =IF($U15="","",IF(ISNUMBER(INDEX('MiT Strom Pipeline'!$A:$A,$U15)),INDEX('MiT Strom Pipeline'!$A:$A,$U15),"")) -> 10 | B15: =IF($U15="","",IF(INDEX('MiT Strom Pipeline'!$B:$B,$U15)="","",INDEX('MiT Strom Pipeline'!$B:$B,$U15))) -> Murg Flums Energie | C15: =IF($U15="","",IF(INDEX('MiT Strom Pipeline'!$C:$C,$U15)="","",INDEX('MiT Strom Pipeline'!$C:$C,$U15))) -> SG | D15: =IF($U15="","",IF(INDEX('MiT Strom Pipeline'!$D:$D,$U15)="","",INDEX('MiT Strom Pipeline'!$D:$D,$U15))) -> EVU / Energie | E15: =IF($U15="","",IF(INDEX('MiT Strom Pipeline'!$H:$H,$U15)="","",INDEX('MiT Strom Pipeline'!$H:$H,$U15))) -> Auf Abruf | F15: =IF($U15="","",IF(INDEX('MiT Strom Pipeline'!$E:$E,$U15)="","",INDEX('MiT Strom Pipeline'!$E:$E,$U15))) -> 250 kVA Generator | G15: =IF($U15="","",IF(ISNUMBER(INDEX('MiT Strom Pipeline'!$I:$I,$U15)),INDEX('MiT Strom Pipeline'!$I:$I,$U15),0)) -> 96658.69 | H15: =IF($U15="","",IF(ISNUMBER(INDEX('MiT Strom Pipeline'!$Q:$Q,$U15)),INDEX('MiT Strom Pipeline'!$Q:$Q,$U15),0)) -> 96658.69 | I15: =IF($U15="","",INDEX('MiT Strom Pipeline'!$R:$R,$U15)) -> WON | J15: =IF($U15="","",IF(ISNUMBER(INDEX('MiT Strom Pipeline'!$S:$S,$U15)),INDEX('MiT Strom Pipeline'!$S:$S,$U15),"")) -> 1 | K15: =IF($U15="","",IF(LEN(INDEX('MiT Strom Pipeline'!$V:$V,$U15))>0,LEFT(INDEX('MiT Strom Pipeline'!$V:$V,$U15),55),"")) -> Abrufbereitschaft | U15: =IFERROR(MATCH(5,'MiT Strom Pipeline'!$AB$6:$AB$860,0)+5,"") -> 14
A16: =IF($U16="","",IF(ISNUMBER(INDEX('MiT Strom Pipeline'!$A:$A,$U16)),INDEX('MiT Strom Pipeline'!$A:$A,$U16),"")) -> 21 | B16: =IF($U16="","",IF(INDEX('MiT Strom Pipeline'!$B:$B,$U16)="","",INDEX('MiT Strom Pipeline'!$B:$B,$U16))) -> X-Event | C16: =IF($U16="","",IF(INDEX('MiT Strom Pipeline'!$C:$C,$U16)="","",INDEX('MiT Strom Pipeline'!$C:$C,$U16))) -> SH | D16: =IF($U16="","",IF(INDEX('MiT Strom Pipeline'!$D:$D,$U16)="","",INDEX('MiT Strom Pipeline'!$D:$D,$U16))) -> Events / Medien | E16: =IF($U16="","",IF(INDEX('MiT Strom Pipeline'!$H:$H,$U16)="","",INDEX('MiT Strom Pipeline'!$H:$H,$U16))) -> Juni | F16: =IF($U16="","",IF(INDEX('MiT Strom Pipeline'!$E:$E,$U16)="","",INDEX('MiT Strom Pipeline'!$E:$E,$U16))) -> 100 kVA Generator | G16: =IF($U16="","",IF(ISNUMBER(INDEX('MiT Strom Pipeline'!$I:$I,$U16)),INDEX('MiT Strom Pipeline'!$I:$I,$U16),0)) -> 0 | H16: =IF($U16="","",IF(ISNUMBER(INDEX('MiT Strom Pipeline'!$Q:$Q,$U16)),INDEX('MiT Strom Pipeline'!$Q:$Q,$U16),0)) -> 0 | I16: =IF($U16="","",INDEX('MiT Strom Pipeline'!$R:$R,$U16)) -> WON | J16: =IF($U16="","",IF(ISNUMBER(INDEX('MiT Strom Pipeline'!$S:$S,$U16)),INDEX('MiT Strom Pipeline'!$S:$S,$U16),"")) -> 1 | K16: =IF($U16="","",IF(LEN(INDEX('MiT Strom Pipeline'!$V:$V,$U16))>0,LEFT(INDEX('MiT Strom Pipeline'!$V:$V,$U16),55),"")) -> Abgeschlossen | U16: =IFERROR(MATCH(6,'MiT Strom Pipeline'!$AB$6:$AB$860,0)+5,"") -> 15
A17: =IF($U17="","",IF(ISNUMBER(INDEX('MiT Strom Pipeline'!$A:$A,$U17)),INDEX('MiT Strom Pipeline'!$A:$A,$U17),"")) -> 29 | B17: =IF($U17="","",IF(INDEX('MiT Strom Pipeline'!$B:$B,$U17)="","",INDEX('MiT Strom Pipeline'!$B:$B,$U17))) -> Gampeln | C17: =IF($U17="","",IF(INDEX('MiT Strom Pipeline'!$C:$C,$U17)="","",INDEX('MiT Strom Pipeline'!$C:$C,$U17))) -> VS | D17: =IF($U17="","",IF(INDEX('MiT Strom Pipeline'!$D:$D,$U17)="","",INDEX('MiT Strom Pipeline'!$D:$D,$U17))) -> Event | E17: =IF($U17="","",IF(INDEX('MiT Strom Pipeline'!$H:$H,$U17)="","",INDEX('MiT Strom Pipeline'!$H:$H,$U17))) -> Aug | F17: =IF($U17="","",IF(INDEX('MiT Strom Pipeline'!$E:$E,$U17)="","",INDEX('MiT Strom Pipeline'!$E:$E,$U17))) -> 6x300 kVA, 9x200 kVA Generator ,1x150 kWH BESS | G17: =IF($U17="","",IF(ISNUMBER(INDEX('MiT Strom Pipeline'!$I:$I,$U17)),INDEX('MiT Strom Pipeline'!$I:$I,$U17),0)) -> 80621.21 | H17: =IF($U17="","",IF(ISNUMBER(INDEX('MiT Strom Pipeline'!$Q:$Q,$U17)),INDEX('MiT Strom Pipeline'!$Q:$Q,$U17),0)) -> 80621.21 | I17: =IF($U17="","",INDEX('MiT Strom Pipeline'!$R:$R,$U17)) -> WON | J17: =IF($U17="","",IF(ISNUMBER(INDEX('MiT Strom Pipeline'!$S:$S,$U17)),INDEX('MiT Strom Pipeline'!$S:$S,$U17),"")) -> 1 | K17: =IF($U17="","",IF(LEN(INDEX('MiT Strom Pipeline'!$V:$V,$U17))>0,LEFT(INDEX('MiT Strom Pipeline'!$V:$V,$U17),55),"")) -> Abgeschlossen | U17: =IFERROR(MATCH(7,'MiT Strom Pipeline'!$AB$6:$AB$860,0)+5,"") -> 22
A18: =IF($U18="","",IF(ISNUMBER(INDEX('MiT Strom Pipeline'!$A:$A,$U18)),INDEX('MiT Strom Pipeline'!$A:$A,$U18),"")) -> 50 | B18: =IF($U18="","",IF(INDEX('MiT Strom Pipeline'!$B:$B,$U18)="","",INDEX('MiT Strom Pipeline'!$B:$B,$U18))) -> EIDG AMT Agroscope | C18: =IF($U18="","",IF(INDEX('MiT Strom Pipeline'!$C:$C,$U18)="","",INDEX('MiT Strom Pipeline'!$C:$C,$U18))) -> ZH | D18: =IF($U18="","",IF(INDEX('MiT Strom Pipeline'!$D:$D,$U18)="","",INDEX('MiT Strom Pipeline'!$D:$D,$U18))) -> Forschung | E18: =IF($U18="","",IF(INDEX('MiT Strom Pipeline'!$H:$H,$U18)="","",INDEX('MiT Strom Pipeline'!$H:$H,$U18))) -> Aug | F18: =IF($U18="","",IF(INDEX('MiT Strom Pipeline'!$E:$E,$U18)="","",INDEX('MiT Strom Pipeline'!$E:$E,$U18))) -> 450 kVA | G18: =IF($U18="","",IF(ISNUMBER(INDEX('MiT Strom Pipeline'!$I:$I,$U18)),INDEX('MiT Strom Pipeline'!$I:$I,$U18),0)) -> 13533 | H18: =IF($U18="","",IF(ISNUMBER(INDEX('MiT Strom Pipeline'!$Q:$Q,$U18)),INDEX('MiT Strom Pipeline'!$Q:$Q,$U18),0)) -> 13533 | I18: =IF($U18="","",INDEX('MiT Strom Pipeline'!$R:$R,$U18)) -> WON | J18: =IF($U18="","",IF(ISNUMBER(INDEX('MiT Strom Pipeline'!$S:$S,$U18)),INDEX('MiT Strom Pipeline'!$S:$S,$U18),"")) -> 1 | K18: =IF($U18="","",IF(LEN(INDEX('MiT Strom Pipeline'!$V:$V,$U18))>0,LEFT(INDEX('MiT Strom Pipeline'!$V:$V,$U18),55),"")) -> Abgeschlossen | U18: =IFERROR(MATCH(8,'MiT Strom Pipeline'!$AB$6:$AB$860,0)+5,"") -> 60
A19: =IF($U19="","",IF(ISNUMBER(INDEX('MiT Strom Pipeline'!$A:$A,$U19)),INDEX('MiT Strom Pipeline'!$A:$A,$U19),"")) -> 51 | B19: =IF($U19="","",IF(INDEX('MiT Strom Pipeline'!$B:$B,$U19)="","",INDEX('MiT Strom Pipeline'!$B:$B,$U19))) -> (Megger) Power Diagnostix Service GmbH | C19: =IF($U19="","",IF(INDEX('MiT Strom Pipeline'!$C:$C,$U19)="","",INDEX('MiT Strom Pipeline'!$C:$C,$U19))) -> TG | D19: =IF($U19="","",IF(INDEX('MiT Strom Pipeline'!$D:$D,$U19)="","",INDEX('MiT Strom Pipeline'!$D:$D,$U19))) -> EVU | E19: =IF($U19="","",IF(INDEX('MiT Strom Pipeline'!$H:$H,$U19)="","",INDEX('MiT Strom Pipeline'!$H:$H,$U19))) -> Juli | F19: =IF($U19="","",IF(INDEX('MiT Strom Pipeline'!$E:$E,$U19)="","",INDEX('MiT Strom Pipeline'!$E:$E,$U19))) -> 600 kVA | G19: =IF($U19="","",IF(ISNUMBER(INDEX('MiT Strom Pipeline'!$I:$I,$U19)),INDEX('MiT Strom Pipeline'!$I:$I,$U19),0)) -> 5488.9 | H19: =IF($U19="","",IF(ISNUMBER(INDEX('MiT Strom Pipeline'!$Q:$Q,$U19)),INDEX('MiT Strom Pipeline'!$Q:$Q,$U19),0)) -> 5488.9 | I19: =IF($U19="","",INDEX('MiT Strom Pipeline'!$R:$R,$U19)) -> WON | J19: =IF($U19="","",IF(ISNUMBER(INDEX('MiT Strom Pipeline'!$S:$S,$U19)),INDEX('MiT Strom Pipeline'!$S:$S,$U19),"")) -> 1 | K19: =IF($U19="","",IF(LEN(INDEX('MiT Strom Pipeline'!$V:$V,$U19))>0,LEFT(INDEX('MiT Strom Pipeline'!$V:$V,$U19),55),"")) -> Abgeschlossen | U19: =IFERROR(MATCH(9,'MiT Strom Pipeline'!$AB$6:$AB$860,0)+5,"") -> 61
A20: =IF($U20="","",IF(ISNUMBER(INDEX('MiT Strom Pipeline'!$A:$A,$U20)),INDEX('MiT Strom Pipeline'!$A:$A,$U20),"")) -> 52 | B20: =IF($U20="","",IF(INDEX('MiT Strom Pipeline'!$B:$B,$U20)="","",INDEX('MiT Strom Pipeline'!$B:$B,$U20))) -> DPR Heat Loadbank | C20: =IF($U20="","",IF(INDEX('MiT Strom Pipeline'!$C:$C,$U20)="","",INDEX('MiT Strom Pipeline'!$C:$C,$U20))) -> ZH | D20: =IF($U20="","",IF(INDEX('MiT Strom Pipeline'!$D:$D,$U20)="","",INDEX('MiT Strom Pipeline'!$D:$D,$U20))) -> Datacenter | E20: =IF($U20="","",IF(INDEX('MiT Strom Pipeline'!$H:$H,$U20)="","",INDEX('MiT Strom Pipeline'!$H:$H,$U20))) -> Aug | F20: =IF($U20="","",IF(INDEX('MiT Strom Pipeline'!$E:$E,$U20)="","",INDEX('MiT Strom Pipeline'!$E:$E,$U20))) -> 54x200 kVA Loadbank | G20: =IF($U20="","",IF(ISNUMBER(INDEX('MiT Strom Pipeline'!$I:$I,$U20)),INDEX('MiT Strom Pipeline'!$I:$I,$U20),0)) -> 333790 | H20: =IF($U20="","",IF(ISNUMBER(INDEX('MiT Strom Pipeline'!$Q:$Q,$U20)),INDEX('MiT Strom Pipeline'!$Q:$Q,$U20),0)) -> 333790 | I20: =IF($U20="","",INDEX('MiT Strom Pipeline'!$R:$R,$U20)) -> WON | J20: =IF($U20="","",IF(ISNUMBER(INDEX('MiT Strom Pipeline'!$S:$S,$U20)),INDEX('MiT Strom Pipeline'!$S:$S,$U20),"")) -> 1 | K20: =IF($U20="","",IF(LEN(INDEX('MiT Strom Pipeline'!$V:$V,$U20))>0,LEFT(INDEX('MiT Strom Pipeline'!$V:$V,$U20),55),"")) -> Kunde angeschrieben auf MiT seite mit aktueller CHF Pre | U20: =IFERROR(MATCH(10,'MiT Strom Pipeline'!$AB$6:$AB$860,0)+5,"") -> 62
A21: =IF($U21="","",IF(ISNUMBER(INDEX('MiT Strom Pipeline'!$A:$A,$U21)),INDEX('MiT Strom Pipeline'!$A:$A,$U21),"")) -> 53 | B21: =IF($U21="","",IF(INDEX('MiT Strom Pipeline'!$B:$B,$U21)="","",INDEX('MiT Strom Pipeline'!$B:$B,$U21))) -> DPR Generator Loadbank Test | C21: =IF($U21="","",IF(INDEX('MiT Strom Pipeline'!$C:$C,$U21)="","",INDEX('MiT Strom Pipeline'!$C:$C,$U21))) -> ZH | D21: =IF($U21="","",IF(INDEX('MiT Strom Pipeline'!$D:$D,$U21)="","",INDEX('MiT Strom Pipeline'!$D:$D,$U21))) -> Datacenter | E21: =IF($U21="","",IF(INDEX('MiT Strom Pipeline'!$H:$H,$U21)="","",INDEX('MiT Strom Pipeline'!$H:$H,$U21))) -> Aug | F21: =IF($U21="","",IF(INDEX('MiT Strom Pipeline'!$E:$E,$U21)="","",INDEX('MiT Strom Pipeline'!$E:$E,$U21))) -> 6000 kVA Loadbank | G21: =IF($U21="","",IF(ISNUMBER(INDEX('MiT Strom Pipeline'!$I:$I,$U21)),INDEX('MiT Strom Pipeline'!$I:$I,$U21),0)) -> 331889.15 | H21: =IF($U21="","",IF(ISNUMBER(INDEX('MiT Strom Pipeline'!$Q:$Q,$U21)),INDEX('MiT Strom Pipeline'!$Q:$Q,$U21),0)) -> 331889.15 | I21: =IF($U21="","",INDEX('MiT Strom Pipeline'!$R:$R,$U21)) -> WON | J21: =IF($U21="","",IF(ISNUMBER(INDEX('MiT Strom Pipeline'!$S:$S,$U21)),INDEX('MiT Strom Pipeline'!$S:$S,$U21),"")) -> 1 | K21: =IF($U21="","",IF(LEN(INDEX('MiT Strom Pipeline'!$V:$V,$U21))>0,LEFT(INDEX('MiT Strom Pipeline'!$V:$V,$U21),55),"")) -> Kunde angeschrieben auf MiT seite mit aktueller CHF Pre | U21: =IFERROR(MATCH(11,'MiT Strom Pipeline'!$AB$6:$AB$860,0)+5,"") -> 63
A22: =IF($U22="","",IF(ISNUMBER(INDEX('MiT Strom Pipeline'!$A:$A,$U22)),INDEX('MiT Strom Pipeline'!$A:$A,$U22),"")) -> 61 | B22: =IF($U22="","",IF(INDEX('MiT Strom Pipeline'!$B:$B,$U22)="","",INDEX('MiT Strom Pipeline'!$B:$B,$U22))) -> GETEC Park.Swiss AG | C22: =IF($U22="","",IF(INDEX('MiT Strom Pipeline'!$C:$C,$U22)="","",INDEX('MiT Strom Pipeline'!$C:$C,$U22))) -> BL | D22: =IF($U22="","",IF(INDEX('MiT Strom Pipeline'!$D:$D,$U22)="","",INDEX('MiT Strom Pipeline'!$D:$D,$U22))) -> Industrie | E22: =IF($U22="","",IF(INDEX('MiT Strom Pipeline'!$H:$H,$U22)="","",INDEX('MiT Strom Pipeline'!$H:$H,$U22))) -> August | F22: =IF($U22="","",IF(INDEX('MiT Strom Pipeline'!$E:$E,$U22)="","",INDEX('MiT Strom Pipeline'!$E:$E,$U22))) -> 600 kVA | G22: =IF($U22="","",IF(ISNUMBER(INDEX('MiT Strom Pipeline'!$I:$I,$U22)),INDEX('MiT Strom Pipeline'!$I:$I,$U22),0)) -> 13472.18 | H22: =IF($U22="","",IF(ISNUMBER(INDEX('MiT Strom Pipeline'!$Q:$Q,$U22)),INDEX('MiT Strom Pipeline'!$Q:$Q,$U22),0)) -> 13472.18 | I22: =IF($U22="","",INDEX('MiT Strom Pipeline'!$R:$R,$U22)) -> WON | J22: =IF($U22="","",IF(ISNUMBER(INDEX('MiT Strom Pipeline'!$S:$S,$U22)),INDEX('MiT Strom Pipeline'!$S:$S,$U22),"")) -> 1 | K22: =IF($U22="","",IF(LEN(INDEX('MiT Strom Pipeline'!$V:$V,$U22))>0,LEFT(INDEX('MiT Strom Pipeline'!$V:$V,$U22),55),"")) -> Kunde angeschrieben, Offerte erstellt, Kunde hat Offert | U22: =IFERROR(MATCH(12,'MiT Strom Pipeline'!$AB$6:$AB$860,0)+5,"") -> 71
A23: =IF($U23="","",IF(ISNUMBER(INDEX('MiT Strom Pipeline'!$A:$A,$U23)),INDEX('MiT Strom Pipeline'!$A:$A,$U23),"")) | B23: =IF($U23="","",IF(INDEX('MiT Strom Pipeline'!$B:$B,$U23)="","",INDEX('MiT Strom Pipeline'!$B:$B,$U23))) | C23: =IF($U23="","",IF(INDEX('MiT Strom Pipeline'!$C:$C,$U23)="","",INDEX('MiT Strom Pipeline'!$C:$C,$U23))) | D23: =IF($U23="","",IF(INDEX('MiT Strom Pipeline'!$D:$D,$U23)="","",INDEX('MiT Strom Pipeline'!$D:$D,$U23))) | E23: =IF($U23="","",IF(INDEX('MiT Strom Pipeline'!$H:$H,$U23)="","",INDEX('MiT Strom Pipeline'!$H:$H,$U23))) | F23: =IF($U23="","",IF(INDEX('MiT Strom Pipeline'!$E:$E,$U23)="","",INDEX('MiT Strom Pipeline'!$E:$E,$U23))) | G23: =IF($U23="","",IF(ISNUMBER(INDEX('MiT Strom Pipeline'!$I:$I,$U23)),INDEX('MiT Strom Pipeline'!$I:$I,$U23),0)) | H23: =IF($U23="","",IF(ISNUMBER(INDEX('MiT Strom Pipeline'!$Q:$Q,$U23)),INDEX('MiT Strom Pipeline'!$Q:$Q,$U23),0)) | I23: =IF($U23="","",INDEX('MiT Strom Pipeline'!$R:$R,$U23)) | J23: =IF($U23="","",IF(ISNUMBER(INDEX('MiT Strom Pipeline'!$S:$S,$U23)),INDEX('MiT Strom Pipeline'!$S:$S,$U23),"")) | K23: =IF($U23="","",IF(LEN(INDEX('MiT Strom Pipeline'!$V:$V,$U23))>0,LEFT(INDEX('MiT Strom Pipeline'!$V:$V,$U23),55),"")) | U23: =IFERROR(MATCH(13,'MiT Strom Pipeline'!$AB$6:$AB$860,0)+5,"")
A24: =IF($U24="","",IF(ISNUMBER(INDEX('MiT Strom Pipeline'!$A:$A,$U24)),INDEX('MiT Strom Pipeline'!$A:$A,$U24),"")) | B24: =IF($U24="","",IF(INDEX('MiT Strom Pipeline'!$B:$B,$U24)="","",INDEX('MiT Strom Pipeline'!$B:$B,$U24))) | C24: =IF($U24="","",IF(INDEX('MiT Strom Pipeline'!$C:$C,$U24)="","",INDEX('MiT Strom Pipeline'!$C:$C,$U24))) | D24: =IF($U24="","",IF(INDEX('MiT Strom Pipeline'!$D:$D,$U24)="","",INDEX('MiT Strom Pipeline'!$D:$D,$U24))) | E24: =IF($U24="","",IF(INDEX('MiT Strom Pipeline'!$H:$H,$U24)="","",INDEX('MiT Strom Pipeline'!$H:$H,$U24))) | F24: =IF($U24="","",IF(INDEX('MiT Strom Pipeline'!$E:$E,$U24)="","",INDEX('MiT Strom Pipeline'!$E:$E,$U24))) | G24: =IF($U24="","",IF(ISNUMBER(INDEX('MiT Strom Pipeline'!$I:$I,$U24)),INDEX('MiT Strom Pipeline'!$I:$I,$U24),0)) | H24: =IF($U24="","",IF(ISNUMBER(INDEX('MiT Strom Pipeline'!$Q:$Q,$U24)),INDEX('MiT Strom Pipeline'!$Q:$Q,$U24),0)) | I24: =IF($U24="","",INDEX('MiT Strom Pipeline'!$R:$R,$U24)) | J24: =IF($U24="","",IF(ISNUMBER(INDEX('MiT Strom Pipeline'!$S:$S,$U24)),INDEX('MiT Strom Pipeline'!$S:$S,$U24),"")) | K24: =IF($U24="","",IF(LEN(INDEX('MiT Strom Pipeline'!$V:$V,$U24))>0,LEFT(INDEX('MiT Strom Pipeline'!$V:$V,$U24),55),"")) | U24: =IFERROR(MATCH(14,'MiT Strom Pipeline'!$AB$6:$AB$860,0)+5,"")
A25: =IF($U25="","",IF(ISNUMBER(INDEX('MiT Strom Pipeline'!$A:$A,$U25)),INDEX('MiT Strom Pipeline'!$A:$A,$U25),"")) | B25: =IF($U25="","",IF(INDEX('MiT Strom Pipeline'!$B:$B,$U25)="","",INDEX('MiT Strom Pipeline'!$B:$B,$U25))) | C25: =IF($U25="","",IF(INDEX('MiT Strom Pipeline'!$C:$C,$U25)="","",INDEX('MiT Strom Pipeline'!$C:$C,$U25))) | D25: =IF($U25="","",IF(INDEX('MiT Strom Pipeline'!$D:$D,$U25)="","",INDEX('MiT Strom Pipeline'!$D:$D,$U25))) | E25: =IF($U25="","",IF(INDEX('MiT Strom Pipeline'!$H:$H,$U25)="","",INDEX('MiT Strom Pipeline'!$H:$H,$U25))) | F25: =IF($U25="","",IF(INDEX('MiT Strom Pipeline'!$E:$E,$U25)="","",INDEX('MiT Strom Pipeline'!$E:$E,$U25))) | G25: =IF($U25="","",IF(ISNUMBER(INDEX('MiT Strom Pipeline'!$I:$I,$U25)),INDEX('MiT Strom Pipeline'!$I:$I,$U25),0)) | H25: =IF($U25="","",IF(ISNUMBER(INDEX('MiT Strom Pipeline'!$Q:$Q,$U25)),INDEX('MiT Strom Pipeline'!$Q:$Q,$U25),0)) | I25: =IF($U25="","",INDEX('MiT Strom Pipeline'!$R:$R,$U25)) | J25: =IF($U25="","",IF(ISNUMBER(INDEX('MiT Strom Pipeline'!$S:$S,$U25)),INDEX('MiT Strom Pipeline'!$S:$S,$U25),"")) | K25: =IF($U25="","",IF(LEN(INDEX('MiT Strom Pipeline'!$V:$V,$U25))>0,LEFT(INDEX('MiT Strom Pipeline'!$V:$V,$U25),55),"")) | U25: =IFERROR(MATCH(15,'MiT Strom Pipeline'!$AB$6:$AB$860,0)+5,"")
A26: =IF($U26="","",IF(ISNUMBER(INDEX('MiT Strom Pipeline'!$A:$A,$U26)),INDEX('MiT Strom Pipeline'!$A:$A,$U26),"")) | B26: =IF($U26="","",IF(INDEX('MiT Strom Pipeline'!$B:$B,$U26)="","",INDEX('MiT Strom Pipeline'!$B:$B,$U26))) | C26: =IF($U26="","",IF(INDEX('MiT Strom Pipeline'!$C:$C,$U26)="","",INDEX('MiT Strom Pipeline'!$C:$C,$U26))) | D26: =IF($U26="","",IF(INDEX('MiT Strom Pipeline'!$D:$D,$U26)="","",INDEX('MiT Strom Pipeline'!$D:$D,$U26))) | E26: =IF($U26="","",IF(INDEX('MiT Strom Pipeline'!$H:$H,$U26)="","",INDEX('MiT Strom Pipeline'!$H:$H,$U26))) | F26: =IF($U26="","",IF(INDEX('MiT Strom Pipeline'!$E:$E,$U26)="","",INDEX('MiT Strom Pipeline'!$E:$E,$U26))) | G26: =IF($U26="","",IF(ISNUMBER(INDEX('MiT Strom Pipeline'!$I:$I,$U26)),INDEX('MiT Strom Pipeline'!$I:$I,$U26),0)) | H26: =IF($U26="","",IF(ISNUMBER(INDEX('MiT Strom Pipeline'!$Q:$Q,$U26)),INDEX('MiT Strom Pipeline'!$Q:$Q,$U26),0)) | I26: =IF($U26="","",INDEX('MiT Strom Pipeline'!$R:$R,$U26)) | J26: =IF($U26="","",IF(ISNUMBER(INDEX('MiT Strom Pipeline'!$S:$S,$U26)),INDEX('MiT Strom Pipeline'!$S:$S,$U26),"")) | K26: =IF($U26="","",IF(LEN(INDEX('MiT Strom Pipeline'!$V:$V,$U26))>0,LEFT(INDEX('MiT Strom Pipeline'!$V:$V,$U26),55),"")) | U26: =IFERROR(MATCH(16,'MiT Strom Pipeline'!$AB$6:$AB$860,0)+5,"")
A27: =IF($U27="","",IF(ISNUMBER(INDEX('MiT Strom Pipeline'!$A:$A,$U27)),INDEX('MiT Strom Pipeline'!$A:$A,$U27),"")) | B27: =IF($U27="","",IF(INDEX('MiT Strom Pipeline'!$B:$B,$U27)="","",INDEX('MiT Strom Pipeline'!$B:$B,$U27))) | C27: =IF($U27="","",IF(INDEX('MiT Strom Pipeline'!$C:$C,$U27)="","",INDEX('MiT Strom Pipeline'!$C:$C,$U27))) | D27: =IF($U27="","",IF(INDEX('MiT Strom Pipeline'!$D:$D,$U27)="","",INDEX('MiT Strom Pipeline'!$D:$D,$U27))) | E27: =IF($U27="","",IF(INDEX('MiT Strom Pipeline'!$H:$H,$U27)="","",INDEX('MiT Strom Pipeline'!$H:$H,$U27))) | F27: =IF($U27="","",IF(INDEX('MiT Strom Pipeline'!$E:$E,$U27)="","",INDEX('MiT Strom Pipeline'!$E:$E,$U27))) | G27: =IF($U27="","",IF(ISNUMBER(INDEX('MiT Strom Pipeline'!$I:$I,$U27)),INDEX('MiT Strom Pipeline'!$I:$I,$U27),0)) | H27: =IF($U27="","",IF(ISNUMBER(INDEX('MiT Strom Pipeline'!$Q:$Q,$U27)),INDEX('MiT Strom Pipeline'!$Q:$Q,$U27),0)) | I27: =IF($U27="","",INDEX('MiT Strom Pipeline'!$R:$R,$U27)) | J27: =IF($U27="","",IF(ISNUMBER(INDEX('MiT Strom Pipeline'!$S:$S,$U27)),INDEX('MiT Strom Pipeline'!$S:$S,$U27),"")) | K27: =IF($U27="","",IF(LEN(INDEX('MiT Strom Pipeline'!$V:$V,$U27))>0,LEFT(INDEX('MiT Strom Pipeline'!$V:$V,$U27),55),"")) | U27: =IFERROR(MATCH(17,'MiT Strom Pipeline'!$AB$6:$AB$860,0)+5,"")
A28: =IF($U28="","",IF(ISNUMBER(INDEX('MiT Strom Pipeline'!$A:$A,$U28)),INDEX('MiT Strom Pipeline'!$A:$A,$U28),"")) | B28: =IF($U28="","",IF(INDEX('MiT Strom Pipeline'!$B:$B,$U28)="","",INDEX('MiT Strom Pipeline'!$B:$B,$U28))) | C28: =IF($U28="","",IF(INDEX('MiT Strom Pipeline'!$C:$C,$U28)="","",INDEX('MiT Strom Pipeline'!$C:$C,$U28))) | D28: =IF($U28="","",IF(INDEX('MiT Strom Pipeline'!$D:$D,$U28)="","",INDEX('MiT Strom Pipeline'!$D:$D,$U28))) | E28: =IF($U28="","",IF(INDEX('MiT Strom Pipeline'!$H:$H,$U28)="","",INDEX('MiT Strom Pipeline'!$H:$H,$U28))) | F28: =IF($U28="","",IF(INDEX('MiT Strom Pipeline'!$E:$E,$U28)="","",INDEX('MiT Strom Pipeline'!$E:$E,$U28))) | G28: =IF($U28="","",IF(ISNUMBER(INDEX('MiT Strom Pipeline'!$I:$I,$U28)),INDEX('MiT Strom Pipeline'!$I:$I,$U28),0)) | H28: =IF($U28="","",IF(ISNUMBER(INDEX('MiT Strom Pipeline'!$Q:$Q,$U28)),INDEX('MiT Strom Pipeline'!$Q:$Q,$U28),0)) | I28: =IF($U28="","",INDEX('MiT Strom Pipeline'!$R:$R,$U28)) | J28: =IF($U28="","",IF(ISNUMBER(INDEX('MiT Strom Pipeline'!$S:$S,$U28)),INDEX('MiT Strom Pipeline'!$S:$S,$U28),"")) | K28: =IF($U28="","",IF(LEN(INDEX('MiT Strom Pipeline'!$V:$V,$U28))>0,LEFT(INDEX('MiT Strom Pipeline'!$V:$V,$U28),55),"")) | U28: =IFERROR(MATCH(18,'MiT Strom Pipeline'!$AB$6:$AB$860,0)+5,"")
A29: =IF($U29="","",IF(ISNUMBER(INDEX('MiT Strom Pipeline'!$A:$A,$U29)),INDEX('MiT Strom Pipeline'!$A:$A,$U29),"")) | B29: =IF($U29="","",IF(INDEX('MiT Strom Pipeline'!$B:$B,$U29)="","",INDEX('MiT Strom Pipeline'!$B:$B,$U29))) | C29: =IF($U29="","",IF(INDEX('MiT Strom Pipeline'!$C:$C,$U29)="","",INDEX('MiT Strom Pipeline'!$C:$C,$U29))) | D29: =IF($U29="","",IF(INDEX('MiT Strom Pipeline'!$D:$D,$U29)="","",INDEX('MiT Strom Pipeline'!$D:$D,$U29))) | E29: =IF($U29="","",IF(INDEX('MiT Strom Pipeline'!$H:$H,$U29)="","",INDEX('MiT Strom Pipeline'!$H:$H,$U29))) | F29: =IF($U29="","",IF(INDEX('MiT Strom Pipeline'!$E:$E,$U29)="","",INDEX('MiT Strom Pipeline'!$E:$E,$U29))) | G29: =IF($U29="","",IF(ISNUMBER(INDEX('MiT Strom Pipeline'!$I:$I,$U29)),INDEX('MiT Strom Pipeline'!$I:$I,$U29),0)) | H29: =IF($U29="","",IF(ISNUMBER(INDEX('MiT Strom Pipeline'!$Q:$Q,$U29)),INDEX('MiT Strom Pipeline'!$Q:$Q,$U29),0)) | I29: =IF($U29="","",INDEX('MiT Strom Pipeline'!$R:$R,$U29)) | J29: =IF($U29="","",IF(ISNUMBER(INDEX('MiT Strom Pipeline'!$S:$S,$U29)),INDEX('MiT Strom Pipeline'!$S:$S,$U29),"")) | K29: =IF($U29="","",IF(LEN(INDEX('MiT Strom Pipeline'!$V:$V,$U29))>0,LEFT(INDEX('MiT Strom Pipeline'!$V:$V,$U29),55),"")) | U29: =IFERROR(MATCH(19,'MiT Strom Pipeline'!$AB$6:$AB$860,0)+5,"")
A30: =IF($U30="","",IF(ISNUMBER(INDEX('MiT Strom Pipeline'!$A:$A,$U30)),INDEX('MiT Strom Pipeline'!$A:$A,$U30),"")) | B30: =IF($U30="","",IF(INDEX('MiT Strom Pipeline'!$B:$B,$U30)="","",INDEX('MiT Strom Pipeline'!$B:$B,$U30))) | C30: =IF($U30="","",IF(INDEX('MiT Strom Pipeline'!$C:$C,$U30)="","",INDEX('MiT Strom Pipeline'!$C:$C,$U30))) | D30: =IF($U30="","",IF(INDEX('MiT Strom Pipeline'!$D:$D,$U30)="","",INDEX('MiT Strom Pipeline'!$D:$D,$U30))) | E30: =IF($U30="","",IF(INDEX('MiT Strom Pipeline'!$H:$H,$U30)="","",INDEX('MiT Strom Pipeline'!$H:$H,$U30))) | F30: =IF($U30="","",IF(INDEX('MiT Strom Pipeline'!$E:$E,$U30)="","",INDEX('MiT Strom Pipeline'!$E:$E,$U30))) | G30: =IF($U30="","",IF(ISNUMBER(INDEX('MiT Strom Pipeline'!$I:$I,$U30)),INDEX('MiT Strom Pipeline'!$I:$I,$U30),0)) | H30: =IF($U30="","",IF(ISNUMBER(INDEX('MiT Strom Pipeline'!$Q:$Q,$U30)),INDEX('MiT Strom Pipeline'!$Q:$Q,$U30),0)) | I30: =IF($U30="","",INDEX('MiT Strom Pipeline'!$R:$R,$U30)) | J30: =IF($U30="","",IF(ISNUMBER(INDEX('MiT Strom Pipeline'!$S:$S,$U30)),INDEX('MiT Strom Pipeline'!$S:$S,$U30),"")) | K30: =IF($U30="","",IF(LEN(INDEX('MiT Strom Pipeline'!$V:$V,$U30))>0,LEFT(INDEX('MiT Strom Pipeline'!$V:$V,$U30),55),"")) | U30: =IFERROR(MATCH(20,'MiT Strom Pipeline'!$AB$6:$AB$860,0)+5,"")
A31: =IF($U31="","",IF(ISNUMBER(INDEX('MiT Strom Pipeline'!$A:$A,$U31)),INDEX('MiT Strom Pipeline'!$A:$A,$U31),"")) | B31: =IF($U31="","",IF(INDEX('MiT Strom Pipeline'!$B:$B,$U31)="","",INDEX('MiT Strom Pipeline'!$B:$B,$U31))) | C31: =IF($U31="","",IF(INDEX('MiT Strom Pipeline'!$C:$C,$U31)="","",INDEX('MiT Strom Pipeline'!$C:$C,$U31))) | D31: =IF($U31="","",IF(INDEX('MiT Strom Pipeline'!$D:$D,$U31)="","",INDEX('MiT Strom Pipeline'!$D:$D,$U31))) | E31: =IF($U31="","",IF(INDEX('MiT Strom Pipeline'!$H:$H,$U31)="","",INDEX('MiT Strom Pipeline'!$H:$H,$U31))) | F31: =IF($U31="","",IF(INDEX('MiT Strom Pipeline'!$E:$E,$U31)="","",INDEX('MiT Strom Pipeline'!$E:$E,$U31))) | G31: =IF($U31="","",IF(ISNUMBER(INDEX('MiT Strom Pipeline'!$I:$I,$U31)),INDEX('MiT Strom Pipeline'!$I:$I,$U31),0)) | H31: =IF($U31="","",IF(ISNUMBER(INDEX('MiT Strom Pipeline'!$Q:$Q,$U31)),INDEX('MiT Strom Pipeline'!$Q:$Q,$U31),0)) | I31: =IF($U31="","",INDEX('MiT Strom Pipeline'!$R:$R,$U31)) | J31: =IF($U31="","",IF(ISNUMBER(INDEX('MiT Strom Pipeline'!$S:$S,$U31)),INDEX('MiT Strom Pipeline'!$S:$S,$U31),"")) | K31: =IF($U31="","",IF(LEN(INDEX('MiT Strom Pipeline'!$V:$V,$U31))>0,LEFT(INDEX('MiT Strom Pipeline'!$V:$V,$U31),55),"")) | U31: =IFERROR(MATCH(21,'MiT Strom Pipeline'!$AB$6:$AB$860,0)+5,"")
A32: =IF($U32="","",IF(ISNUMBER(INDEX('MiT Strom Pipeline'!$A:$A,$U32)),INDEX('MiT Strom Pipeline'!$A:$A,$U32),"")) | B32: =IF($U32="","",IF(INDEX('MiT Strom Pipeline'!$B:$B,$U32)="","",INDEX('MiT Strom Pipeline'!$B:$B,$U32))) | C32: =IF($U32="","",IF(INDEX('MiT Strom Pipeline'!$C:$C,$U32)="","",INDEX('MiT Strom Pipeline'!$C:$C,$U32))) | D32: =IF($U32="","",IF(INDEX('MiT Strom Pipeline'!$D:$D,$U32)="","",INDEX('MiT Strom Pipeline'!$D:$D,$U32))) | E32: =IF($U32="","",IF(INDEX('MiT Strom Pipeline'!$H:$H,$U32)="","",INDEX('MiT Strom Pipeline'!$H:$H,$U32))) | F32: =IF($U32="","",IF(INDEX('MiT Strom Pipeline'!$E:$E,$U32)="","",INDEX('MiT Strom Pipeline'!$E:$E,$U32))) | G32: =IF($U32="","",IF(ISNUMBER(INDEX('MiT Strom Pipeline'!$I:$I,$U32)),INDEX('MiT Strom Pipeline'!$I:$I,$U32),0)) | H32: =IF($U32="","",IF(ISNUMBER(INDEX('MiT Strom Pipeline'!$Q:$Q,$U32)),INDEX('MiT Strom Pipeline'!$Q:$Q,$U32),0)) | I32: =IF($U32="","",INDEX('MiT Strom Pipeline'!$R:$R,$U32)) | J32: =IF($U32="","",IF(ISNUMBER(INDEX('MiT Strom Pipeline'!$S:$S,$U32)),INDEX('MiT Strom Pipeline'!$S:$S,$U32),"")) | K32: =IF($U32="","",IF(LEN(INDEX('MiT Strom Pipeline'!$V:$V,$U32))>0,LEFT(INDEX('MiT Strom Pipeline'!$V:$V,$U32),55),"")) | U32: =IFERROR(MATCH(22,'MiT Strom Pipeline'!$AB$6:$AB$860,0)+5,"")
A33: =IF($U33="","",IF(ISNUMBER(INDEX('MiT Strom Pipeline'!$A:$A,$U33)),INDEX('MiT Strom Pipeline'!$A:$A,$U33),"")) | B33: =IF($U33="","",IF(INDEX('MiT Strom Pipeline'!$B:$B,$U33)="","",INDEX('MiT Strom Pipeline'!$B:$B,$U33))) | C33: =IF($U33="","",IF(INDEX('MiT Strom Pipeline'!$C:$C,$U33)="","",INDEX('MiT Strom Pipeline'!$C:$C,$U33))) | D33: =IF($U33="","",IF(INDEX('MiT Strom Pipeline'!$D:$D,$U33)="","",INDEX('MiT Strom Pipeline'!$D:$D,$U33))) | E33: =IF($U33="","",IF(INDEX('MiT Strom Pipeline'!$H:$H,$U33)="","",INDEX('MiT Strom Pipeline'!$H:$H,$U33))) | F33: =IF($U33="","",IF(INDEX('MiT Strom Pipeline'!$E:$E,$U33)="","",INDEX('MiT Strom Pipeline'!$E:$E,$U33))) | G33: =IF($U33="","",IF(ISNUMBER(INDEX('MiT Strom Pipeline'!$I:$I,$U33)),INDEX('MiT Strom Pipeline'!$I:$I,$U33),0)) | H33: =IF($U33="","",IF(ISNUMBER(INDEX('MiT Strom Pipeline'!$Q:$Q,$U33)),INDEX('MiT Strom Pipeline'!$Q:$Q,$U33),0)) | I33: =IF($U33="","",INDEX('MiT Strom Pipeline'!$R:$R,$U33)) | J33: =IF($U33="","",IF(ISNUMBER(INDEX('MiT Strom Pipeline'!$S:$S,$U33)),INDEX('MiT Strom Pipeline'!$S:$S,$U33),"")) | K33: =IF($U33="","",IF(LEN(INDEX('MiT Strom Pipeline'!$V:$V,$U33))>0,LEFT(INDEX('MiT Strom Pipeline'!$V:$V,$U33),55),"")) | U33: =IFERROR(MATCH(23,'MiT Strom Pipeline'!$AB$6:$AB$860,0)+5,"")
A34: =IF($U34="","",IF(ISNUMBER(INDEX('MiT Strom Pipeline'!$A:$A,$U34)),INDEX('MiT Strom Pipeline'!$A:$A,$U34),"")) | B34: =IF($U34="","",IF(INDEX('MiT Strom Pipeline'!$B:$B,$U34)="","",INDEX('MiT Strom Pipeline'!$B:$B,$U34))) | C34: =IF($U34="","",IF(INDEX('MiT Strom Pipeline'!$C:$C,$U34)="","",INDEX('MiT Strom Pipeline'!$C:$C,$U34))) | D34: =IF($U34="","",IF(INDEX('MiT Strom Pipeline'!$D:$D,$U34)="","",INDEX('MiT Strom Pipeline'!$D:$D,$U34))) | E34: =IF($U34="","",IF(INDEX('MiT Strom Pipeline'!$H:$H,$U34)="","",INDEX('MiT Strom Pipeline'!$H:$H,$U34))) | F34: =IF($U34="","",IF(INDEX('MiT Strom Pipeline'!$E:$E,$U34)="","",INDEX('MiT Strom Pipeline'!$E:$E,$U34))) | G34: =IF($U34="","",IF(ISNUMBER(INDEX('MiT Strom Pipeline'!$I:$I,$U34)),INDEX('MiT Strom Pipeline'!$I:$I,$U34),0)) | H34: =IF($U34="","",IF(ISNUMBER(INDEX('MiT Strom Pipeline'!$Q:$Q,$U34)),INDEX('MiT Strom Pipeline'!$Q:$Q,$U34),0)) | I34: =IF($U34="","",INDEX('MiT Strom Pipeline'!$R:$R,$U34)) | J34: =IF($U34="","",IF(ISNUMBER(INDEX('MiT Strom Pipeline'!$S:$S,$U34)),INDEX('MiT Strom Pipeline'!$S:$S,$U34),"")) | K34: =IF($U34="","",IF(LEN(INDEX('MiT Strom Pipeline'!$V:$V,$U34))>0,LEFT(INDEX('MiT Strom Pipeline'!$V:$V,$U34),55),"")) | U34: =IFERROR(MATCH(24,'MiT Strom Pipeline'!$AB$6:$AB$860,0)+5,"")
A35: =IF($U35="","",IF(ISNUMBER(INDEX('MiT Strom Pipeline'!$A:$A,$U35)),INDEX('MiT Strom Pipeline'!$A:$A,$U35),"")) | B35: =IF($U35="","",IF(INDEX('MiT Strom Pipeline'!$B:$B,$U35)="","",INDEX('MiT Strom Pipeline'!$B:$B,$U35))) | C35: =IF($U35="","",IF(INDEX('MiT Strom Pipeline'!$C:$C,$U35)="","",INDEX('MiT Strom Pipeline'!$C:$C,$U35))) | D35: =IF($U35="","",IF(INDEX('MiT Strom Pipeline'!$D:$D,$U35)="","",INDEX('MiT Strom Pipeline'!$D:$D,$U35))) | E35: =IF($U35="","",IF(INDEX('MiT Strom Pipeline'!$H:$H,$U35)="","",INDEX('MiT Strom Pipeline'!$H:$H,$U35))) | F35: =IF($U35="","",IF(INDEX('MiT Strom Pipeline'!$E:$E,$U35)="","",INDEX('MiT Strom Pipeline'!$E:$E,$U35))) | G35: =IF($U35="","",IF(ISNUMBER(INDEX('MiT Strom Pipeline'!$I:$I,$U35)),INDEX('MiT Strom Pipeline'!$I:$I,$U35),0)) | H35: =IF($U35="","",IF(ISNUMBER(INDEX('MiT Strom Pipeline'!$Q:$Q,$U35)),INDEX('MiT Strom Pipeline'!$Q:$Q,$U35),0)) | I35: =IF($U35="","",INDEX('MiT Strom Pipeline'!$R:$R,$U35)) | J35: =IF($U35="","",IF(ISNUMBER(INDEX('MiT Strom Pipeline'!$S:$S,$U35)),INDEX('MiT Strom Pipeline'!$S:$S,$U35),"")) | K35: =IF($U35="","",IF(LEN(INDEX('MiT Strom Pipeline'!$V:$V,$U35))>0,LEFT(INDEX('MiT Strom Pipeline'!$V:$V,$U35),55),"")) | U35: =IFERROR(MATCH(25,'MiT Strom Pipeline'!$AB$6:$AB$860,0)+5,"")
A36: =IF($U36="","",IF(ISNUMBER(INDEX('MiT Strom Pipeline'!$A:$A,$U36)),INDEX('MiT Strom Pipeline'!$A:$A,$U36),"")) | B36: =IF($U36="","",IF(INDEX('MiT Strom Pipeline'!$B:$B,$U36)="","",INDEX('MiT Strom Pipeline'!$B:$B,$U36))) | C36: =IF($U36="","",IF(INDEX('MiT Strom Pipeline'!$C:$C,$U36)="","",INDEX('MiT Strom Pipeline'!$C:$C,$U36))) | D36: =IF($U36="","",IF(INDEX('MiT Strom Pipeline'!$D:$D,$U36)="","",INDEX('MiT Strom Pipeline'!$D:$D,$U36))) | E36: =IF($U36="","",IF(INDEX('MiT Strom Pipeline'!$H:$H,$U36)="","",INDEX('MiT Strom Pipeline'!$H:$H,$U36))) | F36: =IF($U36="","",IF(INDEX('MiT Strom Pipeline'!$E:$E,$U36)="","",INDEX('MiT Strom Pipeline'!$E:$E,$U36))) | G36: =IF($U36="","",IF(ISNUMBER(INDEX('MiT Strom Pipeline'!$I:$I,$U36)),INDEX('MiT Strom Pipeline'!$I:$I,$U36),0)) | H36: =IF($U36="","",IF(ISNUMBER(INDEX('MiT Strom Pipeline'!$Q:$Q,$U36)),INDEX('MiT Strom Pipeline'!$Q:$Q,$U36),0)) | I36: =IF($U36="","",INDEX('MiT Strom Pipeline'!$R:$R,$U36)) | J36: =IF($U36="","",IF(ISNUMBER(INDEX('MiT Strom Pipeline'!$S:$S,$U36)),INDEX('MiT Strom Pipeline'!$S:$S,$U36),"")) | K36: =IF($U36="","",IF(LEN(INDEX('MiT Strom Pipeline'!$V:$V,$U36))>0,LEFT(INDEX('MiT Strom Pipeline'!$V:$V,$U36),55),"")) | U36: =IFERROR(MATCH(26,'MiT Strom Pipeline'!$AB$6:$AB$860,0)+5,"")
