Workbook

Sheet Übersicht
A1: Übersicht Zielkunden Schweiz
A2: Stand 27.09.2026 | alle Zahlen per Formel aus «Kundenliste» | VERTRAULICH
A4: Firmen gesamt | B4: Kernliste | C4: Prio A | D4: Prio B | E4: Prio C | F4: Status offen (CRM)
A5: =COUNTA(Kundenliste!$E$5:$E$129) -> 125 | B5: =COUNTIF(Kundenliste!$B$5:$B$129,"Ja") -> 70 | C5: =COUNTIF(Kundenliste!$X$5:$X$129,"A") -> 36 | D5: =COUNTIF(Kundenliste!$X$5:$X$129,"B") -> 69 | E5: =COUNTIF(Kundenliste!$X$5:$X$129,"C") -> 20 | F5: =COUNTIF(Kundenliste!$Y$5:$Y$129,"Offen: CRM prüfen") -> 125
A7: Segmentmix gemäss Vorgabe 60/20/20
A8: Segment | B8: Firmen gesamt | C8: Kernliste | D8: Soll-Anteil | E8: Ist-Anteil Kernliste | F8: Abweichung | G8: Prio A | H8: Prio B | I8: Prio C
A9: Installateure (60 %) | B9: =COUNTIF(Kundenliste!$C$5:$C$129,$A9) -> 42 | C9: =COUNTIFS(Kundenliste!$C$5:$C$129,$A9,Kundenliste!$B$5:$B$129,"Ja") -> 42 | D9: 0.6 | E9: =IF($C$12=0,0,C9/$C$12) -> 0.6 | F9: =E9-D9 -> 0 | G9: =COUNTIFS(Kundenliste!$C$5:$C$129,$A9,Kundenliste!$X$5:$X$129,"A") -> 11 | H9: =COUNTIFS(Kundenliste!$C$5:$C$129,$A9,Kundenliste!$X$5:$X$129,"B") -> 20 | I9: =COUNTIFS(Kundenliste!$C$5:$C$129,$A9,Kundenliste!$X$5:$X$129,"C") -> 11
A10: FM / EVU / Planer (20 %) | B10: =COUNTIF(Kundenliste!$C$5:$C$129,$A10) -> 35 | C10: =COUNTIFS(Kundenliste!$C$5:$C$129,$A10,Kundenliste!$B$5:$B$129,"Ja") -> 14 | D10: 0.2 | E10: =IF($C$12=0,0,C10/$C$12) -> 0.2 | F10: =E10-D10 -> 0 | G10: =COUNTIFS(Kundenliste!$C$5:$C$129,$A10,Kundenliste!$X$5:$X$129,"A") -> 7 | H10: =COUNTIFS(Kundenliste!$C$5:$C$129,$A10,Kundenliste!$X$5:$X$129,"B") -> 25 | I10: =COUNTIFS(Kundenliste!$C$5:$C$129,$A10,Kundenliste!$X$5:$X$129,"C") -> 3
A11: GU/TU + Industrie (20 %) | B11: =COUNTIF(Kundenliste!$C$5:$C$129,$A11) -> 48 | C11: =COUNTIFS(Kundenliste!$C$5:$C$129,$A11,Kundenliste!$B$5:$B$129,"Ja") -> 14 | D11: 0.2 | E11: =IF($C$12=0,0,C11/$C$12) -> 0.2 | F11: =E11-D11 -> 0 | G11: =COUNTIFS(Kundenliste!$C$5:$C$129,$A11,Kundenliste!$X$5:$X$129,"A") -> 18 | H11: =COUNTIFS(Kundenliste!$C$5:$C$129,$A11,Kundenliste!$X$5:$X$129,"B") -> 24 | I11: =COUNTIFS(Kundenliste!$C$5:$C$129,$A11,Kundenliste!$X$5:$X$129,"C") -> 6
A12: Total | B12: =SUM(B9:B11) -> 125 | C12: =SUM(C9:C11) -> 70 | D12: =SUM(D9:D11) -> 1 | E12: =SUM(E9:E11) -> 1 | G12: =SUM(G9:G11) -> 36 | H12: =SUM(H9:H11) -> 69 | I12: =SUM(I9:I11) -> 20
A14: Regionen x Prio
A15: Region | B15: Prio A | C15: Prio B | D15: Prio C | E15: Total | F15: davon Kernliste | G15: Installateure | H15: FM/EVU/Planer | I15: GU/TU+Industrie
A16: West (Romandie) | B16: =COUNTIFS(Kundenliste!$I$5:$I$129,$A16,Kundenliste!$X$5:$X$129,"A") -> 4 | C16: =COUNTIFS(Kundenliste!$I$5:$I$129,$A16,Kundenliste!$X$5:$X$129,"B") -> 17 | D16: =COUNTIFS(Kundenliste!$I$5:$I$129,$A16,Kundenliste!$X$5:$X$129,"C") -> 6 | E16: =SUM(B16:D16) -> 27 | F16: =COUNTIFS(Kundenliste!$I$5:$I$129,$A16,Kundenliste!$B$5:$B$129,"Ja") -> 13 | G16: =COUNTIFS(Kundenliste!$I$5:$I$129,$A16,Kundenliste!$C$5:$C$129,"Installateure (60 %)") -> 9 | H16: =COUNTIFS(Kundenliste!$I$5:$I$129,$A16,Kundenliste!$C$5:$C$129,"FM / EVU / Planer (20 %)") -> 7 | I16: =COUNTIFS(Kundenliste!$I$5:$I$129,$A16,Kundenliste!$C$5:$C$129,"GU/TU + Industrie (20 %)") -> 11
A17: Mittelland/Bern | B17: =COUNTIFS(Kundenliste!$I$5:$I$129,$A17,Kundenliste!$X$5:$X$129,"A") -> 4 | C17: =COUNTIFS(Kundenliste!$I$5:$I$129,$A17,Kundenliste!$X$5:$X$129,"B") -> 9 | D17: =COUNTIFS(Kundenliste!$I$5:$I$129,$A17,Kundenliste!$X$5:$X$129,"C") -> 3 | E17: =SUM(B17:D17) -> 16 | F17: =COUNTIFS(Kundenliste!$I$5:$I$129,$A17,Kundenliste!$B$5:$B$129,"Ja") -> 9 | G17: =COUNTIFS(Kundenliste!$I$5:$I$129,$A17,Kundenliste!$C$5:$C$129,"Installateure (60 %)") -> 8 | H17: =COUNTIFS(Kundenliste!$I$5:$I$129,$A17,Kundenliste!$C$5:$C$129,"FM / EVU / Planer (20 %)") -> 2 | I17: =COUNTIFS(Kundenliste!$I$5:$I$129,$A17,Kundenliste!$C$5:$C$129,"GU/TU + Industrie (20 %)") -> 6
A18: Nordwestschweiz | B18: =COUNTIFS(Kundenliste!$I$5:$I$129,$A18,Kundenliste!$X$5:$X$129,"A") -> 11 | C18: =COUNTIFS(Kundenliste!$I$5:$I$129,$A18,Kundenliste!$X$5:$X$129,"B") -> 10 | D18: =COUNTIFS(Kundenliste!$I$5:$I$129,$A18,Kundenliste!$X$5:$X$129,"C") -> 1 | E18: =SUM(B18:D18) -> 22 | F18: =COUNTIFS(Kundenliste!$I$5:$I$129,$A18,Kundenliste!$B$5:$B$129,"Ja") -> 16 | G18: =COUNTIFS(Kundenliste!$I$5:$I$129,$A18,Kundenliste!$C$5:$C$129,"Installateure (60 %)") -> 6 | H18: =COUNTIFS(Kundenliste!$I$5:$I$129,$A18,Kundenliste!$C$5:$C$129,"FM / EVU / Planer (20 %)") -> 6 | I18: =COUNTIFS(Kundenliste!$I$5:$I$129,$A18,Kundenliste!$C$5:$C$129,"GU/TU + Industrie (20 %)") -> 10
A19: Zürich | B19: =COUNTIFS(Kundenliste!$I$5:$I$129,$A19,Kundenliste!$X$5:$X$129,"A") -> 11 | C19: =COUNTIFS(Kundenliste!$I$5:$I$129,$A19,Kundenliste!$X$5:$X$129,"B") -> 15 | D19: =COUNTIFS(Kundenliste!$I$5:$I$129,$A19,Kundenliste!$X$5:$X$129,"C") -> 0 | E19: =SUM(B19:D19) -> 26 | F19: =COUNTIFS(Kundenliste!$I$5:$I$129,$A19,Kundenliste!$B$5:$B$129,"Ja") -> 15 | G19: =COUNTIFS(Kundenliste!$I$5:$I$129,$A19,Kundenliste!$C$5:$C$129,"Installateure (60 %)") -> 8 | H19: =COUNTIFS(Kundenliste!$I$5:$I$129,$A19,Kundenliste!$C$5:$C$129,"FM / EVU / Planer (20 %)") -> 8 | I19: =COUNTIFS(Kundenliste!$I$5:$I$129,$A19,Kundenliste!$C$5:$C$129,"GU/TU + Industrie (20 %)") -> 10
A20: Ostschweiz | B20: =COUNTIFS(Kundenliste!$I$5:$I$129,$A20,Kundenliste!$X$5:$X$129,"A") -> 2 | C20: =COUNTIFS(Kundenliste!$I$5:$I$129,$A20,Kundenliste!$X$5:$X$129,"B") -> 8 | D20: =COUNTIFS(Kundenliste!$I$5:$I$129,$A20,Kundenliste!$X$5:$X$129,"C") -> 1 | E20: =SUM(B20:D20) -> 11 | F20: =COUNTIFS(Kundenliste!$I$5:$I$129,$A20,Kundenliste!$B$5:$B$129,"Ja") -> 5 | G20: =COUNTIFS(Kundenliste!$I$5:$I$129,$A20,Kundenliste!$C$5:$C$129,"Installateure (60 %)") -> 4 | H20: =COUNTIFS(Kundenliste!$I$5:$I$129,$A20,Kundenliste!$C$5:$C$129,"FM / EVU / Planer (20 %)") -> 4 | I20: =COUNTIFS(Kundenliste!$I$5:$I$129,$A20,Kundenliste!$C$5:$C$129,"GU/TU + Industrie (20 %)") -> 3
A21: Zentralschweiz | B21: =COUNTIFS(Kundenliste!$I$5:$I$129,$A21,Kundenliste!$X$5:$X$129,"A") -> 3 | C21: =COUNTIFS(Kundenliste!$I$5:$I$129,$A21,Kundenliste!$X$5:$X$129,"B") -> 4 | D21: =COUNTIFS(Kundenliste!$I$5:$I$129,$A21,Kundenliste!$X$5:$X$129,"C") -> 3 | E21: =SUM(B21:D21) -> 10 | F21: =COUNTIFS(Kundenliste!$I$5:$I$129,$A21,Kundenliste!$B$5:$B$129,"Ja") -> 7 | G21: =COUNTIFS(Kundenliste!$I$5:$I$129,$A21,Kundenliste!$C$5:$C$129,"Installateure (60 %)") -> 4 | H21: =COUNTIFS(Kundenliste!$I$5:$I$129,$A21,Kundenliste!$C$5:$C$129,"FM / EVU / Planer (20 %)") -> 4 | I21: =COUNTIFS(Kundenliste!$I$5:$I$129,$A21,Kundenliste!$C$5:$C$129,"GU/TU + Industrie (20 %)") -> 2
A22: Tessin | B22: =COUNTIFS(Kundenliste!$I$5:$I$129,$A22,Kundenliste!$X$5:$X$129,"A") -> 1 | C22: =COUNTIFS(Kundenliste!$I$5:$I$129,$A22,Kundenliste!$X$5:$X$129,"B") -> 6 | D22: =COUNTIFS(Kundenliste!$I$5:$I$129,$A22,Kundenliste!$X$5:$X$129,"C") -> 6 | E22: =SUM(B22:D22) -> 13 | F22: =COUNTIFS(Kundenliste!$I$5:$I$129,$A22,Kundenliste!$B$5:$B$129,"Ja") -> 5 | G22: =COUNTIFS(Kundenliste!$I$5:$I$129,$A22,Kundenliste!$C$5:$C$129,"Installateure (60 %)") -> 3 | H22: =COUNTIFS(Kundenliste!$I$5:$I$129,$A22,Kundenliste!$C$5:$C$129,"FM / EVU / Planer (20 %)") -> 4 | I22: =COUNTIFS(Kundenliste!$I$5:$I$129,$A22,Kundenliste!$C$5:$C$129,"GU/TU + Industrie (20 %)") -> 6
A23: Total | B23: =SUM(B16:B22) -> 36 | C23: =SUM(C16:C22) -> 69 | D23: =SUM(D16:D22) -> 20 | E23: =SUM(E16:E22) -> 125 | F23: =SUM(F16:F22) -> 70 | G23: =SUM(G16:G22) -> 42 | H23: =SUM(H16:H22) -> 35 | I23: =SUM(I16:I22) -> 48
A25: Verkaufsgebiet
A26: Gebiet | B26: Prio A | C26: Prio B | D26: Prio C | E26: Total
A27: West | B27: =COUNTIFS(Kundenliste!$J$5:$J$129,$A27,Kundenliste!$X$5:$X$129,"A") -> 4 | C27: =COUNTIFS(Kundenliste!$J$5:$J$129,$A27,Kundenliste!$X$5:$X$129,"B") -> 17 | D27: =COUNTIFS(Kundenliste!$J$5:$J$129,$A27,Kundenliste!$X$5:$X$129,"C") -> 6 | E27: =SUM(B27:D27) -> 27
A28: Deutschschweiz | B28: =COUNTIFS(Kundenliste!$J$5:$J$129,$A28,Kundenliste!$X$5:$X$129,"A") -> 31 | C28: =COUNTIFS(Kundenliste!$J$5:$J$129,$A28,Kundenliste!$X$5:$X$129,"B") -> 46 | D28: =COUNTIFS(Kundenliste!$J$5:$J$129,$A28,Kundenliste!$X$5:$X$129,"C") -> 8 | E28: =SUM(B28:D28) -> 85
A29: Tessin | B29: =COUNTIFS(Kundenliste!$J$5:$J$129,$A29,Kundenliste!$X$5:$X$129,"A") -> 1 | C29: =COUNTIFS(Kundenliste!$J$5:$J$129,$A29,Kundenliste!$X$5:$X$129,"B") -> 6 | D29: =COUNTIFS(Kundenliste!$J$5:$J$129,$A29,Kundenliste!$X$5:$X$129,"C") -> 6 | E29: =SUM(B29:D29) -> 13
A31: Kategorien
A32: Kategorie | B32: Prio A | C32: Prio B | D32: Prio C | E32: Total | F32: Ø Score
A33: Installateur | B33: =COUNTIFS(Kundenliste!$D$5:$D$129,$A33,Kundenliste!$X$5:$X$129,"A") -> 11 | C33: =COUNTIFS(Kundenliste!$D$5:$D$129,$A33,Kundenliste!$X$5:$X$129,"B") -> 20 | D33: =COUNTIFS(Kundenliste!$D$5:$D$129,$A33,Kundenliste!$X$5:$X$129,"C") -> 11 | E33: =SUM(B33:D33) -> 42 | F33: =IFERROR(AVERAGEIF(Kundenliste!$D$5:$D$129,$A33,Kundenliste!$U$5:$U$129),0) -> 3.497619
A34: Facility Manager | B34: =COUNTIFS(Kundenliste!$D$5:$D$129,$A34,Kundenliste!$X$5:$X$129,"A") -> 2 | C34: =COUNTIFS(Kundenliste!$D$5:$D$129,$A34,Kundenliste!$X$5:$X$129,"B") -> 5 | D34: =COUNTIFS(Kundenliste!$D$5:$D$129,$A34,Kundenliste!$X$5:$X$129,"C") -> 0 | E34: =SUM(B34:D34) -> 7 | F34: =IFERROR(AVERAGEIF(Kundenliste!$D$5:$D$129,$A34,Kundenliste!$U$5:$U$129),0) -> 3.6357143
A35: Stadtwerk/EVU | B35: =COUNTIFS(Kundenliste!$D$5:$D$129,$A35,Kundenliste!$X$5:$X$129,"A") -> 4 | C35: =COUNTIFS(Kundenliste!$D$5:$D$129,$A35,Kundenliste!$X$5:$X$129,"B") -> 12 | D35: =COUNTIFS(Kundenliste!$D$5:$D$129,$A35,Kundenliste!$X$5:$X$129,"C") -> 0 | E35: =SUM(B35:D35) -> 16 | F35: =IFERROR(AVERAGEIF(Kundenliste!$D$5:$D$129,$A35,Kundenliste!$U$5:$U$129),0) -> 3.675
A36: Elektroplaner | B36: =COUNTIFS(Kundenliste!$D$5:$D$129,$A36,Kundenliste!$X$5:$X$129,"A") -> 1 | C36: =COUNTIFS(Kundenliste!$D$5:$D$129,$A36,Kundenliste!$X$5:$X$129,"B") -> 8 | D36: =COUNTIFS(Kundenliste!$D$5:$D$129,$A36,Kundenliste!$X$5:$X$129,"C") -> 3 | E36: =SUM(B36:D36) -> 12 | F36: =IFERROR(AVERAGEIF(Kundenliste!$D$5:$D$129,$A36,Kundenliste!$U$5:$U$129),0) -> 3.3
A37: GU/TU | B37: =COUNTIFS(Kundenliste!$D$5:$D$129,$A37,Kundenliste!$X$5:$X$129,"A") -> 5 | C37: =COUNTIFS(Kundenliste!$D$5:$D$129,$A37,Kundenliste!$X$5:$X$129,"B") -> 5 | D37: =COUNTIFS(Kundenliste!$D$5:$D$129,$A37,Kundenliste!$X$5:$X$129,"C") -> 1 | E37: =SUM(B37:D37) -> 11 | F37: =IFERROR(AVERAGEIF(Kundenliste!$D$5:$D$129,$A37,Kundenliste!$U$5:$U$129),0) -> 3.8045455
A38: Rechenzentrum | B38: =COUNTIFS(Kundenliste!$D$5:$D$129,$A38,Kundenliste!$X$5:$X$129,"A") -> 6 | C38: =COUNTIFS(Kundenliste!$D$5:$D$129,$A38,Kundenliste!$X$5:$X$129,"B") -> 5 | D38: =COUNTIFS(Kundenliste!$D$5:$D$129,$A38,Kundenliste!$X$5:$X$129,"C") -> 1 | E38: =SUM(B38:D38) -> 12 | F38: =IFERROR(AVERAGEIF(Kundenliste!$D$5:$D$129,$A38,Kundenliste!$U$5:$U$129),0) -> 3.9083333
A39: Industrie | B39: =COUNTIFS(Kundenliste!$D$5:$D$129,$A39,Kundenliste!$X$5:$X$129,"A") -> 3 | C39: =COUNTIFS(Kundenliste!$D$5:$D$129,$A39,Kundenliste!$X$5:$X$129,"B") -> 3 | D39: =COUNTIFS(Kundenliste!$D$5:$D$129,$A39,Kundenliste!$X$5:$X$129,"C") -> 4 | E39: =SUM(B39:D39) -> 10 | F39: =IFERROR(AVERAGEIF(Kundenliste!$D$5:$D$129,$A39,Kundenliste!$U$5:$U$129),0) -> 3.23
A40: Spital | B40: =COUNTIFS(Kundenliste!$D$5:$D$129,$A40,Kundenliste!$X$5:$X$129,"A") -> 1 | C40: =COUNTIFS(Kundenliste!$D$5:$D$129,$A40,Kundenliste!$X$5:$X$129,"B") -> 4 | D40: =COUNTIFS(Kundenliste!$D$5:$D$129,$A40,Kundenliste!$X$5:$X$129,"C") -> 0 | E40: =SUM(B40:D40) -> 5 | F40: =IFERROR(AVERAGEIF(Kundenliste!$D$5:$D$129,$A40,Kundenliste!$U$5:$U$129),0) -> 3.5
A41: Infrastruktur | B41: =COUNTIFS(Kundenliste!$D$5:$D$129,$A41,Kundenliste!$X$5:$X$129,"A") -> 2 | C41: =COUNTIFS(Kundenliste!$D$5:$D$129,$A41,Kundenliste!$X$5:$X$129,"B") -> 1 | D41: =COUNTIFS(Kundenliste!$D$5:$D$129,$A41,Kundenliste!$X$5:$X$129,"C") -> 0 | E41: =SUM(B41:D41) -> 3 | F41: =IFERROR(AVERAGEIF(Kundenliste!$D$5:$D$129,$A41,Kundenliste!$U$5:$U$129),0) -> 3.8166667
A42: Event | B42: =COUNTIFS(Kundenliste!$D$5:$D$129,$A42,Kundenliste!$X$5:$X$129,"A") -> 1 | C42: =COUNTIFS(Kundenliste!$D$5:$D$129,$A42,Kundenliste!$X$5:$X$129,"B") -> 6 | D42: =COUNTIFS(Kundenliste!$D$5:$D$129,$A42,Kundenliste!$X$5:$X$129,"C") -> 0 | E42: =SUM(B42:D42) -> 7 | F42: =IFERROR(AVERAGEIF(Kundenliste!$D$5:$D$129,$A42,Kundenliste!$U$5:$U$129),0) -> 3.7
A44: Kundenstatus MiT (aus CRM zu befüllen)
A45: Status | B45: Anzahl | C45: davon Prio A
A46: Offen: CRM prüfen | B46: =COUNTIF(Kundenliste!$Y$5:$Y$129,$A46) -> 125 | C46: =COUNTIFS(Kundenliste!$Y$5:$Y$129,$A46,Kundenliste!$X$5:$X$129,"A") -> 36
A47: A-Kunde | B47: =COUNTIF(Kundenliste!$Y$5:$Y$129,$A47) -> 0 | C47: =COUNTIFS(Kundenliste!$Y$5:$Y$129,$A47,Kundenliste!$X$5:$X$129,"A") -> 0
A48: Bestandskunde mit Potenzial | B48: =COUNTIF(Kundenliste!$Y$5:$Y$129,$A48) -> 0 | C48: =COUNTIFS(Kundenliste!$Y$5:$Y$129,$A48,Kundenliste!$X$5:$X$129,"A") -> 0
A49: Verlorener Kunde | B49: =COUNTIF(Kundenliste!$Y$5:$Y$129,$A49) -> 0 | C49: =COUNTIFS(Kundenliste!$Y$5:$Y$129,$A49,Kundenliste!$X$5:$X$129,"A") -> 0
A50: Potenzial / Aufbau | B50: =COUNTIF(Kundenliste!$Y$5:$Y$129,$A50) -> 0 | C50: =COUNTIFS(Kundenliste!$Y$5:$Y$129,$A50,Kundenliste!$X$5:$X$129,"A") -> 0

Sheet Kundenliste
A1: Zielkundenliste Schweiz: Mobile Energie (Generator, BESS, USV, Trafo, NEA, PQ, Baustrom, Event)
A2: Stand 27.09.2026 | 125 Firmen | Kernliste 70 (60/20/20) | Score und Prio rechnen aus Blatt «Methodik» | VERTRAULICH
A3: Blaue Spalten Q-T (Fit/Volumen/Timing/Zugang) sowie Prio final, Kundenstatus, Ansprechperson, Verantwortlich, nächster Schritt und Datum sind Eingabefelder.
A4: ID | B4: Kernliste Top 70 | C4: Segment | D4: Kategorie | E4: Firma | F4: Gruppe / Mutter | G4: Ort | H4: Kt. | I4: Region | J4: Gebiet | K4: Sprache | L4: Website | M4: Grösse | N4: Anlass / Projekt 2025-2027 | O4: MiT-Leistungen | P4: Warum (Begründung) | Q4: Fit | R4: Volumen | S4: Timing | T4: Zugang | U4: Score | V4: Prio Vorschlag | W4: Prio final | X4: Prio | Y4: Kundenstatus MiT | Z4: Verloren seit | AA4: Zielrolle Ansprechperson | AB4: Ansprechperson (Name) | AC4: GL öffentlich (Quelle) | AD4: LinkedIn Firma | AE4: LinkedIn Personen | AF4: Quelle | AG4: Validierung / Hinweis | AH4: Verantwortlich | AI4: Nächster Schritt | AJ4: Datum nächster Schritt | AK4: Letzter Kontakt
A5: CH-001 | B5: Ja | C5: Installateure (60 %) | D5: Installateur | E5: Burkhalter Gruppe (Holding) | F5: börsenkotiert | G5: Zürich | H5: ZH | I5: Zürich | J5: Deutschschweiz | K5: DE | L5: burkhalter.ch | M5: 5'356 FTE, 83 Gesellschaften, 169 Standorte (31.12.2025) | N5: Kein spezifischer Anlass recherchiert | O5: Baustrom, Generator, USV, NEA-Test | P5: Grösster Elektroinstallateur CH. Ein Rahmenvertrag öffnet Dutzende Töchter (u.a. Sedelec, Mérinat, EAGB, Hufschmid, Celio, Grichting & Valterio). | Q5: 5 | R5: 5 | S5: 4 | T5: 3 | U5: =ROUND(Q5*Methodik!$B$5+R5*Methodik!$B$6+S5*Methodik!$B$7+T5*Methodik!$B$8,2) -> 4.45 | V5: =IF(U5>=Methodik!$B$11,"A",IF(U5>=Methodik!$B$12,"B","C")) -> A | X5: =IF(W5="",V5,W5) -> A | Y5: Offen: CRM prüfen | AA5: Leiter Grossprojekte / Bereichsleiter Baustrom / Einkauf | AC5: CEO Zeno Böhm (Moneycab) | AD5: Suche öffnen | AE5: Suche öffnen | AF5: Link
A6: CH-002 | B6: Ja | C6: Installateure (60 %) | D6: Installateur | E6: ETAVIS AG | F6: VINCI Energies | G6: Zürich | H6: ZH | I6: Zürich | J6: Deutschschweiz | K6: DE | L6: etavis.ch | M6: >2'400 MA | N6: Kein spezifischer Anlass recherchiert | O6: Baustrom, Generator, USV, NEA-Test | P6: Landesweit in Infrastruktur (Flughafen, Tunnel, Bahn) und Rechenzentren. Zugang zu VINCI-Schwestern (Actemium, Gfeller). | Q6: 5 | R6: 5 | S6: 4 | T6: 3 | U6: =ROUND(Q6*Methodik!$B$5+R6*Methodik!$B$6+S6*Methodik!$B$7+T6*Methodik!$B$8,2) -> 4.45 | V6: =IF(U6>=Methodik!$B$11,"A",IF(U6>=Methodik!$B$12,"B","C")) -> A | X6: =IF(W6="",V6,W6) -> A | Y6: Offen: CRM prüfen | AA6: Leiter Grossprojekte / Bereichsleiter Baustrom / Einkauf | AD6: Suche öffnen | AE6: Suche öffnen | AF6: Link
A7: CH-003 | B7: Ja | C7: Installateure (60 %) | D7: Installateur | E7: Equans Switzerland AG | F7: Bouygues (ex Bouygues E&S InTec / Alpiq InTec) | G7: Zürich | H7: ZH | I7: Zürich | J7: Deutschschweiz | K7: DE | L7: equans.ch | M7: >1'600 MA, >20 Standorte (Broschüre 2025, Zahl prüfen) | N7: Kein spezifischer Anlass recherchiert | O7: Generator, Trafo, NEA-Test, USV, Baustrom | P7: Energie, Verkehr, Industrie und FM unter einem Dach: NEA-Tests, Service-Unterbrüche, temporäre Einspeisung. | Q7: 5 | R7: 5 | S7: 4 | T7: 3 | U7: =ROUND(Q7*Methodik!$B$5+R7*Methodik!$B$6+S7*Methodik!$B$7+T7*Methodik!$B$8,2) -> 4.45 | V7: =IF(U7>=Methodik!$B$11,"A",IF(U7>=Methodik!$B$12,"B","C")) -> A | X7: =IF(W7="",V7,W7) -> A | Y7: Offen: CRM prüfen | AA7: Leiter Grossprojekte / Bereichsleiter Baustrom / Einkauf | AD7: Suche öffnen | AE7: Suche öffnen | AF7: Link | AG7: Seit 07/2024 unter diesem Namen. MA-Zahl wirkt tief, prüfen.
A8: CH-004 | B8: Ja | C8: Installateure (60 %) | D8: Installateur | E8: BKW Building Solutions AG | F8: BKW | G8: Ostermundigen | H8: BE | I8: Mittelland/Bern | J8: Deutschschweiz | K8: DE/FR | L8: bkw.ch | M8: ca. 4'000 MA in ca. 50 Firmen | N8: Kein spezifischer Anlass recherchiert | O8: Baustrom, BESS, Generator | P8: Dach von AEK, ISP, swisspro, Arnold, inelectro. Zentraler Einkaufsrahmen für Baustrom und BESS. | Q8: 5 | R8: 5 | S8: 3 | T8: 3 | U8: =ROUND(Q8*Methodik!$B$5+R8*Methodik!$B$6+S8*Methodik!$B$7+T8*Methodik!$B$8,2) -> 4.2 | V8: =IF(U8>=Methodik!$B$11,"A",IF(U8>=Methodik!$B$12,"B","C")) -> A | X8: =IF(W8="",V8,W8) -> A | Y8: Offen: CRM prüfen | AA8: Leiter Grossprojekte / Bereichsleiter Baustrom / Einkauf | AD8: Suche öffnen | AE8: Suche öffnen | AF8: Link | AG8: BKW ist Lauberhorn-Sponsor: Nähe zu Energiethemen, evtl. Eigenlösungen.
A9: CH-005 | B9: Ja | C9: Installateure (60 %) | D9: Installateur | E9: Actemium Schweiz AG | F9: VINCI Energies (ex Cegelec) | G9: Ittigen | H9: BE | I9: Mittelland/Bern | J9: Deutschschweiz | K9: DE/FR | L9: actemium.ch | M9: ca. 930 MA (prüfen) | N9: Kein spezifischer Anlass recherchiert | O9: Generator, Lastbank/NEA-Test, Trafo, USV | P9: Industrieautomation und Prozessanlagen: Shutdowns, Inbetriebnahmen, Lastbanktests. | Q9: 5 | R9: 4 | S9: 4 | T9: 3 | U9: =ROUND(Q9*Methodik!$B$5+R9*Methodik!$B$6+S9*Methodik!$B$7+T9*Methodik!$B$8,2) -> 4.15 | V9: =IF(U9>=Methodik!$B$11,"A",IF(U9>=Methodik!$B$12,"B","C")) -> A | X9: =IF(W9="",V9,W9) -> A | Y9: Offen: CRM prüfen | AA9: Leiter Grossprojekte / Bereichsleiter Baustrom / Einkauf | AD9: Suche öffnen | AE9: Suche öffnen | AF9: Link
A10: CH-006 | B10: Ja | C10: Installateure (60 %) | D10: Installateur | E10: Arnold AG | F10: BKW (Infra Services) | G10: Wangen an der Aare | H10: BE | I10: Mittelland/Bern | J10: Deutschschweiz | K10: DE | L10: arnold.ch | M10: ca. 1'000 MA Infra-Services-Gruppe | N10: Kein spezifischer Anlass recherchiert | O10: Trafo, Generator, Netzersatz | P10: Hochspannungs- und Kabelnetzbau: Ersatzversorgung bei Netzumbauten, Trafo-Miete. | Q10: 5 | R10: 4 | S10: 4 | T10: 3 | U10: =ROUND(Q10*Methodik!$B$5+R10*Methodik!$B$6+S10*Methodik!$B$7+T10*Methodik!$B$8,2) -> 4.15 | V10: =IF(U10>=Methodik!$B$11,"A",IF(U10>=Methodik!$B$12,"B","C")) -> A | X10: =IF(W10="",V10,W10) -> A | Y10: Offen: CRM prüfen | AA10: Leiter Grossprojekte / Bereichsleiter Baustrom / Einkauf | AD10: Suche öffnen | AE10: Suche öffnen | AF10: Link
A11: CH-007 | B11: Ja | C11: Installateure (60 %) | D11: Installateur | E11: CKW Gebäudetechnik AG | F11: CKW / Axpo | G11: Luzern | H11: LU | I11: Zentralschweiz | J11: Deutschschweiz | K11: DE | L11: ckw.ch | M11: ca. 1'400 MA, 60 Standorte | N11: Kein spezifischer Anlass recherchiert | O11: Baustrom, Generator, BESS | P11: Grösster Installateur Zentralschweiz mit eigenen Grossbaustellen-Teams. | Q11: 5 | R11: 4 | S11: 4 | T11: 3 | U11: =ROUND(Q11*Methodik!$B$5+R11*Methodik!$B$6+S11*Methodik!$B$7+T11*Methodik!$B$8,2) -> 4.15 | V11: =IF(U11>=Methodik!$B$11,"A",IF(U11>=Methodik!$B$12,"B","C")) -> A | X11: =IF(W11="",V11,W11) -> A | Y11: Offen: CRM prüfen | AA11: Leiter Grossprojekte / Bereichsleiter Baustrom / Einkauf | AD11: Suche öffnen | AE11: Suche öffnen | AF11: Link | AG11: Firmenname (ex CKW Conex) prüfen.
A12: CH-008 | B12: Ja | C12: Installateure (60 %) | D12: Installateur | E12: EKZ Eltop AG | F12: EKZ | G12: Fahrweid (Weiningen) | H12: ZH | I12: Zürich | J12: Deutschschweiz | K12: DE | L12: ekzeltop.ch | M12: ca. 550 MA, ca. 40 Standorte | N12: Kein spezifischer Anlass recherchiert | O12: Baustrom, BESS, Generator | P12: Flächendeckend im Kanton ZH, PV und Speicher im Portfolio. | Q12: 5 | R12: 4 | S12: 4 | T12: 3 | U12: =ROUND(Q12*Methodik!$B$5+R12*Methodik!$B$6+S12*Methodik!$B$7+T12*Methodik!$B$8,2) -> 4.15 | V12: =IF(U12>=Methodik!$B$11,"A",IF(U12>=Methodik!$B$12,"B","C")) -> A | X12: =IF(W12="",V12,W12) -> A | Y12: Offen: CRM prüfen | AA12: Leiter Grossprojekte / Bereichsleiter Baustrom / Einkauf | AC12: CEO Claudio Gallo (EKZ-MM 2023, Aktualität prüfen) | AD12: Suche öffnen | AE12: Suche öffnen | AF12: Link
A13: CH-009 | B13: Ja | C13: Installateure (60 %) | D13: Installateur | E13: ETAVIS Kriegel+Schaffner AG | F13: VINCI Energies / ETAVIS | G13: Basel | H13: BS | I13: Nordwestschweiz | J13: Deutschschweiz | K13: DE | L13: etavis.ch | M13: ca. 700 MA Region NWCH (prüfen) | N13: Pharma-Grossprojekte Basel (Roche Bau 12, Bachem) | O13: USV, Generator, NEA-Test, Trafo | P13: Pharma und Chemie Basel: Shutdowns, Umbauten unter GMP, hohe Ausfallkosten beim Endkunden. | Q13: 5 | R13: 4 | S13: 4 | T13: 3 | U13: =ROUND(Q13*Methodik!$B$5+R13*Methodik!$B$6+S13*Methodik!$B$7+T13*Methodik!$B$8,2) -> 4.15 | V13: =IF(U13>=Methodik!$B$11,"A",IF(U13>=Methodik!$B$12,"B","C")) -> A | X13: =IF(W13="",V13,W13) -> A | Y13: Offen: CRM prüfen | AA13: Leiter Grossprojekte / Bereichsleiter Baustrom / Einkauf | AD13: Suche öffnen | AE13: Suche öffnen | AF13: Link
A14: CH-010 | B14: Ja | C14: Installateure (60 %) | D14: Installateur | E14: Egg-Telsa SA | F14: unabhängig (prüfen) | G14: Genève | H14: GE | I14: West (Romandie) | J14: West | K14: FR | L14: eggtelsa.com | M14: 300 bis knapp 500 MA | N14: Cap2030 Genève Aéroport (2026-2032) | O14: Baustrom, Event, Generator, USV | P14: Grösster unabhängiger Installateur in Genf: Baustrom, Events, internationale Organisationen. | Q14: 5 | R14: 4 | S14: 4 | T14: 3 | U14: =ROUND(Q14*Methodik!$B$5+R14*Methodik!$B$6+S14*Methodik!$B$7+T14*Methodik!$B$8,2) -> 4.15 | V14: =IF(U14>=Methodik!$B$11,"A",IF(U14>=Methodik!$B$12,"B","C")) -> A | X14: =IF(W14="",V14,W14) -> A | Y14: Offen: CRM prüfen | AA14: Leiter Grossprojekte / Bereichsleiter Baustrom / Einkauf | AD14: Suche öffnen | AE14: Suche öffnen | AF14: Link
A15: CH-011 | B15: Ja | C15: Installateure (60 %) | D15: Installateur | E15: Selmoni Gruppe | F15: unabhängig (prüfen) | G15: Münchenstein | H15: BL | I15: Nordwestschweiz | J15: Deutschschweiz | K15: DE | L15: selmoni.ch | M15: ca. 600 MA | N15: Life-Sciences-Projekte Basel | O15: USV, NEA-Test, Generator | P15: Life Sciences Basel, Verteilbau: USV, NEA, Shutdowns. | Q15: 5 | R15: 4 | S15: 4 | T15: 3 | U15: =ROUND(Q15*Methodik!$B$5+R15*Methodik!$B$6+S15*Methodik!$B$7+T15*Methodik!$B$8,2) -> 4.15 | V15: =IF(U15>=Methodik!$B$11,"A",IF(U15>=Methodik!$B$12,"B","C")) -> A | X15: =IF(W15="",V15,W15) -> A | Y15: Offen: CRM prüfen | AA15: Leiter Grossprojekte / Bereichsleiter Baustrom / Einkauf | AD15: Suche öffnen | AE15: Suche öffnen | AF15: Link | AG15: CEO-Name nur aus Suche, nicht verifiziert.
A16: CH-012 | B16: Ja | C16: Installateure (60 %) | D16: Installateur | E16: cablex AG | F16: Swisscom | G16: Gümligen | H16: BE | I16: Mittelland/Bern | J16: Deutschschweiz | K16: DE/FR/IT | L16: cablex.ch | M16: ca. 2'300 MA | N16: Kein spezifischer Anlass recherchiert | O16: BESS, Generator, USV | P16: Netzinfrastruktur und Mobilfunk landesweit: Notstrom für Antennen und Knoten, BESS für Umbauten. | Q16: 5 | R16: 4 | S16: 3 | T16: 3 | U16: =ROUND(Q16*Methodik!$B$5+R16*Methodik!$B$6+S16*Methodik!$B$7+T16*Methodik!$B$8,2) -> 3.9 | V16: =IF(U16>=Methodik!$B$11,"A",IF(U16>=Methodik!$B$12,"B","C")) -> B | X16: =IF(W16="",V16,W16) -> B | Y16: Offen: CRM prüfen | AA16: Leiter Grossprojekte / Bereichsleiter Baustrom / Einkauf | AC16: CEO Roger Keller (seit 01.01.2025, cablex.ch) | AD16: Suche öffnen | AE16: Suche öffnen | AF16: Link
A17: CH-013 | B17: Ja | C17: Installateure (60 %) | D17: Installateur | E17: Alpine-Energie Schweiz AG | F17: ALPINE-ENERGIE Gruppe (DE/AT) | G17: Oftringen | H17: AG | I17: Nordwestschweiz | J17: Deutschschweiz | K17: DE | L17: prüfen | M17: k.A. | N17: Kein spezifischer Anlass recherchiert | O17: Generator, Trafo | P17: Freileitung, Fahrleitung, Tunnel: mobile Energie auf Linienbaustellen. | Q17: 5 | R17: 3 | S17: 4 | T17: 3 | U17: =ROUND(Q17*Methodik!$B$5+R17*Methodik!$B$6+S17*Methodik!$B$7+T17*Methodik!$B$8,2) -> 3.85 | V17: =IF(U17>=Methodik!$B$11,"A",IF(U17>=Methodik!$B$12,"B","C")) -> B | X17: =IF(W17="",V17,W17) -> B | Y17: Offen: CRM prüfen | AA17: Leiter Grossprojekte / Bereichsleiter Baustrom / Einkauf | AD17: Suche öffnen | AE17: Suche öffnen | AF17: Link | AG17: Website prüfen.
A18: CH-014 | B18: Ja | C18: Installateure (60 %) | D18: Installateur | E18: Baumann Koelliker Gruppe | F18: unabhängig (Familie) | G18: Zürich | H18: ZH | I18: Zürich | J18: Deutschschweiz | K18: DE | L18: baumann-koelliker-gruppe.ch | M18: 1'250 MA, 16-17 Firmen | N18: Kein spezifischer Anlass recherchiert | O18: Baustrom, Generator | P18: Viele Grossbaustellen in ZH: Baustrom-Rahmenvertrag. | Q18: 4 | R18: 4 | S18: 4 | T18: 3 | U18: =ROUND(Q18*Methodik!$B$5+R18*Methodik!$B$6+S18*Methodik!$B$7+T18*Methodik!$B$8,2) -> 3.85 | V18: =IF(U18>=Methodik!$B$11,"A",IF(U18>=Methodik!$B$12,"B","C")) -> B | X18: =IF(W18="",V18,W18) -> B | Y18: Offen: CRM prüfen | AA18: Leiter Grossprojekte / Bereichsleiter Baustrom / Einkauf | AD18: Suche öffnen | AE18: Suche öffnen | AF18: Link
A19: CH-015 | B19: Ja | C19: Installateure (60 %) | D19: Installateur | E19: Grichting & Valterio Electro SA | F19: Burkhalter (seit 2009) | G19: Sion | H19: VS | I19: West (Romandie) | J19: West | K19: FR/DE | L19: grichting-valterio.ch | M19: 104-170 MA (uneinheitlich) | N19: Lonza Visp Ramp-up 2026 | O19: Baustrom, NEA-Test, Generator | P19: Walliser Industrie (Lonza-Umfeld) und Infrastruktur. | Q19: 5 | R19: 3 | S19: 4 | T19: 3 | U19: =ROUND(Q19*Methodik!$B$5+R19*Methodik!$B$6+S19*Methodik!$B$7+T19*Methodik!$B$8,2) -> 3.85 | V19: =IF(U19>=Methodik!$B$11,"A",IF(U19>=Methodik!$B$12,"B","C")) -> B | X19: =IF(W19="",V19,W19) -> B | Y19: Offen: CRM prüfen | AA19: Leiter Grossprojekte / Bereichsleiter Baustrom / Einkauf | AD19: Suche öffnen | AE19: Suche öffnen | AF19: Link
A20: CH-016 | B20: Ja | C20: Installateure (60 %) | D20: Installateur | E20: Sedelec SA | F20: Burkhalter | G20: Carouge | H20: GE | I20: West (Romandie) | J20: West | K20: FR | L20: sedelec-geneve.ch | M20: >200 MA | N20: Kein spezifischer Anlass recherchiert | O20: Baustrom, USV | P20: Genfer Grossbaustellen, dazu Sedelec Lausanne. | Q20: 4 | R20: 4 | S20: 4 | T20: 3 | U20: =ROUND(Q20*Methodik!$B$5+R20*Methodik!$B$6+S20*Methodik!$B$7+T20*Methodik!$B$8,2) -> 3.85 | V20: =IF(U20>=Methodik!$B$11,"A",IF(U20>=Methodik!$B$12,"B","C")) -> B | X20: =IF(W20="",V20,W20) -> B | Y20: Offen: CRM prüfen | AA20: Leiter Grossprojekte / Bereichsleiter Baustrom / Einkauf | AD20: Suche öffnen | AE20: Suche öffnen | AF20: Link
A21: CH-017 | B21: Ja | C21: Installateure (60 %) | D21: Installateur | E21: Elektro Compagnoni AG | F21: unabhängig (Familie, 2. Generation) | G21: Zürich | H21: ZH | I21: Zürich | J21: Deutschschweiz | K21: DE | L21: elektro-compagnoni.ch | M21: ca. 140 MA | N21: Kein spezifischer Anlass recherchiert | O21: Trafo, NEA-Test, Generator | P21: Hochspannung, Schaltanlagen, Telecom: direkter Bedarf an Trafo-Miete und NEA. | Q21: 5 | R21: 3 | S21: 3 | T21: 4 | U21: =ROUND(Q21*Methodik!$B$5+R21*Methodik!$B$6+S21*Methodik!$B$7+T21*Methodik!$B$8,2) -> 3.75 | V21: =IF(U21>=Methodik!$B$11,"A",IF(U21>=Methodik!$B$12,"B","C")) -> B | X21: =IF(W21="",V21,W21) -> B | Y21: Offen: CRM prüfen | AA21: Leiter Grossprojekte / Bereichsleiter Baustrom / Einkauf | AD21: Suche öffnen | AE21: Suche öffnen | AF21: Link | AG21: Keine Burkhalter-Tochter.
A22: CH-018 | B22: Ja | C22: Installateure (60 %) | D22: Installateur | E22: ETAVIS Grossenbacher AG | F22: VINCI Energies / ETAVIS | G22: St. Gallen | H22: SG | I22: Ostschweiz | J22: Deutschschweiz | K22: DE | L22: etavis.ch | M22: k.A. | N22: Kein spezifischer Anlass recherchiert | O22: Baustrom, Generator | P22: Ostschweizer Grossbaustellen und Industrie, Einstieg über ETAVIS-Rahmen. | Q22: 4 | R22: 4 | S22: 3 | T22: 3 | U22: =ROUND(Q22*Methodik!$B$5+R22*Methodik!$B$6+S22*Methodik!$B$7+T22*Methodik!$B$8,2) -> 3.6 | V22: =IF(U22>=Methodik!$B$11,"A",IF(U22>=Methodik!$B$12,"B","C")) -> B | X22: =IF(W22="",V22,W22) -> B | Y22: Offen: CRM prüfen | AA22: Leiter Grossprojekte / Bereichsleiter Baustrom / Einkauf | AD22: Suche öffnen | AE22: Suche öffnen | AF22: Link
A23: CH-019 | B23: Ja | C23: Installateure (60 %) | D23: Installateur | E23: Groupe E Connect SA | F23: Groupe E | G23: Granges-Paccot / Matran | H23: FR | I23: West (Romandie) | J23: West | K23: FR/DE | L23: groupe-e.ch | M23: 880 MA, 12 Filialen FR/VD/VS/GE | N23: Groupe E baut 2025 rund 188 Stellen ab | O23: Baustrom, Generator | P23: Grossbaustellen Romandie: Baustrom, Tableaux. | Q23: 4 | R23: 4 | S23: 3 | T23: 3 | U23: =ROUND(Q23*Methodik!$B$5+R23*Methodik!$B$6+S23*Methodik!$B$7+T23*Methodik!$B$8,2) -> 3.6 | V23: =IF(U23>=Methodik!$B$11,"A",IF(U23>=Methodik!$B$12,"B","C")) -> B | X23: =IF(W23="",V23,W23) -> B | Y23: Offen: CRM prüfen | AA23: Leiter Grossprojekte / Bereichsleiter Baustrom / Einkauf | AC23: CEO Mutter Groupe E: Alain Sapin | AD23: Suche öffnen | AE23: Suche öffnen | AF23: Link | AG23: Restrukturierung: Kostendruck.
A24: CH-020 | B24: Ja | C24: Installateure (60 %) | D24: Installateur | E24: Kummler+Matter EVT AG | F24: Equans Switzerland (inkl. Mauerhofer & Zuber) | G24: Zürich | H24: ZH | I24: Zürich | J24: Deutschschweiz | K24: DE/FR | L24: kuma-evt.ch | M24: k.A. | N24: Kein spezifischer Anlass recherchiert | O24: Generator, BESS, Trafo | P24: Netz- und Freileitungsbau, Bahnstrom. Hat eigene mobile Trafostationen: Partner bei Spitzen, zugleich Wettbewerber. | Q24: 4 | R24: 4 | S24: 3 | T24: 3 | U24: =ROUND(Q24*Methodik!$B$5+R24*Methodik!$B$6+S24*Methodik!$B$7+T24*Methodik!$B$8,2) -> 3.6 | V24: =IF(U24>=Methodik!$B$11,"A",IF(U24>=Methodik!$B$12,"B","C")) -> B | X24: =IF(W24="",V24,W24) -> B | Y24: Offen: CRM prüfen | AA24: Leiter Grossprojekte / Bereichsleiter Baustrom / Einkauf | AD24: Suche öffnen | AE24: Suche öffnen | AF24: Link | AG24: Partner- oder Wettbewerberrolle intern klären.
A25: CH-021 | B25: Ja | C25: Installateure (60 %) | D25: Installateur | E25: Maréchaux Elektro AG / Gruppe | F25: unabhängig (Familie) | G25: Luzern | H25: LU | I25: Zentralschweiz | J25: Deutschschweiz | K25: DE | L25: marechaux.ch | M25: ca. 1'000 MA Gruppe, davon 750 Elektro | N25: Kein spezifischer Anlass recherchiert | O25: Baustrom, Generator | P25: Grösster unabhängiger Anbieter Zentralschweiz, Grossprojekte. | Q25: 4 | R25: 4 | S25: 3 | T25: 3 | U25: =ROUND(Q25*Methodik!$B$5+R25*Methodik!$B$6+S25*Methodik!$B$7+T25*Methodik!$B$8,2) -> 3.6 | V25: =IF(U25>=Methodik!$B$11,"A",IF(U25>=Methodik!$B$12,"B","C")) -> B | X25: =IF(W25="",V25,W25) -> B | Y25: Offen: CRM prüfen | AA25: Leiter Grossprojekte / Bereichsleiter Baustrom / Einkauf | AD25: Suche öffnen | AE25: Suche öffnen | AF25: Link
A26: CH-022 | B26: Ja | C26: Installateure (60 %) | D26: Installateur | E26: ETAVIS Elettro-Impianti SA | F26: VINCI Energies / ETAVIS | G26: Pregassona-Lugano | H26: TI | I26: Tessin | J26: Tessin | K26: IT | L26: etavis.ch/it | M26: k.A. | N26: 2. Gotthardröhre Süd (Airolo) im Umfeld | O26: Baustrom, Generator, Trafo | P26: Tessiner Grossprojekte und Tunnel. Einer der wenigen grösseren Installateure im Tessin. | Q26: 4 | R26: 3 | S26: 4 | T26: 3 | U26: =ROUND(Q26*Methodik!$B$5+R26*Methodik!$B$6+S26*Methodik!$B$7+T26*Methodik!$B$8,2) -> 3.55 | V26: =IF(U26>=Methodik!$B$11,"A",IF(U26>=Methodik!$B$12,"B","C")) -> B | X26: =IF(W26="",V26,W26) -> B | Y26: Offen: CRM prüfen | AA26: Leiter Grossprojekte / Bereichsleiter Baustrom / Einkauf | AD26: Suche öffnen | AE26: Suche öffnen | AF26: Link | AG26: Tunnelbezug unbestätigt.
A27: CH-023 | B27: Ja | C27: Installateure (60 %) | D27: Installateur | E27: AEK AG | F27: BKW (seit 2022) | G27: Solothurn | H27: SO | I27: Mittelland/Bern | J27: Deutschschweiz | K27: DE | L27: aek.ch | M27: ca. 250 MA | N27: Kein spezifischer Anlass recherchiert | O27: NEA-Test, Baustrom, Generator | P27: Industrie Solothurn (z.B. Grossauftrag Bell). | Q27: 4 | R27: 3 | S27: 3 | T27: 3 | U27: =ROUND(Q27*Methodik!$B$5+R27*Methodik!$B$6+S27*Methodik!$B$7+T27*Methodik!$B$8,2) -> 3.3 | V27: =IF(U27>=Methodik!$B$11,"A",IF(U27>=Methodik!$B$12,"B","C")) -> B | X27: =IF(W27="",V27,W27) -> B | Y27: Offen: CRM prüfen | AA27: Leiter Grossprojekte / Bereichsleiter Baustrom / Einkauf | AD27: Suche öffnen | AE27: Suche öffnen | AF27: Link
A28: CH-024 | B28: Ja | C28: Installateure (60 %) | D28: Installateur | E28: Elektrotechnik AG EAGB | F28: Burkhalter (seit 2020) | G28: Basel | H28: BS | I28: Nordwestschweiz | J28: Deutschschweiz | K28: DE | L28: eagb.ch | M28: ca. 175 MA | N28: Kein spezifischer Anlass recherchiert | O28: Generator, USV | P28: Basler Industrie und Spitäler: Notstrom und Überbrückung. | Q28: 4 | R28: 3 | S28: 3 | T28: 3 | U28: =ROUND(Q28*Methodik!$B$5+R28*Methodik!$B$6+S28*Methodik!$B$7+T28*Methodik!$B$8,2) -> 3.3 | V28: =IF(U28>=Methodik!$B$11,"A",IF(U28>=Methodik!$B$12,"B","C")) -> B | X28: =IF(W28="",V28,W28) -> B | Y28: Offen: CRM prüfen | AA28: Leiter Grossprojekte / Bereichsleiter Baustrom / Einkauf | AD28: Suche öffnen | AE28: Suche öffnen | AF28: Link
A29: CH-025 | B29: Ja | C29: Installateure (60 %) | D29: Installateur | E29: Ellenbroek Hugentobler AG | F29: unabhängig (prüfen) | G29: Frauenfeld | H29: TG | I29: Ostschweiz | J29: Deutschschweiz | K29: DE | L29: elhag.ch | M29: >160 MA | N29: Kein spezifischer Anlass recherchiert | O29: Netzersatz, Generator | P29: Leader im Thurgau inkl. Netzbau NS/MS: Netzersatz bei Kabelzug. | Q29: 4 | R29: 3 | S29: 3 | T29: 3 | U29: =ROUND(Q29*Methodik!$B$5+R29*Methodik!$B$6+S29*Methodik!$B$7+T29*Methodik!$B$8,2) -> 3.3 | V29: =IF(U29>=Methodik!$B$11,"A",IF(U29>=Methodik!$B$12,"B","C")) -> B | X29: =IF(W29="",V29,W29) -> B | Y29: Offen: CRM prüfen | AA29: Leiter Grossprojekte / Bereichsleiter Baustrom / Einkauf | AD29: Suche öffnen | AE29: Suche öffnen | AF29: Link
A30: CH-026 | B30: Ja | C30: Installateure (60 %) | D30: Installateur | E30: Jost Elektro AG Brugg | F30: unabhängig (Familie Bürgi) | G30: Brugg | H30: AG | I30: Nordwestschweiz | J30: Deutschschweiz | K30: DE | L30: jostelektro.ch | M30: ca. 200 MA | N30: Kein spezifischer Anlass recherchiert | O30: Baustrom, NEA-Test | P30: Aargauer Industrie und Kraftwerksumfeld. | Q30: 4 | R30: 3 | S30: 3 | T30: 3 | U30: =ROUND(Q30*Methodik!$B$5+R30*Methodik!$B$6+S30*Methodik!$B$7+T30*Methodik!$B$8,2) -> 3.3 | V30: =IF(U30>=Methodik!$B$11,"A",IF(U30>=Methodik!$B$12,"B","C")) -> B | X30: =IF(W30="",V30,W30) -> B | Y30: Offen: CRM prüfen | AA30: Leiter Grossprojekte / Bereichsleiter Baustrom / Einkauf | AD30: Suche öffnen | AE30: Suche öffnen | AF30: Link | AG30: Firma wurde laut AZ aufgeteilt: aktuelle Struktur prüfen.
A31: CH-027 | B31: Ja | C31: Installateure (60 %) | D31: Installateur | E31: Romande Energie Services SA | F31: Romande Energie | G31: Morges (prüfen) | H31: VD | I31: West (Romandie) | J31: West | K31: FR | L31: romande-energie.ch | M31: >200 MA | N31: Kein spezifischer Anlass recherchiert | O31: BESS, Generator, USV | P31: Industrie und Tertiär VD/FR/GE/VS/NE, PV und Speicher im Portfolio. | Q31: 4 | R31: 3 | S31: 3 | T31: 3 | U31: =ROUND(Q31*Methodik!$B$5+R31*Methodik!$B$6+S31*Methodik!$B$7+T31*Methodik!$B$8,2) -> 3.3 | V31: =IF(U31>=Methodik!$B$11,"A",IF(U31>=Methodik!$B$12,"B","C")) -> B | X31: =IF(W31="",V31,W31) -> B | Y31: Offen: CRM prüfen | AA31: Leiter Grossprojekte / Bereichsleiter Baustrom / Einkauf | AD31: Suche öffnen | AE31: Suche öffnen | AF31: Link
A32: CH-028 | B32: Ja | C32: Installateure (60 %) | D32: Installateur | E32: swisspro AG | F32: BKW (seit 2019) | G32: Urdorf | H32: ZH | I32: Zürich | J32: Deutschschweiz | K32: DE | L32: swisspro.ch | M32: ca. 430 MA (prüfen) | N32: Kein spezifischer Anlass recherchiert | O32: USV, BESS | P32: ICT und Gebäudeautomation: USV bei Rechenzentrums- und Netzumbauten. | Q32: 4 | R32: 3 | S32: 3 | T32: 3 | U32: =ROUND(Q32*Methodik!$B$5+R32*Methodik!$B$6+S32*Methodik!$B$7+T32*Methodik!$B$8,2) -> 3.3 | V32: =IF(U32>=Methodik!$B$11,"A",IF(U32>=Methodik!$B$12,"B","C")) -> B | X32: =IF(W32="",V32,W32) -> B | Y32: Offen: CRM prüfen | AA32: Leiter Grossprojekte / Bereichsleiter Baustrom / Einkauf | AD32: Suche öffnen | AE32: Suche öffnen | AF32: Link
A33: CH-029 | B33: Ja | C33: Installateure (60 %) | D33: Installateur | E33: Wenger + Wirz AG | F33: unabhängig | G33: Schaffhausen | H33: SH | I33: Ostschweiz | J33: Deutschschweiz | K33: DE | L33: wenger-wirz.ch | M33: ca. 130 MA (prüfen) | N33: STACK-Rechenzentrum Beringen SH (36 MW, Eröffnung 2026) | O33: PQ-Audit, Baustrom, Generator | P33: Nr. 1 in SH, macht Netzanalysen. Nähe zum RZ-Campus Beringen. | Q33: 4 | R33: 2 | S33: 4 | T33: 3 | U33: =ROUND(Q33*Methodik!$B$5+R33*Methodik!$B$6+S33*Methodik!$B$7+T33*Methodik!$B$8,2) -> 3.25 | V33: =IF(U33>=Methodik!$B$11,"A",IF(U33>=Methodik!$B$12,"B","C")) -> B | X33: =IF(W33="",V33,W33) -> B | Y33: Offen: CRM prüfen | AA33: Leiter Grossprojekte / Bereichsleiter Baustrom / Einkauf | AD33: Suche öffnen | AE33: Suche öffnen | AF33: Link | AG33: Beteiligung an STACK Beringen nicht belegt.
A34: CH-030 | B34: Ja | C34: Installateure (60 %) | D34: Installateur | E34: BKW ISP AG | F34: BKW | G34: Oberhofen am Thunersee (prüfen) | H34: BE | I34: Mittelland/Bern | J34: Deutschschweiz | K34: DE | L34: bkw.ch | M34: 200-499 MA (uneinheitlich) | N34: Kein spezifischer Anlass recherchiert | O34: Baustrom, Generator | P34: Elektroinstallation und PV im Raum Bern. | Q34: 3 | R34: 3 | S34: 3 | T34: 3 | U34: =ROUND(Q34*Methodik!$B$5+R34*Methodik!$B$6+S34*Methodik!$B$7+T34*Methodik!$B$8,2) -> 3 | V34: =IF(U34>=Methodik!$B$11,"A",IF(U34>=Methodik!$B$12,"B","C")) -> B | X34: =IF(W34="",V34,W34) -> B | Y34: Offen: CRM prüfen | AA34: Leiter Grossprojekte / Bereichsleiter Baustrom / Einkauf | AD34: Suche öffnen | AE34: Suche öffnen | AF34: Link | AG34: Sitz prüfen.
A35: CH-031 | B35: Ja | C35: Installateure (60 %) | D35: Installateur | E35: Elektro-Bau AG Rothrist | F35: k.A. | G35: Rothrist | H35: AG | I35: Nordwestschweiz | J35: Deutschschweiz | K35: DE | L35: elektro-bau.ch | M35: ca. 130 MA | N35: Kein spezifischer Anlass recherchiert | O35: Baustrom, Generator | P35: Logistik- und Industriebauten an der Mittelland-Achse. | Q35: 3 | R35: 3 | S35: 3 | T35: 3 | U35: =ROUND(Q35*Methodik!$B$5+R35*Methodik!$B$6+S35*Methodik!$B$7+T35*Methodik!$B$8,2) -> 3 | V35: =IF(U35>=Methodik!$B$11,"A",IF(U35>=Methodik!$B$12,"B","C")) -> B | X35: =IF(W35="",V35,W35) -> B | Y35: Offen: CRM prüfen | AA35: Leiter Grossprojekte / Bereichsleiter Baustrom / Einkauf | AD35: Suche öffnen | AE35: Suche öffnen | AF35: Link
A36: CH-032 | B36: Ja | C36: Installateure (60 %) | D36: Installateur | E36: Elettro-Celio SA | F36: Burkhalter | G36: Giubiasco | H36: TI | I36: Tessin | J36: Tessin | K36: IT | L36: celio.ch | M36: ca. 30 MA | N36: SBB-Frequenzumformer Giubiasco in Modernisierung | O36: Baustrom, Generator | P36: Sopraceneri und Mesolcina. | Q36: 3 | R36: 2 | S36: 4 | T36: 3 | U36: =ROUND(Q36*Methodik!$B$5+R36*Methodik!$B$6+S36*Methodik!$B$7+T36*Methodik!$B$8,2) -> 2.95 | V36: =IF(U36>=Methodik!$B$11,"A",IF(U36>=Methodik!$B$12,"B","C")) -> C | X36: =IF(W36="",V36,W36) -> C | Y36: Offen: CRM prüfen | AA36: Leiter Grossprojekte / Bereichsleiter Baustrom / Einkauf | AD36: Suche öffnen | AE36: Suche öffnen | AF36: Link
A37: CH-033 | B37: Ja | C37: Installateure (60 %) | D37: Installateur | E37: Mérinat SA | F37: Burkhalter (seit 2021) | G37: Vevey | H37: VD | I37: West (Romandie) | J37: West | K37: FR | L37: merinat.ch | M37: ca. 80 MA | N37: Montreux Jazz Festival in der Region | O37: Generator, Event | P37: Riviera, Hotellerie und Kliniken: Notstrom. | Q37: 3 | R37: 2 | S37: 4 | T37: 3 | U37: =ROUND(Q37*Methodik!$B$5+R37*Methodik!$B$6+S37*Methodik!$B$7+T37*Methodik!$B$8,2) -> 2.95 | V37: =IF(U37>=Methodik!$B$11,"A",IF(U37>=Methodik!$B$12,"B","C")) -> C | X37: =IF(W37="",V37,W37) -> C | Y37: Offen: CRM prüfen | AA37: Leiter Grossprojekte / Bereichsleiter Baustrom / Einkauf | AD37: Suche öffnen | AE37: Suche öffnen | AF37: Link
A38: CH-034 | B38: Ja | C38: Installateure (60 %) | D38: Installateur | E38: Gfeller Elektro AG | F38: VINCI Energies / ETAVIS (seit 2022) | G38: Bern | H38: BE | I38: Mittelland/Bern | J38: Deutschschweiz | K38: DE | L38: prüfen | M38: ca. 90-100 MA | N38: Kein spezifischer Anlass recherchiert | O38: Baustrom, Generator | P38: Gewerbe- und Verwaltungsbauten Bern. Kleinere Volumen, guter Zugang. | Q38: 3 | R38: 2 | S38: 3 | T38: 4 | U38: =ROUND(Q38*Methodik!$B$5+R38*Methodik!$B$6+S38*Methodik!$B$7+T38*Methodik!$B$8,2) -> 2.85 | V38: =IF(U38>=Methodik!$B$11,"A",IF(U38>=Methodik!$B$12,"B","C")) -> C | X38: =IF(W38="",V38,W38) -> C | Y38: Offen: CRM prüfen | AA38: Leiter Grossprojekte / Bereichsleiter Baustrom / Einkauf | AD38: Suche öffnen | AE38: Suche öffnen | AF38: Link
A39: CH-035 | B39: Ja | C39: Installateure (60 %) | D39: Installateur | E39: Scherler AG, Elektro und Telematik | F39: unabhängig (Familie) | G39: Bern | H39: BE | I39: Mittelland/Bern | J39: Deutschschweiz | K39: DE | L39: scherler-ag.ch | M39: k.A. | N39: Kein spezifischer Anlass recherchiert | O39: Baustrom, Generator | P39: Schaltanlagenbau und Installation Bern. | Q39: 3 | R39: 2 | S39: 3 | T39: 4 | U39: =ROUND(Q39*Methodik!$B$5+R39*Methodik!$B$6+S39*Methodik!$B$7+T39*Methodik!$B$8,2) -> 2.85 | V39: =IF(U39>=Methodik!$B$11,"A",IF(U39>=Methodik!$B$12,"B","C")) -> C | X39: =IF(W39="",V39,W39) -> C | Y39: Offen: CRM prüfen | AA39: Leiter Grossprojekte / Bereichsleiter Baustrom / Einkauf | AD39: Suche öffnen | AE39: Suche öffnen | AF39: Link | AG39: Nicht verwechseln mit SCHERLER AG Luzern (Planer).
A40: CH-036 | B40: Ja | C40: Installateure (60 %) | D40: Installateur | E40: Cauderay SA | F40: unabhängig | G40: Lausanne | H40: VD | I40: West (Romandie) | J40: West | K40: FR | L40: cauderay.com | M40: ca. 85 MA | N40: Kein spezifischer Anlass recherchiert | O40: Baustrom, Generator | P40: Gewerbe und Tertiär Lausanne. | Q40: 3 | R40: 2 | S40: 3 | T40: 3 | U40: =ROUND(Q40*Methodik!$B$5+R40*Methodik!$B$6+S40*Methodik!$B$7+T40*Methodik!$B$8,2) -> 2.7 | V40: =IF(U40>=Methodik!$B$11,"A",IF(U40>=Methodik!$B$12,"B","C")) -> C | X40: =IF(W40="",V40,W40) -> C | Y40: Offen: CRM prüfen | AA40: Leiter Grossprojekte / Bereichsleiter Baustrom / Einkauf | AD40: Suche öffnen | AE40: Suche öffnen | AF40: Link
A41: CH-037 | B41: Ja | C41: Installateure (60 %) | D41: Installateur | E41: EWS AG (Elektrizitätswerk Schwyz) | F41: Mehrheit CKW / Axpo | G41: Ibach | H41: SZ | I41: Zentralschweiz | J41: Deutschschweiz | K41: DE | L41: ews.ch | M41: 130-200 MA (uneinheitlich) | N41: Kein spezifischer Anlass recherchiert | O41: Netzersatz, Baustrom | P41: Netzbetreiber mit Installationsabteilung, deckt SZ ab. | Q41: 3 | R41: 2 | S41: 3 | T41: 3 | U41: =ROUND(Q41*Methodik!$B$5+R41*Methodik!$B$6+S41*Methodik!$B$7+T41*Methodik!$B$8,2) -> 2.7 | V41: =IF(U41>=Methodik!$B$11,"A",IF(U41>=Methodik!$B$12,"B","C")) -> C | X41: =IF(W41="",V41,W41) -> C | Y41: Offen: CRM prüfen | AA41: Leiter Grossprojekte / Bereichsleiter Baustrom / Einkauf | AD41: Suche öffnen | AE41: Suche öffnen | AF41: Link
A42: CH-038 | B42: Ja | C42: Installateure (60 %) | D42: Installateur | E42: Electrasim SA | F42: unabhängig | G42: Lugano / Balerna | H42: TI | I42: Tessin | J42: Tessin | K42: IT | L42: electrasim.ch | M42: 50 MA | N42: Kein spezifischer Anlass recherchiert | O42: USV, Generator | P42: Industrie-Tableaux und Automation im Tessin: USV, Shutdowns. | Q42: 3 | R42: 2 | S42: 3 | T42: 3 | U42: =ROUND(Q42*Methodik!$B$5+R42*Methodik!$B$6+S42*Methodik!$B$7+T42*Methodik!$B$8,2) -> 2.7 | V42: =IF(U42>=Methodik!$B$11,"A",IF(U42>=Methodik!$B$12,"B","C")) -> C | X42: =IF(W42="",V42,W42) -> C | Y42: Offen: CRM prüfen | AA42: Leiter Grossprojekte / Bereichsleiter Baustrom / Einkauf | AD42: Suche öffnen | AE42: Suche öffnen | AF42: Link
A43: CH-039 | B43: Ja | C43: Installateure (60 %) | D43: Installateur | E43: Groupe E Arc SA | F43: Groupe E (ex Vuilliomenet) | G43: Boudry | H43: NE | I43: West (Romandie) | J43: West | K43: FR | L43: groupe-e.ch | M43: >130 MA (prüfen) | N43: Kein spezifischer Anlass recherchiert | O43: USV, Generator | P43: Arc jurassien: Uhrenindustrie, USV bei Unterbrüchen. | Q43: 3 | R43: 2 | S43: 3 | T43: 3 | U43: =ROUND(Q43*Methodik!$B$5+R43*Methodik!$B$6+S43*Methodik!$B$7+T43*Methodik!$B$8,2) -> 2.7 | V43: =IF(U43>=Methodik!$B$11,"A",IF(U43>=Methodik!$B$12,"B","C")) -> C | X43: =IF(W43="",V43,W43) -> C | Y43: Offen: CRM prüfen | AA43: Leiter Grossprojekte / Bereichsleiter Baustrom / Einkauf | AD43: Suche öffnen | AE43: Suche öffnen | AF43: Link
A44: CH-040 | B44: Ja | C44: Installateure (60 %) | D44: Installateur | E44: Marcel Hufschmid AG | F44: Burkhalter | G44: Zug | H44: ZG | I44: Zentralschweiz | J44: Deutschschweiz | K44: DE | L44: hufschmid-elektro.ch | M44: ca. 100 MA | N44: WWZ-Unterwerk Herti geplant (Zug) | O44: USV, Generator | P44: Gewerbe- und Bürobauten Zug. | Q44: 3 | R44: 2 | S44: 3 | T44: 3 | U44: =ROUND(Q44*Methodik!$B$5+R44*Methodik!$B$6+S44*Methodik!$B$7+T44*Methodik!$B$8,2) -> 2.7 | V44: =IF(U44>=Methodik!$B$11,"A",IF(U44>=Methodik!$B$12,"B","C")) -> C | X44: =IF(W44="",V44,W44) -> C | Y44: Offen: CRM prüfen | AA44: Leiter Grossprojekte / Bereichsleiter Baustrom / Einkauf | AD44: Suche öffnen | AE44: Suche öffnen | AF44: Link
A45: CH-041 | B45: Ja | C45: Installateure (60 %) | D45: Installateur | E45: inelectro sa | F45: BKW | G45: Porrentruy | H45: JU | I45: West (Romandie) | J45: West | K45: FR | L45: inelectro.ch | M45: 55 MA | N45: Kein spezifischer Anlass recherchiert | O45: USV, Generator | P45: Jura-Industrie (Uhren, Präzision): USV bei geplanten Stromunterbrüchen. | Q45: 3 | R45: 2 | S45: 3 | T45: 3 | U45: =ROUND(Q45*Methodik!$B$5+R45*Methodik!$B$6+S45*Methodik!$B$7+T45*Methodik!$B$8,2) -> 2.7 | V45: =IF(U45>=Methodik!$B$11,"A",IF(U45>=Methodik!$B$12,"B","C")) -> C | X45: =IF(W45="",V45,W45) -> C | Y45: Offen: CRM prüfen | AA45: Leiter Grossprojekte / Bereichsleiter Baustrom / Einkauf | AD45: Suche öffnen | AE45: Suche öffnen | AF45: Link
A46: CH-042 | B46: Ja | C46: Installateure (60 %) | D46: Installateur | E46: Hälg Group | F46: unabhängig (Familie) | G46: St. Gallen | H46: SG | I46: Ostschweiz | J46: Deutschschweiz | K46: DE | L46: haelg.ch | M46: 1'295 MA, 30 Standorte (2025) | N46: Kein spezifischer Anlass recherchiert | O46: Generator (Kälte/Lüftung) | P46: Primär HLKS, kaum Elektro. Nur Überbrückung für Kälte und Lüftung. | Q46: 2 | R46: 3 | S46: 2 | T46: 3 | U46: =ROUND(Q46*Methodik!$B$5+R46*Methodik!$B$6+S46*Methodik!$B$7+T46*Methodik!$B$8,2) -> 2.45 | V46: =IF(U46>=Methodik!$B$11,"A",IF(U46>=Methodik!$B$12,"B","C")) -> C | X46: =IF(W46="",V46,W46) -> C | Y46: Offen: CRM prüfen | AA46: Leiter Grossprojekte / Bereichsleiter Baustrom / Einkauf | AD46: Suche öffnen | AE46: Suche öffnen | AF46: Link
A47: CH-043 | B47: Ja | C47: FM / EVU / Planer (20 %) | D47: Facility Manager | E47: CBRE GWS GmbH | F47: CBRE | G47: Basel | H47: BS | I47: Nordwestschweiz | J47: Deutschschweiz | K47: DE | L47: cbre.ch | M47: 550-1'000 MA (widersprüchlich) | N47: Pharmamandate Basel | O47: NEA-Test, USV, Generator | P47: Starke Pharma- und Industriemandate in Basel mit kritischer Stromversorgung. | Q47: 5 | R47: 4 | S47: 4 | T47: 3 | U47: =ROUND(Q47*Methodik!$B$5+R47*Methodik!$B$6+S47*Methodik!$B$7+T47*Methodik!$B$8,2) -> 4.15 | V47: =IF(U47>=Methodik!$B$11,"A",IF(U47>=Methodik!$B$12,"B","C")) -> A | X47: =IF(W47="",V47,W47) -> A | Y47: Offen: CRM prüfen | AA47: Leiter Technisches FM / Key Account Industrie & Pharma | AD47: Suche öffnen | AE47: Suche öffnen | AF47: Link
A48: CH-044 | B48: Ja | C48: FM / EVU / Planer (20 %) | D48: Facility Manager | E48: Equans Switzerland Facility Management AG | F48: Bouygues / Equans | G48: Zug | H48: ZG | I48: Zentralschweiz | J48: Deutschschweiz | K48: DE/FR | L48: equans.ch | M48: k.A. | N48: Fusion mit Equans Solutions Suisse SA (02/2026), neue ZN Sisseln und Kloten | O48: NEA-Test, Trafo, Generator | P48: Technisches FM in Industrie und Pharma (Sisseln). Neuordnung 2026: Lieferanten werden neu gewählt. | Q48: 5 | R48: 4 | S48: 4 | T48: 3 | U48: =ROUND(Q48*Methodik!$B$5+R48*Methodik!$B$6+S48*Methodik!$B$7+T48*Methodik!$B$8,2) -> 4.15 | V48: =IF(U48>=Methodik!$B$11,"A",IF(U48>=Methodik!$B$12,"B","C")) -> A | X48: =IF(W48="",V48,W48) -> A | Y48: Offen: CRM prüfen | AA48: Leiter Technisches FM / Key Account Industrie & Pharma | AD48: Suche öffnen | AE48: Suche öffnen | AF48: Link
A49: CH-045 | B49: Ja | C49: FM / EVU / Planer (20 %) | D49: Facility Manager | E49: ISS Schweiz AG | F49: ISS A/S | G49: Zürich | H49: ZH | I49: Zürich | J49: Deutschschweiz | K49: DE/FR/IT | L49: ch.issworld.com | M49: ca. 14'200 MA CH (2024) | N49: Kein spezifischer Anlass recherchiert | O49: NEA-Test, USV, Generator | P49: Grösster IFM-Anbieter: NEA-Tests und USV-Überbrückung in tausenden Liegenschaften. Rahmenvertrag skaliert. | Q49: 4 | R49: 5 | S49: 3 | T49: 3 | U49: =ROUND(Q49*Methodik!$B$5+R49*Methodik!$B$6+S49*Methodik!$B$7+T49*Methodik!$B$8,2) -> 3.9 | V49: =IF(U49>=Methodik!$B$11,"A",IF(U49>=Methodik!$B$12,"B","C")) -> B | X49: =IF(W49="",V49,W49) -> B | Y49: Offen: CRM prüfen | AA49: Leiter Technisches FM / Key Account Industrie & Pharma | AD49: Suche öffnen | AE49: Suche öffnen | AF49: Link
A50: CH-046 | B50: Nein | C50: FM / EVU / Planer (20 %) | D50: Facility Manager | E50: Apleona Schweiz AG | F50: Apleona | G50: Schaffhausen (HSG: Wallisellen) | H50: SH | I50: Ostschweiz | J50: Deutschschweiz | K50: DE/FR | L50: apleona.ch | M50: ca. 1'700 MA, 14 Standorte GE-SG | N50: Kein spezifischer Anlass recherchiert | O50: NEA-Test, Generator, Trafo | P50: Technisches FM: Mietgeneratoren bei NEA-Revisionen und Trafo-Wartungen. | Q50: 4 | R50: 4 | S50: 3 | T50: 3 | U50: =ROUND(Q50*Methodik!$B$5+R50*Methodik!$B$6+S50*Methodik!$B$7+T50*Methodik!$B$8,2) -> 3.6 | V50: =IF(U50>=Methodik!$B$11,"A",IF(U50>=Methodik!$B$12,"B","C")) -> B | X50: =IF(W50="",V50,W50) -> B | Y50: Offen: CRM prüfen | AA50: Leiter Technisches FM / Key Account Industrie & Pharma | AD50: Suche öffnen | AE50: Suche öffnen | AF50: Link
A51: CH-047 | B51: Ja | C51: FM / EVU / Planer (20 %) | D51: Facility Manager | E51: Honegger AG | F51: unabhängig (inkl. Cabiancardi SA, TI) | G51: Köniz | H51: BE | I51: Mittelland/Bern | J51: Deutschschweiz | K51: DE/FR/IT | L51: honegger.ch | M51: ca. 6'500 MA, 23 Standorte | N51: Kein spezifischer Anlass recherchiert | O51: USV, NEA-Test | P51: FM für Spitäler und Reinräume: USV und Notstrom in Wartungsfenstern. | Q51: 4 | R51: 4 | S51: 3 | T51: 3 | U51: =ROUND(Q51*Methodik!$B$5+R51*Methodik!$B$6+S51*Methodik!$B$7+T51*Methodik!$B$8,2) -> 3.6 | V51: =IF(U51>=Methodik!$B$11,"A",IF(U51>=Methodik!$B$12,"B","C")) -> B | X51: =IF(W51="",V51,W51) -> B | Y51: Offen: CRM prüfen | AA51: Leiter Technisches FM / Key Account Industrie & Pharma | AD51: Suche öffnen | AE51: Suche öffnen | AF51: Link
... A56: CH-052 | B56: Ja | C56: FM / EVU / Planer (20 %) | D56: Stadtwerk/EVU | E56: IWB | F56: Kanton Basel-Stadt | G56: Basel | H56: BS | I56: Nordwestschweiz | J56: Deutschschweiz | K56: DE | L56: iwb.ch | M56: ca. 1'100 GWh/a Stromabsatz | N56: Verstärkung Netzknoten Basel | O56: Trafo, Generator | P56: Bei Umschaltungen an Netzknoten Bedarf an temporärer Einspeisung. | Q56: 5 | R56: 4 | S56: 4 | T56: 3 | U56: =ROUND(Q56*Methodik!$B$5+R56*Methodik!$B$6+S56*Methodik!$B$7+T56*Methodik!$B$8,2) -> 4.15 | V56: =IF(U56>=Methodik!$B$11,"A",IF(U56>=Methodik!$B$12,"B","C")) -> A | X56: =IF(W56="",V56,W56) -> A | Y56: Offen: CRM prüfen | AA56: Leiter Netzbau / Leiter Unterwerke / Asset Management | AD56: Suche öffnen | AE56: Suche öffnen | AF56: Link
A57: CH-053 | B57: Ja | C57: FM / EVU / Planer (20 %) | D57: Stadtwerk/EVU | E57: ewz (Elektrizitätswerk der Stadt Zürich) | F57: Stadt Zürich | G57: Zürich | H57: ZH | I57: Zürich | J57: Deutschschweiz | K57: DE | L57: ewz.ch | M57: Stadtnetz Zürich | N57: Unterwerk-Neubauten/-Umbauten (z.B. Oerlikon) | O57: Trafo, Generator, BESS | P57: Unterwerksprojekte: provisorische Einspeisung per mobilem Trafo oder Generator. | Q57: 5 | R57: 4 | S57: 4 | T57: 3 | U57: =ROUND(Q57*Methodik!$B$5+R57*Methodik!$B$6+S57*Methodik!$B$7+T57*Methodik!$B$8,2) -> 4.15 | V57: =IF(U57>=Methodik!$B$11,"A",IF(U57>=Methodik!$B$12,"B","C")) -> A | X57: =IF(W57="",V57,W57) -> A | Y57: Offen: CRM prüfen | AA57: Leiter Netzbau / Leiter Unterwerke / Asset Management | AD57: Suche öffnen | AE57: Suche öffnen | AF57: Link | AG57: Öffentliche Beschaffung (IVöB) beachten.
A58: CH-054 | B58: Ja | C58: FM / EVU / Planer (20 %) | D58: Stadtwerk/EVU | E58: Romande Energie | F58: börsenkotiert | G58: Morges | H58: VD | I58: West (Romandie) | J58: West | K58: FR | L58: romande-energie.ch | M58: 1'467 MA (30.06.2025) | N58: Kein spezifischer Anlass recherchiert | O58: BESS, Trafo, Generator | P58: Grösster Verteilnetzbetreiber der Romandie. Netzausbau und PV-Integration. | Q58: 5 | R58: 4 | S58: 3 | T58: 3 | U58: =ROUND(Q58*Methodik!$B$5+R58*Methodik!$B$6+S58*Methodik!$B$7+T58*Methodik!$B$8,2) -> 3.9 | V58: =IF(U58>=Methodik!$B$11,"A",IF(U58>=Methodik!$B$12,"B","C")) -> B | X58: =IF(W58="",V58,W58) -> B | Y58: Offen: CRM prüfen | AA58: Leiter Netzbau / Leiter Unterwerke / Asset Management | AD58: Suche öffnen | AE58: Suche öffnen | AF58: Link
A59: CH-055 | B59: Ja | C59: FM / EVU / Planer (20 %) | D59: Stadtwerk/EVU | E59: SIG Services Industriels de Genève | F59: Kanton Genf | G59: Le Lignon (Vernier) | H59: GE | I59: West (Romandie) | J59: West | K59: FR | L59: sig-ge.ch | M59: 1'736 MA, 4'712 km Netz | N59: Kein spezifischer Anlass recherchiert | O59: Generator, Trafo, BESS | P59: Grosses urbanes Netz mit vielen Baustellen: Notstrom für Kunden bei Netzarbeiten. | Q59: 5 | R59: 4 | S59: 3 | T59: 3 | U59: =ROUND(Q59*Methodik!$B$5+R59*Methodik!$B$6+S59*Methodik!$B$7+T59*Methodik!$B$8,2) -> 3.9 | V59: =IF(U59>=Methodik!$B$11,"A",IF(U59>=Methodik!$B$12,"B","C")) -> B | X59: =IF(W59="",V59,W59) -> B | Y59: Offen: CRM prüfen | AA59: Leiter Netzbau / Leiter Unterwerke / Asset Management | AD59: Suche öffnen | AE59: Suche öffnen | AF59: Link
A60: CH-056 | B60: Nein | C60: FM / EVU / Planer (20 %) | D60: Stadtwerk/EVU | E60: Energie Wasser Bern (ewb) | F60: Stadt Bern | G60: Bern | H60: BE | I60: Mittelland/Bern | J60: Deutschschweiz | K60: DE | L60: ewb.ch | M60: ca. 780 MA | N60: UW Engehalde Sanierung 2022-2026 | O60: Trafo, Generator | P60: Unterwerk-Sanierungen: mobile Trafos und Überbrückung. | Q60: 5 | R60: 3 | S60: 4 | T60: 3 | U60: =ROUND(Q60*Methodik!$B$5+R60*Methodik!$B$6+S60*Methodik!$B$7+T60*Methodik!$B$8,2) -> 3.85 | V60: =IF(U60>=Methodik!$B$11,"A",IF(U60>=Methodik!$B$12,"B","C")) -> B | X60: =IF(W60="",V60,W60) -> B | Y60: Offen: CRM prüfen | AA60: Leiter Netzbau / Leiter Unterwerke / Asset Management | AD60: Suche öffnen | AE60: Suche öffnen | AF60: Link
A61: CH-057 | B61: Nein | C61: FM / EVU / Planer (20 %) | D61: Stadtwerk/EVU | E61: Groupe E | F61: Kantone FR/NE | G61: Granges-Paccot | H61: FR | I61: West (Romandie) | J61: West | K61: FR/DE | L61: groupe-e.ch | M61: 2'597 MA (Ende 2024) | N61: Stellenabbau 2025 | O61: Trafo, Generator | P61: Netzbetreiber mit eigener Installationssparte: Netzersatz bei Umbauten. | Q61: 4 | R61: 4 | S61: 3 | T61: 3 | U61: =ROUND(Q61*Methodik!$B$5+R61*Methodik!$B$6+S61*Methodik!$B$7+T61*Methodik!$B$8,2) -> 3.6 | V61: =IF(U61>=Methodik!$B$11,"A",IF(U61>=Methodik!$B$12,"B","C")) -> B | X61: =IF(W61="",V61,W61) -> B | Y61: Offen: CRM prüfen | AA61: Leiter Netzbau / Leiter Unterwerke / Asset Management | AC61: CEO Alain Sapin | AD61: Suche öffnen | AE61: Suche öffnen | AF61: Link
A62: CH-058 | B62: Nein | C62: FM / EVU / Planer (20 %) | D62: Stadtwerk/EVU | E62: AET (Azienda Elettrica Ticinese) | F62: Kanton Tessin | G62: Monte Carasso (Bellinzona) | H62: TI | I62: Tessin | J62: Tessin | K62: IT | L62: aet.ch | M62: >400 km MS/HS-Netz | N62: Unterwerk-Projekt mit Swissgrid in Biasca | O62: Trafo, Generator | P62: Temporäre Versorgung während Unterwerk-Umbauten. | Q62: 4 | R62: 3 | S62: 4 | T62: 3 | U62: =ROUND(Q62*Methodik!$B$5+R62*Methodik!$B$6+S62*Methodik!$B$7+T62*Methodik!$B$8,2) -> 3.55 | V62: =IF(U62>=Methodik!$B$11,"A",IF(U62>=Methodik!$B$12,"B","C")) -> B | X62: =IF(W62="",V62,W62) -> B | Y62: Offen: CRM prüfen | AA62: Leiter Netzbau / Leiter Unterwerke / Asset Management | AD62: Suche öffnen | AE62: Suche öffnen | AF62: Link
A63: CH-059 | B63: Nein | C63: FM / EVU / Planer (20 %) | D63: Stadtwerk/EVU | E63: WWZ | F63: börsenkotiert | G63: Zug | H63: ZG | I63: Zentralschweiz | J63: Deutschschweiz | K63: DE | L63: wwz.ch | M63: >470 MA, 2'200 km Netz | N63: Unterwerk Herti geplant | O63: Trafo, BESS, Generator | P63: Unterwerk-Neubau: temporäre Einspeisung und BESS. | Q63: 4 | R63: 3 | S63: 4 | T63: 3 | U63: =ROUND(Q63*Methodik!$B$5+R63*Methodik!$B$6+S63*Methodik!$B$7+T63*Methodik!$B$8,2) -> 3.55 | V63: =IF(U63>=Methodik!$B$11,"A",IF(U63>=Methodik!$B$12,"B","C")) -> B | X63: =IF(W63="",V63,W63) -> B | Y63: Offen: CRM prüfen | AA63: Leiter Netzbau / Leiter Unterwerke / Asset Management | AD63: Suche öffnen | AE63: Suche öffnen | AF63: Link
A64: CH-060 | B64: Ja | C64: FM / EVU / Planer (20 %) | D64: Stadtwerk/EVU | E64: AIL SA (Aziende Industriali di Lugano) | F64: Stadt Lugano | G64: Muzzano | H64: TI | I64: Tessin | J64: Tessin | K64: IT | L64: ail.ch | M64: >430 MA, >110'000 Kunden | N64: Kein spezifischer Anlass recherchiert | O64: Generator, Event, Trafo | P64: Grösster Verteiler im Tessin: Netzersatz bei Bauarbeiten und Events in Lugano. | Q64: 4 | R64: 3 | S64: 3 | T64: 3 | U64: =ROUND(Q64*Methodik!$B$5+R64*Methodik!$B$6+S64*Methodik!$B$7+T64*Methodik!$B$8,2) -> 3.3 | V64: =IF(U64>=Methodik!$B$11,"A",IF(U64>=Methodik!$B$12,"B","C")) -> B | X64: =IF(W64="",V64,W64) -> B | Y64: Offen: CRM prüfen | AA64: Leiter Netzbau / Leiter Unterwerke / Asset Management | AD64: Suche öffnen | AE64: Suche öffnen | AF64: Link
A65: CH-061 | B65: Nein | C65: FM / EVU / Planer (20 %) | D65: Stadtwerk/EVU | E65: OIKEN SA | F65: ex ESR + Sierre-Energie (seit 2020) | G65: Sion | H65: VS | I65: West (Romandie) | J65: West | K65: FR | L65: oiken.ch | M65: >470 MA, ca. 150'000 Kunden | N65: Kein spezifischer Anlass recherchiert | O65: Generator, Trafo | P65: Grösster EVU im Wallis. Bergregion mit Netzbau, mobile Einspeisung bei Leitungsarbeiten. | Q65: 4 | R65: 3 | S65: 3 | T65: 3 | U65: =ROUND(Q65*Methodik!$B$5+R65*Methodik!$B$6+S65*Methodik!$B$7+T65*Methodik!$B$8,2) -> 3.3 | V65: =IF(U65>=Methodik!$B$11,"A",IF(U65>=Methodik!$B$12,"B","C")) -> B | X65: =IF(W65="",V65,W65) -> B | Y65: Offen: CRM prüfen | AA65: Leiter Netzbau / Leiter Unterwerke / Asset Management | AD65: Suche öffnen | AE65: Suche öffnen | AF65: Link
A66: CH-062 | B66: Nein | C66: FM / EVU / Planer (20 %) | D66: Stadtwerk/EVU | E66: Primeo Energie | F66: Genossenschaft | G66: Münchenstein | H66: BL | I66: Nordwestschweiz | J66: Deutschschweiz | K66: DE/FR | L66: primeo-energie.ch | M66: 615-652 MA, >170'000 Kunden | N66: Kein spezifischer Anlass recherchiert | O66: Generator, BESS | P66: Netzbetreiber mit Energiedienstleistungen, auch als Wiederverkaufspartner denkbar. | Q66: 4 | R66: 3 | S66: 3 | T66: 3 | U66: =ROUND(Q66*Methodik!$B$5+R66*Methodik!$B$6+S66*Methodik!$B$7+T66*Methodik!$B$8,2) -> 3.3 | V66: =IF(U66>=Methodik!$B$11,"A",IF(U66>=Methodik!$B$12,"B","C")) -> B | X66: =IF(W66="",V66,W66) -> B | Y66: Offen: CRM prüfen | AA66: Leiter Netzbau / Leiter Unterwerke / Asset Management | AD66: Suche öffnen | AE66: Suche öffnen | AF66: Link
A67: CH-063 | B67: Nein | C67: FM / EVU / Planer (20 %) | D67: Stadtwerk/EVU | E67: Repower AG | F67: börsenkotiert | G67: Poschiavo | H67: GR | I67: Ostschweiz | J67: Deutschschweiz | K67: DE/IT | L67: repower.com | M67: 747 MA (Ende 2025), ca. 3'000 km Netz | N67: Kein spezifischer Anlass recherchiert | O67: Trafo, Generator | P67: Unterwerke und Trafostationen in abgelegenen Tälern: mobile Trafos und Generatoren bei Revisionen. | Q67: 4 | R67: 3 | S67: 3 | T67: 3 | U67: =ROUND(Q67*Methodik!$B$5+R67*Methodik!$B$6+S67*Methodik!$B$7+T67*Methodik!$B$8,2) -> 3.3 | V67: =IF(U67>=Methodik!$B$11,"A",IF(U67>=Methodik!$B$12,"B","C")) -> B | X67: =IF(W67="",V67,W67) -> B | Y67: Offen: CRM prüfen | AA67: Leiter Netzbau / Leiter Unterwerke / Asset Management | AD67: Suche öffnen | AE67: Suche öffnen | AF67: Link
A68: CH-064 | B68: Nein | C68: FM / EVU / Planer (20 %) | D68: Stadtwerk/EVU | E68: SAK | F68: Kantone SG/AR/AI | G68: St. Gallen | H68: SG | I68: Ostschweiz | J68: Deutschschweiz | K68: DE | L68: sak.ch | M68: ca. 460-480 MA | N68: Übernahme Fremdnetze (z.B. Marthy Energie) | O68: Netzersatz, BESS, Generator | P68: Hat Installation und Grossbatteriespeicher. Netzintegration braucht mobilen Netzersatz. | Q68: 4 | R68: 3 | S68: 3 | T68: 3 | U68: =ROUND(Q68*Methodik!$B$5+R68*Methodik!$B$6+S68*Methodik!$B$7+T68*Methodik!$B$8,2) -> 3.3 | V68: =IF(U68>=Methodik!$B$11,"A",IF(U68>=Methodik!$B$12,"B","C")) -> B | X68: =IF(W68="",V68,W68) -> B | Y68: Offen: CRM prüfen | AA68: Leiter Netzbau / Leiter Unterwerke / Asset Management | AD68: Suche öffnen | AE68: Suche öffnen | AF68: Link
A69: CH-065 | B69: Nein | C69: FM / EVU / Planer (20 %) | D69: Stadtwerk/EVU | E69: Viteos SA | F69: Städte NE | G69: Neuchâtel | H69: NE | I69: West (Romandie) | J69: West | K69: FR | L69: viteos.ch | M69: >320 MA | N69: Kein spezifischer Anlass recherchiert | O69: Generator, Trafo | P69: Netzbetreiber. Tochter Betelec (Elektrotechnik) als zweiter Ansprechpartner. | Q69: 3 | R69: 3 | S69: 3 | T69: 3 | U69: =ROUND(Q69*Methodik!$B$5+R69*Methodik!$B$6+S69*Methodik!$B$7+T69*Methodik!$B$8,2) -> 3 | V69: =IF(U69>=Methodik!$B$11,"A",IF(U69>=Methodik!$B$12,"B","C")) -> B | X69: =IF(W69="",V69,W69) -> B | Y69: Offen: CRM prüfen | AA69: Leiter Netzbau / Leiter Unterwerke / Asset Management | AD69: Suche öffnen | AE69: Suche öffnen | AF69: Link
A70: CH-066 | B70: Ja | C70: FM / EVU / Planer (20 %) | D70: Elektroplaner | E70: Amstein + Walthert | F70: unabhängig | G70: Zürich | H70: ZH | I70: Zürich | J70: Deutschschweiz | K70: DE/FR | L70: amstein-walthert.ch | M70: >1'100 MA, 10 Standorte | N70: Kein spezifischer Anlass recherchiert | O70: Spezifikation NEA/USV/BESS, PQ-Audit | P70: Führender Gebäudetechnikplaner: legt Notstrom und USV in Ausschreibungen für Spitäler und RZ fest. | Q70: 5 | R70: 4 | S70: 4 | T70: 3 | U70: =ROUND(Q70*Methodik!$B$5+R70*Methodik!$B$6+S70*Methodik!$B$7+T70*Methodik!$B$8,2) -> 4.15 | V70: =IF(U70>=Methodik!$B$11,"A",IF(U70>=Methodik!$B$12,"B","C")) -> A | X70: =IF(W70="",V70,W70) -> A | Y70: Offen: CRM prüfen | AA70: Fachbereichsleiter Elektro / Energie | AD70: Suche öffnen | AE70: Suche öffnen | AF70: Link | AG70: Planer kauft nicht selbst: Ziel ist Nennung in Ausschreibungen.
A71: CH-067 | B71: Ja | C71: FM / EVU / Planer (20 %) | D71: Elektroplaner | E71: HHM Gruppe (Hefti. Hess. Martignoni.) | F71: unabhängig | G71: Aarau | H71: AG | I71: Nordwestschweiz | J71: Deutschschweiz | K71: DE | L71: hhm.ch | M71: >280 MA | N71: Kein spezifischer Anlass recherchiert | O71: Spezifikation NEA/USV, PQ-Audit | P71: Reiner Elektroplaner mit Kompetenzfeld Energie: schreibt NEA und USV aus. | Q71: 5 | R71: 3 | S71: 4 | T71: 3 | U71: =ROUND(Q71*Methodik!$B$5+R71*Methodik!$B$6+S71*Methodik!$B$7+T71*Methodik!$B$8,2) -> 3.85 | V71: =IF(U71>=Methodik!$B$11,"A",IF(U71>=Methodik!$B$12,"B","C")) -> B | X71: =IF(W71="",V71,W71) -> B | Y71: Offen: CRM prüfen | AA71: Fachbereichsleiter Elektro / Energie | AD71: Suche öffnen | AE71: Suche öffnen | AF71: Link
A72: CH-068 | B72: Ja | C72: FM / EVU / Planer (20 %) | D72: Elektroplaner | E72: SCHERLER AG (Ingenieurbüro) | F72: unabhängig | G72: Luzern | H72: LU | I72: Zentralschweiz | J72: Deutschschweiz | K72: DE | L72: scherler.swiss | M72: >200 MA | N72: Kein spezifischer Anlass recherchiert | O72: Spezifikation NEA/USV/Mittelspannung, PQ-Audit | P72: Planer für NEA, USV und Mittelspannung: Einfluss auf Ausschreibungen. | Q72: 5 | R72: 3 | S72: 4 | T72: 3 | U72: =ROUND(Q72*Methodik!$B$5+R72*Methodik!$B$6+S72*Methodik!$B$7+T72*Methodik!$B$8,2) -> 3.85 | V72: =IF(U72>=Methodik!$B$11,"A",IF(U72>=Methodik!$B$12,"B","C")) -> B | X72: =IF(W72="",V72,W72) -> B | Y72: Offen: CRM prüfen | AA72: Fachbereichsleiter Elektro / Energie | AD72: Suche öffnen | AE72: Suche öffnen | AF72: Link | AG72: Nicht verwechseln mit Scherler AG Bern (Installateur).
A73: CH-069 | B73: Nein | C73: FM / EVU / Planer (20 %) | D73: Elektroplaner | E73: AFRY Schweiz AG | F73: AFRY (ex Pöyry) | G73: Zürich | H73: ZH | I73: Zürich | J73: Deutschschweiz | K73: DE/FR/IT | L73: afry.com | M73: >1'000 MA CH, 20 Standorte | N73: Kein spezifischer Anlass recherchiert | O73: Spezifikation Trafo/Generator | P73: Energie- und Netzplaner (Kraftwerke, UW): Bauprogramme mit temporärer Einspeisung. | Q73: 4 | R73: 4 | S73: 3 | T73: 3 | U73: =ROUND(Q73*Methodik!$B$5+R73*Methodik!$B$6+S73*Methodik!$B$7+T73*Methodik!$B$8,2) -> 3.6 | V73: =IF(U73>=Methodik!$B$11,"A",IF(U73>=Methodik!$B$12,"B","C")) -> B | X73: =IF(W73="",V73,W73) -> B | Y73: Offen: CRM prüfen | AA73: Fachbereichsleiter Elektro / Energie | AD73: Suche öffnen | AE73: Suche öffnen | AF73: Link
A74: CH-070 | B74: Nein | C74: FM / EVU / Planer (20 %) | D74: Elektroplaner | E74: Basler & Hofmann | F74: unabhängig | G74: Esslingen | H74: ZH | I74: Zürich | J74: Deutschschweiz | K74: DE | L74: baslerhofmann.ch | M74: ca. 530 MA in CH | N74: Kein spezifischer Anlass recherchiert | O74: Spezifikation BESS, PQ-Audit | P74: Kompetenzzentrum Erneuerbare inkl. Speicher: BESS-Spezifikation. | Q74: 4 | R74: 3 | S74: 3 | T74: 3 | U74: =ROUND(Q74*Methodik!$B$5+R74*Methodik!$B$6+S74*Methodik!$B$7+T74*Methodik!$B$8,2) -> 3.3 | V74: =IF(U74>=Methodik!$B$11,"A",IF(U74>=Methodik!$B$12,"B","C")) -> B | X74: =IF(W74="",V74,W74) -> B | Y74: Offen: CRM prüfen | AA74: Fachbereichsleiter Elektro / Energie | AD74: Suche öffnen | AE74: Suche öffnen | AF74: Link
A75: CH-071 | B75: Nein | C75: FM / EVU / Planer (20 %) | D75: Elektroplaner | E75: Gruner AG | F75: unabhängig | G75: Basel | H75: BS | I75: Nordwestschweiz | J75: Deutschschweiz | K75: DE | L75: gruner.ch | M75: >1'100 MA (international) | N75: Kein spezifischer Anlass recherchiert | O75: Spezifikation NEA/USV | P75: Gebäudetechnik und Energieanlagen, Planung von Notstromkonzepten. | Q75: 4 | R75: 3 | S75: 3 | T75: 3 | U75: =ROUND(Q75*Methodik!$B$5+R75*Methodik!$B$6+S75*Methodik!$B$7+T75*Methodik!$B$8,2) -> 3.3 | V75: =IF(U75>=Methodik!$B$11,"A",IF(U75>=Methodik!$B$12,"B","C")) -> B | X75: =IF(W75="",V75,W75) -> B | Y75: Offen: CRM prüfen | AA75: Fachbereichsleiter Elektro / Energie | AD75: Suche öffnen | AE75: Suche öffnen | AF75: Link
A76: CH-072 | B76: Nein | C76: FM / EVU / Planer (20 %) | D76: Elektroplaner | E76: HKG Engineering AG (Herzog Kull Group) | F76: unabhängig | G76: Baden (ab 01.03.2026) | H76: AG | I76: Nordwestschweiz | J76: Deutschschweiz | K76: DE/FR | L76: hkg.ch | M76: ca. 180 MA, 12 Standorte | N76: Neuer Firmensitz Baden 2026 | O76: Spezifikation Provisorien | P76: Elektroplanung und Gebäudeautomation: Provisorien bei Umbauten. | Q76: 4 | R76: 3 | S76: 3 | T76: 3 | U76: =ROUND(Q76*Methodik!$B$5+R76*Methodik!$B$6+S76*Methodik!$B$7+T76*Methodik!$B$8,2) -> 3.3 | V76: =IF(U76>=Methodik!$B$11,"A",IF(U76>=Methodik!$B$12,"B","C")) -> B | X76: =IF(W76="",V76,W76) -> B | Y76: Offen: CRM prüfen | AA76: Fachbereichsleiter Elektro / Energie | AD76: Suche öffnen | AE76: Suche öffnen | AF76: Link
A77: CH-073 | B77: Nein | C77: FM / EVU / Planer (20 %) | D77: Elektroplaner | E77: Weinmann-Energies SA | F77: unabhängig | G77: Echallens | H77: VD | I77: West (Romandie) | J77: West | K77: FR | L77: weinmann-energies.ch | M77: >100 MA, Filialen GE/NE | N77: Kein spezifischer Anlass recherchiert | O77: Spezifikation NEA/USV | P77: CVSE-Ingenieure Romandie: Notstrom und USV in Bau und Industrie. | Q77: 4 | R77: 3 | S77: 3 | T77: 3 | U77: =ROUND(Q77*Methodik!$B$5+R77*Methodik!$B$6+S77*Methodik!$B$7+T77*Methodik!$B$8,2) -> 3.3 | V77: =IF(U77>=Methodik!$B$11,"A",IF(U77>=Methodik!$B$12,"B","C")) -> B | X77: =IF(W77="",V77,W77) -> B | Y77: Offen: CRM prüfen | AA77: Fachbereichsleiter Elektro / Energie | AD77: Suche öffnen | AE77: Suche öffnen | AF77: Link
A78: CH-074 | B78: Nein | C78: FM / EVU / Planer (20 %) | D78: Elektroplaner | E78: IBG Engineering AG | F78: unabhängig | G78: Winterthur | H78: ZH | I78: Ostschweiz | J78: Deutschschweiz | K78: DE | L78: ibg.ch | M78: k.A., Standorte SG, Chur, Weinfelden u.a. | N78: Kein spezifischer Anlass recherchiert | O78: Spezifikation NEA | P78: Elektroplanung Stark- und Schwachstrom, Energietechnik. Stark in der Ostschweiz. | Q78: 4 | R78: 2 | S78: 3 | T78: 3 | U78: =ROUND(Q78*Methodik!$B$5+R78*Methodik!$B$6+S78*Methodik!$B$7+T78*Methodik!$B$8,2) -> 3 | V78: =IF(U78>=Methodik!$B$11,"A",IF(U78>=Methodik!$B$12,"B","C")) -> B | X78: =IF(W78="",V78,W78) -> B | Y78: Offen: CRM prüfen | AA78: Fachbereichsleiter Elektro / Energie | AD78: Suche öffnen | AE78: Suche öffnen | AF78: Link
A79: CH-075 | B79: Nein | C79: FM / EVU / Planer (20 %) | D79: Elektroplaner | E79: SRG Engineering | F79: unabhängig | G79: Le Mont-sur-Lausanne | H79: VD | I79: West (Romandie) | J79: West | K79: FR | L79: srg-engineering.ch | M79: k.A., Büros VD/GE/FR | N79: Kein spezifischer Anlass recherchiert | O79: Spezifikation Sicherheitsstrom | P79: CVSE-Planer, Elektroteil inkl. Sicherheitsstrom. | Q79: 3 | R79: 2 | S79: 3 | T79: 3 | U79: =ROUND(Q79*Methodik!$B$5+R79*Methodik!$B$6+S79*Methodik!$B$7+T79*Methodik!$B$8,2) -> 2.7 | V79: =IF(U79>=Methodik!$B$11,"A",IF(U79>=Methodik!$B$12,"B","C")) -> C | X79: =IF(W79="",V79,W79) -> C | Y79: Offen: CRM prüfen | AA79: Fachbereichsleiter Elektro / Energie | AD79: Suche öffnen | AE79: Suche öffnen | AF79: Link | AG79: Website nicht abrufbar gewesen.
A80: CH-076 | B80: Nein | C80: FM / EVU / Planer (20 %) | D80: Elektroplaner | E80: Studio d'ingegneria Visani Rusconi Talleri (VRT) SA | F80: unabhängig | G80: Taverne | H80: TI | I80: Tessin | J80: Tessin | K80: IT | L80: vrt.ch | M80: k.A., Standorte Taverne, Losone | N80: EOC-Spitalprojekte Tessin | O80: Spezifikation Notstrom | P80: Planer für Spitäler und Energiezentralen im Tessin (HLK-Schwerpunkt). | Q80: 3 | R80: 2 | S80: 3 | T80: 3 | U80: =ROUND(Q80*Methodik!$B$5+R80*Methodik!$B$6+S80*Methodik!$B$7+T80*Methodik!$B$8,2) -> 2.7 | V80: =IF(U80>=Methodik!$B$11,"A",IF(U80>=Methodik!$B$12,"B","C")) -> C | X80: =IF(W80="",V80,W80) -> C | Y80: Offen: CRM prüfen | AA80: Fachbereichsleiter Elektro / Energie | AD80: Suche öffnen | AE80: Suche öffnen | AF80: Link
A81: CH-077 | B81: Nein | C81: FM / EVU / Planer (20 %) | D81: Elektroplaner | E81: MORE Engineering SA | F81: k.A. | G81: Tessin (Ort prüfen) | H81: TI | I81: Tessin | J81: Tessin | K81: IT | L81: moreengineering.ch | M81: k.A. | N81: Kein spezifischer Anlass recherchiert | O81: Spezifikation NEA | P81: Elektro- und Energieplaner im Tessin. | Q81: 3 | R81: 2 | S81: 3 | T81: 2 | U81: =ROUND(Q81*Methodik!$B$5+R81*Methodik!$B$6+S81*Methodik!$B$7+T81*Methodik!$B$8,2) -> 2.55 | V81: =IF(U81>=Methodik!$B$11,"A",IF(U81>=Methodik!$B$12,"B","C")) -> C | X81: =IF(W81="",V81,W81) -> C | Y81: Offen: CRM prüfen | AA81: Fachbereichsleiter Elektro / Energie | AD81: Suche öffnen | AE81: Suche öffnen | AF81: Link | AG81: Existenz und Grösse vor Ansprache prüfen.
A82: CH-078 | B82: Ja | C82: GU/TU + Industrie (20 %) | D82: GU/TU | E82: Implenia | F82: börsenkotiert | G82: Lupfig, Dielsdorf, Sisikon, Zürich | H82: ZH | I82: Zürich | J82: Deutschschweiz | K82: DE/FR | L82: implenia.com | M82: Grösster Baukonzern CH | N82: GU Green-RZ Lupfig und Dielsdorf; Sisikoner Tunnel (ARGE, 2025-2034); Hagenholztunnel SBB | O82: Baustrom, Lastbank/NEA-Test, Generator, Trafo | P82: RZ-Bau mit Commissioning plus Tunnelbaustrom über Jahre. Höchster Hebel in der Liste. | Q82: 5 | R82: 5 | S82: 5 | T82: 3 | U82: =ROUND(Q82*Methodik!$B$5+R82*Methodik!$B$6+S82*Methodik!$B$7+T82*Methodik!$B$8,2) -> 4.7 | V82: =IF(U82>=Methodik!$B$11,"A",IF(U82>=Methodik!$B$12,"B","C")) -> A | X82: =IF(W82="",V82,W82) -> A | Y82: Offen: CRM prüfen | AA82: Projektleiter Baustelleneinrichtung / Einkauf | AD82: Suche öffnen | AE82: Suche öffnen | AF82: Link
A83: CH-079 | B83: Ja | C83: GU/TU + Industrie (20 %) | D83: GU/TU | E83: Losinger Marazzi | F83: Bouygues | G83: Genève / Vernier | H83: GE | I83: West (Romandie) | J83: West | K83: FR | L83: losinger-marazzi.ch | M83: k.A. | N83: Konsortium LMB: neues Terminal GVA (Cap2030, ca. 600 Mio., 2026-2032) | O83: Baustrom, Generator, Überbrückung | P83: Baustrom im laufenden Flughafenbetrieb, Überbrückung bei Netzumschaltungen. | Q83: 5 | R83: 5 | S83: 4 | T83: 3 | U83: =ROUND(Q83*Methodik!$B$5+R83*Methodik!$B$6+S83*Methodik!$B$7+T83*Methodik!$B$8,2) -> 4.45 | V83: =IF(U83>=Methodik!$B$11,"A",IF(U83>=Methodik!$B$12,"B","C")) -> A | X83: =IF(W83="",V83,W83) -> A | Y83: Offen: CRM prüfen | AA83: Projektleiter Baustelleneinrichtung / Einkauf | AD83: Suche öffnen | AE83: Suche öffnen | AF83: Link
A84: CH-080 | B84: Ja | C84: GU/TU + Industrie (20 %) | D84: GU/TU | E84: Marti-Gruppe | F84: unabhängig | G84: Moosseedorf / Airolo | H84: BE | I84: Tessin | J84: Tessin | K84: DE/IT | L84: marti.com | M84: k.A. | N84: 2. Gotthardröhre, Hauptlos Süd (ca. 7,8 km TBM) | O84: Trafo, Generator, Redundanz | P84: Redundante Versorgung für TBM und Tunnellüftung, mobile Trafos. | Q84: 5 | R84: 5 | S84: 4 | T84: 3 | U84: =ROUND(Q84*Methodik!$B$5+R84*Methodik!$B$6+S84*Methodik!$B$7+T84*Methodik!$B$8,2) -> 4.45 | V84: =IF(U84>=Methodik!$B$11,"A",IF(U84>=Methodik!$B$12,"B","C")) -> A | X84: =IF(W84="",V84,W84) -> A | Y84: Offen: CRM prüfen | AA84: Projektleiter Baustelleneinrichtung / Einkauf | AD84: Suche öffnen | AE84: Suche öffnen | AF84: Link | AG84: Region nach Baustelle (Airolo) gesetzt, HQ Moosseedorf BE.
A85: CH-081 | B85: Ja | C85: GU/TU + Industrie (20 %) | D85: GU/TU | E85: ERNE Gruppe | F85: unabhängig | G85: Laufenburg | H85: AG | I85: Nordwestschweiz | J85: Deutschschweiz | K85: DE | L85: erne-gruppe.ch | M85: k.A. | N85: Bauunternehmer FlexBase Laufenburg (BESS plus KI-RZ, ca. 1 Mrd.) | O85: Baustrom, Generator, Lastbank | P85: Grossaushub ca. 400'000 m³, danach NEA- und Testlastbedarf. | Q85: 5 | R85: 4 | S85: 5 | T85: 3 | U85: =ROUND(Q85*Methodik!$B$5+R85*Methodik!$B$6+S85*Methodik!$B$7+T85*Methodik!$B$8,2) -> 4.4 | V85: =IF(U85>=Methodik!$B$11,"A",IF(U85>=Methodik!$B$12,"B","C")) -> A | X85: =IF(W85="",V85,W85) -> A | Y85: Offen: CRM prüfen | AA85: Projektleiter Baustelleneinrichtung / Einkauf | AD85: Suche öffnen | AE85: Suche öffnen | AF85: Link
A86: CH-082 | B86: Nein | C86: GU/TU + Industrie (20 %) | D86: GU/TU | E86: Frutiger AG | F86: unabhängig | G86: Thun | H86: BE | I86: Mittelland/Bern | J86: Deutschschweiz | K86: DE | L86: frutiger.com | M86: k.A. | N86: Sisikoner Tunnel (ARGE); Neubau Bernstrasse 11 Thun (bis 2027) | O86: Generator, Trafo, Baustrom | P86: Aggregate für Tunnelvortrieb und Lüftung, Baustrom im Hochbau. | Q86: 5 | R86: 4 | S86: 5 | T86: 3 | U86: =ROUND(Q86*Methodik!$B$5+R86*Methodik!$B$6+S86*Methodik!$B$7+T86*Methodik!$B$8,2) -> 4.4 | V86: =IF(U86>=Methodik!$B$11,"A",IF(U86>=Methodik!$B$12,"B","C")) -> A | X86: =IF(W86="",V86,W86) -> A | Y86: Offen: CRM prüfen | AA86: Projektleiter Baustelleneinrichtung / Einkauf | AD86: Suche öffnen | AE86: Suche öffnen | AF86: Link
A87: CH-083 | B87: Nein | C87: GU/TU + Industrie (20 %) | D87: GU/TU | E87: HRS Real Estate | F87: unabhängig | G87: Frauenfeld | H87: TG | I87: Ostschweiz | J87: Deutschschweiz | K87: DE | L87: hrs.ch | M87: k.A. | N87: Hochhaus «Chez Fritz» Frauenfeld (2026-2029) | O87: Baustrom, BESS | P87: TU mit Grossbaustellen in der ganzen Schweiz. | Q87: 4 | R87: 4 | S87: 3 | T87: 3 | U87: =ROUND(Q87*Methodik!$B$5+R87*Methodik!$B$6+S87*Methodik!$B$7+T87*Methodik!$B$8,2) -> 3.6 | V87: =IF(U87>=Methodik!$B$11,"A",IF(U87>=Methodik!$B$12,"B","C")) -> B | X87: =IF(W87="",V87,W87) -> B | Y87: Offen: CRM prüfen | AA87: Projektleiter Baustelleneinrichtung / Einkauf | AD87: Suche öffnen | AE87: Suche öffnen | AF87: Link
A88: CH-084 | B88: Nein | C88: GU/TU + Industrie (20 %) | D88: GU/TU | E88: Anliker AG | F88: unabhängig | G88: Emmenbrücke | H88: LU | I88: Zentralschweiz | J88: Deutschschweiz | K88: DE | L88: anliker.ch | M88: k.A. | N88: Rohbau USZ Campus MITTE1|2; Forum UZH (Spatenstich 22.09.2026) | O88: Baustrom, Generator | P88: Baustrom im Spitalumfeld mit hohem Anspruch an Versorgungssicherheit. | Q88: 4 | R88: 3 | S88: 4 | T88: 3 | U88: =ROUND(Q88*Methodik!$B$5+R88*Methodik!$B$6+S88*Methodik!$B$7+T88*Methodik!$B$8,2) -> 3.55 | V88: =IF(U88>=Methodik!$B$11,"A",IF(U88>=Methodik!$B$12,"B","C")) -> B | X88: =IF(W88="",V88,W88) -> B | Y88: Offen: CRM prüfen | AA88: Projektleiter Baustelleneinrichtung / Einkauf | AD88: Suche öffnen | AE88: Suche öffnen | AF88: Link
A89: CH-085 | B89: Nein | C89: GU/TU + Industrie (20 %) | D89: GU/TU | E89: Walo Bertschinger | F89: unabhängig | G89: Dietikon | H89: ZH | I89: Zürich | J89: Deutschschweiz | K89: DE/FR | L89: walo.ch | M89: k.A. | N89: Zwei N16-Brücken Péry für ASTRA (bis Ende 2026) | O89: Generator, BESS | P89: Linienbaustellen Strassen- und Tiefbau: mobile Generatoren. | Q89: 4 | R89: 3 | S89: 4 | T89: 3 | U89: =ROUND(Q89*Methodik!$B$5+R89*Methodik!$B$6+S89*Methodik!$B$7+T89*Methodik!$B$8,2) -> 3.55 | V89: =IF(U89>=Methodik!$B$11,"A",IF(U89>=Methodik!$B$12,"B","C")) -> B | X89: =IF(W89="",V89,W89) -> B | Y89: Offen: CRM prüfen | AA89: Projektleiter Baustelleneinrichtung / Einkauf | AD89: Suche öffnen | AE89: Suche öffnen | AF89: Link
A90: CH-086 | B90: Nein | C90: GU/TU + Industrie (20 %) | D90: GU/TU | E90: Halter AG | F90: unabhängig | G90: Schlieren | H90: ZH | I90: Zürich | J90: Deutschschweiz | K90: DE/FR | L90: halter.ch | M90: k.A., Filialen BE/BS/Lausanne/Genf | N90: AuPark Wädenswil Etappe 2 (03/2026) | O90: Baustrom, BESS | P90: TU für Grossareale: BESS für emissionsarme Wohnbaustellen. | Q90: 4 | R90: 3 | S90: 3 | T90: 3 | U90: =ROUND(Q90*Methodik!$B$5+R90*Methodik!$B$6+S90*Methodik!$B$7+T90*Methodik!$B$8,2) -> 3.3 | V90: =IF(U90>=Methodik!$B$11,"A",IF(U90>=Methodik!$B$12,"B","C")) -> B | X90: =IF(W90="",V90,W90) -> B | Y90: Offen: CRM prüfen | AA90: Projektleiter Baustelleneinrichtung / Einkauf | AD90: Suche öffnen | AE90: Suche öffnen | AF90: Link
A91: CH-087 | B91: Nein | C91: GU/TU + Industrie (20 %) | D91: GU/TU | E91: Induni & Cie SA | F91: unabhängig | G91: Genève | H91: GE | I91: West (Romandie) | J91: West | K91: FR | L91: induni.ch | M91: k.A. | N91: Baustellen En Sauvy/Lancy, Hauts de Vandoeuvres | O91: Baustrom, Generator | P91: Baustrom im urbanen Genf. | Q91: 3 | R91: 3 | S91: 3 | T91: 3 | U91: =ROUND(Q91*Methodik!$B$5+R91*Methodik!$B$6+S91*Methodik!$B$7+T91*Methodik!$B$8,2) -> 3 | V91: =IF(U91>=Methodik!$B$11,"A",IF(U91>=Methodik!$B$12,"B","C")) -> B | X91: =IF(W91="",V91,W91) -> B | Y91: Offen: CRM prüfen | AA91: Projektleiter Baustelleneinrichtung / Einkauf | AD91: Suche öffnen | AE91: Suche öffnen | AF91: Link
A92: CH-088 | B92: Nein | C92: GU/TU + Industrie (20 %) | D92: GU/TU | E92: Mancini & Marti SA | F92: unabhängig | G92: Tessin | H92: TI | I92: Tessin | J92: Tessin | K92: IT | L92: mancinimarti.ch | M92: k.A. | N92: Kein spezifischer Anlass recherchiert | O92: Baustrom | P92: Traditionsbauer im Tessin, kein konkretes Projekt verifiziert. | Q92: 3 | R92: 2 | S92: 2 | T92: 3 | U92: =ROUND(Q92*Methodik!$B$5+R92*Methodik!$B$6+S92*Methodik!$B$7+T92*Methodik!$B$8,2) -> 2.45 | V92: =IF(U92>=Methodik!$B$11,"A",IF(U92>=Methodik!$B$12,"B","C")) -> C | X92: =IF(W92="",V92,W92) -> C | Y92: Offen: CRM prüfen | AA92: Projektleiter Baustelleneinrichtung / Einkauf | AD92: Suche öffnen | AE92: Suche öffnen | AF92: Link | AG92: Projektlage prüfen.
A93: CH-089 | B93: Ja | C93: GU/TU + Industrie (20 %) | D93: Rechenzentrum | E93: Digital Realty (ex Interxion) | F93: Digital Realty | G93: Glattbrugg | H93: ZH | I93: Zürich | J93: Deutschschweiz | K93: EN/DE | L93: digitalrealty.com | M93: Campus ZUR1-4, danach ca. 60 MW | N93: Spatenstich ZUR4 26.08.2026: 15 MW, Eröffnung 2028 | O93: Baustrom, Lastbank/NEA-Test | P93: Neubau mit Commissioning 2027/28. Früh in Spezifikation kommen. | Q93: 5 | R93: 5 | S93: 5 | T93: 3 | U93: =ROUND(Q93*Methodik!$B$5+R93*Methodik!$B$6+S93*Methodik!$B$7+T93*Methodik!$B$8,2) -> 4.7 | V93: =IF(U93>=Methodik!$B$11,"A",IF(U93>=Methodik!$B$12,"B","C")) -> A | X93: =IF(W93="",V93,W93) -> A | Y93: Offen: CRM prüfen | AA93: Construction / Commissioning Manager, Critical Facility Ops | AD93: Suche öffnen | AE93: Suche öffnen | AF93: Link | AG93: Sprache: Englisch klären.
A94: CH-090 | B94: Ja | C94: GU/TU + Industrie (20 %) | D94: Rechenzentrum | E94: Green Datacenter | F94: green.ch | G94: Lupfig / Dielsdorf | H94: AG | I94: Nordwestschweiz | J94: Deutschschweiz | K94: DE | L94: green.ch | M94: Lupfig 12 MW | N94: Lupfig: Start 2026; Dielsdorf: Baustart RZ 3 für 2026 geplant | O94: Lastbank/NEA-Test, Generator, USV | P94: Jedes neue RZ braucht Commissioning-Lastbanktests und Inbetriebnahmestrom. | Q94: 5 | R94: 5 | S94: 5 | T94: 3 | U94: =ROUND(Q94*Methodik!$B$5+R94*Methodik!$B$6+S94*Methodik!$B$7+T94*Methodik!$B$8,2) -> 4.7 | V94: =IF(U94>=Methodik!$B$11,"A",IF(U94>=Methodik!$B$12,"B","C")) -> A | X94: =IF(W94="",V94,W94) -> A | Y94: Offen: CRM prüfen | AA94: Construction / Commissioning Manager, Critical Facility Ops | AD94: Suche öffnen | AE94: Suche öffnen | AF94: Link
A95: CH-091 | B95: Ja | C95: GU/TU + Industrie (20 %) | D95: Rechenzentrum | E95: STACK Infrastructure | F95: STACK | G95: Beringen | H95: SH | I95: Ostschweiz | J95: Deutschschweiz | K95: EN/DE | L95: stackinfra.com | M95: 36 MW Hyperscale | N95: Beringen: Eröffnung 2026 geplant, eigenes Unterwerk | O95: Überbrückung, Lastbank, Generator | P95: Verzögert sich das Unterwerk, braucht es Überbrückung. Commissioning-Lastbank sicher. | Q95: 5 | R95: 5 | S95: 5 | T95: 2 | U95: =ROUND(Q95*Methodik!$B$5+R95*Methodik!$B$6+S95*Methodik!$B$7+T95*Methodik!$B$8,2) -> 4.55 | V95: =IF(U95>=Methodik!$B$11,"A",IF(U95>=Methodik!$B$12,"B","C")) -> A | X95: =IF(W95="",V95,W95) -> A | Y95: Offen: CRM prüfen | AA95: Construction / Commissioning Manager, Critical Facility Ops | AD95: Suche öffnen | AE95: Suche öffnen | AF95: Link
A96: CH-092 | B96: Ja | C96: GU/TU + Industrie (20 %) | D96: Rechenzentrum | E96: NorthC Datacenters | F96: NorthC | G96: Arlesheim / Genf / Winterthur | H96: BL | I96: Nordwestschweiz | J96: Deutschschweiz | K96: DE/FR/EN | L96: northcdatacenters.com | M96: 3 Standorte CH | N96: Arlesheim bis Mitte 2027; Genf Baustart Q1 2026 | O96: Baustrom, Lastbank/NEA-Test | P96: Zwei laufende RZ-Baustellen gleichzeitig (NWCH und West). | Q96: 5 | R96: 4 | S96: 5 | T96: 3 | U96: =ROUND(Q96*Methodik!$B$5+R96*Methodik!$B$6+S96*Methodik!$B$7+T96*Methodik!$B$8,2) -> 4.4 | V96: =IF(U96>=Methodik!$B$11,"A",IF(U96>=Methodik!$B$12,"B","C")) -> A | X96: =IF(W96="",V96,W96) -> A | Y96: Offen: CRM prüfen | AA96: Construction / Commissioning Manager, Critical Facility Ops | AD96: Suche öffnen | AE96: Suche öffnen | AF96: Link
A97: CH-093 | B97: Ja | C97: GU/TU + Industrie (20 %) | D97: Rechenzentrum | E97: FlexBase Group | F97: unabhängig | G97: Laufenburg | H97: AG | I97: Nordwestschweiz | J97: Deutschschweiz | K97: DE/EN | L97: flexbase.ch | M97: BESS >1,6 GWh / 800 MW plus KI-RZ | N97: Bau seit Frühling 2025, IBN Sommer 2028 (Zeitplan umstritten) | O97: Baustrom, Lastbank, BESS-Know-how | P97: Grösstes BESS-Projekt der Schweiz. BESS-Kompetenz von MiT als Türöffner. | Q97: 5 | R97: 5 | S97: 4 | T97: 2 | U97: =ROUND(Q97*Methodik!$B$5+R97*Methodik!$B$6+S97*Methodik!$B$7+T97*Methodik!$B$8,2) -> 4.3 | V97: =IF(U97>=Methodik!$B$11,"A",IF(U97>=Methodik!$B$12,"B","C")) -> A | X97: =IF(W97="",V97,W97) -> A | Y97: Offen: CRM prüfen | AA97: Construction / Commissioning Manager, Critical Facility Ops | AD97: Suche öffnen | AE97: Suche öffnen | AF97: Link | AG97: Finanzierung und Zeitplan kritisch beobachten.
A98: CH-094 | B98: Ja | C98: GU/TU + Industrie (20 %) | D98: Rechenzentrum | E98: Vantage Data Centers | F98: Vantage | G98: Winterthur / Glattfelden | H98: ZH | I98: Zürich | J98: Deutschschweiz | K98: EN | L98: vantage-dc.com | M98: ZRH2 Glattfelden 24 MW (>370 Mio.) | N98: ZRH12 im Bau (Rohbau 10/2025); ZRH2 Glattfelden | O98: Lastbank, Generator, Überbrückung | P98: Load-Bank-Tests und temporäre Versorgung bis zum Netzanschluss. | Q98: 5 | R98: 5 | S98: 4 | T98: 2 | U98: =ROUND(Q98*Methodik!$B$5+R98*Methodik!$B$6+S98*Methodik!$B$7+T98*Methodik!$B$8,2) -> 4.3 | V98: =IF(U98>=Methodik!$B$11,"A",IF(U98>=Methodik!$B$12,"B","C")) -> A | X98: =IF(W98="",V98,W98) -> A | Y98: Offen: CRM prüfen | AA98: Construction / Commissioning Manager, Critical Facility Ops | AD98: Suche öffnen | AE98: Suche öffnen | AF98: Link | AG98: Beschaffung oft zentral (EMEA).
A99: CH-095 | B99: Nein | C99: GU/TU + Industrie (20 %) | D99: Rechenzentrum | E99: Infomaniak | F99: unabhängig | G99: Genève | H99: GE | I99: West (Romandie) | J99: West | K99: FR | L99: infomaniak.com | M99: RZ D4 | N99: D4 seit 01/2025, bei 25 % Auslastung, Vollausbau bis 2028 | O99: Lastbank, USV | P99: Stufenweiser Ausbau mit wiederkehrendem Commissioning-Bedarf. Schweizer Firma, kurze Wege. | Q99: 4 | R99: 3 | S99: 4 | T99: 4 | U99: =ROUND(Q99*Methodik!$B$5+R99*Methodik!$B$6+S99*Methodik!$B$7+T99*Methodik!$B$8,2) -> 3.7 | V99: =IF(U99>=Methodik!$B$11,"A",IF(U99>=Methodik!$B$12,"B","C")) -> B | X99: =IF(W99="",V99,W99) -> B | Y99: Offen: CRM prüfen | AA99: Construction / Commissioning Manager, Critical Facility Ops | AD99: Suche öffnen | AE99: Suche öffnen | AF99: Link
A100: CH-096 | B100: Nein | C100: GU/TU + Industrie (20 %) | D100: Rechenzentrum | E100: Vaultica (ex Safe Host / STACK Genf) | F100: Apollo (Verkauf 2025) | G100: Plan-les-Ouates | H100: GE | I100: West (Romandie) | J100: West | K100: FR/EN | L100: prüfen | M100: GEN01/GEN02 | N100: Namenswechsel, neuer Eigentümer 2025 | O100: NEA-Test, USV | P100: Neuer Betreiber: Service-Verträge werden neu vergeben. | Q100: 4 | R100: 3 | S100: 4 | T100: 3 | U100: =ROUND(Q100*Methodik!$B$5+R100*Methodik!$B$6+S100*Methodik!$B$7+T100*Methodik!$B$8,2) -> 3.55 | V100: =IF(U100>=Methodik!$B$11,"A",IF(U100>=Methodik!$B$12,"B","C")) -> B | X100: =IF(W100="",V100,W100) -> B | Y100: Offen: CRM prüfen | AA100: Construction / Commissioning Manager, Critical Facility Ops | AD100: Suche öffnen | AE100: Suche öffnen | AF100: Link | AG100: Name und Website prüfen.
A101: CH-097 | B101: Nein | C101: GU/TU + Industrie (20 %) | D101: Rechenzentrum | E101: Equinix | F101: Equinix | G101: Zürich / Genf | H101: ZH | I101: Zürich | J101: Deutschschweiz | K101: EN/DE | L101: equinix.ch | M101: ZH2/ZH4/ZH5, GV1/GV2 | N101: Ausbau Zürcher RZ für 40 Mio. (11/2024) | O101: NEA-Test, Überbrückung | P101: NEA-Tests und temporäre Versorgung bei Erweiterungen. | Q101: 4 | R101: 4 | S101: 3 | T101: 2 | U101: =ROUND(Q101*Methodik!$B$5+R101*Methodik!$B$6+S101*Methodik!$B$7+T101*Methodik!$B$8,2) -> 3.45 | V101: =IF(U101>=Methodik!$B$11,"A",IF(U101>=Methodik!$B$12,"B","C")) -> B | X101: =IF(W101="",V101,W101) -> B | Y101: Offen: CRM prüfen | AA101: Construction / Commissioning Manager, Critical Facility Ops | AD101: Suche öffnen | AE101: Suche öffnen | AF101: Link
A102: CH-098 | B102: Nein | C102: GU/TU + Industrie (20 %) | D102: Rechenzentrum | E102: Swisscom (Rechenzentren) | F102: Swisscom | G102: Bern-Wankdorf | H102: BE | I102: Mittelland/Bern | J102: Deutschschweiz | K102: DE | L102: swisscom.ch | M102: k.A. | N102: Neubau-RZ ca. 100 Mio. als Ersatz Zentweg (Datum prüfen) | O102: Überbrückung, NEA-Test | P102: Migrations-Überbrückung und NEA-Tests. Zugang evtl. über cablex. | Q102: 4 | R102: 4 | S102: 3 | T102: 2 | U102: =ROUND(Q102*Methodik!$B$5+R102*Methodik!$B$6+S102*Methodik!$B$7+T102*Methodik!$B$8,2) -> 3.45 | V102: =IF(U102>=Methodik!$B$11,"A",IF(U102>=Methodik!$B$12,"B","C")) -> B | X102: =IF(W102="",V102,W102) -> B | Y102: Offen: CRM prüfen | AA102: Construction / Commissioning Manager, Critical Facility Ops | AD102: Suche öffnen | AE102: Suche öffnen | AF102: Link | AG102: Projektstand prüfen.
A103: CH-099 | B103: Nein | C103: GU/TU + Industrie (20 %) | D103: Rechenzentrum | E103: NTT Global Data Centers | F103: NTT | G103: Rümlang | H103: ZH | I103: Zürich | J103: Deutschschweiz | K103: EN/DE | L103: services.global.ntt | M103: bis 20 MW | N103: Kein spezifischer Anlass recherchiert | O103: NEA-Test, USV | P103: Wiederkehrende NEA- und USV-Tests, Überbrückung bei Retrofits. | Q103: 4 | R103: 3 | S103: 2 | T103: 3 | U103: =ROUND(Q103*Methodik!$B$5+R103*Methodik!$B$6+S103*Methodik!$B$7+T103*Methodik!$B$8,2) -> 3.05 | V103: =IF(U103>=Methodik!$B$11,"A",IF(U103>=Methodik!$B$12,"B","C")) -> B | X103: =IF(W103="",V103,W103) -> B | Y103: Offen: CRM prüfen | AA103: Construction / Commissioning Manager, Critical Facility Ops | AD103: Suche öffnen | AE103: Suche öffnen | AF103: Link
A104: CH-100 | B104: Nein | C104: GU/TU + Industrie (20 %) | D104: Rechenzentrum | E104: CSCS (ETH Zürich) | F104: ETH | G104: Lugano-Cornaredo | H104: TI | I104: Tessin | J104: Tessin | K104: IT/EN | L104: cscs.ch | M104: Supercomputer «Alps» | N104: Kein spezifischer Anlass recherchiert | O104: USV, NEA-Test | P104: USV- und NEA-Wartungsfenster eines HPC-Centers. | Q104: 4 | R104: 2 | S104: 2 | T104: 3 | U104: =ROUND(Q104*Methodik!$B$5+R104*Methodik!$B$6+S104*Methodik!$B$7+T104*Methodik!$B$8,2) -> 2.75 | V104: =IF(U104>=Methodik!$B$11,"A",IF(U104>=Methodik!$B$12,"B","C")) -> C | X104: =IF(W104="",V104,W104) -> C | Y104: Offen: CRM prüfen | AA104: Construction / Commissioning Manager, Critical Facility Ops | AD104: Suche öffnen | AE104: Suche öffnen | AF104: Link | AG104: Öffentliche Beschaffung.
...

Sheet Methodik
A1: Methodik, Legende und Grenzen der Recherche
A2: Stand 27.09.2026
A4: Gewichtung Score | B4: Wert | C4: Bedeutung (Skala je Kriterium 1 = schwach bis 5 = stark)
A5: Fit | B5: 0.3 | C5: Passt der Bedarf zum MiT-Portfolio (Generator, BESS, USV, Trafo, NEA-Test, PQ, Baustrom, Event)?
A6: Volumen | B6: 0.3 | C6: Erwartbares Mietvolumen pro Jahr bzw. Hebel über Töchter/Rahmenvertrag.
A7: Timing | B7: 0.25 | C7: Konkreter Anlass 2025-2027 (Bau, UW-Umbau, Commissioning, Ramp-up, Event-Saison).
A8: Zugang | B8: 0.15 | C8: Erreichbarkeit: regionale Nähe, Entscheid lokal vs. Konzern/EMEA, öffentliche Beschaffung.
A9: Summe Gewichte | B9: =SUM(B5:B8) -> 1
A11: Schwelle Prio A | B11: 4 | C11: Score >= Schwelle A: jetzt aktiv angehen (Termin in den nächsten 6 Wochen).
A12: Schwelle Prio B | B12: 3 | C12: Score >= Schwelle B: im Quartal angehen, Anlass beobachten.
A13: Prio C | C13: Darunter: Beobachten, opportunistisch bedienen, über Partner/Töchter abdecken.
A15: Bedienung
A16: Gelbe Zellen | C16: Eingaben. Gewichte und Schwellen hier ändern, Score und Prio in der Kundenliste rechnen neu.
A17: Prio final | C17: Leer lassen = Vorschlag gilt. A/B/C eintragen = übersteuert den Vorschlag. Spalte «Prio» ist die gültige.
A18: Kundenstatus MiT | C18: Alle Zeilen stehen auf «Offen: CRM prüfen». Bestands-, A- und verlorene Kunden sind öffentlich nicht
C19: recherchierbar und müssen aus dem MiT-CRM bzw. von Mauro, Jörg und Roberto eingetragen werden (Dropdown).
A20: Verloren seit | C20: Nur bei Status «Verlorener Kunde» ausfüllen (Datum). Grund in «Validierung / Hinweis».
A21: Kernliste Top 70 | C21: 70 Firmen im Verhältnis 60/20/20 (42/14/14) nach Vorgabe. Alle übrigen Zeilen sind Reserve bzw. Ergänzung.
A23: Grenzen der Recherche
A24: Quellen | C24: Websuche vom 27.09.2026: Firmenwebsites, Handelsregister-Aggregatoren, Medienmitteilungen, Fachpresse.
C25: Einige Seiten (u.a. NZZ, SRF, einzelne .ch-Domains) waren nicht direkt abrufbar: Werte teils nur aus Suchergebnissen.
A26: Mitarbeiterzahlen | C26: Teils aus Vorjahren oder Sekundärquellen. «(prüfen)» bzw. «uneinheitlich» = vor externer Verwendung verifizieren.
A27: Ansprechpersonen | C27: Keine Namen erfunden. Nur öffentlich genannte GL-Mitglieder mit Quelle. Die LinkedIn-Links öffnen eine
C28: Suche (Firma bzw. Firma + Zielfunktion), keine verifizierten Profile. Namen nach Prüfung in «Ansprechperson» eintragen.
A29: Relevanz / Warum | C29: Einschätzung aus Sicht mobiler Energie. Belegt sind nur die Fakten in «Anlass / Projekt» und «Grösse».
A30: Nicht aufgenommen | C30: Steiner AG (Nachlassstundung), Deltalis (RZ-Betrieb eingestellt). Ohne belastbare Quelle weggelassen:
C31: Dussmann, Kaufmann, Perenzia, Nine, Swiss Fort Knox, atNorth, Colt. BKW (Konzern), Axpo Grid, Swissgrid, AEW, EKT, EWL,
C32: St.Galler Stadtwerke sind reale Zielkunden, aber noch ohne geprüfte Kennzahlen: als nächste Ergänzung vorgesehen.
A33: Wettbewerb/Partner | C33: Kummler+Matter EVT vermietet eigene mobile Trafostationen: Partner und Wettbewerber zugleich.
A34: Vertraulich | C34: Interne Arbeitsliste. Nicht an Kunden weitergeben.

Sheet Listen
A1: Segment | B1: Kategorie | C1: Region | D1: Prio | E1: Kundenstatus | F1: Team | G1: Kernliste | H1: Skala | I1: Gebiet
A2: Installateure (60 %) | B2: Installateur | C2: West (Romandie) | D2: A | E2: Offen: CRM prüfen | F2: Burak | G2: Ja | H2: 1 | I2: West
A3: FM / EVU / Planer (20 %) | B3: Facility Manager | C3: Mittelland/Bern | D3: B | E3: A-Kunde | F3: Mauro | G3: Nein | H3: 2 | I3: Deutschschweiz
A4: GU/TU + Industrie (20 %) | B4: Stadtwerk/EVU | C4: Nordwestschweiz | D4: C | E4: Bestandskunde mit Potenzial | F4: Jörg | H4: 3 | I4: Tessin
B5: Elektroplaner | C5: Zürich | E5: Verlorener Kunde | F5: Roberto | H5: 4
B6: GU/TU | C6: Ostschweiz | E6: Potenzial / Aufbau | H6: 5
B7: Rechenzentrum | C7: Zentralschweiz
B8: Industrie | C8: Tessin
B9: Spital
B10: Infrastruktur
B11: Event
